{"index": "I_1044", "messy_full": "\\n      \\n        DEPARTMENT OF THE INTERIOR\\n        National Park Service\\n        [NPS-WASO-NAGPRA-10375; 2200-1100-665]\\n        Notice of Inventory Completion: Museum of Anthropology, University of Michigan, Ann Arbor, MI; Correction\\n        \\n          AGENCY:\\n          National Park Service, Interior.\\n        \\n        \\n          ACTION:\\n          Notice; correction.\\n        \\n        Notice is here given in accordance with the Native American Graves Protection and Repatriation Act (NAGPRA), 25 U.S.C. 3003, of the completion of an inventory of human remains in the possession of the University of Michigan, Ann Arbor, MI. The human remains were removed from Emmet County, MI.\\n        This notice is published as part of the National Park Service\\'s administrative responsibilities under NAGPRA, 25 U.S.C. 3003(d)(3). The determinations in this notice are the sole responsibility of the museum, institution, or Federal agency that has control of the Native American human remains and associated funerary objects. The National Park Service is not responsible for the determinations in this notice.\\n\\n        This notice corrects the minimum number of individuals in the Notice of Inventory Completion published in the Federal Register (74 FR 42094-42095, August 20, 2009).\\n        In the Federal Register (74 FR 42094, August 20, 2009), paragraph four is corrected by deleting the following sentences at the top of column three:\\n        The human remains are of an adult and a second, younger adult individual. Since that time, based on skeletal and dental morphology, the older individual has been identified as being of mixed European and Native American ancestry. There is insufficient evidence to positively determine the biological affiliation of the younger individual, but they may also be of mixed European and Native American ancestry.\\n        In the Federal Register (74 FR 42094, August 20, 2009), paragraph four is corrected by inserting the following sentences at the top of column three:\\n        The human remains are of two adults and a third, younger adult individual. Since that time, based on skeletal and dental morphology, one of the older individuals has been identified as being of mixed European and Native American ancestry. There is insufficient evidence to positively determine the biological affiliation of the other individuals, but they may also be of mixed European and Native American ancestry.\\n        In the Federal Register (74 FR 42094, August 20, 2009), paragraph seven is corrected by changing the words \\xe2\\x80\\x9ctwo individuals\\xe2\\x80\\x9d to \\xe2\\x80\\x9cthree individuals.\\xe2\\x80\\x9d\\n        In the Federal Register (74 FR 42094, August 20, 2009), paragraph eight is corrected by changing the words \\xe2\\x80\\x9ctwo individuals\\xe2\\x80\\x9d to \\xe2\\x80\\x9cthree individuals.\\xe2\\x80\\x9d\\n        Additional Requestors and Disposition\\n        Representatives of any other Indian tribe that believes itself to be culturally affiliated with the human remains should contact Dr. Ben Secunda, NAGPRA Project Manager, University of Michigan, Office of the Vice President for Research, 4080 Fleming Building, 503 Thompson St., Ann Arbor, MI 48109-1340; telephone (734) 647-9085, before July 12, 2012. Repatriation of the human remains to the Little Traverse Bay Bands of Odawa Indians may proceed after that date if no additional claimants come forward.\\n        The University of Michigan is responsible for notifying the Little Traverse Bay Bands of Odawa Indians that this notice has been published.\\n        \\n          Dated: June 7, 2012.\\n          David Tarler,\\n          Acting Manager, National NAGPRA Program.\\n        \\n      \\n      [FR Doc. 2012-14301 Filed 6-11-12; 8:45 am]\\n      BILLING CODE 4312-50-P\\n    ", "agency1": "DEPARTMENT OF THE INTERIOR", "sub_agency1": "National Park Service", "dep_doc": "[NPS-WASO-NAGPRA-10375; 2200-1100-665]", "subject": "Notice of Inventory Completion: Museum of Anthropology, University of Michigan, Ann Arbor, MI; Correction", "agency2": "National Park Service, Interior.", "action": "Notice; correction.", "summary": "Null", "dates": "Null", "addresses": "Null", "signature_dated": "Dated: June 7, 2012.", "signature_name": "David Tarler,", "signature_title": "Acting Manager, National NAGPRA Program.", "fr_doc": "[FR Doc. 2012-14301 Filed 6-11-12; 8:45 am]", "billing_code": "BILLING CODE 4312-50-P", "supp_info": "Null", "consultation": "Null", "h_d_r": "Null", "h_d_ci": "Null", "determinations": "Null", "a_r_d": "Representatives of any other Indian tribe that believes itself to be culturally affiliated with the human remains should contact Dr. Ben Secunda, NAGPRA Project Manager, University of Michigan, Office of the Vice President for Research, 4080 Fleming Building, 503 Thompson St., Ann Arbor, MI 48109-1340; telephone (734) 647-9085, before July 12, 2012. Repatriation of the human remains to the Little Traverse Bay Bands of Odawa Indians may proceed after that date if no additional claimants come forward. \n The University of Michigan is responsible for notifying the Little Traverse Bay Bands of Odawa Indians that this notice has been published. \n "}