{"index": "I_1018", "messy_full": "\\n      \\n        DEPARTMENT OF THE INTERIOR\\n        National Park Service\\n        [NPS-WASO-NAGPRA-10885; 2200-1100-665]\\n        Notice of Inventory Completion: State Historical Society of Wisconsin, Madison, WI\\n        \\n          AGENCY:\\n          National Park Service, Interior.\\n        \\n        \\n          ACTION:\\n          Notice.\\n        \\n        \\n          SUMMARY:\\n          The State Historical Society of Wisconsin, Museum Division, has completed an inventory of human remains, in consultation with the appropriate Indian tribes, and has determined that there is no cultural affiliation between the remains and any present-day Indian tribe. Representatives of any Indian tribe that believes itself to be culturally affiliated with the human remains may contact the State Historical Society of Wisconsin. Disposition of the human remains to the Indian tribe stated below may occur if no additional requestors come forward.\\n        \\n        \\n          DATES:\\n          Representatives of any Indian tribe that believes it has a cultural affiliation with the human remains should contact the State Historical Society of Wisconsin at the address below by September 13, 2012.\\n        \\n        \\n          ADDRESSES:\\n          Jennifer Kolb, Wisconsin Historical Museum, 30 North Carroll Street, Madison, WI 53703, telephone (608) 261-2461.\\n        \\n      \\n      \\n        SUPPLEMENTARY INFORMATION:\\n        Notice is here given in accordance with the Native American Graves Protection and Repatriation Act (NAGPRA), 25 U.S.C. 3003, of the completion of an inventory of human remains in the possession of the State Historical Society of Wisconsin, Madison, WI. The human remains were removed from Newaygo County, MI.\\n        This notice is published as part of the National Park Service\\'s administrative responsibilities under NAGPRA, 25 U.S.C. 3003(d)(3) and 43 CFR 10.11(d). The determinations in this notice are the sole responsibility of the museum, institution, or Federal agency that has control of the Native American human remains. The National Park Service is not responsible for the determinations in this notice.\\n        Consultation\\n        A detailed assessment of the human remains was made by the State Historical Society of Wisconsin professional staff in consultation with the following Federally recognized tribal entities belonging to the Michigan Anishinaabek Cultural Preservation and Repatriation Alliance (MACPRA): Bay Mills Indian Community, Michigan; Grand Traverse Band of Ottawa and Chippewa Indians, Michigan; Hannahville Indian Community, Michigan; Keweenaw Bay Indian Community, Michigan; Lac Vieux Desert Band of Lake Superior Chippewa Indians, Michigan; Little River Band of Ottawa Indians, Michigan; Little Traverse Bay Bands of Odawa Indians, Michigan; Nottawasppi Huron Band of the Potawatomi, Michigan (formerly the Huron Potawatomi, Inc.); Saginaw Chippewa Indian Tribe of Michigan; and the Sault Ste. Marie Tribe of Chippewa Indians of Michigan.\\n        History and Description of the Remains\\n        Sometime prior to 1930, human remains representing, at minimum, one individual were removed from a mound near the city of Newaygo in Newaygo County, MI. They were donated to the Wisconsin Historical Society in 1930 by the University of Wisconsin-Madison through George Wagner. The remains were originally in the collection of H.B. Ogden of Milwaukee, WI. No known individuals were identified. No associated funerary objects are present.\\n        Determinations Made by State Historical Society of Wisconsin\\n        Officials of the State Historical Society of Wisconsin have determined that:\\n        \\xe2\\x80\\xa2 Based on skeletal analysis, the human remains are Native American.\\n        \\xe2\\x80\\xa2 Pursuant to 25 U.S.C. 3001(2), a relationship of shared group identity cannot be reasonably traced between the Native American human remains and any present-day Indian tribe.\\n        \\xe2\\x80\\xa2 Multiple lines of evidence, including treaties, Acts of Congress, and Executive Orders, indicate that the land from which the Native American human remains were removed is the aboriginal land of the Bay Mills Indian Community, Michigan; Grand Traverse Band of Ottawa and Chippewa Indians, Michigan; Little River Band of Ottawa Indians, Michigan; Little Traverse Bay Bands of Odawa Indians, Michigan; Saginaw Chippewa Indian Tribe of Michigan; and the Sault Ste. Marie Tribe of Chippewa Indians of Michigan.\\n        \\xe2\\x80\\xa2 Other credible lines of evidence, supplied by MACPRA participant tribes, indicate that the land from which the Native American human remains were removed is the aboriginal land of the Bay Mills Indian Community, Michigan; Grand Traverse Band of Ottawa and Chippewa Indians, Michigan; Little River Band of Ottawa Indians, Michigan; Little Traverse Bay Bands of Odawa Indians, Michigan; Saginaw Chippewa Indian Tribe of Michigan; and the Sault Ste. Marie Tribe of Chippewa Indians of Michigan.\\n        \\xe2\\x80\\xa2 Pursuant to 25 U.S.C. 3001(9), the human remains described in this notice represent the physical remains of one individual of Native American ancestry.\\n        \\xe2\\x80\\xa2 Pursuant to 43 CFR 10.11(c)(1), the disposition of the human remains is to the Little River Band of Ottawa Indians, Michigan.\\n        Additional Requestors and Disposition\\n        Representatives of any Indian tribe that believes itself to be culturally affiliated with the human remains or any other Indian tribe that believes it satisfies the criteria in 43 CFR 10.11(c)(1) should contact Jennifer Kolb, Wisconsin Historical Museum, 30 N Carroll Street, Madison, WI 53703, telephone (608) 261-2461, before September 13, 2012. Disposition of the human remains to the Little River Band of Ottawa Indians, Michigan, may proceed after that date if no additional requestors come forward.\\n        The State Historical Society of Wisconsin is responsible for notifying the Bay Mills Indian Community, Michigan; Grand Traverse Band of Ottawa and Chippewa Indians, Michigan; Hannahville Indian Community, Michigan; Keweenaw Bay Indian Community, Michigan; Lac Vieux Desert Band of Lake Superior Chippewa Indians, Michigan; Little River Band of Ottawa Indians, Michigan; Little Traverse Bay Bands of Odawa Indians, Michigan; Nottawasppi Huron Band of the Potawatomi, Michigan (formerly the Huron Potawatomi, Inc.); Saginaw Chippewa Indian Tribe of Michigan; and the Sault Ste. Marie Tribe of Chippewa Indians of Michigan that this notice has been published.\\n        \\n          Dated: July 19, 2012.\\n          David Tarler,\\n          Acting Manager, National NAGPRA Program. \\n        \\n      \\n      [FR Doc. 2012-19928 Filed 8-13-12; 8:45 am]\\n      BILLING CODE 4312-50-P\\n    ", "agency1": "DEPARTMENT OF THE INTERIOR", "sub_agency1": "National Park Service", "dep_doc": "[NPS-WASO-NAGPRA-10885; 2200-1100-665]", "subject": "Notice of Inventory Completion: State Historical Society of Wisconsin, Madison, WI", "agency2": "National Park Service, Interior.", "action": "Notice.", "summary": "The State Historical Society of Wisconsin, Museum Division, has completed an inventory of human remains, in consultation with the appropriate Indian tribes, and has determined that there is no cultural affiliation between the remains and any present-day Indian tribe. Representatives of any Indian tribe that believes itself to be culturally affiliated with the human remains may contact the State Historical Society of Wisconsin. Disposition of the human remains to the Indian tribe stated below may occur if no additional requestors come forward.", "dates": "Representatives of any Indian tribe that believes it has a cultural affiliation with the human remains should contact the State Historical Society of Wisconsin at the address below by September 13, 2012.", "addresses": "Jennifer Kolb, Wisconsin Historical Museum, 30 North Carroll Street, Madison, WI 53703, telephone (608) 261-2461.", "signature_dated": "Dated: July 19, 2012.", "signature_name": "David Tarler,", "signature_title": "Acting Manager, National NAGPRA Program. ", "fr_doc": "[FR Doc. 2012-19928 Filed 8-13-12; 8:45 am]", "billing_code": "BILLING CODE 4312-50-P", "supp_info": "SUPPLEMENTARY INFORMATION: \n Notice is here given in accordance with the Native American Graves Protection and Repatriation Act (NAGPRA), 25 U.S.C. 3003, of the completion of an inventory of human remains in the possession of the State Historical Society of Wisconsin, Madison, WI. The human remains were removed from Newaygo County, MI. \n This notice is published as part of the National Park Service\\'s administrative responsibilities under NAGPRA, 25 U.S.C. 3003(d)(3) and 43 CFR 10.11(d). The determinations in this notice are the sole responsibility of the museum, institution, or Federal agency that has control of the Native American human remains. The National Park Service is not responsible for the determinations in this notice. \n Consultation \n A detailed assessment of the human remains was made by the State Historical Society of Wisconsin professional staff in consultation with the following Federally recognized tribal entities belonging to the Michigan Anishinaabek Cultural Preservation and Repatriation Alliance (MACPRA): Bay Mills Indian Community, Michigan; Grand Traverse Band of Ottawa and Chippewa Indians, Michigan; Hannahville Indian Community, Michigan; Keweenaw Bay Indian Community, Michigan; Lac Vieux Desert Band of Lake Superior Chippewa Indians, Michigan; Little River Band of Ottawa Indians, Michigan; Little Traverse Bay Bands of Odawa Indians, Michigan; Nottawasppi Huron Band of the Potawatomi, Michigan (formerly the Huron Potawatomi, Inc.); Saginaw Chippewa Indian Tribe of Michigan; and the Sault Ste. Marie Tribe of Chippewa Indians of Michigan. \n History and Description of the Remains \n Sometime prior to 1930, human remains representing, at minimum, one individual were removed from a mound near the city of Newaygo in Newaygo County, MI. They were donated to the Wisconsin Historical Society in 1930 by the University of Wisconsin-Madison through George Wagner. The remains were originally in the collection of H.B. Ogden of Milwaukee, WI. No known individuals were identified. No associated funerary objects are present. \n Determinations Made by State Historical Society of Wisconsin \n Officials of the State Historical Society of Wisconsin have determined that: \n \\xe2\\x80\\xa2 Based on skeletal analysis, the human remains are Native American. \n \\xe2\\x80\\xa2 Pursuant to 25 U.S.C. 3001(2), a relationship of shared group identity cannot be reasonably traced between the Native American human remains and any present-day Indian tribe. \n \\xe2\\x80\\xa2 Multiple lines of evidence, including treaties, Acts of Congress, and Executive Orders, indicate that the land from which the Native American human remains were removed is the aboriginal land of the Bay Mills Indian Community, Michigan; Grand Traverse Band of Ottawa and Chippewa Indians, Michigan; Little River Band of Ottawa Indians, Michigan; Little Traverse Bay Bands of Odawa Indians, Michigan; Saginaw Chippewa Indian Tribe of Michigan; and the Sault Ste. Marie Tribe of Chippewa Indians of Michigan. \n \\xe2\\x80\\xa2 Other credible lines of evidence, supplied by MACPRA participant tribes, indicate that the land from which the Native American human remains were removed is the aboriginal land of the Bay Mills Indian Community, Michigan; Grand Traverse Band of Ottawa and Chippewa Indians, Michigan; Little River Band of Ottawa Indians, Michigan; Little Traverse Bay Bands of Odawa Indians, Michigan; Saginaw Chippewa Indian Tribe of Michigan; and the Sault Ste. Marie Tribe of Chippewa Indians of Michigan. \n \\xe2\\x80\\xa2 Pursuant to 25 U.S.C. 3001(9), the human remains described in this notice represent the physical remains of one individual of Native American ancestry. \n \\xe2\\x80\\xa2 Pursuant to 43 CFR 10.11(c)(1), the disposition of the human remains is to the Little River Band of Ottawa Indians, Michigan. \n Additional Requestors and Disposition \n Representatives of any Indian tribe that believes itself to be culturally affiliated with the human remains or any other Indian tribe that believes it satisfies the criteria in 43 CFR 10.11(c)(1) should contact Jennifer Kolb, Wisconsin Historical Museum, 30 N Carroll Street, Madison, WI 53703, telephone (608) 261-2461, before September 13, 2012. Disposition of the human remains to the Little River Band of Ottawa Indians, Michigan, may proceed after that date if no additional requestors come forward. \n The State Historical Society of Wisconsin is responsible for notifying the Bay Mills Indian Community, Michigan; Grand Traverse Band of Ottawa and Chippewa Indians, Michigan; Hannahville Indian Community, Michigan; Keweenaw Bay Indian Community, Michigan; Lac Vieux Desert Band of Lake Superior Chippewa Indians, Michigan; Little River Band of Ottawa Indians, Michigan; Little Traverse Bay Bands of Odawa Indians, Michigan; Nottawasppi Huron Band of the Potawatomi, Michigan (formerly the Huron Potawatomi, Inc.); Saginaw Chippewa Indian Tribe of Michigan; and the Sault Ste. Marie Tribe of Chippewa Indians of Michigan that this notice has been published. \n ", "consultation": "A detailed assessment of the human remains was made by the State Historical Society of Wisconsin professional staff in consultation with the following Federally recognized tribal entities belonging to the Michigan Anishinaabek Cultural Preservation and Repatriation Alliance (MACPRA): Bay Mills Indian Community, Michigan; Grand Traverse Band of Ottawa and Chippewa Indians, Michigan; Hannahville Indian Community, Michigan; Keweenaw Bay Indian Community, Michigan; Lac Vieux Desert Band of Lake Superior Chippewa Indians, Michigan; Little River Band of Ottawa Indians, Michigan; Little Traverse Bay Bands of Odawa Indians, Michigan; Nottawasppi Huron Band of the Potawatomi, Michigan (formerly the Huron Potawatomi, Inc.); Saginaw Chippewa Indian Tribe of Michigan; and the Sault Ste. Marie Tribe of Chippewa Indians of Michigan. \n ", "h_d_r": "Sometime prior to 1930, human remains representing, at minimum, one individual were removed from a mound near the city of Newaygo in Newaygo County, MI. They were donated to the Wisconsin Historical Society in 1930 by the University of Wisconsin-Madison through George Wagner. The remains were originally in the collection of H.B. Ogden of Milwaukee, WI. No known individuals were identified. No associated funerary objects are present. \n ", "h_d_ci": "Null", "determinations": "Determinations Made by State Historical Society of Wisconsin \n Officials of the State Historical Society of Wisconsin have determined that: \n \\xe2\\x80\\xa2 Based on skeletal analysis, the human remains are Native American. \n \\xe2\\x80\\xa2 Pursuant to 25 U.S.C. 3001(2), a relationship of shared group identity cannot be reasonably traced between the Native American human remains and any present-day Indian tribe. \n \\xe2\\x80\\xa2 Multiple lines of evidence, including treaties, Acts of Congress, and Executive Orders, indicate that the land from which the Native American human remains were removed is the aboriginal land of the Bay Mills Indian Community, Michigan; Grand Traverse Band of Ottawa and Chippewa Indians, Michigan; Little River Band of Ottawa Indians, Michigan; Little Traverse Bay Bands of Odawa Indians, Michigan; Saginaw Chippewa Indian Tribe of Michigan; and the Sault Ste. Marie Tribe of Chippewa Indians of Michigan. \n \\xe2\\x80\\xa2 Other credible lines of evidence, supplied by MACPRA participant tribes, indicate that the land from which the Native American human remains were removed is the aboriginal land of the Bay Mills Indian Community, Michigan; Grand Traverse Band of Ottawa and Chippewa Indians, Michigan; Little River Band of Ottawa Indians, Michigan; Little Traverse Bay Bands of Odawa Indians, Michigan; Saginaw Chippewa Indian Tribe of Michigan; and the Sault Ste. Marie Tribe of Chippewa Indians of Michigan. \n \\xe2\\x80\\xa2 Pursuant to 25 U.S.C. 3001(9), the human remains described in this notice represent the physical remains of one individual of Native American ancestry. \n \\xe2\\x80\\xa2 Pursuant to 43 CFR 10.11(c)(1), the disposition of the human remains is to the Little River Band of Ottawa Indians, Michigan. \n ", "a_r_d": "Representatives of any Indian tribe that believes itself to be culturally affiliated with the human remains or any other Indian tribe that believes it satisfies the criteria in 43 CFR 10.11(c)(1) should contact Jennifer Kolb, Wisconsin Historical Museum, 30 N Carroll Street, Madison, WI 53703, telephone (608) 261-2461, before September 13, 2012. Disposition of the human remains to the Little River Band of Ottawa Indians, Michigan, may proceed after that date if no additional requestors come forward. \n The State Historical Society of Wisconsin is responsible for notifying the Bay Mills Indian Community, Michigan; Grand Traverse Band of Ottawa and Chippewa Indians, Michigan; Hannahville Indian Community, Michigan; Keweenaw Bay Indian Community, Michigan; Lac Vieux Desert Band of Lake Superior Chippewa Indians, Michigan; Little River Band of Ottawa Indians, Michigan; Little Traverse Bay Bands of Odawa Indians, Michigan; Nottawasppi Huron Band of the Potawatomi, Michigan (formerly the Huron Potawatomi, Inc.); Saginaw Chippewa Indian Tribe of Michigan; and the Sault Ste. Marie Tribe of Chippewa Indians of Michigan that this notice has been published. \n "}