{"index": "I_1025", "messy_full": "\\n      \\n        DEPARTMENT OF THE INTERIOR\\n        National Park Service\\n        [NPS-WASO-NAGPRA-10823; 2200-1100-665]\\n        Notice of Inventory Completion: Thomas Burke Memorial Washington State Museum, University of Washington, Seattle, WA\\n        \\n          AGENCY:\\n          National Park Service, Interior.\\n        \\n        \\n          ACTION:\\n          Notice.\\n        \\n        \\n          SUMMARY:\\n          The Thomas Burke Memorial Washington State Museum (Burke Museum) has completed an inventory of human remains and associated funerary objects, in consultation with the appropriate Indian tribes, and has determined that there is no cultural affiliation between the remains and any present-day Indian tribe. Representatives of any Indian tribe that believes itself to be culturally affiliated with the human remains may contact the Burke Museum. Disposition of the human remains and the associated funerary object to the Indian tribes stated below may occur if no additional requestors come forward.\\n        \\n        \\n          DATES:\\n          Representatives of any Indian tribe that believes it has a cultural affiliation with the human remains should contact the Burke Museum at the address below by September 4, 2012.\\n        \\n        \\n          ADDRESSES:\\n          Peter Lape, Burke Museum, University of Washington, Box 353010, Seattle, WA 98195-3010, telephone (206) 685-3849.\\n        \\n      \\n      \\n        SUPPLEMENTARY INFORMATION:\\n        Notice is hereby given in accordance with the Native American Graves Protection and Repatriation Act (NAGPRA), 25 U.S.C. 3003, of the completion of an inventory of human remains and associated funerary object in the possession of the Burke Museum. The human remains and associated funerary object were removed from an unknown location, most likely in the state of Washington.\\n        This notice is published as part of the National Park Service\\'s administrative responsibilities under NAGPRA, 25 U.S.C. 3003(d)(3) and 43 CFR 10.11(d). The determinations in this notice are the sole responsibility of the museum, institution, or Federal agency that has control of the Native American human remains. The National Park Service is not responsible for the determinations in this notice.\\n        Consultation\\n        A detailed assessment of the human remains was made by the Burke Museum professional staff in consultation with representatives of the Coeur D\\'Alene Tribe of the Coeur D\\'Alene Reservation, Idaho; Confederated Tribes and Bands of the Yakama Nation, Washington; Confederated Tribes of the Colville Reservation, Washington; Confederated Tribes of the Umatilla Reservation, Oregon; Confederated Tribes of the Warm Springs Reservation of Oregon; Cowlitz Indian Tribe, Washington; Jamestown S\\'Klallam Tribe of Washington; Kalispel Indian Community of the Kalispel Reservation, Washington; Lower Elwha Tribal Community of the Lower Elwha Reservation, Washington; Lummi Tribe of the Lummi Reservation, Washington; Makah Indian Tribe of the Makah Indian Reservation, Washington; Muckleshoot Indian Tribe of the Muckleshoot Reservation, Washington; Nez Perce Tribe, Idaho (previously listed as Nez Perce Tribe of Idaho); Nooksack Indian Tribe of Washington; Port Gamble Indian Community of the Port Gamble Reservation, Washington; Puyallup Tribe of the Puyallup Reservation, Washington; Samish Indian Tribe, Washington; Skokomish Indian Tribe of the Skokomish Reservation, Washington; Snoqualmie Tribe, Washington; Spokane Tribe of the Spokane Reservation, Washington; Squaxin Island Tribe of the Squaxin Island Reservation, Washington; Stillaguamish Tribe of Washington; Suquamish Indian Tribe of the Port Madison Reservation, Washington; Swinomish Indians of the Swinomish Reservation, Washington; and the Wanapum Band of Priest Rapids, a non-Federally recognized Indian group. The following tribes with aboriginal territory in the state of Washington were also invited to participate but were not involved in consultations: the Confederated Tribes of the Chehalis Reservation, Washington; Hoh Indian Tribe of the Hoh Indian Reservation, Washington; Nisqually Indian Tribe of the Nisqually Reservation, Washington; Quileute Tribe of the Quileute Reservation, Washington; Quinault Tribe of the Quinault Reservation, Washington; Sauk-Suiattle Indian Tribe of Washington; Shoalwater Bay Tribe of the Shoalwater Bay Indian Reservation, Washington; Tulalip Tribes of the Tulalip Reservation, Washington; and the Upper Skagit Indian Tribe of Washington.\\n        History and Description of the Remains\\n        At unknown dates, human remains representing, at minimum, 27 individuals were removed from unknown sites throughout the state of Washington. There is limited or no provenience information for the human remains. Based on the fact that they were disassociated from any acquisition documentation, they were assigned \\xe2\\x80\\x9cfound in collection\\xe2\\x80\\x9d accession numbers in 1973 and 1995. These human remains were crosschecked against the documentation for human remains known to have been missing, but did not match documentation for any specific collection. These human remains and the associated funerary object are most likely to have been removed from sites within the state of Washington. No known individuals were identified. The one associated funerary object is a composite artifact bag containing non-human mammal bones, shells, a rock, and two twigs.\\n        Determinations Made by the Burke Museum\\n        Officials of the Burke Museum have determined that:\\n        \\xe2\\x80\\xa2 Based on cranial morphology, dental traits, taphonomy, and museum accession documentation, the human remains are Native American.\\n        \\xe2\\x80\\xa2 Pursuant to 25 U.S.C. 3001(2), a relationship of shared group identity cannot be reasonably traced between the Native American human remains and any present-day Indian tribe.\\n\\n        \\xe2\\x80\\xa2 According to final judgments of the Indian Claims Commission, the land from which the Native American human remains and the associated funerary object were removed is the aboriginal land of the Coeur D\\'Alene Tribe of the Coeur D\\'Alene Reservation, Idaho; Confederated Tribes and Bands of the Yakama Nation, Washington; Confederated Tribes of the Chehalis Reservation, Washington; Confederated Tribes of the Colville Reservation, Washington; Confederated Tribes of the Umatilla Reservation, Oregon; Cowlitz Indian Tribe, Washington; Hoh Indian Tribe of the Hoh Indian Reservation, Washington; Jamestown S\\'Klallam Tribe of Washington; Kalispel Indian Community of the Kalispel Reservation, Washington; Lower Elwha Tribal Community of the Lower Elwha Reservation, Washington; Lummi Tribe of the Lummi Reservation, Washington; Makah Indian Tribe of the Makah Indian Reservation, Washington; Muckleshoot Indian Tribe of the Muckleshoot Reservation, Washington; Nisqually Indian Tribe of the Nisqually Reservation, Washington; Nez Perce Tribe, Idaho (previously listed as Nez Perce of Idaho); Nooksack Indian Tribe of Washington; Port Gamble Indian Community of the Port Gamble Reservation, Washington; Puyallup Tribe of the Puyallup Reservation, Washington; Quileute Tribe of the Quileute Reservation, Washington; Quinault Tribe of the Quinault Reservation, Washington; Samish Indian Tribe, Washington; Sauk-Suiattle Indian Tribe of Washington; Shoalwater Bay Tribe of the Shoalwater Bay Indian Reservation, Washington; Skokomish Indian Tribe of the Skokomish Reservation, Washington; Snoqualmie Tribe, Washington; Spokane Tribe of the Spokane Reservation, Washington; Squaxin Island Tribe of the Squaxin Island Reservation, Washington; Stillaguamish Tribe of Washington; Suquamish Indian Tribe of the Port Madison Reservation, Washington; Swinomish Indians of the Swinomish Reservation, Washington; Tulalip Tribes of the Tulalip Reservation, Washington; and the Upper Skagit Indian Tribe of Washington (hereafter referred to as \\xe2\\x80\\x9cThe Tribes\\xe2\\x80\\x9d).\\n        \\xe2\\x80\\xa2 Multiple lines of evidence, including treaties, Acts of Congress, and Executive Orders, indicate that the land from which the Native American human remains and the associated funerary object were removed is the aboriginal land of The Tribes.\\n        \\xe2\\x80\\xa2 Other credible lines of evidence, indicate that the land from which the Native American human remains and the associated funerary object were removed is the aboriginal land of The Tribes; the Confederated Tribes of the Warm Springs Reservation of Oregon; and the Wanapum Band of Priest Rapids, a non-Federally recognized Indian group.\\n        \\xe2\\x80\\xa2 Pursuant to 25 U.S.C. 3001(9), the human remains described in this notice represent the physical remains of 27 individuals of Native American ancestry.\\n        \\xe2\\x80\\xa2 Pursuant to 25 U.S.C. 3001(3)(A), the one object described above is reasonably believed to have been placed with or near individual human remains at the time of death or later as part of the death rite or ceremony.\\n        \\xe2\\x80\\xa2 Pursuant to 43 CFR 10.11(c)(1), the disposition of the human remains is to the Confederated Tribes of the Colville Reservation, Washington; Confederated Tribes of the Umatilla Reservation, Oregon; Lummi Tribe of the Lummi Reservation, Washington; Nez Perce Tribe, Idaho (previously listed as Nez Perce of Idaho); Samish Indian Tribe, Washington; Spokane Tribe of the Spokane Reservation, Washington; Stillaguamish Tribe of Washington; Suquamish Indian Tribe of the Port Madison Reservation, Washington; and the Wanapum Band of Priest Rapids, a non-Federally recognized Indian group (which together, comprise the Washington State Inter-Tribal Consortium).\\n        The Washington State Inter-Tribal Consortium tribes have come together to claim the human remains and the associated funerary object jointly. The Coeur D\\'Alene Tribe of the Coeur D\\'Alene Reservation, Idaho; Confederated Tribes and Bands of the Yakama Nation, Washington; Confederated Tribes of the Warm Springs Reservation of Oregon; Jamestown S\\'Klallam Tribe of Washington; Kalispel Indian Community of the Kalispel Reservation, Washington; Lower Elwha Tribal Community of the Lower Elwha Reservation, Washington; Nooksack Indian Tribe of Washington; Skokomish Indian Tribe of the Skokomish Reservation, Washington; and the Squaxin Island Tribe of the Squaxin Island Reservation, Washington, have stated their support for repatriation to the Washington State Inter-Tribal Consortium tribes.\\n        Additional Requestors and Disposition\\n        Representatives of any Indian tribe that believes itself to be culturally affiliated with the human remains or any other Indian tribe that believes it satisfies the criteria in 43 CFR 10.11(c)(1) should contact Peter Lape, Burke Museum, University of Washington, Box 353010, Seattle, WA 98115, telephone (206) 685-3849, before September 4, 2012. Disposition of the human remains to the Washington State Inter-Tribal Consortium tribes may proceed after that date if no additional requestors come forward.\\n        The Burke Museum is responsible for notifying The Tribes; the Confederated Tribes of the Warm Springs Reservation of Oregon; and the Wanapum Band of Priest Rapids, a non-Federally recognized Indian group that this notice has been published.\\n        \\n          Dated: July 11, 2012.\\n          David Tarler,\\n          Acting Manager, National NAGPRA Program. \\n        \\n      \\n      [FR Doc. 2012-18924 Filed 8-1-12; 8:45 am]\\n      BILLING CODE 4312-50-P\\n    ", "agency1": "DEPARTMENT OF THE INTERIOR", "sub_agency1": "National Park Service", "dep_doc": "[NPS-WASO-NAGPRA-10823; 2200-1100-665]", "subject": "Notice of Inventory Completion: Thomas Burke Memorial Washington State Museum, University of Washington, Seattle, WA", "agency2": "National Park Service, Interior.", "action": "Notice.", "summary": "The Thomas Burke Memorial Washington State Museum (Burke Museum) has completed an inventory of human remains and associated funerary objects, in consultation with the appropriate Indian tribes, and has determined that there is no cultural affiliation between the remains and any present-day Indian tribe. Representatives of any Indian tribe that believes itself to be culturally affiliated with the human remains may contact the Burke Museum. Disposition of the human remains and the associated funerary object to the Indian tribes stated below may occur if no additional requestors come forward.", "dates": "Representatives of any Indian tribe that believes it has a cultural affiliation with the human remains should contact the Burke Museum at the address below by September 4, 2012.", "addresses": "Peter Lape, Burke Museum, University of Washington, Box 353010, Seattle, WA 98195-3010, telephone (206) 685-3849.", "signature_dated": "Dated: July 11, 2012.", "signature_name": "David Tarler,", "signature_title": "Acting Manager, National NAGPRA Program. ", "fr_doc": "[FR Doc. 2012-18924 Filed 8-1-12; 8:45 am]", "billing_code": "BILLING CODE 4312-50-P", "supp_info": "SUPPLEMENTARY INFORMATION: \n Notice is hereby given in accordance with the Native American Graves Protection and Repatriation Act (NAGPRA), 25 U.S.C. 3003, of the completion of an inventory of human remains and associated funerary object in the possession of the Burke Museum. The human remains and associated funerary object were removed from an unknown location, most likely in the state of Washington. \n This notice is published as part of the National Park Service\\'s administrative responsibilities under NAGPRA, 25 U.S.C. 3003(d)(3) and 43 CFR 10.11(d). The determinations in this notice are the sole responsibility of the museum, institution, or Federal agency that has control of the Native American human remains. The National Park Service is not responsible for the determinations in this notice. \n Consultation \n A detailed assessment of the human remains was made by the Burke Museum professional staff in consultation with representatives of the Coeur D\\'Alene Tribe of the Coeur D\\'Alene Reservation, Idaho; Confederated Tribes and Bands of the Yakama Nation, Washington; Confederated Tribes of the Colville Reservation, Washington; Confederated Tribes of the Umatilla Reservation, Oregon; Confederated Tribes of the Warm Springs Reservation of Oregon; Cowlitz Indian Tribe, Washington; Jamestown S\\'Klallam Tribe of Washington; Kalispel Indian Community of the Kalispel Reservation, Washington; Lower Elwha Tribal Community of the Lower Elwha Reservation, Washington; Lummi Tribe of the Lummi Reservation, Washington; Makah Indian Tribe of the Makah Indian Reservation, Washington; Muckleshoot Indian Tribe of the Muckleshoot Reservation, Washington; Nez Perce Tribe, Idaho (previously listed as Nez Perce Tribe of Idaho); Nooksack Indian Tribe of Washington; Port Gamble Indian Community of the Port Gamble Reservation, Washington; Puyallup Tribe of the Puyallup Reservation, Washington; Samish Indian Tribe, Washington; Skokomish Indian Tribe of the Skokomish Reservation, Washington; Snoqualmie Tribe, Washington; Spokane Tribe of the Spokane Reservation, Washington; Squaxin Island Tribe of the Squaxin Island Reservation, Washington; Stillaguamish Tribe of Washington; Suquamish Indian Tribe of the Port Madison Reservation, Washington; Swinomish Indians of the Swinomish Reservation, Washington; and the Wanapum Band of Priest Rapids, a non-Federally recognized Indian group. The following tribes with aboriginal territory in the state of Washington were also invited to participate but were not involved in consultations: the Confederated Tribes of the Chehalis Reservation, Washington; Hoh Indian Tribe of the Hoh Indian Reservation, Washington; Nisqually Indian Tribe of the Nisqually Reservation, Washington; Quileute Tribe of the Quileute Reservation, Washington; Quinault Tribe of the Quinault Reservation, Washington; Sauk-Suiattle Indian Tribe of Washington; Shoalwater Bay Tribe of the Shoalwater Bay Indian Reservation, Washington; Tulalip Tribes of the Tulalip Reservation, Washington; and the Upper Skagit Indian Tribe of Washington. \n History and Description of the Remains \n At unknown dates, human remains representing, at minimum, 27 individuals were removed from unknown sites throughout the state of Washington. There is limited or no provenience information for the human remains. Based on the fact that they were disassociated from any acquisition documentation, they were assigned \\xe2\\x80\\x9cfound in collection\\xe2\\x80\\x9d accession numbers in 1973 and 1995. These human remains were crosschecked against the documentation for human remains known to have been missing, but did not match documentation for any specific collection. These human remains and the associated funerary object are most likely to have been removed from sites within the state of Washington. No known individuals were identified. The one associated funerary object is a composite artifact bag containing non-human mammal bones, shells, a rock, and two twigs. \n Determinations Made by the Burke Museum \n Officials of the Burke Museum have determined that: \n \\xe2\\x80\\xa2 Based on cranial morphology, dental traits, taphonomy, and museum accession documentation, the human remains are Native American. \n \\xe2\\x80\\xa2 Pursuant to 25 U.S.C. 3001(2), a relationship of shared group identity cannot be reasonably traced between the Native American human remains and any present-day Indian tribe. \n \\xe2\\x80\\xa2 According to final judgments of the Indian Claims Commission, the land from which the Native American human remains and the associated funerary object were removed is the aboriginal land of the Coeur D\\'Alene Tribe of the Coeur D\\'Alene Reservation, Idaho; Confederated Tribes and Bands of the Yakama Nation, Washington; Confederated Tribes of the Chehalis Reservation, Washington; Confederated Tribes of the Colville Reservation, Washington; Confederated Tribes of the Umatilla Reservation, Oregon; Cowlitz Indian Tribe, Washington; Hoh Indian Tribe of the Hoh Indian Reservation, Washington; Jamestown S\\'Klallam Tribe of Washington; Kalispel Indian Community of the Kalispel Reservation, Washington; Lower Elwha Tribal Community of the Lower Elwha Reservation, Washington; Lummi Tribe of the Lummi Reservation, Washington; Makah Indian Tribe of the Makah Indian Reservation, Washington; Muckleshoot Indian Tribe of the Muckleshoot Reservation, Washington; Nisqually Indian Tribe of the Nisqually Reservation, Washington; Nez Perce Tribe, Idaho (previously listed as Nez Perce of Idaho); Nooksack Indian Tribe of Washington; Port Gamble Indian Community of the Port Gamble Reservation, Washington; Puyallup Tribe of the Puyallup Reservation, Washington; Quileute Tribe of the Quileute Reservation, Washington; Quinault Tribe of the Quinault Reservation, Washington; Samish Indian Tribe, Washington; Sauk-Suiattle Indian Tribe of Washington; Shoalwater Bay Tribe of the Shoalwater Bay Indian Reservation, Washington; Skokomish Indian Tribe of the Skokomish Reservation, Washington; Snoqualmie Tribe, Washington; Spokane Tribe of the Spokane Reservation, Washington; Squaxin Island Tribe of the Squaxin Island Reservation, Washington; Stillaguamish Tribe of Washington; Suquamish Indian Tribe of the Port Madison Reservation, Washington; Swinomish Indians of the Swinomish Reservation, Washington; Tulalip Tribes of the Tulalip Reservation, Washington; and the Upper Skagit Indian Tribe of Washington (hereafter referred to as \\xe2\\x80\\x9cThe Tribes\\xe2\\x80\\x9d). \n \\xe2\\x80\\xa2 Multiple lines of evidence, including treaties, Acts of Congress, and Executive Orders, indicate that the land from which the Native American human remains and the associated funerary object were removed is the aboriginal land of The Tribes. \n \\xe2\\x80\\xa2 Other credible lines of evidence, indicate that the land from which the Native American human remains and the associated funerary object were removed is the aboriginal land of The Tribes; the Confederated Tribes of the Warm Springs Reservation of Oregon; and the Wanapum Band of Priest Rapids, a non-Federally recognized Indian group. \n \\xe2\\x80\\xa2 Pursuant to 25 U.S.C. 3001(9), the human remains described in this notice represent the physical remains of 27 individuals of Native American ancestry. \n \\xe2\\x80\\xa2 Pursuant to 25 U.S.C. 3001(3)(A), the one object described above is reasonably believed to have been placed with or near individual human remains at the time of death or later as part of the death rite or ceremony. \n \\xe2\\x80\\xa2 Pursuant to 43 CFR 10.11(c)(1), the disposition of the human remains is to the Confederated Tribes of the Colville Reservation, Washington; Confederated Tribes of the Umatilla Reservation, Oregon; Lummi Tribe of the Lummi Reservation, Washington; Nez Perce Tribe, Idaho (previously listed as Nez Perce of Idaho); Samish Indian Tribe, Washington; Spokane Tribe of the Spokane Reservation, Washington; Stillaguamish Tribe of Washington; Suquamish Indian Tribe of the Port Madison Reservation, Washington; and the Wanapum Band of Priest Rapids, a non-Federally recognized Indian group (which together, comprise the Washington State Inter-Tribal Consortium). \n The Washington State Inter-Tribal Consortium tribes have come together to claim the human remains and the associated funerary object jointly. The Coeur D\\'Alene Tribe of the Coeur D\\'Alene Reservation, Idaho; Confederated Tribes and Bands of the Yakama Nation, Washington; Confederated Tribes of the Warm Springs Reservation of Oregon; Jamestown S\\'Klallam Tribe of Washington; Kalispel Indian Community of the Kalispel Reservation, Washington; Lower Elwha Tribal Community of the Lower Elwha Reservation, Washington; Nooksack Indian Tribe of Washington; Skokomish Indian Tribe of the Skokomish Reservation, Washington; and the Squaxin Island Tribe of the Squaxin Island Reservation, Washington, have stated their support for repatriation to the Washington State Inter-Tribal Consortium tribes. \n Additional Requestors and Disposition \n Representatives of any Indian tribe that believes itself to be culturally affiliated with the human remains or any other Indian tribe that believes it satisfies the criteria in 43 CFR 10.11(c)(1) should contact Peter Lape, Burke Museum, University of Washington, Box 353010, Seattle, WA 98115, telephone (206) 685-3849, before September 4, 2012. Disposition of the human remains to the Washington State Inter-Tribal Consortium tribes may proceed after that date if no additional requestors come forward. \n The Burke Museum is responsible for notifying The Tribes; the Confederated Tribes of the Warm Springs Reservation of Oregon; and the Wanapum Band of Priest Rapids, a non-Federally recognized Indian group that this notice has been published. \n ", "consultation": "A detailed assessment of the human remains was made by the Burke Museum professional staff in consultation with representatives of the Coeur D\\'Alene Tribe of the Coeur D\\'Alene Reservation, Idaho; Confederated Tribes and Bands of the Yakama Nation, Washington; Confederated Tribes of the Colville Reservation, Washington; Confederated Tribes of the Umatilla Reservation, Oregon; Confederated Tribes of the Warm Springs Reservation of Oregon; Cowlitz Indian Tribe, Washington; Jamestown S\\'Klallam Tribe of Washington; Kalispel Indian Community of the Kalispel Reservation, Washington; Lower Elwha Tribal Community of the Lower Elwha Reservation, Washington; Lummi Tribe of the Lummi Reservation, Washington; Makah Indian Tribe of the Makah Indian Reservation, Washington; Muckleshoot Indian Tribe of the Muckleshoot Reservation, Washington; Nez Perce Tribe, Idaho (previously listed as Nez Perce Tribe of Idaho); Nooksack Indian Tribe of Washington; Port Gamble Indian Community of the Port Gamble Reservation, Washington; Puyallup Tribe of the Puyallup Reservation, Washington; Samish Indian Tribe, Washington; Skokomish Indian Tribe of the Skokomish Reservation, Washington; Snoqualmie Tribe, Washington; Spokane Tribe of the Spokane Reservation, Washington; Squaxin Island Tribe of the Squaxin Island Reservation, Washington; Stillaguamish Tribe of Washington; Suquamish Indian Tribe of the Port Madison Reservation, Washington; Swinomish Indians of the Swinomish Reservation, Washington; and the Wanapum Band of Priest Rapids, a non-Federally recognized Indian group. The following tribes with aboriginal territory in the state of Washington were also invited to participate but were not involved in consultations: the Confederated Tribes of the Chehalis Reservation, Washington; Hoh Indian Tribe of the Hoh Indian Reservation, Washington; Nisqually Indian Tribe of the Nisqually Reservation, Washington; Quileute Tribe of the Quileute Reservation, Washington; Quinault Tribe of the Quinault Reservation, Washington; Sauk-Suiattle Indian Tribe of Washington; Shoalwater Bay Tribe of the Shoalwater Bay Indian Reservation, Washington; Tulalip Tribes of the Tulalip Reservation, Washington; and the Upper Skagit Indian Tribe of Washington. \n ", "h_d_r": "At unknown dates, human remains representing, at minimum, 27 individuals were removed from unknown sites throughout the state of Washington. There is limited or no provenience information for the human remains. Based on the fact that they were disassociated from any acquisition documentation, they were assigned \\xe2\\x80\\x9cfound in collection\\xe2\\x80\\x9d accession numbers in 1973 and 1995. These human remains were crosschecked against the documentation for human remains known to have been missing, but did not match documentation for any specific collection. These human remains and the associated funerary object are most likely to have been removed from sites within the state of Washington. No known individuals were identified. The one associated funerary object is a composite artifact bag containing non-human mammal bones, shells, a rock, and two twigs. \n ", "h_d_ci": "Null", "determinations": "Determinations Made by the Burke Museum \n Officials of the Burke Museum have determined that: \n \\xe2\\x80\\xa2 Based on cranial morphology, dental traits, taphonomy, and museum accession documentation, the human remains are Native American. \n \\xe2\\x80\\xa2 Pursuant to 25 U.S.C. 3001(2), a relationship of shared group identity cannot be reasonably traced between the Native American human remains and any present-day Indian tribe. \n \\xe2\\x80\\xa2 According to final judgments of the Indian Claims Commission, the land from which the Native American human remains and the associated funerary object were removed is the aboriginal land of the Coeur D\\'Alene Tribe of the Coeur D\\'Alene Reservation, Idaho; Confederated Tribes and Bands of the Yakama Nation, Washington; Confederated Tribes of the Chehalis Reservation, Washington; Confederated Tribes of the Colville Reservation, Washington; Confederated Tribes of the Umatilla Reservation, Oregon; Cowlitz Indian Tribe, Washington; Hoh Indian Tribe of the Hoh Indian Reservation, Washington; Jamestown S\\'Klallam Tribe of Washington; Kalispel Indian Community of the Kalispel Reservation, Washington; Lower Elwha Tribal Community of the Lower Elwha Reservation, Washington; Lummi Tribe of the Lummi Reservation, Washington; Makah Indian Tribe of the Makah Indian Reservation, Washington; Muckleshoot Indian Tribe of the Muckleshoot Reservation, Washington; Nisqually Indian Tribe of the Nisqually Reservation, Washington; Nez Perce Tribe, Idaho (previously listed as Nez Perce of Idaho); Nooksack Indian Tribe of Washington; Port Gamble Indian Community of the Port Gamble Reservation, Washington; Puyallup Tribe of the Puyallup Reservation, Washington; Quileute Tribe of the Quileute Reservation, Washington; Quinault Tribe of the Quinault Reservation, Washington; Samish Indian Tribe, Washington; Sauk-Suiattle Indian Tribe of Washington; Shoalwater Bay Tribe of the Shoalwater Bay Indian Reservation, Washington; Skokomish Indian Tribe of the Skokomish Reservation, Washington; Snoqualmie Tribe, Washington; Spokane Tribe of the Spokane Reservation, Washington; Squaxin Island Tribe of the Squaxin Island Reservation, Washington; Stillaguamish Tribe of Washington; Suquamish Indian Tribe of the Port Madison Reservation, Washington; Swinomish Indians of the Swinomish Reservation, Washington; Tulalip Tribes of the Tulalip Reservation, Washington; and the Upper Skagit Indian Tribe of Washington (hereafter referred to as \\xe2\\x80\\x9cThe Tribes\\xe2\\x80\\x9d). \n \\xe2\\x80\\xa2 Multiple lines of evidence, including treaties, Acts of Congress, and Executive Orders, indicate that the land from which the Native American human remains and the associated funerary object were removed is the aboriginal land of The Tribes. \n \\xe2\\x80\\xa2 Other credible lines of evidence, indicate that the land from which the Native American human remains and the associated funerary object were removed is the aboriginal land of The Tribes; the Confederated Tribes of the Warm Springs Reservation of Oregon; and the Wanapum Band of Priest Rapids, a non-Federally recognized Indian group. \n \\xe2\\x80\\xa2 Pursuant to 25 U.S.C. 3001(9), the human remains described in this notice represent the physical remains of 27 individuals of Native American ancestry. \n \\xe2\\x80\\xa2 Pursuant to 25 U.S.C. 3001(3)(A), the one object described above is reasonably believed to have been placed with or near individual human remains at the time of death or later as part of the death rite or ceremony. \n \\xe2\\x80\\xa2 Pursuant to 43 CFR 10.11(c)(1), the disposition of the human remains is to the Confederated Tribes of the Colville Reservation, Washington; Confederated Tribes of the Umatilla Reservation, Oregon; Lummi Tribe of the Lummi Reservation, Washington; Nez Perce Tribe, Idaho (previously listed as Nez Perce of Idaho); Samish Indian Tribe, Washington; Spokane Tribe of the Spokane Reservation, Washington; Stillaguamish Tribe of Washington; Suquamish Indian Tribe of the Port Madison Reservation, Washington; and the Wanapum Band of Priest Rapids, a non-Federally recognized Indian group (which together, comprise the Washington State Inter-Tribal Consortium). \n The Washington State Inter-Tribal Consortium tribes have come together to claim the human remains and the associated funerary object jointly. The Coeur D\\'Alene Tribe of the Coeur D\\'Alene Reservation, Idaho; Confederated Tribes and Bands of the Yakama Nation, Washington; Confederated Tribes of the Warm Springs Reservation of Oregon; Jamestown S\\'Klallam Tribe of Washington; Kalispel Indian Community of the Kalispel Reservation, Washington; Lower Elwha Tribal Community of the Lower Elwha Reservation, Washington; Nooksack Indian Tribe of Washington; Skokomish Indian Tribe of the Skokomish Reservation, Washington; and the Squaxin Island Tribe of the Squaxin Island Reservation, Washington, have stated their support for repatriation to the Washington State Inter-Tribal Consortium tribes. \n ", "a_r_d": "Representatives of any Indian tribe that believes itself to be culturally affiliated with the human remains or any other Indian tribe that believes it satisfies the criteria in 43 CFR 10.11(c)(1) should contact Peter Lape, Burke Museum, University of Washington, Box 353010, Seattle, WA 98115, telephone (206) 685-3849, before September 4, 2012. Disposition of the human remains to the Washington State Inter-Tribal Consortium tribes may proceed after that date if no additional requestors come forward. \n The Burke Museum is responsible for notifying The Tribes; the Confederated Tribes of the Warm Springs Reservation of Oregon; and the Wanapum Band of Priest Rapids, a non-Federally recognized Indian group that this notice has been published. \n "}