{"index": "I_1061", "messy_full": "\\n      \\n        DEPARTMENT OF THE INTERIOR\\n        National Park Service\\n        [2253-665]\\n        Notice of Inventory Completion: Sheboygan County Historical Museum, Sheboygan, WI\\n        \\n          AGENCY:\\n          National Park Service, Interior.\\n        \\n        \\n          ACTION:\\n          Notice.\\n        \\n        \\n          SUMMARY:\\n          The Sheboygan County Historical Museum has completed an inventory of human remains, in consultation with the appropriate Indian tribes, and has determined that there is no cultural affiliation between the remains and any present-day Indian tribe. Representatives of any Indian tribe that believes itself to be culturally affiliated with the human remains may contact the Sheboygan County Historical Museum. Disposition of the human remains to the Indian tribes stated below may occur if no additional requestors come forward.\\n        \\n        \\n          \\n          DATES:\\n          Representatives of any Indian tribe that believes it has a cultural affiliation with the human remains should contact the Sheboygan County Historical Museum at the address below by May 21, 2012.\\n        \\n        \\n          ADDRESSES:\\n          Tamara Lange, Collection Coordinator/Registrar, Sheboygan County Historical Museum, 3110 Erie Avenue, Sheboygan, WI 53081, telephone (920) 458-1103.\\n        \\n      \\n      \\n        SUPPLEMENTARY INFORMATION:\\n        Notice is here given in accordance with the Native American Graves Protection and Repatriation Act (NAGPRA), 25 U.S.C. 3003, of the completion of an inventory of human remains under the control of the Sheboygan County Historical Museum, Sheboygan, Wisconsin. The human remains are believed to have been removed from an unknown location in or adjoining to Sheboygan County, WI.\\n        This notice is published as part of the National Park Service\\'s administrative responsibilities under NAGPRA, 25 U.S.C. 3003(d)(3) and 43 CFR 10.11(d). The determinations in this notice are the sole responsibility of the museum, institution, or Federal agency that has control of the Native American human remains. The National Park Service is not responsible for the determinations in this notice.\\n        Consultation\\n        A detailed assessment of the human remains was made by the Sheboygan County Historical Museum professional staff in consultation with representatives of the Bad River Band of the Lake Superior Tribe of Chippewa Indians of the Bad River Reservation, Wisconsin; Bois Forte Band (Nett Lake) of the Minnesota Chippewa Tribe, Minnesota; Citizen Potawatomi Nation, Oklahoma; Flandreau Santee Sioux Tribe of South Dakota; Fond du Lac Band of the Minnesota Chippewa Tribe, Minnesota; Forest County Potawatomi Community, Wisconsin; Grand Portage Band of the Minnesota Chippewa Tribe, Minnesota; Hannahville Indian Community, Michigan; Ho-Chunk Nation of Wisconsin; Keweenaw Bay Indian Community, Michigan; Lac Courte Oreilles Band of Lake Superior Chippewa Indians of Wisconsin; Lac du Flambeau Band of Lake Superior Chippewa Indians of the Lac du Flambeau Reservation of Wisconsin; Lac Vieux Desert Band of Lake Superior Chippewa Indians, Michigan; Leech Lake Band of the Minnesota Chippewa Tribe, Minnesota; Lower Sioux Indian Community in the State of Minnesota; Menominee Indian Tribe of Wisconsin; Mille Lacs Band of the Minnesota Chippewa Tribe, Minnesota; Oneida Tribe of Indians of Wisconsin; Prairie Band of Potawatomi Nation, Kansas; Prairie Island Indian Community in the State of Minnesota; Red Cliff Band of Lake Superior Chippewa Indians of Wisconsin; Sac & Fox Nation of Missouri in Kansas and Nebraska; Sac & Fox Nation, Oklahoma; Sac & Fox Tribe of the Mississippi in Iowa; Santee Sioux Nation, Nebraska; Sisseton-Wahpeton Oyate of the Lake Traverse Reservation, South Dakota; Sokaogon Chippewa Community, Wisconsin; Spirit Lake Tribe, North Dakota; St. Croix Chippewa Indians of Wisconsin; Stockbridge Munsee Community, Wisconsin; Upper Sioux Community, Minnesota; White Earth Band of Minnesota Chippewa Tribe, Minnesota; and Winnebago Tribe of Nebraska (herein referred to as \\xe2\\x80\\x9cThe Tribes\\xe2\\x80\\x9d).\\n        History and Description of the Remains\\n        At an unknown date between 1899 and 1917, human remains representing, at minimum, one individual were removed from a site believed to have been in or adjoining to Sheboygan County, WI, by Dr. Alphonse J. Gerend. At least a portion of Dr. Gerend\\'s collection was held at the Public Library in Sheboygan with the intention that the items be on exhibit there until a museum or other appropriate gallery was established in the city. At some time following the establishment of the Sheboygan County Historical Society in 1923, the Gerend Collection, including the human remains, was transferred to the custody of the Sheboygan County Historical Society & Museum. The exact circumstances or date of the transfer are unknown. Later efforts by staff at the Museum to inventory Dr. Gerend\\'s collection included a 1994 inventory where the bone was misclassified as a potsherd (SCHM Object Number 3240.126). A subsequent inventory in the fall of 2009 uncovered the misidentification. The human remains consist of a single cranial fragment. No known individuals were identified. No associated funerary objects are present.\\n        Determinations Made by the Sheboygan County Historical Museum\\n        Officials of the Sheboygan County Historical Museum have determined that:\\n        \\xe2\\x80\\xa2 Based upon non-destructive physical analysis and the history and collecting practices of the donor (Dr. Alphonse Gerend), the human remains are Native American.\\n        \\xe2\\x80\\xa2 Pursuant to 25 U.S.C. 3001(2), a relationship of shared group identity cannot be reasonably traced between the Native American human remains and any present-day Indian tribe.\\n        \\xe2\\x80\\xa2 According to final judgments of the Indian Claims Commission, the land from which the Native American human remains were removed is the aboriginal land of The Tribes.\\n        \\xe2\\x80\\xa2 Multiple lines of evidence, including treaties, Acts of Congress, and Executive Orders, indicate that the land from which the Native American human remains were removed is the aboriginal land of The Tribes.\\n        \\xe2\\x80\\xa2 Other credible lines of evidence indicate that the land from which the Native American human remains were removed is the aboriginal land of The Tribes.\\n        \\xe2\\x80\\xa2 Pursuant to 25 U.S.C. 3001(9), the human remains described in this notice represent the physical remains of one individual of Native American ancestry.\\n        \\xe2\\x80\\xa2 Pursuant to 43 CFR 10.11(c)(1), the disposition of the human remains is to The Tribes.\\n        Additional Requestors and Disposition\\n        Representatives of any Indian tribe that believes itself to be culturally affiliated with the human remains or any other Indian tribe that believes it satisfies the criteria in 43 CFR 10.11(c)(1) should contact Tamara Lange, Collection Coordinator/Registrar, Sheboygan County Historical Museum, 3110 Erie Avenue, Sheboygan, WI 53081, telephone (920) 458-1103, before May 21, 2012. Disposition of the human remains to The Tribes may proceed after that date if no additional requestors come forward.\\n        The Sheboygan County Historical Museum is responsible for notifying The Tribes that this notice has been published.\\n        \\n          Dated: April 12, 2012.\\n          David Tarler,\\n          Acting Manager, National NAGPRA Program. \\n        \\n      \\n      [FR Doc. 2012-9467 Filed 4-18-12; 8:45 am]\\n      BILLING CODE 4312-50-P\\n    ", "agency1": "DEPARTMENT OF THE INTERIOR", "sub_agency1": "National Park Service", "dep_doc": "[2253-665]", "subject": "Notice of Inventory Completion: Sheboygan County Historical Museum, Sheboygan, WI", "agency2": "National Park Service, Interior.", "action": "Notice.", "summary": "The Sheboygan County Historical Museum has completed an inventory of human remains, in consultation with the appropriate Indian tribes, and has determined that there is no cultural affiliation between the remains and any present-day Indian tribe. Representatives of any Indian tribe that believes itself to be culturally affiliated with the human remains may contact the Sheboygan County Historical Museum. Disposition of the human remains to the Indian tribes stated below may occur if no additional requestors come forward.", "dates": "Representatives of any Indian tribe that believes it has a cultural affiliation with the human remains should contact the Sheboygan County Historical Museum at the address below by May 21, 2012.", "addresses": "Tamara Lange, Collection Coordinator/Registrar, Sheboygan County Historical Museum, 3110 Erie Avenue, Sheboygan, WI 53081, telephone (920) 458-1103.", "signature_dated": "Dated: April 12, 2012.", "signature_name": "David Tarler,", "signature_title": "Acting Manager, National NAGPRA Program. ", "fr_doc": "[FR Doc. 2012-9467 Filed 4-18-12; 8:45 am]", "billing_code": "BILLING CODE 4312-50-P", "supp_info": "SUPPLEMENTARY INFORMATION: \n Notice is here given in accordance with the Native American Graves Protection and Repatriation Act (NAGPRA), 25 U.S.C. 3003, of the completion of an inventory of human remains under the control of the Sheboygan County Historical Museum, Sheboygan, Wisconsin. The human remains are believed to have been removed from an unknown location in or adjoining to Sheboygan County, WI. \n This notice is published as part of the National Park Service\\'s administrative responsibilities under NAGPRA, 25 U.S.C. 3003(d)(3) and 43 CFR 10.11(d). The determinations in this notice are the sole responsibility of the museum, institution, or Federal agency that has control of the Native American human remains. The National Park Service is not responsible for the determinations in this notice. \n Consultation \n A detailed assessment of the human remains was made by the Sheboygan County Historical Museum professional staff in consultation with representatives of the Bad River Band of the Lake Superior Tribe of Chippewa Indians of the Bad River Reservation, Wisconsin; Bois Forte Band (Nett Lake) of the Minnesota Chippewa Tribe, Minnesota; Citizen Potawatomi Nation, Oklahoma; Flandreau Santee Sioux Tribe of South Dakota; Fond du Lac Band of the Minnesota Chippewa Tribe, Minnesota; Forest County Potawatomi Community, Wisconsin; Grand Portage Band of the Minnesota Chippewa Tribe, Minnesota; Hannahville Indian Community, Michigan; Ho-Chunk Nation of Wisconsin; Keweenaw Bay Indian Community, Michigan; Lac Courte Oreilles Band of Lake Superior Chippewa Indians of Wisconsin; Lac du Flambeau Band of Lake Superior Chippewa Indians of the Lac du Flambeau Reservation of Wisconsin; Lac Vieux Desert Band of Lake Superior Chippewa Indians, Michigan; Leech Lake Band of the Minnesota Chippewa Tribe, Minnesota; Lower Sioux Indian Community in the State of Minnesota; Menominee Indian Tribe of Wisconsin; Mille Lacs Band of the Minnesota Chippewa Tribe, Minnesota; Oneida Tribe of Indians of Wisconsin; Prairie Band of Potawatomi Nation, Kansas; Prairie Island Indian Community in the State of Minnesota; Red Cliff Band of Lake Superior Chippewa Indians of Wisconsin; Sac & Fox Nation of Missouri in Kansas and Nebraska; Sac & Fox Nation, Oklahoma; Sac & Fox Tribe of the Mississippi in Iowa; Santee Sioux Nation, Nebraska; Sisseton-Wahpeton Oyate of the Lake Traverse Reservation, South Dakota; Sokaogon Chippewa Community, Wisconsin; Spirit Lake Tribe, North Dakota; St. Croix Chippewa Indians of Wisconsin; Stockbridge Munsee Community, Wisconsin; Upper Sioux Community, Minnesota; White Earth Band of Minnesota Chippewa Tribe, Minnesota; and Winnebago Tribe of Nebraska (herein referred to as \\xe2\\x80\\x9cThe Tribes\\xe2\\x80\\x9d). \n History and Description of the Remains \n At an unknown date between 1899 and 1917, human remains representing, at minimum, one individual were removed from a site believed to have been in or adjoining to Sheboygan County, WI, by Dr. Alphonse J. Gerend. At least a portion of Dr. Gerend\\'s collection was held at the Public Library in Sheboygan with the intention that the items be on exhibit there until a museum or other appropriate gallery was established in the city. At some time following the establishment of the Sheboygan County Historical Society in 1923, the Gerend Collection, including the human remains, was transferred to the custody of the Sheboygan County Historical Society & Museum. The exact circumstances or date of the transfer are unknown. Later efforts by staff at the Museum to inventory Dr. Gerend\\'s collection included a 1994 inventory where the bone was misclassified as a potsherd (SCHM Object Number 3240.126). A subsequent inventory in the fall of 2009 uncovered the misidentification. The human remains consist of a single cranial fragment. No known individuals were identified. No associated funerary objects are present. \n Determinations Made by the Sheboygan County Historical Museum \n Officials of the Sheboygan County Historical Museum have determined that: \n \\xe2\\x80\\xa2 Based upon non-destructive physical analysis and the history and collecting practices of the donor (Dr. Alphonse Gerend), the human remains are Native American. \n \\xe2\\x80\\xa2 Pursuant to 25 U.S.C. 3001(2), a relationship of shared group identity cannot be reasonably traced between the Native American human remains and any present-day Indian tribe. \n \\xe2\\x80\\xa2 According to final judgments of the Indian Claims Commission, the land from which the Native American human remains were removed is the aboriginal land of The Tribes. \n \\xe2\\x80\\xa2 Multiple lines of evidence, including treaties, Acts of Congress, and Executive Orders, indicate that the land from which the Native American human remains were removed is the aboriginal land of The Tribes. \n \\xe2\\x80\\xa2 Other credible lines of evidence indicate that the land from which the Native American human remains were removed is the aboriginal land of The Tribes. \n \\xe2\\x80\\xa2 Pursuant to 25 U.S.C. 3001(9), the human remains described in this notice represent the physical remains of one individual of Native American ancestry. \n \\xe2\\x80\\xa2 Pursuant to 43 CFR 10.11(c)(1), the disposition of the human remains is to The Tribes. \n Additional Requestors and Disposition \n Representatives of any Indian tribe that believes itself to be culturally affiliated with the human remains or any other Indian tribe that believes it satisfies the criteria in 43 CFR 10.11(c)(1) should contact Tamara Lange, Collection Coordinator/Registrar, Sheboygan County Historical Museum, 3110 Erie Avenue, Sheboygan, WI 53081, telephone (920) 458-1103, before May 21, 2012. Disposition of the human remains to The Tribes may proceed after that date if no additional requestors come forward. \n The Sheboygan County Historical Museum is responsible for notifying The Tribes that this notice has been published. \n ", "consultation": "A detailed assessment of the human remains was made by the Sheboygan County Historical Museum professional staff in consultation with representatives of the Bad River Band of the Lake Superior Tribe of Chippewa Indians of the Bad River Reservation, Wisconsin; Bois Forte Band (Nett Lake) of the Minnesota Chippewa Tribe, Minnesota; Citizen Potawatomi Nation, Oklahoma; Flandreau Santee Sioux Tribe of South Dakota; Fond du Lac Band of the Minnesota Chippewa Tribe, Minnesota; Forest County Potawatomi Community, Wisconsin; Grand Portage Band of the Minnesota Chippewa Tribe, Minnesota; Hannahville Indian Community, Michigan; Ho-Chunk Nation of Wisconsin; Keweenaw Bay Indian Community, Michigan; Lac Courte Oreilles Band of Lake Superior Chippewa Indians of Wisconsin; Lac du Flambeau Band of Lake Superior Chippewa Indians of the Lac du Flambeau Reservation of Wisconsin; Lac Vieux Desert Band of Lake Superior Chippewa Indians, Michigan; Leech Lake Band of the Minnesota Chippewa Tribe, Minnesota; Lower Sioux Indian Community in the State of Minnesota; Menominee Indian Tribe of Wisconsin; Mille Lacs Band of the Minnesota Chippewa Tribe, Minnesota; Oneida Tribe of Indians of Wisconsin; Prairie Band of Potawatomi Nation, Kansas; Prairie Island Indian Community in the State of Minnesota; Red Cliff Band of Lake Superior Chippewa Indians of Wisconsin; Sac & Fox Nation of Missouri in Kansas and Nebraska; Sac & Fox Nation, Oklahoma; Sac & Fox Tribe of the Mississippi in Iowa; Santee Sioux Nation, Nebraska; Sisseton-Wahpeton Oyate of the Lake Traverse Reservation, South Dakota; Sokaogon Chippewa Community, Wisconsin; Spirit Lake Tribe, North Dakota; St. Croix Chippewa Indians of Wisconsin; Stockbridge Munsee Community, Wisconsin; Upper Sioux Community, Minnesota; White Earth Band of Minnesota Chippewa Tribe, Minnesota; and Winnebago Tribe of Nebraska (herein referred to as \\xe2\\x80\\x9cThe Tribes\\xe2\\x80\\x9d). \n ", "h_d_r": "At an unknown date between 1899 and 1917, human remains representing, at minimum, one individual were removed from a site believed to have been in or adjoining to Sheboygan County, WI, by Dr. Alphonse J. Gerend. At least a portion of Dr. Gerend\\'s collection was held at the Public Library in Sheboygan with the intention that the items be on exhibit there until a museum or other appropriate gallery was established in the city. At some time following the establishment of the Sheboygan County Historical Society in 1923, the Gerend Collection, including the human remains, was transferred to the custody of the Sheboygan County Historical Society & Museum. The exact circumstances or date of the transfer are unknown. Later efforts by staff at the Museum to inventory Dr. Gerend\\'s collection included a 1994 inventory where the bone was misclassified as a potsherd (SCHM Object Number 3240.126). A subsequent inventory in the fall of 2009 uncovered the misidentification. The human remains consist of a single cranial fragment. No known individuals were identified. No associated funerary objects are present. \n ", "h_d_ci": "Null", "determinations": "Determinations Made by the Sheboygan County Historical Museum \n Officials of the Sheboygan County Historical Museum have determined that: \n \\xe2\\x80\\xa2 Based upon non-destructive physical analysis and the history and collecting practices of the donor (Dr. Alphonse Gerend), the human remains are Native American. \n \\xe2\\x80\\xa2 Pursuant to 25 U.S.C. 3001(2), a relationship of shared group identity cannot be reasonably traced between the Native American human remains and any present-day Indian tribe. \n \\xe2\\x80\\xa2 According to final judgments of the Indian Claims Commission, the land from which the Native American human remains were removed is the aboriginal land of The Tribes. \n \\xe2\\x80\\xa2 Multiple lines of evidence, including treaties, Acts of Congress, and Executive Orders, indicate that the land from which the Native American human remains were removed is the aboriginal land of The Tribes. \n \\xe2\\x80\\xa2 Other credible lines of evidence indicate that the land from which the Native American human remains were removed is the aboriginal land of The Tribes. \n \\xe2\\x80\\xa2 Pursuant to 25 U.S.C. 3001(9), the human remains described in this notice represent the physical remains of one individual of Native American ancestry. \n \\xe2\\x80\\xa2 Pursuant to 43 CFR 10.11(c)(1), the disposition of the human remains is to The Tribes. \n ", "a_r_d": "Representatives of any Indian tribe that believes itself to be culturally affiliated with the human remains or any other Indian tribe that believes it satisfies the criteria in 43 CFR 10.11(c)(1) should contact Tamara Lange, Collection Coordinator/Registrar, Sheboygan County Historical Museum, 3110 Erie Avenue, Sheboygan, WI 53081, telephone (920) 458-1103, before May 21, 2012. Disposition of the human remains to The Tribes may proceed after that date if no additional requestors come forward. \n The Sheboygan County Historical Museum is responsible for notifying The Tribes that this notice has been published. \n "}