{"index": "I_100", "messy_full": "\\n      \\n        DEPARTMENT OF THE INTERIOR\\n        National Park Service\\n        [NPS-WASO-NAGPRA-NPS0027609, PPWOCRADN0-PCU00RP14.R50000]\\n        Notice of Inventory Completion: U.S. Department of the Interior, National Park Service, Petrified Forest National Park, Petrified Forest, AZ\\n        \\n          AGENCY:\\n          National Park Service, Interior.\\n        \\n        \\n          ACTION:\\n          Notice.\\n        \\n        \\n          SUMMARY:\\n          The U.S. Department of the Interior, National Park Service, Petrified Forest National Park has completed an inventory of human remains, in consultation with the appropriate Indian Tribes or Native Hawaiian organizations, and has determined that there is no cultural affiliation between the human remains and any present-day Indian Tribes or Native Hawaiian organizations. Representatives of any Indian Tribe or Native Hawaiian organization not identified in this notice that wish to request transfer of control of these human remains should submit a written request to Petrified Forest National Park. If no additional requestors come forward, transfer of control of the human remains to the Indian Tribes or Native Hawaiian organizations stated in this notice may proceed.\\n        \\n        \\n          DATES:\\n          Representatives of any Indian Tribe or Native Hawaiian organization not identified in this notice that wish to request transfer of control of these human remains should submit a written request with information in support of the request to Petrified Forest National Park at the address in this notice by May 29, 2019.\\n        \\n        \\n          ADDRESSES:\\n\\n          Brad Traver, Superintendent, Petrified Forest National Park, 1 Park Road, P.O. Box 2217, Petrified Forest, AZ 86028, telephone (928) 524-6228 Ext. 225, email brad_traver@nps.gov.\\n          \\n        \\n      \\n      \\n        SUPPLEMENTARY INFORMATION:\\n        Notice is here given in accordance with the Native American Graves Protection and Repatriation Act (NAGPRA), 25 U.S.C. 3003, of the completion of an inventory of human remains under the control of the U.S. Department of the Interior, National Park Service, Petrified Forest National Park, Petrified Forest, AZ, and in the physical custody of the Museum of Northern Arizona in Flagstaff, AZ. The human remains were removed from Petrified Forest National Park, AZ.\\n        This notice is published as part of the National Park Service\\'s administrative responsibilities under NAGPRA, 25 U.S.C. 3003(d)(3) and 43 CFR 10.11(d). The determinations in this notice are the sole responsibility of the Superintendent, Petrified Forest National Park.\\n        Consultation\\n        A detailed assessment of the human remains was made by Petrified Forest National Park professional staff in consultation with representatives of the Fort McDowell Yavapai Nation, Arizona; Hopi Tribe of Arizona; Hualapai Indian Tribe of the Hualapai Indian Reservation, Arizona; Kewa Pueblo, New Mexico (previously listed as the Pueblo of Santo Domingo); Navajo Nation, Arizona, New Mexico & Utah; Pueblo of Acoma, New Mexico; Pueblo of Santa Ana, New Mexico; and the Zuni Tribe of the Zuni Reservation, New Mexico (hereafter referred to as \\xe2\\x80\\x9cThe Consulted Tribes\\xe2\\x80\\x9d).\\n\\n        The following tribes were invited to consult, but did not participate: Colorado River Indian Tribes of the Colorado Indian Reservation, Arizona and California; Fort Mojave Indian Tribe of Arizona, California & Nevada; Gila River Indian Community of the Gila River Indian Reservation, Arizona; Havasupai Tribe of the Havasupai Reservation, Arizona; Kaibab Band of Paiute Indians of the Kaibab Indian Reservation, Arizona; Las Vegas Tribe of Paiute Indians of the Las Vegas Indian Colony, Nevada; Moapa Band of the Paiute Indians of the Moapa River Indian Reservation, Nevada; Ohkay Owingeh, New Mexico (previously listed as the Pueblo of San Juan); Paiute Indian Tribe of Utah (Cedar Band of Paiutes, Kanosh Band of Paiutes, Koosharem Band of Paiutes, Indian Peaks Band of Paiutes, and Shivwits Band of Paiutes (formerly Paiute Indian Tribe of Utah (Cedar City Band of Paiutes, Kanosh Band of Paiutes, Koosharem Band of Paiutes, Indian Peaks Band of Paiutes, and Shivwits Band of Paiutes)); Pascua Yaqui Tribe of Arizona; Pueblo of Cochiti, New Mexico; Pueblo of Isleta, New Mexico; Pueblo of Jemez, New Mexico; Pueblo of Laguna, New Mexico; Pueblo of Nambe, New Mexico; Pueblo of Picuris, New Mexico; Pueblo of Pojoaque, New Mexico; Pueblo of San Felipe, New Mexico; Pueblo of San Ildefonso, New Mexico; Pueblo of Sandia, New Mexico; Pueblo of Santa Clara, New Mexico; Pueblo of Taos, New Mexico; Pueblo of Tesuque, New Mexico; Pueblo of Zia, New Mexico; San Carlos Apache Tribe of the San Carlos Reservation, Arizona; San Juan Southern Paiute Tribe of Arizona; Tohono O\\'odham Nation of Arizona; Tonto Apache Tribe of Arizona; and the Yavapai-Apache Nation of the Camp Verde Indian Reservation, Arizona (hereafter referred to as \\xe2\\x80\\x9cThe Invited Tribes\\xe2\\x80\\x9d).\\n        History and Description of the Remains\\n        On an unknown date, human remains representing, at minimum, one individual were removed from an unknown site likely within the boundaries of Petrified Forest National Park. No known individuals were identified. No associated funerary objects are present.\\n        Determinations Made by Petrified Forest National Park\\n        Officials of Petrified Forest National Park have determined that:\\n        \\xe2\\x80\\xa2 Pursuant to 25 U.S.C. 3001(9), the human remains described in this notice are Native American based on their osteological characteristics, as determined by James T. Watson from Arizona State University in August of 2010.\\n        \\xe2\\x80\\xa2 Pursuant to 25 U.S.C. 3001(9), the human remains described in this notice represent the physical remains of one individual of Native American ancestry.\\n        \\xe2\\x80\\xa2 Pursuant to 25 U.S.C. 3001(2), a relationship of shared group identity cannot be reasonably traced between the Native American human remains and any present-day Indian Tribe.\\n        \\xe2\\x80\\xa2 According to final judgments of the Indian Claims Commission or the Court of Federal Claims, the land from which the Native American human remains were removed is the aboriginal land of the Navajo Nation, Arizona, New Mexico & Utah and the Zuni Tribe of the Zuni Reservation, New Mexico.\\n        \\xe2\\x80\\xa2 Pursuant to 43 CFR 10.11(c)(1), the disposition of the human remains may be to the Navajo Nation, Arizona, New Mexico & Utah and the Zuni Tribe of the Zuni Reservation, New Mexico.\\n        Additional Requestors and Disposition\\n\\n        Representatives of any Indian Tribe or Native Hawaiian organization not identified in this notice that wish to request transfer of control of these human remains should submit a written request with information in support of the request to Brad Traver, Superintendent, Petrified Forest National Park, P.O. Box 2217, Petrified Forest, AZ 86028, telephone (928) 524-6228 Ext. 225, email Brad_Traver@nps.gov, by May 29, 2019. After that date, if no additional requestors have come forward, transfer of control of the human remains to the Navajo Nation, Arizona, New Mexico & Utah and the Zuni Tribe of the Zuni Reservation, New Mexico may proceed.\\n        Petrified Forest National Park is responsible for notifying The Consulted Tribes and The Invited Tribes that this notice has been published.\\n        \\n          Dated: April 2, 2019.\\n          Melanie O\\'Brien,\\n          Manager, National NAGPRA Program. \\n        \\n      \\n      [FR Doc. 2019-08594 Filed 4-26-19; 8:45 am]\\n       BILLING CODE 4312-52-P\\n    ", "agency1": "DEPARTMENT OF THE INTERIOR", "sub_agency1": "National Park Service", "dep_doc": "[NPS-WASO-NAGPRA-NPS0027609, PPWOCRADN0-PCU00RP14.R50000]", "subject": "Notice of Inventory Completion: U.S. Department of the Interior, National Park Service, Petrified Forest National Park, Petrified Forest, AZ", "agency2": "National Park Service, Interior.", "action": "Notice.", "summary": "The U.S. Department of the Interior, National Park Service, Petrified Forest National Park has completed an inventory of human remains, in consultation with the appropriate Indian Tribes or Native Hawaiian organizations, and has determined that there is no cultural affiliation between the human remains and any present-day Indian Tribes or Native Hawaiian organizations. Representatives of any Indian Tribe or Native Hawaiian organization not identified in this notice that wish to request transfer of control of these human remains should submit a written request to Petrified Forest National Park. If no additional requestors come forward, transfer of control of the human remains to the Indian Tribes or Native Hawaiian organizations stated in this notice may proceed.", "dates": "Representatives of any Indian Tribe or Native Hawaiian organization not identified in this notice that wish to request transfer of control of these human remains should submit a written request with information in support of the request to Petrified Forest National Park at the address in this notice by May 29, 2019.", "addresses": "Brad Traver, Superintendent, Petrified Forest National Park, 1 Park Road, P.O. Box 2217, Petrified Forest, AZ 86028, telephone (928) 524-6228 Ext. 225, email brad_traver@nps.gov.\\n          ", "signature_dated": "Dated: April 2, 2019.", "signature_name": "Melanie O\\'Brien,", "signature_title": "Manager, National NAGPRA Program. ", "fr_doc": "[FR Doc. 2019-08594 Filed 4-26-19; 8:45 am]", "billing_code": " BILLING CODE 4312-52-P", "supp_info": "SUPPLEMENTARY INFORMATION: \n Notice is here given in accordance with the Native American Graves Protection and Repatriation Act (NAGPRA), 25 U.S.C. 3003, of the completion of an inventory of human remains under the control of the U.S. Department of the Interior, National Park Service, Petrified Forest National Park, Petrified Forest, AZ, and in the physical custody of the Museum of Northern Arizona in Flagstaff, AZ. The human remains were removed from Petrified Forest National Park, AZ. \n This notice is published as part of the National Park Service\\'s administrative responsibilities under NAGPRA, 25 U.S.C. 3003(d)(3) and 43 CFR 10.11(d). The determinations in this notice are the sole responsibility of the Superintendent, Petrified Forest National Park. \n Consultation \n A detailed assessment of the human remains was made by Petrified Forest National Park professional staff in consultation with representatives of the Fort McDowell Yavapai Nation, Arizona; Hopi Tribe of Arizona; Hualapai Indian Tribe of the Hualapai Indian Reservation, Arizona; Kewa Pueblo, New Mexico (previously listed as the Pueblo of Santo Domingo); Navajo Nation, Arizona, New Mexico & Utah; Pueblo of Acoma, New Mexico; Pueblo of Santa Ana, New Mexico; and the Zuni Tribe of the Zuni Reservation, New Mexico (hereafter referred to as \\xe2\\x80\\x9cThe Consulted Tribes\\xe2\\x80\\x9d). \n The following tribes were invited to consult, but did not participate: Colorado River Indian Tribes of the Colorado Indian Reservation, Arizona and California; Fort Mojave Indian Tribe of Arizona, California & Nevada; Gila River Indian Community of the Gila River Indian Reservation, Arizona; Havasupai Tribe of the Havasupai Reservation, Arizona; Kaibab Band of Paiute Indians of the Kaibab Indian Reservation, Arizona; Las Vegas Tribe of Paiute Indians of the Las Vegas Indian Colony, Nevada; Moapa Band of the Paiute Indians of the Moapa River Indian Reservation, Nevada; Ohkay Owingeh, New Mexico (previously listed as the Pueblo of San Juan); Paiute Indian Tribe of Utah (Cedar Band of Paiutes, Kanosh Band of Paiutes, Koosharem Band of Paiutes, Indian Peaks Band of Paiutes, and Shivwits Band of Paiutes (formerly Paiute Indian Tribe of Utah (Cedar City Band of Paiutes, Kanosh Band of Paiutes, Koosharem Band of Paiutes, Indian Peaks Band of Paiutes, and Shivwits Band of Paiutes)); Pascua Yaqui Tribe of Arizona; Pueblo of Cochiti, New Mexico; Pueblo of Isleta, New Mexico; Pueblo of Jemez, New Mexico; Pueblo of Laguna, New Mexico; Pueblo of Nambe, New Mexico; Pueblo of Picuris, New Mexico; Pueblo of Pojoaque, New Mexico; Pueblo of San Felipe, New Mexico; Pueblo of San Ildefonso, New Mexico; Pueblo of Sandia, New Mexico; Pueblo of Santa Clara, New Mexico; Pueblo of Taos, New Mexico; Pueblo of Tesuque, New Mexico; Pueblo of Zia, New Mexico; San Carlos Apache Tribe of the San Carlos Reservation, Arizona; San Juan Southern Paiute Tribe of Arizona; Tohono O\\'odham Nation of Arizona; Tonto Apache Tribe of Arizona; and the Yavapai-Apache Nation of the Camp Verde Indian Reservation, Arizona (hereafter referred to as \\xe2\\x80\\x9cThe Invited Tribes\\xe2\\x80\\x9d). \n History and Description of the Remains \n On an unknown date, human remains representing, at minimum, one individual were removed from an unknown site likely within the boundaries of Petrified Forest National Park. No known individuals were identified. No associated funerary objects are present. \n Determinations Made by Petrified Forest National Park \n Officials of Petrified Forest National Park have determined that: \n \\xe2\\x80\\xa2 Pursuant to 25 U.S.C. 3001(9), the human remains described in this notice are Native American based on their osteological characteristics, as determined by James T. Watson from Arizona State University in August of 2010. \n \\xe2\\x80\\xa2 Pursuant to 25 U.S.C. 3001(9), the human remains described in this notice represent the physical remains of one individual of Native American ancestry. \n \\xe2\\x80\\xa2 Pursuant to 25 U.S.C. 3001(2), a relationship of shared group identity cannot be reasonably traced between the Native American human remains and any present-day Indian Tribe. \n \\xe2\\x80\\xa2 According to final judgments of the Indian Claims Commission or the Court of Federal Claims, the land from which the Native American human remains were removed is the aboriginal land of the Navajo Nation, Arizona, New Mexico & Utah and the Zuni Tribe of the Zuni Reservation, New Mexico. \n \\xe2\\x80\\xa2 Pursuant to 43 CFR 10.11(c)(1), the disposition of the human remains may be to the Navajo Nation, Arizona, New Mexico & Utah and the Zuni Tribe of the Zuni Reservation, New Mexico. \n Additional Requestors and Disposition \n Representatives of any Indian Tribe or Native Hawaiian organization not identified in this notice that wish to request transfer of control of these human remains should submit a written request with information in support of the request to Brad Traver, Superintendent, Petrified Forest National Park, P.O. Box 2217, Petrified Forest, AZ 86028, telephone (928) 524-6228 Ext. 225, email Brad_Traver@nps.gov, by May 29, 2019. After that date, if no additional requestors have come forward, transfer of control of the human remains to the Navajo Nation, Arizona, New Mexico & Utah and the Zuni Tribe of the Zuni Reservation, New Mexico may proceed. \n Petrified Forest National Park is responsible for notifying The Consulted Tribes and The Invited Tribes that this notice has been published. \n ", "consultation": "A detailed assessment of the human remains was made by Petrified Forest National Park professional staff in consultation with representatives of the Fort McDowell Yavapai Nation, Arizona; Hopi Tribe of Arizona; Hualapai Indian Tribe of the Hualapai Indian Reservation, Arizona; Kewa Pueblo, New Mexico (previously listed as the Pueblo of Santo Domingo); Navajo Nation, Arizona, New Mexico & Utah; Pueblo of Acoma, New Mexico; Pueblo of Santa Ana, New Mexico; and the Zuni Tribe of the Zuni Reservation, New Mexico (hereafter referred to as \\xe2\\x80\\x9cThe Consulted Tribes\\xe2\\x80\\x9d). \n The following tribes were invited to consult, but did not participate: Colorado River Indian Tribes of the Colorado Indian Reservation, Arizona and California; Fort Mojave Indian Tribe of Arizona, California & Nevada; Gila River Indian Community of the Gila River Indian Reservation, Arizona; Havasupai Tribe of the Havasupai Reservation, Arizona; Kaibab Band of Paiute Indians of the Kaibab Indian Reservation, Arizona; Las Vegas Tribe of Paiute Indians of the Las Vegas Indian Colony, Nevada; Moapa Band of the Paiute Indians of the Moapa River Indian Reservation, Nevada; Ohkay Owingeh, New Mexico (previously listed as the Pueblo of San Juan); Paiute Indian Tribe of Utah (Cedar Band of Paiutes, Kanosh Band of Paiutes, Koosharem Band of Paiutes, Indian Peaks Band of Paiutes, and Shivwits Band of Paiutes (formerly Paiute Indian Tribe of Utah (Cedar City Band of Paiutes, Kanosh Band of Paiutes, Koosharem Band of Paiutes, Indian Peaks Band of Paiutes, and Shivwits Band of Paiutes)); Pascua Yaqui Tribe of Arizona; Pueblo of Cochiti, New Mexico; Pueblo of Isleta, New Mexico; Pueblo of Jemez, New Mexico; Pueblo of Laguna, New Mexico; Pueblo of Nambe, New Mexico; Pueblo of Picuris, New Mexico; Pueblo of Pojoaque, New Mexico; Pueblo of San Felipe, New Mexico; Pueblo of San Ildefonso, New Mexico; Pueblo of Sandia, New Mexico; Pueblo of Santa Clara, New Mexico; Pueblo of Taos, New Mexico; Pueblo of Tesuque, New Mexico; Pueblo of Zia, New Mexico; San Carlos Apache Tribe of the San Carlos Reservation, Arizona; San Juan Southern Paiute Tribe of Arizona; Tohono O\\'odham Nation of Arizona; Tonto Apache Tribe of Arizona; and the Yavapai-Apache Nation of the Camp Verde Indian Reservation, Arizona (hereafter referred to as \\xe2\\x80\\x9cThe Invited Tribes\\xe2\\x80\\x9d). \n ", "h_d_r": "On an unknown date, human remains representing, at minimum, one individual were removed from an unknown site likely within the boundaries of Petrified Forest National Park. No known individuals were identified. No associated funerary objects are present. \n ", "h_d_ci": "Null", "determinations": "Determinations Made by Petrified Forest National Park \n Officials of Petrified Forest National Park have determined that: \n \\xe2\\x80\\xa2 Pursuant to 25 U.S.C. 3001(9), the human remains described in this notice are Native American based on their osteological characteristics, as determined by James T. Watson from Arizona State University in August of 2010. \n \\xe2\\x80\\xa2 Pursuant to 25 U.S.C. 3001(9), the human remains described in this notice represent the physical remains of one individual of Native American ancestry. \n \\xe2\\x80\\xa2 Pursuant to 25 U.S.C. 3001(2), a relationship of shared group identity cannot be reasonably traced between the Native American human remains and any present-day Indian Tribe. \n \\xe2\\x80\\xa2 According to final judgments of the Indian Claims Commission or the Court of Federal Claims, the land from which the Native American human remains were removed is the aboriginal land of the Navajo Nation, Arizona, New Mexico & Utah and the Zuni Tribe of the Zuni Reservation, New Mexico. \n \\xe2\\x80\\xa2 Pursuant to 43 CFR 10.11(c)(1), the disposition of the human remains may be to the Navajo Nation, Arizona, New Mexico & Utah and the Zuni Tribe of the Zuni Reservation, New Mexico. \n ", "a_r_d": "Representatives of any Indian Tribe or Native Hawaiian organization not identified in this notice that wish to request transfer of control of these human remains should submit a written request with information in support of the request to Brad Traver, Superintendent, Petrified Forest National Park, P.O. Box 2217, Petrified Forest, AZ 86028, telephone (928) 524-6228 Ext. 225, email Brad_Traver@nps.gov, by May 29, 2019. After that date, if no additional requestors have come forward, transfer of control of the human remains to the Navajo Nation, Arizona, New Mexico & Utah and the Zuni Tribe of the Zuni Reservation, New Mexico may proceed. \n Petrified Forest National Park is responsible for notifying The Consulted Tribes and The Invited Tribes that this notice has been published. \n "}