{"index": "I_1139", "messy_full": "\\n      \\n        DEPARTMENT OF THE INTERIOR\\n        National Park Service\\n        [2253-665]\\n        Notice of Inventory Completion: University of Colorado Museum, Boulder, CO\\n        \\n          AGENCY:\\n          National Park Service, Interior.\\n        \\n        \\n          ACTION:\\n          Notice.\\n        \\n        \\n          SUMMARY:\\n          The University of Colorado Museum has completed an inventory of human remains, in consultation with the appropriate Indian tribes, and has determined that there is no cultural affiliation between the human remains and any present-day Indian tribe. Representatives of any Indian tribe that believes itself to be culturally affiliated with the human remains may contact the University of Colorado Museum. Disposition of the human remains to the Indian tribes stated below may occur if no additional requestors come forward.\\n        \\n        \\n          DATES:\\n          Representatives of any Indian tribe that believes it has a cultural affiliation with the human remains should contact the University of Colorado Museum at the address below by August 22, 2011.\\n        \\n        \\n          ADDRESSES:\\n          Stephen Lekson, Curator of Anthropology, University of Colorado Museum, in care of Jan Bernstein, NAGPRA Consultant, Bernstein & Associates, 1041 Lafayette St., Denver, CO 80218, telephone (303) 894-0648.\\n        \\n      \\n      \\n        SUPPLEMENTARY INFORMATION:\\n        Notice is here given in accordance with the Native American Graves Protection and Repatriation Act (NAGPRA), 25 U.S.C. 3003, of the completion of an inventory of human remains in the possession of the University of Colorado Museum, Boulder, CO. The human remains were removed from near Laguna, Cibola County, NM.\\n        This notice is published as part of the National Park Service\\'s administrative responsibilities under NAGPRA, 25 U.S.C. 3003(d)(3) and 43 CFR 10.11(d). The determinations in this notice are the sole responsibility of the museum, institution, or Federal agency that has control of the Native American human remains. The National Park Service is not responsible for the determinations in this notice.\\n        Consultation\\n\\n        A detailed assessment of the human remains was made by the University of Colorado Museum professional staff in consultation with representatives of the Fort Sill Apache Tribe of Oklahoma; Hopi Tribe of Arizona; Mescalero Apache Tribe of the Mescalero Reservation, New Mexico; Navajo Nation, Arizona, New Mexico & Utah; Pueblo of Acoma, New Mexico; Pueblo of Cochiti, New Mexico; Pueblo of Isleta, New Mexico; Pueblo of Jemez, New Mexico; Pueblo of Laguna, New Mexico; Pueblo of San Ildefonso, New Mexico; Pueblo of Zia, New Mexico; San Carlos Apache Tribe of the San Carlos Reservation, Arizona; Tonto Apache Tribe of Arizona; White Mountain Apache Tribe of the Fort Apache Reservation, Arizona; and Zuni Tribe of the Zuni Reservation, New Mexico. Information was provided to the Kewa Pueblo, New Mexico; Ohkay Owingeh, New Mexico; Pueblo of Nambe, New Mexico; Pueblo of Picuris, New Mexico; Pueblo of Pojoaque, New Mexico; Pueblo of San Felipe, New Mexico; Pueblo of Sandia, New Mexico; Pueblo of Santa Ana, New Mexico; Pueblo of Santa Clara, New Mexico; Pueblo of Taos, New Mexico; Pueblo of Tesuque, New Mexico; and Ysleta Del Sur Pueblo of Texas.\\n        The Fort Sill Apache Tribe of Oklahoma; Mescalero Apache Tribe of the Mescalero Reservation, New Mexico; Navajo Nation, Arizona, New Mexico & Utah; Pueblo of Acoma, New Mexico; Pueblo of Laguna, New Mexico; San Carlos Apache Tribe of the San Carlos Reservation, Arizona; Tonto Apache Tribe of Arizona; and White Mountain Apache Tribe of the Fort Apache Reservation, Arizona (hereinafter the \\xe2\\x80\\x9cAboriginal Land Tribes\\xe2\\x80\\x9d), do not object to the disposition of the human remains described in this notice to the Pueblo of Acoma, New Mexico, and Pueblo of Laguna, New Mexico.\\n        History and description of the remains\\n        On an unknown date, human remains representing a minimum of one individual were removed from Maxson site number 121, a rock fall near Laguna, Cibola County, NM, by Asa Maxson, an avocational archeologist. In 1982, Mr. Maxson donated his large archeological collection to the museum. On February 6, 2008, during an inventory, the human remains were found in the museum. No known individual was identified. No associated funerary objects are present.\\n        Determinations Made by the University of Colorado Museum\\n        Officials of the University of Colorado Museum have determined that:\\n        \\xe2\\x80\\xa2 Based on the archeological context and the collecting history of Mr. Maxson, the human remains are Native American.\\n        \\xe2\\x80\\xa2 Pursuant to 25 U.S.C. 3001(2), a relationship of shared group identity cannot be reasonably traced between the Native American human remains and any present-day Indian tribe.\\n        \\xe2\\x80\\xa2 According to final judgments of the Indian Claims Commission, the land from which the Native American human remains were removed is the aboriginal land of the Navajo Nation, Arizona, New Mexico & Utah; Pueblo of Acoma, New Mexico; and Pueblo of Laguna, New Mexico.\\n        \\xe2\\x80\\xa2 Multiple lines of evidence, including treaties, Acts of Congress, and Executive Orders, indicate that the land from which the Native American human remains were removed is the aboriginal land of the Navajo Nation, Arizona, New Mexico & Utah; Pueblo of Acoma, New Mexico; Pueblo of Laguna, New Mexico; San Carlos Apache Tribe of the San Carlos Reservation, Arizona; Tonto Apache Tribe of Arizona; and White Mountain Apache Tribe of the Fort Apache Reservation, Arizona.\\n        \\xe2\\x80\\xa2 Other credible lines of evidence indicate that the land from which the Native American human remains were removed is the aboriginal land of the Chiricahua Apache. The Chiricahua Apache are Federally-recognized as the Fort Sill Apache Tribe of Oklahoma and Mescalero Apache Tribe of the Mescalero Reservation, New Mexico.\\n        \\xe2\\x80\\xa2 Pursuant to 25 U.S.C. 3001(9), the human remains described in this notice represent the physical remains of one individual of Native American ancestry.\\n        \\xe2\\x80\\xa2 Pursuant to 43 CFR 10.11(c)(1), the disposition of the human remains is to the Pueblo of Acoma, New Mexico, and Pueblo of Laguna, New Mexico.\\n        Additional Requestors and Disposition\\n        Representatives of any Indian tribe that believes itself to be culturally affiliated with the human remains or any other Indian tribe that believes it satisfies the criteria in 43 CFR 10.11(c)(1) should contact Steve Lekson, Curator of Anthropology, University of Colorado Museum, in care of Jan Bernstein, NAGPRA Consultant, Bernstein & Associates, 1041 Lafayette St., Denver, CO 80218, telephone (303) 894-0648, before August 22, 2011. Disposition of the human remains to the Pueblo of Acoma, New Mexico, and Pueblo of Laguna, New Mexico, may proceed after that date if no additional requestors come forward.\\n        The University of Colorado Museum is responsible for notifying the Aboriginal Land Tribes that this notice has been published.\\n        \\n          Dated: July 14, 2011.\\n          Sangita Chari,\\n          Acting Manager, National NAGPRA Program. \\n        \\n      \\n      [FR Doc. 2011-18354 Filed 7-20-11; 8:45 am]\\n      BILLING CODE 4312-50-P\\n    ", "agency1": "DEPARTMENT OF THE INTERIOR", "sub_agency1": "National Park Service", "dep_doc": "[2253-665]", "subject": "Notice of Inventory Completion: University of Colorado Museum, Boulder, CO", "agency2": "National Park Service, Interior.", "action": "Notice.", "summary": "The University of Colorado Museum has completed an inventory of human remains, in consultation with the appropriate Indian tribes, and has determined that there is no cultural affiliation between the human remains and any present-day Indian tribe. Representatives of any Indian tribe that believes itself to be culturally affiliated with the human remains may contact the University of Colorado Museum. Disposition of the human remains to the Indian tribes stated below may occur if no additional requestors come forward.", "dates": "Representatives of any Indian tribe that believes it has a cultural affiliation with the human remains should contact the University of Colorado Museum at the address below by August 22, 2011.", "addresses": "Stephen Lekson, Curator of Anthropology, University of Colorado Museum, in care of Jan Bernstein, NAGPRA Consultant, Bernstein & Associates, 1041 Lafayette St., Denver, CO 80218, telephone (303) 894-0648.", "signature_dated": "Dated: July 14, 2011.", "signature_name": "Sangita Chari,", "signature_title": "Acting Manager, National NAGPRA Program. ", "fr_doc": "[FR Doc. 2011-18354 Filed 7-20-11; 8:45 am]", "billing_code": "BILLING CODE 4312-50-P", "supp_info": "SUPPLEMENTARY INFORMATION: \n Notice is here given in accordance with the Native American Graves Protection and Repatriation Act (NAGPRA), 25 U.S.C. 3003, of the completion of an inventory of human remains in the possession of the University of Colorado Museum, Boulder, CO. The human remains were removed from near Laguna, Cibola County, NM. \n This notice is published as part of the National Park Service\\'s administrative responsibilities under NAGPRA, 25 U.S.C. 3003(d)(3) and 43 CFR 10.11(d). The determinations in this notice are the sole responsibility of the museum, institution, or Federal agency that has control of the Native American human remains. The National Park Service is not responsible for the determinations in this notice. \n Consultation \n A detailed assessment of the human remains was made by the University of Colorado Museum professional staff in consultation with representatives of the Fort Sill Apache Tribe of Oklahoma; Hopi Tribe of Arizona; Mescalero Apache Tribe of the Mescalero Reservation, New Mexico; Navajo Nation, Arizona, New Mexico & Utah; Pueblo of Acoma, New Mexico; Pueblo of Cochiti, New Mexico; Pueblo of Isleta, New Mexico; Pueblo of Jemez, New Mexico; Pueblo of Laguna, New Mexico; Pueblo of San Ildefonso, New Mexico; Pueblo of Zia, New Mexico; San Carlos Apache Tribe of the San Carlos Reservation, Arizona; Tonto Apache Tribe of Arizona; White Mountain Apache Tribe of the Fort Apache Reservation, Arizona; and Zuni Tribe of the Zuni Reservation, New Mexico. Information was provided to the Kewa Pueblo, New Mexico; Ohkay Owingeh, New Mexico; Pueblo of Nambe, New Mexico; Pueblo of Picuris, New Mexico; Pueblo of Pojoaque, New Mexico; Pueblo of San Felipe, New Mexico; Pueblo of Sandia, New Mexico; Pueblo of Santa Ana, New Mexico; Pueblo of Santa Clara, New Mexico; Pueblo of Taos, New Mexico; Pueblo of Tesuque, New Mexico; and Ysleta Del Sur Pueblo of Texas. \n The Fort Sill Apache Tribe of Oklahoma; Mescalero Apache Tribe of the Mescalero Reservation, New Mexico; Navajo Nation, Arizona, New Mexico & Utah; Pueblo of Acoma, New Mexico; Pueblo of Laguna, New Mexico; San Carlos Apache Tribe of the San Carlos Reservation, Arizona; Tonto Apache Tribe of Arizona; and White Mountain Apache Tribe of the Fort Apache Reservation, Arizona (hereinafter the \\xe2\\x80\\x9cAboriginal Land Tribes\\xe2\\x80\\x9d), do not object to the disposition of the human remains described in this notice to the Pueblo of Acoma, New Mexico, and Pueblo of Laguna, New Mexico. \n History and description of the remains \n On an unknown date, human remains representing a minimum of one individual were removed from Maxson site number 121, a rock fall near Laguna, Cibola County, NM, by Asa Maxson, an avocational archeologist. In 1982, Mr. Maxson donated his large archeological collection to the museum. On February 6, 2008, during an inventory, the human remains were found in the museum. No known individual was identified. No associated funerary objects are present. \n Determinations Made by the University of Colorado Museum \n Officials of the University of Colorado Museum have determined that: \n \\xe2\\x80\\xa2 Based on the archeological context and the collecting history of Mr. Maxson, the human remains are Native American. \n \\xe2\\x80\\xa2 Pursuant to 25 U.S.C. 3001(2), a relationship of shared group identity cannot be reasonably traced between the Native American human remains and any present-day Indian tribe. \n \\xe2\\x80\\xa2 According to final judgments of the Indian Claims Commission, the land from which the Native American human remains were removed is the aboriginal land of the Navajo Nation, Arizona, New Mexico & Utah; Pueblo of Acoma, New Mexico; and Pueblo of Laguna, New Mexico. \n \\xe2\\x80\\xa2 Multiple lines of evidence, including treaties, Acts of Congress, and Executive Orders, indicate that the land from which the Native American human remains were removed is the aboriginal land of the Navajo Nation, Arizona, New Mexico & Utah; Pueblo of Acoma, New Mexico; Pueblo of Laguna, New Mexico; San Carlos Apache Tribe of the San Carlos Reservation, Arizona; Tonto Apache Tribe of Arizona; and White Mountain Apache Tribe of the Fort Apache Reservation, Arizona. \n \\xe2\\x80\\xa2 Other credible lines of evidence indicate that the land from which the Native American human remains were removed is the aboriginal land of the Chiricahua Apache. The Chiricahua Apache are Federally-recognized as the Fort Sill Apache Tribe of Oklahoma and Mescalero Apache Tribe of the Mescalero Reservation, New Mexico. \n \\xe2\\x80\\xa2 Pursuant to 25 U.S.C. 3001(9), the human remains described in this notice represent the physical remains of one individual of Native American ancestry. \n \\xe2\\x80\\xa2 Pursuant to 43 CFR 10.11(c)(1), the disposition of the human remains is to the Pueblo of Acoma, New Mexico, and Pueblo of Laguna, New Mexico. \n Additional Requestors and Disposition \n Representatives of any Indian tribe that believes itself to be culturally affiliated with the human remains or any other Indian tribe that believes it satisfies the criteria in 43 CFR 10.11(c)(1) should contact Steve Lekson, Curator of Anthropology, University of Colorado Museum, in care of Jan Bernstein, NAGPRA Consultant, Bernstein & Associates, 1041 Lafayette St., Denver, CO 80218, telephone (303) 894-0648, before August 22, 2011. Disposition of the human remains to the Pueblo of Acoma, New Mexico, and Pueblo of Laguna, New Mexico, may proceed after that date if no additional requestors come forward. \n The University of Colorado Museum is responsible for notifying the Aboriginal Land Tribes that this notice has been published. \n ", "consultation": "A detailed assessment of the human remains was made by the University of Colorado Museum professional staff in consultation with representatives of the Fort Sill Apache Tribe of Oklahoma; Hopi Tribe of Arizona; Mescalero Apache Tribe of the Mescalero Reservation, New Mexico; Navajo Nation, Arizona, New Mexico & Utah; Pueblo of Acoma, New Mexico; Pueblo of Cochiti, New Mexico; Pueblo of Isleta, New Mexico; Pueblo of Jemez, New Mexico; Pueblo of Laguna, New Mexico; Pueblo of San Ildefonso, New Mexico; Pueblo of Zia, New Mexico; San Carlos Apache Tribe of the San Carlos Reservation, Arizona; Tonto Apache Tribe of Arizona; White Mountain Apache Tribe of the Fort Apache Reservation, Arizona; and Zuni Tribe of the Zuni Reservation, New Mexico. Information was provided to the Kewa Pueblo, New Mexico; Ohkay Owingeh, New Mexico; Pueblo of Nambe, New Mexico; Pueblo of Picuris, New Mexico; Pueblo of Pojoaque, New Mexico; Pueblo of San Felipe, New Mexico; Pueblo of Sandia, New Mexico; Pueblo of Santa Ana, New Mexico; Pueblo of Santa Clara, New Mexico; Pueblo of Taos, New Mexico; Pueblo of Tesuque, New Mexico; and Ysleta Del Sur Pueblo of Texas. \n The Fort Sill Apache Tribe of Oklahoma; Mescalero Apache Tribe of the Mescalero Reservation, New Mexico; Navajo Nation, Arizona, New Mexico & Utah; Pueblo of Acoma, New Mexico; Pueblo of Laguna, New Mexico; San Carlos Apache Tribe of the San Carlos Reservation, Arizona; Tonto Apache Tribe of Arizona; and White Mountain Apache Tribe of the Fort Apache Reservation, Arizona (hereinafter the \\xe2\\x80\\x9cAboriginal Land Tribes\\xe2\\x80\\x9d), do not object to the disposition of the human remains described in this notice to the Pueblo of Acoma, New Mexico, and Pueblo of Laguna, New Mexico. \n ", "h_d_r": "On an unknown date, human remains representing a minimum of one individual were removed from Maxson site number 121, a rock fall near Laguna, Cibola County, NM, by Asa Maxson, an avocational archeologist. In 1982, Mr. Maxson donated his large archeological collection to the museum. On February 6, 2008, during an inventory, the human remains were found in the museum. No known individual was identified. No associated funerary objects are present. \n ", "h_d_ci": "Null", "determinations": "Determinations Made by the University of Colorado Museum \n Officials of the University of Colorado Museum have determined that: \n \\xe2\\x80\\xa2 Based on the archeological context and the collecting history of Mr. Maxson, the human remains are Native American. \n \\xe2\\x80\\xa2 Pursuant to 25 U.S.C. 3001(2), a relationship of shared group identity cannot be reasonably traced between the Native American human remains and any present-day Indian tribe. \n \\xe2\\x80\\xa2 According to final judgments of the Indian Claims Commission, the land from which the Native American human remains were removed is the aboriginal land of the Navajo Nation, Arizona, New Mexico & Utah; Pueblo of Acoma, New Mexico; and Pueblo of Laguna, New Mexico. \n \\xe2\\x80\\xa2 Multiple lines of evidence, including treaties, Acts of Congress, and Executive Orders, indicate that the land from which the Native American human remains were removed is the aboriginal land of the Navajo Nation, Arizona, New Mexico & Utah; Pueblo of Acoma, New Mexico; Pueblo of Laguna, New Mexico; San Carlos Apache Tribe of the San Carlos Reservation, Arizona; Tonto Apache Tribe of Arizona; and White Mountain Apache Tribe of the Fort Apache Reservation, Arizona. \n \\xe2\\x80\\xa2 Other credible lines of evidence indicate that the land from which the Native American human remains were removed is the aboriginal land of the Chiricahua Apache. The Chiricahua Apache are Federally-recognized as the Fort Sill Apache Tribe of Oklahoma and Mescalero Apache Tribe of the Mescalero Reservation, New Mexico. \n \\xe2\\x80\\xa2 Pursuant to 25 U.S.C. 3001(9), the human remains described in this notice represent the physical remains of one individual of Native American ancestry. \n \\xe2\\x80\\xa2 Pursuant to 43 CFR 10.11(c)(1), the disposition of the human remains is to the Pueblo of Acoma, New Mexico, and Pueblo of Laguna, New Mexico. \n ", "a_r_d": "Representatives of any Indian tribe that believes itself to be culturally affiliated with the human remains or any other Indian tribe that believes it satisfies the criteria in 43 CFR 10.11(c)(1) should contact Steve Lekson, Curator of Anthropology, University of Colorado Museum, in care of Jan Bernstein, NAGPRA Consultant, Bernstein & Associates, 1041 Lafayette St., Denver, CO 80218, telephone (303) 894-0648, before August 22, 2011. Disposition of the human remains to the Pueblo of Acoma, New Mexico, and Pueblo of Laguna, New Mexico, may proceed after that date if no additional requestors come forward. \n The University of Colorado Museum is responsible for notifying the Aboriginal Land Tribes that this notice has been published. \n "}