{"index": "I_1189", "messy_full": "\\n      \\n        DEPARTMENT OF THE INTERIOR\\n        National Park Service\\n        [2253-665]\\n        Notice of Inventory Completion: Denver Museum of Nature & Science, Denver, CO\\n        \\n          AGENCY:\\n          National Park Service, Interior.\\n        \\n        \\n          ACTION:\\n          Notice.\\n        \\n        \\n          SUMMARY:\\n          The Denver Museum of Nature & Science has completed an inventory of human remains, in consultation with the appropriate Indian Tribes, and has determined that there is no cultural affiliation between the remains and any present-day Tribe. Representatives of any Indian Tribe that believes itself to be culturally affiliated with the human remains may contact the museum. Disposition of the human remains to the Tribes stated below may occur if no additional requestors come forward.\\n        \\n        \\n          DATES:\\n          Representatives of any Indian Tribe that believes it has a cultural affiliation with the human remains should contact the museum at the address below by March 21, 2011.\\n        \\n        \\n          ADDRESSES:\\n          Any Tribe that believes it has a cultural affiliation with the human remains should contact Dr. Chip Colwell-Chanthaphonh, Denver Museum of Nature & Science, 2001 Colorado Blvd., Denver, CO 80205, telephone (303) 370-6378.\\n        \\n      \\n      \\n        SUPPLEMENTARY INFORMATION:\\n        Notice is here given in accordance with the Native American Graves Protection and Repatriation Act (NAGPRA), 25 U.S.C. 3003, of the completion of an inventory of human remains in the possession of the Denver Museum of Nature & Science, Denver, CO. The human remains were removed from an unknown location in the Great Plains.\\n        This notice is published as part of the National Park Service\\'s administrative responsibilities under NAGPRA, 25 U.S.C. 3003(d)(3) and 43 CFR 10.11(d). The determinations in this notice are the sole responsibility of the museum, institution, or Federal agency that has control of the Native American human remains. The National Park Service is not responsible for the determinations in this notice.\\n        Consultation\\n        A detailed assessment of the human remains was made by the Denver Museum of Nature & Science professional staff in consultation with representatives of the Absentee-Shawnee Tribe of Indians of Oklahoma; Apache Tribe of Oklahoma; Arapahoe Tribe of the Wind River Reservation, Wyoming; Assiniboine and Sioux Tribes of the Fort Peck Indian Reservation, Montana; Bad River Band of the Lake Superior Tribe of Chippewa Indians of the Bad River Reservation, Wisconsin; Bay Mills Indian Community, Michigan; Big Pine Band of Owens Valley Paiute Shoshone Indians of the Big Pine Reservation, California; Blackfeet Tribe of the Blackfeet Indian Reservation of Montana; Bois Forte Band (Nett Lake) of the Minnesota Chippewa Tribe, Minnesota; Caddo Nation of Oklahoma; Cherokee Nation, Oklahoma; Cheyenne and Arapaho Tribes, Oklahoma; Cheyenne River Sioux Tribe of the Cheyenne River Reservation, South Dakota; Chickasaw Nation, Oklahoma; Chippewa-Cree Indians of the Rocky Boy\\'s Reservation, Montana; Choctaw Nation of Oklahoma; Citizen Potawatomi Nation, Oklahoma; Comanche Nation, Oklahoma; Crow Creek Sioux Tribe of the Crow Creek Reservation, South Dakota; Crow Tribe of Montana; Death Valley Timbi-Sha Shoshone Band of California; Delaware Nation, Oklahoma; Duckwater Shoshone Tribe of the Duckwater Reservation, Nevada; Eastern Band of Cherokee Indians of North Carolina; Ely Shoshone Tribe of Nevada; Flandreau Santee Sioux Tribe of South Dakota; Fond du Lac Band of the Minnesota Chippewa Tribe, Minnesota; Forest County Potawatomi Community, Wisconsin; Fort Belknap Indian Community of the Fort Belknap Reservation of Montana; Fort McDermitt Paiute and Shoshone Tribes of the Fort McDermitt Indian Reservation, Nevada and Oregon; Fort Sill Apache Tribe of Oklahoma; Grand Portage Band of the Minnesota Chippewa Tribe, Minnesota; Grand Traverse Band of Ottawa and Chippewa Indians, Michigan; Hannahville Indian Community, Michigan; Ho-Chunk Nation of Wisconsin; Iowa Tribe of Kansas and Nebraska; Iowa Tribe of Oklahoma; Jena Band of Choctaw Indians, Louisiana; Jicarilla Apache Nation, New Mexico; Kaw Nation, Oklahoma; Keweenaw Bay Indian Community, Michigan; Kickapoo Traditional Tribe of Texas; Kickapoo Tribe of Indians of the Kickapoo Reservation in Kansas; Kickapoo Tribe of Oklahoma; Kiowa Indian Tribe of Oklahoma; Lac Courte Oreilles Band of Lake Superior Chippewa Indians of Wisconsin; Lac du Flambeau Band of Lake Superior Chippewa Indians of the Lac du Flambeau Reservation of Wisconsin; Lac Vieux Desert Band of Lake Superior Chippewa Indians, Michigan; Leech Lake Band of the Minnesota Chippewa Tribe, Minnesota; Lower Brule Sioux Tribe of the Lower Brule Reservation, South Dakota; Lower Sioux Indian Community in the State of Minnesota; Match-e-be-nash-she-wish Band of Pottawatomi Indians of Michigan; Menominee Indian Tribe of Wisconsin; Mescalero Apache Tribe of the Mescalero Reservation, New Mexico; Miami Tribe of Oklahoma; Mille Lacs Band of the Minnesota Chippewa Tribe, Minnesota; Minnesota Chippewa Tribe, Minnesota; Mississippi Band of Choctaw Indians, Mississippi; Muscogee (Creek) Nation, Oklahoma; Nez Perce Tribe, Idaho; Northern Cheyenne Tribe of the Northern Cheyenne Indian Reservation, Montana; Nottawaseppi Huron Band of the Potawatomi, Michigan; Oglala Sioux Tribe of the Pine Ridge Reservation, South Dakota; Ohkay Owingeh, New Mexico; Omaha Tribe of Nebraska; Osage Nation, Oklahoma; Otoe-Missouria Tribe of Indians, Oklahoma; Ottawa Tribe of Oklahoma; Pawnee Nation of Oklahoma; Peoria Tribe of Indians of Oklahoma; Poarch Band of Creek Indians of Alabama; Pokagon Band of Potawatomi Indians, Michigan and Indiana; Ponca Tribe of Indians of Oklahoma; Ponca Tribe of Nebraska; Prairie Band of Potawatomi Nation, Kansas; Prairie Island Indian Community in the State of Minnesota; Pueblo of Cochiti, New Mexico; Pueblo of San Ildefonso, New Mexico; Pueblo of Santa Ana, New Mexico; Pueblo of Santa Clara, New Mexico; Quapaw Tribe of Indians, Oklahoma; Quechan Tribe of the Fort Yuma Indian Reservation, California & Arizona; Red Cliff Band of Lake Superior Chippewa Indians of Wisconsin; Red Lake Band of Chippewa Indians, Minnesota; Rosebud Sioux Tribe of the Rosebud Indian Reservation, South Dakota; Sac & Fox Nation of Missouri in Kansas and Nebraska; Sac & Fox Nation, Oklahoma; Sac & Fox Tribe of the Mississippi in Iowa; Saginaw Chippewa Indian Tribe of Michigan; San Carlos Apache Tribe of the San Carlos Reservation, Arizona; Santee Sioux Nation, Nebraska; Sault Ste. Marie Tribe of Chippewa Indians of Michigan; Seminole Nation of Oklahoma; Seminole Tribe of Florida (Dania, Big Cypress, Brighton, Hollywood & Tampa Reservations); Seneca Nation of New York; Seneca-Cayuga Tribe of Oklahoma; Shakopee Mdewakanton Sioux Community of Minnesota; Shawnee Tribe, Oklahoma; Shoshone Tribe of the Wind River Reservation, Wyoming; Sisseton-Wahpeton Oyate of the Lake Traverse Reservation, South Dakota; Sokaogon Chippewa Community, Wisconsin; Southern Ute Indian Tribe of the Southern Ute Reservation, Colorado; Spirit Lake Tribe, North Dakota; St. Croix Chippewa Indians of Wisconsin; Standing Rock Sioux Tribe of North & South Dakota; Te-Moak Tribe of Western Shoshone Indians of Nevada (Four constituent bands: Battle Mountain Band; Elko Band; South Fork Band and Wells Band); Three Affiliated Tribes of the Fort Berthold Reservation, North Dakota; Tonawanda Band of Seneca Indians of New York; Tonto Apache Tribe of Arizona; Turtle Mountain Band of Chippewa Indians of North Dakota; United Keetoowah Band of Cherokee Indians in Oklahoma; Upper Sioux Community, Minnesota; Ute Indian Tribe of the Uintah & Ouray Reservation, Utah; Ute Mountain Tribe of the Ute Mountain Reservation, Colorado, New Mexico & Utah; White Earth Band of the Minnesota Chippewa Tribe, Minnesota; White Mountain Apache Tribe of the Fort Apache Reservation, Arizona; Wichita and Affiliated Tribes (Wichita, Keechi, Waco & Tawakonie), Oklahoma; Winnebago Tribe of Nebraska; Wyandotte Nation, Oklahoma; Yankton Sioux Tribe of South Dakota; and the Zuni Tribe of the Zuni Reservation, New Mexico (hereinafter referred to as \\xe2\\x80\\x9cThe Tribes\\xe2\\x80\\x9d).\\n        History and Description of the Remains\\n\\n        In 1959, Francis and Mary Crane purchased human remains representing a minimum of one individual from Kohlberg\\'s Antiques and Indian Arts, in Denver, CO. In 1972, the human remains were donated by Mr. and Mrs. Crane and accessioned into the collections (AC.4224 (CUI 21)). The remains include a scalp lock with black hair, approximately 16 inches long, and one quarter of an inch wide. The upper end of the scalp lock is covered with sinew, yellow dyed deerskin, and tufts of red feather. No known individual was identified. No associated funerary objects are present.\\n        In 1956, Francis and Mary Crane purchased human remains representing a minimum of one individual from Kohlberg\\'s Antiques and Indian Arts. The remains were reportedly a part of the George A. Cuneo Collection of Southwestern and Plains Indian objects collected in the late 19th and early 20th centuries. In 1983, the human remains were donated by Mr. and Mrs. Crane and accessioned into the collections (AC.35D (CUI 23)). The remains include seven inches of black and grey hair and scalp with traces of red pigment and a row of perforations along one edge of it. No known individual was identified. No associated funerary objects are present.\\n        Determinations Made by the Denver Museum\\n        Officials of the Denver Museum of Nature & Science have determined that:\\n        \\xe2\\x80\\xa2 Based on non-destructive physical analysis and catalogue records, the human remains are Native American.\\n        \\xe2\\x80\\xa2 Pursuant to 25 U.S.C. 3001(2), a relationship of shared group identity cannot be reasonably traced between the Native American human remains and any present-day Indian Tribe.\\n        \\xe2\\x80\\xa2 According to final judgments of the Indian Claims Commission, the land from which the Native American human remains were removed is the aboriginal land of the Apache Tribe of Oklahoma; Arapahoe Tribe of the Wind River Reservation, Wyoming; Assiniboine and Sioux Tribes of the Fort Peck Indian Reservation, Montana; Big Pine Band of Owens Valley Paiute Shoshone Indians of the Big Pine Reservation, California; Blackfeet Tribe of the Blackfeet Indian Reservation of Montana; Caddo Nation of Oklahoma; Cheyenne and Arapaho Tribes, Oklahoma; Cheyenne River Sioux Tribe of the Cheyenne River Reservation, South Dakota; Citizen Potawatomi Nation, Oklahoma; Comanche Nation, Oklahoma; Crow Creek Sioux Tribe of the Crow Creek Reservation, South Dakota; Crow Tribe of Montana; Death Valley Timbi-Sha Shoshone Band of California; Duckwater Shoshone Tribe of the Duckwater Reservation, Nevada; Ely Shoshone Tribe of Nevada; Flandreau Santee Sioux Tribe of South Dakota; Forest County Potawatomi Community, Wisconsin; Fort McDermitt Paiute and Shoshone Tribes of the Fort McDermitt Indian Reservation, Nevada and Oregon; Fort Sill Apache Tribe of Oklahoma; Ho-Chunk Nation of Wisconsin; Iowa Tribe of Kansas and Nebraska; Iowa Tribe of Oklahoma; Jicarilla Apache Nation, New Mexico; Kickapoo Traditional Tribe of Texas; Kickapoo Tribe of Indians of the Kickapoo Reservation in Kansas; Kickapoo Tribe of Oklahoma; Kiowa Indian Tribe of Oklahoma; Lower Brule Sioux Tribe of the Lower Brule Reservation, South Dakota; Lower Sioux Indian Community in the State of Minnesota; Match-e-be-nash-she-wish Band of Pottawatomi Indians of Michigan; Mescalero Apache Tribe of the Mescalero Reservation, New Mexico; Nez Perce Tribe, Idaho; Northern Cheyenne Tribe of the Northern Cheyenne Indian Reservation, Montana; Nottawaseppi Huron Band of the Potawatomi, Michigan; Oglala Sioux Tribe of the Pine Ridge Reservation, South Dakota; Omaha Tribe of Nebraska; Osage Nation, Oklahoma; Otoe-Missouria Tribe of Indians, Oklahoma; Pawnee Nation of Oklahoma; Pokagon Band of Potawatomi Indians, Michigan and Indiana; Ponca Tribe of Indians of Oklahoma; Ponca Tribe of Nebraska; Prairie Band of Potawatomi Nation, Kansas; Prairie Island Indian Community in the State of Minnesota; Quapaw Tribe of Indians, Oklahoma; Rosebud Sioux Tribe of the Rosebud Indian Reservation, South Dakota; Sac & Fox Nation of Missouri in Kansas and Nebraska; Sac & Fox Nation, Oklahoma; Sac & Fox Tribe of the Mississippi in Iowa; San Carlos Apache Tribe of the San Carlos Reservation, Arizona; Santee Sioux Nation, Nebraska; Shakopee Mdewakanton Sioux Community of Minnesota; Sisseton-Wahpeton Oyate of the Lake Traverse Reservation, South Dakota; Southern Ute Indian Tribe of the Southern Ute Reservation, Colorado; Spirit Lake Tribe, North Dakota; Standing Rock Sioux Tribe of North & South Dakota; Tonto Apache Tribe of Arizona; Upper Sioux Community, Minnesota; Ute Indian Tribe of the Uintah & Ouray Reservation, Utah; Ute Mountain Tribe of the Ute Mountain Reservation, Colorado, New Mexico & Utah; White Mountain Apache Tribe of the Fort Apache Reservation, Arizona; Winnebago Tribe of Nebraska; and Yankton Sioux Tribe of South Dakota.\\n\\n        \\xe2\\x80\\xa2 Multiple lines of evidence, including treaties, Acts of Congress, and Executive Orders, indicate that the land from which the Native American human remains were removed is the aboriginal land of the Absentee-Shawnee Tribe of Indians of Oklahoma; Apache Tribe of Oklahoma; Arapahoe Tribe of the Wind River Reservation, Wyoming; Assiniboine and Sioux Tribes of the Fort Peck Indian Reservation, Montana; Bad River Band of the Lake Superior Tribe of Chippewa Indians of the Bad River Reservation, Wisconsin; Bay Mills Indian Community, Michigan; Big Pine Band of Owens Valley Paiute Shoshone Indians of the Big Pine Reservation, California; Blackfeet Tribe of the Blackfeet Indian Reservation of Montana; Bois Forte Band (Nett Lake) of the Minnesota Chippewa Tribe, Minnesota; Caddo Nation of Oklahoma; Cherokee Nation, Oklahoma; Cheyenne and Arapaho Tribes, Oklahoma; Cheyenne River Sioux Tribe of the Cheyenne River Reservation, South Dakota; Chickasaw Nation, Oklahoma; Chippewa-Cree Indians of the Rocky Boy\\'s Reservation, Montana; Choctaw Nation of Oklahoma; Citizen Potawatomi Nation, Oklahoma; Comanche Nation, Oklahoma; Crow Creek Sioux Tribe of the Crow Creek Reservation, South Dakota; Crow Tribe of Montana; Death Valley Timbi-Sha Shoshone Band of California; Delaware Nation, Oklahoma; Duckwater Shoshone Tribe of the Duckwater Reservation, Nevada; Eastern Band of Cherokee Indians of North Carolina; Ely Shoshone Tribe of Nevada; Flandreau Santee Sioux Tribe of South Dakota; Fond du Lac Band of the Minnesota Chippewa Tribe, Minnesota; Forest County Potawatomi Community, Wisconsin; Fort Belknap Indian Community of the Fort Belknap Reservation of Montana; Fort McDermitt Paiute and Shoshone Tribes of the Fort McDermitt Indian Reservation, Nevada and Oregon; Fort Sill Apache Tribe of Oklahoma; Grand Portage Band of the Minnesota Chippewa Tribe, Minnesota; Grand Traverse Band of Ottawa and Chippewa Indians, Michigan; Hannahville Indian Community, Michigan; Ho-Chunk Nation of Wisconsin; Iowa Tribe of Kansas and Nebraska; Iowa Tribe of Oklahoma; Jena Band of Choctaw Indians, Louisiana; Jicarilla Apache Nation, New Mexico; Kaw Nation, Oklahoma; Keweenaw Bay Indian Community, Michigan; Kickapoo Traditional Tribe of Texas; Kickapoo Tribe of Indians of the Kickapoo Reservation in Kansas; Kickapoo Tribe of Oklahoma; Kiowa Indian Tribe of Oklahoma; Lac Courte Oreilles Band of Lake Superior Chippewa Indians of Wisconsin; Lac du Flambeau Band of Lake Superior Chippewa Indians of the Lac du Flambeau Reservation of Wisconsin; Lac Vieux Desert Band of Lake Superior Chippewa Indians, Michigan; Leech Lake Band of the Minnesota Chippewa Tribe, Minnesota; Lower Brule Sioux Tribe of the Lower Brule Reservation, South Dakota; Lower Sioux Indian Community in the State of Minnesota; Match-e-be-nash-she-wish Band of Pottawatomi Indians of Michigan; Menominee Indian Tribe of Wisconsin; Mescalero Apache Tribe of the Mescalero Reservation, New Mexico; Miami Tribe of Oklahoma; Mille Lacs Band of the Minnesota Chippewa Tribe, Minnesota; Minnesota Chippewa Tribe, Minnesota; Mississippi Band of Choctaw Indians, Mississippi; Muscogee (Creek) Nation, Oklahoma; Northern Cheyenne Tribe of the Northern Cheyenne Indian Reservation, Montana; Nottawaseppi Huron Band of the Potawatomi, Michigan; Oglala Sioux Tribe of the Pine Ridge Reservation, South Dakota; Omaha Tribe of Nebraska; Osage Nation, Oklahoma; Otoe-Missouria Tribe of Indians, Oklahoma; Ottawa Tribe of Oklahoma; Pawnee Nation of Oklahoma; Peoria Tribe of Indians of Oklahoma; Poarch Band of Creek Indians of Alabama; Pokagon Band of Potawatomi Indians, Michigan and Indiana; Ponca Tribe of Indians of Oklahoma; Ponca Tribe of Nebraska; Prairie Band of Potawatomi Nation, Kansas; Prairie Island Indian Community in the State of Minnesota; Quapaw Tribe of Indians, Oklahoma; Quechan Tribe of the Fort Yuma Indian Reservation, California & Arizona; Red Cliff Band of Lake Superior Chippewa Indians of Wisconsin; Red Lake Band of Chippewa Indians, Minnesota; Rosebud Sioux Tribe of the Rosebud Indian Reservation, South Dakota; Sac & Fox Nation of Missouri in Kansas and Nebraska; Sac & Fox Nation, Oklahoma; Sac & Fox Tribe of the Mississippi in Iowa; Saginaw Chippewa Indian Tribe of Michigan; San Carlos Apache Tribe of the San Carlos Reservation, Arizona; Santee Sioux Nation, Nebraska; Sault Ste. Marie Tribe of Chippewa Indians of Michigan; Seminole Nation of Oklahoma; Seminole Tribe of Florida (Dania, Big Cypress, Brighton, Hollywood & Tampa Reservations); Seneca Nation of New York; Seneca-Cayuga Tribe of Oklahoma; Shakopee Mdewakanton Sioux Community of Minnesota; Shawnee Tribe, Oklahoma; Shoshone Tribe of the Wind River Reservation, Wyoming; Sisseton-Wahpeton Oyate of the Lake Traverse Reservation, South Dakota; Sokaogon Chippewa Community, Wisconsin; Southern Ute Indian Tribe of the Southern Ute Reservation, Colorado; Spirit Lake Tribe, North Dakota; St. Croix Chippewa Indians of Wisconsin; Standing Rock Sioux Tribe of North & South Dakota; Te-Moak Tribe of Western Shoshone Indians of Nevada; Three Affiliated Tribes of the Fort Berthold Reservation, North Dakota; Tonawanda Band of Seneca Indians of New York; Tonto Apache Tribe of Arizona; Turtle Mountain Band of Chippewa Indians of North Dakota; United Keetoowah Band of Cherokee Indians in Oklahoma; Upper Sioux Community, Minnesota; Ute Indian Tribe of the Uintah & Ouray Reservation, Utah; Ute Mountain Tribe of the Ute Mountain Reservation, Colorado, New Mexico & Utah; White Earth Band of the Minnesota Chippewa Tribe, Minnesota; White Mountain Apache Tribe of the Fort Apache Reservation, Arizona; Wichita and Affiliated Tribes (Wichita, Keechi, Waco & Tawakonie), Oklahoma; Winnebago Tribe of Nebraska; Wyandotte Nation, Oklahoma; and Yankton Sioux Tribe of South Dakota.\\n        \\xe2\\x80\\xa2 Other credible lines of evidence, including consultation with Tribal representatives, indicate that the land from which the Native American human remains were removed is the aboriginal land of the Apache Tribe of Oklahoma; Arapahoe Tribe of the Wind River Reservation, Wyoming; Assiniboine and Sioux Tribes of the Fort Peck Indian Reservation, Montana; Blackfeet Tribe of the Blackfeet Indian Reservation of Montana; Bois Forte Band (Nett Lake) of the Minnesota Chippewa Tribe, Minnesota; Cheyenne and Arapaho Tribes, Oklahoma; Cheyenne River Sioux Tribe of the Cheyenne River Reservation, South Dakota; Choctaw Nation of Oklahoma; Comanche Nation, Oklahoma; Crow Creek Sioux Tribe of the Crow Creek Reservation, South Dakota; Crow Tribe of Montana; Flandreau Santee Sioux Tribe of South Dakota; Fond du Lac Band of the Minnesota Chippewa Tribe, Minnesota; Fort Sill Apache Tribe of Oklahoma; Ho-Chunk Nation of Wisconsin; Iowa Tribe of Kansas and Nebraska; Iowa Tribe of Oklahoma; Jicarilla Apache Nation, New Mexico; Kickapoo Tribe of Indians of the Kickapoo Reservation in Kansas; Kiowa Indian Tribe of Oklahoma; Leech Lake Band of the Minnesota Chippewa Tribe, Minnesota; Lower Brule Sioux Tribe of the Lower Brule Reservation, South Dakota; Lower Sioux Indian Community in the State of Minnesota; Menominee Indian Tribe of Wisconsin; Mescalero Apache Tribe of the Mescalero Reservation, New Mexico; Mille Lacs Band of the Minnesota Chippewa Tribe, Minnesota; Muscogee (Creek) Nation, Oklahoma; Nez Perce Tribe, Idaho; Northern Cheyenne Tribe of the Northern Cheyenne Indian Reservation, Montana; Oglala Sioux Tribe of the Pine Ridge Reservation, South Dakota; Ohkay Owingeh, New Mexico; Omaha Tribe of Nebraska; Osage Nation, Oklahoma; Otoe-Missouria Tribe of Indians, Oklahoma; Pawnee Nation of Oklahoma; Ponca Tribe of Indians of Oklahoma; Ponca Tribe of Nebraska; Prairie Band of Potawatomi Nation, Kansas; Pueblo of Cochiti, New Mexico; Pueblo of San Ildefonso, New Mexico; Pueblo of Santa Ana, New Mexico; Pueblo of Santa Clara, New Mexico; Quapaw Tribe of Indians, Oklahoma; Rosebud Sioux Tribe of the Rosebud Indian Reservation, South Dakota; Sac & Fox Nation of Missouri in Kansas and Nebraska; Sac & Fox Nation, Oklahoma; Sac & Fox Tribe of the Mississippi in Iowa; Santee Sioux Nation, Nebraska; Shakopee Mdewakanton Sioux Community of Minnesota; Shoshone Tribe of the Wind River Reservation, Wyoming; Sisseton-Wahpeton Oyate of the Lake Traverse Reservation, South Dakota; Southern Ute Indian Tribe of the Southern Ute Reservation, Colorado; Spirit Lake Tribe, North Dakota; Standing Rock Sioux Tribe of North & South Dakota; Three Affiliated Tribes of the Fort Berthold Reservation, North Dakota; Upper Sioux Community, Minnesota; Ute Indian Tribe of the Uintah & Ouray Reservation, Utah; Ute Mountain Tribe of the Ute Mountain Reservation, Colorado, New Mexico & Utah; White Earth Band of the Minnesota Chippewa Tribe, Minnesota; Wichita and Affiliated Tribes (Wichita, Keechi, Waco & Tawakonie), Oklahoma; Yankton Sioux Tribe of South Dakota; and the Zuni Tribe of the Zuni Reservation, New Mexico.\\n        \\xe2\\x80\\xa2 Pursuant to 25 U.S.C. 3001(9), the human remains described in this notice represent the physical remains of two individuals of Native American ancestry.\\n        \\xe2\\x80\\xa2 Pursuant to 43 CFR 10.11(c)(1), the disposition of the human remains is to The Tribes.\\n        Additional Requestors and Disposition\\n        Representatives of any Indian Tribe that believes itself to be culturally affiliated with the human remains or any other Indian Tribe that believes it satisfies the criteria in 43 CFR 10.11(c)(1) should contact Dr. Chip Colwell-Chanthaphonh, Denver Museum of Nature & Science, 2001 Colorado Blvd., Denver, CO 80205, telephone (303) 370-6378 by March 21, 2011. Disposition of the human remains to The Tribes may proceed after that date if no additional requestors come forward.\\n        The Denver Museum of Nature & Science is responsible for notifying The Tribes that this notice has been published.\\n        \\n          \\n          Dated: February 15, 2011.\\n          Sherry Hutt,\\n          Manager, National NAGPRA Program.\\n        \\n      \\n      [FR Doc. 2011-3757 Filed 2-17-11; 8:45 am]\\n      BILLING CODE 4312-50-P\\n    ", "agency1": "DEPARTMENT OF THE INTERIOR", "sub_agency1": "National Park Service", "dep_doc": "[2253-665]", "subject": "Notice of Inventory Completion: Denver Museum of Nature & Science, Denver, CO", "agency2": "National Park Service, Interior.", "action": "Notice.", "summary": "The Denver Museum of Nature & Science has completed an inventory of human remains, in consultation with the appropriate Indian Tribes, and has determined that there is no cultural affiliation between the remains and any present-day Tribe. Representatives of any Indian Tribe that believes itself to be culturally affiliated with the human remains may contact the museum. Disposition of the human remains to the Tribes stated below may occur if no additional requestors come forward.", "dates": "Representatives of any Indian Tribe that believes it has a cultural affiliation with the human remains should contact the museum at the address below by March 21, 2011.", "addresses": "Any Tribe that believes it has a cultural affiliation with the human remains should contact Dr. Chip Colwell-Chanthaphonh, Denver Museum of Nature & Science, 2001 Colorado Blvd., Denver, CO 80205, telephone (303) 370-6378.", "signature_dated": "Dated: February 15, 2011.", "signature_name": "Sherry Hutt,", "signature_title": "Manager, National NAGPRA Program.", "fr_doc": "[FR Doc. 2011-3757 Filed 2-17-11; 8:45 am]", "billing_code": "BILLING CODE 4312-50-P", "supp_info": "SUPPLEMENTARY INFORMATION: \n Notice is here given in accordance with the Native American Graves Protection and Repatriation Act (NAGPRA), 25 U.S.C. 3003, of the completion of an inventory of human remains in the possession of the Denver Museum of Nature & Science, Denver, CO. The human remains were removed from an unknown location in the Great Plains. \n This notice is published as part of the National Park Service\\'s administrative responsibilities under NAGPRA, 25 U.S.C. 3003(d)(3) and 43 CFR 10.11(d). The determinations in this notice are the sole responsibility of the museum, institution, or Federal agency that has control of the Native American human remains. The National Park Service is not responsible for the determinations in this notice. \n Consultation \n A detailed assessment of the human remains was made by the Denver Museum of Nature & Science professional staff in consultation with representatives of the Absentee-Shawnee Tribe of Indians of Oklahoma; Apache Tribe of Oklahoma; Arapahoe Tribe of the Wind River Reservation, Wyoming; Assiniboine and Sioux Tribes of the Fort Peck Indian Reservation, Montana; Bad River Band of the Lake Superior Tribe of Chippewa Indians of the Bad River Reservation, Wisconsin; Bay Mills Indian Community, Michigan; Big Pine Band of Owens Valley Paiute Shoshone Indians of the Big Pine Reservation, California; Blackfeet Tribe of the Blackfeet Indian Reservation of Montana; Bois Forte Band (Nett Lake) of the Minnesota Chippewa Tribe, Minnesota; Caddo Nation of Oklahoma; Cherokee Nation, Oklahoma; Cheyenne and Arapaho Tribes, Oklahoma; Cheyenne River Sioux Tribe of the Cheyenne River Reservation, South Dakota; Chickasaw Nation, Oklahoma; Chippewa-Cree Indians of the Rocky Boy\\'s Reservation, Montana; Choctaw Nation of Oklahoma; Citizen Potawatomi Nation, Oklahoma; Comanche Nation, Oklahoma; Crow Creek Sioux Tribe of the Crow Creek Reservation, South Dakota; Crow Tribe of Montana; Death Valley Timbi-Sha Shoshone Band of California; Delaware Nation, Oklahoma; Duckwater Shoshone Tribe of the Duckwater Reservation, Nevada; Eastern Band of Cherokee Indians of North Carolina; Ely Shoshone Tribe of Nevada; Flandreau Santee Sioux Tribe of South Dakota; Fond du Lac Band of the Minnesota Chippewa Tribe, Minnesota; Forest County Potawatomi Community, Wisconsin; Fort Belknap Indian Community of the Fort Belknap Reservation of Montana; Fort McDermitt Paiute and Shoshone Tribes of the Fort McDermitt Indian Reservation, Nevada and Oregon; Fort Sill Apache Tribe of Oklahoma; Grand Portage Band of the Minnesota Chippewa Tribe, Minnesota; Grand Traverse Band of Ottawa and Chippewa Indians, Michigan; Hannahville Indian Community, Michigan; Ho-Chunk Nation of Wisconsin; Iowa Tribe of Kansas and Nebraska; Iowa Tribe of Oklahoma; Jena Band of Choctaw Indians, Louisiana; Jicarilla Apache Nation, New Mexico; Kaw Nation, Oklahoma; Keweenaw Bay Indian Community, Michigan; Kickapoo Traditional Tribe of Texas; Kickapoo Tribe of Indians of the Kickapoo Reservation in Kansas; Kickapoo Tribe of Oklahoma; Kiowa Indian Tribe of Oklahoma; Lac Courte Oreilles Band of Lake Superior Chippewa Indians of Wisconsin; Lac du Flambeau Band of Lake Superior Chippewa Indians of the Lac du Flambeau Reservation of Wisconsin; Lac Vieux Desert Band of Lake Superior Chippewa Indians, Michigan; Leech Lake Band of the Minnesota Chippewa Tribe, Minnesota; Lower Brule Sioux Tribe of the Lower Brule Reservation, South Dakota; Lower Sioux Indian Community in the State of Minnesota; Match-e-be-nash-she-wish Band of Pottawatomi Indians of Michigan; Menominee Indian Tribe of Wisconsin; Mescalero Apache Tribe of the Mescalero Reservation, New Mexico; Miami Tribe of Oklahoma; Mille Lacs Band of the Minnesota Chippewa Tribe, Minnesota; Minnesota Chippewa Tribe, Minnesota; Mississippi Band of Choctaw Indians, Mississippi; Muscogee (Creek) Nation, Oklahoma; Nez Perce Tribe, Idaho; Northern Cheyenne Tribe of the Northern Cheyenne Indian Reservation, Montana; Nottawaseppi Huron Band of the Potawatomi, Michigan; Oglala Sioux Tribe of the Pine Ridge Reservation, South Dakota; Ohkay Owingeh, New Mexico; Omaha Tribe of Nebraska; Osage Nation, Oklahoma; Otoe-Missouria Tribe of Indians, Oklahoma; Ottawa Tribe of Oklahoma; Pawnee Nation of Oklahoma; Peoria Tribe of Indians of Oklahoma; Poarch Band of Creek Indians of Alabama; Pokagon Band of Potawatomi Indians, Michigan and Indiana; Ponca Tribe of Indians of Oklahoma; Ponca Tribe of Nebraska; Prairie Band of Potawatomi Nation, Kansas; Prairie Island Indian Community in the State of Minnesota; Pueblo of Cochiti, New Mexico; Pueblo of San Ildefonso, New Mexico; Pueblo of Santa Ana, New Mexico; Pueblo of Santa Clara, New Mexico; Quapaw Tribe of Indians, Oklahoma; Quechan Tribe of the Fort Yuma Indian Reservation, California & Arizona; Red Cliff Band of Lake Superior Chippewa Indians of Wisconsin; Red Lake Band of Chippewa Indians, Minnesota; Rosebud Sioux Tribe of the Rosebud Indian Reservation, South Dakota; Sac & Fox Nation of Missouri in Kansas and Nebraska; Sac & Fox Nation, Oklahoma; Sac & Fox Tribe of the Mississippi in Iowa; Saginaw Chippewa Indian Tribe of Michigan; San Carlos Apache Tribe of the San Carlos Reservation, Arizona; Santee Sioux Nation, Nebraska; Sault Ste. Marie Tribe of Chippewa Indians of Michigan; Seminole Nation of Oklahoma; Seminole Tribe of Florida (Dania, Big Cypress, Brighton, Hollywood & Tampa Reservations); Seneca Nation of New York; Seneca-Cayuga Tribe of Oklahoma; Shakopee Mdewakanton Sioux Community of Minnesota; Shawnee Tribe, Oklahoma; Shoshone Tribe of the Wind River Reservation, Wyoming; Sisseton-Wahpeton Oyate of the Lake Traverse Reservation, South Dakota; Sokaogon Chippewa Community, Wisconsin; Southern Ute Indian Tribe of the Southern Ute Reservation, Colorado; Spirit Lake Tribe, North Dakota; St. Croix Chippewa Indians of Wisconsin; Standing Rock Sioux Tribe of North & South Dakota; Te-Moak Tribe of Western Shoshone Indians of Nevada (Four constituent bands: Battle Mountain Band; Elko Band; South Fork Band and Wells Band); Three Affiliated Tribes of the Fort Berthold Reservation, North Dakota; Tonawanda Band of Seneca Indians of New York; Tonto Apache Tribe of Arizona; Turtle Mountain Band of Chippewa Indians of North Dakota; United Keetoowah Band of Cherokee Indians in Oklahoma; Upper Sioux Community, Minnesota; Ute Indian Tribe of the Uintah & Ouray Reservation, Utah; Ute Mountain Tribe of the Ute Mountain Reservation, Colorado, New Mexico & Utah; White Earth Band of the Minnesota Chippewa Tribe, Minnesota; White Mountain Apache Tribe of the Fort Apache Reservation, Arizona; Wichita and Affiliated Tribes (Wichita, Keechi, Waco & Tawakonie), Oklahoma; Winnebago Tribe of Nebraska; Wyandotte Nation, Oklahoma; Yankton Sioux Tribe of South Dakota; and the Zuni Tribe of the Zuni Reservation, New Mexico (hereinafter referred to as \\xe2\\x80\\x9cThe Tribes\\xe2\\x80\\x9d). \n History and Description of the Remains \n In 1959, Francis and Mary Crane purchased human remains representing a minimum of one individual from Kohlberg\\'s Antiques and Indian Arts, in Denver, CO. In 1972, the human remains were donated by Mr. and Mrs. Crane and accessioned into the collections (AC.4224 (CUI 21)). The remains include a scalp lock with black hair, approximately 16 inches long, and one quarter of an inch wide. The upper end of the scalp lock is covered with sinew, yellow dyed deerskin, and tufts of red feather. No known individual was identified. No associated funerary objects are present. \n In 1956, Francis and Mary Crane purchased human remains representing a minimum of one individual from Kohlberg\\'s Antiques and Indian Arts. The remains were reportedly a part of the George A. Cuneo Collection of Southwestern and Plains Indian objects collected in the late 19th and early 20th centuries. In 1983, the human remains were donated by Mr. and Mrs. Crane and accessioned into the collections (AC.35D (CUI 23)). The remains include seven inches of black and grey hair and scalp with traces of red pigment and a row of perforations along one edge of it. No known individual was identified. No associated funerary objects are present. \n Determinations Made by the Denver Museum \n Officials of the Denver Museum of Nature & Science have determined that: \n \\xe2\\x80\\xa2 Based on non-destructive physical analysis and catalogue records, the human remains are Native American. \n \\xe2\\x80\\xa2 Pursuant to 25 U.S.C. 3001(2), a relationship of shared group identity cannot be reasonably traced between the Native American human remains and any present-day Indian Tribe. \n \\xe2\\x80\\xa2 According to final judgments of the Indian Claims Commission, the land from which the Native American human remains were removed is the aboriginal land of the Apache Tribe of Oklahoma; Arapahoe Tribe of the Wind River Reservation, Wyoming; Assiniboine and Sioux Tribes of the Fort Peck Indian Reservation, Montana; Big Pine Band of Owens Valley Paiute Shoshone Indians of the Big Pine Reservation, California; Blackfeet Tribe of the Blackfeet Indian Reservation of Montana; Caddo Nation of Oklahoma; Cheyenne and Arapaho Tribes, Oklahoma; Cheyenne River Sioux Tribe of the Cheyenne River Reservation, South Dakota; Citizen Potawatomi Nation, Oklahoma; Comanche Nation, Oklahoma; Crow Creek Sioux Tribe of the Crow Creek Reservation, South Dakota; Crow Tribe of Montana; Death Valley Timbi-Sha Shoshone Band of California; Duckwater Shoshone Tribe of the Duckwater Reservation, Nevada; Ely Shoshone Tribe of Nevada; Flandreau Santee Sioux Tribe of South Dakota; Forest County Potawatomi Community, Wisconsin; Fort McDermitt Paiute and Shoshone Tribes of the Fort McDermitt Indian Reservation, Nevada and Oregon; Fort Sill Apache Tribe of Oklahoma; Ho-Chunk Nation of Wisconsin; Iowa Tribe of Kansas and Nebraska; Iowa Tribe of Oklahoma; Jicarilla Apache Nation, New Mexico; Kickapoo Traditional Tribe of Texas; Kickapoo Tribe of Indians of the Kickapoo Reservation in Kansas; Kickapoo Tribe of Oklahoma; Kiowa Indian Tribe of Oklahoma; Lower Brule Sioux Tribe of the Lower Brule Reservation, South Dakota; Lower Sioux Indian Community in the State of Minnesota; Match-e-be-nash-she-wish Band of Pottawatomi Indians of Michigan; Mescalero Apache Tribe of the Mescalero Reservation, New Mexico; Nez Perce Tribe, Idaho; Northern Cheyenne Tribe of the Northern Cheyenne Indian Reservation, Montana; Nottawaseppi Huron Band of the Potawatomi, Michigan; Oglala Sioux Tribe of the Pine Ridge Reservation, South Dakota; Omaha Tribe of Nebraska; Osage Nation, Oklahoma; Otoe-Missouria Tribe of Indians, Oklahoma; Pawnee Nation of Oklahoma; Pokagon Band of Potawatomi Indians, Michigan and Indiana; Ponca Tribe of Indians of Oklahoma; Ponca Tribe of Nebraska; Prairie Band of Potawatomi Nation, Kansas; Prairie Island Indian Community in the State of Minnesota; Quapaw Tribe of Indians, Oklahoma; Rosebud Sioux Tribe of the Rosebud Indian Reservation, South Dakota; Sac & Fox Nation of Missouri in Kansas and Nebraska; Sac & Fox Nation, Oklahoma; Sac & Fox Tribe of the Mississippi in Iowa; San Carlos Apache Tribe of the San Carlos Reservation, Arizona; Santee Sioux Nation, Nebraska; Shakopee Mdewakanton Sioux Community of Minnesota; Sisseton-Wahpeton Oyate of the Lake Traverse Reservation, South Dakota; Southern Ute Indian Tribe of the Southern Ute Reservation, Colorado; Spirit Lake Tribe, North Dakota; Standing Rock Sioux Tribe of North & South Dakota; Tonto Apache Tribe of Arizona; Upper Sioux Community, Minnesota; Ute Indian Tribe of the Uintah & Ouray Reservation, Utah; Ute Mountain Tribe of the Ute Mountain Reservation, Colorado, New Mexico & Utah; White Mountain Apache Tribe of the Fort Apache Reservation, Arizona; Winnebago Tribe of Nebraska; and Yankton Sioux Tribe of South Dakota. \n \\xe2\\x80\\xa2 Multiple lines of evidence, including treaties, Acts of Congress, and Executive Orders, indicate that the land from which the Native American human remains were removed is the aboriginal land of the Absentee-Shawnee Tribe of Indians of Oklahoma; Apache Tribe of Oklahoma; Arapahoe Tribe of the Wind River Reservation, Wyoming; Assiniboine and Sioux Tribes of the Fort Peck Indian Reservation, Montana; Bad River Band of the Lake Superior Tribe of Chippewa Indians of the Bad River Reservation, Wisconsin; Bay Mills Indian Community, Michigan; Big Pine Band of Owens Valley Paiute Shoshone Indians of the Big Pine Reservation, California; Blackfeet Tribe of the Blackfeet Indian Reservation of Montana; Bois Forte Band (Nett Lake) of the Minnesota Chippewa Tribe, Minnesota; Caddo Nation of Oklahoma; Cherokee Nation, Oklahoma; Cheyenne and Arapaho Tribes, Oklahoma; Cheyenne River Sioux Tribe of the Cheyenne River Reservation, South Dakota; Chickasaw Nation, Oklahoma; Chippewa-Cree Indians of the Rocky Boy\\'s Reservation, Montana; Choctaw Nation of Oklahoma; Citizen Potawatomi Nation, Oklahoma; Comanche Nation, Oklahoma; Crow Creek Sioux Tribe of the Crow Creek Reservation, South Dakota; Crow Tribe of Montana; Death Valley Timbi-Sha Shoshone Band of California; Delaware Nation, Oklahoma; Duckwater Shoshone Tribe of the Duckwater Reservation, Nevada; Eastern Band of Cherokee Indians of North Carolina; Ely Shoshone Tribe of Nevada; Flandreau Santee Sioux Tribe of South Dakota; Fond du Lac Band of the Minnesota Chippewa Tribe, Minnesota; Forest County Potawatomi Community, Wisconsin; Fort Belknap Indian Community of the Fort Belknap Reservation of Montana; Fort McDermitt Paiute and Shoshone Tribes of the Fort McDermitt Indian Reservation, Nevada and Oregon; Fort Sill Apache Tribe of Oklahoma; Grand Portage Band of the Minnesota Chippewa Tribe, Minnesota; Grand Traverse Band of Ottawa and Chippewa Indians, Michigan; Hannahville Indian Community, Michigan; Ho-Chunk Nation of Wisconsin; Iowa Tribe of Kansas and Nebraska; Iowa Tribe of Oklahoma; Jena Band of Choctaw Indians, Louisiana; Jicarilla Apache Nation, New Mexico; Kaw Nation, Oklahoma; Keweenaw Bay Indian Community, Michigan; Kickapoo Traditional Tribe of Texas; Kickapoo Tribe of Indians of the Kickapoo Reservation in Kansas; Kickapoo Tribe of Oklahoma; Kiowa Indian Tribe of Oklahoma; Lac Courte Oreilles Band of Lake Superior Chippewa Indians of Wisconsin; Lac du Flambeau Band of Lake Superior Chippewa Indians of the Lac du Flambeau Reservation of Wisconsin; Lac Vieux Desert Band of Lake Superior Chippewa Indians, Michigan; Leech Lake Band of the Minnesota Chippewa Tribe, Minnesota; Lower Brule Sioux Tribe of the Lower Brule Reservation, South Dakota; Lower Sioux Indian Community in the State of Minnesota; Match-e-be-nash-she-wish Band of Pottawatomi Indians of Michigan; Menominee Indian Tribe of Wisconsin; Mescalero Apache Tribe of the Mescalero Reservation, New Mexico; Miami Tribe of Oklahoma; Mille Lacs Band of the Minnesota Chippewa Tribe, Minnesota; Minnesota Chippewa Tribe, Minnesota; Mississippi Band of Choctaw Indians, Mississippi; Muscogee (Creek) Nation, Oklahoma; Northern Cheyenne Tribe of the Northern Cheyenne Indian Reservation, Montana; Nottawaseppi Huron Band of the Potawatomi, Michigan; Oglala Sioux Tribe of the Pine Ridge Reservation, South Dakota; Omaha Tribe of Nebraska; Osage Nation, Oklahoma; Otoe-Missouria Tribe of Indians, Oklahoma; Ottawa Tribe of Oklahoma; Pawnee Nation of Oklahoma; Peoria Tribe of Indians of Oklahoma; Poarch Band of Creek Indians of Alabama; Pokagon Band of Potawatomi Indians, Michigan and Indiana; Ponca Tribe of Indians of Oklahoma; Ponca Tribe of Nebraska; Prairie Band of Potawatomi Nation, Kansas; Prairie Island Indian Community in the State of Minnesota; Quapaw Tribe of Indians, Oklahoma; Quechan Tribe of the Fort Yuma Indian Reservation, California & Arizona; Red Cliff Band of Lake Superior Chippewa Indians of Wisconsin; Red Lake Band of Chippewa Indians, Minnesota; Rosebud Sioux Tribe of the Rosebud Indian Reservation, South Dakota; Sac & Fox Nation of Missouri in Kansas and Nebraska; Sac & Fox Nation, Oklahoma; Sac & Fox Tribe of the Mississippi in Iowa; Saginaw Chippewa Indian Tribe of Michigan; San Carlos Apache Tribe of the San Carlos Reservation, Arizona; Santee Sioux Nation, Nebraska; Sault Ste. Marie Tribe of Chippewa Indians of Michigan; Seminole Nation of Oklahoma; Seminole Tribe of Florida (Dania, Big Cypress, Brighton, Hollywood & Tampa Reservations); Seneca Nation of New York; Seneca-Cayuga Tribe of Oklahoma; Shakopee Mdewakanton Sioux Community of Minnesota; Shawnee Tribe, Oklahoma; Shoshone Tribe of the Wind River Reservation, Wyoming; Sisseton-Wahpeton Oyate of the Lake Traverse Reservation, South Dakota; Sokaogon Chippewa Community, Wisconsin; Southern Ute Indian Tribe of the Southern Ute Reservation, Colorado; Spirit Lake Tribe, North Dakota; St. Croix Chippewa Indians of Wisconsin; Standing Rock Sioux Tribe of North & South Dakota; Te-Moak Tribe of Western Shoshone Indians of Nevada; Three Affiliated Tribes of the Fort Berthold Reservation, North Dakota; Tonawanda Band of Seneca Indians of New York; Tonto Apache Tribe of Arizona; Turtle Mountain Band of Chippewa Indians of North Dakota; United Keetoowah Band of Cherokee Indians in Oklahoma; Upper Sioux Community, Minnesota; Ute Indian Tribe of the Uintah & Ouray Reservation, Utah; Ute Mountain Tribe of the Ute Mountain Reservation, Colorado, New Mexico & Utah; White Earth Band of the Minnesota Chippewa Tribe, Minnesota; White Mountain Apache Tribe of the Fort Apache Reservation, Arizona; Wichita and Affiliated Tribes (Wichita, Keechi, Waco & Tawakonie), Oklahoma; Winnebago Tribe of Nebraska; Wyandotte Nation, Oklahoma; and Yankton Sioux Tribe of South Dakota. \n \\xe2\\x80\\xa2 Other credible lines of evidence, including consultation with Tribal representatives, indicate that the land from which the Native American human remains were removed is the aboriginal land of the Apache Tribe of Oklahoma; Arapahoe Tribe of the Wind River Reservation, Wyoming; Assiniboine and Sioux Tribes of the Fort Peck Indian Reservation, Montana; Blackfeet Tribe of the Blackfeet Indian Reservation of Montana; Bois Forte Band (Nett Lake) of the Minnesota Chippewa Tribe, Minnesota; Cheyenne and Arapaho Tribes, Oklahoma; Cheyenne River Sioux Tribe of the Cheyenne River Reservation, South Dakota; Choctaw Nation of Oklahoma; Comanche Nation, Oklahoma; Crow Creek Sioux Tribe of the Crow Creek Reservation, South Dakota; Crow Tribe of Montana; Flandreau Santee Sioux Tribe of South Dakota; Fond du Lac Band of the Minnesota Chippewa Tribe, Minnesota; Fort Sill Apache Tribe of Oklahoma; Ho-Chunk Nation of Wisconsin; Iowa Tribe of Kansas and Nebraska; Iowa Tribe of Oklahoma; Jicarilla Apache Nation, New Mexico; Kickapoo Tribe of Indians of the Kickapoo Reservation in Kansas; Kiowa Indian Tribe of Oklahoma; Leech Lake Band of the Minnesota Chippewa Tribe, Minnesota; Lower Brule Sioux Tribe of the Lower Brule Reservation, South Dakota; Lower Sioux Indian Community in the State of Minnesota; Menominee Indian Tribe of Wisconsin; Mescalero Apache Tribe of the Mescalero Reservation, New Mexico; Mille Lacs Band of the Minnesota Chippewa Tribe, Minnesota; Muscogee (Creek) Nation, Oklahoma; Nez Perce Tribe, Idaho; Northern Cheyenne Tribe of the Northern Cheyenne Indian Reservation, Montana; Oglala Sioux Tribe of the Pine Ridge Reservation, South Dakota; Ohkay Owingeh, New Mexico; Omaha Tribe of Nebraska; Osage Nation, Oklahoma; Otoe-Missouria Tribe of Indians, Oklahoma; Pawnee Nation of Oklahoma; Ponca Tribe of Indians of Oklahoma; Ponca Tribe of Nebraska; Prairie Band of Potawatomi Nation, Kansas; Pueblo of Cochiti, New Mexico; Pueblo of San Ildefonso, New Mexico; Pueblo of Santa Ana, New Mexico; Pueblo of Santa Clara, New Mexico; Quapaw Tribe of Indians, Oklahoma; Rosebud Sioux Tribe of the Rosebud Indian Reservation, South Dakota; Sac & Fox Nation of Missouri in Kansas and Nebraska; Sac & Fox Nation, Oklahoma; Sac & Fox Tribe of the Mississippi in Iowa; Santee Sioux Nation, Nebraska; Shakopee Mdewakanton Sioux Community of Minnesota; Shoshone Tribe of the Wind River Reservation, Wyoming; Sisseton-Wahpeton Oyate of the Lake Traverse Reservation, South Dakota; Southern Ute Indian Tribe of the Southern Ute Reservation, Colorado; Spirit Lake Tribe, North Dakota; Standing Rock Sioux Tribe of North & South Dakota; Three Affiliated Tribes of the Fort Berthold Reservation, North Dakota; Upper Sioux Community, Minnesota; Ute Indian Tribe of the Uintah & Ouray Reservation, Utah; Ute Mountain Tribe of the Ute Mountain Reservation, Colorado, New Mexico & Utah; White Earth Band of the Minnesota Chippewa Tribe, Minnesota; Wichita and Affiliated Tribes (Wichita, Keechi, Waco & Tawakonie), Oklahoma; Yankton Sioux Tribe of South Dakota; and the Zuni Tribe of the Zuni Reservation, New Mexico. \n \\xe2\\x80\\xa2 Pursuant to 25 U.S.C. 3001(9), the human remains described in this notice represent the physical remains of two individuals of Native American ancestry. \n \\xe2\\x80\\xa2 Pursuant to 43 CFR 10.11(c)(1), the disposition of the human remains is to The Tribes. \n Additional Requestors and Disposition \n Representatives of any Indian Tribe that believes itself to be culturally affiliated with the human remains or any other Indian Tribe that believes it satisfies the criteria in 43 CFR 10.11(c)(1) should contact Dr. Chip Colwell-Chanthaphonh, Denver Museum of Nature & Science, 2001 Colorado Blvd., Denver, CO 80205, telephone (303) 370-6378 by March 21, 2011. Disposition of the human remains to The Tribes may proceed after that date if no additional requestors come forward. \n The Denver Museum of Nature & Science is responsible for notifying The Tribes that this notice has been published. \n ", "consultation": "A detailed assessment of the human remains was made by the Denver Museum of Nature & Science professional staff in consultation with representatives of the Absentee-Shawnee Tribe of Indians of Oklahoma; Apache Tribe of Oklahoma; Arapahoe Tribe of the Wind River Reservation, Wyoming; Assiniboine and Sioux Tribes of the Fort Peck Indian Reservation, Montana; Bad River Band of the Lake Superior Tribe of Chippewa Indians of the Bad River Reservation, Wisconsin; Bay Mills Indian Community, Michigan; Big Pine Band of Owens Valley Paiute Shoshone Indians of the Big Pine Reservation, California; Blackfeet Tribe of the Blackfeet Indian Reservation of Montana; Bois Forte Band (Nett Lake) of the Minnesota Chippewa Tribe, Minnesota; Caddo Nation of Oklahoma; Cherokee Nation, Oklahoma; Cheyenne and Arapaho Tribes, Oklahoma; Cheyenne River Sioux Tribe of the Cheyenne River Reservation, South Dakota; Chickasaw Nation, Oklahoma; Chippewa-Cree Indians of the Rocky Boy\\'s Reservation, Montana; Choctaw Nation of Oklahoma; Citizen Potawatomi Nation, Oklahoma; Comanche Nation, Oklahoma; Crow Creek Sioux Tribe of the Crow Creek Reservation, South Dakota; Crow Tribe of Montana; Death Valley Timbi-Sha Shoshone Band of California; Delaware Nation, Oklahoma; Duckwater Shoshone Tribe of the Duckwater Reservation, Nevada; Eastern Band of Cherokee Indians of North Carolina; Ely Shoshone Tribe of Nevada; Flandreau Santee Sioux Tribe of South Dakota; Fond du Lac Band of the Minnesota Chippewa Tribe, Minnesota; Forest County Potawatomi Community, Wisconsin; Fort Belknap Indian Community of the Fort Belknap Reservation of Montana; Fort McDermitt Paiute and Shoshone Tribes of the Fort McDermitt Indian Reservation, Nevada and Oregon; Fort Sill Apache Tribe of Oklahoma; Grand Portage Band of the Minnesota Chippewa Tribe, Minnesota; Grand Traverse Band of Ottawa and Chippewa Indians, Michigan; Hannahville Indian Community, Michigan; Ho-Chunk Nation of Wisconsin; Iowa Tribe of Kansas and Nebraska; Iowa Tribe of Oklahoma; Jena Band of Choctaw Indians, Louisiana; Jicarilla Apache Nation, New Mexico; Kaw Nation, Oklahoma; Keweenaw Bay Indian Community, Michigan; Kickapoo Traditional Tribe of Texas; Kickapoo Tribe of Indians of the Kickapoo Reservation in Kansas; Kickapoo Tribe of Oklahoma; Kiowa Indian Tribe of Oklahoma; Lac Courte Oreilles Band of Lake Superior Chippewa Indians of Wisconsin; Lac du Flambeau Band of Lake Superior Chippewa Indians of the Lac du Flambeau Reservation of Wisconsin; Lac Vieux Desert Band of Lake Superior Chippewa Indians, Michigan; Leech Lake Band of the Minnesota Chippewa Tribe, Minnesota; Lower Brule Sioux Tribe of the Lower Brule Reservation, South Dakota; Lower Sioux Indian Community in the State of Minnesota; Match-e-be-nash-she-wish Band of Pottawatomi Indians of Michigan; Menominee Indian Tribe of Wisconsin; Mescalero Apache Tribe of the Mescalero Reservation, New Mexico; Miami Tribe of Oklahoma; Mille Lacs Band of the Minnesota Chippewa Tribe, Minnesota; Minnesota Chippewa Tribe, Minnesota; Mississippi Band of Choctaw Indians, Mississippi; Muscogee (Creek) Nation, Oklahoma; Nez Perce Tribe, Idaho; Northern Cheyenne Tribe of the Northern Cheyenne Indian Reservation, Montana; Nottawaseppi Huron Band of the Potawatomi, Michigan; Oglala Sioux Tribe of the Pine Ridge Reservation, South Dakota; Ohkay Owingeh, New Mexico; Omaha Tribe of Nebraska; Osage Nation, Oklahoma; Otoe-Missouria Tribe of Indians, Oklahoma; Ottawa Tribe of Oklahoma; Pawnee Nation of Oklahoma; Peoria Tribe of Indians of Oklahoma; Poarch Band of Creek Indians of Alabama; Pokagon Band of Potawatomi Indians, Michigan and Indiana; Ponca Tribe of Indians of Oklahoma; Ponca Tribe of Nebraska; Prairie Band of Potawatomi Nation, Kansas; Prairie Island Indian Community in the State of Minnesota; Pueblo of Cochiti, New Mexico; Pueblo of San Ildefonso, New Mexico; Pueblo of Santa Ana, New Mexico; Pueblo of Santa Clara, New Mexico; Quapaw Tribe of Indians, Oklahoma; Quechan Tribe of the Fort Yuma Indian Reservation, California & Arizona; Red Cliff Band of Lake Superior Chippewa Indians of Wisconsin; Red Lake Band of Chippewa Indians, Minnesota; Rosebud Sioux Tribe of the Rosebud Indian Reservation, South Dakota; Sac & Fox Nation of Missouri in Kansas and Nebraska; Sac & Fox Nation, Oklahoma; Sac & Fox Tribe of the Mississippi in Iowa; Saginaw Chippewa Indian Tribe of Michigan; San Carlos Apache Tribe of the San Carlos Reservation, Arizona; Santee Sioux Nation, Nebraska; Sault Ste. Marie Tribe of Chippewa Indians of Michigan; Seminole Nation of Oklahoma; Seminole Tribe of Florida (Dania, Big Cypress, Brighton, Hollywood & Tampa Reservations); Seneca Nation of New York; Seneca-Cayuga Tribe of Oklahoma; Shakopee Mdewakanton Sioux Community of Minnesota; Shawnee Tribe, Oklahoma; Shoshone Tribe of the Wind River Reservation, Wyoming; Sisseton-Wahpeton Oyate of the Lake Traverse Reservation, South Dakota; Sokaogon Chippewa Community, Wisconsin; Southern Ute Indian Tribe of the Southern Ute Reservation, Colorado; Spirit Lake Tribe, North Dakota; St. Croix Chippewa Indians of Wisconsin; Standing Rock Sioux Tribe of North & South Dakota; Te-Moak Tribe of Western Shoshone Indians of Nevada (Four constituent bands: Battle Mountain Band; Elko Band; South Fork Band and Wells Band); Three Affiliated Tribes of the Fort Berthold Reservation, North Dakota; Tonawanda Band of Seneca Indians of New York; Tonto Apache Tribe of Arizona; Turtle Mountain Band of Chippewa Indians of North Dakota; United Keetoowah Band of Cherokee Indians in Oklahoma; Upper Sioux Community, Minnesota; Ute Indian Tribe of the Uintah & Ouray Reservation, Utah; Ute Mountain Tribe of the Ute Mountain Reservation, Colorado, New Mexico & Utah; White Earth Band of the Minnesota Chippewa Tribe, Minnesota; White Mountain Apache Tribe of the Fort Apache Reservation, Arizona; Wichita and Affiliated Tribes (Wichita, Keechi, Waco & Tawakonie), Oklahoma; Winnebago Tribe of Nebraska; Wyandotte Nation, Oklahoma; Yankton Sioux Tribe of South Dakota; and the Zuni Tribe of the Zuni Reservation, New Mexico (hereinafter referred to as \\xe2\\x80\\x9cThe Tribes\\xe2\\x80\\x9d). \n ", "h_d_r": "In 1959, Francis and Mary Crane purchased human remains representing a minimum of one individual from Kohlberg\\'s Antiques and Indian Arts, in Denver, CO. In 1972, the human remains were donated by Mr. and Mrs. Crane and accessioned into the collections (AC.4224 (CUI 21)). The remains include a scalp lock with black hair, approximately 16 inches long, and one quarter of an inch wide. The upper end of the scalp lock is covered with sinew, yellow dyed deerskin, and tufts of red feather. No known individual was identified. No associated funerary objects are present. \n In 1956, Francis and Mary Crane purchased human remains representing a minimum of one individual from Kohlberg\\'s Antiques and Indian Arts. The remains were reportedly a part of the George A. Cuneo Collection of Southwestern and Plains Indian objects collected in the late 19th and early 20th centuries. In 1983, the human remains were donated by Mr. and Mrs. Crane and accessioned into the collections (AC.35D (CUI 23)). The remains include seven inches of black and grey hair and scalp with traces of red pigment and a row of perforations along one edge of it. No known individual was identified. No associated funerary objects are present. \n ", "h_d_ci": "Null", "determinations": "Determinations Made by the Denver Museum \n Officials of the Denver Museum of Nature & Science have determined that: \n \\xe2\\x80\\xa2 Based on non-destructive physical analysis and catalogue records, the human remains are Native American. \n \\xe2\\x80\\xa2 Pursuant to 25 U.S.C. 3001(2), a relationship of shared group identity cannot be reasonably traced between the Native American human remains and any present-day Indian Tribe. \n \\xe2\\x80\\xa2 According to final judgments of the Indian Claims Commission, the land from which the Native American human remains were removed is the aboriginal land of the Apache Tribe of Oklahoma; Arapahoe Tribe of the Wind River Reservation, Wyoming; Assiniboine and Sioux Tribes of the Fort Peck Indian Reservation, Montana; Big Pine Band of Owens Valley Paiute Shoshone Indians of the Big Pine Reservation, California; Blackfeet Tribe of the Blackfeet Indian Reservation of Montana; Caddo Nation of Oklahoma; Cheyenne and Arapaho Tribes, Oklahoma; Cheyenne River Sioux Tribe of the Cheyenne River Reservation, South Dakota; Citizen Potawatomi Nation, Oklahoma; Comanche Nation, Oklahoma; Crow Creek Sioux Tribe of the Crow Creek Reservation, South Dakota; Crow Tribe of Montana; Death Valley Timbi-Sha Shoshone Band of California; Duckwater Shoshone Tribe of the Duckwater Reservation, Nevada; Ely Shoshone Tribe of Nevada; Flandreau Santee Sioux Tribe of South Dakota; Forest County Potawatomi Community, Wisconsin; Fort McDermitt Paiute and Shoshone Tribes of the Fort McDermitt Indian Reservation, Nevada and Oregon; Fort Sill Apache Tribe of Oklahoma; Ho-Chunk Nation of Wisconsin; Iowa Tribe of Kansas and Nebraska; Iowa Tribe of Oklahoma; Jicarilla Apache Nation, New Mexico; Kickapoo Traditional Tribe of Texas; Kickapoo Tribe of Indians of the Kickapoo Reservation in Kansas; Kickapoo Tribe of Oklahoma; Kiowa Indian Tribe of Oklahoma; Lower Brule Sioux Tribe of the Lower Brule Reservation, South Dakota; Lower Sioux Indian Community in the State of Minnesota; Match-e-be-nash-she-wish Band of Pottawatomi Indians of Michigan; Mescalero Apache Tribe of the Mescalero Reservation, New Mexico; Nez Perce Tribe, Idaho; Northern Cheyenne Tribe of the Northern Cheyenne Indian Reservation, Montana; Nottawaseppi Huron Band of the Potawatomi, Michigan; Oglala Sioux Tribe of the Pine Ridge Reservation, South Dakota; Omaha Tribe of Nebraska; Osage Nation, Oklahoma; Otoe-Missouria Tribe of Indians, Oklahoma; Pawnee Nation of Oklahoma; Pokagon Band of Potawatomi Indians, Michigan and Indiana; Ponca Tribe of Indians of Oklahoma; Ponca Tribe of Nebraska; Prairie Band of Potawatomi Nation, Kansas; Prairie Island Indian Community in the State of Minnesota; Quapaw Tribe of Indians, Oklahoma; Rosebud Sioux Tribe of the Rosebud Indian Reservation, South Dakota; Sac & Fox Nation of Missouri in Kansas and Nebraska; Sac & Fox Nation, Oklahoma; Sac & Fox Tribe of the Mississippi in Iowa; San Carlos Apache Tribe of the San Carlos Reservation, Arizona; Santee Sioux Nation, Nebraska; Shakopee Mdewakanton Sioux Community of Minnesota; Sisseton-Wahpeton Oyate of the Lake Traverse Reservation, South Dakota; Southern Ute Indian Tribe of the Southern Ute Reservation, Colorado; Spirit Lake Tribe, North Dakota; Standing Rock Sioux Tribe of North & South Dakota; Tonto Apache Tribe of Arizona; Upper Sioux Community, Minnesota; Ute Indian Tribe of the Uintah & Ouray Reservation, Utah; Ute Mountain Tribe of the Ute Mountain Reservation, Colorado, New Mexico & Utah; White Mountain Apache Tribe of the Fort Apache Reservation, Arizona; Winnebago Tribe of Nebraska; and Yankton Sioux Tribe of South Dakota. \n \\xe2\\x80\\xa2 Multiple lines of evidence, including treaties, Acts of Congress, and Executive Orders, indicate that the land from which the Native American human remains were removed is the aboriginal land of the Absentee-Shawnee Tribe of Indians of Oklahoma; Apache Tribe of Oklahoma; Arapahoe Tribe of the Wind River Reservation, Wyoming; Assiniboine and Sioux Tribes of the Fort Peck Indian Reservation, Montana; Bad River Band of the Lake Superior Tribe of Chippewa Indians of the Bad River Reservation, Wisconsin; Bay Mills Indian Community, Michigan; Big Pine Band of Owens Valley Paiute Shoshone Indians of the Big Pine Reservation, California; Blackfeet Tribe of the Blackfeet Indian Reservation of Montana; Bois Forte Band (Nett Lake) of the Minnesota Chippewa Tribe, Minnesota; Caddo Nation of Oklahoma; Cherokee Nation, Oklahoma; Cheyenne and Arapaho Tribes, Oklahoma; Cheyenne River Sioux Tribe of the Cheyenne River Reservation, South Dakota; Chickasaw Nation, Oklahoma; Chippewa-Cree Indians of the Rocky Boy\\'s Reservation, Montana; Choctaw Nation of Oklahoma; Citizen Potawatomi Nation, Oklahoma; Comanche Nation, Oklahoma; Crow Creek Sioux Tribe of the Crow Creek Reservation, South Dakota; Crow Tribe of Montana; Death Valley Timbi-Sha Shoshone Band of California; Delaware Nation, Oklahoma; Duckwater Shoshone Tribe of the Duckwater Reservation, Nevada; Eastern Band of Cherokee Indians of North Carolina; Ely Shoshone Tribe of Nevada; Flandreau Santee Sioux Tribe of South Dakota; Fond du Lac Band of the Minnesota Chippewa Tribe, Minnesota; Forest County Potawatomi Community, Wisconsin; Fort Belknap Indian Community of the Fort Belknap Reservation of Montana; Fort McDermitt Paiute and Shoshone Tribes of the Fort McDermitt Indian Reservation, Nevada and Oregon; Fort Sill Apache Tribe of Oklahoma; Grand Portage Band of the Minnesota Chippewa Tribe, Minnesota; Grand Traverse Band of Ottawa and Chippewa Indians, Michigan; Hannahville Indian Community, Michigan; Ho-Chunk Nation of Wisconsin; Iowa Tribe of Kansas and Nebraska; Iowa Tribe of Oklahoma; Jena Band of Choctaw Indians, Louisiana; Jicarilla Apache Nation, New Mexico; Kaw Nation, Oklahoma; Keweenaw Bay Indian Community, Michigan; Kickapoo Traditional Tribe of Texas; Kickapoo Tribe of Indians of the Kickapoo Reservation in Kansas; Kickapoo Tribe of Oklahoma; Kiowa Indian Tribe of Oklahoma; Lac Courte Oreilles Band of Lake Superior Chippewa Indians of Wisconsin; Lac du Flambeau Band of Lake Superior Chippewa Indians of the Lac du Flambeau Reservation of Wisconsin; Lac Vieux Desert Band of Lake Superior Chippewa Indians, Michigan; Leech Lake Band of the Minnesota Chippewa Tribe, Minnesota; Lower Brule Sioux Tribe of the Lower Brule Reservation, South Dakota; Lower Sioux Indian Community in the State of Minnesota; Match-e-be-nash-she-wish Band of Pottawatomi Indians of Michigan; Menominee Indian Tribe of Wisconsin; Mescalero Apache Tribe of the Mescalero Reservation, New Mexico; Miami Tribe of Oklahoma; Mille Lacs Band of the Minnesota Chippewa Tribe, Minnesota; Minnesota Chippewa Tribe, Minnesota; Mississippi Band of Choctaw Indians, Mississippi; Muscogee (Creek) Nation, Oklahoma; Northern Cheyenne Tribe of the Northern Cheyenne Indian Reservation, Montana; Nottawaseppi Huron Band of the Potawatomi, Michigan; Oglala Sioux Tribe of the Pine Ridge Reservation, South Dakota; Omaha Tribe of Nebraska; Osage Nation, Oklahoma; Otoe-Missouria Tribe of Indians, Oklahoma; Ottawa Tribe of Oklahoma; Pawnee Nation of Oklahoma; Peoria Tribe of Indians of Oklahoma; Poarch Band of Creek Indians of Alabama; Pokagon Band of Potawatomi Indians, Michigan and Indiana; Ponca Tribe of Indians of Oklahoma; Ponca Tribe of Nebraska; Prairie Band of Potawatomi Nation, Kansas; Prairie Island Indian Community in the State of Minnesota; Quapaw Tribe of Indians, Oklahoma; Quechan Tribe of the Fort Yuma Indian Reservation, California & Arizona; Red Cliff Band of Lake Superior Chippewa Indians of Wisconsin; Red Lake Band of Chippewa Indians, Minnesota; Rosebud Sioux Tribe of the Rosebud Indian Reservation, South Dakota; Sac & Fox Nation of Missouri in Kansas and Nebraska; Sac & Fox Nation, Oklahoma; Sac & Fox Tribe of the Mississippi in Iowa; Saginaw Chippewa Indian Tribe of Michigan; San Carlos Apache Tribe of the San Carlos Reservation, Arizona; Santee Sioux Nation, Nebraska; Sault Ste. Marie Tribe of Chippewa Indians of Michigan; Seminole Nation of Oklahoma; Seminole Tribe of Florida (Dania, Big Cypress, Brighton, Hollywood & Tampa Reservations); Seneca Nation of New York; Seneca-Cayuga Tribe of Oklahoma; Shakopee Mdewakanton Sioux Community of Minnesota; Shawnee Tribe, Oklahoma; Shoshone Tribe of the Wind River Reservation, Wyoming; Sisseton-Wahpeton Oyate of the Lake Traverse Reservation, South Dakota; Sokaogon Chippewa Community, Wisconsin; Southern Ute Indian Tribe of the Southern Ute Reservation, Colorado; Spirit Lake Tribe, North Dakota; St. Croix Chippewa Indians of Wisconsin; Standing Rock Sioux Tribe of North & South Dakota; Te-Moak Tribe of Western Shoshone Indians of Nevada; Three Affiliated Tribes of the Fort Berthold Reservation, North Dakota; Tonawanda Band of Seneca Indians of New York; Tonto Apache Tribe of Arizona; Turtle Mountain Band of Chippewa Indians of North Dakota; United Keetoowah Band of Cherokee Indians in Oklahoma; Upper Sioux Community, Minnesota; Ute Indian Tribe of the Uintah & Ouray Reservation, Utah; Ute Mountain Tribe of the Ute Mountain Reservation, Colorado, New Mexico & Utah; White Earth Band of the Minnesota Chippewa Tribe, Minnesota; White Mountain Apache Tribe of the Fort Apache Reservation, Arizona; Wichita and Affiliated Tribes (Wichita, Keechi, Waco & Tawakonie), Oklahoma; Winnebago Tribe of Nebraska; Wyandotte Nation, Oklahoma; and Yankton Sioux Tribe of South Dakota. \n \\xe2\\x80\\xa2 Other credible lines of evidence, including consultation with Tribal representatives, indicate that the land from which the Native American human remains were removed is the aboriginal land of the Apache Tribe of Oklahoma; Arapahoe Tribe of the Wind River Reservation, Wyoming; Assiniboine and Sioux Tribes of the Fort Peck Indian Reservation, Montana; Blackfeet Tribe of the Blackfeet Indian Reservation of Montana; Bois Forte Band (Nett Lake) of the Minnesota Chippewa Tribe, Minnesota; Cheyenne and Arapaho Tribes, Oklahoma; Cheyenne River Sioux Tribe of the Cheyenne River Reservation, South Dakota; Choctaw Nation of Oklahoma; Comanche Nation, Oklahoma; Crow Creek Sioux Tribe of the Crow Creek Reservation, South Dakota; Crow Tribe of Montana; Flandreau Santee Sioux Tribe of South Dakota; Fond du Lac Band of the Minnesota Chippewa Tribe, Minnesota; Fort Sill Apache Tribe of Oklahoma; Ho-Chunk Nation of Wisconsin; Iowa Tribe of Kansas and Nebraska; Iowa Tribe of Oklahoma; Jicarilla Apache Nation, New Mexico; Kickapoo Tribe of Indians of the Kickapoo Reservation in Kansas; Kiowa Indian Tribe of Oklahoma; Leech Lake Band of the Minnesota Chippewa Tribe, Minnesota; Lower Brule Sioux Tribe of the Lower Brule Reservation, South Dakota; Lower Sioux Indian Community in the State of Minnesota; Menominee Indian Tribe of Wisconsin; Mescalero Apache Tribe of the Mescalero Reservation, New Mexico; Mille Lacs Band of the Minnesota Chippewa Tribe, Minnesota; Muscogee (Creek) Nation, Oklahoma; Nez Perce Tribe, Idaho; Northern Cheyenne Tribe of the Northern Cheyenne Indian Reservation, Montana; Oglala Sioux Tribe of the Pine Ridge Reservation, South Dakota; Ohkay Owingeh, New Mexico; Omaha Tribe of Nebraska; Osage Nation, Oklahoma; Otoe-Missouria Tribe of Indians, Oklahoma; Pawnee Nation of Oklahoma; Ponca Tribe of Indians of Oklahoma; Ponca Tribe of Nebraska; Prairie Band of Potawatomi Nation, Kansas; Pueblo of Cochiti, New Mexico; Pueblo of San Ildefonso, New Mexico; Pueblo of Santa Ana, New Mexico; Pueblo of Santa Clara, New Mexico; Quapaw Tribe of Indians, Oklahoma; Rosebud Sioux Tribe of the Rosebud Indian Reservation, South Dakota; Sac & Fox Nation of Missouri in Kansas and Nebraska; Sac & Fox Nation, Oklahoma; Sac & Fox Tribe of the Mississippi in Iowa; Santee Sioux Nation, Nebraska; Shakopee Mdewakanton Sioux Community of Minnesota; Shoshone Tribe of the Wind River Reservation, Wyoming; Sisseton-Wahpeton Oyate of the Lake Traverse Reservation, South Dakota; Southern Ute Indian Tribe of the Southern Ute Reservation, Colorado; Spirit Lake Tribe, North Dakota; Standing Rock Sioux Tribe of North & South Dakota; Three Affiliated Tribes of the Fort Berthold Reservation, North Dakota; Upper Sioux Community, Minnesota; Ute Indian Tribe of the Uintah & Ouray Reservation, Utah; Ute Mountain Tribe of the Ute Mountain Reservation, Colorado, New Mexico & Utah; White Earth Band of the Minnesota Chippewa Tribe, Minnesota; Wichita and Affiliated Tribes (Wichita, Keechi, Waco & Tawakonie), Oklahoma; Yankton Sioux Tribe of South Dakota; and the Zuni Tribe of the Zuni Reservation, New Mexico. \n \\xe2\\x80\\xa2 Pursuant to 25 U.S.C. 3001(9), the human remains described in this notice represent the physical remains of two individuals of Native American ancestry. \n \\xe2\\x80\\xa2 Pursuant to 43 CFR 10.11(c)(1), the disposition of the human remains is to The Tribes. \n ", "a_r_d": "Representatives of any Indian Tribe that believes itself to be culturally affiliated with the human remains or any other Indian Tribe that believes it satisfies the criteria in 43 CFR 10.11(c)(1) should contact Dr. Chip Colwell-Chanthaphonh, Denver Museum of Nature & Science, 2001 Colorado Blvd., Denver, CO 80205, telephone (303) 370-6378 by March 21, 2011. Disposition of the human remains to The Tribes may proceed after that date if no additional requestors come forward. \n The Denver Museum of Nature & Science is responsible for notifying The Tribes that this notice has been published. \n "}