{"index": "I_1159", "messy_full": "\\n      \\n        DEPARTMENT OF THE INTERIOR\\n        National Park Service\\n        [NPS-WASO-CRHPF-0511-7554; 2256-672]\\n        Information Collection Request Sent to the Office of Management and Budget (OMB) for Approval; Procedures for State, Tribal, and Local Government Historic Preservation Programs\\n        \\n          AGENCY:\\n          National Park Service, Interior.\\n        \\n        \\n          ACTION:\\n          Notice; request for comments.\\n        \\n        \\n          SUMMARY:\\n          We (National Park Service, NPS) have sent an Information Collection Request (ICR) to OMB for review and approval. We summarize the ICR below and describe the nature of the collection and the estimated burden and cost. This ICR is scheduled to expire on May 31, 2011. We may not conduct or sponsor and a person is not required to respond to a collection of information unless it displays a currently valid OMB control number. However, under OMB regulations, we may continue to conduct or sponsor this information collection while it is pending at OMB.\\n        \\n        \\n          DATES:\\n          You must submit comments on or before June 30, 2011.\\n        \\n        \\n          ADDRESSES:\\n\\n          Send your comments and suggestions on this information collection to the Desk Officer for the Department of the Interior at OMB-OIRA at (202) 395-5806 (fax) or OIRA_docket@omb.eop.gov (e-mail). Please send a copy of your comments to John W. Renaud, Project Coordinator, Historic Preservation Grants, Heritage Assistance Programs, NPS, 1849 C St., NW. (2256), Washington, DC 20240; or via fax at (202) 371-1961; or via e-mail at John_Renaud@nps.gov. Please also provide a copy of your comments to Rob Gordon, Information Collection Clearance Officer, National Park Service, MS 2605, 1201 Eye Street, NW., Washington, DC 20240 (mail), or robert_gordon@nps.gov (e-mail). Please include 1024-0038 in the subject line of your comments.\\n        \\n        \\n          FOR FURTHER INFORMATION CONTACT:\\n\\n          To request additional information about this ICR, contact John Renaud by mail or e-mail (see ADDRESSES) or by telephone at (202) 354-2066. You may review the ICR online at http://www.reginfo.gov. Follow the instructions to review Department of the Interior collections under review by OMB.\\n        \\n      \\n      \\n        SUPPLEMENTARY INFORMATION:\\n        \\n          OMB Control Number: 1024-0038.\\n        \\n          Title: Procedures for State, Tribal, and Local Government Historic Preservation Programs; 36 CFR part 61.\\n        \\n          Service Form Number: None.\\n        \\n          Type of Request: Extension of a currently approved collection.\\n        \\n          Description of Respondents: State, tribal, and local governments.\\n        \\n          Respondent\\'s Obligation: Required to obtain or retain a benefit.\\n        \\n          Frequency of Collection: Annually or on occasion.\\n        \\n          Estimated Number of Respondents: 1,924 (59 States, territories, and the District of Columbia; 100 tribes; and 1,765 certified local governments).\\n        \\n          Estimated Annual Nonhour Burden Cost: $340,474, primarily for photocopying, mailing, office supplies, travel expenses, etc.\\n        \\n        \\n          \\xe2\\x80\\x83\\n          \\n            Activity\\n            Annualnumber of\\n              responses\\n            \\n            Completion time perresponse \\n              (hours)\\n            \\n            Total annual burden hours\\n          \\n          \\n            Local Government Certification Application\\n            55\\n            21.40\\n            1,177\\n          \\n          \\n            Certified Local Government Monitoring\\n            1,765\\n            7.00\\n            12,355\\n          \\n          \\n            Certified Local Government Evaluations\\n            441\\n            13.33\\n            5,879\\n          \\n          \\n            Baseline Questionnaire for CLGs\\n            250\\n            .59\\n            148\\n          \\n          \\n            Annual Achievements Report for CLGs\\n            900\\n            2.20\\n            1,980\\n          \\n          \\n            State Inventory Maintenance\\n            26,904\\n            .46\\n            12,376\\n          \\n          \\n            State Review and Compliance Task Tracking\\n            25,370\\n            .17\\n            4,313\\n          \\n          \\n            State Program Review\\n            14\\n            90.00\\n            1,260\\n          \\n          \\n            State Cumulative Products Table\\n            59\\n            7.46\\n            440\\n          \\n          \\n            State Organization Chart and Staffing Summary\\n            30\\n            1.15\\n            35\\n          \\n          \\n            State Anticipated Activities List\\n            30\\n            7.47\\n            224\\n          \\n          \\n            State Project Notification\\n            30\\n            1.37\\n            41\\n          \\n          \\n            State Final Project Report\\n            30\\n            1.03\\n            31\\n          \\n          \\n            State Project/Activity Database Report\\n            59\\n            7.14\\n            421\\n          \\n          \\n            State Sources of Non-Federal Matching Share Report\\n            52\\n            4.28\\n            223\\n          \\n          \\n            State Unexpended Funds Carryover Table and Statement\\n            59\\n            .08\\n            5\\n          \\n          \\n            State Significant Preservation Accomplishments Summary\\n            59\\n            2.09\\n            123\\n          \\n          \\n            Annual Achievements Report for States\\n            25\\n            2.22\\n            56\\n          \\n          \\n            Tribal Historic Preservation Office (THPO) Grants Product Summary Page\\n            100\\n            12.00\\n            1,200\\n          \\n          \\n            THPO Unexpected Funds Carryover Statement\\n            50\\n            7.08\\n            354\\n          \\n          \\n            THPO Annual Report\\n            100\\n            17.49\\n            1,749\\n          \\n          \\n            Totals\\n            56,382\\n            \\n            44,390\\n          \\n        \\n        \\n          Abstract: This set of information collection requirements has an impact on State, tribal, and local governments that wish to participate formally in the National Historic Preservation Partnership (NHPP) Program, and State and tribal governments that wish to apply for Historic Preservation Fund (HPF) grants. The National Historic Preservation Act (16 U.S.C. 470 et seq.), as amended, established these programs. Implementing regulations at 36 CFR part 61 detail the processes for approval of State and tribal programs, the certification of local governments, and the monitoring and evaluation of State and certified local government programs. We developed the information collections associated with 36 CFR part 61 in consultation with State, tribal, and local government partners.\\n\\n        The NPS uses the information to ensure compliance with the National Historic Preservation Act, as amended (16 USC 470 et seq.), as well as governmentwide grant requirements and Department of the Interior regulations at 43 CFR part 12. This information collection also produces performance data that we use to assess program effectiveness.\\n        \\n          Comments: On March 25, 2011, we published in the Federal Register (76 FR 16813) a notice of our intent to request that OMB renew approval for this information collection. In that notice, we solicited comments for 60 days, ending on May 24, 2011. We did not receive any comments.\\n        We again invite comments concerning this information collection on:\\n        \\xe2\\x80\\xa2 Whether or not the collection of information is necessary, including whether or not the information will have practical utility;\\n        \\xe2\\x80\\xa2 The accuracy of our estimate of the burden for this collection of information;\\n        \\xe2\\x80\\xa2 Ways to enhance the quality, utility, and clarity of the information to be collected; and\\n        \\xe2\\x80\\xa2 Ways to minimize the burden of the collection of information on respondents.\\n        Comments that you submit in response to this notice are a matter of public record. Before including your address, phone number, e-mail address, or other personal identifying information in your comment, you should be aware that your entire comment, including your personal identifying information, may be made publicly available at any time. While you can ask OMB in your comment to withhold your personal identifying information from public review, we cannot guarantee that it will be done.\\n        \\n          Rob Gordon,\\n          Information Collection Clearance Officer, National Park Service.\\n        \\n      \\n      [FR Doc. 2011-13378 Filed 5-27-11; 8:45 am]\\n      BILLING CODE 4310-52-P\\n    ", "agency1": "DEPARTMENT OF THE INTERIOR", "sub_agency1": "National Park Service", "dep_doc": "[NPS-WASO-CRHPF-0511-7554; 2256-672]", "subject": "Information Collection Request Sent to the Office of Management and Budget (OMB) for Approval; Procedures for State, Tribal, and Local Government Historic Preservation Programs", "agency2": "National Park Service, Interior.", "action": "Notice; request for comments.", "summary": "We (National Park Service, NPS) have sent an Information Collection Request (ICR) to OMB for review and approval. We summarize the ICR below and describe the nature of the collection and the estimated burden and cost. This ICR is scheduled to expire on May 31, 2011. We may not conduct or sponsor and a person is not required to respond to a collection of information unless it displays a currently valid OMB control number. However, under OMB regulations, we may continue to conduct or sponsor this information collection while it is pending at OMB.", "dates": "You must submit comments on or before June 30, 2011.", "addresses": "Send your comments and suggestions on this information collection to the Desk Officer for the Department of the Interior at OMB-OIRA at (202) 395-5806 (fax) or OIRA_docket@omb.eop.gov (e-mail). Please send a copy of your comments to John W. Renaud, Project Coordinator, Historic Preservation Grants, Heritage Assistance Programs, NPS, 1849 C St., NW. (2256), Washington, DC 20240; or via fax at (202) 371-1961; or via e-mail at John_Renaud@nps.gov. Please also provide a copy of your comments to Rob Gordon, Information Collection Clearance Officer, National Park Service, MS 2605, 1201 Eye Street, NW., Washington, DC 20240 (mail), or robert_gordon@nps.gov (e-mail). Please include 1024-0038 in the subject line of your comments.", "signature_dated": "Null", "signature_name": "Rob Gordon,", "signature_title": "Information Collection Clearance Officer, National Park Service.", "fr_doc": "[FR Doc. 2011-13378 Filed 5-27-11; 8:45 am]", "billing_code": "BILLING CODE 4310-52-P", "supp_info": "SUPPLEMENTARY INFORMATION: \n \\n          OMB Control Number: 1024-0038. \n \\n          Title: Procedures for State, Tribal, and Local Government Historic Preservation Programs; 36 CFR part 61. \n \\n          Service Form Number: None. \n \\n          Type of Request: Extension of a currently approved collection. \n \\n          Description of Respondents: State, tribal, and local governments. \n \\n          Respondent\\'s Obligation: Required to obtain or retain a benefit. \n \\n          Frequency of Collection: Annually or on occasion. \n \\n          Estimated Number of Respondents: 1,924 (59 States, territories, and the District of Columbia; 100 tribes; and 1,765 certified local governments). \n \\n          Estimated Annual Nonhour Burden Cost: $340,474, primarily for photocopying, mailing, office supplies, travel expenses, etc.\\n         \n \\n          Abstract: This set of information collection requirements has an impact on State, tribal, and local governments that wish to participate formally in the National Historic Preservation Partnership (NHPP) Program, and State and tribal governments that wish to apply for Historic Preservation Fund (HPF) grants. The National Historic Preservation Act (16 U.S.C. 470 et seq.), as amended, established these programs. Implementing regulations at 36 CFR part 61 detail the processes for approval of State and tribal programs, the certification of local governments, and the monitoring and evaluation of State and certified local government programs. We developed the information collections associated with 36 CFR part 61 in consultation with State, tribal, and local government partners. \n The NPS uses the information to ensure compliance with the National Historic Preservation Act, as amended (16 USC 470 et seq.), as well as governmentwide grant requirements and Department of the Interior regulations at 43 CFR part 12. This information collection also produces performance data that we use to assess program effectiveness. \n \\n          Comments: On March 25, 2011, we published in the Federal Register (76 FR 16813) a notice of our intent to request that OMB renew approval for this information collection. In that notice, we solicited comments for 60 days, ending on May 24, 2011. We did not receive any comments. \n We again invite comments concerning this information collection on: \n \\xe2\\x80\\xa2 Whether or not the collection of information is necessary, including whether or not the information will have practical utility; \n \\xe2\\x80\\xa2 The accuracy of our estimate of the burden for this collection of information; \n \\xe2\\x80\\xa2 Ways to enhance the quality, utility, and clarity of the information to be collected; and \n \\xe2\\x80\\xa2 Ways to minimize the burden of the collection of information on respondents. \n Comments that you submit in response to this notice are a matter of public record. Before including your address, phone number, e-mail address, or other personal identifying information in your comment, you should be aware that your entire comment, including your personal identifying information, may be made publicly available at any time. While you can ask OMB in your comment to withhold your personal identifying information from public review, we cannot guarantee that it will be done. \n ", "consultation": "Null", "h_d_r": "Null", "h_d_ci": "Null", "determinations": "Null", "a_r_d": "Null"}