{"index": "I_1111", "messy_full": "\\n      \\n        DEPARTMENT OF THE INTERIOR\\n        National Park Service\\n        [2253-665]\\n        Notice of Inventory Completion: Minnesota Indian Affairs Council, Bemidji, MN\\n        \\n          AGENCY:\\n          National Park Service, Interior.\\n        \\n        \\n          ACTION:\\n          Notice.\\n        \\n        \\n          SUMMARY:\\n          The Minnesota Indian Affairs Council has completed an inventory of human remains in consultation with the appropriate Indian tribes, and has determined that there is no cultural affiliation between the remains and any present-day Indian tribe. Representatives of any Indian tribe that believes itself to be culturally affiliated with the human remains may contact the Minnesota Indian Affairs Council. Disposition of the human remains to the Indian tribes stated below may occur if no additional requestors come forward.\\n        \\n        \\n          DATES:\\n          Representatives of any Indian tribe that believes it has a cultural affiliation with the human remains should contact the Minnesota Indian Affairs Council at the address below by January 4, 2012.\\n        \\n        \\n          ADDRESSES:\\n          James L. (Jim) Jones, Cultural Resource Director, Minnesota Indian Affairs Council, 3801 Bemidji Avenue NW., Suite 5, Bemidji, MN 56601, telephone (218) 755-3223.\\n        \\n      \\n      \\n        SUPPLEMENTARY INFORMATION:\\n        Notice is here given in accordance with the Native American Graves Protection and Repatriation Act (NAGPRA), 25 U.S.C. 3003, of the completion of an inventory of human remains in the possession of the Minnesota Indian Affairs Council (MIAC). The human remains were removed from Marshall County, MN.\\n        This notice is published as part of the National Park Service\\'s administrative responsibilities under NAGPRA, 25 U.S.C. 3003(d)(3) and 43 CFR 10.11(d). The determinations in this notice are the sole responsibility of the museum, institution, or Federal agency that has control of the Native American human remains. The National Park Service is not responsible for the determinations in this notice.\\n        Consultation\\n        A detailed assessment of the human remains was made by the MIAC professional staff in consultation with representatives of the Lower Sioux Indian Community in the State of Minnesota; Prairie Island Indian Community in the State of Minnesota; Red Lake Band of Chippewa Indians, Minnesota; Sisseton-Wahpeton Oyate of the Lake Traverse Reservation, South Dakota; Turtle Mountain Band of Chippewa Indians of North Dakota (hereinafter referred to as \\xe2\\x80\\x9cThe Tribes\\xe2\\x80\\x9d).\\n        History and Description of the Remains\\n        In 1998, human remains representing, at minimum, three individuals were recovered from site 21-MA-70, Wright Quarry, in Marshall County during gravel quarrying operations by the Marshall County Highway Department. In 1999, the human remains were transferred to the Minnesota Office of the State Archaeologist. In 2002, the human remains were transferred to the MIAC (H375). No known individuals were identified. No associated funerary objects are present.\\n        Examination of the site context by professional staff of the Minnesota Office of the State Archaeologist suggests a pre-contact burial site. Additionally, a number of pre-historic sites are recorded in the immediate vicinity. Cranial, dental and femora morphology identify the human remains as American Indian. These human remains have no archeological classification and cannot be associated with any present-day Indian tribe.\\n        In 2009, human remains representing, at minimum, one individual were unearthed from an unknown site in Warren, MN, during new home construction. The human remains were transferred to the Marshall County Sheriff\\'s Department, to the Minnesota Bureau of Criminal Apprehension Laboratory, and then to the Human Identification Laboratory at the University of North Dakota for identification. The human remains were then transferred to the MIAC (H443). No known individuals were identified. No associated funerary objects are present.\\n        The burial context and morphology of the human remains suggest identification as pre-contact American Indian. These human remains have no archeological classification and cannot be associated with any present-day Indian tribe.\\n        Determinations Made by the Minnesota Indian Affairs Council\\n        Officials of the MIAC have determined that:\\n        \\xe2\\x80\\xa2 Based on non-destructive physical analysis and catalogue records, the human remains are Native American.\\n        \\xe2\\x80\\xa2 Pursuant to 25 U.S.C. 3001(2), a relationship of shared group identity cannot be reasonably traced between the Native American human remains and any present-day Indian tribe.\\n        \\xe2\\x80\\xa2 According to final judgments of the Indian Claims Commission, the land from which the Native American human remains were removed is the aboriginal land of The Tribes.\\n        \\xe2\\x80\\xa2 Pursuant to 25 U.S.C. 3001(9), the human remains described in this notice represent the physical remains of four individuals of Native American ancestry.\\n        \\xe2\\x80\\xa2 Pursuant to 43 CFR 10.11(c)(1), the disposition of the human remains is to The Tribes.\\n        Additional Requestors and Disposition\\n\\n        Representatives of any Indian tribe that believes itself to be culturally affiliated with the human remains or any other Indian tribe that believes it satisfies the criteria in 43 CFR 10.11(c)(1) should contact James L. (Jim) Jones, Cultural Resource Director, Minnesota Indian Affairs Council, 3801 Bemidji Avenue NW., Suite 5, Bemidji, MN 56601, telephone (218) 755-3223, before January 4, 2012. Disposition of the human remains to The Tribes may proceed after that date if no additional requestors come forward.\\n        The Minnesota Indian Affairs Council is responsible for notifying The Tribes that this notice has been published.\\n        \\n          Dated: November 29, 2011.\\n          Sherry Hutt,\\n          Manager, National NAGPRA Program. \\n        \\n      \\n      [FR Doc. 2011-31071 Filed 12-2-11; 8:45 am]\\n      BILLING CODE 4312-50-P\\n    ", "agency1": "DEPARTMENT OF THE INTERIOR", "sub_agency1": "National Park Service", "dep_doc": "[2253-665]", "subject": "Notice of Inventory Completion: Minnesota Indian Affairs Council, Bemidji, MN", "agency2": "National Park Service, Interior.", "action": "Notice.", "summary": "The Minnesota Indian Affairs Council has completed an inventory of human remains in consultation with the appropriate Indian tribes, and has determined that there is no cultural affiliation between the remains and any present-day Indian tribe. Representatives of any Indian tribe that believes itself to be culturally affiliated with the human remains may contact the Minnesota Indian Affairs Council. Disposition of the human remains to the Indian tribes stated below may occur if no additional requestors come forward.", "dates": "Representatives of any Indian tribe that believes it has a cultural affiliation with the human remains should contact the Minnesota Indian Affairs Council at the address below by January 4, 2012.", "addresses": "James L. (Jim) Jones, Cultural Resource Director, Minnesota Indian Affairs Council, 3801 Bemidji Avenue NW., Suite 5, Bemidji, MN 56601, telephone (218) 755-3223.", "signature_dated": "Dated: November 29, 2011.", "signature_name": "Sherry Hutt,", "signature_title": "Manager, National NAGPRA Program. ", "fr_doc": "[FR Doc. 2011-31071 Filed 12-2-11; 8:45 am]", "billing_code": "BILLING CODE 4312-50-P", "supp_info": "SUPPLEMENTARY INFORMATION: \n Notice is here given in accordance with the Native American Graves Protection and Repatriation Act (NAGPRA), 25 U.S.C. 3003, of the completion of an inventory of human remains in the possession of the Minnesota Indian Affairs Council (MIAC). The human remains were removed from Marshall County, MN. \n This notice is published as part of the National Park Service\\'s administrative responsibilities under NAGPRA, 25 U.S.C. 3003(d)(3) and 43 CFR 10.11(d). The determinations in this notice are the sole responsibility of the museum, institution, or Federal agency that has control of the Native American human remains. The National Park Service is not responsible for the determinations in this notice. \n Consultation \n A detailed assessment of the human remains was made by the MIAC professional staff in consultation with representatives of the Lower Sioux Indian Community in the State of Minnesota; Prairie Island Indian Community in the State of Minnesota; Red Lake Band of Chippewa Indians, Minnesota; Sisseton-Wahpeton Oyate of the Lake Traverse Reservation, South Dakota; Turtle Mountain Band of Chippewa Indians of North Dakota (hereinafter referred to as \\xe2\\x80\\x9cThe Tribes\\xe2\\x80\\x9d). \n History and Description of the Remains \n In 1998, human remains representing, at minimum, three individuals were recovered from site 21-MA-70, Wright Quarry, in Marshall County during gravel quarrying operations by the Marshall County Highway Department. In 1999, the human remains were transferred to the Minnesota Office of the State Archaeologist. In 2002, the human remains were transferred to the MIAC (H375). No known individuals were identified. No associated funerary objects are present. \n Examination of the site context by professional staff of the Minnesota Office of the State Archaeologist suggests a pre-contact burial site. Additionally, a number of pre-historic sites are recorded in the immediate vicinity. Cranial, dental and femora morphology identify the human remains as American Indian. These human remains have no archeological classification and cannot be associated with any present-day Indian tribe. \n In 2009, human remains representing, at minimum, one individual were unearthed from an unknown site in Warren, MN, during new home construction. The human remains were transferred to the Marshall County Sheriff\\'s Department, to the Minnesota Bureau of Criminal Apprehension Laboratory, and then to the Human Identification Laboratory at the University of North Dakota for identification. The human remains were then transferred to the MIAC (H443). No known individuals were identified. No associated funerary objects are present. \n The burial context and morphology of the human remains suggest identification as pre-contact American Indian. These human remains have no archeological classification and cannot be associated with any present-day Indian tribe. \n Determinations Made by the Minnesota Indian Affairs Council \n Officials of the MIAC have determined that: \n \\xe2\\x80\\xa2 Based on non-destructive physical analysis and catalogue records, the human remains are Native American. \n \\xe2\\x80\\xa2 Pursuant to 25 U.S.C. 3001(2), a relationship of shared group identity cannot be reasonably traced between the Native American human remains and any present-day Indian tribe. \n \\xe2\\x80\\xa2 According to final judgments of the Indian Claims Commission, the land from which the Native American human remains were removed is the aboriginal land of The Tribes. \n \\xe2\\x80\\xa2 Pursuant to 25 U.S.C. 3001(9), the human remains described in this notice represent the physical remains of four individuals of Native American ancestry. \n \\xe2\\x80\\xa2 Pursuant to 43 CFR 10.11(c)(1), the disposition of the human remains is to The Tribes. \n Additional Requestors and Disposition \n Representatives of any Indian tribe that believes itself to be culturally affiliated with the human remains or any other Indian tribe that believes it satisfies the criteria in 43 CFR 10.11(c)(1) should contact James L. (Jim) Jones, Cultural Resource Director, Minnesota Indian Affairs Council, 3801 Bemidji Avenue NW., Suite 5, Bemidji, MN 56601, telephone (218) 755-3223, before January 4, 2012. Disposition of the human remains to The Tribes may proceed after that date if no additional requestors come forward. \n The Minnesota Indian Affairs Council is responsible for notifying The Tribes that this notice has been published. \n ", "consultation": "A detailed assessment of the human remains was made by the MIAC professional staff in consultation with representatives of the Lower Sioux Indian Community in the State of Minnesota; Prairie Island Indian Community in the State of Minnesota; Red Lake Band of Chippewa Indians, Minnesota; Sisseton-Wahpeton Oyate of the Lake Traverse Reservation, South Dakota; Turtle Mountain Band of Chippewa Indians of North Dakota (hereinafter referred to as \\xe2\\x80\\x9cThe Tribes\\xe2\\x80\\x9d). \n ", "h_d_r": "In 1998, human remains representing, at minimum, three individuals were recovered from site 21-MA-70, Wright Quarry, in Marshall County during gravel quarrying operations by the Marshall County Highway Department. In 1999, the human remains were transferred to the Minnesota Office of the State Archaeologist. In 2002, the human remains were transferred to the MIAC (H375). No known individuals were identified. No associated funerary objects are present. \n Examination of the site context by professional staff of the Minnesota Office of the State Archaeologist suggests a pre-contact burial site. Additionally, a number of pre-historic sites are recorded in the immediate vicinity. Cranial, dental and femora morphology identify the human remains as American Indian. These human remains have no archeological classification and cannot be associated with any present-day Indian tribe. \n In 2009, human remains representing, at minimum, one individual were unearthed from an unknown site in Warren, MN, during new home construction. The human remains were transferred to the Marshall County Sheriff\\'s Department, to the Minnesota Bureau of Criminal Apprehension Laboratory, and then to the Human Identification Laboratory at the University of North Dakota for identification. The human remains were then transferred to the MIAC (H443). No known individuals were identified. No associated funerary objects are present. \n The burial context and morphology of the human remains suggest identification as pre-contact American Indian. These human remains have no archeological classification and cannot be associated with any present-day Indian tribe. \n ", "h_d_ci": "Null", "determinations": "Determinations Made by the Minnesota Indian Affairs Council \n Officials of the MIAC have determined that: \n \\xe2\\x80\\xa2 Based on non-destructive physical analysis and catalogue records, the human remains are Native American. \n \\xe2\\x80\\xa2 Pursuant to 25 U.S.C. 3001(2), a relationship of shared group identity cannot be reasonably traced between the Native American human remains and any present-day Indian tribe. \n \\xe2\\x80\\xa2 According to final judgments of the Indian Claims Commission, the land from which the Native American human remains were removed is the aboriginal land of The Tribes. \n \\xe2\\x80\\xa2 Pursuant to 25 U.S.C. 3001(9), the human remains described in this notice represent the physical remains of four individuals of Native American ancestry. \n \\xe2\\x80\\xa2 Pursuant to 43 CFR 10.11(c)(1), the disposition of the human remains is to The Tribes. \n ", "a_r_d": "Representatives of any Indian tribe that believes itself to be culturally affiliated with the human remains or any other Indian tribe that believes it satisfies the criteria in 43 CFR 10.11(c)(1) should contact James L. (Jim) Jones, Cultural Resource Director, Minnesota Indian Affairs Council, 3801 Bemidji Avenue NW., Suite 5, Bemidji, MN 56601, telephone (218) 755-3223, before January 4, 2012. Disposition of the human remains to The Tribes may proceed after that date if no additional requestors come forward. \n The Minnesota Indian Affairs Council is responsible for notifying The Tribes that this notice has been published. \n "}