{"index": "I_1130", "messy_full": "\\n      \\n        DEPARTMENT OF THE INTERIOR\\n        National Park Service\\n        [2253-665]\\n        Notice of Inventory Completion: Maxwell Museum of Anthropology, University of New Mexico, Albuquerque, NM\\n        \\n          AGENCY:\\n          National Park Service, Interior.\\n        \\n        \\n          ACTION:\\n          Notice.\\n        \\n        \\n          SUMMARY:\\n          The Maxwell Museum of Anthropology, University of New Mexico has completed an inventory of human remains, in consultation with the appropriate Indian tribe, and has determined that there is a cultural affiliation between the human remains and a present-day Indian tribe. Representatives of any Indian tribe that believes itself to be culturally affiliated with the human remains may contact the Maxwell Museum of Anthropology, University of New Mexico. Repatriation of the human remains to the Indian tribe stated below may occur if no additional claimants come forward.\\n        \\n        \\n          DATES:\\n          Representatives of any Indian tribe that believes it has a cultural affiliation with the human remains should contact the Maxwell Museum of Anthropology, University of New Mexico at the address below by October 13, 2011.\\n        \\n        \\n          ADDRESSES:\\n          Heather Edgar, Curator of Human Osteology, Maxwell Museum of Anthropology, University of New Mexico, MSC01 1050, 1 University of New Mexico, Albuquerque, NM 87131, telephone (505) 277-4415.\\n        \\n      \\n      \\n        SUPPLEMENTARY INFORMATION:\\n        Notice is here given in accordance with the Native American Graves Protection and Repatriation Act (NAGPRA), 25 U.S.C. 3003, of the completion of an inventory of human remains in the possession of Maxwell Museum of Anthropology, University of New Mexico, Albuquerque, NM. The human remains were removed from Sandoval County, NM.\\n        This notice is published as part of the National Park Service\\'s administrative responsibilities under NAGPRA, 25 U.S.C. 3003(d)(3). The determinations in this notice are the sole responsibility of the museum, institution, or Federal agency that has control of the Native American human remains. The National Park Service is not responsible for the determinations in this notice.\\n        Consultation\\n        A detailed assessment of the human remains was made by Maxwell Museum of Anthropology, University of New Mexico professional staff in consultation with representatives of the Pueblo of Jemez, New Mexico.\\n        History and Description of the Remains\\n        Between the 1930s and 1940s, human remains representing a minimum of 189 individuals were removed from the Unshagi site (LA 123), Sandoval County, NM, during excavations by University of New Mexico field schools. The human remains were accessioned by the museum between 1973 and 1975. No known individuals were identified. No associated funerary objects are present.\\n        Between the 1930s and 1940s, human remains representing a minimum of 78 individuals were removed from the Guisewa site (LA 679), Sandoval County, NM, during excavations by University of New Mexico field schools. The human remains were accessioned by the museum between 1973 and 1975. No known individuals were identified. No associated funerary objects are present.\\n        Between the 1930s and 1940s, human remains representing a minimum of 65 individuals were removed from the Nonishagi site (LA 541), Sandoval County, NM, during excavations by University of New Mexico field schools. The human remains were accessioned by the museum between 1973 and 1975. No known individuals were identified. No associated funerary objects are present.\\n        At unknown dates, human remains representing a minimum of 84 individuals were removed from various sites located in the area of \\xe2\\x80\\x9cJemez.\\xe2\\x80\\x9d No known individuals were identified. No associated funerary objects are present.\\n        The human remains are identified as ancestral Jemez because they came from Puebloan sites of the upper Jemez River drainage. Populations that inhabited these sites are linked by Native oral tradition, Euro-American records, and archeological evidence to members of the present-day Pueblo of Jemez, New Mexico.\\n        Determinations Made by the Maxwell Museum of Anthropology, University of New Mexico\\n        Officials of the Maxwell Museum of Anthropology, University of New Mexico have determined that:\\n        \\xe2\\x80\\xa2 Pursuant to 25 U.S.C. 3001(9), the human remains described above represent the physical remains of at least 416 individuals of Native American ancestry.\\n        \\xe2\\x80\\xa2 Pursuant to 25 U.S.C. 3001(2), there is a relationship of shared group identity that can be reasonably traced between the Native American human remains and the Pueblo of Jemez, New Mexico.\\n        Additional Requestors and Disposition\\n\\n        Representatives of any other Indian tribe that believes itself to be culturally affiliated with the human remains should contact Heather Edgar, Curator of Human Osteology, Maxwell Museum of Anthropology, University of New Mexico, MSC01 1050, 1 University of New Mexico, Albuquerque, NM 87131, telephone (505) 277-4415, before October 13, 2011. Repatriation of the human remains to the Pueblo of Jemez, New Mexico, may proceed after that date if no additional claimants come forward.\\n        The Maxwell Museum of Anthropology, University of New Mexico is responsible for notifying the Pueblo of Jemez, New Mexico, that this notice has been published.\\n        \\n          Dated: September 7, 2011.\\n          Sherry Hutt,\\n          Manager, National NAGPRA Program.\\n        \\n      \\n      [FR Doc. 2011-23290 Filed 9-12-11; 8:45 am]\\n      BILLING CODE 4312-50-P\\n    ", "agency1": "DEPARTMENT OF THE INTERIOR", "sub_agency1": "National Park Service", "dep_doc": "[2253-665]", "subject": "Notice of Inventory Completion: Maxwell Museum of Anthropology, University of New Mexico, Albuquerque, NM", "agency2": "National Park Service, Interior.", "action": "Notice.", "summary": "The Maxwell Museum of Anthropology, University of New Mexico has completed an inventory of human remains, in consultation with the appropriate Indian tribe, and has determined that there is a cultural affiliation between the human remains and a present-day Indian tribe. Representatives of any Indian tribe that believes itself to be culturally affiliated with the human remains may contact the Maxwell Museum of Anthropology, University of New Mexico. Repatriation of the human remains to the Indian tribe stated below may occur if no additional claimants come forward.", "dates": "Representatives of any Indian tribe that believes it has a cultural affiliation with the human remains should contact the Maxwell Museum of Anthropology, University of New Mexico at the address below by October 13, 2011.", "addresses": "Heather Edgar, Curator of Human Osteology, Maxwell Museum of Anthropology, University of New Mexico, MSC01 1050, 1 University of New Mexico, Albuquerque, NM 87131, telephone (505) 277-4415.", "signature_dated": "Dated: September 7, 2011.", "signature_name": "Sherry Hutt,", "signature_title": "Manager, National NAGPRA Program.", "fr_doc": "[FR Doc. 2011-23290 Filed 9-12-11; 8:45 am]", "billing_code": "BILLING CODE 4312-50-P", "supp_info": "SUPPLEMENTARY INFORMATION: \n Notice is here given in accordance with the Native American Graves Protection and Repatriation Act (NAGPRA), 25 U.S.C. 3003, of the completion of an inventory of human remains in the possession of Maxwell Museum of Anthropology, University of New Mexico, Albuquerque, NM. The human remains were removed from Sandoval County, NM. \n This notice is published as part of the National Park Service\\'s administrative responsibilities under NAGPRA, 25 U.S.C. 3003(d)(3). The determinations in this notice are the sole responsibility of the museum, institution, or Federal agency that has control of the Native American human remains. The National Park Service is not responsible for the determinations in this notice. \n Consultation \n A detailed assessment of the human remains was made by Maxwell Museum of Anthropology, University of New Mexico professional staff in consultation with representatives of the Pueblo of Jemez, New Mexico. \n History and Description of the Remains \n Between the 1930s and 1940s, human remains representing a minimum of 189 individuals were removed from the Unshagi site (LA 123), Sandoval County, NM, during excavations by University of New Mexico field schools. The human remains were accessioned by the museum between 1973 and 1975. No known individuals were identified. No associated funerary objects are present. \n Between the 1930s and 1940s, human remains representing a minimum of 78 individuals were removed from the Guisewa site (LA 679), Sandoval County, NM, during excavations by University of New Mexico field schools. The human remains were accessioned by the museum between 1973 and 1975. No known individuals were identified. No associated funerary objects are present. \n Between the 1930s and 1940s, human remains representing a minimum of 65 individuals were removed from the Nonishagi site (LA 541), Sandoval County, NM, during excavations by University of New Mexico field schools. The human remains were accessioned by the museum between 1973 and 1975. No known individuals were identified. No associated funerary objects are present. \n At unknown dates, human remains representing a minimum of 84 individuals were removed from various sites located in the area of \\xe2\\x80\\x9cJemez.\\xe2\\x80\\x9d No known individuals were identified. No associated funerary objects are present. \n The human remains are identified as ancestral Jemez because they came from Puebloan sites of the upper Jemez River drainage. Populations that inhabited these sites are linked by Native oral tradition, Euro-American records, and archeological evidence to members of the present-day Pueblo of Jemez, New Mexico. \n Determinations Made by the Maxwell Museum of Anthropology, University of New Mexico \n Officials of the Maxwell Museum of Anthropology, University of New Mexico have determined that: \n \\xe2\\x80\\xa2 Pursuant to 25 U.S.C. 3001(9), the human remains described above represent the physical remains of at least 416 individuals of Native American ancestry. \n \\xe2\\x80\\xa2 Pursuant to 25 U.S.C. 3001(2), there is a relationship of shared group identity that can be reasonably traced between the Native American human remains and the Pueblo of Jemez, New Mexico. \n Additional Requestors and Disposition \n Representatives of any other Indian tribe that believes itself to be culturally affiliated with the human remains should contact Heather Edgar, Curator of Human Osteology, Maxwell Museum of Anthropology, University of New Mexico, MSC01 1050, 1 University of New Mexico, Albuquerque, NM 87131, telephone (505) 277-4415, before October 13, 2011. Repatriation of the human remains to the Pueblo of Jemez, New Mexico, may proceed after that date if no additional claimants come forward. \n The Maxwell Museum of Anthropology, University of New Mexico is responsible for notifying the Pueblo of Jemez, New Mexico, that this notice has been published. \n ", "consultation": "A detailed assessment of the human remains was made by Maxwell Museum of Anthropology, University of New Mexico professional staff in consultation with representatives of the Pueblo of Jemez, New Mexico. \n ", "h_d_r": "Between the 1930s and 1940s, human remains representing a minimum of 189 individuals were removed from the Unshagi site (LA 123), Sandoval County, NM, during excavations by University of New Mexico field schools. The human remains were accessioned by the museum between 1973 and 1975. No known individuals were identified. No associated funerary objects are present. \n Between the 1930s and 1940s, human remains representing a minimum of 78 individuals were removed from the Guisewa site (LA 679), Sandoval County, NM, during excavations by University of New Mexico field schools. The human remains were accessioned by the museum between 1973 and 1975. No known individuals were identified. No associated funerary objects are present. \n Between the 1930s and 1940s, human remains representing a minimum of 65 individuals were removed from the Nonishagi site (LA 541), Sandoval County, NM, during excavations by University of New Mexico field schools. The human remains were accessioned by the museum between 1973 and 1975. No known individuals were identified. No associated funerary objects are present. \n At unknown dates, human remains representing a minimum of 84 individuals were removed from various sites located in the area of \\xe2\\x80\\x9cJemez.\\xe2\\x80\\x9d No known individuals were identified. No associated funerary objects are present. \n The human remains are identified as ancestral Jemez because they came from Puebloan sites of the upper Jemez River drainage. Populations that inhabited these sites are linked by Native oral tradition, Euro-American records, and archeological evidence to members of the present-day Pueblo of Jemez, New Mexico. \n ", "h_d_ci": "Null", "determinations": "Determinations Made by the Maxwell Museum of Anthropology, University of New Mexico \n Officials of the Maxwell Museum of Anthropology, University of New Mexico have determined that: \n \\xe2\\x80\\xa2 Pursuant to 25 U.S.C. 3001(9), the human remains described above represent the physical remains of at least 416 individuals of Native American ancestry. \n \\xe2\\x80\\xa2 Pursuant to 25 U.S.C. 3001(2), there is a relationship of shared group identity that can be reasonably traced between the Native American human remains and the Pueblo of Jemez, New Mexico. \n ", "a_r_d": "Representatives of any other Indian tribe that believes itself to be culturally affiliated with the human remains should contact Heather Edgar, Curator of Human Osteology, Maxwell Museum of Anthropology, University of New Mexico, MSC01 1050, 1 University of New Mexico, Albuquerque, NM 87131, telephone (505) 277-4415, before October 13, 2011. Repatriation of the human remains to the Pueblo of Jemez, New Mexico, may proceed after that date if no additional claimants come forward. \n The Maxwell Museum of Anthropology, University of New Mexico is responsible for notifying the Pueblo of Jemez, New Mexico, that this notice has been published. \n "}