{"index": "I_136", "messy_full": "\\n      \\n        DEPARTMENT OF THE INTERIOR\\n        National Park Service\\n        [NPS-WASO-NAGPRA-NPS0027336; PPWOCRADN0-PCU00RP14.R50000]\\n        Notice of Inventory Completion: Historical Society of Saginaw County, Inc., Saginaw County, MI\\n        \\n          AGENCY:\\n          National Park Service, Interior.\\n        \\n        \\n          ACTION:\\n          Notice.\\n        \\n        \\n          SUMMARY:\\n          The Historical Society of Saginaw County, Inc. has completed an inventory of human remains, in consultation with the appropriate Indian Tribes or Native Hawaiian organizations, and has determined that there is no cultural affiliation between the human remains and any present-day Indian Tribes or Native Hawaiian organizations. Representatives of any Indian Tribe or Native Hawaiian organization not identified in this notice that wish to request transfer of control of these human remains should submit a written request to the Historical Society of Saginaw County, Inc. If no additional requestors come forward, transfer of control of the human remains to the Indian Tribes or Native Hawaiian organizations stated in this notice may proceed.\\n        \\n        \\n          DATES:\\n          Representatives of any Indian Tribe or Native Hawaiian organization not identified in this notice that wish to request transfer of control of these human remains should submit a written request with information in support of the request to the Historical Society of Saginaw County, Inc. at the address in this notice by April 17, 2019.\\n        \\n        \\n          ADDRESSES:\\n\\n          Jeffrey Sommer, Historical Society of Saginaw County, Inc., 500 Federal Avenue, Saginaw, MI 48607, telephone (989) 752-2861 Ext. 308, email jsommer@castlemuseum.org.\\n          \\n        \\n      \\n      \\n        SUPPLEMENTARY INFORMATION:\\n\\n        Notice is here given in accordance with the Native American Graves Protection and Repatriation Act (NAGPRA), 25 U.S.C. 3003, of the completion of an inventory of human remains under the control of the Historical Society of Saginaw County, Inc., Saginaw County, MI. The human remains were removed from 20SA510 (Linton Street site) Saginaw County, MI.\\n        This notice is published as part of the National Park Service\\'s administrative responsibilities under NAGPRA, 25 U.S.C. 3003(d)(3) and 43 CFR 10.11(d). The determinations in this notice are the sole responsibility of the museum, institution, or Federal agency that has control of the Native American human remains. The National Park Service is not responsible for the determinations in this notice.\\n        Consultation\\n        A detailed assessment of the human remains was made by the Historical Society of Saginaw County, Inc. professional staff in consultation with representatives of the Little Traverse Bay Bands of Odawa Indians, Michigan; Minnesota Chippewa Tribe, Minnesota (Six component reservations: Bois Forte Band (Nett Lake); Fond du Lac Band; Grand Portage Band; Leech Lake Band; Mille Lacs Band; White Earth Band); and the Saginaw Chippewa Indian Tribe of Michigan.\\n        The Bad River Band of the Lake Superior Tribe of Chippewa Indians of the Bad River Reservation, Wisconsin; Bay Mills Indian Community, Michigan; Chippewa Cree Indians of the Rocky Boy\\'s Reservation, Montana (previously listed as the Chippewa-Cree Indians of the Rocky Boy\\'s Reservation, Montana); Grand Traverse Band of Ottawa and Chippewa Indians, Michigan; Keweenaw Bay Indian Community, Michigan; Kickapoo Traditional Tribe of Texas; Kickapoo Tribe of Indians of the Kickapoo Reservation in Kansas; Kickapoo Tribe of Oklahoma; Lac Courte Oreilles Band of Lake Superior Chippewa Indians of Wisconsin; Lac du Flambeau Band of Lake Superior Chippewa Indians of the Lac du Flambeau Reservation of Wisconsin; Lac Vieux Desert Band of Lake Superior Chippewa Indians of Michigan; Minnesota Chippewa Tribe, Minnesota (Six component reservations: Bois Forte Band (Nett Lake), Fond du Lac Band, Grand Portage Band, Leech Lake Band, Mille Lacs Band, White Earth Band); Red Cliff Band of Lake Superior Chippewa Indians of Wisconsin; Red Lake Band of Chippewa Indians, Minnesota; Sac & Fox Nation of Missouri in Kansas and Nebraska; Sac & Fox Nation, Oklahoma; Sac & Fox Tribe of the Mississippi in Iowa; Sault Ste. Marie Tribe of Chippewa Indians, Michigan; Sokaogon Chippewa Community, Wisconsin; St. Croix Chippewa Indians of Wisconsin; Tonawanda Band of Seneca (previously listed as the Tonawanda Band of Seneca Indians of New York); Turtle Mountain Band of Chippewa Indians of North Dakota; and the Wyandotte Nation were invited to consult but did not participate.\\n        Hereafter, all Tribes listed in this section are referred to as \\xe2\\x80\\x9cThe Consulted and Invited Tribes.\\xe2\\x80\\x9d\\n        History and Description of the Remains\\n        In 1979, human remains representing, at minimum, seven individuals were removed from the Linton Street site (20SA510) in Saginaw County, MI. The human remains were discovered by workers doing routine maintenance on a gas line. An archeologist from the Saginaw Archaeological Commission removed the exposed remains. A sketch map of the site area and a newspaper article describing the circumstances of the discovery are the only known documentation of the recovery. The fragmentary human remains are determined to be Native American based on the presence of red ochre staining on some of the human remains and, in one case, dental morphology. No known individuals were identified. No associated funerary objects are present.\\n        Determinations Made by the Historical Society of Saginaw County, Inc.\\n        Officials of the Historical Society of Saginaw County, Inc. have determined that:\\n        \\xe2\\x80\\xa2 Pursuant to 25 U.S.C. 3001(9), the human remains described in this notice are Native American based on the presence of red ochre staining on some of the human remains and, in one case, dental morphology.\\n        \\xe2\\x80\\xa2 Pursuant to 25 U.S.C. 3001(9), the human remains described in this notice represent the physical remains of seven individuals of Native American ancestry.\\n        \\xe2\\x80\\xa2 Pursuant to 25 U.S.C. 3001(2), a relationship of shared group identity cannot be reasonably traced between the Native American human remains and any present-day Indian Tribe.\\n        \\xe2\\x80\\xa2 According to final judgments of the Indian Claims Commission or the Court of Federal Claims, the land from which the Native American human remains were removed is the aboriginal land of the Saginaw Chippewa Indian Tribe of Michigan.\\n        \\xe2\\x80\\xa2 Treaties, Acts of Congress, or Executive Orders, indicate that the land from which the Native American human remains were removed is the aboriginal land of The Consulted and Invited Tribes.\\n        \\xe2\\x80\\xa2 Pursuant to 43 CFR 10.11(c)(1), the disposition of the human remains may be to The Consulted and Invited Tribes.\\n        Additional Requestors and Disposition\\n\\n        Representatives of any Indian Tribe or Native Hawaiian organization not identified in this notice that wish to request transfer of control of these human remains should submit a written request with information in support of the request to Jeffrey Sommer, Historical Society of Saginaw County, Inc., 500 Federal Avenue, Saginaw, MI 48607, telephone (989) 752-2861 Ext. 308, email jsommer@castlemuseum.org, by April 17, 2019. After that date, if no additional requestors have come forward, transfer of control of the human remains to The Consulted and Invited Tribes may proceed.\\n        The Historical Society of Saginaw County, Inc. is responsible for notifying The Consulted and Invited Tribes that this notice has been published.\\n        \\n          Dated: February 12, 2019.\\n          Melanie O\\'Brien,\\n          Manager, National NAGPRA Program. \\n        \\n      \\n      [FR Doc. 2019-04920 Filed 3-15-19; 8:45 am]\\n       BILLING CODE 4312-52-P\\n    ", "agency1": "DEPARTMENT OF THE INTERIOR", "sub_agency1": "National Park Service", "dep_doc": "[NPS-WASO-NAGPRA-NPS0027336; PPWOCRADN0-PCU00RP14.R50000]", "subject": "Notice of Inventory Completion: Historical Society of Saginaw County, Inc., Saginaw County, MI", "agency2": "National Park Service, Interior.", "action": "Notice.", "summary": "The Historical Society of Saginaw County, Inc. has completed an inventory of human remains, in consultation with the appropriate Indian Tribes or Native Hawaiian organizations, and has determined that there is no cultural affiliation between the human remains and any present-day Indian Tribes or Native Hawaiian organizations. Representatives of any Indian Tribe or Native Hawaiian organization not identified in this notice that wish to request transfer of control of these human remains should submit a written request to the Historical Society of Saginaw County, Inc. If no additional requestors come forward, transfer of control of the human remains to the Indian Tribes or Native Hawaiian organizations stated in this notice may proceed.", "dates": "Representatives of any Indian Tribe or Native Hawaiian organization not identified in this notice that wish to request transfer of control of these human remains should submit a written request with information in support of the request to the Historical Society of Saginaw County, Inc. at the address in this notice by April 17, 2019.", "addresses": "Jeffrey Sommer, Historical Society of Saginaw County, Inc., 500 Federal Avenue, Saginaw, MI 48607, telephone (989) 752-2861 Ext. 308, email jsommer@castlemuseum.org.\\n          ", "signature_dated": "Dated: February 12, 2019.", "signature_name": "Melanie O\\'Brien,", "signature_title": "Manager, National NAGPRA Program. ", "fr_doc": "[FR Doc. 2019-04920 Filed 3-15-19; 8:45 am]", "billing_code": " BILLING CODE 4312-52-P", "supp_info": "SUPPLEMENTARY INFORMATION: \n Notice is here given in accordance with the Native American Graves Protection and Repatriation Act (NAGPRA), 25 U.S.C. 3003, of the completion of an inventory of human remains under the control of the Historical Society of Saginaw County, Inc., Saginaw County, MI. The human remains were removed from 20SA510 (Linton Street site) Saginaw County, MI. \n This notice is published as part of the National Park Service\\'s administrative responsibilities under NAGPRA, 25 U.S.C. 3003(d)(3) and 43 CFR 10.11(d). The determinations in this notice are the sole responsibility of the museum, institution, or Federal agency that has control of the Native American human remains. The National Park Service is not responsible for the determinations in this notice. \n Consultation \n A detailed assessment of the human remains was made by the Historical Society of Saginaw County, Inc. professional staff in consultation with representatives of the Little Traverse Bay Bands of Odawa Indians, Michigan; Minnesota Chippewa Tribe, Minnesota (Six component reservations: Bois Forte Band (Nett Lake); Fond du Lac Band; Grand Portage Band; Leech Lake Band; Mille Lacs Band; White Earth Band); and the Saginaw Chippewa Indian Tribe of Michigan. \n The Bad River Band of the Lake Superior Tribe of Chippewa Indians of the Bad River Reservation, Wisconsin; Bay Mills Indian Community, Michigan; Chippewa Cree Indians of the Rocky Boy\\'s Reservation, Montana (previously listed as the Chippewa-Cree Indians of the Rocky Boy\\'s Reservation, Montana); Grand Traverse Band of Ottawa and Chippewa Indians, Michigan; Keweenaw Bay Indian Community, Michigan; Kickapoo Traditional Tribe of Texas; Kickapoo Tribe of Indians of the Kickapoo Reservation in Kansas; Kickapoo Tribe of Oklahoma; Lac Courte Oreilles Band of Lake Superior Chippewa Indians of Wisconsin; Lac du Flambeau Band of Lake Superior Chippewa Indians of the Lac du Flambeau Reservation of Wisconsin; Lac Vieux Desert Band of Lake Superior Chippewa Indians of Michigan; Minnesota Chippewa Tribe, Minnesota (Six component reservations: Bois Forte Band (Nett Lake), Fond du Lac Band, Grand Portage Band, Leech Lake Band, Mille Lacs Band, White Earth Band); Red Cliff Band of Lake Superior Chippewa Indians of Wisconsin; Red Lake Band of Chippewa Indians, Minnesota; Sac & Fox Nation of Missouri in Kansas and Nebraska; Sac & Fox Nation, Oklahoma; Sac & Fox Tribe of the Mississippi in Iowa; Sault Ste. Marie Tribe of Chippewa Indians, Michigan; Sokaogon Chippewa Community, Wisconsin; St. Croix Chippewa Indians of Wisconsin; Tonawanda Band of Seneca (previously listed as the Tonawanda Band of Seneca Indians of New York); Turtle Mountain Band of Chippewa Indians of North Dakota; and the Wyandotte Nation were invited to consult but did not participate. \n Hereafter, all Tribes listed in this section are referred to as \\xe2\\x80\\x9cThe Consulted and Invited Tribes.\\xe2\\x80\\x9d \n History and Description of the Remains \n In 1979, human remains representing, at minimum, seven individuals were removed from the Linton Street site (20SA510) in Saginaw County, MI. The human remains were discovered by workers doing routine maintenance on a gas line. An archeologist from the Saginaw Archaeological Commission removed the exposed remains. A sketch map of the site area and a newspaper article describing the circumstances of the discovery are the only known documentation of the recovery. The fragmentary human remains are determined to be Native American based on the presence of red ochre staining on some of the human remains and, in one case, dental morphology. No known individuals were identified. No associated funerary objects are present. \n Determinations Made by the Historical Society of Saginaw County, Inc. \n Officials of the Historical Society of Saginaw County, Inc. have determined that: \n \\xe2\\x80\\xa2 Pursuant to 25 U.S.C. 3001(9), the human remains described in this notice are Native American based on the presence of red ochre staining on some of the human remains and, in one case, dental morphology. \n \\xe2\\x80\\xa2 Pursuant to 25 U.S.C. 3001(9), the human remains described in this notice represent the physical remains of seven individuals of Native American ancestry. \n \\xe2\\x80\\xa2 Pursuant to 25 U.S.C. 3001(2), a relationship of shared group identity cannot be reasonably traced between the Native American human remains and any present-day Indian Tribe. \n \\xe2\\x80\\xa2 According to final judgments of the Indian Claims Commission or the Court of Federal Claims, the land from which the Native American human remains were removed is the aboriginal land of the Saginaw Chippewa Indian Tribe of Michigan. \n \\xe2\\x80\\xa2 Treaties, Acts of Congress, or Executive Orders, indicate that the land from which the Native American human remains were removed is the aboriginal land of The Consulted and Invited Tribes. \n \\xe2\\x80\\xa2 Pursuant to 43 CFR 10.11(c)(1), the disposition of the human remains may be to The Consulted and Invited Tribes. \n Additional Requestors and Disposition \n Representatives of any Indian Tribe or Native Hawaiian organization not identified in this notice that wish to request transfer of control of these human remains should submit a written request with information in support of the request to Jeffrey Sommer, Historical Society of Saginaw County, Inc., 500 Federal Avenue, Saginaw, MI 48607, telephone (989) 752-2861 Ext. 308, email jsommer@castlemuseum.org, by April 17, 2019. After that date, if no additional requestors have come forward, transfer of control of the human remains to The Consulted and Invited Tribes may proceed. \n The Historical Society of Saginaw County, Inc. is responsible for notifying The Consulted and Invited Tribes that this notice has been published. \n ", "consultation": "A detailed assessment of the human remains was made by the Historical Society of Saginaw County, Inc. professional staff in consultation with representatives of the Little Traverse Bay Bands of Odawa Indians, Michigan; Minnesota Chippewa Tribe, Minnesota (Six component reservations: Bois Forte Band (Nett Lake); Fond du Lac Band; Grand Portage Band; Leech Lake Band; Mille Lacs Band; White Earth Band); and the Saginaw Chippewa Indian Tribe of Michigan. \n The Bad River Band of the Lake Superior Tribe of Chippewa Indians of the Bad River Reservation, Wisconsin; Bay Mills Indian Community, Michigan; Chippewa Cree Indians of the Rocky Boy\\'s Reservation, Montana (previously listed as the Chippewa-Cree Indians of the Rocky Boy\\'s Reservation, Montana); Grand Traverse Band of Ottawa and Chippewa Indians, Michigan; Keweenaw Bay Indian Community, Michigan; Kickapoo Traditional Tribe of Texas; Kickapoo Tribe of Indians of the Kickapoo Reservation in Kansas; Kickapoo Tribe of Oklahoma; Lac Courte Oreilles Band of Lake Superior Chippewa Indians of Wisconsin; Lac du Flambeau Band of Lake Superior Chippewa Indians of the Lac du Flambeau Reservation of Wisconsin; Lac Vieux Desert Band of Lake Superior Chippewa Indians of Michigan; Minnesota Chippewa Tribe, Minnesota (Six component reservations: Bois Forte Band (Nett Lake), Fond du Lac Band, Grand Portage Band, Leech Lake Band, Mille Lacs Band, White Earth Band); Red Cliff Band of Lake Superior Chippewa Indians of Wisconsin; Red Lake Band of Chippewa Indians, Minnesota; Sac & Fox Nation of Missouri in Kansas and Nebraska; Sac & Fox Nation, Oklahoma; Sac & Fox Tribe of the Mississippi in Iowa; Sault Ste. Marie Tribe of Chippewa Indians, Michigan; Sokaogon Chippewa Community, Wisconsin; St. Croix Chippewa Indians of Wisconsin; Tonawanda Band of Seneca (previously listed as the Tonawanda Band of Seneca Indians of New York); Turtle Mountain Band of Chippewa Indians of North Dakota; and the Wyandotte Nation were invited to consult but did not participate. \n Hereafter, all Tribes listed in this section are referred to as \\xe2\\x80\\x9cThe Consulted and Invited Tribes.\\xe2\\x80\\x9d \n ", "h_d_r": "In 1979, human remains representing, at minimum, seven individuals were removed from the Linton Street site (20SA510) in Saginaw County, MI. The human remains were discovered by workers doing routine maintenance on a gas line. An archeologist from the Saginaw Archaeological Commission removed the exposed remains. A sketch map of the site area and a newspaper article describing the circumstances of the discovery are the only known documentation of the recovery. The fragmentary human remains are determined to be Native American based on the presence of red ochre staining on some of the human remains and, in one case, dental morphology. No known individuals were identified. No associated funerary objects are present. \n ", "h_d_ci": "Null", "determinations": "Determinations Made by the Historical Society of Saginaw County, Inc. \n Officials of the Historical Society of Saginaw County, Inc. have determined that: \n \\xe2\\x80\\xa2 Pursuant to 25 U.S.C. 3001(9), the human remains described in this notice are Native American based on the presence of red ochre staining on some of the human remains and, in one case, dental morphology. \n \\xe2\\x80\\xa2 Pursuant to 25 U.S.C. 3001(9), the human remains described in this notice represent the physical remains of seven individuals of Native American ancestry. \n \\xe2\\x80\\xa2 Pursuant to 25 U.S.C. 3001(2), a relationship of shared group identity cannot be reasonably traced between the Native American human remains and any present-day Indian Tribe. \n \\xe2\\x80\\xa2 According to final judgments of the Indian Claims Commission or the Court of Federal Claims, the land from which the Native American human remains were removed is the aboriginal land of the Saginaw Chippewa Indian Tribe of Michigan. \n \\xe2\\x80\\xa2 Treaties, Acts of Congress, or Executive Orders, indicate that the land from which the Native American human remains were removed is the aboriginal land of The Consulted and Invited Tribes. \n \\xe2\\x80\\xa2 Pursuant to 43 CFR 10.11(c)(1), the disposition of the human remains may be to The Consulted and Invited Tribes. \n ", "a_r_d": "Representatives of any Indian Tribe or Native Hawaiian organization not identified in this notice that wish to request transfer of control of these human remains should submit a written request with information in support of the request to Jeffrey Sommer, Historical Society of Saginaw County, Inc., 500 Federal Avenue, Saginaw, MI 48607, telephone (989) 752-2861 Ext. 308, email jsommer@castlemuseum.org, by April 17, 2019. After that date, if no additional requestors have come forward, transfer of control of the human remains to The Consulted and Invited Tribes may proceed. \n The Historical Society of Saginaw County, Inc. is responsible for notifying The Consulted and Invited Tribes that this notice has been published. \n "}