{"index": "I_135", "messy_full": "\\n      \\n        DEPARTMENT OF THE INTERIOR\\n        National Park Service\\n        [NPS-WASO-NAGPRA-NPS0027329; PPWOCRADN0-PCU00RP14.R50000]\\n        Notice of Inventory Completion: The State Center Community College District\\xe2\\x80\\x94Fresno City College, Fresno, CA\\n        \\n          AGENCY:\\n          National Park Service, Interior.\\n        \\n        \\n          ACTION:\\n          Notice.\\n        \\n        \\n          SUMMARY:\\n          The State Center Community College District\\xe2\\x80\\x94Fresno City College has completed an inventory of human remains and associated funerary objects, in consultation with the appropriate Indian Tribes or Native Hawaiian organizations, and has determined that there is a cultural affiliation between the human remains and associated funerary objects and present-day Indian Tribes or Native Hawaiian organizations. Lineal descendants or representatives of any Indian Tribes or Native Hawaiian organization not identified in this notice that wish to request transfer of control of these human remains and associated funerary objects should submit a written request to the State Center Community College District\\xe2\\x80\\x94Fresno City College. If no additional requestors come forward, transfer of control of the human remains and associated funerary objects to the lineal descendants, Indian Tribes, or Native Hawaiian organizations stated in this notice may proceed.\\n        \\n        \\n          DATES:\\n          Lineal descendants or representatives of any Indian Tribes or Native Hawaiian organization not identified in this notice that wish to request transfer of control of these human remains and associated funerary objects should submit a written request with information in support of the request to the State Center Community College District\\xe2\\x80\\x94Fresno City College at the address in this notice by April 17, 2019.\\n        \\n        \\n          ADDRESSES:\\n\\n          Mary Beth Miller, Interim Dean of Social Sciences, in care of Jill Minar, Ph.D., Fresno City College of The State Center Community College District, 1101 E University Avenue, Fresno, CA 93741, telephone (559) 442-8210, email jill.minar@fresnocitycollege.edu.\\n          \\n        \\n      \\n      \\n        SUPPLEMENTARY INFORMATION:\\n        Notice is here given in accordance with the Native American Graves Protection and Repatriation Act (NAGPRA), 25 U.S.C. 3003, of the completion of an inventory of human remains and associated funerary objects under the control of the State Center Community College District\\xe2\\x80\\x94Fresno City College, Fresno, CA. The human remains and associated funerary objects were removed from CA-FRE-2849, Fresno County, CA.\\n        This notice is published as part of the National Park Service\\'s administrative responsibilities under NAGPRA, 25 U.S.C. 3003(d)(3). The determinations in this notice are the sole responsibility of the museum, institution, or Federal agency that has control of the Native American human remains and associated funerary objects. The National Park Service is not responsible for the determinations in this notice.\\n        Consultation\\n        A detailed assessment of the human remains was made by the State Center Community College District\\xe2\\x80\\x94Fresno City College professional staff in consultation with representatives of the Big Sandy Rancheria of Western Mono Indians of California (previously listed as the Big Sandy Rancheria of Mono Indians of California); Buena Vista Rancheria of Me-Wuk Indians of California; Cold Springs Rancheria of Mono Indians of California; Middletown Rancheria of Pomo Indians of California; Northfork Rancheria of Mono Indians of California; Picayune Rancheria of Chukchansi Indians of California; Santa Rosa Indian Community of the Santa Rosa Rancheria, California; Shingle Springs Band of Miwok Indians, Shingle Springs Rancheria (Verona Tract), California; Table Mountain Rancheria (previously listed as the Table Mountain Rancheria of California); Tejon Indian Tribe; Tule River Indian Tribes of the Tule River Reservation, California; and Tuolumne Band of Me-Wuk Indians of the Tuolumne Rancheria of California.\\n        The California Valley Miwok Tribe, California; Chicken Ranch Rancheria of Me-Wuk Indians of California; Fort McDermitt Paiute and Shoshone Tribes of the Fort McDermitt Indian Reservation, Nevada and Oregon; Ione Band of Miwok Indians of California; Jackson Band of Miwuk Indians (previously listed as the Jackson Rancheria of Me-Wuk Indians of California); Pyramid Lake Paiute Tribe of the Pyramid Lake Reservation, Nevada; Reno-Sparks Indian Colony, Nevada; Walker River Paiute Tribe of the Walker River Reservation, Nevada; and Yerington Paiute Tribe of the Yerington Colony & Campbell Ranch, Nevada were contacted and invited to consult, but did not participate.\\n        Two non-federally recognized Indian groups, the Dunlap Band of Mono Indians and the Traditional Choinumni Tribe, participated in consultation. One non-federally recognized group, the Wukchumni Tribes, was invited to consult, but did not participate.\\n        Hereafter, all the Indian Tribes and non-federally recognized Indian groups listed in this section are referred to as \\xe2\\x80\\x9cThe Consulted and Notified Tribes and Groups.\\xe2\\x80\\x9d\\n        History and Description of the Remains\\n        In 1994, human remains representing, at minimum, two individuals were removed from CA-FRE-2849 in Fresno County, CA, by Don Wren, who excavated the site on a contract for the Auberry Road Project. In January 2017, an osteological examination of the faunal collections was conducted to determine if human remains were present. The human remains belong to one adult of indeterminate sex and one sub-adult of indeterminate sex and are represented by fourteen bone fragments and two teeth. No known individuals were identified. The 18 associated funerary objects are shell beads.\\n        Determinations Made by the State Center Community College District\\xe2\\x80\\x94Fresno City College\\n        Officials of the State Center Community College District\\xe2\\x80\\x94Fresno City College have determined that:\\n        \\xe2\\x80\\xa2 Pursuant to 25 U.S.C. 3001(9), the human remains described in this notice represent the physical remains of two individuals of Native American ancestry, based on archeological context.\\n        \\xe2\\x80\\xa2 Pursuant to 25 U.S.C. 3001(3)(A), the 18 objects described in this notice are reasonably believed to have been placed with or near individual human remains at the time of death or later as part of the death rite or ceremony.\\n\\n        \\xe2\\x80\\xa2 Pursuant to 25 U.S.C. 3001(2), there is a relationship of shared group identity that can be reasonably traced between the Native American human remains and associated funerary objects and the Big Sandy Rancheria of Western Mono Indians of California (previously listed as the Big Sandy Rancheria of Mono Indians of California) and the Table Mountain Rancheria (previously listed as the Table Mountain Rancheria of California), based on geographic information and oral tradition.\\n        \\n        Additional Requestors and Disposition\\n\\n        Lineal descendants or representatives of any Indian Tribes or Native Hawaiian organization not identified in this notice that wish to request transfer of control of these human remains and associated funerary objects should submit a written request with information in support of the request to Mary Beth Miller, Interim Dean of Social Sciences, in care of Jill Minar, Ph.D., Fresno City College of The State Center Community College District, 1101 E University Avenue, Fresno, CA 93741, telephone (559) 442-8210, email jill.minar@fresnocitycollege.edu, by April 17, 2019. After that date, if no additional requestors have come forward, transfer of control of the human remains and associated funerary objects to the Big Sandy Rancheria of Western Mono Indians of California (previously listed as the Big Sandy Rancheria of Mono Indians of California) and the Table Mountain Rancheria (previously listed as the Table Mountain Rancheria of California) may proceed.\\n        The State Center Community College District\\xe2\\x80\\x94Fresno City College is responsible for notifying The Consulted and Notified Tribes and Groups that this notice has been published.\\n        \\n          Dated: February 12, 2019.\\n          Melanie O\\'Brien,\\n          Manager, National NAGPRA Program.\\n        \\n      \\n      [FR Doc. 2019-04916 Filed 3-15-19; 8:45 am]\\n      BILLING CODE 4312-52-P\\n    ", "agency1": "DEPARTMENT OF THE INTERIOR", "sub_agency1": "National Park Service", "dep_doc": "[NPS-WASO-NAGPRA-NPS0027329; PPWOCRADN0-PCU00RP14.R50000]", "subject": "Notice of Inventory Completion: The State Center Community College District\\xe2\\x80\\x94Fresno City College, Fresno, CA", "agency2": "National Park Service, Interior.", "action": "Notice.", "summary": "The State Center Community College District\\xe2\\x80\\x94Fresno City College has completed an inventory of human remains and associated funerary objects, in consultation with the appropriate Indian Tribes or Native Hawaiian organizations, and has determined that there is a cultural affiliation between the human remains and associated funerary objects and present-day Indian Tribes or Native Hawaiian organizations. Lineal descendants or representatives of any Indian Tribes or Native Hawaiian organization not identified in this notice that wish to request transfer of control of these human remains and associated funerary objects should submit a written request to the State Center Community College District\\xe2\\x80\\x94Fresno City College. If no additional requestors come forward, transfer of control of the human remains and associated funerary objects to the lineal descendants, Indian Tribes, or Native Hawaiian organizations stated in this notice may proceed.", "dates": "Lineal descendants or representatives of any Indian Tribes or Native Hawaiian organization not identified in this notice that wish to request transfer of control of these human remains and associated funerary objects should submit a written request with information in support of the request to the State Center Community College District\\xe2\\x80\\x94Fresno City College at the address in this notice by April 17, 2019.", "addresses": "Mary Beth Miller, Interim Dean of Social Sciences, in care of Jill Minar, Ph.D., Fresno City College of The State Center Community College District, 1101 E University Avenue, Fresno, CA 93741, telephone (559) 442-8210, email jill.minar@fresnocitycollege.edu.\\n          ", "signature_dated": "Dated: February 12, 2019.", "signature_name": "Melanie O\\'Brien,", "signature_title": "Manager, National NAGPRA Program.", "fr_doc": "[FR Doc. 2019-04916 Filed 3-15-19; 8:45 am]", "billing_code": "BILLING CODE 4312-52-P", "supp_info": "SUPPLEMENTARY INFORMATION: \n Notice is here given in accordance with the Native American Graves Protection and Repatriation Act (NAGPRA), 25 U.S.C. 3003, of the completion of an inventory of human remains and associated funerary objects under the control of the State Center Community College District\\xe2\\x80\\x94Fresno City College, Fresno, CA. The human remains and associated funerary objects were removed from CA-FRE-2849, Fresno County, CA. \n This notice is published as part of the National Park Service\\'s administrative responsibilities under NAGPRA, 25 U.S.C. 3003(d)(3). The determinations in this notice are the sole responsibility of the museum, institution, or Federal agency that has control of the Native American human remains and associated funerary objects. The National Park Service is not responsible for the determinations in this notice. \n Consultation \n A detailed assessment of the human remains was made by the State Center Community College District\\xe2\\x80\\x94Fresno City College professional staff in consultation with representatives of the Big Sandy Rancheria of Western Mono Indians of California (previously listed as the Big Sandy Rancheria of Mono Indians of California); Buena Vista Rancheria of Me-Wuk Indians of California; Cold Springs Rancheria of Mono Indians of California; Middletown Rancheria of Pomo Indians of California; Northfork Rancheria of Mono Indians of California; Picayune Rancheria of Chukchansi Indians of California; Santa Rosa Indian Community of the Santa Rosa Rancheria, California; Shingle Springs Band of Miwok Indians, Shingle Springs Rancheria (Verona Tract), California; Table Mountain Rancheria (previously listed as the Table Mountain Rancheria of California); Tejon Indian Tribe; Tule River Indian Tribes of the Tule River Reservation, California; and Tuolumne Band of Me-Wuk Indians of the Tuolumne Rancheria of California. \n The California Valley Miwok Tribe, California; Chicken Ranch Rancheria of Me-Wuk Indians of California; Fort McDermitt Paiute and Shoshone Tribes of the Fort McDermitt Indian Reservation, Nevada and Oregon; Ione Band of Miwok Indians of California; Jackson Band of Miwuk Indians (previously listed as the Jackson Rancheria of Me-Wuk Indians of California); Pyramid Lake Paiute Tribe of the Pyramid Lake Reservation, Nevada; Reno-Sparks Indian Colony, Nevada; Walker River Paiute Tribe of the Walker River Reservation, Nevada; and Yerington Paiute Tribe of the Yerington Colony & Campbell Ranch, Nevada were contacted and invited to consult, but did not participate. \n Two non-federally recognized Indian groups, the Dunlap Band of Mono Indians and the Traditional Choinumni Tribe, participated in consultation. One non-federally recognized group, the Wukchumni Tribes, was invited to consult, but did not participate. \n Hereafter, all the Indian Tribes and non-federally recognized Indian groups listed in this section are referred to as \\xe2\\x80\\x9cThe Consulted and Notified Tribes and Groups.\\xe2\\x80\\x9d \n History and Description of the Remains \n In 1994, human remains representing, at minimum, two individuals were removed from CA-FRE-2849 in Fresno County, CA, by Don Wren, who excavated the site on a contract for the Auberry Road Project. In January 2017, an osteological examination of the faunal collections was conducted to determine if human remains were present. The human remains belong to one adult of indeterminate sex and one sub-adult of indeterminate sex and are represented by fourteen bone fragments and two teeth. No known individuals were identified. The 18 associated funerary objects are shell beads. \n Determinations Made by the State Center Community College District\\xe2\\x80\\x94Fresno City College \n Officials of the State Center Community College District\\xe2\\x80\\x94Fresno City College have determined that: \n \\xe2\\x80\\xa2 Pursuant to 25 U.S.C. 3001(9), the human remains described in this notice represent the physical remains of two individuals of Native American ancestry, based on archeological context. \n \\xe2\\x80\\xa2 Pursuant to 25 U.S.C. 3001(3)(A), the 18 objects described in this notice are reasonably believed to have been placed with or near individual human remains at the time of death or later as part of the death rite or ceremony. \n \\xe2\\x80\\xa2 Pursuant to 25 U.S.C. 3001(2), there is a relationship of shared group identity that can be reasonably traced between the Native American human remains and associated funerary objects and the Big Sandy Rancheria of Western Mono Indians of California (previously listed as the Big Sandy Rancheria of Mono Indians of California) and the Table Mountain Rancheria (previously listed as the Table Mountain Rancheria of California), based on geographic information and oral tradition.\\n         \n Additional Requestors and Disposition \n Lineal descendants or representatives of any Indian Tribes or Native Hawaiian organization not identified in this notice that wish to request transfer of control of these human remains and associated funerary objects should submit a written request with information in support of the request to Mary Beth Miller, Interim Dean of Social Sciences, in care of Jill Minar, Ph.D., Fresno City College of The State Center Community College District, 1101 E University Avenue, Fresno, CA 93741, telephone (559) 442-8210, email jill.minar@fresnocitycollege.edu, by April 17, 2019. After that date, if no additional requestors have come forward, transfer of control of the human remains and associated funerary objects to the Big Sandy Rancheria of Western Mono Indians of California (previously listed as the Big Sandy Rancheria of Mono Indians of California) and the Table Mountain Rancheria (previously listed as the Table Mountain Rancheria of California) may proceed. \n The State Center Community College District\\xe2\\x80\\x94Fresno City College is responsible for notifying The Consulted and Notified Tribes and Groups that this notice has been published. \n ", "consultation": "A detailed assessment of the human remains was made by the State Center Community College District\\xe2\\x80\\x94Fresno City College professional staff in consultation with representatives of the Big Sandy Rancheria of Western Mono Indians of California (previously listed as the Big Sandy Rancheria of Mono Indians of California); Buena Vista Rancheria of Me-Wuk Indians of California; Cold Springs Rancheria of Mono Indians of California; Middletown Rancheria of Pomo Indians of California; Northfork Rancheria of Mono Indians of California; Picayune Rancheria of Chukchansi Indians of California; Santa Rosa Indian Community of the Santa Rosa Rancheria, California; Shingle Springs Band of Miwok Indians, Shingle Springs Rancheria (Verona Tract), California; Table Mountain Rancheria (previously listed as the Table Mountain Rancheria of California); Tejon Indian Tribe; Tule River Indian Tribes of the Tule River Reservation, California; and Tuolumne Band of Me-Wuk Indians of the Tuolumne Rancheria of California. \n The California Valley Miwok Tribe, California; Chicken Ranch Rancheria of Me-Wuk Indians of California; Fort McDermitt Paiute and Shoshone Tribes of the Fort McDermitt Indian Reservation, Nevada and Oregon; Ione Band of Miwok Indians of California; Jackson Band of Miwuk Indians (previously listed as the Jackson Rancheria of Me-Wuk Indians of California); Pyramid Lake Paiute Tribe of the Pyramid Lake Reservation, Nevada; Reno-Sparks Indian Colony, Nevada; Walker River Paiute Tribe of the Walker River Reservation, Nevada; and Yerington Paiute Tribe of the Yerington Colony & Campbell Ranch, Nevada were contacted and invited to consult, but did not participate. \n Two non-federally recognized Indian groups, the Dunlap Band of Mono Indians and the Traditional Choinumni Tribe, participated in consultation. One non-federally recognized group, the Wukchumni Tribes, was invited to consult, but did not participate. \n Hereafter, all the Indian Tribes and non-federally recognized Indian groups listed in this section are referred to as \\xe2\\x80\\x9cThe Consulted and Notified Tribes and Groups.\\xe2\\x80\\x9d \n ", "h_d_r": "In 1994, human remains representing, at minimum, two individuals were removed from CA-FRE-2849 in Fresno County, CA, by Don Wren, who excavated the site on a contract for the Auberry Road Project. In January 2017, an osteological examination of the faunal collections was conducted to determine if human remains were present. The human remains belong to one adult of indeterminate sex and one sub-adult of indeterminate sex and are represented by fourteen bone fragments and two teeth. No known individuals were identified. The 18 associated funerary objects are shell beads. \n ", "h_d_ci": "Null", "determinations": "Determinations Made by the State Center Community College District\\xe2\\x80\\x94Fresno City College \n Officials of the State Center Community College District\\xe2\\x80\\x94Fresno City College have determined that: \n \\xe2\\x80\\xa2 Pursuant to 25 U.S.C. 3001(9), the human remains described in this notice represent the physical remains of two individuals of Native American ancestry, based on archeological context. \n \\xe2\\x80\\xa2 Pursuant to 25 U.S.C. 3001(3)(A), the 18 objects described in this notice are reasonably believed to have been placed with or near individual human remains at the time of death or later as part of the death rite or ceremony. \n \\xe2\\x80\\xa2 Pursuant to 25 U.S.C. 3001(2), there is a relationship of shared group identity that can be reasonably traced between the Native American human remains and associated funerary objects and the Big Sandy Rancheria of Western Mono Indians of California (previously listed as the Big Sandy Rancheria of Mono Indians of California) and the Table Mountain Rancheria (previously listed as the Table Mountain Rancheria of California), based on geographic information and oral tradition.\\n         \n ", "a_r_d": "Lineal descendants or representatives of any Indian Tribes or Native Hawaiian organization not identified in this notice that wish to request transfer of control of these human remains and associated funerary objects should submit a written request with information in support of the request to Mary Beth Miller, Interim Dean of Social Sciences, in care of Jill Minar, Ph.D., Fresno City College of The State Center Community College District, 1101 E University Avenue, Fresno, CA 93741, telephone (559) 442-8210, email jill.minar@fresnocitycollege.edu, by April 17, 2019. After that date, if no additional requestors have come forward, transfer of control of the human remains and associated funerary objects to the Big Sandy Rancheria of Western Mono Indians of California (previously listed as the Big Sandy Rancheria of Mono Indians of California) and the Table Mountain Rancheria (previously listed as the Table Mountain Rancheria of California) may proceed. \n The State Center Community College District\\xe2\\x80\\x94Fresno City College is responsible for notifying The Consulted and Notified Tribes and Groups that this notice has been published. \n "}