{"index": "I_145", "messy_full": "\\n      \\n        DEPARTMENT OF THE INTERIOR\\n        National Park Service\\n        [NPS-WASO-NAGPRA-NPS0027269; PPWOCRADN0-PCU00RP14.R50000]\\n        Notice of Inventory Completion: San Diego Museum of Man, San Diego, CA\\n        \\n          AGENCY:\\n          National Park Service, Interior.\\n        \\n        \\n          ACTION:\\n          Notice.\\n        \\n        \\n          SUMMARY:\\n          The San Diego Museum of Man has completed an inventory of human remains, in consultation with the appropriate Indian Tribes or Native Hawaiian organizations, and has determined that there is a cultural affiliation between the human remains and present-day Indian Tribes or Native Hawaiian organizations. Lineal descendants or representatives of any Indian Tribe or Native Hawaiian organization not identified in this notice that wish to request transfer of control of these human remains should submit a written request to the San Diego Museum of Man. If no additional requestors come forward, transfer of control of the human remains to the lineal descendants, Indian Tribes, or Native Hawaiian organizations stated in this notice may proceed.\\n        \\n        \\n          DATES:\\n          Lineal descendants or representatives of any Indian Tribe or Native Hawaiian organization not identified in this notice that wish to request transfer of control of these human remains should submit a written request with information in support of the request to the San Diego Museum of Man at the address in this notice by April 1, 2019.\\n        \\n        \\n          ADDRESSES:\\n\\n          Ben Garcia, Deputy Director, San Diego Museum of Man, 1350 El Prado, San Diego, CA 92101, telephone (619) 239-2001 Ext. 17, email bgarcia@museumofman.org.\\n          \\n        \\n      \\n      \\n        SUPPLEMENTARY INFORMATION:\\n        Notice is here given in accordance with the Native American Graves Protection and Repatriation Act (NAGPRA), 25 U.S.C. 3003, of the completion of an inventory of human remains under the control of the San Diego Museum of Man, San Diego, CA. The human remains were removed from San Nicolas Island, Ventura County, CA.\\n        This notice is published as part of the National Park Service\\'s administrative responsibilities under NAGPRA, 25 U.S.C. 3003(d)(3). The determinations in this notice are the sole responsibility of the museum, institution, or Federal agency that has control of the Native American human remains. The National Park Service is not responsible for the determinations in this notice.\\n        Consultation\\n        A detailed assessment of the human remains was made by the San Diego Museum of Man professional staff in consultation with representatives of the Pauma Band of Luiseno Mission Indians of the Pauma & Yuima Reservation, California; Pechanga Band of Luiseno Mission Indians of the Pechanga Reservation, California; Rincon Band of Luiseno Mission Indians of the Rincon Reservation, California; and the Santa Ynez Band of Chumash Mission Indians of the Santa Ynez Reservation, California (hereafter referred to as \\xe2\\x80\\x9cThe Tribes\\xe2\\x80\\x9d).\\n        History and Description of the Remains\\n        In 1937, human remains representing, at minimum, one individual were donated to the San Diego Museum of Man by Mrs. L. H. Sherman. These human remains had been removed from San Nicolas Island (SNI), Ventura County, CA. No primary documentation or specific provenience information beyond their SNI origin exists for these human remains. No known individual was identified.\\n        An examination of the human remains by San Diego Museum of Man physical anthropology professional staff determined the individual to be of Native American origin. Archeological data indicate that The Tribes can trace their ancestry back to the people who previously occupied on the Channel Islands.\\n        Determinations Made by the San Diego Museum of Man\\n        Officials of the San Diego Museum of Man have determined that:\\n        \\xe2\\x80\\xa2 Pursuant to 25 U.S.C. 3001(9), the human remains described in this notice represent the physical remains of one individual of Native American ancestry.\\n        \\xe2\\x80\\xa2 Pursuant to 25 U.S.C. 3001(2), there is a relationship of shared group identity that can be reasonably traced between the Native American human remains and The Tribes.\\n        Additional Requestors and Disposition\\n\\n        Lineal descendants or representatives of any Indian Tribe or Native Hawaiian organization not identified in this notice that wish to request transfer of control of these human remains should submit a written request with information in support of the request to Ben Garcia, Deputy Director, San Diego Museum of Man, 1350 El Prado, San Diego, CA 92101, telephone (619) 239-2001 Ext. 17, email bgarcia@museumofman.org, by April 1, 2019. After that date, if no additional requestors have come forward, transfer of control of the human remains to The Tribes may proceed.\\n        The San Diego Museum of Man is responsible for notifying The Tribes that this notice has been published.\\n        \\n          Dated: February 1, 2019.\\n          Melanie O\\'Brien,\\n          Manager, National NAGPRA Program. \\n        \\n      \\n      [FR Doc. 2019-03582 Filed 2-28-19; 8:45 am]\\n       BILLING CODE 4312-52-P\\n    ", "agency1": "DEPARTMENT OF THE INTERIOR", "sub_agency1": "National Park Service", "dep_doc": "[NPS-WASO-NAGPRA-NPS0027269; PPWOCRADN0-PCU00RP14.R50000]", "subject": "Notice of Inventory Completion: San Diego Museum of Man, San Diego, CA", "agency2": "National Park Service, Interior.", "action": "Notice.", "summary": "The San Diego Museum of Man has completed an inventory of human remains, in consultation with the appropriate Indian Tribes or Native Hawaiian organizations, and has determined that there is a cultural affiliation between the human remains and present-day Indian Tribes or Native Hawaiian organizations. Lineal descendants or representatives of any Indian Tribe or Native Hawaiian organization not identified in this notice that wish to request transfer of control of these human remains should submit a written request to the San Diego Museum of Man. If no additional requestors come forward, transfer of control of the human remains to the lineal descendants, Indian Tribes, or Native Hawaiian organizations stated in this notice may proceed.", "dates": "Lineal descendants or representatives of any Indian Tribe or Native Hawaiian organization not identified in this notice that wish to request transfer of control of these human remains should submit a written request with information in support of the request to the San Diego Museum of Man at the address in this notice by April 1, 2019.", "addresses": "Ben Garcia, Deputy Director, San Diego Museum of Man, 1350 El Prado, San Diego, CA 92101, telephone (619) 239-2001 Ext. 17, email bgarcia@museumofman.org.\\n          ", "signature_dated": "Dated: February 1, 2019.", "signature_name": "Melanie O\\'Brien,", "signature_title": "Manager, National NAGPRA Program. ", "fr_doc": "[FR Doc. 2019-03582 Filed 2-28-19; 8:45 am]", "billing_code": " BILLING CODE 4312-52-P", "supp_info": "SUPPLEMENTARY INFORMATION: \n Notice is here given in accordance with the Native American Graves Protection and Repatriation Act (NAGPRA), 25 U.S.C. 3003, of the completion of an inventory of human remains under the control of the San Diego Museum of Man, San Diego, CA. The human remains were removed from San Nicolas Island, Ventura County, CA. \n This notice is published as part of the National Park Service\\'s administrative responsibilities under NAGPRA, 25 U.S.C. 3003(d)(3). The determinations in this notice are the sole responsibility of the museum, institution, or Federal agency that has control of the Native American human remains. The National Park Service is not responsible for the determinations in this notice. \n Consultation \n A detailed assessment of the human remains was made by the San Diego Museum of Man professional staff in consultation with representatives of the Pauma Band of Luiseno Mission Indians of the Pauma & Yuima Reservation, California; Pechanga Band of Luiseno Mission Indians of the Pechanga Reservation, California; Rincon Band of Luiseno Mission Indians of the Rincon Reservation, California; and the Santa Ynez Band of Chumash Mission Indians of the Santa Ynez Reservation, California (hereafter referred to as \\xe2\\x80\\x9cThe Tribes\\xe2\\x80\\x9d). \n History and Description of the Remains \n In 1937, human remains representing, at minimum, one individual were donated to the San Diego Museum of Man by Mrs. L. H. Sherman. These human remains had been removed from San Nicolas Island (SNI), Ventura County, CA. No primary documentation or specific provenience information beyond their SNI origin exists for these human remains. No known individual was identified. \n An examination of the human remains by San Diego Museum of Man physical anthropology professional staff determined the individual to be of Native American origin. Archeological data indicate that The Tribes can trace their ancestry back to the people who previously occupied on the Channel Islands. \n Determinations Made by the San Diego Museum of Man \n Officials of the San Diego Museum of Man have determined that: \n \\xe2\\x80\\xa2 Pursuant to 25 U.S.C. 3001(9), the human remains described in this notice represent the physical remains of one individual of Native American ancestry. \n \\xe2\\x80\\xa2 Pursuant to 25 U.S.C. 3001(2), there is a relationship of shared group identity that can be reasonably traced between the Native American human remains and The Tribes. \n Additional Requestors and Disposition \n Lineal descendants or representatives of any Indian Tribe or Native Hawaiian organization not identified in this notice that wish to request transfer of control of these human remains should submit a written request with information in support of the request to Ben Garcia, Deputy Director, San Diego Museum of Man, 1350 El Prado, San Diego, CA 92101, telephone (619) 239-2001 Ext. 17, email bgarcia@museumofman.org, by April 1, 2019. After that date, if no additional requestors have come forward, transfer of control of the human remains to The Tribes may proceed. \n The San Diego Museum of Man is responsible for notifying The Tribes that this notice has been published. \n ", "consultation": "A detailed assessment of the human remains was made by the San Diego Museum of Man professional staff in consultation with representatives of the Pauma Band of Luiseno Mission Indians of the Pauma & Yuima Reservation, California; Pechanga Band of Luiseno Mission Indians of the Pechanga Reservation, California; Rincon Band of Luiseno Mission Indians of the Rincon Reservation, California; and the Santa Ynez Band of Chumash Mission Indians of the Santa Ynez Reservation, California (hereafter referred to as \\xe2\\x80\\x9cThe Tribes\\xe2\\x80\\x9d). \n ", "h_d_r": "In 1937, human remains representing, at minimum, one individual were donated to the San Diego Museum of Man by Mrs. L. H. Sherman. These human remains had been removed from San Nicolas Island (SNI), Ventura County, CA. No primary documentation or specific provenience information beyond their SNI origin exists for these human remains. No known individual was identified. \n An examination of the human remains by San Diego Museum of Man physical anthropology professional staff determined the individual to be of Native American origin. Archeological data indicate that The Tribes can trace their ancestry back to the people who previously occupied on the Channel Islands. \n ", "h_d_ci": "Null", "determinations": "Determinations Made by the San Diego Museum of Man \n Officials of the San Diego Museum of Man have determined that: \n \\xe2\\x80\\xa2 Pursuant to 25 U.S.C. 3001(9), the human remains described in this notice represent the physical remains of one individual of Native American ancestry. \n \\xe2\\x80\\xa2 Pursuant to 25 U.S.C. 3001(2), there is a relationship of shared group identity that can be reasonably traced between the Native American human remains and The Tribes. \n ", "a_r_d": "Lineal descendants or representatives of any Indian Tribe or Native Hawaiian organization not identified in this notice that wish to request transfer of control of these human remains should submit a written request with information in support of the request to Ben Garcia, Deputy Director, San Diego Museum of Man, 1350 El Prado, San Diego, CA 92101, telephone (619) 239-2001 Ext. 17, email bgarcia@museumofman.org, by April 1, 2019. After that date, if no additional requestors have come forward, transfer of control of the human remains to The Tribes may proceed. \n The San Diego Museum of Man is responsible for notifying The Tribes that this notice has been published. \n "}