{"index": "I_1527", "messy_full": "\\n      \\n        DEPARTMENT OF THE INTERIOR\\n        National Park Service\\n        Notice of Inventory Completion for Human Remains in the Possession of the Bernice Pauahi Bishop Museum, Honolulu, HI; Correction\\n        \\n          AGENCY:\\n          National Park Service, Interior.\\n        \\n        \\n          ACTION:\\n          Notice; correction.\\n        \\n        Notice is here given in accordance with the Native American Graves Protection and Repatriation Act (NAGPRA), 25 U.S.C. 3003, of the completion of an inventory of human remains in the possession and control of the Bishop Museum, Honolulu, HI. The human remains were removed from Lanai Island, HI.\\n        This notice is published as part of the National Park Service\\'s administrative responsibilities under NAGPRA, 25 U.S.C. 3003 (d)(3). The determinations in this notice are the sole responsibility of the museum, institution, or Federal agency that has control of the Native American human remains and associated funerary objects. The National Park Service is not responsible for the determinations in this notice.\\n        This notice corrects the Native Hawaiian Organizations to whom the human remains will be repatriated.\\n        In the Federal Register of October 10, 2002 (FR Doc 02-25871, pages 63151-63152), paragraph numbers 6 and 7 are corrected by substituting the following paragraphs:\\n        Officials of the Bishop Museum have determined that, pursuant to 25 U.S.C. 3001 (9-10), the human remains described above represent the physical remains of two individuals of Native Hawaiian ancestry. Officials of the Bishop Museum also have determined that, pursuant to 25 U.S.C. 3001 (2), there is a relationship of shared group identity that can be reasonably traced between the Native Hawaiian human remains and Hui Kako`o and Hui Malama I Na Kupuna O Hawaii Nei. Lastly, officials of the Bishop Museum have determined that Hui Kako`o is the most appropriate claimant for repatriation of the human remains.\\n        Representatives of any other Native Hawaiian Organization that believes itself to be culturally affiliated with the human remains should contact Betty Lou Kam, Vice President, Cultural Studies, Bishop Museum, 1525 Bernice Street, Honolulu, HI 96817, telephone (808) 848-4144, before June 30, 2008. Repatriation to Hui Kako`o will proceed after that date if no additional claimants come forward.\\n        The Bishop Museum is responsible for notifying Hui Kako`o, Lana`i Island Burial Council, Hui Malama I Na Kupuna O Hawaii Nei, and Office of Hawaiian Affairs.\\n        \\n          Dated: April 23, 2008\\n          Sherry Hutt,\\n          Manager, National NAGPRA Program.\\n        \\n      \\n      [FR Doc. E8-12003 Filed 5-28-08; 8:45 am]\\n      BILLING CODE 4312-50-S\\n    ", "agency1": "DEPARTMENT OF THE INTERIOR", "sub_agency1": "National Park Service", "dep_doc": "Null", "subject": "Notice of Inventory Completion for Human Remains in the Possession of the Bernice Pauahi Bishop Museum, Honolulu, HI; Correction", "agency2": "National Park Service, Interior.", "action": "Notice; correction.", "summary": "Null", "dates": "Null", "addresses": "Null", "signature_dated": "Dated: April 23, 2008", "signature_name": "Sherry Hutt,", "signature_title": "Manager, National NAGPRA Program.", "fr_doc": "[FR Doc. E8-12003 Filed 5-28-08; 8:45 am]", "billing_code": "BILLING CODE 4312-50-S", "supp_info": "Null", "consultation": "Null", "h_d_r": "Null", "h_d_ci": "Null", "determinations": "Null", "a_r_d": "Null"}