{"index": "I_1618", "messy_full": "\\n      \\n        DEPARTMENT OF THE INTERIOR\\n        National Park Service\\n        Notice of Inventory Completion: Bishop Museum, Honolulu, HI\\n        \\n          AGENCY:\\n          National Park Service, Interior.\\n        \\n        \\n          ACTION:\\n          Notice.\\n        \\n        Notice is here given in accordance with the Native American Graves Protection and Repatriation Act (NAGPRA), 25 U.S.C. 3003, of the completion of an inventory of human remains in the possession and control of Bishop Museum, Honolulu, HI. The human remains were removed from multiple locations on the island of Kauai, HI.\\n        This notice is published as part of the National Park Service\\'s administrative responsibilities under NAGPRA, 25 U.S.C. 3003 (d)(3). The determinations in this notice are the sole responsibility of the museum, institution, or Federal agency that has control of the Native American human remains. The National Park Service is not responsible for the determinations in this notice.\\n        A detailed assessment of the human remains was made by Bishop Museum professional staff in consultation with representatives of Hui Malama I Na Kupuna O Hawaii Nei and Kauai Island Burial Council.\\n        In 1949, two bags of human bone representing a minimum of one individual were collected by Tiare Emory and Rebecca Banks from Milolii, Napali, Kauai, HI. No known individual was identified. No associated funerary objects are present.\\n        In 1949, one human tooth and one bag of possible human bone fragments representing a minimum of one individual were collected by Tiare Emory and Rebecca Banks possibly from Canoe Shed Cave, Hanalei, Kauai, HI. No known individual was identified. No associated funerary objects are present.\\n        In 1955, Bishop Museum received two human teeth representing a minimum of one individual collected by George F. Arnemann from archeology site 50-Ka-C07-001, Haeleele, Kauai, HI. No known individual was identified. No associated funerary objects are present.\\n        In 1955, one human tooth representing a minimum of one individual was collected during a Bishop Museum and University of Hawaii-Manoa field school project by Bishop Museum staff from Haeleele Shelter (archeology site 50-Ka-C07-001), Kauai, HI. No known individual was identified. No associated funerary objects are present.\\n        In 1967, one human tooth and one human tooth fragment representing a minimum of one individual were found among midden at Moir\\'s Garden, Koloa, Kauai, HI, by Bishop Museum staff. No known individual was identified. No associated funerary objects are present.\\n        In 2002, three human teeth representing a minimum of one individual were found in the Bishop Museum collections from an unknown area of Kauai, HI. No known individual was identified. No associated funerary objects are present.\\n        Officials of the Bishop Museum have determined that, pursuant to 25 U.S.C. 3001 (9-10), the human remains described above represent the physical remains of a minimum of six individuals of Native Hawaiian ancestry. Officials of the Bishop Museum also have determined that, pursuant to 25 U.S.C. 3001 (2), there is a relationship of shared group identity that can be reasonably traced between the Native Hawaiian human remains and Hui Malama I Na Kupuna O Hawaii Nei.\\n        Representatives of any other Native Hawaiian organization that believes itself to be culturally affiliated with the human remains should contact Betty Lou Kam, Vice-President, Cultural Resources, Bishop Museum, 1525 Bernice Street, Honolulu, HI 96817, telephone (808) 848-4144, before September 12, 2007. Repatriation of the human remains to Hui Malama I Na Kupuna O Hawaii Nei will proceed after that date if no additional claimants come forward.\\n        The Bishop Museum is responsible for notifying Hui Malama I Na Kupuna O Hawaii Nei and Kauai Island Burial Council that this notice has been published.\\n        \\n          Dated: July 13, 2007\\n          Sherry Hutt,\\n          Manager, National NAGPRA Program.\\n        \\n      \\n      [FR Doc. E7-15822 Filed 8-10-07; 8:45 am]\\n      BILLING CODE 4312-50-S\\n    ", "agency1": "DEPARTMENT OF THE INTERIOR", "sub_agency1": "National Park Service", "dep_doc": "Null", "subject": "Notice of Inventory Completion: Bishop Museum, Honolulu, HI", "agency2": "National Park Service, Interior.", "action": "Notice.", "summary": "Null", "dates": "Null", "addresses": "Null", "signature_dated": "Dated: July 13, 2007", "signature_name": "Sherry Hutt,", "signature_title": "Manager, National NAGPRA Program.", "fr_doc": "[FR Doc. E7-15822 Filed 8-10-07; 8:45 am]", "billing_code": "BILLING CODE 4312-50-S", "supp_info": "Null", "consultation": "Null", "h_d_r": "Null", "h_d_ci": "Null", "determinations": "Null", "a_r_d": "Null"}