{"index": "I_1793", "messy_full": "\\n      \\n        DEPARTMENT OF THE INTERIOR\\n        National Park Service\\n        Notice of Inventory Completion: Missouri Department of Natural Resources\\n        \\n          AGENCY:\\n          National Park Service, Interior.\\n        \\n        \\n          ACTION:\\n          Notice.\\n        \\n        Notice is here given in accordance with the Native American Graves Protection and Repatriation Act (NAGPRA), 25 U.S.C. 3003, of the completion of an inventory of human remains in the possession of the Missouri Department of Natural Resources, Jefferson City, MO. The human remains were removed from archeological site 23CK116, the Illiniwek Village State Historic Site, Clark County, MO.\\n        This notice is published as part of the National Park Service\\'s administrative responsibilities under NAGPRA, 25 U.S.C. 3003 (d)(3). The determinations in this notice are the sole responsibility of the museum, institution, or Federal agency that has control of the Native American human remains. The National Park Service is not responsible for the determinations in this notice. \\n        A detailed assessment of the human remains was made by the Missouri Department of Natural Resources professional staff in consultation with representatives of the Peoria Tribe of Indians of Oklahoma.\\n        In 1998, human remains representing a minimum of one individual were removed from 23CK116, the Illiniwek Village State Historic Site, in Clark County, MO (burial case 95\\xc2\\xaf006). The human remains were recovered by Department of Natural Resources, Division of State Parks archeologists in 1998 from an actively eroding farm road crossing the Illiniwek Village site. The human remains were transported to Jefferson City and have been kept in curation in a state\\xc2\\xafowned facility. No known individual was identified. No associated funerary objects are present. \\n        The human remains have been identified as Illinois based on the information in the 1673 Mississippi river journals of Marquette and Joliet, describing a village on the Des Moines River known as \\xe2\\x80\\x9cPeoria\\xe2\\x80\\x9d with approximately 8,000 inhabitants, and on the recovery of historic artifacts and trade goods. The human remains are very gracile, as is typical of the Illinois.\\n        Officials of the Missouri Department of Natural Resources have determined that, pursuant to 25 U.S.C. 3001 (9\\xc2\\xaf10), the human remains described above represent the physical remains of one individual of Native American ancestry. Officials of the Missouri Department of Natural Resources also have determined that, pursuant to 25 U.S.C. 3001 (2), there is a relationship of shared group identity that can be reasonably traced between the Native American human remains and the Peoria Tribe of Indians of Oklahoma.\\n        \\n        Representatives of any other Indian tribe that believes itself to be culturally affiliated with the human remains should contact Judith Deel, Department of Natural Resources, State Historic Preservation Office, 101 East High Street, Jefferson City, MO 65101, telephone (573) 751\\xc2\\xaf7862, before March 24, 2005. Repatriation of the human remains to the Peoria Tribe of Indians of Oklahoma may proceed after that date if no additional claimants come forward.\\n        The Missouri Department of Natural Resources is responsible for notifying the Peoria Tribe of Indians of Oklahoma that this notice has been published.\\n        \\n          Sherry Hutt,\\n          Manager, National NAGPRA Program.\\n        \\n      \\n      [FR Doc. 05-3322 Filed 2-18-05; 8:45 am]\\n      BILLING CODE 4312-50-S\\n    ", "agency1": "DEPARTMENT OF THE INTERIOR", "sub_agency1": "National Park Service", "dep_doc": "Null", "subject": "Notice of Inventory Completion: Missouri Department of Natural Resources", "agency2": "National Park Service, Interior.", "action": "Notice.", "summary": "Null", "dates": "Null", "addresses": "Null", "signature_dated": "Null", "signature_name": "Sherry Hutt,", "signature_title": "Manager, National NAGPRA Program.", "fr_doc": "[FR Doc. 05-3322 Filed 2-18-05; 8:45 am]", "billing_code": "BILLING CODE 4312-50-S", "supp_info": "Null", "consultation": "Null", "h_d_r": "Null", "h_d_ci": "Null", "determinations": "Null", "a_r_d": "Null"}