{"index": "I_178", "messy_full": "\\n      \\n        DEPARTMENT OF THE INTERIOR\\n        National Park Service\\n        [NPS-WASO-NAGPRA-NPS0027077; PPWOCRADN0-PCU00RP14.R50000]\\n        Notice of Inventory Completion: Peabody Museum of Archaeology and Ethnology, Harvard University, Cambridge, MA\\n        \\n          AGENCY:\\n          National Park Service, Interior.\\n        \\n        \\n          ACTION:\\n          Notice.\\n        \\n        \\n          SUMMARY:\\n          The Peabody Museum of Archaeology and Ethnology has completed an inventory of human remains in consultation with the appropriate Indian Tribes or Native Hawaiian organizations, and has determined that there is no cultural affiliation between the human remains and any present-day Indian Tribes or Native Hawaiian organizations. Representatives of any Indian Tribe or Native Hawaiian organization not identified in this notice that wish to request transfer of control of these human remains should submit a written request to the Peabody Museum of Archaeology and Ethnology. If no additional requestors come forward, transfer of control of the human remains to the Indian Tribes or Native Hawaiian organizations stated in this notice may proceed.\\n        \\n        \\n          DATES:\\n          Representatives of any Indian Tribe or Native Hawaiian organization not identified in this notice that wish to request transfer of control of these human remains should submit a written request with information in support of the request to the Peabody Museum of Archaeology and Ethnology at the address in this notice by January 22, 2019.\\n        \\n        \\n          ADDRESSES:\\n\\n          Patricia Capone, Museum Curator and Director of Research and Repatriation, Peabody Museum of Archaeology and Ethnology, Harvard University, 11 Divinity Avenue, Cambridge, MA 02138, telephone (617) 496-3702, email pcapone@fas.harvard.edu.\\n          \\n        \\n      \\n      \\n        SUPPLEMENTARY INFORMATION:\\n        Notice is here given in accordance with the Native American Graves Protection and Repatriation Act (NAGPRA), 25 U.S.C. 3003, of the completion of an inventory of human remains under the control of the Peabody Museum of Archaeology and Ethnology, Harvard University, Cambridge, MA. The human remains were removed from DeSoto County, MS.\\n        This notice is published as part of the National Park Service\\'s administrative responsibilities under NAGPRA, 25 U.S.C. 3003(d)(3) and 43 CFR 10.11(d). The determinations in this notice are the sole responsibility of the museum, institution, or Federal agency that has control of the Native American human remains. The National Park Service is not responsible for the determinations in this notice.\\n        Consultation\\n        A detailed assessment of the human remains was made by the Peabody Museum of Archaeology and Ethnology professional staff in consultation with representatives of the Cherokee Nation; Eastern Band of Cherokee Indians; The Chickasaw Nation; The Choctaw Nation of Oklahoma; The Muscogee (Creek) Nation; and United Keetoowah Band of Cherokee Indians in Oklahoma.\\n        History and Description of the Remains\\n\\n        Sometime prior to 1887, human remains representing, at minimum, one individual were removed from the mound at the Lake Cormorant Site (22Ds501), in DeSoto County, MS, by F. H. Bierbower. The Peabody Museum of Archaeology and Ethnology purchased these human remains from Mr. Bierbower in 1887. No known individuals were identified.\\n        \\n        Determinations Made by the Peabody Museum of Archaeology and Ethnology\\n        Officials of the Peabody Museum of Archaeology and Ethnology have determined that:\\n        \\xe2\\x80\\xa2 Pursuant to 25 U.S.C. 3001(9), the human remains described in this notice are Native American based on archeological context, museum records, and osteological analysis.\\n        \\xe2\\x80\\xa2 Pursuant to 25 U.S.C. 3001(9), the human remains described in this notice represent the physical remains of one individual of Native American ancestry.\\n        \\xe2\\x80\\xa2 Pursuant to 25 U.S.C. 3001(2), a relationship of shared group identity cannot be reasonably traced between the Native American human remains and any present-day Indian Tribe.\\n        \\xe2\\x80\\xa2 According to final judgments of the Indian Claims Commission or the Court of Federal Claims, Treaties, Acts of Congress, or Executive Orders, the land from which the Native American human remains were removed is the aboriginal land of The Chickasaw Nation.\\n        \\xe2\\x80\\xa2 Pursuant to 43 CFR 10.11(c)(1), the disposition of the human remains may be to The Chickasaw Nation.\\n        Additional Requestors and Disposition\\n\\n        Representatives of any Indian Tribe or Native Hawaiian organization not identified in this notice that wish to request transfer of control of these human remains should submit a written request with information in support of the request to Patricia Capone, Museum Curator and Director of Research and Repatriation, Peabody Museum of Archaeology and Ethnology, Harvard University, 11 Divinity Avenue, Cambridge, MA 02138, telephone (617) 496-3702, email pcapone@fas.harvard.edu, by January 22, 2019. After that date, if no additional requestors have come forward, transfer of control of the human remains to The Chickasaw Nation may proceed.\\n        The Peabody Museum of Archaeology and Ethnology is responsible for notifying the Cherokee Nation; Eastern Band of Cherokee Indians; The Chickasaw Nation; The Choctaw Nation of Oklahoma; The Muscogee (Creek) Nation; and the United Keetoowah Band of Cherokee Indians in Oklahoma that this notice has been published.\\n        \\n          Dated: November 28, 2018.\\n          Melanie O\\'Brien,\\n          Manager, National NAGPRA Program. \\n        \\n      \\n      [FR Doc. 2018-27700 Filed 12-20-18; 8:45 am]\\n       BILLING CODE 4312-52-P\\n    ", "agency1": "DEPARTMENT OF THE INTERIOR", "sub_agency1": "National Park Service", "dep_doc": "[NPS-WASO-NAGPRA-NPS0027077; PPWOCRADN0-PCU00RP14.R50000]", "subject": "Notice of Inventory Completion: Peabody Museum of Archaeology and Ethnology, Harvard University, Cambridge, MA", "agency2": "National Park Service, Interior.", "action": "Notice.", "summary": "The Peabody Museum of Archaeology and Ethnology has completed an inventory of human remains in consultation with the appropriate Indian Tribes or Native Hawaiian organizations, and has determined that there is no cultural affiliation between the human remains and any present-day Indian Tribes or Native Hawaiian organizations. Representatives of any Indian Tribe or Native Hawaiian organization not identified in this notice that wish to request transfer of control of these human remains should submit a written request to the Peabody Museum of Archaeology and Ethnology. If no additional requestors come forward, transfer of control of the human remains to the Indian Tribes or Native Hawaiian organizations stated in this notice may proceed.", "dates": "Representatives of any Indian Tribe or Native Hawaiian organization not identified in this notice that wish to request transfer of control of these human remains should submit a written request with information in support of the request to the Peabody Museum of Archaeology and Ethnology at the address in this notice by January 22, 2019.", "addresses": "Patricia Capone, Museum Curator and Director of Research and Repatriation, Peabody Museum of Archaeology and Ethnology, Harvard University, 11 Divinity Avenue, Cambridge, MA 02138, telephone (617) 496-3702, email pcapone@fas.harvard.edu.\\n          ", "signature_dated": "Dated: November 28, 2018.", "signature_name": "Melanie O\\'Brien,", "signature_title": "Manager, National NAGPRA Program. ", "fr_doc": "[FR Doc. 2018-27700 Filed 12-20-18; 8:45 am]", "billing_code": " BILLING CODE 4312-52-P", "supp_info": "SUPPLEMENTARY INFORMATION: \n Notice is here given in accordance with the Native American Graves Protection and Repatriation Act (NAGPRA), 25 U.S.C. 3003, of the completion of an inventory of human remains under the control of the Peabody Museum of Archaeology and Ethnology, Harvard University, Cambridge, MA. The human remains were removed from DeSoto County, MS. \n This notice is published as part of the National Park Service\\'s administrative responsibilities under NAGPRA, 25 U.S.C. 3003(d)(3) and 43 CFR 10.11(d). The determinations in this notice are the sole responsibility of the museum, institution, or Federal agency that has control of the Native American human remains. The National Park Service is not responsible for the determinations in this notice. \n Consultation \n A detailed assessment of the human remains was made by the Peabody Museum of Archaeology and Ethnology professional staff in consultation with representatives of the Cherokee Nation; Eastern Band of Cherokee Indians; The Chickasaw Nation; The Choctaw Nation of Oklahoma; The Muscogee (Creek) Nation; and United Keetoowah Band of Cherokee Indians in Oklahoma. \n History and Description of the Remains \n Sometime prior to 1887, human remains representing, at minimum, one individual were removed from the mound at the Lake Cormorant Site (22Ds501), in DeSoto County, MS, by F. H. Bierbower. The Peabody Museum of Archaeology and Ethnology purchased these human remains from Mr. Bierbower in 1887. No known individuals were identified.\\n         \n Determinations Made by the Peabody Museum of Archaeology and Ethnology \n Officials of the Peabody Museum of Archaeology and Ethnology have determined that: \n \\xe2\\x80\\xa2 Pursuant to 25 U.S.C. 3001(9), the human remains described in this notice are Native American based on archeological context, museum records, and osteological analysis. \n \\xe2\\x80\\xa2 Pursuant to 25 U.S.C. 3001(9), the human remains described in this notice represent the physical remains of one individual of Native American ancestry. \n \\xe2\\x80\\xa2 Pursuant to 25 U.S.C. 3001(2), a relationship of shared group identity cannot be reasonably traced between the Native American human remains and any present-day Indian Tribe. \n \\xe2\\x80\\xa2 According to final judgments of the Indian Claims Commission or the Court of Federal Claims, Treaties, Acts of Congress, or Executive Orders, the land from which the Native American human remains were removed is the aboriginal land of The Chickasaw Nation. \n \\xe2\\x80\\xa2 Pursuant to 43 CFR 10.11(c)(1), the disposition of the human remains may be to The Chickasaw Nation. \n Additional Requestors and Disposition \n Representatives of any Indian Tribe or Native Hawaiian organization not identified in this notice that wish to request transfer of control of these human remains should submit a written request with information in support of the request to Patricia Capone, Museum Curator and Director of Research and Repatriation, Peabody Museum of Archaeology and Ethnology, Harvard University, 11 Divinity Avenue, Cambridge, MA 02138, telephone (617) 496-3702, email pcapone@fas.harvard.edu, by January 22, 2019. After that date, if no additional requestors have come forward, transfer of control of the human remains to The Chickasaw Nation may proceed. \n The Peabody Museum of Archaeology and Ethnology is responsible for notifying the Cherokee Nation; Eastern Band of Cherokee Indians; The Chickasaw Nation; The Choctaw Nation of Oklahoma; The Muscogee (Creek) Nation; and the United Keetoowah Band of Cherokee Indians in Oklahoma that this notice has been published. \n ", "consultation": "A detailed assessment of the human remains was made by the Peabody Museum of Archaeology and Ethnology professional staff in consultation with representatives of the Cherokee Nation; Eastern Band of Cherokee Indians; The Chickasaw Nation; The Choctaw Nation of Oklahoma; The Muscogee (Creek) Nation; and United Keetoowah Band of Cherokee Indians in Oklahoma. \n ", "h_d_r": "Sometime prior to 1887, human remains representing, at minimum, one individual were removed from the mound at the Lake Cormorant Site (22Ds501), in DeSoto County, MS, by F. H. Bierbower. The Peabody Museum of Archaeology and Ethnology purchased these human remains from Mr. Bierbower in 1887. No known individuals were identified.\\n         \n ", "h_d_ci": "Null", "determinations": "Determinations Made by the Peabody Museum of Archaeology and Ethnology \n Officials of the Peabody Museum of Archaeology and Ethnology have determined that: \n \\xe2\\x80\\xa2 Pursuant to 25 U.S.C. 3001(9), the human remains described in this notice are Native American based on archeological context, museum records, and osteological analysis. \n \\xe2\\x80\\xa2 Pursuant to 25 U.S.C. 3001(9), the human remains described in this notice represent the physical remains of one individual of Native American ancestry. \n \\xe2\\x80\\xa2 Pursuant to 25 U.S.C. 3001(2), a relationship of shared group identity cannot be reasonably traced between the Native American human remains and any present-day Indian Tribe. \n \\xe2\\x80\\xa2 According to final judgments of the Indian Claims Commission or the Court of Federal Claims, Treaties, Acts of Congress, or Executive Orders, the land from which the Native American human remains were removed is the aboriginal land of The Chickasaw Nation. \n \\xe2\\x80\\xa2 Pursuant to 43 CFR 10.11(c)(1), the disposition of the human remains may be to The Chickasaw Nation. \n ", "a_r_d": "Representatives of any Indian Tribe or Native Hawaiian organization not identified in this notice that wish to request transfer of control of these human remains should submit a written request with information in support of the request to Patricia Capone, Museum Curator and Director of Research and Repatriation, Peabody Museum of Archaeology and Ethnology, Harvard University, 11 Divinity Avenue, Cambridge, MA 02138, telephone (617) 496-3702, email pcapone@fas.harvard.edu, by January 22, 2019. After that date, if no additional requestors have come forward, transfer of control of the human remains to The Chickasaw Nation may proceed. \n The Peabody Museum of Archaeology and Ethnology is responsible for notifying the Cherokee Nation; Eastern Band of Cherokee Indians; The Chickasaw Nation; The Choctaw Nation of Oklahoma; The Muscogee (Creek) Nation; and the United Keetoowah Band of Cherokee Indians in Oklahoma that this notice has been published. \n "}