{"index": "I_189", "messy_full": "\\n      \\n        DEPARTMENT OF THE INTERIOR\\n        National Park Service\\n        [NPS-WASO-NAGPRA-NPS0026955; PPWOCRADN0-PCU00RP14.R50000]\\n        Notice of Inventory Completion: Wisconsin Historical Society, Madison, WI\\n        \\n          AGENCY:\\n          National Park Service, Interior.\\n        \\n        \\n          ACTION:\\n          Notice.\\n        \\n        \\n          SUMMARY:\\n          The Wisconsin Historical Society has completed an inventory of human remains and associated funerary objects, in consultation with the appropriate Indian Tribes or Native Hawaiian organizations, and has determined that there is no cultural affiliation between the human remains and associated funerary objects and any present-day Indian Tribes or Native Hawaiian organizations. Representatives of any Indian Tribe or Native Hawaiian organization not identified in this notice that wish to request transfer of control of these human remains and associated funerary objects should submit a written request to the Wisconsin Historical Society. If no additional requestors come forward, transfer of control of the human remains and associated funerary objects to the Indian Tribes or Native Hawaiian organizations stated in this notice may proceed.\\n        \\n        \\n          DATES:\\n          Representatives of any Indian Tribe or Native Hawaiian organization not identified in this notice that wish to request transfer of control of these human remains and associated funerary objects should submit a written request with information in support of the request to the Wisconsin Historical Society at the address in this notice by January 4, 2019.\\n        \\n        \\n          ADDRESSES:\\n\\n          Jennifer Kolb, Wisconsin Historical Society, 816 State St., Madison, WI 53706, telephone (608) 264-6434, email Jennifer.Kolb@wisconsinhistory.org.\\n          \\n        \\n      \\n      \\n        SUPPLEMENTARY INFORMATION:\\n        Notice is here given in accordance with the Native American Graves Protection and Repatriation Act (NAGPRA), 25 U.S.C. 3003, of the completion of an inventory of human remains and associated funerary objects under the control of the Wisconsin Historical Society, Madison, WI. The human remains and associated funerary objects were removed from the Earll II Site, Vernon County, WI.\\n\\n        This notice is published as part of the National Park Service\\'s administrative responsibilities under NAGPRA, 25 U.S.C. 3003(d)(3) and 43 CFR 10.11(d). The determinations in this notice are the sole responsibility of the museum, institution, or Federal agency that has control of the Native American human remains and associated funerary objects. The National Park Service is not responsible for the determinations in this notice.\\n        Consultation\\n        A detailed assessment of the human remains was made by the Wisconsin Historical Society professional staff in consultation with representatives of the Forest County Potawatomi Community, Wisconsin; Ho-Chunk Nation of Wisconsin; Lac du Flambeau Band of Lake Superior Chippewa Indians of the Lac du Flambeau Reservation of Wisconsin; Menominee Indian Tribe of Wisconsin; and the Upper Sioux Community, Minnesota, hereafter referred to as \\xe2\\x80\\x9cThe Consulted Tribes.\\xe2\\x80\\x9d\\n        History and Description of the Remains\\n        In 1960, human remains representing, at minimum, one individual were removed from the Earll II Site (47-VE-0050) in Vernon County, WI. The site was investigated by the Wisconsin Historical Society (WHS) in 1960, as part of the LaFarge Dam Project. During this project, the WHS excavated two of three mounds found at the site\\xe2\\x80\\x94the linear mound (Mound 2) and one of the oval mounds (Mound 1)\\xe2\\x80\\x94that were slated for destruction to make way for the relocation of State Highway 131. In Mound 2, WHS archeologists found a subfloor burial pit that contained human remains that were later determined to belong to a Native American adult of indeterminate sex. No known individuals were identified. The seven associated funerary objects are one group of stone flakes, one chert flake, one chert projectile point, one biface fragment, one chert projectile point fragment, one faunal tooth, and one ceramic sherd.\\n        Determinations Made by the Wisconsin Historical Society\\n        Officials of the Wisconsin Historical Society have determined that:\\n        \\xe2\\x80\\xa2 Pursuant to 25 U.S.C. 3001(9), the human remains described in this notice are Native American based on Wisconsin Historical Society records, burial location, archeological context, oral histories, and skeletal analysis.\\n        \\xe2\\x80\\xa2 Pursuant to 25 U.S.C. 3001(9), the human remains described in this notice represent the physical remains of one individual of Native American ancestry.\\n        \\xe2\\x80\\xa2 Pursuant to 25 U.S.C. 3001(3)(A), the seven objects described in this notice are reasonably believed to have been placed with or near individual human remains at the time of death or later as part of the death rite or ceremony.\\n        \\xe2\\x80\\xa2 Pursuant to 25 U.S.C. 3001(2), a relationship of shared group identity cannot be reasonably traced between the Native American human remains associated funerary objects and any present-day Indian Tribe.\\n        \\xe2\\x80\\xa2 According to final judgments of the Indian Claims Commission or the Court of Federal Claims, the land from which the Native American human remains were removed is the aboriginal land of the Ho-Chunk Nation of Wisconsin and the Winnebago Tribe of Nebraska.\\n        \\xe2\\x80\\xa2 Treaties, Acts of Congress, or Executive Orders, indicate that the land from which the Native American human remains were removed is the aboriginal land of the Assiniboine and Sioux Tribes of the Fort Peck Indian Reservation, Montana; Cheyenne River Sioux Tribe of the Cheyenne River Reservation, South Dakota; Crow Creek Sioux Tribe of the Crow Creek Reservation, South Dakota; Flandreau Santee Sioux Tribe of South Dakota; Ho-Chunk Nation of Wisconsin; Lower Brule Sioux Tribe of the Lower Brule Reservation, South Dakota; Lower Sioux Indian Community in the State of Minnesota; Oglala Sioux Tribe (previously listed as the Oglala Sioux Tribe of the Pine Ridge Reservation, South Dakota); Prairie Island Indian Community in the State of Minnesota; Rosebud Sioux Tribe of the Rosebud Indian Reservation, South Dakota; Santee Sioux Nation, Nebraska; Shakopee Mdewakanton Sioux Community of Minnesota; Sisseton-Wahpeton Oyate of the Lake Traverse Reservation, South Dakota; Spirit Lake Tribe, North Dakota; Standing Rock Sioux Tribe of North & South Dakota; Upper Sioux Community, Minnesota; Winnebago Tribe of Nebraska; and the Yankton Sioux Tribe of South Dakota, hereafter referred to as \\xe2\\x80\\x9cThe Aboriginal Land Tribes.\\xe2\\x80\\x9d\\n        \\xe2\\x80\\xa2 Pursuant to 43 CFR 10.11(c)(1), the disposition of the human remains may be to The Aboriginal Land Tribes.\\n        Additional Requestors and Disposition\\n\\n        Representatives of any Indian Tribe or Native Hawaiian organization not identified in this notice that wish to request transfer of control of these human remains and associated funerary objects should submit a written request with information in support of the request to Jennifer Kolb, Wisconsin Historical Society, 816 State St., Madison, WI 53706, telephone (608) 264-6434, email Jennifer.Kolb@wisconsinhistory.org, by January 4, 2019. After that date, if no additional requestors have come forward, transfer of control of the human remains and associated funerary objects to The Aboriginal Land Tribes may proceed.\\n        The Wisconsin Historical Society is responsible for notifying The Aboriginal Land Tribes and The Consulted Tribes that this notice has been published.\\n        \\n          Dated: November 7, 2018.\\n          Melanie O\\'Brien,\\n          Manager, National NAGPRA Program. \\n        \\n      \\n      [FR Doc. 2018-26440 Filed 12-4-18; 8:45 am]\\n       BILLING CODE 4312-52-P\\n    ", "agency1": "DEPARTMENT OF THE INTERIOR", "sub_agency1": "National Park Service", "dep_doc": "[NPS-WASO-NAGPRA-NPS0026955; PPWOCRADN0-PCU00RP14.R50000]", "subject": "Notice of Inventory Completion: Wisconsin Historical Society, Madison, WI", "agency2": "National Park Service, Interior.", "action": "Notice.", "summary": "The Wisconsin Historical Society has completed an inventory of human remains and associated funerary objects, in consultation with the appropriate Indian Tribes or Native Hawaiian organizations, and has determined that there is no cultural affiliation between the human remains and associated funerary objects and any present-day Indian Tribes or Native Hawaiian organizations. Representatives of any Indian Tribe or Native Hawaiian organization not identified in this notice that wish to request transfer of control of these human remains and associated funerary objects should submit a written request to the Wisconsin Historical Society. If no additional requestors come forward, transfer of control of the human remains and associated funerary objects to the Indian Tribes or Native Hawaiian organizations stated in this notice may proceed.", "dates": "Representatives of any Indian Tribe or Native Hawaiian organization not identified in this notice that wish to request transfer of control of these human remains and associated funerary objects should submit a written request with information in support of the request to the Wisconsin Historical Society at the address in this notice by January 4, 2019.", "addresses": "Jennifer Kolb, Wisconsin Historical Society, 816 State St., Madison, WI 53706, telephone (608) 264-6434, email Jennifer.Kolb@wisconsinhistory.org.\\n          ", "signature_dated": "Dated: November 7, 2018.", "signature_name": "Melanie O\\'Brien,", "signature_title": "Manager, National NAGPRA Program. ", "fr_doc": "[FR Doc. 2018-26440 Filed 12-4-18; 8:45 am]", "billing_code": " BILLING CODE 4312-52-P", "supp_info": "SUPPLEMENTARY INFORMATION: \n Notice is here given in accordance with the Native American Graves Protection and Repatriation Act (NAGPRA), 25 U.S.C. 3003, of the completion of an inventory of human remains and associated funerary objects under the control of the Wisconsin Historical Society, Madison, WI. The human remains and associated funerary objects were removed from the Earll II Site, Vernon County, WI. \n This notice is published as part of the National Park Service\\'s administrative responsibilities under NAGPRA, 25 U.S.C. 3003(d)(3) and 43 CFR 10.11(d). The determinations in this notice are the sole responsibility of the museum, institution, or Federal agency that has control of the Native American human remains and associated funerary objects. The National Park Service is not responsible for the determinations in this notice. \n Consultation \n A detailed assessment of the human remains was made by the Wisconsin Historical Society professional staff in consultation with representatives of the Forest County Potawatomi Community, Wisconsin; Ho-Chunk Nation of Wisconsin; Lac du Flambeau Band of Lake Superior Chippewa Indians of the Lac du Flambeau Reservation of Wisconsin; Menominee Indian Tribe of Wisconsin; and the Upper Sioux Community, Minnesota, hereafter referred to as \\xe2\\x80\\x9cThe Consulted Tribes.\\xe2\\x80\\x9d \n History and Description of the Remains \n In 1960, human remains representing, at minimum, one individual were removed from the Earll II Site (47-VE-0050) in Vernon County, WI. The site was investigated by the Wisconsin Historical Society (WHS) in 1960, as part of the LaFarge Dam Project. During this project, the WHS excavated two of three mounds found at the site\\xe2\\x80\\x94the linear mound (Mound 2) and one of the oval mounds (Mound 1)\\xe2\\x80\\x94that were slated for destruction to make way for the relocation of State Highway 131. In Mound 2, WHS archeologists found a subfloor burial pit that contained human remains that were later determined to belong to a Native American adult of indeterminate sex. No known individuals were identified. The seven associated funerary objects are one group of stone flakes, one chert flake, one chert projectile point, one biface fragment, one chert projectile point fragment, one faunal tooth, and one ceramic sherd. \n Determinations Made by the Wisconsin Historical Society \n Officials of the Wisconsin Historical Society have determined that: \n \\xe2\\x80\\xa2 Pursuant to 25 U.S.C. 3001(9), the human remains described in this notice are Native American based on Wisconsin Historical Society records, burial location, archeological context, oral histories, and skeletal analysis. \n \\xe2\\x80\\xa2 Pursuant to 25 U.S.C. 3001(9), the human remains described in this notice represent the physical remains of one individual of Native American ancestry. \n \\xe2\\x80\\xa2 Pursuant to 25 U.S.C. 3001(3)(A), the seven objects described in this notice are reasonably believed to have been placed with or near individual human remains at the time of death or later as part of the death rite or ceremony. \n \\xe2\\x80\\xa2 Pursuant to 25 U.S.C. 3001(2), a relationship of shared group identity cannot be reasonably traced between the Native American human remains associated funerary objects and any present-day Indian Tribe. \n \\xe2\\x80\\xa2 According to final judgments of the Indian Claims Commission or the Court of Federal Claims, the land from which the Native American human remains were removed is the aboriginal land of the Ho-Chunk Nation of Wisconsin and the Winnebago Tribe of Nebraska. \n \\xe2\\x80\\xa2 Treaties, Acts of Congress, or Executive Orders, indicate that the land from which the Native American human remains were removed is the aboriginal land of the Assiniboine and Sioux Tribes of the Fort Peck Indian Reservation, Montana; Cheyenne River Sioux Tribe of the Cheyenne River Reservation, South Dakota; Crow Creek Sioux Tribe of the Crow Creek Reservation, South Dakota; Flandreau Santee Sioux Tribe of South Dakota; Ho-Chunk Nation of Wisconsin; Lower Brule Sioux Tribe of the Lower Brule Reservation, South Dakota; Lower Sioux Indian Community in the State of Minnesota; Oglala Sioux Tribe (previously listed as the Oglala Sioux Tribe of the Pine Ridge Reservation, South Dakota); Prairie Island Indian Community in the State of Minnesota; Rosebud Sioux Tribe of the Rosebud Indian Reservation, South Dakota; Santee Sioux Nation, Nebraska; Shakopee Mdewakanton Sioux Community of Minnesota; Sisseton-Wahpeton Oyate of the Lake Traverse Reservation, South Dakota; Spirit Lake Tribe, North Dakota; Standing Rock Sioux Tribe of North & South Dakota; Upper Sioux Community, Minnesota; Winnebago Tribe of Nebraska; and the Yankton Sioux Tribe of South Dakota, hereafter referred to as \\xe2\\x80\\x9cThe Aboriginal Land Tribes.\\xe2\\x80\\x9d \n \\xe2\\x80\\xa2 Pursuant to 43 CFR 10.11(c)(1), the disposition of the human remains may be to The Aboriginal Land Tribes. \n Additional Requestors and Disposition \n Representatives of any Indian Tribe or Native Hawaiian organization not identified in this notice that wish to request transfer of control of these human remains and associated funerary objects should submit a written request with information in support of the request to Jennifer Kolb, Wisconsin Historical Society, 816 State St., Madison, WI 53706, telephone (608) 264-6434, email Jennifer.Kolb@wisconsinhistory.org, by January 4, 2019. After that date, if no additional requestors have come forward, transfer of control of the human remains and associated funerary objects to The Aboriginal Land Tribes may proceed. \n The Wisconsin Historical Society is responsible for notifying The Aboriginal Land Tribes and The Consulted Tribes that this notice has been published. \n ", "consultation": "A detailed assessment of the human remains was made by the Wisconsin Historical Society professional staff in consultation with representatives of the Forest County Potawatomi Community, Wisconsin; Ho-Chunk Nation of Wisconsin; Lac du Flambeau Band of Lake Superior Chippewa Indians of the Lac du Flambeau Reservation of Wisconsin; Menominee Indian Tribe of Wisconsin; and the Upper Sioux Community, Minnesota, hereafter referred to as \\xe2\\x80\\x9cThe Consulted Tribes.\\xe2\\x80\\x9d \n ", "h_d_r": "In 1960, human remains representing, at minimum, one individual were removed from the Earll II Site (47-VE-0050) in Vernon County, WI. The site was investigated by the Wisconsin Historical Society (WHS) in 1960, as part of the LaFarge Dam Project. During this project, the WHS excavated two of three mounds found at the site\\xe2\\x80\\x94the linear mound (Mound 2) and one of the oval mounds (Mound 1)\\xe2\\x80\\x94that were slated for destruction to make way for the relocation of State Highway 131. In Mound 2, WHS archeologists found a subfloor burial pit that contained human remains that were later determined to belong to a Native American adult of indeterminate sex. No known individuals were identified. The seven associated funerary objects are one group of stone flakes, one chert flake, one chert projectile point, one biface fragment, one chert projectile point fragment, one faunal tooth, and one ceramic sherd. \n ", "h_d_ci": "Null", "determinations": "Determinations Made by the Wisconsin Historical Society \n Officials of the Wisconsin Historical Society have determined that: \n \\xe2\\x80\\xa2 Pursuant to 25 U.S.C. 3001(9), the human remains described in this notice are Native American based on Wisconsin Historical Society records, burial location, archeological context, oral histories, and skeletal analysis. \n \\xe2\\x80\\xa2 Pursuant to 25 U.S.C. 3001(9), the human remains described in this notice represent the physical remains of one individual of Native American ancestry. \n \\xe2\\x80\\xa2 Pursuant to 25 U.S.C. 3001(3)(A), the seven objects described in this notice are reasonably believed to have been placed with or near individual human remains at the time of death or later as part of the death rite or ceremony. \n \\xe2\\x80\\xa2 Pursuant to 25 U.S.C. 3001(2), a relationship of shared group identity cannot be reasonably traced between the Native American human remains associated funerary objects and any present-day Indian Tribe. \n \\xe2\\x80\\xa2 According to final judgments of the Indian Claims Commission or the Court of Federal Claims, the land from which the Native American human remains were removed is the aboriginal land of the Ho-Chunk Nation of Wisconsin and the Winnebago Tribe of Nebraska. \n \\xe2\\x80\\xa2 Treaties, Acts of Congress, or Executive Orders, indicate that the land from which the Native American human remains were removed is the aboriginal land of the Assiniboine and Sioux Tribes of the Fort Peck Indian Reservation, Montana; Cheyenne River Sioux Tribe of the Cheyenne River Reservation, South Dakota; Crow Creek Sioux Tribe of the Crow Creek Reservation, South Dakota; Flandreau Santee Sioux Tribe of South Dakota; Ho-Chunk Nation of Wisconsin; Lower Brule Sioux Tribe of the Lower Brule Reservation, South Dakota; Lower Sioux Indian Community in the State of Minnesota; Oglala Sioux Tribe (previously listed as the Oglala Sioux Tribe of the Pine Ridge Reservation, South Dakota); Prairie Island Indian Community in the State of Minnesota; Rosebud Sioux Tribe of the Rosebud Indian Reservation, South Dakota; Santee Sioux Nation, Nebraska; Shakopee Mdewakanton Sioux Community of Minnesota; Sisseton-Wahpeton Oyate of the Lake Traverse Reservation, South Dakota; Spirit Lake Tribe, North Dakota; Standing Rock Sioux Tribe of North & South Dakota; Upper Sioux Community, Minnesota; Winnebago Tribe of Nebraska; and the Yankton Sioux Tribe of South Dakota, hereafter referred to as \\xe2\\x80\\x9cThe Aboriginal Land Tribes.\\xe2\\x80\\x9d \n \\xe2\\x80\\xa2 Pursuant to 43 CFR 10.11(c)(1), the disposition of the human remains may be to The Aboriginal Land Tribes. \n ", "a_r_d": "Representatives of any Indian Tribe or Native Hawaiian organization not identified in this notice that wish to request transfer of control of these human remains and associated funerary objects should submit a written request with information in support of the request to Jennifer Kolb, Wisconsin Historical Society, 816 State St., Madison, WI 53706, telephone (608) 264-6434, email Jennifer.Kolb@wisconsinhistory.org, by January 4, 2019. After that date, if no additional requestors have come forward, transfer of control of the human remains and associated funerary objects to The Aboriginal Land Tribes may proceed. \n The Wisconsin Historical Society is responsible for notifying The Aboriginal Land Tribes and The Consulted Tribes that this notice has been published. \n "}