{"index": "I_1832", "messy_full": "\\n      \\n        DEPARTMENT OF THE INTERIOR\\n        National Park Service\\n        Notice of Inventory Completion: Field Museum of Natural History, Chicago, IL\\n        \\n          AGENCY:\\n          National Park Service, Interior.\\n        \\n        \\n          ACTION:\\n          Notice.\\n        \\n        Notice is here given in accordance with the Native American Graves Protection and Repatriation Act (NAGPRA), 25 U.S.C. 3003, of the completion of an inventory of human remains in the possession of the Field Museum of Natural History, Chicago, IL.  The human remains were removed from Boundary County, ID.\\n        This notice is published as part of the National Park Service\\'s administrative responsibilities under NAGPRA, 25 U.S.C. 3003 (d)(3).  The determinations in this notice are the sole responsibility of the museum, institution, or Federal agency that has control of the Native American human remains and associated funerary objects.  The National Park Service is not responsible for the determinations in this notice.\\n        A detailed assessment of the human remains was made by Field Museum of Natural History professional staff in consultation with representatives of the Kootenai Tribe of Idaho and the Confederated Salish & Kootenai Tribes of the Flathead Reservation, Montana.\\n        In 1897, human remains representing a minimum of two individuals were obtained in Bonner\\'s Ferry, Boundary County, ID, by George A. Dorsey for the Field Museum of Natural History.  The 1896-1897 Annual Report of the Director to the Board of Trustees describes a four-month trip that assistant curator of anthropology George A. Dorsey and museum photographer Edward Allen made \\xe2\\x80\\x9camong the Indians of the far West,\\xe2\\x80\\x9d that included a visit to the \\xe2\\x80\\x9cKootenay\\xe2\\x80\\x9d tribe.  The report states that \\xe2\\x80\\x9ctwo complete skeletons, a male and a female, were also secured from the Kootenay near Bonner\\'s Ferry.\\xe2\\x80\\x9d  No known individuals were identified.  No associated funerary objects are present.\\n        The human remains have been identified as Native American, based on the specific cultural and geographic attribution in Field Museum of Natural History records.  The records identify the human remains as \\xe2\\x80\\x9cKootenay\\xe2\\x80\\x9d from Bonner\\'s Ferry, ID.  \\xe2\\x80\\x9cKootenay\\xe2\\x80\\x9d descendents in Idaho are represented by the present-day Kootenai Tribe of Idaho.\\n        Officials of the Field Museum of Natural History have determined that, pursuant to 25 U.S.C. 3001 (9-10), the human remains described above represent the physical remains of two individuals of Native American ancestry.  Officials of the Field Museum of Natural History also have determined that, pursuant to 25 U.S.C. 3001 (2), there is a relationship of shared group identity that can be reasonably traced between the Native American human remains and the Kootenai Tribe of Idaho.\\n        Representatives of any other Indian tribe that believes itself to be culturally affiliated with the human remains should contact Helen Robbins, Repatriation Specialist, Field Museum of Natural History, 1400 South Lake Shore Drive, Chicago, IL 60605-2496, telephone (312) 665-7317, before October 14, 2004.  Repatriation of the human remains to the Kootenai Tribe of Idaho may proceed after that date if no additional claimants come forward.\\n\\n        The Field Museum of Natural History is responsible for notifying the Kootenai Tribe of Idaho and the Confederated Salish and Kootenai Tribes of the Flathead Reservation, Montana that this notice has been published.\\n        \\n          Dated: August 3, 2004.\\n          Sherry Hutt,\\n          Manager, National NAGPRA Program.\\n        \\n      \\n      [FR Doc. 04-20653 Filed 9-13-04; 8:45 am]\\n      BILLING CODE 4312-50-S\\n    ", "agency1": "DEPARTMENT OF THE INTERIOR", "sub_agency1": "National Park Service", "dep_doc": "Null", "subject": "Notice of Inventory Completion: Field Museum of Natural History, Chicago, IL", "agency2": "National Park Service, Interior.", "action": "Notice.", "summary": "Null", "dates": "Null", "addresses": "Null", "signature_dated": "Dated: August 3, 2004.", "signature_name": "Sherry Hutt,", "signature_title": "Manager, National NAGPRA Program.", "fr_doc": "[FR Doc. 04-20653 Filed 9-13-04; 8:45 am]", "billing_code": "BILLING CODE 4312-50-S", "supp_info": "Null", "consultation": "Null", "h_d_r": "Null", "h_d_ci": "Null", "determinations": "Null", "a_r_d": "Null"}