{"index": "I_1937", "messy_full": "\\n      \\n        DEPARTMENT OF THE INTERIOR \\n        National Park Service\\n        Notice of Inventory Completion for Native American Human Remains and Associated Funerary Objects in the Possession of the American Museum of Natural History, New York, NY\\n        \\n          AGENCY:\\n          National Park Service, Interior. \\n        \\n        \\n          ACTION:\\n          Notice. \\n        \\n        Notice is hereby given in accordance with provisions of the Native American Graves Protection and Repatriation Act (NAGPRA), 43 CFR 10.9, of the completion of an inventory of human remains in the possession of the American Museum of Natural History, New York, NY.\\n        This notice is published as part of the National Park Service\\xe2\\x80\\x99s administrative responsibilities under NAGPRA, 43 CFR 10.2 (c).  The determinations within this notice are the sole responsibility of the museum, institution, or Federal agency that has control of these Native American human remains and associated funerary objects.  The National Park Service is not responsible for the determinations within this notice.\\n        A detailed assessment of the human remains was made by American Museum of Natural History professional staff in consultation with representatives of the Hawai\\xe2\\x80\\x99i Island Burial Council, Hui Malama I Na Kupuna \\'O Hawai\\xe2\\x80\\x99i Nei, Kaua\\xe2\\x80\\x99i/Ni\\xe2\\x80\\x99ihau Island Burial Council, Maui/Lana\\xe2\\x80\\x99i Island Burial Council, Moloka\\xe2\\x80\\x99i Island Burial Council, O\\'ahu Island Burial Council, and Office of Hawaiian Affairs.\\n\\n        In an unknown year, human remains representing a minimum of one individual were collected by an unknown person from \\xe2\\x80\\x9cSandwich Islands.\\xe2\\x80\\x9d  The American Museum of Natural History received these remains in 1929 as a gift from Jessie Y. Loomis in the name of Earnest Yates Loomis, deceased.  The American Museum of Natural History\\xe2\\x80\\x99s documentation states that these human remains had been held by the American Institute of Phrenology, but it does not indicate whether Mr. or Mrs. Loomis was a member of the American Institute of Phrenology.  The American Museum of Natural History has no information regarding the American Institute of Phrenology\\xe2\\x80\\x99s acquisition of these remains.  No known individual was identified.  No associated funerary objects are present.\\n        In an unknown year, human remains representing a minimum of one individual were collected by an unknown person and identified as a \\xe2\\x80\\x9cSandwich Islander from Kahahlooa.\\xe2\\x80\\x9d  The American Museum of Natural History received these remains in 1929 as a gift from Jessie Y. Loomis in the name of Earnest Yates Loomis, deceased.  The American Museum of Natural History\\xe2\\x80\\x99s documentation states that these human remains had been held by the American Institute of Phrenology, but it does not indicate whether Mr. or Mrs. Loomis was a member of the American Institute of Phrenology.  American Museum of Natural History documentation indicates that, in 1867, these remains were in the possession of John Butler, Esq.  The American Museum of Natural History has no information regarding the American Institute of Phrenology\\xe2\\x80\\x99s or Mr. Butler\\xe2\\x80\\x99s acquisition of these remains.  No known individual was identified.  No associated funerary objects are present.\\n        These individuals have been identified as Native Hawaiian based on the American Museum of Natural History\\xe2\\x80\\x99s documentation describing each as a \\xe2\\x80\\x9cSandwich Islander.\\xe2\\x80\\x9d  Sandwich Islands is a former name of the Hawaiian Islands.  Archeological, biological, geographic, linguistic, and consultation evidence indicate a lengthy Native Hawaiian occupation of the Hawaiian Islands.  The geographic location reported for the human remains is consistent with the traditional territory of Native Hawaiians, represented here by the Hawai\\xe2\\x80\\x99i Island Burial Council, Hui Malama I Na Kupuna \\'O Hawai\\xe2\\x80\\x99i Nei, Kaua\\xe2\\x80\\x99i/Ni\\xe2\\x80\\x99ihau Island Burial Council, Maui/Lana\\xe2\\x80\\x99i Island Burial Council, Moloka\\xe2\\x80\\x99i Island Burial Council, O\\'ahu Island Burial Council, and Office of Hawaiian Affairs.\\n        Based on the above-mentioned information, officials of the American Museum of Natural History have determined that, pursuant to 43 CFR 10.2 (d)(1), the human remains listed above represent the physical remains of a minimum of two individuals of Native Hawaiian ancestry.  Officials of the American Museum of Natural History also have determined that, pursuant to 43 CFR 10.2 (e), there is a relationship of shared group identity that can be reasonably traced between these Native Hawaiian human remains and the Hawai\\xe2\\x80\\x99i Island Burial Council, Hui Malama I Na Kupuna \\'O Hawai\\xe2\\x80\\x99i Nei, Kaua\\xe2\\x80\\x99i/Ni\\xe2\\x80\\x99ihau Island Burial Council, Maui/Lana\\xe2\\x80\\x99i Island Burial Council, Moloka\\xe2\\x80\\x99i Island Burial Council, O\\'ahu Island Burial Council, and Office of Hawaiian Affairs.\\n        This notice has been sent to officials of the Hawai\\xe2\\x80\\x99i Island Burial Council, Hui Malama I Na Kupuna \\'O Hawai\\xe2\\x80\\x99i Nei, Kaua\\xe2\\x80\\x99i/Ni\\xe2\\x80\\x99ihau Island Burial Council, Maui/Lana\\xe2\\x80\\x99i Island Burial Council, Moloka\\xe2\\x80\\x99i Island Burial Council, O\\'ahu Island Burial Council, and Office of Hawaiian Affairs.  Representatives of any other Native Hawaiian organization that believes itself to be culturally affiliated with these human remains should contact Elaine Guthrie, Acting Director of Cultural Resources, American Museum of Natural History, Central Park West at 79th Street, New York, NY 10024-5192, telephone (212) 769-5835, before August 12, 2002.  Repatriation of the human remains to the Hawai\\xe2\\x80\\x99i Island Burial Council, Hui Malama I Na Kupuna \\'O Hawai\\xe2\\x80\\x99i Nei, Kaua\\xe2\\x80\\x99i/Ni\\xe2\\x80\\x99ihau Island Burial Council, Maui/Lana\\xe2\\x80\\x99i Island Burial Council, Moloka\\xe2\\x80\\x99i Island Burial Council, O\\'ahu Island Burial Council, and Office of Hawaiian Affairs may begin after that date if no additional claimants come forward.\\n        \\n          Dated: June 18, 2002\\n          Robert Stearns,\\n          Manager, National NAGPRA Program.\\n        \\n      \\n      [FR Doc. 02-17415 Filed 7-10-02; 8:45 am]\\n      BILLING CODE 4310-70-S\\n    ", "agency1": "DEPARTMENT OF THE INTERIOR ", "sub_agency1": "National Park Service", "dep_doc": "Null", "subject": "Notice of Inventory Completion for Native American Human Remains and Associated Funerary Objects in the Possession of the American Museum of Natural History, New York, NY", "agency2": "National Park Service, Interior. ", "action": "Notice. ", "summary": "Null", "dates": "Null", "addresses": "Null", "signature_dated": "Dated: June 18, 2002", "signature_name": "Robert Stearns,", "signature_title": "Manager, National NAGPRA Program.", "fr_doc": "[FR Doc. 02-17415 Filed 7-10-02; 8:45 am]", "billing_code": "BILLING CODE 4310-70-S", "supp_info": "Null", "consultation": "Null", "h_d_r": "Null", "h_d_ci": "Null", "determinations": "Null", "a_r_d": "Null"}