{"index": "I_2005", "messy_full": "\\n      \\n        DEPARTMENT OF THE INTERIOR\\n        National Park Service\\n        Notice of Inventory Completion for Native American Human Remains and Associated Funerary Objects in the Possession of the American Museum of Natural History, New York, NY\\n        \\n          AGENCY:\\n          National Park Service, Interior.\\n        \\n        \\n          ACTION:\\n          Notice.\\n        \\n\\n        Notice is hereby given in accordance with provisions of the Native American Graves Protection and Repatriation Act (NAGPRA), 43 CFR 10.9, of the completion of an inventory of human remains and associated funerary objects in the possession of the American Museum of Natural History, New York, NY.\\n        This notice is published as part of the National Park Service\\xe2\\x80\\x99s administrative responsibilities under NAGPRA, 43 CFR 10.2 (c).  The determinations within this notice are the sole responsibility of the museum, institution, or Federal agency that has control of these Native American human remains and associated funerary objects.  The National Park Service is not responsible for the determinations within this notice.\\n        A detailed assessment of the human remains was made by the American Museum of Natural History professional staff in consultation with representatives of the Battle Mountain Band of the Te-Moak Tribe of Western Shoshone Indians of Nevada; Big Pine Band of Owens Valley Paiute Shoshone Indians of the Big Pine Reservation, California; Death Valley Timbi-Sha Shoshone Band of California; Duckwater Shoshone Tribe of the Duckwater Reservation, Nevada; Elko Band of the Te-Moak Tribe of Western Shoshone Indians of Nevada; Ely Shoshone Tribe of Nevada; Fort McDermitt Paiute and Shoshone Tribes of the Fort McDermitt Indian Reservation, Nevada and Oregon; Northwestern Band of Shoshoni Nation of Utah (Washakie); Paiute-Shoshone Indians of the Bishop Community of the Bishop Colony, California; Paiute-Shoshone Indians of the Lone Pine Community of the Lone Pine Reservation, California; Paiute-Shoshone Tribe of the Fallon Reservation and Colony, Nevada; Shoshone Tribe of the Wind River Reservation, Wyoming; Shoshone-Bannock Tribes of the Fort Hall Reservation of Idaho; Shoshone-Paiute Tribes of the Duck Valley Reservation, Nevada; South Fork Band of the Te-Moak Tribe of Western Shoshone Indians of Nevada; Wells Indian Colony Band of the Te-Moak Tribe of Western Shoshone Indians of Nevada; Winnemucca Indian Colony of Nevada; and Yomba Shoshone Tribe of the Yomba Reservation, Nevada.\\n        At an unknown date, human remains representing a minimum of one individual were collected by R.W. Sears from the mouth of the Snake River, WA.  The American Museum of Natural History has no information regarding subsequent transfers of these remains until it acquired them as a purchase from the Giffort brothers in 1896.  No known individual was identified.  No associated funerary objects are present.\\n        This individual has been identified as Native American based on the American Museum of Natural History\\xe2\\x80\\x99s catalog description, which refers to the remains as \\xe2\\x80\\x9cShoshone.\\xe2\\x80\\x9d\\n        Based on the above-mentioned information, officials of the American Museum of Natural History have determined that, pursuant to 43 CFR 10.2 (d)(1), the human remains listed above represent the physical remains of a minimum of one individual of Native American ancestry.  Officials of the American Museum of Natural History also have determined that, pursuant to 43 CFR 10.2 (e), there is a relationship of shared group identity that can be reasonably traced between these Native American human remains and the Battle Mountain Band of the Te-Moak Tribe of Western Shoshone Indians of Nevada; Big Pine Band of Owens Valley Paiute Shoshone Indians of the Big Pine Reservation, California; Death Valley Timbi-Sha Shoshone Band of California; Duckwater Shoshone Tribe of the Duckwater Reservation, Nevada; Elko Band of the Te-Moak Tribe of Western Shoshone Indians of Nevada; Ely Shoshone Tribe of Nevada; Fort McDermitt Paiute and Shoshone Tribes of the Fort McDermitt Indian Reservation, Nevada and Oregon; Northwestern Band of Shoshoni Nation of Utah (Washakie); Paiute-Shoshone Indians of the Bishop Community of the Bishop Colony, California; Paiute-Shoshone Indians of the Lone Pine Community of the Lone Pine Reservation, California; Paiute-Shoshone Tribe of the Fallon Reservation and Colony, Nevada; Shoshone Tribe of the Wind River Reservation, Wyoming; Shoshone-Bannock Tribes of the Fort Hall Reservation of Idaho; Shoshone-Paiute Tribes of the Duck Valley Reservation, Nevada; South Fork Band of the Te-Moak Tribe of Western Shoshone Indians of Nevada; Wells Indian Colony Band of the Te-Moak Tribe of Western Shoshone Indians of Nevada; Winnemucca Indian Colony of Nevada; and Yomba Shoshone Tribe of the Yomba Reservation, Nevada.\\n\\n        This notice has been sent to officials of the Battle Mountain Band of the Te-Moak Tribe of Western Shoshone Indians of Nevada; Big Pine Band of Owens Valley Paiute Shoshone Indians of the Big Pine Reservation, California; Death Valley Timbi-Sha Shoshone Band of California; Duckwater Shoshone Tribe of the Duckwater Reservation, Nevada; Elko Band of the Te-Moak Tribe of Western Shoshone Indians of Nevada; Ely Shoshone Tribe of Nevada; Fort McDermitt Paiute and Shoshone Tribes of the Fort McDermitt Indian Reservation, Nevada and Oregon; Northwestern Band of Shoshoni Nation of Utah (Washakie); Paiute-Shoshone Indians of the Bishop Community of the Bishop Colony, California; Paiute-Shoshone Indians of the Lone Pine Community of the Lone Pine Reservation, California; Paiute-Shoshone Tribe of the Fallon Reservation and Colony, Nevada; Shoshone Tribe of the Wind River Reservation, Wyoming; Shoshone-Bannock Tribes of the Fort Hall Reservation of Idaho; Shoshone-Paiute Tribes of the Duck Valley Reservation, Nevada; South Fork Band of the Te-Moak Tribe of Western Shoshone Indians of Nevada; Wells Indian Colony Band of the Te-Moak Tribe of Western Shoshone Indians of Nevada; Winnemucca Indian Colony of Nevada; and Yomba Shoshone Tribe of the Yomba Reservation, Nevada.  Representatives of any other Indian tribe that believes itself to be culturally affiliated with these human remains should contact Martha Graham, Director of Cultural Resources, American Museum of Natural History, Central Park West at 79th Street, New York, NY 10024-5192, telephone (212) 769-5846, before November 8, 2001.  Repatriation of the human remains to the Battle Mountain Band of the Te-Moak Tribe of Western Shoshone Indians of Nevada; Big Pine Band of Owens Valley Paiute Shoshone Indians of the Big Pine Reservation, California; Death Valley Timbi-Sha Shoshone Band of California; Duckwater Shoshone Tribe of the Duckwater Reservation, Nevada; Elko Band of the Te-Moak Tribe of Western Shoshone Indians of Nevada; Ely Shoshone Tribe of Nevada; Fort McDermitt Paiute and Shoshone Tribes of the Fort McDermitt Indian Reservation, Nevada and Oregon; Northwestern Band of Shoshoni Nation of Utah (Washakie); Paiute-Shoshone Indians of the Bishop Community of the Bishop Colony, California; Paiute-Shoshone Indians of the Lone Pine Community of the Lone Pine Reservation, California; Paiute-Shoshone Tribe of the Fallon Reservation and Colony, Nevada; Shoshone Tribe of the Wind River Reservation, Wyoming; Shoshone-Bannock Tribes of the Fort Hall Reservation of Idaho; Shoshone-Paiute Tribes of the Duck Valley Reservation, Nevada; South Fork Band of the Te-Moak Tribe of Western Shoshone Indians of Nevada; Wells Indian Colony Band of the Te-Moak Tribe of Western Shoshone Indians of Nevada; Winnemucca Indian Colony of Nevada; and Yomba Shoshone Tribe of the Yomba Reservation, Nevada may begin after that date if no additional claimants come forward.\\n        \\n          Dated: August 15, 2001.\\n          John Robbins,\\n          Assistant Director, Cultural Resources Stewardship and Partnerships.\\n        \\n      \\n      [FR Doc. 01-25149  Filed 10-5-01; 8:45 am]\\n      BILLING CODE 4310-70-S\\n    ", "agency1": "DEPARTMENT OF THE INTERIOR", "sub_agency1": "National Park Service", "dep_doc": "Null", "subject": "Notice of Inventory Completion for Native American Human Remains and Associated Funerary Objects in the Possession of the American Museum of Natural History, New York, NY", "agency2": "National Park Service, Interior.", "action": "Notice.", "summary": "Null", "dates": "Null", "addresses": "Null", "signature_dated": "Dated: August 15, 2001.", "signature_name": "John Robbins,", "signature_title": "Assistant Director, Cultural Resources Stewardship and Partnerships.", "fr_doc": "[FR Doc. 01-25149  Filed 10-5-01; 8:45 am]", "billing_code": "BILLING CODE 4310-70-S", "supp_info": "Null", "consultation": "Null", "h_d_r": "Null", "h_d_ci": "Null", "determinations": "Null", "a_r_d": "Null"}