{"index": "I_201", "messy_full": "\\n      \\n        DEPARTMENT OF THE INTERIOR\\n        National Park Service\\n        [NPS-WASO-NAGPRA-NPS0026440; PPWOCRADN0-PCU00RP14.R50000]\\n        Notice of Inventory Completion: Fowler Museum at the University of California Los Angeles, Los Angeles, CA; Correction\\n        \\n          AGENCY:\\n          National Park Service, Interior.\\n        \\n        \\n          ACTION:\\n          Notice; correction.\\n        \\n        \\n          SUMMARY:\\n\\n          The Fowler Museum at the University of California Los Angeles (UCLA) has corrected an inventory of human remains and associated funerary objects, published in a Notice of Inventory Completion in the Federal Register on January 27, 2016. This notice corrects the minimum number of individuals. Lineal descendants or representatives of any Indian Tribe or Native Hawaiian organization not identified in this notice that wish to request transfer of control of these human remains should submit a written request to the Fowler Museum at UCLA. If no additional requestors come forward, transfer of control of the human remains to the lineal descendants, Indian Tribes, or Native Hawaiian organizations stated in this notice may proceed.\\n        \\n        \\n          DATES:\\n          Lineal descendants or representatives of any Indian Tribe or Native Hawaiian organization not identified in this notice that wish to request transfer of control of these human remains should submit a written request with information in support of the request to the Fowler Museum at UCLA at the address in this notice by November 19, 2018.\\n        \\n        \\n          ADDRESSES:\\n\\n          Wendy G. Teeter, Ph.D., Fowler Museum at UCLA, Box 951549, Los Angeles, CA 90095-1549, telephone (310) 825-1864, email wteeter@arts.ucla.edu.\\n        \\n      \\n      \\n        SUPPLEMENTARY INFORMATION:\\n        Notice is here given in accordance with the Native American Graves Protection and Repatriation Act (NAGPRA), 25 U.S.C. 3003, of the correction of an inventory of human remains under the control of the Fowler Museum at UCLA, Los Angeles, CA. The human remains were removed from Los Angeles County, CA.\\n\\n        This notice is published as part of the National Park Service\\'s administrative responsibilities under NAGPRA, 25 U.S.C. 3003(d)(3). The determinations in this notice are the sole responsibility of the museum, institution, or Federal agency that has control of the Native American human remains. The National Park Service is not responsible for the determinations in this notice.\\n\\n        This notice corrects the minimum number of individuals published in a Notice of Inventory Completion in the Federal Register (81 FR 4659-4662, January 27, 2016). A re-inventory discovered more human remains than was previously recorded. Transfer of control of the items in this correction notice has not occurred.\\n        Correction\\n        In the Federal Register (81 FR 4660, January 27, 2016), column 1, paragraph 1, sentence 1 is corrected by substituting the following sentence:\\n        \\n        \\n          In 1981 and 1984, human remains representing, at minimum, four individuals were removed from Playa del Rey Site #2 (CA-LAN-61), also known as the Loyola Marymount Site, in Los Angeles County, CA.\\n        \\n        \\n        In the Federal Register (81 FR 4660, January 27, 2016), column 1, paragraph 1, sentence 2 is corrected by substituting the following sentence:\\n        \\n        \\n          The site was surface collected by Vincent Lambert and excavated by the Archeological Associates of Sun City. \\n        \\n        \\n        In the Federal Register (81 FR 4660, January 27, 2016), column 1, paragraph 1, sentence 6 is corrected by substituting the following sentence:\\n        \\n        \\n          One adult individual represented by burned cranial and limb fragment, two juvenile individuals of unknown sex are represented by a single tooth each, and one infant individual represented by a molar were identified. \\n        \\n        \\n        In the Federal Register (81 FR 4660, January 27, 2016), column 1, paragraph 2, sentence 1 is corrected by substituting the following sentence:\\n        \\n        \\n          In 1981 and 1986, human remains representing, at minimum, 13 individuals were removed from Playa del Rey Site #4 (CA-LAN-63), also known as The Del Rey Site, in Los Angeles County, CA.\\n        \\n        \\n        In the Federal Register (81 FR 4660, January 27, 2016), column 1, paragraph 2, sentence 2 is corrected by substituting the following sentence:\\n        \\n        \\n          The site was surface collected by Vincent Lambert and excavated by the Archeological Associates of Sun City.\\n        \\n        \\n        In the Federal Register (81 FR 4660, January 27, 2016), column 1, paragraph 2, sentence 6 is corrected by substituting the following sentence:\\n        \\n        \\n          Fragmentary human remains represent two adults (some burned), one juvenile, and ten individuals that could not be identified to age or sex. \\n        \\n        \\n        In the Federal Register (81 FR 4661, January 27, 2016), column 3, paragraph 1, sentence 1 is corrected by substituting the following sentence:\\n        \\n        \\n          \\xe2\\x80\\xa2 Pursuant to 25 U.S.C. 3001(9), the human remains described in this notice represent the physical remains of 58 individuals of Native American ancestry based on metric and non-metric analysis.\\n        \\n        \\n        Additional Requestors and Disposition\\n\\n        Lineal descendants or representatives of any Indian Tribe or Native Hawaiian organization not identified in this notice that wish to request transfer of control of these human remains should submit a written request with information in support of the request to Wendy G. Teeter, Ph.D., Fowler Museum at UCLA, Box 951549, Los Angeles, CA 90095-1549, telephone (310) 825-1864, email wteeter@arts.ucla.edu, by November 19, 2018. After that date, if no additional requestors have come forward, transfer of control of the human remains and associated funerary objects to the San Manuel Band of Mission Indians, California (previously listed as the San Manual Band of Serrano Mission Indians of the San Manual Reservation) may proceed.\\n        The Fowler Museum is responsible for notifying the San Manuel Band of Mission Indians, California (previously listed as the San Manual Band of Serrano Mission Indians of the San Manual Reservation) that this notice has been published.\\n        \\n          Dated: September 6, 2018.\\n          Melanie O\\'Brien,\\n          Manager, National NAGPRA Program. \\n        \\n      \\n      [FR Doc. 2018-22791 Filed 10-18-18; 8:45 am]\\n      BILLING CODE 4312-52-P\\n    ", "agency1": "DEPARTMENT OF THE INTERIOR", "sub_agency1": "National Park Service", "dep_doc": "[NPS-WASO-NAGPRA-NPS0026440; PPWOCRADN0-PCU00RP14.R50000]", "subject": "Notice of Inventory Completion: Fowler Museum at the University of California Los Angeles, Los Angeles, CA; Correction", "agency2": "National Park Service, Interior.", "action": "Notice; correction.", "summary": "The Fowler Museum at the University of California Los Angeles (UCLA) has corrected an inventory of human remains and associated funerary objects, published in a Notice of Inventory Completion in the Federal Register on January 27, 2016. This notice corrects the minimum number of individuals. Lineal descendants or representatives of any Indian Tribe or Native Hawaiian organization not identified in this notice that wish to request transfer of control of these human remains should submit a written request to the Fowler Museum at UCLA. If no additional requestors come forward, transfer of control of the human remains to the lineal descendants, Indian Tribes, or Native Hawaiian organizations stated in this notice may proceed.", "dates": "Lineal descendants or representatives of any Indian Tribe or Native Hawaiian organization not identified in this notice that wish to request transfer of control of these human remains should submit a written request with information in support of the request to the Fowler Museum at UCLA at the address in this notice by November 19, 2018.", "addresses": "Wendy G. Teeter, Ph.D., Fowler Museum at UCLA, Box 951549, Los Angeles, CA 90095-1549, telephone (310) 825-1864, email wteeter@arts.ucla.edu.", "signature_dated": "Dated: September 6, 2018.", "signature_name": "Melanie O\\'Brien,", "signature_title": "Manager, National NAGPRA Program. ", "fr_doc": "[FR Doc. 2018-22791 Filed 10-18-18; 8:45 am]", "billing_code": "BILLING CODE 4312-52-P", "supp_info": "SUPPLEMENTARY INFORMATION: \n Notice is here given in accordance with the Native American Graves Protection and Repatriation Act (NAGPRA), 25 U.S.C. 3003, of the correction of an inventory of human remains under the control of the Fowler Museum at UCLA, Los Angeles, CA. The human remains were removed from Los Angeles County, CA. \n This notice is published as part of the National Park Service\\'s administrative responsibilities under NAGPRA, 25 U.S.C. 3003(d)(3). The determinations in this notice are the sole responsibility of the museum, institution, or Federal agency that has control of the Native American human remains. The National Park Service is not responsible for the determinations in this notice. \n This notice corrects the minimum number of individuals published in a Notice of Inventory Completion in the Federal Register (81 FR 4659-4662, January 27, 2016). A re-inventory discovered more human remains than was previously recorded. Transfer of control of the items in this correction notice has not occurred. \n Correction \n In the Federal Register (81 FR 4660, January 27, 2016), column 1, paragraph 1, sentence 1 is corrected by substituting the following sentence: \n In the Federal Register (81 FR 4660, January 27, 2016), column 1, paragraph 1, sentence 2 is corrected by substituting the following sentence: \n In the Federal Register (81 FR 4660, January 27, 2016), column 1, paragraph 1, sentence 6 is corrected by substituting the following sentence: \n In the Federal Register (81 FR 4660, January 27, 2016), column 1, paragraph 2, sentence 1 is corrected by substituting the following sentence: \n In the Federal Register (81 FR 4660, January 27, 2016), column 1, paragraph 2, sentence 2 is corrected by substituting the following sentence: \n In the Federal Register (81 FR 4660, January 27, 2016), column 1, paragraph 2, sentence 6 is corrected by substituting the following sentence: \n In the Federal Register (81 FR 4661, January 27, 2016), column 3, paragraph 1, sentence 1 is corrected by substituting the following sentence: \n Additional Requestors and Disposition \n Lineal descendants or representatives of any Indian Tribe or Native Hawaiian organization not identified in this notice that wish to request transfer of control of these human remains should submit a written request with information in support of the request to Wendy G. Teeter, Ph.D., Fowler Museum at UCLA, Box 951549, Los Angeles, CA 90095-1549, telephone (310) 825-1864, email wteeter@arts.ucla.edu, by November 19, 2018. After that date, if no additional requestors have come forward, transfer of control of the human remains and associated funerary objects to the San Manuel Band of Mission Indians, California (previously listed as the San Manual Band of Serrano Mission Indians of the San Manual Reservation) may proceed. \n The Fowler Museum is responsible for notifying the San Manuel Band of Mission Indians, California (previously listed as the San Manual Band of Serrano Mission Indians of the San Manual Reservation) that this notice has been published. \n ", "consultation": "Null", "h_d_r": "Null", "h_d_ci": "Null", "determinations": "Null", "a_r_d": "Lineal descendants or representatives of any Indian Tribe or Native Hawaiian organization not identified in this notice that wish to request transfer of control of these human remains should submit a written request with information in support of the request to Wendy G. Teeter, Ph.D., Fowler Museum at UCLA, Box 951549, Los Angeles, CA 90095-1549, telephone (310) 825-1864, email wteeter@arts.ucla.edu, by November 19, 2018. After that date, if no additional requestors have come forward, transfer of control of the human remains and associated funerary objects to the San Manuel Band of Mission Indians, California (previously listed as the San Manual Band of Serrano Mission Indians of the San Manual Reservation) may proceed. \n The Fowler Museum is responsible for notifying the San Manuel Band of Mission Indians, California (previously listed as the San Manual Band of Serrano Mission Indians of the San Manual Reservation) that this notice has been published. \n "}