{"index": "I_2020", "messy_full": "\\n      \\n        DEPARTMENT OF THE INTERIOR \\n        National Park Service \\n        Correction\\xe2\\x80\\x94Notice of Inventory Completion for Native American Human Remains and Associated Funerary Objects in the Possession of the Putnam Museum of History and Natural Science, Davenport, IA \\n        \\n          AGENCY:\\n          National Park Service, Interior. \\n        \\n        \\n          ACTION:\\n          Correction. \\n        \\n        Notice is hereby given in accordance with provisions of the Native American Graves Protection and Repatriation Act (NAGPRA), 43 CFR 10.9, of the completion of an inventory of human remains and associated funerary objects in the possession of the Putnam Museum of History and Natural Science, Davenport, IA. \\n        This notice is published as part of the National Park Service\\'s administrative responsibilities under NAGPRA, 43 CFR 10.2 (c). The determinations within this notice are the sole responsibility of the museum, institution, or Federal agency that has control of these Native American human remains and associated funerary objects. The National Park Service is not responsible for the determinations within this notice. \\n        This notice corrects the list of tribes to which the human remains and associated funerary objects may be repatriated in the Notice of Inventory Completion published March 26, 1997 (Federal Register Document 97-7602, pages 14441-14442). \\n\\n        In the sixth paragraph, the final sentence which reads \\xe2\\x80\\x9cRepatriation of the human remains and associated funerary objects to the Iowa Tribe of Oklahoma may begin after that date if no additional claimants come forward,\\xe2\\x80\\x9d is corrected to read \\xe2\\x80\\x9cRepatriation of the human remains and associated funerary objects to the Iowa Tribe of Oklahoma; the Sac and Fox Tribe of the Mississippi in Iowa; the Sac and Fox Nation of Missouri in Kansas and Nebraska; and the Sac and Fox Nation, Oklahoma may begin after that date if no additional claimants come forward.\\xe2\\x80\\x9d \\n        \\n          Dated: April 20, 2001. \\n          John Robbins, \\n          Assistant Director, Cultural Resources Stewardship and Partnerships. \\n        \\n      \\n      [FR Doc. 01-15303 Filed 6-15-01; 8:45 am] \\n      BILLING CODE 4310-70-F\\n    ", "agency1": "DEPARTMENT OF THE INTERIOR ", "sub_agency1": "National Park Service ", "dep_doc": "Null", "subject": "Correction\\xe2\\x80\\x94Notice of Inventory Completion for Native American Human Remains and Associated Funerary Objects in the Possession of the Putnam Museum of History and Natural Science, Davenport, IA ", "agency2": "National Park Service, Interior. ", "action": "Correction. ", "summary": "Null", "dates": "Null", "addresses": "Null", "signature_dated": "Dated: April 20, 2001. ", "signature_name": "John Robbins, ", "signature_title": "Assistant Director, Cultural Resources Stewardship and Partnerships. ", "fr_doc": "[FR Doc. 01-15303 Filed 6-15-01; 8:45 am] ", "billing_code": "BILLING CODE 4310-70-F", "supp_info": "Null", "consultation": "Null", "h_d_r": "Null", "h_d_ci": "Null", "determinations": "Null", "a_r_d": "Null"}