{"index": "I_2113", "messy_full": "\\n      \\n        DEPARTMENT OF THE INTERIOR \\n        National Park Service \\n        CORRECTION-CORRECTION-Notice of Inventory Completion for Native American Human Remains and Associated Funerary Objects in the Possession of the Anthropological Studies Center, Archaeological Collections Facility, Sonoma State University, Rohnert Park, CA; and in the Control of the California Department of Transportation, Sacramento, CA \\n        \\n          AGENCY:\\n          National Park Service.\\n        \\n        \\n          ACTION:\\n          Notice.\\n        \\n\\n        Notice is hereby given in accordance with provisions of the Native American Graves Protection and Repatriation Act (NAGPRA), 43 CFR 10.9, of the completion of an inventory of human remains and associated funerary objects in the possession of the Anthropological Studies Center (ASC), Archaeological Collections Facility, Sonoma State University, Rohnert Park, CA; and in the control of the California Department of Transportation (CALTRANS), Sacramento, CA. This notice corrects the contact address of the Correction to the Notice of Inventory Completion published December 5, 2000. The correction paragraph of the December 5, 2000 notice is corrected as follows: This notice has been sent to the officials of the Santa Rosa Indian Community of the Santa Rosa Rancheria, California. Representatives of any other Indian tribe that believes itself to be culturally affiliated with these human remains should contact Tina Biorn, Environmental Program, Department of Transportation, P. O. Box 942874 (M.S. 27), Sacramento, CA 94274-0001, telephone (916) 653-0013, before August 16, 2000. Repatriation of the human remains to the Santa Rosa Indian Community of the Santa Rosa Rancheria, California may begin after that date if no additional claimants come forward. \\n        \\n          Dated: January 19, 2001. \\n          John Robbins, \\n          Assistant Director, Cultural Resources Stewardship and Partnerships. \\n        \\n      \\n      [FR Doc. 01-4009 Filed 2-15-01; 8:45 am] \\n      BILLING CODE 4310-70-F\\n    ", "agency1": "DEPARTMENT OF THE INTERIOR ", "sub_agency1": "National Park Service ", "dep_doc": "Null", "subject": "CORRECTION-CORRECTION-Notice of Inventory Completion for Native American Human Remains and Associated Funerary Objects in the Possession of the Anthropological Studies Center, Archaeological Collections Facility, Sonoma State University, Rohnert Park, CA; and in the Control of the California Department of Transportation, Sacramento, CA ", "agency2": "National Park Service.", "action": "Notice.", "summary": "Null", "dates": "Null", "addresses": "Null", "signature_dated": "Dated: January 19, 2001. ", "signature_name": "John Robbins, ", "signature_title": "Assistant Director, Cultural Resources Stewardship and Partnerships. ", "fr_doc": "[FR Doc. 01-4009 Filed 2-15-01; 8:45 am] ", "billing_code": "BILLING CODE 4310-70-F", "supp_info": "Null", "consultation": "Null", "h_d_r": "Null", "h_d_ci": "Null", "determinations": "Null", "a_r_d": "Null"}