{"index": "I_2129", "messy_full": "\\n      \\n        DEPARTMENT OF THE INTERIOR \\n        National Park Service \\n        Notice of Inventory Completion for Native American Human Remains and Associated Funerary Objects in the Possession of the National Museum of Health and Medicine, Armed Forces Institute of Pathology, Washington, DC \\n        \\n          AGENCY:\\n          National Park Service \\n        \\n        \\n          ACTION:\\n          Notice \\n        \\n        Notice is hereby given in accordance with provisions of the Native American Graves Protection and Repatriation Act (NAGPRA), 43 CFR 10.9, of the completion of an inventory of human remains and associated funerary objects in the possession of the National Museum of Health and Medicine, Armed Forces Institute of Pathology, Washington, DC. \\n        This notice is published as part of the National Park Service\\'s administrative responsibilities under NAGPRA, 43 CFR 10.2 (c). The determinations within this notice are the sole responsibility of the museum, institution, or Federal agency that has control of these Native American human remains and associated funerary objects. The National Park Service is not responsible for the determinations within this notice. \\n        A detailed assessment of the human remains was made by the National Museum of Health and Medicine, Armed Forces Institute of Pathology professional staff in consultation with representatives of the Klamath Indian Tribe of Oregon and the Modoc Tribe of Oklahoma. \\n        In 1873, human remains representing one individual were collected from an unknown area in Oregon or California referred to as \\xe2\\x80\\x9cthe lava beds,\\xe2\\x80\\x9d by J. D. Skinner. Accession records identify this individual is as brother of Sconchin, a former chief of the Modoc. No associated funerary objects are present. \\n\\n        Based on accession records from the National Museum of Health and Medicine, this individual has been identified as Native American. The Klamath Indian Tribe of Oregon and the Modoc Tribe of Oklahoma have a shared ancestry. Following the conclusion of the Modoc wars, the Modoc people were relocated to Oklahoma. In 1888, the Modoc reservation was established. In 1909, permission was granted to the Modoc to return to Oregon. Those who returned became part of the Klamath Indian Tribe of Oregon. To date, consultation with the Klamath Indian Tribe of Oregon and the Modoc Tribe of Oklahoma has not identified a lineal descendent. \\n        In 1874, human remains representing four individuals were collected by an unknown individual from an unknown area. The circumstances surrounding the recovery of the remains are unknown. In 1874, the remains were donated to the National Museum of Health and Medicine (formerly the Army Medical Museum) by E. T. Parker. The museum is in possession of only two individuals. No known individuals were identified. No associated funerary objects are present. \\n        Accession records from the National Museum of Health and Medicine indicate that the remains are from Modoc Indians who were hung. The Klamath Indian Tribe of Oregon and the Modoc Tribe of Oklahoma have a shared ancestry. Following the conclusion of the Modoc wars, the Modoc people were relocated to Oklahoma. In 1888, the Modoc reservation was established. In 1909, permission was granted to the Modoc to return to Oregon. Those who returned became part of the Klamath Indian Tribe of Oregon. \\n        Based on the above-mentioned information, officials of the National Museum of Health and Medicine of the Armed Forces Institute of Pathology have determined that, pursuant to 43 CFR 10.2 (d)(1), the human remains listed above represent the physical remains of three individuals of Native American ancestry. Officials of the National Museum of Health and Medicine of the Armed Forces Institute of Pathology have determined that, pursuant to 43 CFR 10.2 (e), there is a relationship of shared group identity that can be reasonably traced between these Native American human remains and the Klamath Indian Tribe of Oregon and the Modoc Tribe of Oklahoma. \\n        This notice has been sent to officials of the Klamath Indian Tribe of Oregon and the Modoc Tribe of Oklahoma. Representatives of any other Indian tribe that believes itself to be culturally affiliated with these human remains should contact Lenore Barbian, Assistant Curator, National Museum of Health and Medicine, Armed Forces Institute of Pathology, Walter Reed Army Medical Center, Building 54, Washington, DC 20306, telephone (202) 782-2203, before January 29, 2001. Repatriation of the human remains and associated funerary objects to the Klamath Indian Tribe of Oregon may begin after that date if no additional claimants come forward. \\n        \\n          Dated: December 21, 2000 \\n          John Robbins, \\n          Assistant Director, Cultural Resources Stewardship and Partnerships \\n        \\n      \\n      [FR Doc. 00-33274 Filed 12-28-00; 8:45 am] \\n      BILLING CODE 4310-70-F\\n    ", "agency1": "DEPARTMENT OF THE INTERIOR ", "sub_agency1": "National Park Service ", "dep_doc": "Null", "subject": "Notice of Inventory Completion for Native American Human Remains and Associated Funerary Objects in the Possession of the National Museum of Health and Medicine, Armed Forces Institute of Pathology, Washington, DC ", "agency2": "National Park Service ", "action": "Notice ", "summary": "Null", "dates": "Null", "addresses": "Null", "signature_dated": "Dated: December 21, 2000 ", "signature_name": "John Robbins, ", "signature_title": "Assistant Director, Cultural Resources Stewardship and Partnerships ", "fr_doc": "[FR Doc. 00-33274 Filed 12-28-00; 8:45 am] ", "billing_code": "BILLING CODE 4310-70-F", "supp_info": "Null", "consultation": "Null", "h_d_r": "Null", "h_d_ci": "Null", "determinations": "Null", "a_r_d": "Null"}