{"index": "I_214", "messy_full": "\\n      \\n        DEPARTMENT OF THE INTERIOR\\n        National Park Service\\n        [NPS-WASO-NAGPRA-NPS0026436; PPWOCRADN0-PCU00RP14.R50000]\\n        Notice of Inventory Completion: Sternberg Museum of Natural History, Hays, KS\\n        \\n          AGENCY:\\n          National Park Service, Interior.\\n        \\n        \\n          ACTION:\\n          Notice.\\n        \\n        \\n          SUMMARY:\\n          The Sternberg Museum of Natural History has completed an inventory of human remains and associated funerary objects, in consultation with the appropriate Indian Tribes or Native Hawaiian organizations, and has determined that there is a cultural affiliation between the human remains and associated funerary objects and present-day Indian Tribes or Native Hawaiian organizations. Lineal descendants or representatives of any Indian Tribe or Native Hawaiian organization not identified in this notice that wish to request transfer of control of these human remains and associated funerary objects should submit a written request to the Sternberg Museum of Natural History. If no additional requestors come forward, transfer of control of the human remains and associated funerary objects to the lineal descendants, Indian Tribes, or Native Hawaiian organizations stated in this notice may proceed.\\n        \\n        \\n          DATES:\\n          Lineal descendants or representatives of any Indian Tribe or Native Hawaiian organization not identified in this notice that wish to request transfer of control of these human remains and associated funerary objects should submit a written request with information in support of the request to the Sternberg Museum of Natural History at the address in this notice by November 16, 2018.\\n        \\n        \\n          ADDRESSES:\\n\\n          Dr. Laura E. Wilson, Sternberg Museum of Natural History, 3000 Sternberg Drive, Hays, KS 67601, telephone (785) 639-6192, email lewilson6@fhsu.edu.\\n          \\n        \\n      \\n      \\n        SUPPLEMENTARY INFORMATION:\\n        Notice is here given in accordance with the Native American Graves Protection and Repatriation Act (NAGPRA), 25 U.S.C. 3003, of the completion of an inventory of human remains and associated funerary objects under the control of the Sternberg Museum of Natural History, Hays, KS. The human remains and associated funerary objects were removed from Nogales, Santa Cruz County, AZ.\\n        This notice is published as part of the National Park Service\\'s administrative responsibilities under NAGPRA, 25 U.S.C. 3003(d)(3). The determinations in this notice are the sole responsibility of the museum, institution, or Federal agency that has control of the Native American human remains and associated funerary objects. The National Park Service is not responsible for the determinations in this notice.\\n        Consultation\\n        A detailed assessment of the human remains was made by the Sternberg Museum of Natural History professional staff in consultation with representatives of Tohono O\\'odham Nation of Arizona.\\n        History and Description of the Remains\\n        In 1928, human remains representing, at minimum, two individuals were removed from Nogales, in Santa Cruz County, AZ. Two ollas, each of which contained the cremated remains of one individual, were uncovered during an operation to lower and pave a street. The two ollas were donated by Mr. James W. Haddock of Nogales High School in 1929. No known individuals were identified.\\n        According to a letter from Mr. Haddock, Dr. Dean Cummings of the University of Arizona supervised the excavation of the ollas. Dr. Cummings identified the ollas as belonging to the \\xe2\\x80\\x9cPithouse Indians and about 2000 years old.\\xe2\\x80\\x9d Mr. Peter Steere, Tribal Historic Preservation Officer for the Tohono O\\'odham Nation Cultural Center & Museum, identified the ollas as Hohokam plain ware vessels that date to A.D. 1000-1400. The Hohokam are regarded as the ancestors of the Tohono O\\'odham, and the Nogales area of Southern Arizona is within the geographic area covered by the Tohono O\\'odham Nation under NAGPRA repatriation.\\n        Determinations Made by the Sternberg Museum of Natural History\\n        Officials of the Sternberg Museum of Natural History have determined that:\\n        \\xe2\\x80\\xa2 Pursuant to 25 U.S.C. 3001(9), the human remains described in this notice represent the physical remains of two individuals of Native American ancestry.\\n        \\xe2\\x80\\xa2 Pursuant to 25 U.S.C. 3001(3)(A), the two objects described in this notice are reasonably believed to have been placed with or near individual human remains at the time of death or later as part of the death rite or ceremony.\\n\\n        \\xe2\\x80\\xa2 Pursuant to 25 U.S.C. 3001(2), there is a relationship of shared group identity that can be reasonably traced between the Native American human remains and associated funerary objects and the Tohono O\\'odham Nation of Arizona.\\n        Additional Requestors and Disposition\\n\\n        Lineal descendants or representatives of any Indian Tribe or Native Hawaiian organization not identified in this notice that wish to request transfer of control of these human remains and associated funerary objects should submit a written request with information in support of the request to Dr. Laura E. Wilson, Sternberg Museum of Natural History, 3000 Sternberg Drive, Hays, KS 67601, telephone (785) 639-6192, email lewilson6@fhsu.edu, by November 16, 2018. After that date, if no additional requestors have come forward, transfer of control of the human remains and associated funerary objects to the Tohono O\\'odham Nation of Arizona may proceed.\\n        The Sternberg Museum of Natural History is responsible for notifying the Tohono O\\'odham Nation of Arizona that this notice has been published.\\n        \\n          Dated: September 6, 2018.\\n          Melanie O\\'Brien,\\n          Manager, National NAGPRA Program. \\n        \\n      \\n      [FR Doc. 2018-22587 Filed 10-16-18; 8:45 am]\\n       BILLING CODE 4312-52-P\\n    ", "agency1": "DEPARTMENT OF THE INTERIOR", "sub_agency1": "National Park Service", "dep_doc": "[NPS-WASO-NAGPRA-NPS0026436; PPWOCRADN0-PCU00RP14.R50000]", "subject": "Notice of Inventory Completion: Sternberg Museum of Natural History, Hays, KS", "agency2": "National Park Service, Interior.", "action": "Notice.", "summary": "The Sternberg Museum of Natural History has completed an inventory of human remains and associated funerary objects, in consultation with the appropriate Indian Tribes or Native Hawaiian organizations, and has determined that there is a cultural affiliation between the human remains and associated funerary objects and present-day Indian Tribes or Native Hawaiian organizations. Lineal descendants or representatives of any Indian Tribe or Native Hawaiian organization not identified in this notice that wish to request transfer of control of these human remains and associated funerary objects should submit a written request to the Sternberg Museum of Natural History. If no additional requestors come forward, transfer of control of the human remains and associated funerary objects to the lineal descendants, Indian Tribes, or Native Hawaiian organizations stated in this notice may proceed.", "dates": "Lineal descendants or representatives of any Indian Tribe or Native Hawaiian organization not identified in this notice that wish to request transfer of control of these human remains and associated funerary objects should submit a written request with information in support of the request to the Sternberg Museum of Natural History at the address in this notice by November 16, 2018.", "addresses": "Dr. Laura E. Wilson, Sternberg Museum of Natural History, 3000 Sternberg Drive, Hays, KS 67601, telephone (785) 639-6192, email lewilson6@fhsu.edu.\\n          ", "signature_dated": "Dated: September 6, 2018.", "signature_name": "Melanie O\\'Brien,", "signature_title": "Manager, National NAGPRA Program. ", "fr_doc": "[FR Doc. 2018-22587 Filed 10-16-18; 8:45 am]", "billing_code": " BILLING CODE 4312-52-P", "supp_info": "SUPPLEMENTARY INFORMATION: \n Notice is here given in accordance with the Native American Graves Protection and Repatriation Act (NAGPRA), 25 U.S.C. 3003, of the completion of an inventory of human remains and associated funerary objects under the control of the Sternberg Museum of Natural History, Hays, KS. The human remains and associated funerary objects were removed from Nogales, Santa Cruz County, AZ. \n This notice is published as part of the National Park Service\\'s administrative responsibilities under NAGPRA, 25 U.S.C. 3003(d)(3). The determinations in this notice are the sole responsibility of the museum, institution, or Federal agency that has control of the Native American human remains and associated funerary objects. The National Park Service is not responsible for the determinations in this notice. \n Consultation \n A detailed assessment of the human remains was made by the Sternberg Museum of Natural History professional staff in consultation with representatives of Tohono O\\'odham Nation of Arizona. \n History and Description of the Remains \n In 1928, human remains representing, at minimum, two individuals were removed from Nogales, in Santa Cruz County, AZ. Two ollas, each of which contained the cremated remains of one individual, were uncovered during an operation to lower and pave a street. The two ollas were donated by Mr. James W. Haddock of Nogales High School in 1929. No known individuals were identified. \n According to a letter from Mr. Haddock, Dr. Dean Cummings of the University of Arizona supervised the excavation of the ollas. Dr. Cummings identified the ollas as belonging to the \\xe2\\x80\\x9cPithouse Indians and about 2000 years old.\\xe2\\x80\\x9d Mr. Peter Steere, Tribal Historic Preservation Officer for the Tohono O\\'odham Nation Cultural Center & Museum, identified the ollas as Hohokam plain ware vessels that date to A.D. 1000-1400. The Hohokam are regarded as the ancestors of the Tohono O\\'odham, and the Nogales area of Southern Arizona is within the geographic area covered by the Tohono O\\'odham Nation under NAGPRA repatriation. \n Determinations Made by the Sternberg Museum of Natural History \n Officials of the Sternberg Museum of Natural History have determined that: \n \\xe2\\x80\\xa2 Pursuant to 25 U.S.C. 3001(9), the human remains described in this notice represent the physical remains of two individuals of Native American ancestry. \n \\xe2\\x80\\xa2 Pursuant to 25 U.S.C. 3001(3)(A), the two objects described in this notice are reasonably believed to have been placed with or near individual human remains at the time of death or later as part of the death rite or ceremony. \n \\xe2\\x80\\xa2 Pursuant to 25 U.S.C. 3001(2), there is a relationship of shared group identity that can be reasonably traced between the Native American human remains and associated funerary objects and the Tohono O\\'odham Nation of Arizona. \n Additional Requestors and Disposition \n Lineal descendants or representatives of any Indian Tribe or Native Hawaiian organization not identified in this notice that wish to request transfer of control of these human remains and associated funerary objects should submit a written request with information in support of the request to Dr. Laura E. Wilson, Sternberg Museum of Natural History, 3000 Sternberg Drive, Hays, KS 67601, telephone (785) 639-6192, email lewilson6@fhsu.edu, by November 16, 2018. After that date, if no additional requestors have come forward, transfer of control of the human remains and associated funerary objects to the Tohono O\\'odham Nation of Arizona may proceed. \n The Sternberg Museum of Natural History is responsible for notifying the Tohono O\\'odham Nation of Arizona that this notice has been published. \n ", "consultation": "A detailed assessment of the human remains was made by the Sternberg Museum of Natural History professional staff in consultation with representatives of Tohono O\\'odham Nation of Arizona. \n ", "h_d_r": "In 1928, human remains representing, at minimum, two individuals were removed from Nogales, in Santa Cruz County, AZ. Two ollas, each of which contained the cremated remains of one individual, were uncovered during an operation to lower and pave a street. The two ollas were donated by Mr. James W. Haddock of Nogales High School in 1929. No known individuals were identified. \n According to a letter from Mr. Haddock, Dr. Dean Cummings of the University of Arizona supervised the excavation of the ollas. Dr. Cummings identified the ollas as belonging to the \\xe2\\x80\\x9cPithouse Indians and about 2000 years old.\\xe2\\x80\\x9d Mr. Peter Steere, Tribal Historic Preservation Officer for the Tohono O\\'odham Nation Cultural Center & Museum, identified the ollas as Hohokam plain ware vessels that date to A.D. 1000-1400. The Hohokam are regarded as the ancestors of the Tohono O\\'odham, and the Nogales area of Southern Arizona is within the geographic area covered by the Tohono O\\'odham Nation under NAGPRA repatriation. \n ", "h_d_ci": "Null", "determinations": "Determinations Made by the Sternberg Museum of Natural History \n Officials of the Sternberg Museum of Natural History have determined that: \n \\xe2\\x80\\xa2 Pursuant to 25 U.S.C. 3001(9), the human remains described in this notice represent the physical remains of two individuals of Native American ancestry. \n \\xe2\\x80\\xa2 Pursuant to 25 U.S.C. 3001(3)(A), the two objects described in this notice are reasonably believed to have been placed with or near individual human remains at the time of death or later as part of the death rite or ceremony. \n \\xe2\\x80\\xa2 Pursuant to 25 U.S.C. 3001(2), there is a relationship of shared group identity that can be reasonably traced between the Native American human remains and associated funerary objects and the Tohono O\\'odham Nation of Arizona. \n ", "a_r_d": "Lineal descendants or representatives of any Indian Tribe or Native Hawaiian organization not identified in this notice that wish to request transfer of control of these human remains and associated funerary objects should submit a written request with information in support of the request to Dr. Laura E. Wilson, Sternberg Museum of Natural History, 3000 Sternberg Drive, Hays, KS 67601, telephone (785) 639-6192, email lewilson6@fhsu.edu, by November 16, 2018. After that date, if no additional requestors have come forward, transfer of control of the human remains and associated funerary objects to the Tohono O\\'odham Nation of Arizona may proceed. \n The Sternberg Museum of Natural History is responsible for notifying the Tohono O\\'odham Nation of Arizona that this notice has been published. \n "}