{"index": "I_238", "messy_full": "\\n      \\n        DEPARTMENT OF THE INTERIOR\\n        National Park Service\\n        [NPS-WASO-NAGPRA-NPS0026234; PPWOCRADN0-PCU00RP14.R50000]\\n        Notice of Inventory Completion: State Historical Society of North Dakota, Bismarck, ND\\n        \\n          AGENCY:\\n          National Park Service, Interior.\\n        \\n        \\n          ACTION:\\n          Notice.\\n        \\n        \\n          SUMMARY:\\n          The State Historical Society of North Dakota has completed an inventory of human remains and associated funerary objects, in consultation with the appropriate Indian Tribes or Native Hawaiian organizations, and has determined that there is no cultural affiliation between the human remains and associated funerary objects and any present-day Indian Tribes or Native Hawaiian organizations. Representatives of any Indian Tribe or Native Hawaiian organization not identified in this notice that wish to request transfer of control of these human remains and associated funerary objects should submit a written request to the State Historical Society of North Dakota. If no additional requestors come forward, transfer of control of the human remains and associated funerary objects to the Indian Tribes or Native Hawaiian organizations stated in this notice may proceed.\\n        \\n        \\n          DATES:\\n          Representatives of any Indian Tribe or Native Hawaiian organization not identified in this notice that wish to request transfer of control of these human remains and associated funerary objects should submit a written request with information in support of the request to the State Historical Society of North Dakota at the address in this notice by October 10, 2018.\\n        \\n        \\n          ADDRESSES:\\n\\n          Wendi Field Murray, State Historical Society of North Dakota, 612 East Boulevard Avenue, Bismarck, ND 58505, telephone (701) 328-3506, email wmurray@nd.gov.\\n          \\n        \\n      \\n      \\n        SUPPLEMENTARY INFORMATION:\\n        Notice is here given in accordance with the Native American Graves Protection and Repatriation Act (NAGPRA), 25 U.S.C. 3003, of the completion of an inventory of human remains and associated funerary objects under the control of the State Historical Society of North Dakota, Bismarck, ND. The human remains and associated funerary objects were removed from an unknown location in western North Dakota.\\n        This notice is published as part of the National Park Service\\'s administrative responsibilities under NAGPRA, 25 U.S.C. 3003(d)(3) and 43 CFR 10.11(d). The determinations in this notice are the sole responsibility of the museum, institution, or Federal agency that has control of the Native American human remains and associated funerary objects. The National Park Service is not responsible for the determinations in this notice.\\n        Consultation\\n\\n        A detailed assessment of the human remains and associated funerary objects was made by the State Historical Society of North Dakota professional staff in consultation with representatives of the Crow Tribe of Montana; Lower Sioux Indian Community in the State of Minnesota; Northern Cheyenne Tribe of the Northern Cheyenne Indian Reservation, Montana; Sisseton-Wahpeton Oyate of the Lake Traverse Reservation, South Dakota; Spirit Lake Tribe, North Dakota; Standing Rock Sioux Tribe of North & South Dakota; Three Affiliated Tribes of the Fort Berthold Indian Reservation, North Dakota; Turtle Mountain Band of Chippewa Indians of North Dakota; and Upper Sioux Community, Minnesota. The Assiniboine and Sioux Tribes of the Fort Peck Indian Reservation, Montana was invited to consult but did not participate. Hereafter all tribes listed in this section are referred to as \\xe2\\x80\\x9cThe Consulted and Notified Tribes.\\xe2\\x80\\x9d\\n        History and Description of the Remains\\n        Sometime before 1931, human remains representing, at minimum, one individual were removed from the ground surface in an unknown location in western North Dakota. According to museum records, the human remains were collected by Dr. James Grassick of North Dakota, and were donated to the museum in October 1931. No known individuals were identified. The one associated funerary object is one metal projectile point, which was embedded in the human remains.\\n        Determinations Made by the State Historical Society of North Dakota\\n        Officials of the State Historical Society of North Dakota have determined that:\\n        \\xe2\\x80\\xa2 Pursuant to 25 U.S.C. 3001(9), the human remains described in this notice are Native American based on the donor\\'s collecting history.\\n        \\xe2\\x80\\xa2 Pursuant to 25 U.S.C. 3001(9), the human remains described in this notice represent the physical remains of one individual of Native American ancestry.\\n        \\xe2\\x80\\xa2 Pursuant to 25 U.S.C. 3001(3)(A), the one object described in this notice is reasonably believed to have been placed with or near individual human remains at the time of death or later as part of the death rite or ceremony and was embedded in the human remains either before or after the individual\\'s death.\\n        \\xe2\\x80\\xa2 Pursuant to 25 U.S.C. 3001(2), a relationship of shared group identity cannot be reasonably traced between the Native American human remains and associated funerary objects and any present-day Indian Tribe.\\n        \\xe2\\x80\\xa2 Treaties, Acts of Congress, or Executive Orders, indicate that the land from which the Native American human remains and associated funerary objects were removed is the aboriginal land of the Lower Sioux Indian Community in the State of Minnesota; Sisseton-Wahpeton Oyate of the Lake Traverse Reservation, South Dakota; Spirit Lake Tribe, North Dakota; Standing Rock Sioux Tribe of North & South Dakota; Three Affiliated Tribes of the Fort Berthold Indian Reservation, North Dakota; Turtle Mountain Band of Chippewa Indians of North Dakota; and the Upper Sioux Community, Minnesota.\\n        \\xe2\\x80\\xa2 Pursuant to 43 CFR 10.11(c)(1), the disposition of the human remains and associated funerary objects may be to of the Lower Sioux Indian Community in the State of Minnesota; Sisseton-Wahpeton Oyate of the Lake Traverse Reservation, South Dakota; Spirit Lake Tribe, North Dakota; Standing Rock Sioux Tribe of North & South Dakota; Three Affiliated Tribes of the Fort Berthold Indian Reservation, North Dakota; Turtle Mountain Band of Chippewa Indians of North Dakota; and the Upper Sioux Community, Minnesota.\\n        Additional Requestors and Disposition\\n\\n        Representatives of any Indian Tribe or Native Hawaiian organization not identified in this notice that wish to request transfer of control of these human remains and associated funerary objects should submit a written request with information in support of the request to Wendi Field Murray, State Historical Society of North Dakota, 612 East Boulevard Avenue, Bismarck, ND 58505, telephone (701) 325-3506, email wmurray@nd.gov, by October 10, 2018. After that date, if no additional requestors have come forward, transfer of control of the human remains and associated funerary objects to the Lower Sioux Indian Community in the State of Minnesota; Sisseton-Wahpeton Oyate of the Lake Traverse Reservation, South Dakota; Spirit Lake Tribe, North Dakota; Standing Rock Sioux Tribe of North & South Dakota; Three Affiliated Tribes of the Fort Berthold Indian Reservation, North Dakota; Turtle Mountain Band of Chippewa Indians of North Dakota; and the Upper Sioux Community, Minnesota may proceed.\\n        The State Historical Society of North Dakota is responsible for notifying The Consulted and Notified Tribes that this notice has been published.\\n        \\n          Dated: August 9, 2018.\\n          Melanie O\\'Brien,\\n          Manager, National NAGPRA Program. \\n        \\n      \\n      [FR Doc. 2018-19543 Filed 9-7-18; 8:45 am]\\n       BILLING CODE 4312-52-P\\n    ", "agency1": "DEPARTMENT OF THE INTERIOR", "sub_agency1": "National Park Service", "dep_doc": "[NPS-WASO-NAGPRA-NPS0026234; PPWOCRADN0-PCU00RP14.R50000]", "subject": "Notice of Inventory Completion: State Historical Society of North Dakota, Bismarck, ND", "agency2": "National Park Service, Interior.", "action": "Notice.", "summary": "The State Historical Society of North Dakota has completed an inventory of human remains and associated funerary objects, in consultation with the appropriate Indian Tribes or Native Hawaiian organizations, and has determined that there is no cultural affiliation between the human remains and associated funerary objects and any present-day Indian Tribes or Native Hawaiian organizations. Representatives of any Indian Tribe or Native Hawaiian organization not identified in this notice that wish to request transfer of control of these human remains and associated funerary objects should submit a written request to the State Historical Society of North Dakota. If no additional requestors come forward, transfer of control of the human remains and associated funerary objects to the Indian Tribes or Native Hawaiian organizations stated in this notice may proceed.", "dates": "Representatives of any Indian Tribe or Native Hawaiian organization not identified in this notice that wish to request transfer of control of these human remains and associated funerary objects should submit a written request with information in support of the request to the State Historical Society of North Dakota at the address in this notice by October 10, 2018.", "addresses": "Wendi Field Murray, State Historical Society of North Dakota, 612 East Boulevard Avenue, Bismarck, ND 58505, telephone (701) 328-3506, email wmurray@nd.gov.\\n          ", "signature_dated": "Dated: August 9, 2018.", "signature_name": "Melanie O\\'Brien,", "signature_title": "Manager, National NAGPRA Program. ", "fr_doc": "[FR Doc. 2018-19543 Filed 9-7-18; 8:45 am]", "billing_code": " BILLING CODE 4312-52-P", "supp_info": "SUPPLEMENTARY INFORMATION: \n Notice is here given in accordance with the Native American Graves Protection and Repatriation Act (NAGPRA), 25 U.S.C. 3003, of the completion of an inventory of human remains and associated funerary objects under the control of the State Historical Society of North Dakota, Bismarck, ND. The human remains and associated funerary objects were removed from an unknown location in western North Dakota. \n This notice is published as part of the National Park Service\\'s administrative responsibilities under NAGPRA, 25 U.S.C. 3003(d)(3) and 43 CFR 10.11(d). The determinations in this notice are the sole responsibility of the museum, institution, or Federal agency that has control of the Native American human remains and associated funerary objects. The National Park Service is not responsible for the determinations in this notice. \n Consultation \n A detailed assessment of the human remains and associated funerary objects was made by the State Historical Society of North Dakota professional staff in consultation with representatives of the Crow Tribe of Montana; Lower Sioux Indian Community in the State of Minnesota; Northern Cheyenne Tribe of the Northern Cheyenne Indian Reservation, Montana; Sisseton-Wahpeton Oyate of the Lake Traverse Reservation, South Dakota; Spirit Lake Tribe, North Dakota; Standing Rock Sioux Tribe of North & South Dakota; Three Affiliated Tribes of the Fort Berthold Indian Reservation, North Dakota; Turtle Mountain Band of Chippewa Indians of North Dakota; and Upper Sioux Community, Minnesota. The Assiniboine and Sioux Tribes of the Fort Peck Indian Reservation, Montana was invited to consult but did not participate. Hereafter all tribes listed in this section are referred to as \\xe2\\x80\\x9cThe Consulted and Notified Tribes.\\xe2\\x80\\x9d \n History and Description of the Remains \n Sometime before 1931, human remains representing, at minimum, one individual were removed from the ground surface in an unknown location in western North Dakota. According to museum records, the human remains were collected by Dr. James Grassick of North Dakota, and were donated to the museum in October 1931. No known individuals were identified. The one associated funerary object is one metal projectile point, which was embedded in the human remains. \n Determinations Made by the State Historical Society of North Dakota \n Officials of the State Historical Society of North Dakota have determined that: \n \\xe2\\x80\\xa2 Pursuant to 25 U.S.C. 3001(9), the human remains described in this notice are Native American based on the donor\\'s collecting history. \n \\xe2\\x80\\xa2 Pursuant to 25 U.S.C. 3001(9), the human remains described in this notice represent the physical remains of one individual of Native American ancestry. \n \\xe2\\x80\\xa2 Pursuant to 25 U.S.C. 3001(3)(A), the one object described in this notice is reasonably believed to have been placed with or near individual human remains at the time of death or later as part of the death rite or ceremony and was embedded in the human remains either before or after the individual\\'s death. \n \\xe2\\x80\\xa2 Pursuant to 25 U.S.C. 3001(2), a relationship of shared group identity cannot be reasonably traced between the Native American human remains and associated funerary objects and any present-day Indian Tribe. \n \\xe2\\x80\\xa2 Treaties, Acts of Congress, or Executive Orders, indicate that the land from which the Native American human remains and associated funerary objects were removed is the aboriginal land of the Lower Sioux Indian Community in the State of Minnesota; Sisseton-Wahpeton Oyate of the Lake Traverse Reservation, South Dakota; Spirit Lake Tribe, North Dakota; Standing Rock Sioux Tribe of North & South Dakota; Three Affiliated Tribes of the Fort Berthold Indian Reservation, North Dakota; Turtle Mountain Band of Chippewa Indians of North Dakota; and the Upper Sioux Community, Minnesota. \n \\xe2\\x80\\xa2 Pursuant to 43 CFR 10.11(c)(1), the disposition of the human remains and associated funerary objects may be to of the Lower Sioux Indian Community in the State of Minnesota; Sisseton-Wahpeton Oyate of the Lake Traverse Reservation, South Dakota; Spirit Lake Tribe, North Dakota; Standing Rock Sioux Tribe of North & South Dakota; Three Affiliated Tribes of the Fort Berthold Indian Reservation, North Dakota; Turtle Mountain Band of Chippewa Indians of North Dakota; and the Upper Sioux Community, Minnesota. \n Additional Requestors and Disposition \n Representatives of any Indian Tribe or Native Hawaiian organization not identified in this notice that wish to request transfer of control of these human remains and associated funerary objects should submit a written request with information in support of the request to Wendi Field Murray, State Historical Society of North Dakota, 612 East Boulevard Avenue, Bismarck, ND 58505, telephone (701) 325-3506, email wmurray@nd.gov, by October 10, 2018. After that date, if no additional requestors have come forward, transfer of control of the human remains and associated funerary objects to the Lower Sioux Indian Community in the State of Minnesota; Sisseton-Wahpeton Oyate of the Lake Traverse Reservation, South Dakota; Spirit Lake Tribe, North Dakota; Standing Rock Sioux Tribe of North & South Dakota; Three Affiliated Tribes of the Fort Berthold Indian Reservation, North Dakota; Turtle Mountain Band of Chippewa Indians of North Dakota; and the Upper Sioux Community, Minnesota may proceed. \n The State Historical Society of North Dakota is responsible for notifying The Consulted and Notified Tribes that this notice has been published. \n ", "consultation": "A detailed assessment of the human remains and associated funerary objects was made by the State Historical Society of North Dakota professional staff in consultation with representatives of the Crow Tribe of Montana; Lower Sioux Indian Community in the State of Minnesota; Northern Cheyenne Tribe of the Northern Cheyenne Indian Reservation, Montana; Sisseton-Wahpeton Oyate of the Lake Traverse Reservation, South Dakota; Spirit Lake Tribe, North Dakota; Standing Rock Sioux Tribe of North & South Dakota; Three Affiliated Tribes of the Fort Berthold Indian Reservation, North Dakota; Turtle Mountain Band of Chippewa Indians of North Dakota; and Upper Sioux Community, Minnesota. The Assiniboine and Sioux Tribes of the Fort Peck Indian Reservation, Montana was invited to consult but did not participate. Hereafter all tribes listed in this section are referred to as \\xe2\\x80\\x9cThe Consulted and Notified Tribes.\\xe2\\x80\\x9d \n ", "h_d_r": "Sometime before 1931, human remains representing, at minimum, one individual were removed from the ground surface in an unknown location in western North Dakota. According to museum records, the human remains were collected by Dr. James Grassick of North Dakota, and were donated to the museum in October 1931. No known individuals were identified. The one associated funerary object is one metal projectile point, which was embedded in the human remains. \n ", "h_d_ci": "Null", "determinations": "Determinations Made by the State Historical Society of North Dakota \n Officials of the State Historical Society of North Dakota have determined that: \n \\xe2\\x80\\xa2 Pursuant to 25 U.S.C. 3001(9), the human remains described in this notice are Native American based on the donor\\'s collecting history. \n \\xe2\\x80\\xa2 Pursuant to 25 U.S.C. 3001(9), the human remains described in this notice represent the physical remains of one individual of Native American ancestry. \n \\xe2\\x80\\xa2 Pursuant to 25 U.S.C. 3001(3)(A), the one object described in this notice is reasonably believed to have been placed with or near individual human remains at the time of death or later as part of the death rite or ceremony and was embedded in the human remains either before or after the individual\\'s death. \n \\xe2\\x80\\xa2 Pursuant to 25 U.S.C. 3001(2), a relationship of shared group identity cannot be reasonably traced between the Native American human remains and associated funerary objects and any present-day Indian Tribe. \n \\xe2\\x80\\xa2 Treaties, Acts of Congress, or Executive Orders, indicate that the land from which the Native American human remains and associated funerary objects were removed is the aboriginal land of the Lower Sioux Indian Community in the State of Minnesota; Sisseton-Wahpeton Oyate of the Lake Traverse Reservation, South Dakota; Spirit Lake Tribe, North Dakota; Standing Rock Sioux Tribe of North & South Dakota; Three Affiliated Tribes of the Fort Berthold Indian Reservation, North Dakota; Turtle Mountain Band of Chippewa Indians of North Dakota; and the Upper Sioux Community, Minnesota. \n \\xe2\\x80\\xa2 Pursuant to 43 CFR 10.11(c)(1), the disposition of the human remains and associated funerary objects may be to of the Lower Sioux Indian Community in the State of Minnesota; Sisseton-Wahpeton Oyate of the Lake Traverse Reservation, South Dakota; Spirit Lake Tribe, North Dakota; Standing Rock Sioux Tribe of North & South Dakota; Three Affiliated Tribes of the Fort Berthold Indian Reservation, North Dakota; Turtle Mountain Band of Chippewa Indians of North Dakota; and the Upper Sioux Community, Minnesota. \n ", "a_r_d": "Representatives of any Indian Tribe or Native Hawaiian organization not identified in this notice that wish to request transfer of control of these human remains and associated funerary objects should submit a written request with information in support of the request to Wendi Field Murray, State Historical Society of North Dakota, 612 East Boulevard Avenue, Bismarck, ND 58505, telephone (701) 325-3506, email wmurray@nd.gov, by October 10, 2018. After that date, if no additional requestors have come forward, transfer of control of the human remains and associated funerary objects to the Lower Sioux Indian Community in the State of Minnesota; Sisseton-Wahpeton Oyate of the Lake Traverse Reservation, South Dakota; Spirit Lake Tribe, North Dakota; Standing Rock Sioux Tribe of North & South Dakota; Three Affiliated Tribes of the Fort Berthold Indian Reservation, North Dakota; Turtle Mountain Band of Chippewa Indians of North Dakota; and the Upper Sioux Community, Minnesota may proceed. \n The State Historical Society of North Dakota is responsible for notifying The Consulted and Notified Tribes that this notice has been published. \n "}