{"index": "I_233", "messy_full": "\\n      \\n        DEPARTMENT OF THE INTERIOR\\n        National Park Service\\n        [NPS-WASO-NAGPRA-NPS0026099; PPWOCRADN0-PCU00RP14.R50000]\\n        Notice of Inventory Completion: Heard Museum, Phoenix, AZ\\n        \\n          AGENCY:\\n          National Park Service, Interior.\\n        \\n        \\n          ACTION:\\n          Notice.\\n        \\n        \\n          SUMMARY:\\n          The Heard Museum has completed an inventory of human remains and associated funerary objects, in consultation with the appropriate Indian Tribes or Native Hawaiian organizations, and has determined that there is a cultural affiliation between the human remains and associated funerary objects and present-day Indian Tribes or Native Hawaiian organizations. Lineal descendants or representatives of any Indian Tribe or Native Hawaiian organization not identified in this notice that wish to request transfer of control of these human remains and associated funerary objects should submit a written request to the Heard Museum. If no additional requestors come forward, transfer of control of the human remains and associated funerary objects to the lineal descendants, Indian Tribes, or Native Hawaiian organizations stated in this notice may proceed.\\n        \\n        \\n          DATES:\\n          Lineal descendants or representatives of any Indian Tribe or Native Hawaiian organization not identified in this notice that wish to request transfer of control of these human remains and associated funerary objects should submit a written request with information in support of the request to the Heard Museum at the address in this notice by October 10, 2018.\\n        \\n        \\n          ADDRESSES:\\n\\n          David Roche, Director/CEO, Heard Museum, 2301 North Central Avenue, Phoenix, AZ 85004, telephone (602) 252-8840, email director@heard.org.\\n          \\n        \\n      \\n      \\n        \\n        SUPPLEMENTARY INFORMATION:\\n        Notice is here given in accordance with the Native American Graves Protection and Repatriation Act (NAGPRA), 25 U.S.C. 3003, of the completion of an inventory of human remains and associated funerary objects under the control of the Heard Museum, Phoenix, AZ. The human remains and associated funerary objects were removed from the vicinity of Gila Bend, Maricopa County, AZ.\\n        This notice is published as part of the National Park Service\\'s administrative responsibilities under NAGPRA, 25 U.S.C. 3003(d)(3). The determinations in this notice are the sole responsibility of the museum, institution, or Federal agency that has control of the Native American human remains and associated funerary objects. The National Park Service is not responsible for the determinations in this notice.\\n        Consultation\\n        A detailed assessment of the human remains was made by the Heard Museum professional staff in consultation with representatives of Ak-Chin Indian Community (previously listed as the Ak Chin Indian Community of the Maricopa (Ak Chin) Indian Reservation, Arizona); Gila River Indian Community of the Gila River Indian Reservation, Arizona; Hopi Tribe of Arizona; Salt River Pima-Maricopa Indian Community of the Salt River Reservation, Arizona; Tohono O\\'odham Nation of Arizona; and Zuni Tribe of the Zuni Reservation, New Mexico.\\n        History and Description of the Remains\\n        Prior to 1953, human remains representing, at minimum, one individual were removed from the vicinity of Gila Bend in Maricopa County, AZ, by Russell Cross and then acquired by the Heard Museum. In 1953, the museum assigned the human remains and associated funerary objects catalog number NA-SW-HH-A4-2. The human remains belong to a middle-aged adult of unknown gender. No known individuals were identified. The two associated funerary objects are one jar and one animal bone.\\n        The jar is identified as Hohokam Sacaton Red-on-Buff with a low Gila Shoulder, and was made between approximately A.D. 900 and 1100. In 1990, the Ak-Chin Indian Community, Gila River Indian Community, Salt River Pima-Maricopa Community, and Tohono O\\'odham Nation adopted a joint policy statement stating that a cultural affiliation existed between themselves and the ancestors they described as \\xe2\\x80\\x9cHohokam.\\xe2\\x80\\x9d Subsequently, the Hopi Tribe (in 1994) and Pueblo of Zuni (in 1995) asserted their own cultural affiliation with the Hohokam.\\n        Determinations Made by the Heard Museum\\n        Officials of the Heard Museum have determined that:\\n        \\xe2\\x80\\xa2 Pursuant to 25 U.S.C. 3001(9), the human remains described in this notice represent the physical remains of one individual of Native American ancestry.\\n        \\xe2\\x80\\xa2 Pursuant to 25 U.S.C. 3001(3)(A), the two objects described in this notice are reasonably believed to have been placed with or near individual human remains at the time of death or later as part of the death rite or ceremony.\\n        \\xe2\\x80\\xa2 Pursuant to 25 U.S.C. 3001(2), there is a relationship of shared group identity that can be reasonably traced between the Native American human remains and associated funerary objects and the Ak-Chin Indian Community (previously listed as the Ak Chin Indian Community of the Maricopa (Ak Chin) Indian Reservation, Arizona); Cocopah Tribe of Arizona; Colorado River Indian Tribes of the Colorado River Indian Reservation, Arizona and California; Fort Mojave Indian Tribe of Arizona, California & Nevada; Gila River Indian Community of the Gila River Indian Reservation, Arizona; Hopi Tribe of Arizona; Quechan Tribe of the Fort Yuma Indian Reservation, California & Arizona; Salt River Pima-Maricopa Indian Community of the Salt River Reservation, Arizona; Tohono O\\'odham Nation of Arizona; and Zuni Tribe of the Zuni Reservation, New Mexico (hereafter referred to as \\xe2\\x80\\x9cThe Tribes\\xe2\\x80\\x9d).\\n        Additional Requestors and Disposition\\n\\n        Lineal descendants or representatives of any Indian Tribe or Native Hawaiian organization not identified in this notice that wish to request transfer of control of these human remains and associated funerary objects should submit a written request with information in support of the request to David Roche, Director/CEO, Heard Museum, 2301 North Central Avenue, Phoenix, AZ 85004, telephone (602) 252-8840, email director@heard.org, by October 10, 2018. After that date, if no additional requestors have come forward, transfer of control of the human remains and associated funerary objects to The Tribes may proceed.\\n        The Heard Museum is responsible for notifying The Tribes that this notice has been published.\\n        \\n          Dated: July 25, 2018.\\n          Melanie O\\'Brien,\\n          Manager, National NAGPRA Program. \\n        \\n      \\n      [FR Doc. 2018-19523 Filed 9-7-18; 8:45 am]\\n       BILLING CODE 4312-52-P\\n    ", "agency1": "DEPARTMENT OF THE INTERIOR", "sub_agency1": "National Park Service", "dep_doc": "[NPS-WASO-NAGPRA-NPS0026099; PPWOCRADN0-PCU00RP14.R50000]", "subject": "Notice of Inventory Completion: Heard Museum, Phoenix, AZ", "agency2": "National Park Service, Interior.", "action": "Notice.", "summary": "The Heard Museum has completed an inventory of human remains and associated funerary objects, in consultation with the appropriate Indian Tribes or Native Hawaiian organizations, and has determined that there is a cultural affiliation between the human remains and associated funerary objects and present-day Indian Tribes or Native Hawaiian organizations. Lineal descendants or representatives of any Indian Tribe or Native Hawaiian organization not identified in this notice that wish to request transfer of control of these human remains and associated funerary objects should submit a written request to the Heard Museum. If no additional requestors come forward, transfer of control of the human remains and associated funerary objects to the lineal descendants, Indian Tribes, or Native Hawaiian organizations stated in this notice may proceed.", "dates": "Lineal descendants or representatives of any Indian Tribe or Native Hawaiian organization not identified in this notice that wish to request transfer of control of these human remains and associated funerary objects should submit a written request with information in support of the request to the Heard Museum at the address in this notice by October 10, 2018.", "addresses": "David Roche, Director/CEO, Heard Museum, 2301 North Central Avenue, Phoenix, AZ 85004, telephone (602) 252-8840, email director@heard.org.\\n          ", "signature_dated": "Dated: July 25, 2018.", "signature_name": "Melanie O\\'Brien,", "signature_title": "Manager, National NAGPRA Program. ", "fr_doc": "[FR Doc. 2018-19523 Filed 9-7-18; 8:45 am]", "billing_code": " BILLING CODE 4312-52-P", "supp_info": "SUPPLEMENTARY INFORMATION: \n Notice is here given in accordance with the Native American Graves Protection and Repatriation Act (NAGPRA), 25 U.S.C. 3003, of the completion of an inventory of human remains and associated funerary objects under the control of the Heard Museum, Phoenix, AZ. The human remains and associated funerary objects were removed from the vicinity of Gila Bend, Maricopa County, AZ. \n This notice is published as part of the National Park Service\\'s administrative responsibilities under NAGPRA, 25 U.S.C. 3003(d)(3). The determinations in this notice are the sole responsibility of the museum, institution, or Federal agency that has control of the Native American human remains and associated funerary objects. The National Park Service is not responsible for the determinations in this notice. \n Consultation \n A detailed assessment of the human remains was made by the Heard Museum professional staff in consultation with representatives of Ak-Chin Indian Community (previously listed as the Ak Chin Indian Community of the Maricopa (Ak Chin) Indian Reservation, Arizona); Gila River Indian Community of the Gila River Indian Reservation, Arizona; Hopi Tribe of Arizona; Salt River Pima-Maricopa Indian Community of the Salt River Reservation, Arizona; Tohono O\\'odham Nation of Arizona; and Zuni Tribe of the Zuni Reservation, New Mexico. \n History and Description of the Remains \n Prior to 1953, human remains representing, at minimum, one individual were removed from the vicinity of Gila Bend in Maricopa County, AZ, by Russell Cross and then acquired by the Heard Museum. In 1953, the museum assigned the human remains and associated funerary objects catalog number NA-SW-HH-A4-2. The human remains belong to a middle-aged adult of unknown gender. No known individuals were identified. The two associated funerary objects are one jar and one animal bone. \n The jar is identified as Hohokam Sacaton Red-on-Buff with a low Gila Shoulder, and was made between approximately A.D. 900 and 1100. In 1990, the Ak-Chin Indian Community, Gila River Indian Community, Salt River Pima-Maricopa Community, and Tohono O\\'odham Nation adopted a joint policy statement stating that a cultural affiliation existed between themselves and the ancestors they described as \\xe2\\x80\\x9cHohokam.\\xe2\\x80\\x9d Subsequently, the Hopi Tribe (in 1994) and Pueblo of Zuni (in 1995) asserted their own cultural affiliation with the Hohokam. \n Determinations Made by the Heard Museum \n Officials of the Heard Museum have determined that: \n \\xe2\\x80\\xa2 Pursuant to 25 U.S.C. 3001(9), the human remains described in this notice represent the physical remains of one individual of Native American ancestry. \n \\xe2\\x80\\xa2 Pursuant to 25 U.S.C. 3001(3)(A), the two objects described in this notice are reasonably believed to have been placed with or near individual human remains at the time of death or later as part of the death rite or ceremony. \n \\xe2\\x80\\xa2 Pursuant to 25 U.S.C. 3001(2), there is a relationship of shared group identity that can be reasonably traced between the Native American human remains and associated funerary objects and the Ak-Chin Indian Community (previously listed as the Ak Chin Indian Community of the Maricopa (Ak Chin) Indian Reservation, Arizona); Cocopah Tribe of Arizona; Colorado River Indian Tribes of the Colorado River Indian Reservation, Arizona and California; Fort Mojave Indian Tribe of Arizona, California & Nevada; Gila River Indian Community of the Gila River Indian Reservation, Arizona; Hopi Tribe of Arizona; Quechan Tribe of the Fort Yuma Indian Reservation, California & Arizona; Salt River Pima-Maricopa Indian Community of the Salt River Reservation, Arizona; Tohono O\\'odham Nation of Arizona; and Zuni Tribe of the Zuni Reservation, New Mexico (hereafter referred to as \\xe2\\x80\\x9cThe Tribes\\xe2\\x80\\x9d). \n Additional Requestors and Disposition \n Lineal descendants or representatives of any Indian Tribe or Native Hawaiian organization not identified in this notice that wish to request transfer of control of these human remains and associated funerary objects should submit a written request with information in support of the request to David Roche, Director/CEO, Heard Museum, 2301 North Central Avenue, Phoenix, AZ 85004, telephone (602) 252-8840, email director@heard.org, by October 10, 2018. After that date, if no additional requestors have come forward, transfer of control of the human remains and associated funerary objects to The Tribes may proceed. \n The Heard Museum is responsible for notifying The Tribes that this notice has been published. \n ", "consultation": "A detailed assessment of the human remains was made by the Heard Museum professional staff in consultation with representatives of Ak-Chin Indian Community (previously listed as the Ak Chin Indian Community of the Maricopa (Ak Chin) Indian Reservation, Arizona); Gila River Indian Community of the Gila River Indian Reservation, Arizona; Hopi Tribe of Arizona; Salt River Pima-Maricopa Indian Community of the Salt River Reservation, Arizona; Tohono O\\'odham Nation of Arizona; and Zuni Tribe of the Zuni Reservation, New Mexico. \n ", "h_d_r": "Prior to 1953, human remains representing, at minimum, one individual were removed from the vicinity of Gila Bend in Maricopa County, AZ, by Russell Cross and then acquired by the Heard Museum. In 1953, the museum assigned the human remains and associated funerary objects catalog number NA-SW-HH-A4-2. The human remains belong to a middle-aged adult of unknown gender. No known individuals were identified. The two associated funerary objects are one jar and one animal bone. \n The jar is identified as Hohokam Sacaton Red-on-Buff with a low Gila Shoulder, and was made between approximately A.D. 900 and 1100. In 1990, the Ak-Chin Indian Community, Gila River Indian Community, Salt River Pima-Maricopa Community, and Tohono O\\'odham Nation adopted a joint policy statement stating that a cultural affiliation existed between themselves and the ancestors they described as \\xe2\\x80\\x9cHohokam.\\xe2\\x80\\x9d Subsequently, the Hopi Tribe (in 1994) and Pueblo of Zuni (in 1995) asserted their own cultural affiliation with the Hohokam. \n ", "h_d_ci": "Null", "determinations": "Determinations Made by the Heard Museum \n Officials of the Heard Museum have determined that: \n \\xe2\\x80\\xa2 Pursuant to 25 U.S.C. 3001(9), the human remains described in this notice represent the physical remains of one individual of Native American ancestry. \n \\xe2\\x80\\xa2 Pursuant to 25 U.S.C. 3001(3)(A), the two objects described in this notice are reasonably believed to have been placed with or near individual human remains at the time of death or later as part of the death rite or ceremony. \n \\xe2\\x80\\xa2 Pursuant to 25 U.S.C. 3001(2), there is a relationship of shared group identity that can be reasonably traced between the Native American human remains and associated funerary objects and the Ak-Chin Indian Community (previously listed as the Ak Chin Indian Community of the Maricopa (Ak Chin) Indian Reservation, Arizona); Cocopah Tribe of Arizona; Colorado River Indian Tribes of the Colorado River Indian Reservation, Arizona and California; Fort Mojave Indian Tribe of Arizona, California & Nevada; Gila River Indian Community of the Gila River Indian Reservation, Arizona; Hopi Tribe of Arizona; Quechan Tribe of the Fort Yuma Indian Reservation, California & Arizona; Salt River Pima-Maricopa Indian Community of the Salt River Reservation, Arizona; Tohono O\\'odham Nation of Arizona; and Zuni Tribe of the Zuni Reservation, New Mexico (hereafter referred to as \\xe2\\x80\\x9cThe Tribes\\xe2\\x80\\x9d). \n ", "a_r_d": "Lineal descendants or representatives of any Indian Tribe or Native Hawaiian organization not identified in this notice that wish to request transfer of control of these human remains and associated funerary objects should submit a written request with information in support of the request to David Roche, Director/CEO, Heard Museum, 2301 North Central Avenue, Phoenix, AZ 85004, telephone (602) 252-8840, email director@heard.org, by October 10, 2018. After that date, if no additional requestors have come forward, transfer of control of the human remains and associated funerary objects to The Tribes may proceed. \n The Heard Museum is responsible for notifying The Tribes that this notice has been published. \n "}