{"index": "I_235", "messy_full": "\\n      \\n        DEPARTMENT OF THE INTERIOR\\n        National Park Service\\n        [NPS-WASO-NAGPRA-NPS0026189; PPWOCRADN0-PCU00RP14.R50000]\\n        Notice of Inventory Completion: Children\\'s Museum of Oak Ridge, Oak Ridge, TN\\n        \\n          AGENCY:\\n          National Park Service, Interior.\\n        \\n        \\n          ACTION:\\n          Notice.\\n        \\n        \\n          SUMMARY:\\n          The Children\\'s Museum of Oak Ridge (CMOR) has completed an inventory of human remains, in consultation with the appropriate Indian Tribes or Native Hawaiian organizations, and has determined that there is no cultural affiliation between the human remains and any present-day Indian Tribes or Native Hawaiian organizations. Representatives of any Indian Tribe or Native Hawaiian organization not identified in this notice that wish to request transfer of control of these human remains should submit a written request to the CMOR. If no additional requestors come forward, transfer of control of the human remains to the Indian Tribes or Native Hawaiian organizations stated in this notice may proceed.\\n        \\n        \\n          DATES:\\n          Representatives of any Indian Tribe or Native Hawaiian organization not identified in this notice that wish to request transfer of control of these human remains should submit a written request with information in support of the request to the CMOR at the address in this notice by October 10, 2018.\\n        \\n        \\n          ADDRESSES:\\n\\n          Beth Shea, Children\\'s Museum of Oak Ridge, 461 West Outer Drive, Oak Ridge, TN 37830, telephone (865) 482-1074, email bshea@childrensmuseumofoakridge.org.\\n          \\n        \\n      \\n      \\n        SUPPLEMENTARY INFORMATION:\\n        Notice is here given in accordance with the Native American Graves Protection and Repatriation Act (NAGPRA), 25 U.S.C. 3003, of the completion of an inventory of human remains under the control of the Children\\'s Museum of Oak Ridge, Oak Ridge, TN. The human remains were removed from an unidentified site with the place-name Tellico-Loudoun, TN.\\n        This notice is published as part of the National Park Service\\'s administrative responsibilities under NAGPRA, 25 U.S.C. 3003(d)(3) and 43 CFR 10.11(d). The determinations in this notice are the sole responsibility of the museum, institution, or Federal agency that has control of the Native American human remains. The National Park Service is not responsible for the determinations in this notice.\\n        Consultation\\n        A detailed assessment of the human remains was made by the CMOR professional staff in consultation with representatives of the Cherokee Nation, Eastern Band of Cherokee Indians, and the United Keetoowah Band of Cherokee Indians in Oklahoma.\\n        History and Description of the Remains\\n        On an unknown date in 1974 or earlier, human remains representing, at minimum, two individuals were removed from Tellico-Loudoun in TN. CMOR\\'s records indicate that the skull, the mandible, and the loose teeth were collected by the same individual at the same general location in Tellico-Loudoun. The human remains were donated to CMOR by Mr. Jack Rich in 1974, and consist of one mandible with teeth, including loose teeth; and one skull with a notation of \\xe2\\x80\\x9cbasal flattening by as\\xe2\\x80\\x94infant being carried on a board.\\xe2\\x80\\x9d No known individuals were identified. No associated funerary objects are present.\\n        Determinations Made by the Children\\'s Museum of Oak Ridge\\n        Officials of the CMOR have determined that:\\n        \\xe2\\x80\\xa2 Pursuant to 25 U.S.C. 3001(9), the human remains described in this notice are Native American based on basal flattening of the skull/evidence of cradle boarding.\\n        \\xe2\\x80\\xa2 Pursuant to 25 U.S.C. 3001(9), the human remains described in this notice represent the physical remains of two individuals of Native American ancestry.\\n        \\xe2\\x80\\xa2 Pursuant to 25 U.S.C. 3001(2), a relationship of shared group identity cannot be reasonably traced between the Native American human remains and any present-day Indian Tribe.\\n        \\xe2\\x80\\xa2 Treaties, Acts of Congress, or Executive Orders, indicate that the land from which the Native American human remains were removed is the aboriginal land of the Cherokee Nation; Eastern Band of Cherokee Indians; and United Keetoowah Band of Cherokee Indians in Oklahoma.\\n        \\xe2\\x80\\xa2 Pursuant to 43 CFR 10.11(c)(1), the disposition of the human remains may be to the Cherokee Nation; Eastern Band of Cherokee Indians; and United Keetoowah Band of Cherokee Indians in Oklahoma.\\n        Additional Requestors and Disposition\\n\\n        Representatives of any Indian Tribe or Native Hawaiian organization not identified in this notice that wish to request transfer of control of these human remains should submit a written request with information in support of the request to Beth Shea, Children\\'s Museum of Oak Ridge, 461 West Outer Drive, Oak Ridge, TN 37830, telephone (865) 482-1074, email bshea@childrensmuseumofoakridge.org, by October 10, 2018. After that date, if no additional requestors have come forward, transfer of control of the human remains to the Cherokee Nation, Eastern Band of Cherokee Indians, and United Keetoowah Band of Cherokee Indians in Oklahoma may proceed.\\n        The CMOR is responsible for notifying the Cherokee Nation, Eastern Band of Cherokee Indians, and United Keetoowah Band of Cherokee Indians in Oklahoma that this notice has been published.\\n        \\n          Dated: August 6, 2018.\\n          Melanie O\\'Brien,\\n          Manager, National NAGPRA Program.\\n        \\n      \\n      [FR Doc. 2018-19533 Filed 9-7-18; 8:45 am]\\n       BILLING CODE 4312-52-P\\n    ", "agency1": "DEPARTMENT OF THE INTERIOR", "sub_agency1": "National Park Service", "dep_doc": "[NPS-WASO-NAGPRA-NPS0026189; PPWOCRADN0-PCU00RP14.R50000]", "subject": "Notice of Inventory Completion: Children\\'s Museum of Oak Ridge, Oak Ridge, TN", "agency2": "National Park Service, Interior.", "action": "Notice.", "summary": "The Children\\'s Museum of Oak Ridge (CMOR) has completed an inventory of human remains, in consultation with the appropriate Indian Tribes or Native Hawaiian organizations, and has determined that there is no cultural affiliation between the human remains and any present-day Indian Tribes or Native Hawaiian organizations. Representatives of any Indian Tribe or Native Hawaiian organization not identified in this notice that wish to request transfer of control of these human remains should submit a written request to the CMOR. If no additional requestors come forward, transfer of control of the human remains to the Indian Tribes or Native Hawaiian organizations stated in this notice may proceed.", "dates": "Representatives of any Indian Tribe or Native Hawaiian organization not identified in this notice that wish to request transfer of control of these human remains should submit a written request with information in support of the request to the CMOR at the address in this notice by October 10, 2018.", "addresses": "Beth Shea, Children\\'s Museum of Oak Ridge, 461 West Outer Drive, Oak Ridge, TN 37830, telephone (865) 482-1074, email bshea@childrensmuseumofoakridge.org.\\n          ", "signature_dated": "Dated: August 6, 2018.", "signature_name": "Melanie O\\'Brien,", "signature_title": "Manager, National NAGPRA Program.", "fr_doc": "[FR Doc. 2018-19533 Filed 9-7-18; 8:45 am]", "billing_code": " BILLING CODE 4312-52-P", "supp_info": "SUPPLEMENTARY INFORMATION: \n Notice is here given in accordance with the Native American Graves Protection and Repatriation Act (NAGPRA), 25 U.S.C. 3003, of the completion of an inventory of human remains under the control of the Children\\'s Museum of Oak Ridge, Oak Ridge, TN. The human remains were removed from an unidentified site with the place-name Tellico-Loudoun, TN. \n This notice is published as part of the National Park Service\\'s administrative responsibilities under NAGPRA, 25 U.S.C. 3003(d)(3) and 43 CFR 10.11(d). The determinations in this notice are the sole responsibility of the museum, institution, or Federal agency that has control of the Native American human remains. The National Park Service is not responsible for the determinations in this notice. \n Consultation \n A detailed assessment of the human remains was made by the CMOR professional staff in consultation with representatives of the Cherokee Nation, Eastern Band of Cherokee Indians, and the United Keetoowah Band of Cherokee Indians in Oklahoma. \n History and Description of the Remains \n On an unknown date in 1974 or earlier, human remains representing, at minimum, two individuals were removed from Tellico-Loudoun in TN. CMOR\\'s records indicate that the skull, the mandible, and the loose teeth were collected by the same individual at the same general location in Tellico-Loudoun. The human remains were donated to CMOR by Mr. Jack Rich in 1974, and consist of one mandible with teeth, including loose teeth; and one skull with a notation of \\xe2\\x80\\x9cbasal flattening by as\\xe2\\x80\\x94infant being carried on a board.\\xe2\\x80\\x9d No known individuals were identified. No associated funerary objects are present. \n Determinations Made by the Children\\'s Museum of Oak Ridge \n Officials of the CMOR have determined that: \n \\xe2\\x80\\xa2 Pursuant to 25 U.S.C. 3001(9), the human remains described in this notice are Native American based on basal flattening of the skull/evidence of cradle boarding. \n \\xe2\\x80\\xa2 Pursuant to 25 U.S.C. 3001(9), the human remains described in this notice represent the physical remains of two individuals of Native American ancestry. \n \\xe2\\x80\\xa2 Pursuant to 25 U.S.C. 3001(2), a relationship of shared group identity cannot be reasonably traced between the Native American human remains and any present-day Indian Tribe. \n \\xe2\\x80\\xa2 Treaties, Acts of Congress, or Executive Orders, indicate that the land from which the Native American human remains were removed is the aboriginal land of the Cherokee Nation; Eastern Band of Cherokee Indians; and United Keetoowah Band of Cherokee Indians in Oklahoma. \n \\xe2\\x80\\xa2 Pursuant to 43 CFR 10.11(c)(1), the disposition of the human remains may be to the Cherokee Nation; Eastern Band of Cherokee Indians; and United Keetoowah Band of Cherokee Indians in Oklahoma. \n Additional Requestors and Disposition \n Representatives of any Indian Tribe or Native Hawaiian organization not identified in this notice that wish to request transfer of control of these human remains should submit a written request with information in support of the request to Beth Shea, Children\\'s Museum of Oak Ridge, 461 West Outer Drive, Oak Ridge, TN 37830, telephone (865) 482-1074, email bshea@childrensmuseumofoakridge.org, by October 10, 2018. After that date, if no additional requestors have come forward, transfer of control of the human remains to the Cherokee Nation, Eastern Band of Cherokee Indians, and United Keetoowah Band of Cherokee Indians in Oklahoma may proceed. \n The CMOR is responsible for notifying the Cherokee Nation, Eastern Band of Cherokee Indians, and United Keetoowah Band of Cherokee Indians in Oklahoma that this notice has been published. \n ", "consultation": "A detailed assessment of the human remains was made by the CMOR professional staff in consultation with representatives of the Cherokee Nation, Eastern Band of Cherokee Indians, and the United Keetoowah Band of Cherokee Indians in Oklahoma. \n ", "h_d_r": "On an unknown date in 1974 or earlier, human remains representing, at minimum, two individuals were removed from Tellico-Loudoun in TN. CMOR\\'s records indicate that the skull, the mandible, and the loose teeth were collected by the same individual at the same general location in Tellico-Loudoun. The human remains were donated to CMOR by Mr. Jack Rich in 1974, and consist of one mandible with teeth, including loose teeth; and one skull with a notation of \\xe2\\x80\\x9cbasal flattening by as\\xe2\\x80\\x94infant being carried on a board.\\xe2\\x80\\x9d No known individuals were identified. No associated funerary objects are present. \n ", "h_d_ci": "Null", "determinations": "Determinations Made by the Children\\'s Museum of Oak Ridge \n Officials of the CMOR have determined that: \n \\xe2\\x80\\xa2 Pursuant to 25 U.S.C. 3001(9), the human remains described in this notice are Native American based on basal flattening of the skull/evidence of cradle boarding. \n \\xe2\\x80\\xa2 Pursuant to 25 U.S.C. 3001(9), the human remains described in this notice represent the physical remains of two individuals of Native American ancestry. \n \\xe2\\x80\\xa2 Pursuant to 25 U.S.C. 3001(2), a relationship of shared group identity cannot be reasonably traced between the Native American human remains and any present-day Indian Tribe. \n \\xe2\\x80\\xa2 Treaties, Acts of Congress, or Executive Orders, indicate that the land from which the Native American human remains were removed is the aboriginal land of the Cherokee Nation; Eastern Band of Cherokee Indians; and United Keetoowah Band of Cherokee Indians in Oklahoma. \n \\xe2\\x80\\xa2 Pursuant to 43 CFR 10.11(c)(1), the disposition of the human remains may be to the Cherokee Nation; Eastern Band of Cherokee Indians; and United Keetoowah Band of Cherokee Indians in Oklahoma. \n ", "a_r_d": "Representatives of any Indian Tribe or Native Hawaiian organization not identified in this notice that wish to request transfer of control of these human remains should submit a written request with information in support of the request to Beth Shea, Children\\'s Museum of Oak Ridge, 461 West Outer Drive, Oak Ridge, TN 37830, telephone (865) 482-1074, email bshea@childrensmuseumofoakridge.org, by October 10, 2018. After that date, if no additional requestors have come forward, transfer of control of the human remains to the Cherokee Nation, Eastern Band of Cherokee Indians, and United Keetoowah Band of Cherokee Indians in Oklahoma may proceed. \n The CMOR is responsible for notifying the Cherokee Nation, Eastern Band of Cherokee Indians, and United Keetoowah Band of Cherokee Indians in Oklahoma that this notice has been published. \n "}