{"index": "I_244", "messy_full": "\\n      \\n        DEPARTMENT OF THE INTERIOR\\n        National Park Service\\n        [NPS-WASO-NAGPRA-NPS0026176; PPWOCRADN0-PCU00RP14.R50000]\\n        Notice of Inventory Completion: The University of Oregon Museum of Natural and Cultural History, Eugene, OR\\n        \\n          AGENCY:\\n          National Park Service, Interior.\\n        \\n        \\n          ACTION:\\n          Notice.\\n        \\n        \\n          SUMMARY:\\n          The University of Oregon Museum of Natural and Cultural History has completed an inventory of human remains, in consultation with the appropriate Indian Tribes or Native Hawaiian organizations, and has determined that there is a cultural affiliation between the human remains and present-day Indian Tribes or Native Hawaiian organizations. Lineal descendants or representatives of any Indian Tribe or Native Hawaiian organization not identified in this notice that wish to request transfer of control of these human remains should submit a written request to the University of Oregon Museum of Natural and Cultural History. If no additional requestors come forward, transfer of control of the human remains to the lineal descendants, Indian Tribes, or Native Hawaiian organizations stated in this notice may proceed.\\n        \\n        \\n          DATES:\\n          Lineal descendants or representatives of any Indian Tribe or Native Hawaiian organization not identified in this notice that wish to request transfer of control of these human remains should submit a written request with information in support of the request to the University of Oregon Museum of Natural and Cultural History at the address in this notice by October 10, 2018.\\n        \\n        \\n          ADDRESSES:\\n\\n          Dr. Pamela Endzweig, Director of Collections, Museum of Natural and Cultural History, 1224 University of Oregon, Eugene, OR 97403-1224, telephone (541) 346-5120, email endzweig@uoregon.edu.\\n          \\n        \\n      \\n      \\n        SUPPLEMENTARY INFORMATION:\\n        Notice is here given in accordance with the Native American Graves Protection and Repatriation Act (NAGPRA), 25 U.S.C. 3003, of the completion of an inventory of human remains under the control of the University of Oregon Museum of Natural and Cultural History, Eugene, OR. The human remains were removed from a location northwest of Nixon, Washoe County, NV.\\n        This notice is published as part of the National Park Service\\'s administrative responsibilities under NAGPRA, 25 U.S.C. 3003(d)(3). The determinations in this notice are the sole responsibility of the museum, institution, or Federal agency that has control of the Native American human remains. The National Park Service is not responsible for the determinations in this notice.\\n        Consultation\\n        A detailed assessment of the human remains was made by the University of Oregon Museum of Natural and Cultural History professional staff in consultation with representatives of the Pyramid Lake Paiute Tribe of the Pyramid Lake Reservation, Nevada.\\n        History and Description of the Remains\\n        In 1950, human remains representing one individual were removed from an eroding area along Route 33, about one mile south of the extreme end of Pyramid Lake, Washoe County, NV. In 1950 the human remains were donated to the museum by the private party who initially recovered them. The human remains (cat. #11-257) represent a single adult male. No known individuals were identified. No associated funerary objects are present.\\n        Historical documents, ethnographic sources, and oral history indicate that the Northern Paiute have occupied the Pyramid Lake region since precontact times. Based on skeletal evidence, the remains were determined to be of Native American ancestry and Northern Paiute. The Northern Paiute are represented today by the Pyramid Lake Paiute Tribe of the Pyramid Lake Reservation, Nevada.\\n        Determinations Made by the University of Oregon Museum of Natural and Cultural History\\n        Officials of the University of Oregon Museum of Natural and Cultural History have determined that:\\n        \\xe2\\x80\\xa2 Pursuant to 25 U.S.C. 3001(9), the human remains described in this notice represent the physical remains of one individual of Native American ancestry.\\n        \\xe2\\x80\\xa2 Pursuant to 25 U.S.C. 3001(2), there is a relationship of shared group identity that can be reasonably traced between the Native American human remains and the Pyramid Lake Paiute Tribe of the Pyramid Lake Reservation, Nevada.\\n        Additional Requestors and Disposition\\n\\n        Lineal descendants or representatives of any Indian Tribe or Native Hawaiian organization not identified in this notice that wish to request transfer of control of these human remains should submit a written request with information in support of the request to Dr. Pamela Endzweig, Director of Collections, Museum of Natural and Cultural History, 1224 University of Oregon, Eugene, OR 97403-1224, telephone (541) 346-5120, email endzweig@uoregon.edu, by October 10, 2018. After that date, if no additional requestors have come forward, transfer of control of the human remains to Pyramid Lake Paiute Tribe of the Pyramid Lake Reservation, Nevada, may proceed.\\n        The University of Oregon Museum of Natural and Cultural History is responsible for notifying the Pyramid Lake Paiute Tribe of the Pyramid Lake Reservation, Nevada, that this notice has been published.\\n        \\n          \\n          Dated: August 3, 2018.\\n          Melanie O\\'Brien,\\n          Manager, National NAGPRA Program.\\n        \\n      \\n      [FR Doc. 2018-19526 Filed 9-7-18; 8:45 am]\\n       BILLING CODE 4312-52-P\\n    ", "agency1": "DEPARTMENT OF THE INTERIOR", "sub_agency1": "National Park Service", "dep_doc": "[NPS-WASO-NAGPRA-NPS0026176; PPWOCRADN0-PCU00RP14.R50000]", "subject": "Notice of Inventory Completion: The University of Oregon Museum of Natural and Cultural History, Eugene, OR", "agency2": "National Park Service, Interior.", "action": "Notice.", "summary": "The University of Oregon Museum of Natural and Cultural History has completed an inventory of human remains, in consultation with the appropriate Indian Tribes or Native Hawaiian organizations, and has determined that there is a cultural affiliation between the human remains and present-day Indian Tribes or Native Hawaiian organizations. Lineal descendants or representatives of any Indian Tribe or Native Hawaiian organization not identified in this notice that wish to request transfer of control of these human remains should submit a written request to the University of Oregon Museum of Natural and Cultural History. If no additional requestors come forward, transfer of control of the human remains to the lineal descendants, Indian Tribes, or Native Hawaiian organizations stated in this notice may proceed.", "dates": "Lineal descendants or representatives of any Indian Tribe or Native Hawaiian organization not identified in this notice that wish to request transfer of control of these human remains should submit a written request with information in support of the request to the University of Oregon Museum of Natural and Cultural History at the address in this notice by October 10, 2018.", "addresses": "Dr. Pamela Endzweig, Director of Collections, Museum of Natural and Cultural History, 1224 University of Oregon, Eugene, OR 97403-1224, telephone (541) 346-5120, email endzweig@uoregon.edu.\\n          ", "signature_dated": "Dated: August 3, 2018.", "signature_name": "Melanie O\\'Brien,", "signature_title": "Manager, National NAGPRA Program.", "fr_doc": "[FR Doc. 2018-19526 Filed 9-7-18; 8:45 am]", "billing_code": " BILLING CODE 4312-52-P", "supp_info": "SUPPLEMENTARY INFORMATION: \n Notice is here given in accordance with the Native American Graves Protection and Repatriation Act (NAGPRA), 25 U.S.C. 3003, of the completion of an inventory of human remains under the control of the University of Oregon Museum of Natural and Cultural History, Eugene, OR. The human remains were removed from a location northwest of Nixon, Washoe County, NV. \n This notice is published as part of the National Park Service\\'s administrative responsibilities under NAGPRA, 25 U.S.C. 3003(d)(3). The determinations in this notice are the sole responsibility of the museum, institution, or Federal agency that has control of the Native American human remains. The National Park Service is not responsible for the determinations in this notice. \n Consultation \n A detailed assessment of the human remains was made by the University of Oregon Museum of Natural and Cultural History professional staff in consultation with representatives of the Pyramid Lake Paiute Tribe of the Pyramid Lake Reservation, Nevada. \n History and Description of the Remains \n In 1950, human remains representing one individual were removed from an eroding area along Route 33, about one mile south of the extreme end of Pyramid Lake, Washoe County, NV. In 1950 the human remains were donated to the museum by the private party who initially recovered them. The human remains (cat. #11-257) represent a single adult male. No known individuals were identified. No associated funerary objects are present. \n Historical documents, ethnographic sources, and oral history indicate that the Northern Paiute have occupied the Pyramid Lake region since precontact times. Based on skeletal evidence, the remains were determined to be of Native American ancestry and Northern Paiute. The Northern Paiute are represented today by the Pyramid Lake Paiute Tribe of the Pyramid Lake Reservation, Nevada. \n Determinations Made by the University of Oregon Museum of Natural and Cultural History \n Officials of the University of Oregon Museum of Natural and Cultural History have determined that: \n \\xe2\\x80\\xa2 Pursuant to 25 U.S.C. 3001(9), the human remains described in this notice represent the physical remains of one individual of Native American ancestry. \n \\xe2\\x80\\xa2 Pursuant to 25 U.S.C. 3001(2), there is a relationship of shared group identity that can be reasonably traced between the Native American human remains and the Pyramid Lake Paiute Tribe of the Pyramid Lake Reservation, Nevada. \n Additional Requestors and Disposition \n Lineal descendants or representatives of any Indian Tribe or Native Hawaiian organization not identified in this notice that wish to request transfer of control of these human remains should submit a written request with information in support of the request to Dr. Pamela Endzweig, Director of Collections, Museum of Natural and Cultural History, 1224 University of Oregon, Eugene, OR 97403-1224, telephone (541) 346-5120, email endzweig@uoregon.edu, by October 10, 2018. After that date, if no additional requestors have come forward, transfer of control of the human remains to Pyramid Lake Paiute Tribe of the Pyramid Lake Reservation, Nevada, may proceed. \n The University of Oregon Museum of Natural and Cultural History is responsible for notifying the Pyramid Lake Paiute Tribe of the Pyramid Lake Reservation, Nevada, that this notice has been published. \n ", "consultation": "A detailed assessment of the human remains was made by the University of Oregon Museum of Natural and Cultural History professional staff in consultation with representatives of the Pyramid Lake Paiute Tribe of the Pyramid Lake Reservation, Nevada. \n ", "h_d_r": "In 1950, human remains representing one individual were removed from an eroding area along Route 33, about one mile south of the extreme end of Pyramid Lake, Washoe County, NV. In 1950 the human remains were donated to the museum by the private party who initially recovered them. The human remains (cat. #11-257) represent a single adult male. No known individuals were identified. No associated funerary objects are present. \n Historical documents, ethnographic sources, and oral history indicate that the Northern Paiute have occupied the Pyramid Lake region since precontact times. Based on skeletal evidence, the remains were determined to be of Native American ancestry and Northern Paiute. The Northern Paiute are represented today by the Pyramid Lake Paiute Tribe of the Pyramid Lake Reservation, Nevada. \n ", "h_d_ci": "Null", "determinations": "Determinations Made by the University of Oregon Museum of Natural and Cultural History \n Officials of the University of Oregon Museum of Natural and Cultural History have determined that: \n \\xe2\\x80\\xa2 Pursuant to 25 U.S.C. 3001(9), the human remains described in this notice represent the physical remains of one individual of Native American ancestry. \n \\xe2\\x80\\xa2 Pursuant to 25 U.S.C. 3001(2), there is a relationship of shared group identity that can be reasonably traced between the Native American human remains and the Pyramid Lake Paiute Tribe of the Pyramid Lake Reservation, Nevada. \n ", "a_r_d": "Lineal descendants or representatives of any Indian Tribe or Native Hawaiian organization not identified in this notice that wish to request transfer of control of these human remains should submit a written request with information in support of the request to Dr. Pamela Endzweig, Director of Collections, Museum of Natural and Cultural History, 1224 University of Oregon, Eugene, OR 97403-1224, telephone (541) 346-5120, email endzweig@uoregon.edu, by October 10, 2018. After that date, if no additional requestors have come forward, transfer of control of the human remains to Pyramid Lake Paiute Tribe of the Pyramid Lake Reservation, Nevada, may proceed. \n The University of Oregon Museum of Natural and Cultural History is responsible for notifying the Pyramid Lake Paiute Tribe of the Pyramid Lake Reservation, Nevada, that this notice has been published. \n "}