{"index": "I_254", "messy_full": "\\n      \\n        DEPARTMENT OF THE INTERIOR\\n        National Park Service\\n        [NPS-WASO-NAGPRA-NPS0026039; PPWOCRADN0-PCU00RP14.R50000]\\n        Notice of Inventory Completion: The American Museum of Natural History, New York, NY; Correction; Correction\\n        \\n          AGENCY:\\n          National Park Service, Interior.\\n        \\n        \\n          ACTION:\\n          Notice; correction.\\n        \\n        \\n          SUMMARY:\\n\\n          The American Museum of Natural History has corrected an inventory of human remains and associated funerary objects, published in a Notice of Inventory Completion in the Federal Register on May 11, 2016. This notice corrects the minimum number of individuals. Lineal descendants or representatives of any Indian Tribe or Native Hawaiian organization not identified in this notice that wish to request transfer of control of these human remains and associated funerary objects should submit a written request to the American Museum of Natural History. If no additional requestors come forward, transfer of control of the human remains and associated funerary objects to the lineal descendants, Indian Tribes, or Native Hawaiian organizations stated in this notice may proceed.\\n        \\n        \\n          DATES:\\n          Lineal descendants or representatives of any Indian Tribe or Native Hawaiian organization not identified in this notice that wish to request transfer of control of these human remains and associated funerary objects should submit a written request with information in support of the request to the American Museum of Natural History at the address in this notice by September 10, 2018.\\n        \\n        \\n          ADDRESSES:\\n\\n          Nell Murphy, American Museum of Natural History, Central Park West at 79th Street, New York, NY 10024, telephone (212) 769-5837, email nmurphy@amnh.org.\\n          \\n        \\n      \\n      \\n        SUPPLEMENTARY INFORMATION:\\n        Notice is here given in accordance with the Native American Graves Protection and Repatriation Act (NAGPRA), 25 U.S.C. 3003, of the correction of an inventory of human remains and associated funerary objects under the control of the American Museum of Natural History, New York, NY. The human remains and associated funerary objects were removed from the Sebonac site, Shinnecock Hills, Suffolk County, NY.\\n        This notice is published as part of the National Park Service\\'s administrative responsibilities under NAGPRA, 25 U.S.C. 3003(d)(3). The determinations in this notice are the sole responsibility of the museum, institution, or Federal agency that has control of the Native American human remains and associated funerary objects. The National Park Service is not responsible for the determinations in this notice.\\n\\n        This notice corrects the minimum number of individuals published in a correction to a Notice of Inventory Completion in the Federal Register (81 FR 29304-29305, May 11, 2016). Four individuals were omitted from the inventory of human remains and associated funerary objects from the Sebonac site. Transfer of control of the items in this correction notice has not occurred.\\n        Correction\\n        In the Federal Register (81 FR 29305, May 11, 2016), column 1, paragraph 5, sentence 2 is corrected by substituting the following sentence:\\n        \\n        \\n          In 1902, human remains representing, at minimum, 20 individuals, including 1 adult female, 3 adults of unknown sex, and 16 subadults of unknown sex, were removed from the Sebonac site, Shinnecock Hills, Suffolk County, NY, during Raymond M. Harrington\\'s excavations, sponsored by Frederick Ward Putnam and the American Museum of Natural History. \\n        \\n        \\n        In the Federal Register (81 FR 29305, May 11, 2016), column 1, paragraph 6, sentence 2 is corrected by substituting the following sentence:\\n        \\n        \\n          Pursuant to 25 U.S.C. 3001(9), the human remains described in this notice represent the physical remains of 20 individuals of Native American ancestry.\\n        \\n        Additional Requestors and Disposition\\n\\n        Lineal descendants or representatives of any Indian Tribe or Native Hawaiian organization not identified in this notice that wish to request transfer of control of these human remains and associated funerary objects should submit a written request with information in support of the request to Nell Murphy, American Museum of Natural History, Central Park West at 79th Street, New York, NY 10024, telephone (212) 769-5837, email nmurphy@amnh.org, by September 10, 2018. After that date, if no additional requestors have come forward, transfer of control of the human remains and associated funerary objects to the Shinnecock Indian Nation may proceed.\\n        The American Museum of Natural History is responsible for notifying the Shinnecock Indian Nation that this notice has been published.\\n        \\n          Dated: July 13, 2018.\\n          Melanie O\\'Brien,\\n          Manager, National NAGPRA Program.\\n        \\n      \\n      [FR Doc. 2018-17219 Filed 8-9-18; 8:45 am]\\n       BILLING CODE 4312-52-P\\n    ", "agency1": "DEPARTMENT OF THE INTERIOR", "sub_agency1": "National Park Service", "dep_doc": "[NPS-WASO-NAGPRA-NPS0026039; PPWOCRADN0-PCU00RP14.R50000]", "subject": "Notice of Inventory Completion: The American Museum of Natural History, New York, NY; Correction; Correction", "agency2": "National Park Service, Interior.", "action": "Notice; correction.", "summary": "The American Museum of Natural History has corrected an inventory of human remains and associated funerary objects, published in a Notice of Inventory Completion in the Federal Register on May 11, 2016. This notice corrects the minimum number of individuals. Lineal descendants or representatives of any Indian Tribe or Native Hawaiian organization not identified in this notice that wish to request transfer of control of these human remains and associated funerary objects should submit a written request to the American Museum of Natural History. If no additional requestors come forward, transfer of control of the human remains and associated funerary objects to the lineal descendants, Indian Tribes, or Native Hawaiian organizations stated in this notice may proceed.", "dates": "Lineal descendants or representatives of any Indian Tribe or Native Hawaiian organization not identified in this notice that wish to request transfer of control of these human remains and associated funerary objects should submit a written request with information in support of the request to the American Museum of Natural History at the address in this notice by September 10, 2018.", "addresses": "Nell Murphy, American Museum of Natural History, Central Park West at 79th Street, New York, NY 10024, telephone (212) 769-5837, email nmurphy@amnh.org.\\n          ", "signature_dated": "Dated: July 13, 2018.", "signature_name": "Melanie O\\'Brien,", "signature_title": "Manager, National NAGPRA Program.", "fr_doc": "[FR Doc. 2018-17219 Filed 8-9-18; 8:45 am]", "billing_code": " BILLING CODE 4312-52-P", "supp_info": "SUPPLEMENTARY INFORMATION: \n Notice is here given in accordance with the Native American Graves Protection and Repatriation Act (NAGPRA), 25 U.S.C. 3003, of the correction of an inventory of human remains and associated funerary objects under the control of the American Museum of Natural History, New York, NY. The human remains and associated funerary objects were removed from the Sebonac site, Shinnecock Hills, Suffolk County, NY. \n This notice is published as part of the National Park Service\\'s administrative responsibilities under NAGPRA, 25 U.S.C. 3003(d)(3). The determinations in this notice are the sole responsibility of the museum, institution, or Federal agency that has control of the Native American human remains and associated funerary objects. The National Park Service is not responsible for the determinations in this notice. \n This notice corrects the minimum number of individuals published in a correction to a Notice of Inventory Completion in the Federal Register (81 FR 29304-29305, May 11, 2016). Four individuals were omitted from the inventory of human remains and associated funerary objects from the Sebonac site. Transfer of control of the items in this correction notice has not occurred. \n Correction \n In the Federal Register (81 FR 29305, May 11, 2016), column 1, paragraph 5, sentence 2 is corrected by substituting the following sentence: \n In the Federal Register (81 FR 29305, May 11, 2016), column 1, paragraph 6, sentence 2 is corrected by substituting the following sentence: \n Additional Requestors and Disposition \n Lineal descendants or representatives of any Indian Tribe or Native Hawaiian organization not identified in this notice that wish to request transfer of control of these human remains and associated funerary objects should submit a written request with information in support of the request to Nell Murphy, American Museum of Natural History, Central Park West at 79th Street, New York, NY 10024, telephone (212) 769-5837, email nmurphy@amnh.org, by September 10, 2018. After that date, if no additional requestors have come forward, transfer of control of the human remains and associated funerary objects to the Shinnecock Indian Nation may proceed. \n The American Museum of Natural History is responsible for notifying the Shinnecock Indian Nation that this notice has been published. \n ", "consultation": "Null", "h_d_r": "Null", "h_d_ci": "Null", "determinations": "Null", "a_r_d": "Lineal descendants or representatives of any Indian Tribe or Native Hawaiian organization not identified in this notice that wish to request transfer of control of these human remains and associated funerary objects should submit a written request with information in support of the request to Nell Murphy, American Museum of Natural History, Central Park West at 79th Street, New York, NY 10024, telephone (212) 769-5837, email nmurphy@amnh.org, by September 10, 2018. After that date, if no additional requestors have come forward, transfer of control of the human remains and associated funerary objects to the Shinnecock Indian Nation may proceed. \n The American Museum of Natural History is responsible for notifying the Shinnecock Indian Nation that this notice has been published. \n "}