{"index": "I_272", "messy_full": "\\n      \\n        DEPARTMENT OF THE INTERIOR\\n        National Park Service\\n        [NPS-WASO-NAGPRA-NPS0025758; PPWOCRADN0-PCU00RP14.R50000]\\n        Notice of Inventory Completion: Museum of Ojibwa Culture and Marquette Mission Park, City of St. Ignace, MI\\n        \\n          AGENCY:\\n          National Park Service, Interior.\\n        \\n        \\n          ACTION:\\n          Notice.\\n        \\n        \\n          SUMMARY:\\n          The Museum of Ojibwa Culture and Marquette Mission Park, City of St. Ignace, has completed an inventory of human remains, in consultation with the appropriate Indian Tribes or Native Hawaiian organizations, and has determined that there is no cultural affiliation between the human remains and any present-day Indian Tribes or Native Hawaiian organizations. Representatives of any Indian Tribe or Native Hawaiian organization not identified in this notice that wish to request transfer of control of these human remains should submit a written request to the Museum of Ojibwa Culture and Marquette Mission Park, City of St. Ignace. If no additional requestors come forward, transfer of control of the human remains to the Indian Tribes or Native Hawaiian organizations stated in this notice may proceed.\\n        \\n        \\n          DATES:\\n          Representatives of any Indian Tribe or Native Hawaiian organization not identified in this notice that wish to request transfer of control of these human remains should submit a written request with information in support of the request to the Museum of Ojibwa Culture and Marquette Mission Park, City of St. Ignace at the address in this notice by August 13, 2018.\\n        \\n        \\n          ADDRESSES:\\n\\n          Shirley Sorrels, Director, Museum of Ojibwa Culture and Marquette Mission Park, c/o Bernstein & Associates, 1041 N Lafayette Street, Denver, CO 80218, telephone (303) 894-0648, email jan@nagpra.info.\\n          \\n        \\n      \\n      \\n        SUPPLEMENTARY INFORMATION:\\n        Notice is here given in accordance with the Native American Graves Protection and Repatriation Act (NAGPRA), 25 U.S.C. 3003, of the completion of an inventory of human remains under the control of the Museum of Ojibwa Culture and Marquette Mission Park, City of St. Ignace. The human remains were removed from Marquette Mission Site (20MK82), Mackinac County, MI.\\n        This notice is published as part of the National Park Service\\'s administrative responsibilities under NAGPRA, 25 U.S.C. 3003(d)(3) and 43 CFR 10.11(d). The determinations in this notice are the sole responsibility of the museum, institution, or Federal agency that has control of the Native American human remains. The National Park Service is not responsible for the determinations in this notice.\\n        Consultation\\n        A detailed assessment of the human remains was made by the Museum of Ojibwa Culture and Marquette Mission Park, City of St. Ignace professional staff in consultation with representatives of the Forest County Potawatomi Community, Wisconsin; Little Traverse Bay Bands of Odawa Indians, Michigan; Saginaw Chippewa Indian Tribe of Michigan; and Sault Ste. Marie Tribe of Chippewa Indians, Michigan.\\n        History and Description of the Remains\\n\\n        In 1983, 1997, and 2001, (during excavations by Michigan State University archeologists), human remains representing, at minimum, three individuals were removed with faunal remains from the Marquette Mission site (20MK82) in St. Ignace, Mackinac County, MI. After each excavation season, the excavated material were transported to the Michigan State University Museum, where they were curated. In early 2017, during an examination of the faunal remains, three human teeth were identified: A child\\'s worn shovel-shaped maxillary incisor (5810.005.02 box 8), an adult shovel-shaped incisor (5810.169.91.01), and an adult molar (5810.123.03.03). No known individuals were identified. No associated funerary objects are present.\\n        The archeological site is within Marquette Mission Park. The Museum of Ojibwa Culture and Marquette Mission Park manages the Park. Both the Park and the Museum are under the auspices of the City of St. Ignace. Based on the archaeological context, the human remains date to A.D. 17th century, when Native Americans representing many different cultures, including but not limited to, the Wendat (Huron), Anishinaabek [Ojibwa/Ojibwe (Chippewa), Odawa (Ottawa)], Bod\\xc3\\xa9wadmi (Potawatomi), and Haudenosaunee (Iroquois), lived in proximity to the Marquette Mission site.\\n        Determinations Made by the Museum of Ojibwa Culture and Marquette Mission Park, City of St. Ignace\\n        Officials of the Museum of Ojibwa Culture and Marquette Mission Park, City of St. Ignace have determined that:\\n        \\xe2\\x80\\xa2 Pursuant to 25 U.S.C. 3001(9), the human remains described in this notice are Native American based on the biological and archeological evidence.\\n        \\xe2\\x80\\xa2 Pursuant to 25 U.S.C. 3001(9), the human remains described in this notice represent the physical remains of three individuals of Native American ancestry.\\n        \\xe2\\x80\\xa2 Pursuant to 25 U.S.C. 3001(2), a relationship of shared group identity cannot be reasonably traced between the Native American human remains and any present-day Indian tribe.\\n        \\xe2\\x80\\xa2 According to final judgments of the Indian Claims Commission or the Court of Federal Claims, or Treaties, Acts of Congress, or Executive Orders, the land from which the Native American human remains were removed is the aboriginal land of the Absentee-Shawnee Tribe of Indians of Oklahoma; Bad River Band of the Lake Superior Tribe of Chippewa Indians of the Bad River Reservation, Wisconsin; Bay Mills Indian Community, Michigan; Chippewa Cree Indians of the Rocky Boy\\'s Reservation, Montana (previously listed as the Chippewa-Cree Indians of the Rocky Boy\\'s Reservation, Montana); Citizen Potawatomi Nation, Oklahoma; Delaware Nation, Oklahoma; Delaware Tribe of Indians; Eastern Shawnee Tribe of Oklahoma; Forest County Potawatomi Community, Wisconsin; Grand Traverse Band of Ottawa and Chippewa Indians, Michigan; Hannahville Indian Community, Michigan; Keweenaw Bay Indian Community, Michigan; Kickapoo Traditional Tribe of Texas; Kickapoo Tribe of Indians of the Kickapoo Reservation in Kansas; Kickapoo Tribe of Oklahoma; Lac Courte Oreilles Band of Lake Superior Chippewa Indians of Wisconsin; Lac du Flambeau Band of Lake Superior Chippewa Indians of the Lac du Flambeau Reservation of Wisconsin; Lac Vieux Desert Band of Lake Superior Chippewa Indians of Michigan; Little River Band of Ottawa Indians, Michigan; Little Traverse Bay Bands of Odawa Indians, Michigan; Match-e-be-nash-she-wish Band of Pottawatomi Indians of Michigan; Miami Tribe of Oklahoma; Minnesota Chippewa Tribe, Minnesota (Six component reservations: Bois Forte Band (Nett Lake); Fond du Lac Band; Grand Portage Band; Leech Lake Band; Mille Lacs Band; White Earth Band); Nottawaseppi Huron Band of the Potawatomi, Michigan (previously listed as the Huron Potawatomi, Inc.); Ottawa Tribe of Oklahoma; Peoria Tribe of Indians of Oklahoma; Pokagon Band of Potawatomi Indians, Michigan and Indiana; Prairie Band Potawatomi Nation (previously listed as the Prairie Band of Potawatomi Nation, Kansas); Red Cliff Band of Lake Superior Chippewa Indians of Wisconsin; Red Lake Band of Chippewa Indians, Minnesota; Saginaw Chippewa Indian Tribe of Michigan; Sault Ste. Marie Tribe of Chippewa Indians, Michigan; Shawnee Tribe, Oklahoma; Sokaogon Chippewa Community, Wisconsin; St. Croix Chippewa Indians of Wisconsin; Stockbridge Munsee Community, Wisconsin; Turtle Mountain Band of Chippewa Indians of North Dakota; and Wyandotte Nation (hereinafter referred to as \\xe2\\x80\\x9cThe Tribes\\xe2\\x80\\x9d)\\n        \\xe2\\x80\\xa2 Pursuant to 43 CFR 10.11(c)(1), the disposition of the human remains may be to The Tribes.\\n        Additional Requestors and Disposition\\n\\n        Representatives of any Indian Tribe or Native Hawaiian organization not identified in this notice that wish to request transfer of control of these human remains should submit a written request with information in support of the request to Shirley Sorrels, Director, Museum of Ojibwa Culture and Marquette Mission Park, c/o Bernstein & Associates, 1041 N Lafayette Street, Denver, CO 80218, telephone (303) 894-0648, email jan@nagpra.info, by August 13, 2018. After that date, if no additional requestors have come forward, transfer of control of the human remains to The Tribes may proceed.\\n        The Museum of Ojibwa Culture and Marquette Mission Park, City of St. Ignace is responsible for notifying The Tribes that this notice has been published.\\n        \\n          Dated: June 11, 2018.\\n          Melanie O\\'Brien,\\n          Manager, National NAGPRA Program. \\n        \\n      \\n      [FR Doc. 2018-14900 Filed 7-11-18; 8:45 am]\\n       BILLING CODE 4312-52-P\\n    ", "agency1": "DEPARTMENT OF THE INTERIOR", "sub_agency1": "National Park Service", "dep_doc": "[NPS-WASO-NAGPRA-NPS0025758; PPWOCRADN0-PCU00RP14.R50000]", "subject": "Notice of Inventory Completion: Museum of Ojibwa Culture and Marquette Mission Park, City of St. Ignace, MI", "agency2": "National Park Service, Interior.", "action": "Notice.", "summary": "The Museum of Ojibwa Culture and Marquette Mission Park, City of St. Ignace, has completed an inventory of human remains, in consultation with the appropriate Indian Tribes or Native Hawaiian organizations, and has determined that there is no cultural affiliation between the human remains and any present-day Indian Tribes or Native Hawaiian organizations. Representatives of any Indian Tribe or Native Hawaiian organization not identified in this notice that wish to request transfer of control of these human remains should submit a written request to the Museum of Ojibwa Culture and Marquette Mission Park, City of St. Ignace. If no additional requestors come forward, transfer of control of the human remains to the Indian Tribes or Native Hawaiian organizations stated in this notice may proceed.", "dates": "Representatives of any Indian Tribe or Native Hawaiian organization not identified in this notice that wish to request transfer of control of these human remains should submit a written request with information in support of the request to the Museum of Ojibwa Culture and Marquette Mission Park, City of St. Ignace at the address in this notice by August 13, 2018.", "addresses": "Shirley Sorrels, Director, Museum of Ojibwa Culture and Marquette Mission Park, c/o Bernstein & Associates, 1041 N Lafayette Street, Denver, CO 80218, telephone (303) 894-0648, email jan@nagpra.info.\\n          ", "signature_dated": "Dated: June 11, 2018.", "signature_name": "Melanie O\\'Brien,", "signature_title": "Manager, National NAGPRA Program. ", "fr_doc": "[FR Doc. 2018-14900 Filed 7-11-18; 8:45 am]", "billing_code": " BILLING CODE 4312-52-P", "supp_info": "SUPPLEMENTARY INFORMATION: \n Notice is here given in accordance with the Native American Graves Protection and Repatriation Act (NAGPRA), 25 U.S.C. 3003, of the completion of an inventory of human remains under the control of the Museum of Ojibwa Culture and Marquette Mission Park, City of St. Ignace. The human remains were removed from Marquette Mission Site (20MK82), Mackinac County, MI. \n This notice is published as part of the National Park Service\\'s administrative responsibilities under NAGPRA, 25 U.S.C. 3003(d)(3) and 43 CFR 10.11(d). The determinations in this notice are the sole responsibility of the museum, institution, or Federal agency that has control of the Native American human remains. The National Park Service is not responsible for the determinations in this notice. \n Consultation \n A detailed assessment of the human remains was made by the Museum of Ojibwa Culture and Marquette Mission Park, City of St. Ignace professional staff in consultation with representatives of the Forest County Potawatomi Community, Wisconsin; Little Traverse Bay Bands of Odawa Indians, Michigan; Saginaw Chippewa Indian Tribe of Michigan; and Sault Ste. Marie Tribe of Chippewa Indians, Michigan. \n History and Description of the Remains \n In 1983, 1997, and 2001, (during excavations by Michigan State University archeologists), human remains representing, at minimum, three individuals were removed with faunal remains from the Marquette Mission site (20MK82) in St. Ignace, Mackinac County, MI. After each excavation season, the excavated material were transported to the Michigan State University Museum, where they were curated. In early 2017, during an examination of the faunal remains, three human teeth were identified: A child\\'s worn shovel-shaped maxillary incisor (5810.005.02 box 8), an adult shovel-shaped incisor (5810.169.91.01), and an adult molar (5810.123.03.03). No known individuals were identified. No associated funerary objects are present. \n The archeological site is within Marquette Mission Park. The Museum of Ojibwa Culture and Marquette Mission Park manages the Park. Both the Park and the Museum are under the auspices of the City of St. Ignace. Based on the archaeological context, the human remains date to A.D. 17th century, when Native Americans representing many different cultures, including but not limited to, the Wendat (Huron), Anishinaabek [Ojibwa/Ojibwe (Chippewa), Odawa (Ottawa)], Bod\\xc3\\xa9wadmi (Potawatomi), and Haudenosaunee (Iroquois), lived in proximity to the Marquette Mission site. \n Determinations Made by the Museum of Ojibwa Culture and Marquette Mission Park, City of St. Ignace \n Officials of the Museum of Ojibwa Culture and Marquette Mission Park, City of St. Ignace have determined that: \n \\xe2\\x80\\xa2 Pursuant to 25 U.S.C. 3001(9), the human remains described in this notice are Native American based on the biological and archeological evidence. \n \\xe2\\x80\\xa2 Pursuant to 25 U.S.C. 3001(9), the human remains described in this notice represent the physical remains of three individuals of Native American ancestry. \n \\xe2\\x80\\xa2 Pursuant to 25 U.S.C. 3001(2), a relationship of shared group identity cannot be reasonably traced between the Native American human remains and any present-day Indian tribe. \n \\xe2\\x80\\xa2 According to final judgments of the Indian Claims Commission or the Court of Federal Claims, or Treaties, Acts of Congress, or Executive Orders, the land from which the Native American human remains were removed is the aboriginal land of the Absentee-Shawnee Tribe of Indians of Oklahoma; Bad River Band of the Lake Superior Tribe of Chippewa Indians of the Bad River Reservation, Wisconsin; Bay Mills Indian Community, Michigan; Chippewa Cree Indians of the Rocky Boy\\'s Reservation, Montana (previously listed as the Chippewa-Cree Indians of the Rocky Boy\\'s Reservation, Montana); Citizen Potawatomi Nation, Oklahoma; Delaware Nation, Oklahoma; Delaware Tribe of Indians; Eastern Shawnee Tribe of Oklahoma; Forest County Potawatomi Community, Wisconsin; Grand Traverse Band of Ottawa and Chippewa Indians, Michigan; Hannahville Indian Community, Michigan; Keweenaw Bay Indian Community, Michigan; Kickapoo Traditional Tribe of Texas; Kickapoo Tribe of Indians of the Kickapoo Reservation in Kansas; Kickapoo Tribe of Oklahoma; Lac Courte Oreilles Band of Lake Superior Chippewa Indians of Wisconsin; Lac du Flambeau Band of Lake Superior Chippewa Indians of the Lac du Flambeau Reservation of Wisconsin; Lac Vieux Desert Band of Lake Superior Chippewa Indians of Michigan; Little River Band of Ottawa Indians, Michigan; Little Traverse Bay Bands of Odawa Indians, Michigan; Match-e-be-nash-she-wish Band of Pottawatomi Indians of Michigan; Miami Tribe of Oklahoma; Minnesota Chippewa Tribe, Minnesota (Six component reservations: Bois Forte Band (Nett Lake); Fond du Lac Band; Grand Portage Band; Leech Lake Band; Mille Lacs Band; White Earth Band); Nottawaseppi Huron Band of the Potawatomi, Michigan (previously listed as the Huron Potawatomi, Inc.); Ottawa Tribe of Oklahoma; Peoria Tribe of Indians of Oklahoma; Pokagon Band of Potawatomi Indians, Michigan and Indiana; Prairie Band Potawatomi Nation (previously listed as the Prairie Band of Potawatomi Nation, Kansas); Red Cliff Band of Lake Superior Chippewa Indians of Wisconsin; Red Lake Band of Chippewa Indians, Minnesota; Saginaw Chippewa Indian Tribe of Michigan; Sault Ste. Marie Tribe of Chippewa Indians, Michigan; Shawnee Tribe, Oklahoma; Sokaogon Chippewa Community, Wisconsin; St. Croix Chippewa Indians of Wisconsin; Stockbridge Munsee Community, Wisconsin; Turtle Mountain Band of Chippewa Indians of North Dakota; and Wyandotte Nation (hereinafter referred to as \\xe2\\x80\\x9cThe Tribes\\xe2\\x80\\x9d) \n \\xe2\\x80\\xa2 Pursuant to 43 CFR 10.11(c)(1), the disposition of the human remains may be to The Tribes. \n Additional Requestors and Disposition \n Representatives of any Indian Tribe or Native Hawaiian organization not identified in this notice that wish to request transfer of control of these human remains should submit a written request with information in support of the request to Shirley Sorrels, Director, Museum of Ojibwa Culture and Marquette Mission Park, c/o Bernstein & Associates, 1041 N Lafayette Street, Denver, CO 80218, telephone (303) 894-0648, email jan@nagpra.info, by August 13, 2018. After that date, if no additional requestors have come forward, transfer of control of the human remains to The Tribes may proceed. \n The Museum of Ojibwa Culture and Marquette Mission Park, City of St. Ignace is responsible for notifying The Tribes that this notice has been published. \n ", "consultation": "A detailed assessment of the human remains was made by the Museum of Ojibwa Culture and Marquette Mission Park, City of St. Ignace professional staff in consultation with representatives of the Forest County Potawatomi Community, Wisconsin; Little Traverse Bay Bands of Odawa Indians, Michigan; Saginaw Chippewa Indian Tribe of Michigan; and Sault Ste. Marie Tribe of Chippewa Indians, Michigan. \n ", "h_d_r": "In 1983, 1997, and 2001, (during excavations by Michigan State University archeologists), human remains representing, at minimum, three individuals were removed with faunal remains from the Marquette Mission site (20MK82) in St. Ignace, Mackinac County, MI. After each excavation season, the excavated material were transported to the Michigan State University Museum, where they were curated. In early 2017, during an examination of the faunal remains, three human teeth were identified: A child\\'s worn shovel-shaped maxillary incisor (5810.005.02 box 8), an adult shovel-shaped incisor (5810.169.91.01), and an adult molar (5810.123.03.03). No known individuals were identified. No associated funerary objects are present. \n The archeological site is within Marquette Mission Park. The Museum of Ojibwa Culture and Marquette Mission Park manages the Park. Both the Park and the Museum are under the auspices of the City of St. Ignace. Based on the archaeological context, the human remains date to A.D. 17th century, when Native Americans representing many different cultures, including but not limited to, the Wendat (Huron), Anishinaabek [Ojibwa/Ojibwe (Chippewa), Odawa (Ottawa)], Bod\\xc3\\xa9wadmi (Potawatomi), and Haudenosaunee (Iroquois), lived in proximity to the Marquette Mission site. \n ", "h_d_ci": "Null", "determinations": "Determinations Made by the Museum of Ojibwa Culture and Marquette Mission Park, City of St. Ignace \n Officials of the Museum of Ojibwa Culture and Marquette Mission Park, City of St. Ignace have determined that: \n \\xe2\\x80\\xa2 Pursuant to 25 U.S.C. 3001(9), the human remains described in this notice are Native American based on the biological and archeological evidence. \n \\xe2\\x80\\xa2 Pursuant to 25 U.S.C. 3001(9), the human remains described in this notice represent the physical remains of three individuals of Native American ancestry. \n \\xe2\\x80\\xa2 Pursuant to 25 U.S.C. 3001(2), a relationship of shared group identity cannot be reasonably traced between the Native American human remains and any present-day Indian tribe. \n \\xe2\\x80\\xa2 According to final judgments of the Indian Claims Commission or the Court of Federal Claims, or Treaties, Acts of Congress, or Executive Orders, the land from which the Native American human remains were removed is the aboriginal land of the Absentee-Shawnee Tribe of Indians of Oklahoma; Bad River Band of the Lake Superior Tribe of Chippewa Indians of the Bad River Reservation, Wisconsin; Bay Mills Indian Community, Michigan; Chippewa Cree Indians of the Rocky Boy\\'s Reservation, Montana (previously listed as the Chippewa-Cree Indians of the Rocky Boy\\'s Reservation, Montana); Citizen Potawatomi Nation, Oklahoma; Delaware Nation, Oklahoma; Delaware Tribe of Indians; Eastern Shawnee Tribe of Oklahoma; Forest County Potawatomi Community, Wisconsin; Grand Traverse Band of Ottawa and Chippewa Indians, Michigan; Hannahville Indian Community, Michigan; Keweenaw Bay Indian Community, Michigan; Kickapoo Traditional Tribe of Texas; Kickapoo Tribe of Indians of the Kickapoo Reservation in Kansas; Kickapoo Tribe of Oklahoma; Lac Courte Oreilles Band of Lake Superior Chippewa Indians of Wisconsin; Lac du Flambeau Band of Lake Superior Chippewa Indians of the Lac du Flambeau Reservation of Wisconsin; Lac Vieux Desert Band of Lake Superior Chippewa Indians of Michigan; Little River Band of Ottawa Indians, Michigan; Little Traverse Bay Bands of Odawa Indians, Michigan; Match-e-be-nash-she-wish Band of Pottawatomi Indians of Michigan; Miami Tribe of Oklahoma; Minnesota Chippewa Tribe, Minnesota (Six component reservations: Bois Forte Band (Nett Lake); Fond du Lac Band; Grand Portage Band; Leech Lake Band; Mille Lacs Band; White Earth Band); Nottawaseppi Huron Band of the Potawatomi, Michigan (previously listed as the Huron Potawatomi, Inc.); Ottawa Tribe of Oklahoma; Peoria Tribe of Indians of Oklahoma; Pokagon Band of Potawatomi Indians, Michigan and Indiana; Prairie Band Potawatomi Nation (previously listed as the Prairie Band of Potawatomi Nation, Kansas); Red Cliff Band of Lake Superior Chippewa Indians of Wisconsin; Red Lake Band of Chippewa Indians, Minnesota; Saginaw Chippewa Indian Tribe of Michigan; Sault Ste. Marie Tribe of Chippewa Indians, Michigan; Shawnee Tribe, Oklahoma; Sokaogon Chippewa Community, Wisconsin; St. Croix Chippewa Indians of Wisconsin; Stockbridge Munsee Community, Wisconsin; Turtle Mountain Band of Chippewa Indians of North Dakota; and Wyandotte Nation (hereinafter referred to as \\xe2\\x80\\x9cThe Tribes\\xe2\\x80\\x9d) \n \\xe2\\x80\\xa2 Pursuant to 43 CFR 10.11(c)(1), the disposition of the human remains may be to The Tribes. \n ", "a_r_d": "Representatives of any Indian Tribe or Native Hawaiian organization not identified in this notice that wish to request transfer of control of these human remains should submit a written request with information in support of the request to Shirley Sorrels, Director, Museum of Ojibwa Culture and Marquette Mission Park, c/o Bernstein & Associates, 1041 N Lafayette Street, Denver, CO 80218, telephone (303) 894-0648, email jan@nagpra.info, by August 13, 2018. After that date, if no additional requestors have come forward, transfer of control of the human remains to The Tribes may proceed. \n The Museum of Ojibwa Culture and Marquette Mission Park, City of St. Ignace is responsible for notifying The Tribes that this notice has been published. \n "}