{"index": "I_303", "messy_full": "\\n      \\n        DEPARTMENT OF THE INTERIOR\\n        National Park Service\\n        [NPS-WASO-NAGPRA-NPS0025295: PPWOCRADN0-PCU00RP14.R50000]\\n        Notice of Inventory Completion: Wisconsin Historical Society, Madison, WI\\n        \\n          AGENCY:\\n          National Park Service, Interior.\\n        \\n        \\n          ACTION:\\n          Notice.\\n        \\n        \\n          SUMMARY:\\n          The Wisconsin Historical Society has completed an inventory of human remains and associated funerary objects, in consultation with the appropriate Indian Tribes or Native Hawaiian organizations, and has determined that there is no cultural affiliation between the human remains and associated funerary objects and any present-day Indian Tribes or Native Hawaiian organizations. Representatives of any Indian Tribe or Native Hawaiian organization not identified in this notice that wish to request transfer of control of these human remains and associated funerary objects should submit a written request to the Wisconsin Historical Society. If no additional requestors come forward, transfer of control of the human remains and associated funerary objects to the Indian Tribes or Native Hawaiian organizations stated in this notice may proceed.\\n        \\n        \\n          DATES:\\n          Representatives of any Indian Tribe or Native Hawaiian organization not identified in this notice that wish to request transfer of control of these human remains and associated funerary objects should submit a written request with information in support of the request to the Wisconsin Historical Society at the address in this notice by May 21, 2018.\\n        \\n        \\n          ADDRESSES:\\n\\n          Jennifer Kolb, Wisconsin Historical Society, 816 State Street, Madison, WI 53706, telephone (608) 264-6434, email Jennifer.Kolb@wisconsinhistory.org.\\n          \\n        \\n      \\n      \\n        SUPPLEMENTARY INFORMATION:\\n        Notice is here given in accordance with the Native American Graves Protection and Repatriation Act (NAGPRA), 25 U.S.C. 3003, of the completion of an inventory of human remains and associated funerary objects under the control of the Wisconsin Historical Society, Madison, WI. The human remains and associated funerary objects were removed from the Pole Barn Site, Waukesha County, WI.\\n        This notice is published as part of the National Park Service\\'s administrative responsibilities under NAGPRA, 25 U.S.C. 3003(d)(3) and 43 CFR 10.11(d). The determinations in this notice are the sole responsibility of the museum, institution, or Federal agency that has control of the Native American human remains and associated funerary objects. The National Park Service is not responsible for the determinations in this notice.\\n        Consultation\\n        A detailed assessment of the human remains was made by the Wisconsin Historical Society professional staff in consultation with representatives of the Forest County Potawatomi Community, Wisconsin; Ho-Chunk Nation of Wisconsin; Lac du Flambeau Band of Lake Superior Chippewa Indians of the Lac du Flambeau Reservation of Wisconsin; Menominee Indian Tribe of Wisconsin; and Upper Sioux Community, Minnesota.\\n        History and Description of the Remains\\n        In 1992, human remains representing, at minimum, five individuals were removed from the Pole Barn Site (47-WK-0471) in Waukesha County, WI. The human remains were disturbed while digging a utility trench under a barn in the town of New Berlin. Diane Holiday along with other Wisconsin Historical Society Burial Sites Preservation Office staff and archeologists from University of Wisconsin-Milwaukee salvaged the remainder of the burial feature. Skeletal analysis conducted in 2014 determined that the human remains represent two adult males, one adult female, one infant, and one child. Six artifacts were discovered stored with the human remains during the 2014 skeletal analysis and were determined to be associated funerary objects because they were labeled as being associated with specific burials. No known individuals were identified. The six associated funerary objects are one antler tine, one group of worked avian bones, one group of unworked avian bones, one projectile point, one lithic flake, and one scrapper fragment.\\n        Determinations Made by the Wisconsin Historical Society\\n        Officials of the Wisconsin Historical Society have determined that:\\n        \\xe2\\x80\\xa2 Pursuant to 25 U.S.C. 3001(9), the human remains described in this notice are Native American based on Wisconsin Historical Society records, burial location, archeological context, oral histories, and skeletal analysis.\\n        \\xe2\\x80\\xa2 Pursuant to 25 U.S.C. 3001(9), the human remains described in this notice represent the physical remains of five individuals of Native American ancestry.\\n        \\xe2\\x80\\xa2 Pursuant to 25 U.S.C. 3001(3)(A), the six objects described in this notice are reasonably believed to have been placed with or near individual human remains at the time of death or later as part of the death rite or ceremony.\\n        \\xe2\\x80\\xa2 Pursuant to 25 U.S.C. 3001(2), a relationship of shared group identity cannot be reasonably traced between the Native American human remains associated funerary objects and any present-day Indian Tribe.\\n\\n        \\xe2\\x80\\xa2 According to final judgments of the Indian Claims Commission or the Court of Federal Claims, the land from which the Native American human remains and associated funerary objects were removed is the aboriginal land of the Citizen Potawatomi Nation, Oklahoma; Forest County Potawatomi Community, Wisconsin; Hannahville Indian Community, Michigan; Match-e-be-nash-she-wish Band of Pottawatomi Indians of Michigan; Nottawaseppi Huron Band of the Potawatomi, Michigan (previously listed as the Huron Potawatomi, Inc.); Pokagon Band of Potawatomi Indians, Michigan and Indiana; and the Prairie Band Potawatomi Nation (previously listed as the Prairie Band of Potawatomi Nation, Kansas) (hereafter referred to as \\xe2\\x80\\x9cThe Adjudicated Aboriginal Land Tribes\\xe2\\x80\\x9d).\\n        \\xe2\\x80\\xa2 Treaties, Acts of Congress, or Executive Orders, indicate that the land from which the Native American human remains and associated funerary objects were removed is the aboriginal land of the Bad River Band of the Lake Superior Tribe of Chippewa Indians of the Bad River Reservation, Wisconsin; Bay Mills Indian Community, Michigan; Chippewa Cree Indians of the Rocky Boy\\'s Reservation, Montana (previously listed as the Chippewa-Cree Indians of the Rocky Boy\\'s Reservation, Montana); Citizen Potawatomi Nation, Oklahoma; Forest County Potawatomi Community, Wisconsin; Grand Traverse Band of Ottawa and Chippewa Indians, Michigan; Hannahville Indian Community, Michigan; Keweenaw Bay Indian Community, Michigan; Lac Courte Oreilles Band of Lake Superior Chippewa Indians of Wisconsin; Lac du Flambeau Band of Lake Superior Chippewa Indians of the Lac du Flambeau Reservation of Wisconsin; Lac Vieux Desert Band of Lake Superior Chippewa Indians of Michigan; Match-e-be-nash-she-wish Band of Pottawatomi Indians of Michigan; Minnesota Chippewa Tribe, Minnesota (Six component reservations: Bois Forte Band (Nett Lake); Fond du Lac Band; Grand Portage Band; Leech Lake Band; Mille Lacs Band; White Earth Band); Nottawaseppi Huron Band of the Potawatomi, Michigan (previously listed as the Huron Potawatomi, Inc.); Ottawa Tribe of Oklahoma; Pokagon Band of Potawatomi Indians, Michigan and Indiana; Prairie Band Potawatomi Nation (previously listed as the Prairie Band of Potawatomi Nation, Kansas); Red Cliff Band of Lake Superior Chippewa Indians of Wisconsin; Red Lake Band of Chippewa Indians, Minnesota; Saginaw Chippewa Indian Tribe of Michigan; Sault Ste. Marie Tribe of Chippewa Indians, Michigan; Sokaogon Chippewa Community, Wisconsin; St. Croix Chippewa Indians of Wisconsin; and the Turtle Mountain Band of Chippewa Indians of North Dakota (hereafter referred to as \\xe2\\x80\\x9cThe Acknowledged Aboriginal Land Tribes\\xe2\\x80\\x9d).\\n        \\xe2\\x80\\xa2 Pursuant to 43 CFR 10.11(c)(1), the disposition of the human remains and associated funerary objects may be to The Adjudicated Aboriginal Land Tribes and The Acknowledged Aboriginal Land Tribes.\\n        Additional Requestors and Disposition\\n\\n        Representatives of any Indian Tribe or Native Hawaiian organization not identified in this notice that wish to request transfer of control of these human remains and associated funerary objects should submit a written request with information in support of the request to Jennifer Kolb, Wisconsin Historical Society, 816 State Street, Madison, WI 53706, telephone (608) 264-6434, email Jennifer.Kolb@wisconsinhistory.org, by May 21, 2018. After that date, if no additional requestors have come forward, transfer of control of the human remains and associated funerary objects to The Aboriginal Land Tribes and The Additional Aboriginal Land Tribes may proceed.\\n        The Wisconsin Historical Society is responsible for notifying The Aboriginal Land Tribes; The Additional Aboriginal Land Tribes; Ho-Chunk Nation of Wisconsin; Menominee Indian Tribe of Wisconsin; and Upper Sioux Community, Minnesota, that this notice has been published.\\n        \\n          Dated: March 22, 2018.\\n          Melanie O\\'Brien,\\n          Manager, National NAGPRA Program.\\n        \\n      \\n      [FR Doc. 2018-08182 Filed 4-18-18; 8:45 am]\\n       BILLING CODE 4312-52-P\\n    ", "agency1": "DEPARTMENT OF THE INTERIOR", "sub_agency1": "National Park Service", "dep_doc": "[NPS-WASO-NAGPRA-NPS0025295: PPWOCRADN0-PCU00RP14.R50000]", "subject": "Notice of Inventory Completion: Wisconsin Historical Society, Madison, WI", "agency2": "National Park Service, Interior.", "action": "Notice.", "summary": "The Wisconsin Historical Society has completed an inventory of human remains and associated funerary objects, in consultation with the appropriate Indian Tribes or Native Hawaiian organizations, and has determined that there is no cultural affiliation between the human remains and associated funerary objects and any present-day Indian Tribes or Native Hawaiian organizations. Representatives of any Indian Tribe or Native Hawaiian organization not identified in this notice that wish to request transfer of control of these human remains and associated funerary objects should submit a written request to the Wisconsin Historical Society. If no additional requestors come forward, transfer of control of the human remains and associated funerary objects to the Indian Tribes or Native Hawaiian organizations stated in this notice may proceed.", "dates": "Representatives of any Indian Tribe or Native Hawaiian organization not identified in this notice that wish to request transfer of control of these human remains and associated funerary objects should submit a written request with information in support of the request to the Wisconsin Historical Society at the address in this notice by May 21, 2018.", "addresses": "Jennifer Kolb, Wisconsin Historical Society, 816 State Street, Madison, WI 53706, telephone (608) 264-6434, email Jennifer.Kolb@wisconsinhistory.org.\\n          ", "signature_dated": "Dated: March 22, 2018.", "signature_name": "Melanie O\\'Brien,", "signature_title": "Manager, National NAGPRA Program.", "fr_doc": "[FR Doc. 2018-08182 Filed 4-18-18; 8:45 am]", "billing_code": " BILLING CODE 4312-52-P", "supp_info": "SUPPLEMENTARY INFORMATION: \n Notice is here given in accordance with the Native American Graves Protection and Repatriation Act (NAGPRA), 25 U.S.C. 3003, of the completion of an inventory of human remains and associated funerary objects under the control of the Wisconsin Historical Society, Madison, WI. The human remains and associated funerary objects were removed from the Pole Barn Site, Waukesha County, WI. \n This notice is published as part of the National Park Service\\'s administrative responsibilities under NAGPRA, 25 U.S.C. 3003(d)(3) and 43 CFR 10.11(d). The determinations in this notice are the sole responsibility of the museum, institution, or Federal agency that has control of the Native American human remains and associated funerary objects. The National Park Service is not responsible for the determinations in this notice. \n Consultation \n A detailed assessment of the human remains was made by the Wisconsin Historical Society professional staff in consultation with representatives of the Forest County Potawatomi Community, Wisconsin; Ho-Chunk Nation of Wisconsin; Lac du Flambeau Band of Lake Superior Chippewa Indians of the Lac du Flambeau Reservation of Wisconsin; Menominee Indian Tribe of Wisconsin; and Upper Sioux Community, Minnesota. \n History and Description of the Remains \n In 1992, human remains representing, at minimum, five individuals were removed from the Pole Barn Site (47-WK-0471) in Waukesha County, WI. The human remains were disturbed while digging a utility trench under a barn in the town of New Berlin. Diane Holiday along with other Wisconsin Historical Society Burial Sites Preservation Office staff and archeologists from University of Wisconsin-Milwaukee salvaged the remainder of the burial feature. Skeletal analysis conducted in 2014 determined that the human remains represent two adult males, one adult female, one infant, and one child. Six artifacts were discovered stored with the human remains during the 2014 skeletal analysis and were determined to be associated funerary objects because they were labeled as being associated with specific burials. No known individuals were identified. The six associated funerary objects are one antler tine, one group of worked avian bones, one group of unworked avian bones, one projectile point, one lithic flake, and one scrapper fragment. \n Determinations Made by the Wisconsin Historical Society \n Officials of the Wisconsin Historical Society have determined that: \n \\xe2\\x80\\xa2 Pursuant to 25 U.S.C. 3001(9), the human remains described in this notice are Native American based on Wisconsin Historical Society records, burial location, archeological context, oral histories, and skeletal analysis. \n \\xe2\\x80\\xa2 Pursuant to 25 U.S.C. 3001(9), the human remains described in this notice represent the physical remains of five individuals of Native American ancestry. \n \\xe2\\x80\\xa2 Pursuant to 25 U.S.C. 3001(3)(A), the six objects described in this notice are reasonably believed to have been placed with or near individual human remains at the time of death or later as part of the death rite or ceremony. \n \\xe2\\x80\\xa2 Pursuant to 25 U.S.C. 3001(2), a relationship of shared group identity cannot be reasonably traced between the Native American human remains associated funerary objects and any present-day Indian Tribe. \n \\xe2\\x80\\xa2 According to final judgments of the Indian Claims Commission or the Court of Federal Claims, the land from which the Native American human remains and associated funerary objects were removed is the aboriginal land of the Citizen Potawatomi Nation, Oklahoma; Forest County Potawatomi Community, Wisconsin; Hannahville Indian Community, Michigan; Match-e-be-nash-she-wish Band of Pottawatomi Indians of Michigan; Nottawaseppi Huron Band of the Potawatomi, Michigan (previously listed as the Huron Potawatomi, Inc.); Pokagon Band of Potawatomi Indians, Michigan and Indiana; and the Prairie Band Potawatomi Nation (previously listed as the Prairie Band of Potawatomi Nation, Kansas) (hereafter referred to as \\xe2\\x80\\x9cThe Adjudicated Aboriginal Land Tribes\\xe2\\x80\\x9d). \n \\xe2\\x80\\xa2 Treaties, Acts of Congress, or Executive Orders, indicate that the land from which the Native American human remains and associated funerary objects were removed is the aboriginal land of the Bad River Band of the Lake Superior Tribe of Chippewa Indians of the Bad River Reservation, Wisconsin; Bay Mills Indian Community, Michigan; Chippewa Cree Indians of the Rocky Boy\\'s Reservation, Montana (previously listed as the Chippewa-Cree Indians of the Rocky Boy\\'s Reservation, Montana); Citizen Potawatomi Nation, Oklahoma; Forest County Potawatomi Community, Wisconsin; Grand Traverse Band of Ottawa and Chippewa Indians, Michigan; Hannahville Indian Community, Michigan; Keweenaw Bay Indian Community, Michigan; Lac Courte Oreilles Band of Lake Superior Chippewa Indians of Wisconsin; Lac du Flambeau Band of Lake Superior Chippewa Indians of the Lac du Flambeau Reservation of Wisconsin; Lac Vieux Desert Band of Lake Superior Chippewa Indians of Michigan; Match-e-be-nash-she-wish Band of Pottawatomi Indians of Michigan; Minnesota Chippewa Tribe, Minnesota (Six component reservations: Bois Forte Band (Nett Lake); Fond du Lac Band; Grand Portage Band; Leech Lake Band; Mille Lacs Band; White Earth Band); Nottawaseppi Huron Band of the Potawatomi, Michigan (previously listed as the Huron Potawatomi, Inc.); Ottawa Tribe of Oklahoma; Pokagon Band of Potawatomi Indians, Michigan and Indiana; Prairie Band Potawatomi Nation (previously listed as the Prairie Band of Potawatomi Nation, Kansas); Red Cliff Band of Lake Superior Chippewa Indians of Wisconsin; Red Lake Band of Chippewa Indians, Minnesota; Saginaw Chippewa Indian Tribe of Michigan; Sault Ste. Marie Tribe of Chippewa Indians, Michigan; Sokaogon Chippewa Community, Wisconsin; St. Croix Chippewa Indians of Wisconsin; and the Turtle Mountain Band of Chippewa Indians of North Dakota (hereafter referred to as \\xe2\\x80\\x9cThe Acknowledged Aboriginal Land Tribes\\xe2\\x80\\x9d). \n \\xe2\\x80\\xa2 Pursuant to 43 CFR 10.11(c)(1), the disposition of the human remains and associated funerary objects may be to The Adjudicated Aboriginal Land Tribes and The Acknowledged Aboriginal Land Tribes. \n Additional Requestors and Disposition \n Representatives of any Indian Tribe or Native Hawaiian organization not identified in this notice that wish to request transfer of control of these human remains and associated funerary objects should submit a written request with information in support of the request to Jennifer Kolb, Wisconsin Historical Society, 816 State Street, Madison, WI 53706, telephone (608) 264-6434, email Jennifer.Kolb@wisconsinhistory.org, by May 21, 2018. After that date, if no additional requestors have come forward, transfer of control of the human remains and associated funerary objects to The Aboriginal Land Tribes and The Additional Aboriginal Land Tribes may proceed. \n The Wisconsin Historical Society is responsible for notifying The Aboriginal Land Tribes; The Additional Aboriginal Land Tribes; Ho-Chunk Nation of Wisconsin; Menominee Indian Tribe of Wisconsin; and Upper Sioux Community, Minnesota, that this notice has been published. \n ", "consultation": "A detailed assessment of the human remains was made by the Wisconsin Historical Society professional staff in consultation with representatives of the Forest County Potawatomi Community, Wisconsin; Ho-Chunk Nation of Wisconsin; Lac du Flambeau Band of Lake Superior Chippewa Indians of the Lac du Flambeau Reservation of Wisconsin; Menominee Indian Tribe of Wisconsin; and Upper Sioux Community, Minnesota. \n ", "h_d_r": "In 1992, human remains representing, at minimum, five individuals were removed from the Pole Barn Site (47-WK-0471) in Waukesha County, WI. The human remains were disturbed while digging a utility trench under a barn in the town of New Berlin. Diane Holiday along with other Wisconsin Historical Society Burial Sites Preservation Office staff and archeologists from University of Wisconsin-Milwaukee salvaged the remainder of the burial feature. Skeletal analysis conducted in 2014 determined that the human remains represent two adult males, one adult female, one infant, and one child. Six artifacts were discovered stored with the human remains during the 2014 skeletal analysis and were determined to be associated funerary objects because they were labeled as being associated with specific burials. No known individuals were identified. The six associated funerary objects are one antler tine, one group of worked avian bones, one group of unworked avian bones, one projectile point, one lithic flake, and one scrapper fragment. \n ", "h_d_ci": "Null", "determinations": "Determinations Made by the Wisconsin Historical Society \n Officials of the Wisconsin Historical Society have determined that: \n \\xe2\\x80\\xa2 Pursuant to 25 U.S.C. 3001(9), the human remains described in this notice are Native American based on Wisconsin Historical Society records, burial location, archeological context, oral histories, and skeletal analysis. \n \\xe2\\x80\\xa2 Pursuant to 25 U.S.C. 3001(9), the human remains described in this notice represent the physical remains of five individuals of Native American ancestry. \n \\xe2\\x80\\xa2 Pursuant to 25 U.S.C. 3001(3)(A), the six objects described in this notice are reasonably believed to have been placed with or near individual human remains at the time of death or later as part of the death rite or ceremony. \n \\xe2\\x80\\xa2 Pursuant to 25 U.S.C. 3001(2), a relationship of shared group identity cannot be reasonably traced between the Native American human remains associated funerary objects and any present-day Indian Tribe. \n \\xe2\\x80\\xa2 According to final judgments of the Indian Claims Commission or the Court of Federal Claims, the land from which the Native American human remains and associated funerary objects were removed is the aboriginal land of the Citizen Potawatomi Nation, Oklahoma; Forest County Potawatomi Community, Wisconsin; Hannahville Indian Community, Michigan; Match-e-be-nash-she-wish Band of Pottawatomi Indians of Michigan; Nottawaseppi Huron Band of the Potawatomi, Michigan (previously listed as the Huron Potawatomi, Inc.); Pokagon Band of Potawatomi Indians, Michigan and Indiana; and the Prairie Band Potawatomi Nation (previously listed as the Prairie Band of Potawatomi Nation, Kansas) (hereafter referred to as \\xe2\\x80\\x9cThe Adjudicated Aboriginal Land Tribes\\xe2\\x80\\x9d). \n \\xe2\\x80\\xa2 Treaties, Acts of Congress, or Executive Orders, indicate that the land from which the Native American human remains and associated funerary objects were removed is the aboriginal land of the Bad River Band of the Lake Superior Tribe of Chippewa Indians of the Bad River Reservation, Wisconsin; Bay Mills Indian Community, Michigan; Chippewa Cree Indians of the Rocky Boy\\'s Reservation, Montana (previously listed as the Chippewa-Cree Indians of the Rocky Boy\\'s Reservation, Montana); Citizen Potawatomi Nation, Oklahoma; Forest County Potawatomi Community, Wisconsin; Grand Traverse Band of Ottawa and Chippewa Indians, Michigan; Hannahville Indian Community, Michigan; Keweenaw Bay Indian Community, Michigan; Lac Courte Oreilles Band of Lake Superior Chippewa Indians of Wisconsin; Lac du Flambeau Band of Lake Superior Chippewa Indians of the Lac du Flambeau Reservation of Wisconsin; Lac Vieux Desert Band of Lake Superior Chippewa Indians of Michigan; Match-e-be-nash-she-wish Band of Pottawatomi Indians of Michigan; Minnesota Chippewa Tribe, Minnesota (Six component reservations: Bois Forte Band (Nett Lake); Fond du Lac Band; Grand Portage Band; Leech Lake Band; Mille Lacs Band; White Earth Band); Nottawaseppi Huron Band of the Potawatomi, Michigan (previously listed as the Huron Potawatomi, Inc.); Ottawa Tribe of Oklahoma; Pokagon Band of Potawatomi Indians, Michigan and Indiana; Prairie Band Potawatomi Nation (previously listed as the Prairie Band of Potawatomi Nation, Kansas); Red Cliff Band of Lake Superior Chippewa Indians of Wisconsin; Red Lake Band of Chippewa Indians, Minnesota; Saginaw Chippewa Indian Tribe of Michigan; Sault Ste. Marie Tribe of Chippewa Indians, Michigan; Sokaogon Chippewa Community, Wisconsin; St. Croix Chippewa Indians of Wisconsin; and the Turtle Mountain Band of Chippewa Indians of North Dakota (hereafter referred to as \\xe2\\x80\\x9cThe Acknowledged Aboriginal Land Tribes\\xe2\\x80\\x9d). \n \\xe2\\x80\\xa2 Pursuant to 43 CFR 10.11(c)(1), the disposition of the human remains and associated funerary objects may be to The Adjudicated Aboriginal Land Tribes and The Acknowledged Aboriginal Land Tribes. \n ", "a_r_d": "Representatives of any Indian Tribe or Native Hawaiian organization not identified in this notice that wish to request transfer of control of these human remains and associated funerary objects should submit a written request with information in support of the request to Jennifer Kolb, Wisconsin Historical Society, 816 State Street, Madison, WI 53706, telephone (608) 264-6434, email Jennifer.Kolb@wisconsinhistory.org, by May 21, 2018. After that date, if no additional requestors have come forward, transfer of control of the human remains and associated funerary objects to The Aboriginal Land Tribes and The Additional Aboriginal Land Tribes may proceed. \n The Wisconsin Historical Society is responsible for notifying The Aboriginal Land Tribes; The Additional Aboriginal Land Tribes; Ho-Chunk Nation of Wisconsin; Menominee Indian Tribe of Wisconsin; and Upper Sioux Community, Minnesota, that this notice has been published. \n "}