{"index": "I_334", "messy_full": "\\n      \\n        DEPARTMENT OF THE INTERIOR\\n        National Park Service\\n        [NPS-WASO-NAGPRA-NPS0024428; PPWOCRADN0-PCU00RP14.R50000]\\n        Notice of Inventory Completion: Arkansas Archeological Survey, Fayetteville, AR\\n        \\n          AGENCY:\\n          National Park Service, Interior.\\n        \\n        \\n          ACTION:\\n          Notice.\\n        \\n        \\n          SUMMARY:\\n          The Arkansas Archeological Survey has completed an inventory of human remains, in consultation with the appropriate Indian Tribes or Native Hawaiian organizations, and has determined that there is a cultural affiliation between the human remains and present-day Indian Tribes or Native Hawaiian organizations. Lineal descendants or representatives of any Indian Tribe or Native Hawaiian organization not identified in this notice that wish to request transfer of control of these human remains should submit a written request to the Arkansas Archeological Survey. If no additional requestors come forward, transfer of control of the human remains to the lineal descendants, Indian Tribes, or Native Hawaiian organizations stated in this notice may proceed.\\n        \\n        \\n          DATES:\\n          Lineal descendants or representatives of any Indian Tribe or Native Hawaiian organization not identified in this notice that wish to request transfer of control of these human remains should submit a written request with information in support of the request to the Arkansas Archeological Survey at the address in this notice by March 1, 2018.\\n        \\n        \\n          ADDRESSES:\\n\\n          Dr. George Sabo, Director, Arkansas Archeological Survey, 2475 North Hatch Avenue, Fayetteville, AR 72704, (479) 575-3556, gsabo@uark.edu.\\n          \\n        \\n      \\n      \\n        SUPPLEMENTARY INFORMATION:\\n        Notice is here given in accordance with the Native American Graves Protection and Repatriation Act (NAGPRA), 25 U.S.C. 3003, of the completion of an inventory of human remains under the control of the Arkansas Archeological Survey, Fayetteville, AR. The human remains were removed from multiple locations in the State of Arkansas.\\n        This notice is published as part of the National Park Service\\'s administrative responsibilities under NAGPRA, 25 U.S.C. 3003(d)(3). The determinations in this notice are the sole responsibility of the museum, institution, or Federal agency that has control of the Native American human remains. The National Park Service is not responsible for the determinations in this notice.\\n        Consultation\\n        A detailed assessment of the human remains was made by the Arkansas Archeological Survey professional staff in consultation with representatives of the Caddo Nation of Oklahoma. The human remains were inventoried and documented by Physical Anthropologists at the University of Arkansas.\\n        History and Description of the Remains\\n        In 1970, human remains representing, at minimum, one individual were recovered from the Weber site (3CL2) in Clark County, AR. No known individual was identified. No associated funerary objects were present. Diagnostic artifacts found at the Weber site indicate that these human remains were probably buried during the Middle Caddo Period (A.D. 1300-1450).\\n        At an unknown date, human remains representing, at minimum, one individual were recovered from the Saline Bayou site (3CL24) in Clark County, AR, and were donated to the Arkansas Archeological Survey in 1974. No known individual was identified. No associated funerary objects were present. Diagnostic artifacts found at the Saline Bayou site indicate that these human remains were probably buried during the Middle Caddo Period (A.D. 1300-1450).\\n\\n        At an unknown date, human remains representing, at minimum, one individual were recovered from the Moore Mound site (3CL56) in Clark County, AR. No known individual was identified. No associated funerary objects were present. Diagnostic artifacts found at the Moore Mound site indicate that these human remains were probably buried during the Middle Caddo Period (A.D. 1300-1450).\\n        At an unknown date, human remains representing, at minimum, one individual were recovered from site 3CL63 in Clark County, AR, and were donated to the Arkansas Archeological Survey in 1973. No known individual was identified. No associated funerary objects were present. Diagnostic artifacts found at site 3CL63 indicate that these human remains were probably buried during the Middle Caddo Period (A.D. 1300-1450).\\n        In 2016, human remains representing, at minimum, one individual were recovered from Hempstead County, AR. The Arkansas State Medical Examiner determined these human remains to be of Native American descent. No known individual was identified. No associated funerary objects were present. Diagnostic artifacts found in Hempstead County indicate that these human remains were probably buried during the Prehistoric Period (11,650 B.C.-A.D. 1541).\\n        In 2014, human remains representing, at minimum, one individual were recovered from the Dragover site (3MN298) in Montgomery County, AR. No known individual was identified. No associated funerary objects were present. Diagnostic artifacts found at the Dragover site indicate that these human remains were probably buried between A.D. 1475-1525.\\n        This notice includes a variety of terms commonly used in discussions of Arkansas archeology and the historical trajectories that gave rise to specific Native American communities identified in the historical record. Based on the archeological context for these sites and what is presently known about the peoples who pre-date the historic Caddo people and occupied the sites listed in this notice, the Arkansas Archeological Survey has determined the human remains listed in this notice are culturally affiliated with the Caddo Nation of Oklahoma.\\n        Determinations Made by the Arkansas Archeological Survey\\n        Officials of the Arkansas Archeological Survey have determined that:\\n        \\xe2\\x80\\xa2 Pursuant to 25 U.S.C. 3001(9), the human remains described in this notice represent the physical remains of 6 individuals of Native American ancestry.\\n        \\xe2\\x80\\xa2 Pursuant to 25 U.S.C. 3001(2), there is a relationship of shared group identity that can be reasonably traced between the Native American human remains and the Caddo Nation of Oklahoma.\\n        Additional Requestors and Disposition\\n\\n        Lineal descendants or representatives of any Indian Tribe or Native Hawaiian organization not identified in this notice that wish to request transfer of control of these human remains should submit a written request with information in support of the request to Dr. George Sabo, Director, Arkansas Archeological Survey, 2475 North Hatch Avenue, Fayetteville, AR 72704, (479) 575-3556, gsabo@uark.edu, by March 1, 2018. After that date, if no additional requestors have come forward, transfer of control of the human remains to the Caddo Nation of Oklahoma may proceed.\\n        The Arkansas Archeological Survey is responsible for notifying the Caddo Nation of Oklahoma that this notice has been published.\\n        \\n          Dated: October 11, 2017.\\n          Melanie O\\'Brien,\\n          Manager, National NAGPRA Program.\\n        \\n        \\n          Editorial Note:\\n          This document was received at the Office of the Federal Register on January 25, 2018.\\n        \\n        \\n      \\n      [FR Doc. 2018-01715 Filed 1-29-18; 8:45 am]\\n       BILLING CODE 4312-52-P\\n    ", "agency1": "DEPARTMENT OF THE INTERIOR", "sub_agency1": "National Park Service", "dep_doc": "[NPS-WASO-NAGPRA-NPS0024428; PPWOCRADN0-PCU00RP14.R50000]", "subject": "Notice of Inventory Completion: Arkansas Archeological Survey, Fayetteville, AR", "agency2": "National Park Service, Interior.", "action": "Notice.", "summary": "The Arkansas Archeological Survey has completed an inventory of human remains, in consultation with the appropriate Indian Tribes or Native Hawaiian organizations, and has determined that there is a cultural affiliation between the human remains and present-day Indian Tribes or Native Hawaiian organizations. Lineal descendants or representatives of any Indian Tribe or Native Hawaiian organization not identified in this notice that wish to request transfer of control of these human remains should submit a written request to the Arkansas Archeological Survey. If no additional requestors come forward, transfer of control of the human remains to the lineal descendants, Indian Tribes, or Native Hawaiian organizations stated in this notice may proceed.", "dates": "Lineal descendants or representatives of any Indian Tribe or Native Hawaiian organization not identified in this notice that wish to request transfer of control of these human remains should submit a written request with information in support of the request to the Arkansas Archeological Survey at the address in this notice by March 1, 2018.", "addresses": "Dr. George Sabo, Director, Arkansas Archeological Survey, 2475 North Hatch Avenue, Fayetteville, AR 72704, (479) 575-3556, gsabo@uark.edu.\\n          ", "signature_dated": "Dated: October 11, 2017.", "signature_name": "Melanie O\\'Brien,", "signature_title": "Manager, National NAGPRA Program.", "fr_doc": "[FR Doc. 2018-01715 Filed 1-29-18; 8:45 am]", "billing_code": " BILLING CODE 4312-52-P", "supp_info": "SUPPLEMENTARY INFORMATION: \n Notice is here given in accordance with the Native American Graves Protection and Repatriation Act (NAGPRA), 25 U.S.C. 3003, of the completion of an inventory of human remains under the control of the Arkansas Archeological Survey, Fayetteville, AR. The human remains were removed from multiple locations in the State of Arkansas. \n This notice is published as part of the National Park Service\\'s administrative responsibilities under NAGPRA, 25 U.S.C. 3003(d)(3). The determinations in this notice are the sole responsibility of the museum, institution, or Federal agency that has control of the Native American human remains. The National Park Service is not responsible for the determinations in this notice. \n Consultation \n A detailed assessment of the human remains was made by the Arkansas Archeological Survey professional staff in consultation with representatives of the Caddo Nation of Oklahoma. The human remains were inventoried and documented by Physical Anthropologists at the University of Arkansas. \n History and Description of the Remains \n In 1970, human remains representing, at minimum, one individual were recovered from the Weber site (3CL2) in Clark County, AR. No known individual was identified. No associated funerary objects were present. Diagnostic artifacts found at the Weber site indicate that these human remains were probably buried during the Middle Caddo Period (A.D. 1300-1450). \n At an unknown date, human remains representing, at minimum, one individual were recovered from the Saline Bayou site (3CL24) in Clark County, AR, and were donated to the Arkansas Archeological Survey in 1974. No known individual was identified. No associated funerary objects were present. Diagnostic artifacts found at the Saline Bayou site indicate that these human remains were probably buried during the Middle Caddo Period (A.D. 1300-1450). \n At an unknown date, human remains representing, at minimum, one individual were recovered from the Moore Mound site (3CL56) in Clark County, AR. No known individual was identified. No associated funerary objects were present. Diagnostic artifacts found at the Moore Mound site indicate that these human remains were probably buried during the Middle Caddo Period (A.D. 1300-1450). \n At an unknown date, human remains representing, at minimum, one individual were recovered from site 3CL63 in Clark County, AR, and were donated to the Arkansas Archeological Survey in 1973. No known individual was identified. No associated funerary objects were present. Diagnostic artifacts found at site 3CL63 indicate that these human remains were probably buried during the Middle Caddo Period (A.D. 1300-1450). \n In 2016, human remains representing, at minimum, one individual were recovered from Hempstead County, AR. The Arkansas State Medical Examiner determined these human remains to be of Native American descent. No known individual was identified. No associated funerary objects were present. Diagnostic artifacts found in Hempstead County indicate that these human remains were probably buried during the Prehistoric Period (11,650 B.C.-A.D. 1541). \n In 2014, human remains representing, at minimum, one individual were recovered from the Dragover site (3MN298) in Montgomery County, AR. No known individual was identified. No associated funerary objects were present. Diagnostic artifacts found at the Dragover site indicate that these human remains were probably buried between A.D. 1475-1525. \n This notice includes a variety of terms commonly used in discussions of Arkansas archeology and the historical trajectories that gave rise to specific Native American communities identified in the historical record. Based on the archeological context for these sites and what is presently known about the peoples who pre-date the historic Caddo people and occupied the sites listed in this notice, the Arkansas Archeological Survey has determined the human remains listed in this notice are culturally affiliated with the Caddo Nation of Oklahoma. \n Determinations Made by the Arkansas Archeological Survey \n Officials of the Arkansas Archeological Survey have determined that: \n \\xe2\\x80\\xa2 Pursuant to 25 U.S.C. 3001(9), the human remains described in this notice represent the physical remains of 6 individuals of Native American ancestry. \n \\xe2\\x80\\xa2 Pursuant to 25 U.S.C. 3001(2), there is a relationship of shared group identity that can be reasonably traced between the Native American human remains and the Caddo Nation of Oklahoma. \n Additional Requestors and Disposition \n Lineal descendants or representatives of any Indian Tribe or Native Hawaiian organization not identified in this notice that wish to request transfer of control of these human remains should submit a written request with information in support of the request to Dr. George Sabo, Director, Arkansas Archeological Survey, 2475 North Hatch Avenue, Fayetteville, AR 72704, (479) 575-3556, gsabo@uark.edu, by March 1, 2018. After that date, if no additional requestors have come forward, transfer of control of the human remains to the Caddo Nation of Oklahoma may proceed. \n The Arkansas Archeological Survey is responsible for notifying the Caddo Nation of Oklahoma that this notice has been published. \n ", "consultation": "A detailed assessment of the human remains was made by the Arkansas Archeological Survey professional staff in consultation with representatives of the Caddo Nation of Oklahoma. The human remains were inventoried and documented by Physical Anthropologists at the University of Arkansas. \n ", "h_d_r": "In 1970, human remains representing, at minimum, one individual were recovered from the Weber site (3CL2) in Clark County, AR. No known individual was identified. No associated funerary objects were present. Diagnostic artifacts found at the Weber site indicate that these human remains were probably buried during the Middle Caddo Period (A.D. 1300-1450). \n At an unknown date, human remains representing, at minimum, one individual were recovered from the Saline Bayou site (3CL24) in Clark County, AR, and were donated to the Arkansas Archeological Survey in 1974. No known individual was identified. No associated funerary objects were present. Diagnostic artifacts found at the Saline Bayou site indicate that these human remains were probably buried during the Middle Caddo Period (A.D. 1300-1450). \n At an unknown date, human remains representing, at minimum, one individual were recovered from the Moore Mound site (3CL56) in Clark County, AR. No known individual was identified. No associated funerary objects were present. Diagnostic artifacts found at the Moore Mound site indicate that these human remains were probably buried during the Middle Caddo Period (A.D. 1300-1450). \n At an unknown date, human remains representing, at minimum, one individual were recovered from site 3CL63 in Clark County, AR, and were donated to the Arkansas Archeological Survey in 1973. No known individual was identified. No associated funerary objects were present. Diagnostic artifacts found at site 3CL63 indicate that these human remains were probably buried during the Middle Caddo Period (A.D. 1300-1450). \n In 2016, human remains representing, at minimum, one individual were recovered from Hempstead County, AR. The Arkansas State Medical Examiner determined these human remains to be of Native American descent. No known individual was identified. No associated funerary objects were present. Diagnostic artifacts found in Hempstead County indicate that these human remains were probably buried during the Prehistoric Period (11,650 B.C.-A.D. 1541). \n In 2014, human remains representing, at minimum, one individual were recovered from the Dragover site (3MN298) in Montgomery County, AR. No known individual was identified. No associated funerary objects were present. Diagnostic artifacts found at the Dragover site indicate that these human remains were probably buried between A.D. 1475-1525. \n This notice includes a variety of terms commonly used in discussions of Arkansas archeology and the historical trajectories that gave rise to specific Native American communities identified in the historical record. Based on the archeological context for these sites and what is presently known about the peoples who pre-date the historic Caddo people and occupied the sites listed in this notice, the Arkansas Archeological Survey has determined the human remains listed in this notice are culturally affiliated with the Caddo Nation of Oklahoma. \n ", "h_d_ci": "Null", "determinations": "Determinations Made by the Arkansas Archeological Survey \n Officials of the Arkansas Archeological Survey have determined that: \n \\xe2\\x80\\xa2 Pursuant to 25 U.S.C. 3001(9), the human remains described in this notice represent the physical remains of 6 individuals of Native American ancestry. \n \\xe2\\x80\\xa2 Pursuant to 25 U.S.C. 3001(2), there is a relationship of shared group identity that can be reasonably traced between the Native American human remains and the Caddo Nation of Oklahoma. \n ", "a_r_d": "Lineal descendants or representatives of any Indian Tribe or Native Hawaiian organization not identified in this notice that wish to request transfer of control of these human remains should submit a written request with information in support of the request to Dr. George Sabo, Director, Arkansas Archeological Survey, 2475 North Hatch Avenue, Fayetteville, AR 72704, (479) 575-3556, gsabo@uark.edu, by March 1, 2018. After that date, if no additional requestors have come forward, transfer of control of the human remains to the Caddo Nation of Oklahoma may proceed. \n The Arkansas Archeological Survey is responsible for notifying the Caddo Nation of Oklahoma that this notice has been published. \n "}