{"index": "I_332", "messy_full": "\\n      \\n        DEPARTMENT OF THE INTERIOR\\n        National Park Service\\n        [NPS-WASO-NAGPRA-NPS0024341; PPWOCRADNO-PCU00RP14.R50000]\\n        Notice of Inventory Completion: Arkansas Archeological Survey, Fayetteville, AR; Correction\\n        \\n          AGENCY:\\n          National Park Service, Interior.\\n        \\n        \\n          ACTION:\\n          Notice; correction.\\n        \\n        \\n          SUMMARY:\\n\\n          The Arkansas Archeological Survey has corrected an inventory of human remains and associated funerary objects, published in a Notice of Inventory Completion in the Federal Register on December 22, 2014. This notice corrects the number of associated funerary objects listed in that notice. Lineal descendants or representatives of any Indian Tribe or Native Hawaiian organization not identified in this notice that wish to request transfer of control of these associated funerary objects should submit a written request to the Arkansas Archeological Survey. If no additional requestors come forward, transfer of control of associated funerary objects to the lineal descendants, Indian Tribes, or Native Hawaiian organizations stated in this notice may proceed.\\n        \\n        \\n          DATES:\\n          Lineal descendants or representatives of any Indian Tribe or Native Hawaiian organization not identified in this notice that wish to request transfer of control of these associated funerary objects should submit a written request with information in support of the request to the Arkansas Archeological Survey at the address in this notice by March 1, 2018.\\n        \\n        \\n          ADDRESSES:\\n          George Sabo, Director, Arkansas Archeological Survey, 2475 North Hatch Avenue, Fayetteville, AR 72704, telephone (479) 575-3556.\\n        \\n      \\n      \\n        SUPPLEMENTARY INFORMATION:\\n        Notice is here given in accordance with the Native American Graves Protection and Repatriation Act (NAGPRA), 25 U.S.C. 3003, of the correction of an inventory of human remains and associated funerary objects under the control of the Arkansas Archeological Survey. The human remains and associated funerary objects were removed from multiple counties in the State of Arkansas.\\n        This notice is published as part of the National Park Service\\'s administrative responsibilities under NAGPRA, 25 U.S.C. 3003(d)(3). The determinations in this notice are the sole responsibility of the museum, institution, or Federal Agency that has control of the Native American human remains and associated funerary objects. The National Park Service is not responsible for the determinations in this notice.\\n\\n        This notice corrects the number of associated funerary objects published in Notice of Inventory Completion in the Federal Register (79 FR 76351-76361, December 22, 2014). An additional funerary object was recently identified among the collections. To date, transfer of control of the associated funerary objects has not occurred.\\n        Correction\\n        In the Federal Register (79 FR 76354, December 22, 2014), column 2, paragraph 1, sentence 3, under the heading \\xe2\\x80\\x9cHistory and Description of the Remains,\\xe2\\x80\\x9d is corrected by substituting the following sentence:\\n        The one associated funerary object is a partially reconstructed Mississippi Plain jar.\\n        In the Federal Register (79 FR 76355, December 22, 2014), column 1, paragraph 5, under the heading \\xe2\\x80\\x9cHistory and Description of the Remains,\\xe2\\x80\\x9d is corrected by adding the following sentence:\\n        No associated funerary objects are present.\\n        In the Federal Register (79 FR 76361, December 22, 2014), column 3, paragraph 3, under the heading \\xe2\\x80\\x9cDeterminations made by the Arkansas Archeological Survey,\\xe2\\x80\\x9d is corrected by substituting the number \\xe2\\x80\\x9c274\\xe2\\x80\\x9d with the number \\xe2\\x80\\x9c275\\xe2\\x80\\x9d.\\n        Additional Requestors and Disposition\\n\\n        Lineal descendants or representatives of any Indian Tribe or Native Hawaiian organization not identified in this notice that wish to request transfer of control of these associated funerary objects should submit a written request with information in support of the request to George Sabo, Director, Arkansas Archeological Survey, 2475 North Hatch Avenue, Fayetteville, AR 72704, telephone (479) 575-3556, by March 1, 2018. After that date, if no additional requestors have come forward, transfer of control of the associated funerary objects to the Quapaw Tribe of Indians may proceed.\\n        The Arkansas Archeological Survey is responsible for notifying the Quapaw Tribe of Indians that this notice has been published.\\n        \\n          Dated: October 3, 2017.\\n          Melanie O\\'Brien,\\n          Manager, National NAGPRA Program. \\n        \\n        \\n          Editorial Note:\\n          This document was received at the Office of the Federal Register on January 25, 2018.\\n        \\n      \\n      [FR Doc. 2018-01719 Filed 1-29-18; 8:45 am]\\n       BILLING CODE 4312-52-P\\n    ", "agency1": "DEPARTMENT OF THE INTERIOR", "sub_agency1": "National Park Service", "dep_doc": "[NPS-WASO-NAGPRA-NPS0024341; PPWOCRADNO-PCU00RP14.R50000]", "subject": "Notice of Inventory Completion: Arkansas Archeological Survey, Fayetteville, AR; Correction", "agency2": "National Park Service, Interior.", "action": "Notice; correction.", "summary": "The Arkansas Archeological Survey has corrected an inventory of human remains and associated funerary objects, published in a Notice of Inventory Completion in the Federal Register on December 22, 2014. This notice corrects the number of associated funerary objects listed in that notice. Lineal descendants or representatives of any Indian Tribe or Native Hawaiian organization not identified in this notice that wish to request transfer of control of these associated funerary objects should submit a written request to the Arkansas Archeological Survey. If no additional requestors come forward, transfer of control of associated funerary objects to the lineal descendants, Indian Tribes, or Native Hawaiian organizations stated in this notice may proceed.", "dates": "Lineal descendants or representatives of any Indian Tribe or Native Hawaiian organization not identified in this notice that wish to request transfer of control of these associated funerary objects should submit a written request with information in support of the request to the Arkansas Archeological Survey at the address in this notice by March 1, 2018.", "addresses": "George Sabo, Director, Arkansas Archeological Survey, 2475 North Hatch Avenue, Fayetteville, AR 72704, telephone (479) 575-3556.", "signature_dated": "Dated: October 3, 2017.", "signature_name": "Melanie O\\'Brien,", "signature_title": "Manager, National NAGPRA Program. ", "fr_doc": "[FR Doc. 2018-01719 Filed 1-29-18; 8:45 am]", "billing_code": " BILLING CODE 4312-52-P", "supp_info": "SUPPLEMENTARY INFORMATION: \n Notice is here given in accordance with the Native American Graves Protection and Repatriation Act (NAGPRA), 25 U.S.C. 3003, of the correction of an inventory of human remains and associated funerary objects under the control of the Arkansas Archeological Survey. The human remains and associated funerary objects were removed from multiple counties in the State of Arkansas. \n This notice is published as part of the National Park Service\\'s administrative responsibilities under NAGPRA, 25 U.S.C. 3003(d)(3). The determinations in this notice are the sole responsibility of the museum, institution, or Federal Agency that has control of the Native American human remains and associated funerary objects. The National Park Service is not responsible for the determinations in this notice. \n This notice corrects the number of associated funerary objects published in Notice of Inventory Completion in the Federal Register (79 FR 76351-76361, December 22, 2014). An additional funerary object was recently identified among the collections. To date, transfer of control of the associated funerary objects has not occurred. \n Correction \n In the Federal Register (79 FR 76354, December 22, 2014), column 2, paragraph 1, sentence 3, under the heading \\xe2\\x80\\x9cHistory and Description of the Remains,\\xe2\\x80\\x9d is corrected by substituting the following sentence: \n The one associated funerary object is a partially reconstructed Mississippi Plain jar. \n In the Federal Register (79 FR 76355, December 22, 2014), column 1, paragraph 5, under the heading \\xe2\\x80\\x9cHistory and Description of the Remains,\\xe2\\x80\\x9d is corrected by adding the following sentence: \n No associated funerary objects are present. \n In the Federal Register (79 FR 76361, December 22, 2014), column 3, paragraph 3, under the heading \\xe2\\x80\\x9cDeterminations made by the Arkansas Archeological Survey,\\xe2\\x80\\x9d is corrected by substituting the number \\xe2\\x80\\x9c274\\xe2\\x80\\x9d with the number \\xe2\\x80\\x9c275\\xe2\\x80\\x9d. \n Additional Requestors and Disposition \n Lineal descendants or representatives of any Indian Tribe or Native Hawaiian organization not identified in this notice that wish to request transfer of control of these associated funerary objects should submit a written request with information in support of the request to George Sabo, Director, Arkansas Archeological Survey, 2475 North Hatch Avenue, Fayetteville, AR 72704, telephone (479) 575-3556, by March 1, 2018. After that date, if no additional requestors have come forward, transfer of control of the associated funerary objects to the Quapaw Tribe of Indians may proceed. \n The Arkansas Archeological Survey is responsible for notifying the Quapaw Tribe of Indians that this notice has been published. \n ", "consultation": "Null", "h_d_r": "Null", "h_d_ci": "Null", "determinations": "Null", "a_r_d": "Lineal descendants or representatives of any Indian Tribe or Native Hawaiian organization not identified in this notice that wish to request transfer of control of these associated funerary objects should submit a written request with information in support of the request to George Sabo, Director, Arkansas Archeological Survey, 2475 North Hatch Avenue, Fayetteville, AR 72704, telephone (479) 575-3556, by March 1, 2018. After that date, if no additional requestors have come forward, transfer of control of the associated funerary objects to the Quapaw Tribe of Indians may proceed. \n The Arkansas Archeological Survey is responsible for notifying the Quapaw Tribe of Indians that this notice has been published. \n "}