{"index": "I_359", "messy_full": "\\n      \\n        \\n        DEPARTMENT OF THE INTERIOR\\n        National Park Service\\n        [NPS-WASO-NAGPRA-NPS0024105; PPWOCRADN0-PCU00RP14.R50000]\\n        Notice of Inventory Completion: Wisconsin Historical Society, Madison, WI\\n        \\n          AGENCY:\\n          National Park Service, Interior.\\n        \\n        \\n          ACTION:\\n          Notice.\\n        \\n        \\n          SUMMARY:\\n          The Wisconsin Historical Society has completed an inventory of human remains, in consultation with the appropriate Indian Tribes or Native Hawaiian organizations, and has determined that there is no cultural affiliation between the human remains and any present-day Indian Tribes or Native Hawaiian organizations. Representatives of any Indian Tribe or Native Hawaiian organization not identified in this notice that wish to request transfer of control of these human remains should submit a written request to the Wisconsin Historical Society. If no additional requestors come forward, transfer of control of the human remains to the Indian Tribes or Native Hawaiian organizations stated in this notice may proceed.\\n        \\n        \\n          DATES:\\n          Representatives of any Indian Tribe or Native Hawaiian organization not identified in this notice that wish to request transfer of control of these human remains should submit a written request with information in support of the request to the Wisconsin Historical Society at the address in this notice by November 16, 2017.\\n        \\n        \\n          ADDRESSES:\\n\\n          Jennifer Kolb, Wisconsin Historical Society, 816 State St., Madison, WI 53706, telephone (608) 264-6434, email Jennifer.Kolb@wisconsinhistory.org.\\n          \\n        \\n      \\n      \\n        SUPPLEMENTARY INFORMATION:\\n        Notice is here given in accordance with the Native American Graves Protection and Repatriation Act (NAGPRA), 25 U.S.C. 3003, of the completion of an inventory of human remains under the control of the Wisconsin Historical Society, Madison, WI. The human remains were removed from the Sikora Burial Site and an unknown location near Antigo in Langlade County, WI.\\n        This notice is published as part of the National Park Service\\'s administrative responsibilities under NAGPRA, 25 U.S.C. 3003(d)(3) and 43 CFR 10.11(d). The determinations in this notice are the sole responsibility of the museum, institution, or Federal agency that has control of the Native American human remains. The National Park Service is not responsible for the determinations in this notice.\\n        Consultation\\n        A detailed assessment of the human remains was made by the Wisconsin Historical Society professional staff in consultation with representatives of the Forest County Potawatomi Community, Wisconsin; Ho-Chunk Nation of Wisconsin; Lac du Flambeau Band of Lake Superior Chippewa Indians of the Lac du Flambeau Reservation of Wisconsin; Menominee Indian Tribe of Wisconsin; and the Upper Sioux Community, Minnesota.\\n        History and Description of the Remains\\n        In August of 1991, human remains representing, at minimum, one individual were removed from the Sikora Burial Site (47-LG-0115) in Langlade County, WI. The human remains of one adult male were found during basement construction for a cottage on the southern shore of Rolling Stone Lake in the Township of Ainsworth. No associated funerary objects were recovered. The homeowners contacted the Antigo Police Department the same day as the discovery, and the police subsequently contacted the Wisconsin Burial Site Preservation Office. No known individuals were identified. No associated funerary objects are present.\\n        At an unknown date, human remains representing, at minimum, five individuals were removed from an unknown location near Antigo in Langlade County, WI. It is not known who removed the human remains, who donated them to the Wisconsin Historical Society, or when they were donated. In 1996, the human remains were discovered in a box labeled \\xe2\\x80\\x9cunaccessioned calvarium and representative parts of three mandibles, mound near Antigo, Langlade Co., Wisconsin.\\xe2\\x80\\x9d They were later determined to represent two adults, two children, and a young adult. No known individuals were identified. No associated funerary objects are present.\\n        Determinations Made by the Wisconsin Historical Society\\n        Officials of the Wisconsin Historical Society have determined that:\\n        \\xe2\\x80\\xa2 Pursuant to 25 U.S.C. 3001(9), the human remains described in this notice are Native American based on Wisconsin Historical Society records, burial location, archeological context, oral histories, and skeletal analysis.\\n        \\xe2\\x80\\xa2 Pursuant to 25 U.S.C. 3001(9), the human remains described in this notice represent the physical remains of six individuals of Native American ancestry.\\n        \\xe2\\x80\\xa2 Pursuant to 25 U.S.C. 3001(2), a relationship of shared group identity cannot be reasonably traced between the Native American human remains and any present-day Indian Tribe.\\n        \\xe2\\x80\\xa2 Treaties, Acts of Congress, or Executive Orders indicate that the land from which the Native American human remains were removed is the aboriginal land of the Bad River Band of the Lake Superior Tribe of Chippewa Indians of the Bad River Reservation, Wisconsin; Bay Mills Indian Community, Michigan; Bois Forte Band (Nett Lake) of the Minnesota Chippewa Tribe, Minnesota; Chippewa Cree Indians of the Rocky Boy\\'s Reservation, Montana; Fond du Lac Band of the Minnesota Chippewa Tribe, Minnesota; Grand Portage Band of the Minnesota Chippewa Tribe, Minnesota; Grand Traverse Band of Ottawa and Chippewa Indians, Michigan; Lac Courte Oreilles Band of Lake Superior Chippewa Indians of Wisconsin; Lac du Flambeau Band of Lake Superior Chippewa Indians of the Lac du Flambeau Reservation of Wisconsin; Lac Vieux Desert Band of Lake Superior Chippewa Indians of Michigan; Leech Lake Band of the Minnesota Chippewa Tribe, Minnesota; Mille Lacs Band of the Minnesota Chippewa Tribe, Minnesota; Minnesota Chippewa Tribe, Minnesota; Red Cliff Band of Lake Superior Chippewa Indians of Wisconsin; Red Lake Band of Chippewa Indians, Minnesota; Saginaw Chippewa Indian Tribe of Michigan; Sault Ste. Marie Tribe of Chippewa Indians, Michigan; Sokaogon Chippewa Community, Wisconsin; St. Croix Chippewa Indians of Wisconsin; Turtle Mountain Band of Chippewa Indians of North Dakota; and the White Earth Band of Minnesota Chippewa Tribe, Minnesota (hereafter referred to as The Aboriginal Land Tribes).\\n        \\xe2\\x80\\xa2 Pursuant to 43 CFR 10.11(c)(1), the disposition of the human remains may be to The Aboriginal Land Tribes.\\n        Additional Requestors and Disposition\\n\\n        Representatives of any Indian Tribe or Native Hawaiian organization not identified in this notice that wish to request transfer of control of these human remains should submit a written request with information in support of the request to Jennifer Kolb, Wisconsin Historical Society, 816 State St, Madison, WI 53706, telephone (608) 264-6434, email Jennifer.Kolb@wisconsinhistory.org, by November 16, 2017. After that date, if no additional requestors have come forward, transfer of control of the human remains to The Aboriginal Land Tribes may proceed.\\n\\n        The Wisconsin Historical Society is responsible for notifying The Aboriginal Land Tribes and the Forest County Potawatomi Community, Wisconsin; Ho-Chunk Nation of Wisconsin; and the Menominee Indian Tribe of Wisconsin that this notice has been published.\\n        \\n          Dated: September 5, 2017.\\n          Melanie O\\'Brien,\\n          Manager, National NAGPRA Program.\\n        \\n      \\n      [FR Doc. 2017-22428 Filed 10-16-17; 8:45 am]\\n       BILLING CODE 4312-52-P\\n    ", "agency1": "DEPARTMENT OF THE INTERIOR", "sub_agency1": "National Park Service", "dep_doc": "[NPS-WASO-NAGPRA-NPS0024105; PPWOCRADN0-PCU00RP14.R50000]", "subject": "Notice of Inventory Completion: Wisconsin Historical Society, Madison, WI", "agency2": "National Park Service, Interior.", "action": "Notice.", "summary": "The Wisconsin Historical Society has completed an inventory of human remains, in consultation with the appropriate Indian Tribes or Native Hawaiian organizations, and has determined that there is no cultural affiliation between the human remains and any present-day Indian Tribes or Native Hawaiian organizations. Representatives of any Indian Tribe or Native Hawaiian organization not identified in this notice that wish to request transfer of control of these human remains should submit a written request to the Wisconsin Historical Society. If no additional requestors come forward, transfer of control of the human remains to the Indian Tribes or Native Hawaiian organizations stated in this notice may proceed.", "dates": "Representatives of any Indian Tribe or Native Hawaiian organization not identified in this notice that wish to request transfer of control of these human remains should submit a written request with information in support of the request to the Wisconsin Historical Society at the address in this notice by November 16, 2017.", "addresses": "Jennifer Kolb, Wisconsin Historical Society, 816 State St., Madison, WI 53706, telephone (608) 264-6434, email Jennifer.Kolb@wisconsinhistory.org.\\n          ", "signature_dated": "Dated: September 5, 2017.", "signature_name": "Melanie O\\'Brien,", "signature_title": "Manager, National NAGPRA Program.", "fr_doc": "[FR Doc. 2017-22428 Filed 10-16-17; 8:45 am]", "billing_code": " BILLING CODE 4312-52-P", "supp_info": "SUPPLEMENTARY INFORMATION: \n Notice is here given in accordance with the Native American Graves Protection and Repatriation Act (NAGPRA), 25 U.S.C. 3003, of the completion of an inventory of human remains under the control of the Wisconsin Historical Society, Madison, WI. The human remains were removed from the Sikora Burial Site and an unknown location near Antigo in Langlade County, WI. \n This notice is published as part of the National Park Service\\'s administrative responsibilities under NAGPRA, 25 U.S.C. 3003(d)(3) and 43 CFR 10.11(d). The determinations in this notice are the sole responsibility of the museum, institution, or Federal agency that has control of the Native American human remains. The National Park Service is not responsible for the determinations in this notice. \n Consultation \n A detailed assessment of the human remains was made by the Wisconsin Historical Society professional staff in consultation with representatives of the Forest County Potawatomi Community, Wisconsin; Ho-Chunk Nation of Wisconsin; Lac du Flambeau Band of Lake Superior Chippewa Indians of the Lac du Flambeau Reservation of Wisconsin; Menominee Indian Tribe of Wisconsin; and the Upper Sioux Community, Minnesota. \n History and Description of the Remains \n In August of 1991, human remains representing, at minimum, one individual were removed from the Sikora Burial Site (47-LG-0115) in Langlade County, WI. The human remains of one adult male were found during basement construction for a cottage on the southern shore of Rolling Stone Lake in the Township of Ainsworth. No associated funerary objects were recovered. The homeowners contacted the Antigo Police Department the same day as the discovery, and the police subsequently contacted the Wisconsin Burial Site Preservation Office. No known individuals were identified. No associated funerary objects are present. \n At an unknown date, human remains representing, at minimum, five individuals were removed from an unknown location near Antigo in Langlade County, WI. It is not known who removed the human remains, who donated them to the Wisconsin Historical Society, or when they were donated. In 1996, the human remains were discovered in a box labeled \\xe2\\x80\\x9cunaccessioned calvarium and representative parts of three mandibles, mound near Antigo, Langlade Co., Wisconsin.\\xe2\\x80\\x9d They were later determined to represent two adults, two children, and a young adult. No known individuals were identified. No associated funerary objects are present. \n Determinations Made by the Wisconsin Historical Society \n Officials of the Wisconsin Historical Society have determined that: \n \\xe2\\x80\\xa2 Pursuant to 25 U.S.C. 3001(9), the human remains described in this notice are Native American based on Wisconsin Historical Society records, burial location, archeological context, oral histories, and skeletal analysis. \n \\xe2\\x80\\xa2 Pursuant to 25 U.S.C. 3001(9), the human remains described in this notice represent the physical remains of six individuals of Native American ancestry. \n \\xe2\\x80\\xa2 Pursuant to 25 U.S.C. 3001(2), a relationship of shared group identity cannot be reasonably traced between the Native American human remains and any present-day Indian Tribe. \n \\xe2\\x80\\xa2 Treaties, Acts of Congress, or Executive Orders indicate that the land from which the Native American human remains were removed is the aboriginal land of the Bad River Band of the Lake Superior Tribe of Chippewa Indians of the Bad River Reservation, Wisconsin; Bay Mills Indian Community, Michigan; Bois Forte Band (Nett Lake) of the Minnesota Chippewa Tribe, Minnesota; Chippewa Cree Indians of the Rocky Boy\\'s Reservation, Montana; Fond du Lac Band of the Minnesota Chippewa Tribe, Minnesota; Grand Portage Band of the Minnesota Chippewa Tribe, Minnesota; Grand Traverse Band of Ottawa and Chippewa Indians, Michigan; Lac Courte Oreilles Band of Lake Superior Chippewa Indians of Wisconsin; Lac du Flambeau Band of Lake Superior Chippewa Indians of the Lac du Flambeau Reservation of Wisconsin; Lac Vieux Desert Band of Lake Superior Chippewa Indians of Michigan; Leech Lake Band of the Minnesota Chippewa Tribe, Minnesota; Mille Lacs Band of the Minnesota Chippewa Tribe, Minnesota; Minnesota Chippewa Tribe, Minnesota; Red Cliff Band of Lake Superior Chippewa Indians of Wisconsin; Red Lake Band of Chippewa Indians, Minnesota; Saginaw Chippewa Indian Tribe of Michigan; Sault Ste. Marie Tribe of Chippewa Indians, Michigan; Sokaogon Chippewa Community, Wisconsin; St. Croix Chippewa Indians of Wisconsin; Turtle Mountain Band of Chippewa Indians of North Dakota; and the White Earth Band of Minnesota Chippewa Tribe, Minnesota (hereafter referred to as The Aboriginal Land Tribes). \n \\xe2\\x80\\xa2 Pursuant to 43 CFR 10.11(c)(1), the disposition of the human remains may be to The Aboriginal Land Tribes. \n Additional Requestors and Disposition \n Representatives of any Indian Tribe or Native Hawaiian organization not identified in this notice that wish to request transfer of control of these human remains should submit a written request with information in support of the request to Jennifer Kolb, Wisconsin Historical Society, 816 State St, Madison, WI 53706, telephone (608) 264-6434, email Jennifer.Kolb@wisconsinhistory.org, by November 16, 2017. After that date, if no additional requestors have come forward, transfer of control of the human remains to The Aboriginal Land Tribes may proceed. \n The Wisconsin Historical Society is responsible for notifying The Aboriginal Land Tribes and the Forest County Potawatomi Community, Wisconsin; Ho-Chunk Nation of Wisconsin; and the Menominee Indian Tribe of Wisconsin that this notice has been published. \n ", "consultation": "A detailed assessment of the human remains was made by the Wisconsin Historical Society professional staff in consultation with representatives of the Forest County Potawatomi Community, Wisconsin; Ho-Chunk Nation of Wisconsin; Lac du Flambeau Band of Lake Superior Chippewa Indians of the Lac du Flambeau Reservation of Wisconsin; Menominee Indian Tribe of Wisconsin; and the Upper Sioux Community, Minnesota. \n ", "h_d_r": "In August of 1991, human remains representing, at minimum, one individual were removed from the Sikora Burial Site (47-LG-0115) in Langlade County, WI. The human remains of one adult male were found during basement construction for a cottage on the southern shore of Rolling Stone Lake in the Township of Ainsworth. No associated funerary objects were recovered. The homeowners contacted the Antigo Police Department the same day as the discovery, and the police subsequently contacted the Wisconsin Burial Site Preservation Office. No known individuals were identified. No associated funerary objects are present. \n At an unknown date, human remains representing, at minimum, five individuals were removed from an unknown location near Antigo in Langlade County, WI. It is not known who removed the human remains, who donated them to the Wisconsin Historical Society, or when they were donated. In 1996, the human remains were discovered in a box labeled \\xe2\\x80\\x9cunaccessioned calvarium and representative parts of three mandibles, mound near Antigo, Langlade Co., Wisconsin.\\xe2\\x80\\x9d They were later determined to represent two adults, two children, and a young adult. No known individuals were identified. No associated funerary objects are present. \n ", "h_d_ci": "Null", "determinations": "Determinations Made by the Wisconsin Historical Society \n Officials of the Wisconsin Historical Society have determined that: \n \\xe2\\x80\\xa2 Pursuant to 25 U.S.C. 3001(9), the human remains described in this notice are Native American based on Wisconsin Historical Society records, burial location, archeological context, oral histories, and skeletal analysis. \n \\xe2\\x80\\xa2 Pursuant to 25 U.S.C. 3001(9), the human remains described in this notice represent the physical remains of six individuals of Native American ancestry. \n \\xe2\\x80\\xa2 Pursuant to 25 U.S.C. 3001(2), a relationship of shared group identity cannot be reasonably traced between the Native American human remains and any present-day Indian Tribe. \n \\xe2\\x80\\xa2 Treaties, Acts of Congress, or Executive Orders indicate that the land from which the Native American human remains were removed is the aboriginal land of the Bad River Band of the Lake Superior Tribe of Chippewa Indians of the Bad River Reservation, Wisconsin; Bay Mills Indian Community, Michigan; Bois Forte Band (Nett Lake) of the Minnesota Chippewa Tribe, Minnesota; Chippewa Cree Indians of the Rocky Boy\\'s Reservation, Montana; Fond du Lac Band of the Minnesota Chippewa Tribe, Minnesota; Grand Portage Band of the Minnesota Chippewa Tribe, Minnesota; Grand Traverse Band of Ottawa and Chippewa Indians, Michigan; Lac Courte Oreilles Band of Lake Superior Chippewa Indians of Wisconsin; Lac du Flambeau Band of Lake Superior Chippewa Indians of the Lac du Flambeau Reservation of Wisconsin; Lac Vieux Desert Band of Lake Superior Chippewa Indians of Michigan; Leech Lake Band of the Minnesota Chippewa Tribe, Minnesota; Mille Lacs Band of the Minnesota Chippewa Tribe, Minnesota; Minnesota Chippewa Tribe, Minnesota; Red Cliff Band of Lake Superior Chippewa Indians of Wisconsin; Red Lake Band of Chippewa Indians, Minnesota; Saginaw Chippewa Indian Tribe of Michigan; Sault Ste. Marie Tribe of Chippewa Indians, Michigan; Sokaogon Chippewa Community, Wisconsin; St. Croix Chippewa Indians of Wisconsin; Turtle Mountain Band of Chippewa Indians of North Dakota; and the White Earth Band of Minnesota Chippewa Tribe, Minnesota (hereafter referred to as The Aboriginal Land Tribes). \n \\xe2\\x80\\xa2 Pursuant to 43 CFR 10.11(c)(1), the disposition of the human remains may be to The Aboriginal Land Tribes. \n ", "a_r_d": "Representatives of any Indian Tribe or Native Hawaiian organization not identified in this notice that wish to request transfer of control of these human remains should submit a written request with information in support of the request to Jennifer Kolb, Wisconsin Historical Society, 816 State St, Madison, WI 53706, telephone (608) 264-6434, email Jennifer.Kolb@wisconsinhistory.org, by November 16, 2017. After that date, if no additional requestors have come forward, transfer of control of the human remains to The Aboriginal Land Tribes may proceed. \n The Wisconsin Historical Society is responsible for notifying The Aboriginal Land Tribes and the Forest County Potawatomi Community, Wisconsin; Ho-Chunk Nation of Wisconsin; and the Menominee Indian Tribe of Wisconsin that this notice has been published. \n "}