{"index": "I_40", "messy_full": "\\n      \\n        DEPARTMENT OF THE INTERIOR\\n        National Park Service\\n        [NPS-WASO-NAGPRA-NPS0028456; PPWOCRADN0-PCU00RP14.R50000]\\n        Notice of Inventory Completion: Arizona State Museum, University of Arizona, Tucson, AZ; Correction\\n        \\n          AGENCY:\\n          National Park Service, Interior.\\n        \\n        \\n          ACTION:\\n          Notice; correction.\\n        \\n        \\n          SUMMARY:\\n\\n          The Arizona State Museum, University of Arizona has corrected an inventory of human remains and associated funerary objects, published in a Notice of Inventory Completion in the Federal Register on September 10, 2014. This notice corrects the minimum number of individuals and number of associated funerary objects. Lineal descendants or representatives of any Indian Tribe or Native Hawaiian organization not identified in this notice that wish to request transfer of control of these human remains and associated funerary objects should submit a written request to the Arizona State Museum, University of Arizona. If no additional requestors come forward, transfer of control of the human remains and associated funerary objects to the lineal descendants, Indian Tribes, or Native Hawaiian organizations stated in this notice may proceed.\\n        \\n        \\n          \\n          DATES:\\n          Lineal descendants or representatives of any Indian Tribe or Native Hawaiian organization not identified in this notice that wish to request transfer of control of these human remains and associated funerary objects should submit a written request with information in support of the request to the Arizona State Museum, University of Arizona at the address in this notice by September 4, 2019.\\n        \\n        \\n          ADDRESSES:\\n\\n          Claire S. Barker, Repatriation Coordinator, Arizona State Museum, P.O. Box 210026, Arizona State Museum, University of Arizona, Tucson, AZ 85721, telephone (520) 626-0320, email csbarker@email.arizona.edu.\\n        \\n      \\n      \\n        SUPPLEMENTARY INFORMATION:\\n        Notice is here given in accordance with the Native American Graves Protection and Repatriation Act (NAGPRA), 25 U.S.C. 3003, of the correction of an inventory of human remains and associated funerary objects under the control of the Arizona State Museum, University of Arizona, Tucson, Arizona. The human remains and associated funerary objects were removed from Pima County, AZ.\\n        This notice is published as part of the National Park Service\\'s administrative responsibilities under NAGPRA, 25 U.S.C. 3003(d)(3). The determinations in this notice are the sole responsibility of the museum, institution, or Federal agency that has control of the Native American human remains and associated funerary objects. The National Park Service is not responsible for the determinations in this notice.\\n\\n        This notice corrects the minimum number of individuals and number of associated funerary objects published in a Notice of Inventory Completion in the Federal Register (79 FR 53754-53759, September 10, 2014). The number of human remains and associated funerary objects has changed due to a search through uncatalogued collections. Transfer of control of the items in this correction notice has not occurred.\\n        Correction\\n        In the Federal Register (79 FR 53757, September 10, 2014), column 1, paragraph 1, sentence 5 is corrected by substituting the following sentence:\\n        The 106 associated funerary objects include 62 animal bones, three bone awls, 16 ceramic sherds, one ceramic vessel, one lot of charcoal, 16 chipped stones, one ground stone, two minerals, three soil samples, and one turquoise fragment.\\n        In the Federal Register (79 FR 53757, September 10, 2014), column 1, paragraph 3, sentence 1 is corrected by substituting the following sentence:\\n        In the years 1981 to 1987, human remains representing, at minimum, 57 individuals were removed from the Redtail Village site, AZ AA:12:149(ASM), in Tucson, Pima County, AZ.\\n        In the Federal Register (79 FR 53757, September 10, 2014), column 1, paragraph 3, sentence 7 is corrected by substituting the following sentence:\\n        The 965 associated funerary objects are 45 animal bones, two ceramic bowls, two ceramic jars, two ceramic scoops, 730 ceramic sherds, five lots of charcoal, 74 chipped stones, 78 flotation fraction lots, two ground stones, one metate, one mineral, five pollen samples, three shells, two stone projectile points, and 13 turquoise fragments.\\n        In the Federal Register (79 FR 53757, September 10, 2014), column 3, paragraph 1, sentence 5 is corrected by substituting the following sentence:\\n        The 142 associated funerary objects are two animal bones, two lots of botanical material, 126 ceramic sherds, one lot of charcoal, and 11 chipped stones.\\n        In the Federal Register (79 FR 53758, September 10, 2014), column 1, paragraph 2, sentence 6 is corrected by substituting the following sentence:\\n        The 259 associated funerary objects are six ceramic bowls, three ceramic jars, 17 ceramic jar fragments, 166 ceramic sherds, two lot of charcoal, 27 chipped stones, two chipped stone knives, two flotation fraction lots, 20 flotation samples, one glass fragment, one ground stone, one mano, three minerals, two polishing stones, one shell, one shell bracelet, one soil sample, two stone artifacts, and one stone palette fragment.\\n        In the Federal Register (79 FR 53758, September 10, 2014), column 3, paragraph 4, sentence 1 is corrected by substituting the following sentence:\\n        Pursuant to 25 U.S.C. 3001(9), the human remains described in this notice represent the physical remains of 626 individuals of Native American ancestry.\\n        In the Federal Register (79 FR 53758, September 10, 2014), column 3, paragraph 4, sentence 2 is corrected by substituting the following sentence:\\n        Pursuant to 25 U.S.C. 3001(3)(A), the 7,419 objects described in this notice are reasonably believed to have been placed with or near individual human remains at the time of death or later as part of the death rite or ceremony.\\n        Additional Requestors and Disposition\\n\\n        Lineal descendants or representatives of any Indian Tribe or Native Hawaiian organization not identified in this notice that wish to request transfer of control of these human remains and associated funerary objects should submit a written request with information in support of the request to Claire S. Barker, Repatriation Coordinator, Arizona State Museum, P.O. Box 210026, Arizona State Museum, University of Arizona, Tucson, AZ 85721, telephone (520) 626-0320, email csbarker@email.arizona.edu, by September 4, 2019. After that date, if no additional requestors have come forward, transfer of control of the human remains and associated funerary objects to the Ak-Chin Indian Community (previously listed as the Ak Chin Indian Community of the Maricopa (Ak Chin) Indian Reservation, Arizona); Gila River Indian Community of the Gila River Indian Reservation, Arizona; Hopi Tribe of Arizona; Salt River Pima-Maricopa Indian Community of the Salt River Reservation, Arizona; Tohono O\\'odham Nation of Arizona; and the Zuni Tribe of the Zuni Reservation, New Mexico; hereafter referred to as \\xe2\\x80\\x9cThe Tribes,\\xe2\\x80\\x9d may proceed.\\n        The Arizona State Museum, University of Arizona is responsible for notifying The Tribes that this notice has been published.\\n        \\n          Dated: July 16, 2019.\\n          Melanie O\\'Brien,\\n          Manager, National NAGPRA Program.\\n        \\n      \\n      [FR Doc. 2019-16687 Filed 8-2-19; 8:45 am]\\n      BILLING CODE 4312-52-P\\n    ", "agency1": "DEPARTMENT OF THE INTERIOR", "sub_agency1": "National Park Service", "dep_doc": "[NPS-WASO-NAGPRA-NPS0028456; PPWOCRADN0-PCU00RP14.R50000]", "subject": "Notice of Inventory Completion: Arizona State Museum, University of Arizona, Tucson, AZ; Correction", "agency2": "National Park Service, Interior.", "action": "Notice; correction.", "summary": "The Arizona State Museum, University of Arizona has corrected an inventory of human remains and associated funerary objects, published in a Notice of Inventory Completion in the Federal Register on September 10, 2014. This notice corrects the minimum number of individuals and number of associated funerary objects. Lineal descendants or representatives of any Indian Tribe or Native Hawaiian organization not identified in this notice that wish to request transfer of control of these human remains and associated funerary objects should submit a written request to the Arizona State Museum, University of Arizona. If no additional requestors come forward, transfer of control of the human remains and associated funerary objects to the lineal descendants, Indian Tribes, or Native Hawaiian organizations stated in this notice may proceed.", "dates": "Lineal descendants or representatives of any Indian Tribe or Native Hawaiian organization not identified in this notice that wish to request transfer of control of these human remains and associated funerary objects should submit a written request with information in support of the request to the Arizona State Museum, University of Arizona at the address in this notice by September 4, 2019.", "addresses": "Claire S. Barker, Repatriation Coordinator, Arizona State Museum, P.O. Box 210026, Arizona State Museum, University of Arizona, Tucson, AZ 85721, telephone (520) 626-0320, email csbarker@email.arizona.edu.", "signature_dated": "Dated: July 16, 2019.", "signature_name": "Melanie O\\'Brien,", "signature_title": "Manager, National NAGPRA Program.", "fr_doc": "[FR Doc. 2019-16687 Filed 8-2-19; 8:45 am]", "billing_code": "BILLING CODE 4312-52-P", "supp_info": "SUPPLEMENTARY INFORMATION: \n Notice is here given in accordance with the Native American Graves Protection and Repatriation Act (NAGPRA), 25 U.S.C. 3003, of the correction of an inventory of human remains and associated funerary objects under the control of the Arizona State Museum, University of Arizona, Tucson, Arizona. The human remains and associated funerary objects were removed from Pima County, AZ. \n This notice is published as part of the National Park Service\\'s administrative responsibilities under NAGPRA, 25 U.S.C. 3003(d)(3). The determinations in this notice are the sole responsibility of the museum, institution, or Federal agency that has control of the Native American human remains and associated funerary objects. The National Park Service is not responsible for the determinations in this notice. \n This notice corrects the minimum number of individuals and number of associated funerary objects published in a Notice of Inventory Completion in the Federal Register (79 FR 53754-53759, September 10, 2014). The number of human remains and associated funerary objects has changed due to a search through uncatalogued collections. Transfer of control of the items in this correction notice has not occurred. \n Correction \n In the Federal Register (79 FR 53757, September 10, 2014), column 1, paragraph 1, sentence 5 is corrected by substituting the following sentence: \n The 106 associated funerary objects include 62 animal bones, three bone awls, 16 ceramic sherds, one ceramic vessel, one lot of charcoal, 16 chipped stones, one ground stone, two minerals, three soil samples, and one turquoise fragment. \n In the Federal Register (79 FR 53757, September 10, 2014), column 1, paragraph 3, sentence 1 is corrected by substituting the following sentence: \n In the years 1981 to 1987, human remains representing, at minimum, 57 individuals were removed from the Redtail Village site, AZ AA:12:149(ASM), in Tucson, Pima County, AZ. \n In the Federal Register (79 FR 53757, September 10, 2014), column 1, paragraph 3, sentence 7 is corrected by substituting the following sentence: \n The 965 associated funerary objects are 45 animal bones, two ceramic bowls, two ceramic jars, two ceramic scoops, 730 ceramic sherds, five lots of charcoal, 74 chipped stones, 78 flotation fraction lots, two ground stones, one metate, one mineral, five pollen samples, three shells, two stone projectile points, and 13 turquoise fragments. \n In the Federal Register (79 FR 53757, September 10, 2014), column 3, paragraph 1, sentence 5 is corrected by substituting the following sentence: \n The 142 associated funerary objects are two animal bones, two lots of botanical material, 126 ceramic sherds, one lot of charcoal, and 11 chipped stones. \n In the Federal Register (79 FR 53758, September 10, 2014), column 1, paragraph 2, sentence 6 is corrected by substituting the following sentence: \n The 259 associated funerary objects are six ceramic bowls, three ceramic jars, 17 ceramic jar fragments, 166 ceramic sherds, two lot of charcoal, 27 chipped stones, two chipped stone knives, two flotation fraction lots, 20 flotation samples, one glass fragment, one ground stone, one mano, three minerals, two polishing stones, one shell, one shell bracelet, one soil sample, two stone artifacts, and one stone palette fragment. \n In the Federal Register (79 FR 53758, September 10, 2014), column 3, paragraph 4, sentence 1 is corrected by substituting the following sentence: \n Pursuant to 25 U.S.C. 3001(9), the human remains described in this notice represent the physical remains of 626 individuals of Native American ancestry. \n In the Federal Register (79 FR 53758, September 10, 2014), column 3, paragraph 4, sentence 2 is corrected by substituting the following sentence: \n Pursuant to 25 U.S.C. 3001(3)(A), the 7,419 objects described in this notice are reasonably believed to have been placed with or near individual human remains at the time of death or later as part of the death rite or ceremony. \n Additional Requestors and Disposition \n Lineal descendants or representatives of any Indian Tribe or Native Hawaiian organization not identified in this notice that wish to request transfer of control of these human remains and associated funerary objects should submit a written request with information in support of the request to Claire S. Barker, Repatriation Coordinator, Arizona State Museum, P.O. Box 210026, Arizona State Museum, University of Arizona, Tucson, AZ 85721, telephone (520) 626-0320, email csbarker@email.arizona.edu, by September 4, 2019. After that date, if no additional requestors have come forward, transfer of control of the human remains and associated funerary objects to the Ak-Chin Indian Community (previously listed as the Ak Chin Indian Community of the Maricopa (Ak Chin) Indian Reservation, Arizona); Gila River Indian Community of the Gila River Indian Reservation, Arizona; Hopi Tribe of Arizona; Salt River Pima-Maricopa Indian Community of the Salt River Reservation, Arizona; Tohono O\\'odham Nation of Arizona; and the Zuni Tribe of the Zuni Reservation, New Mexico; hereafter referred to as \\xe2\\x80\\x9cThe Tribes,\\xe2\\x80\\x9d may proceed. \n The Arizona State Museum, University of Arizona is responsible for notifying The Tribes that this notice has been published. \n ", "consultation": "Null", "h_d_r": "Null", "h_d_ci": "Null", "determinations": "Null", "a_r_d": "Lineal descendants or representatives of any Indian Tribe or Native Hawaiian organization not identified in this notice that wish to request transfer of control of these human remains and associated funerary objects should submit a written request with information in support of the request to Claire S. Barker, Repatriation Coordinator, Arizona State Museum, P.O. Box 210026, Arizona State Museum, University of Arizona, Tucson, AZ 85721, telephone (520) 626-0320, email csbarker@email.arizona.edu, by September 4, 2019. After that date, if no additional requestors have come forward, transfer of control of the human remains and associated funerary objects to the Ak-Chin Indian Community (previously listed as the Ak Chin Indian Community of the Maricopa (Ak Chin) Indian Reservation, Arizona); Gila River Indian Community of the Gila River Indian Reservation, Arizona; Hopi Tribe of Arizona; Salt River Pima-Maricopa Indian Community of the Salt River Reservation, Arizona; Tohono O\\'odham Nation of Arizona; and the Zuni Tribe of the Zuni Reservation, New Mexico; hereafter referred to as \\xe2\\x80\\x9cThe Tribes,\\xe2\\x80\\x9d may proceed. \n The Arizona State Museum, University of Arizona is responsible for notifying The Tribes that this notice has been published. \n "}