{"index": "I_41", "messy_full": "\\n      \\n        DEPARTMENT OF THE INTERIOR\\n        National Park Service\\n        [NPS-WASO-NAGPRA-NPS0028457; PPWOCRADN0-PCU00RP14.R50000]\\n        Notice of Inventory Completion: Arizona State Museum, University of Arizona, Tucson, AZ; Correction\\n        \\n          AGENCY:\\n          National Park Service, Interior.\\n        \\n        \\n          ACTION:\\n          Notice; correction.\\n        \\n        \\n          SUMMARY:\\n\\n          The Arizona State Museum, University of Arizona has corrected an inventory of human remains and associated funerary objects, published in a Notice of Inventory Completion in the Federal Register on September 10, 2014. This notice corrects the number of associated funerary objects. Lineal descendants or representatives of any Indian Tribe or Native Hawaiian organization not identified in this notice that wish to request transfer of control of these human remains and associated funerary objects should submit a written request to the Arizona State Museum, University of Arizona. If no additional requestors come forward, transfer of control of the human remains and associated funerary objects to the lineal descendants, Indian Tribes, or Native Hawaiian organizations stated in this notice may proceed.\\n        \\n        \\n          DATES:\\n          Lineal descendants or representatives of any Indian Tribe or Native Hawaiian organization not identified in this notice that wish to request transfer of control of these human remains and associated funerary objects should submit a written request with information in support of the request to the Arizona State Museum, University of Arizona at the address in this notice by September 4, 2019.\\n        \\n        \\n          ADDRESSES:\\n\\n          Claire S. Barker, Repatriation Coordinator, Arizona State Museum, P.O. Box 210026, Arizona State Museum, University of Arizona, Tucson, AZ 85721, telephone (520) 626-0320, email csbarker@email.arizona.edu.\\n          \\n        \\n      \\n      \\n        SUPPLEMENTARY INFORMATION:\\n        Notice is here given in accordance with the Native American Graves Protection and Repatriation Act (NAGPRA), 25 U.S.C. 3003, of the correction of an inventory of human remains and associated funerary objects under the control of the Arizona State Museum, University of Arizona, Tucson, AZ. The human remains and associated funerary objects were removed from Pima County, AZ.\\n        This notice is published as part of the National Park Service\\'s administrative responsibilities under NAGPRA, 25 U.S.C. 3003(d)(3). The determinations in this notice are the sole responsibility of the museum, institution, or Federal agency that has control of the Native American human remains and associated funerary objects. The National Park Service is not responsible for the determinations in this notice.\\n\\n        This notice corrects the number of associated funerary objects published in a Notice of Inventory Completion in the Federal Register (79 FR 53761-53767, September 10, 2014). The number of associated funerary objects has increased due to a search through uncatalogued collections. Transfer of control of the items in this correction notice has not occurred.\\n        Correction\\n        In the Federal Register (79 FR 53762, September 10, 2014), column 3, paragraph 3, sentence 7 is corrected by substituting the following sentence:\\n        \\n        The 179 associated funerary objects are one animal bone, one bone awl, 172 ceramic sherds, two ceramic vessels, one chipped stone, and two soil samples.\\n        In the Federal Register (79 FR 53764, September 10, 2014), column 2, paragraph 3, sentence 5 is corrected by substituting the following sentence:\\n        The 381 associated funerary objects are 130 animal bones, one bead, one ceramic bowl, five ceramic bowl fragments, one ceramic jar, 124 ceramic sherds, nine lots of charcoal, 108 chipped stones, one clay fragment, and one shell bracelet fragment.\\n        In the Federal Register (79 FR 53766, September 10, 2014), column 2, paragraph 4, sentence 2 is corrected by substituting the following sentence:\\n        Pursuant to 25 U.S.C. 3001(3)(A), the 2,011 objects described in this notice are reasonably believed to have been placed with or near individual human remains at the time of death or later as part of the death rite or ceremony.\\n        Additional Requestors and Disposition\\n\\n        Lineal descendants or representatives of any Indian Tribe or Native Hawaiian organization not identified in this notice that wish to request transfer of control of these human remains and associated funerary objects should submit a written request with information in support of the request to Claire S. Barker, Repatriation Coordinator, Arizona State Museum, P.O. Box 210026, Arizona State Museum, University of Arizona, Tucson, AZ 85721, telephone (520) 626-0320, email csbarker@email.arizona.edu, by September 4, 2019. After that date, if no additional requestors have come forward, transfer of control of the human remains and associated funerary objects to the Ak-Chin Indian Community (previously listed as the Ak Chin Indian Community of the Maricopa (Ak Chin) Indian Reservation, Arizona); Gila River Indian Community of the Gila River Indian Reservation, Arizona; Hopi Tribe of Arizona; Salt River Pima-Maricopa Indian Community of the Salt River Reservation, Arizona; Tohono O\\'odham Nation of Arizona; and the Zuni Tribe of the Zuni Reservation, New Mexico; hereafter referred to as \\xe2\\x80\\x9cThe Tribes,\\xe2\\x80\\x9d may proceed.\\n        The Arizona State Museum, University of Arizona is responsible for notifying the Tribes that this notice has been published.\\n        \\n          Dated: July 16, 2019.\\n          Melanie O\\'Brien,\\n          Manager, National NAGPRA Program. \\n        \\n      \\n      [FR Doc. 2019-16688 Filed 8-2-19; 8:45 am]\\n       BILLING CODE 4312-52-P\\n    ", "agency1": "DEPARTMENT OF THE INTERIOR", "sub_agency1": "National Park Service", "dep_doc": "[NPS-WASO-NAGPRA-NPS0028457; PPWOCRADN0-PCU00RP14.R50000]", "subject": "Notice of Inventory Completion: Arizona State Museum, University of Arizona, Tucson, AZ; Correction", "agency2": "National Park Service, Interior.", "action": "Notice; correction.", "summary": "The Arizona State Museum, University of Arizona has corrected an inventory of human remains and associated funerary objects, published in a Notice of Inventory Completion in the Federal Register on September 10, 2014. This notice corrects the number of associated funerary objects. Lineal descendants or representatives of any Indian Tribe or Native Hawaiian organization not identified in this notice that wish to request transfer of control of these human remains and associated funerary objects should submit a written request to the Arizona State Museum, University of Arizona. If no additional requestors come forward, transfer of control of the human remains and associated funerary objects to the lineal descendants, Indian Tribes, or Native Hawaiian organizations stated in this notice may proceed.", "dates": "Lineal descendants or representatives of any Indian Tribe or Native Hawaiian organization not identified in this notice that wish to request transfer of control of these human remains and associated funerary objects should submit a written request with information in support of the request to the Arizona State Museum, University of Arizona at the address in this notice by September 4, 2019.", "addresses": "Claire S. Barker, Repatriation Coordinator, Arizona State Museum, P.O. Box 210026, Arizona State Museum, University of Arizona, Tucson, AZ 85721, telephone (520) 626-0320, email csbarker@email.arizona.edu.\\n          ", "signature_dated": "Dated: July 16, 2019.", "signature_name": "Melanie O\\'Brien,", "signature_title": "Manager, National NAGPRA Program. ", "fr_doc": "[FR Doc. 2019-16688 Filed 8-2-19; 8:45 am]", "billing_code": " BILLING CODE 4312-52-P", "supp_info": "SUPPLEMENTARY INFORMATION: \n Notice is here given in accordance with the Native American Graves Protection and Repatriation Act (NAGPRA), 25 U.S.C. 3003, of the correction of an inventory of human remains and associated funerary objects under the control of the Arizona State Museum, University of Arizona, Tucson, AZ. The human remains and associated funerary objects were removed from Pima County, AZ. \n This notice is published as part of the National Park Service\\'s administrative responsibilities under NAGPRA, 25 U.S.C. 3003(d)(3). The determinations in this notice are the sole responsibility of the museum, institution, or Federal agency that has control of the Native American human remains and associated funerary objects. The National Park Service is not responsible for the determinations in this notice. \n This notice corrects the number of associated funerary objects published in a Notice of Inventory Completion in the Federal Register (79 FR 53761-53767, September 10, 2014). The number of associated funerary objects has increased due to a search through uncatalogued collections. Transfer of control of the items in this correction notice has not occurred. \n Correction \n In the Federal Register (79 FR 53762, September 10, 2014), column 3, paragraph 3, sentence 7 is corrected by substituting the following sentence:\\n         \n The 179 associated funerary objects are one animal bone, one bone awl, 172 ceramic sherds, two ceramic vessels, one chipped stone, and two soil samples. \n In the Federal Register (79 FR 53764, September 10, 2014), column 2, paragraph 3, sentence 5 is corrected by substituting the following sentence: \n The 381 associated funerary objects are 130 animal bones, one bead, one ceramic bowl, five ceramic bowl fragments, one ceramic jar, 124 ceramic sherds, nine lots of charcoal, 108 chipped stones, one clay fragment, and one shell bracelet fragment. \n In the Federal Register (79 FR 53766, September 10, 2014), column 2, paragraph 4, sentence 2 is corrected by substituting the following sentence: \n Pursuant to 25 U.S.C. 3001(3)(A), the 2,011 objects described in this notice are reasonably believed to have been placed with or near individual human remains at the time of death or later as part of the death rite or ceremony. \n Additional Requestors and Disposition \n Lineal descendants or representatives of any Indian Tribe or Native Hawaiian organization not identified in this notice that wish to request transfer of control of these human remains and associated funerary objects should submit a written request with information in support of the request to Claire S. Barker, Repatriation Coordinator, Arizona State Museum, P.O. Box 210026, Arizona State Museum, University of Arizona, Tucson, AZ 85721, telephone (520) 626-0320, email csbarker@email.arizona.edu, by September 4, 2019. After that date, if no additional requestors have come forward, transfer of control of the human remains and associated funerary objects to the Ak-Chin Indian Community (previously listed as the Ak Chin Indian Community of the Maricopa (Ak Chin) Indian Reservation, Arizona); Gila River Indian Community of the Gila River Indian Reservation, Arizona; Hopi Tribe of Arizona; Salt River Pima-Maricopa Indian Community of the Salt River Reservation, Arizona; Tohono O\\'odham Nation of Arizona; and the Zuni Tribe of the Zuni Reservation, New Mexico; hereafter referred to as \\xe2\\x80\\x9cThe Tribes,\\xe2\\x80\\x9d may proceed. \n The Arizona State Museum, University of Arizona is responsible for notifying the Tribes that this notice has been published. \n ", "consultation": "Null", "h_d_r": "Null", "h_d_ci": "Null", "determinations": "Null", "a_r_d": "Lineal descendants or representatives of any Indian Tribe or Native Hawaiian organization not identified in this notice that wish to request transfer of control of these human remains and associated funerary objects should submit a written request with information in support of the request to Claire S. Barker, Repatriation Coordinator, Arizona State Museum, P.O. Box 210026, Arizona State Museum, University of Arizona, Tucson, AZ 85721, telephone (520) 626-0320, email csbarker@email.arizona.edu, by September 4, 2019. After that date, if no additional requestors have come forward, transfer of control of the human remains and associated funerary objects to the Ak-Chin Indian Community (previously listed as the Ak Chin Indian Community of the Maricopa (Ak Chin) Indian Reservation, Arizona); Gila River Indian Community of the Gila River Indian Reservation, Arizona; Hopi Tribe of Arizona; Salt River Pima-Maricopa Indian Community of the Salt River Reservation, Arizona; Tohono O\\'odham Nation of Arizona; and the Zuni Tribe of the Zuni Reservation, New Mexico; hereafter referred to as \\xe2\\x80\\x9cThe Tribes,\\xe2\\x80\\x9d may proceed. \n The Arizona State Museum, University of Arizona is responsible for notifying the Tribes that this notice has been published. \n "}