{"index": "I_442", "messy_full": "\\n      \\n        DEPARTMENT OF THE INTERIOR\\n        National Park Service\\n        [NPS-WASO-NAGPRA-22947; PPWOCRADN0-PCU00RP14.R50000]\\n        Notice of Inventory Completion: Human Remains Repository, Department of Anthropology, University of Wyoming, Laramie, WY\\n        \\n          AGENCY:\\n          National Park Service, Interior.\\n        \\n        \\n          ACTION:\\n          Notice.\\n        \\n        \\n          SUMMARY:\\n          The Human Remains Repository, Department of Anthropology, University of Wyoming, has completed an inventory of human remains and associated funerary objects, in consultation with the appropriate Indian tribes or Native Hawaiian organizations, and has determined that there is no cultural affiliation between the human remains and associated funerary objects and any present-day Indian tribes or Native Hawaiian organizations. Representatives of any Indian tribe or Native Hawaiian organization not identified in this notice that wish to request transfer of control of these human remains and associated funerary objects should submit a written request to the Human Remains Repository, Department of Anthropology, University of Wyoming. If no additional requestors come forward, transfer of control of the human remains and associated funerary objects to the Indian tribes or Native Hawaiian organizations stated in this notice may proceed.\\n        \\n        \\n          DATES:\\n\\n          Representatives of any Indian tribe or Native Hawaiian organization not identified in this notice that wish to request transfer of control of these human remains and associated funerary objects should submit a written request with information in support of the request to the Human Remains Repository, Department of Anthropology, University of Wyoming, at the address in this notice by April 12, 2017.\\n        \\n        \\n          ADDRESSES:\\n\\n          Dr. Rick L. Weathermon, Curator, Human Remains Repository, Department 3431, Anthropology, 1000 East University Avenue, University of Wyoming, Laramie, WY 82071, telephone (307) 314-2035, email rikw@uwyo.edu.\\n          \\n        \\n      \\n      \\n        SUPPLEMENTARY INFORMATION:\\n        Notice is here given in accordance with the Native American Graves Protection and Repatriation Act (NAGPRA), 25 U.S.C. 3003, of the completion of an inventory of human remains and associated funerary objects under the control of the Human Remains Repository, Department of Anthropology, University of Wyoming, Laramie, WY. The human remains and associated funerary objects were removed from an unknown location near Julesburg, Sedgwick County, CO.\\n        This notice is published as part of the National Park Service\\'s administrative responsibilities under NAGPRA, 25 U.S.C. 3003(d)(3) and 43 CFR 10.11(d). The determinations in this notice are the sole responsibility of the museum, institution, or Federal agency that has control of the Native American human remains and associated funerary objects. The National Park Service is not responsible for the determinations in this notice.\\n        Consultation\\n        A detailed assessment of the human remains was made by the Human Remains Repository, Department of Anthropology, University of Wyoming, Laramie, WY, professional staff in consultation with representatives of the Arapaho Tribe of the Wind River Reservation, Wyoming. The following tribes were invited to consult but did not participate in consultation: Cheyenne and Arapaho Tribes, Oklahoma (previously listed as the Cheyenne-Arapaho Tribes of Oklahoma); and Northern Cheyenne Tribe of the Northern Cheyenne Indian Reservation, Montana.\\n        History and Description of the Remains\\n        At some time prior to 1995, human remains representing, at minimum, one individual were removed from an unknown location in near Julesburg, Sedgwick County, CO. The human remains and associated funerary objects were given to an instructor at the University of Wyoming in 1995. That individual transferred the human remains and associated funerary objects to the Human Remains Repository, Department of Anthropology, University of Wyoming, in 1997. The human remains represent a single male individual of American Indian ancestry, over the age of 65 years. The human remains and associated funerary objects are recorded as HR201 in the Human Remains Repository records. No known individual was identified. The four associated funerary objects are one (bison) first rib, one partial leather knife scabbard, one brass wire bracelet, and one lot of leather and fur fragments.\\n        Determinations Made by the Human Remains Repository, Department of Anthropology, University of Wyoming\\n        Officials of the Human Remains Repository, Department of Anthropology, University of Wyoming have determined that:\\n        \\xe2\\x80\\xa2 Pursuant to 25 U.S.C. 3001(9), the human remains described in this notice are Native American based on features of the cranium.\\n        \\xe2\\x80\\xa2 Pursuant to 25 U.S.C. 3001(9), the human remains described in this notice represent the physical remains of one individual of Native American ancestry.\\n        \\xe2\\x80\\xa2 Pursuant to 25 U.S.C. 3001(3)(A), the four objects described in this notice are reasonably believed to have been placed with or near individual human remains at the time of death or later as part of the death rite or ceremony.\\n        \\xe2\\x80\\xa2 Pursuant to 25 U.S.C. 3001(2), a relationship of shared group identity cannot be reasonably traced between the Native American human remains and associated funerary objects and any present-day Indian tribe.\\n        \\xe2\\x80\\xa2 According to final judgments of the Indian Claims Commission or the Court of Federal Claims, the land from which the Native American human remains and associated funerary objects were removed is the aboriginal land of the Arapaho Tribe of the Wind River Reservation, Wyoming; Cheyenne and Arapaho Tribes, Oklahoma (previously listed as the Cheyenne-Arapaho Tribes of Oklahoma); and Northern Cheyenne Tribe of the Northern Cheyenne Indian Reservation, Montana.\\n        \\xe2\\x80\\xa2 Treaties, Acts of Congress, or Executive Orders, indicate that the land from which the Native American human remains and associated funerary objects were removed is the aboriginal land of the Arapaho Tribe of the Wind River Reservation, Wyoming; Cheyenne and Arapaho Tribes, Oklahoma (previously listed as the Cheyenne-Arapaho Tribes of Oklahoma); and Northern Cheyenne Tribe of the Northern Cheyenne Indian Reservation, Montana.\\n        \\xe2\\x80\\xa2 Pursuant to 43 CFR 10.11(c)(1), the disposition of the human remains and associated funerary objects may be to the Arapaho Tribe of the Wind River Reservation, Wyoming; Cheyenne and Arapaho Tribes, Oklahoma (previously listed as the Cheyenne-Arapaho Tribes of Oklahoma); and Northern Cheyenne Tribe of the Northern Cheyenne Indian Reservation, Montana.\\n        Additional Requestors and Disposition\\n\\n        Representatives of any Indian tribe or Native Hawaiian organization not identified in this notice that wish to request transfer of control of these human remains and associated funerary objects should submit a written request with information in support of the request to Dr. Rick L. Weathermon, Curator, Human Remains Repository, Department 3431, Anthropology, 1000 East University Avenue, University of Wyoming, Laramie, WY 82071, telephone (307) 314-2035, email rikw@uwyo.edu, by April 12, 2017. After that date, if no additional requestors have come forward, transfer of control of the human remains and associated funerary objects to the Arapaho Tribe of the Wind River Reservation, Wyoming; Cheyenne and Arapaho Tribes, Oklahoma (previously listed as the Cheyenne-Arapaho Tribes of Oklahoma); and Northern Cheyenne Tribe of the Northern Cheyenne Indian Reservation, Montana may proceed.\\n        The Human Remains Repository, Department of Anthropology, University of Wyoming, is responsible for notifying the Arapaho Tribe of the Wind River Reservation, Wyoming; Cheyenne and Arapaho Tribes, Oklahoma (previously listed as the Cheyenne-Arapaho Tribes of Oklahoma); and Northern Cheyenne Tribe of the Northern Cheyenne Indian Reservation, Montana that this notice has been published.\\n        \\n          Dated: February 17, 2017.\\n          Melanie O\\'Brien,\\n          Manager, National NAGPRA Program.\\n        \\n      \\n      [FR Doc. 2017-04856 Filed 3-10-17; 8:45 am]\\n       BILLING CODE 4312-52-P\\n    ", "agency1": "DEPARTMENT OF THE INTERIOR", "sub_agency1": "National Park Service", "dep_doc": "[NPS-WASO-NAGPRA-22947; PPWOCRADN0-PCU00RP14.R50000]", "subject": "Notice of Inventory Completion: Human Remains Repository, Department of Anthropology, University of Wyoming, Laramie, WY", "agency2": "National Park Service, Interior.", "action": "Notice.", "summary": "The Human Remains Repository, Department of Anthropology, University of Wyoming, has completed an inventory of human remains and associated funerary objects, in consultation with the appropriate Indian tribes or Native Hawaiian organizations, and has determined that there is no cultural affiliation between the human remains and associated funerary objects and any present-day Indian tribes or Native Hawaiian organizations. Representatives of any Indian tribe or Native Hawaiian organization not identified in this notice that wish to request transfer of control of these human remains and associated funerary objects should submit a written request to the Human Remains Repository, Department of Anthropology, University of Wyoming. If no additional requestors come forward, transfer of control of the human remains and associated funerary objects to the Indian tribes or Native Hawaiian organizations stated in this notice may proceed.", "dates": "Representatives of any Indian tribe or Native Hawaiian organization not identified in this notice that wish to request transfer of control of these human remains and associated funerary objects should submit a written request with information in support of the request to the Human Remains Repository, Department of Anthropology, University of Wyoming, at the address in this notice by April 12, 2017.", "addresses": "Dr. Rick L. Weathermon, Curator, Human Remains Repository, Department 3431, Anthropology, 1000 East University Avenue, University of Wyoming, Laramie, WY 82071, telephone (307) 314-2035, email rikw@uwyo.edu.\\n          ", "signature_dated": "Dated: February 17, 2017.", "signature_name": "Melanie O\\'Brien,", "signature_title": "Manager, National NAGPRA Program.", "fr_doc": "[FR Doc. 2017-04856 Filed 3-10-17; 8:45 am]", "billing_code": " BILLING CODE 4312-52-P", "supp_info": "SUPPLEMENTARY INFORMATION: \n Notice is here given in accordance with the Native American Graves Protection and Repatriation Act (NAGPRA), 25 U.S.C. 3003, of the completion of an inventory of human remains and associated funerary objects under the control of the Human Remains Repository, Department of Anthropology, University of Wyoming, Laramie, WY. The human remains and associated funerary objects were removed from an unknown location near Julesburg, Sedgwick County, CO. \n This notice is published as part of the National Park Service\\'s administrative responsibilities under NAGPRA, 25 U.S.C. 3003(d)(3) and 43 CFR 10.11(d). The determinations in this notice are the sole responsibility of the museum, institution, or Federal agency that has control of the Native American human remains and associated funerary objects. The National Park Service is not responsible for the determinations in this notice. \n Consultation \n A detailed assessment of the human remains was made by the Human Remains Repository, Department of Anthropology, University of Wyoming, Laramie, WY, professional staff in consultation with representatives of the Arapaho Tribe of the Wind River Reservation, Wyoming. The following tribes were invited to consult but did not participate in consultation: Cheyenne and Arapaho Tribes, Oklahoma (previously listed as the Cheyenne-Arapaho Tribes of Oklahoma); and Northern Cheyenne Tribe of the Northern Cheyenne Indian Reservation, Montana. \n History and Description of the Remains \n At some time prior to 1995, human remains representing, at minimum, one individual were removed from an unknown location in near Julesburg, Sedgwick County, CO. The human remains and associated funerary objects were given to an instructor at the University of Wyoming in 1995. That individual transferred the human remains and associated funerary objects to the Human Remains Repository, Department of Anthropology, University of Wyoming, in 1997. The human remains represent a single male individual of American Indian ancestry, over the age of 65 years. The human remains and associated funerary objects are recorded as HR201 in the Human Remains Repository records. No known individual was identified. The four associated funerary objects are one (bison) first rib, one partial leather knife scabbard, one brass wire bracelet, and one lot of leather and fur fragments. \n Determinations Made by the Human Remains Repository, Department of Anthropology, University of Wyoming \n Officials of the Human Remains Repository, Department of Anthropology, University of Wyoming have determined that: \n \\xe2\\x80\\xa2 Pursuant to 25 U.S.C. 3001(9), the human remains described in this notice are Native American based on features of the cranium. \n \\xe2\\x80\\xa2 Pursuant to 25 U.S.C. 3001(9), the human remains described in this notice represent the physical remains of one individual of Native American ancestry. \n \\xe2\\x80\\xa2 Pursuant to 25 U.S.C. 3001(3)(A), the four objects described in this notice are reasonably believed to have been placed with or near individual human remains at the time of death or later as part of the death rite or ceremony. \n \\xe2\\x80\\xa2 Pursuant to 25 U.S.C. 3001(2), a relationship of shared group identity cannot be reasonably traced between the Native American human remains and associated funerary objects and any present-day Indian tribe. \n \\xe2\\x80\\xa2 According to final judgments of the Indian Claims Commission or the Court of Federal Claims, the land from which the Native American human remains and associated funerary objects were removed is the aboriginal land of the Arapaho Tribe of the Wind River Reservation, Wyoming; Cheyenne and Arapaho Tribes, Oklahoma (previously listed as the Cheyenne-Arapaho Tribes of Oklahoma); and Northern Cheyenne Tribe of the Northern Cheyenne Indian Reservation, Montana. \n \\xe2\\x80\\xa2 Treaties, Acts of Congress, or Executive Orders, indicate that the land from which the Native American human remains and associated funerary objects were removed is the aboriginal land of the Arapaho Tribe of the Wind River Reservation, Wyoming; Cheyenne and Arapaho Tribes, Oklahoma (previously listed as the Cheyenne-Arapaho Tribes of Oklahoma); and Northern Cheyenne Tribe of the Northern Cheyenne Indian Reservation, Montana. \n \\xe2\\x80\\xa2 Pursuant to 43 CFR 10.11(c)(1), the disposition of the human remains and associated funerary objects may be to the Arapaho Tribe of the Wind River Reservation, Wyoming; Cheyenne and Arapaho Tribes, Oklahoma (previously listed as the Cheyenne-Arapaho Tribes of Oklahoma); and Northern Cheyenne Tribe of the Northern Cheyenne Indian Reservation, Montana. \n Additional Requestors and Disposition \n Representatives of any Indian tribe or Native Hawaiian organization not identified in this notice that wish to request transfer of control of these human remains and associated funerary objects should submit a written request with information in support of the request to Dr. Rick L. Weathermon, Curator, Human Remains Repository, Department 3431, Anthropology, 1000 East University Avenue, University of Wyoming, Laramie, WY 82071, telephone (307) 314-2035, email rikw@uwyo.edu, by April 12, 2017. After that date, if no additional requestors have come forward, transfer of control of the human remains and associated funerary objects to the Arapaho Tribe of the Wind River Reservation, Wyoming; Cheyenne and Arapaho Tribes, Oklahoma (previously listed as the Cheyenne-Arapaho Tribes of Oklahoma); and Northern Cheyenne Tribe of the Northern Cheyenne Indian Reservation, Montana may proceed. \n The Human Remains Repository, Department of Anthropology, University of Wyoming, is responsible for notifying the Arapaho Tribe of the Wind River Reservation, Wyoming; Cheyenne and Arapaho Tribes, Oklahoma (previously listed as the Cheyenne-Arapaho Tribes of Oklahoma); and Northern Cheyenne Tribe of the Northern Cheyenne Indian Reservation, Montana that this notice has been published. \n ", "consultation": "A detailed assessment of the human remains was made by the Human Remains Repository, Department of Anthropology, University of Wyoming, Laramie, WY, professional staff in consultation with representatives of the Arapaho Tribe of the Wind River Reservation, Wyoming. The following tribes were invited to consult but did not participate in consultation: Cheyenne and Arapaho Tribes, Oklahoma (previously listed as the Cheyenne-Arapaho Tribes of Oklahoma); and Northern Cheyenne Tribe of the Northern Cheyenne Indian Reservation, Montana. \n ", "h_d_r": "At some time prior to 1995, human remains representing, at minimum, one individual were removed from an unknown location in near Julesburg, Sedgwick County, CO. The human remains and associated funerary objects were given to an instructor at the University of Wyoming in 1995. That individual transferred the human remains and associated funerary objects to the Human Remains Repository, Department of Anthropology, University of Wyoming, in 1997. The human remains represent a single male individual of American Indian ancestry, over the age of 65 years. The human remains and associated funerary objects are recorded as HR201 in the Human Remains Repository records. No known individual was identified. The four associated funerary objects are one (bison) first rib, one partial leather knife scabbard, one brass wire bracelet, and one lot of leather and fur fragments. \n ", "h_d_ci": "Null", "determinations": "Determinations Made by the Human Remains Repository, Department of Anthropology, University of Wyoming \n Officials of the Human Remains Repository, Department of Anthropology, University of Wyoming have determined that: \n \\xe2\\x80\\xa2 Pursuant to 25 U.S.C. 3001(9), the human remains described in this notice are Native American based on features of the cranium. \n \\xe2\\x80\\xa2 Pursuant to 25 U.S.C. 3001(9), the human remains described in this notice represent the physical remains of one individual of Native American ancestry. \n \\xe2\\x80\\xa2 Pursuant to 25 U.S.C. 3001(3)(A), the four objects described in this notice are reasonably believed to have been placed with or near individual human remains at the time of death or later as part of the death rite or ceremony. \n \\xe2\\x80\\xa2 Pursuant to 25 U.S.C. 3001(2), a relationship of shared group identity cannot be reasonably traced between the Native American human remains and associated funerary objects and any present-day Indian tribe. \n \\xe2\\x80\\xa2 According to final judgments of the Indian Claims Commission or the Court of Federal Claims, the land from which the Native American human remains and associated funerary objects were removed is the aboriginal land of the Arapaho Tribe of the Wind River Reservation, Wyoming; Cheyenne and Arapaho Tribes, Oklahoma (previously listed as the Cheyenne-Arapaho Tribes of Oklahoma); and Northern Cheyenne Tribe of the Northern Cheyenne Indian Reservation, Montana. \n \\xe2\\x80\\xa2 Treaties, Acts of Congress, or Executive Orders, indicate that the land from which the Native American human remains and associated funerary objects were removed is the aboriginal land of the Arapaho Tribe of the Wind River Reservation, Wyoming; Cheyenne and Arapaho Tribes, Oklahoma (previously listed as the Cheyenne-Arapaho Tribes of Oklahoma); and Northern Cheyenne Tribe of the Northern Cheyenne Indian Reservation, Montana. \n \\xe2\\x80\\xa2 Pursuant to 43 CFR 10.11(c)(1), the disposition of the human remains and associated funerary objects may be to the Arapaho Tribe of the Wind River Reservation, Wyoming; Cheyenne and Arapaho Tribes, Oklahoma (previously listed as the Cheyenne-Arapaho Tribes of Oklahoma); and Northern Cheyenne Tribe of the Northern Cheyenne Indian Reservation, Montana. \n ", "a_r_d": "Representatives of any Indian tribe or Native Hawaiian organization not identified in this notice that wish to request transfer of control of these human remains and associated funerary objects should submit a written request with information in support of the request to Dr. Rick L. Weathermon, Curator, Human Remains Repository, Department 3431, Anthropology, 1000 East University Avenue, University of Wyoming, Laramie, WY 82071, telephone (307) 314-2035, email rikw@uwyo.edu, by April 12, 2017. After that date, if no additional requestors have come forward, transfer of control of the human remains and associated funerary objects to the Arapaho Tribe of the Wind River Reservation, Wyoming; Cheyenne and Arapaho Tribes, Oklahoma (previously listed as the Cheyenne-Arapaho Tribes of Oklahoma); and Northern Cheyenne Tribe of the Northern Cheyenne Indian Reservation, Montana may proceed. \n The Human Remains Repository, Department of Anthropology, University of Wyoming, is responsible for notifying the Arapaho Tribe of the Wind River Reservation, Wyoming; Cheyenne and Arapaho Tribes, Oklahoma (previously listed as the Cheyenne-Arapaho Tribes of Oklahoma); and Northern Cheyenne Tribe of the Northern Cheyenne Indian Reservation, Montana that this notice has been published. \n "}