{"index": "I_440", "messy_full": "\\n      \\n        DEPARTMENT OF THE INTERIOR\\n        National Park Service\\n        [NPS-WASO-NAGPRA-22911; PPWOCRADN0-PCU00RP14.R50000]\\n        Notice of Inventory Completion: Human Remains Repository, Department of Anthropology, University of Wyoming, Laramie, WY\\n        \\n          AGENCY:\\n          National Park Service, Interior.\\n        \\n        \\n          ACTION:\\n          Notice.\\n        \\n        \\n          SUMMARY:\\n          The Human Remains Repository, Department of Anthropology, University of Wyoming, Laramie, WY, has completed an inventory of human remains, in consultation with the appropriate Indian tribes or Native Hawaiian organizations, and has determined that there is a cultural affiliation between the human remains and present-day Indian tribes or Native Hawaiian organizations. Lineal descendants or representatives of any Indian tribe or Native Hawaiian organization not identified in this notice that wish to request transfer of control of these human remains should submit a written request to the Human Remains Repository, Department of Anthropology, University of Wyoming, Laramie, WY. If no additional requestors come forward, transfer of control of the human remains to the lineal descendants, Indian tribes, or Native Hawaiian organizations stated in this notice may proceed.\\n        \\n        \\n          DATES:\\n          Lineal descendants or representatives of any Indian tribe or Native Hawaiian organization not identified in this notice that wish to request transfer of control of these human remains should submit a written request with information in support of the request to the Human Remains Repository, Department of Anthropology, University of Wyoming, Laramie, WY, at the address in this notice by April 12, 2017.\\n        \\n        \\n          ADDRESSES:\\n\\n          Dr. Rick L. Weathermon, Curator, Human Remains Repository, Department 3431, Anthropology, 1000 East University Avenue, University of Wyoming, Laramie, WY 82071, telephone (307) 314-2035, email rikw@uwyo.edu.\\n          \\n        \\n      \\n      \\n        SUPPLEMENTARY INFORMATION:\\n        Notice is here given in accordance with the Native American Graves Protection and Repatriation Act (NAGPRA), 25 U.S.C. 3003, of the completion of an inventory of human remains under the control of the Human Remains Repository, Department of Anthropology, University of Wyoming, Laramie, WY. The human remains were removed from the west side of the Miners Point site (HR330), Kodiak Island, AK.\\n        This notice is published as part of the National Park Service\\'s administrative responsibilities under NAGPRA, 25 U.S.C. 3003(d)(3). The determinations in this notice are the sole responsibility of the museum, institution, or Federal agency that has control of the Native American human remains. The National Park Service is not responsible for the determinations in this notice.\\n        Consultation\\n        A detailed assessment of the human remains was made by the Human Remains Repository, Department of Anthropology, University of Wyoming, professional staff in consultation with representatives of the Native Village of Larsen Bay.\\n        History and Description of the Remains\\n        Prior to 1991, human remains representing, at minimum, one individual were removed from the west side of the Miner\\'s Point site (HR330), Kodiak Island, AK, probably by a Rock Springs, WY, physician. By 1991, the human remains had been given to Western Wyoming College in Rock Springs, WY. In October 2016, the University of Wyoming evaluated the NAGPRA status of all human remains in their possession. Following analysis, in December of 2016, the Miner\\'s Point individual (HR330) was formally accessioned into the Human Remains Repository, Department of Anthropology, University of Wyoming. The remains consist of a fragmentary human cranium of a Native American male, over the age of 50. No known individual was identified. No associated funerary objects are present.\\n        The human remains are of an unknown age. The Alutiiq people assert that they have continuously lived on Kodiak Island and the surrounding areas for at least 7,000 years, which is the entire human history of the location. The human remains exhibit skeletal characteristics consistent with an assessment of Alaskan Native.\\n        Determinations Made by the Human Remains Repository, Department of Anthropology, University of Wyoming\\n        Officials of the Human Remains Repository, Department of Anthropology, University of Wyoming have determined that:\\n        \\xe2\\x80\\xa2 Pursuant to 25 U.S.C. 3001(9), the human remains described in this notice represent the physical remains of one individual of Native American ancestry.\\n        \\xe2\\x80\\xa2 Pursuant to 25 U.S.C. 3001(3)(A), no objects are present that are reasonably believed to have been placed with or near individual human remains at the time of death or later as part of the death rite or ceremony.\\n        \\xe2\\x80\\xa2 Pursuant to 25 U.S.C. 3001(2), there is a relationship of shared group identity that can be reasonably traced between the Native American human remains and the Native Village of Larsen Bay.\\n        Additional Requestors and Disposition\\n\\n        Lineal descendants or representatives of any Indian tribe or Native Hawaiian organization not identified in this notice that wish to request transfer of control of these human remains should submit a written request with information in support of the request to Dr. Rick L. Weathermon, Curator, Human Remains Repository, Department 3431, Anthropology, 1000 East University Avenue, University of Wyoming, Laramie, WY 82071, telephone (307) 314-2035, email rikw@uwyo.edu.by April 12, 2017. After that date, if no additional requestors have come forward, transfer of control of the human remains to the Native Village of Larsen Bay may proceed.\\n\\n        The Human Remains Repository, Department of Anthropology, University of Wyoming is responsible for notifying the Native Village of Larsen Bay that this notice has been published.\\n        \\n          Dated: February 9, 2017.\\n          Melanie O\\'Brien,\\n          Manager, National NAGPRA Program. \\n        \\n      \\n      [FR Doc. 2017-04861 Filed 3-10-17; 8:45 am]\\n       BILLING CODE 4312-52-P\\n    ", "agency1": "DEPARTMENT OF THE INTERIOR", "sub_agency1": "National Park Service", "dep_doc": "[NPS-WASO-NAGPRA-22911; PPWOCRADN0-PCU00RP14.R50000]", "subject": "Notice of Inventory Completion: Human Remains Repository, Department of Anthropology, University of Wyoming, Laramie, WY", "agency2": "National Park Service, Interior.", "action": "Notice.", "summary": "The Human Remains Repository, Department of Anthropology, University of Wyoming, Laramie, WY, has completed an inventory of human remains, in consultation with the appropriate Indian tribes or Native Hawaiian organizations, and has determined that there is a cultural affiliation between the human remains and present-day Indian tribes or Native Hawaiian organizations. Lineal descendants or representatives of any Indian tribe or Native Hawaiian organization not identified in this notice that wish to request transfer of control of these human remains should submit a written request to the Human Remains Repository, Department of Anthropology, University of Wyoming, Laramie, WY. If no additional requestors come forward, transfer of control of the human remains to the lineal descendants, Indian tribes, or Native Hawaiian organizations stated in this notice may proceed.", "dates": "Lineal descendants or representatives of any Indian tribe or Native Hawaiian organization not identified in this notice that wish to request transfer of control of these human remains should submit a written request with information in support of the request to the Human Remains Repository, Department of Anthropology, University of Wyoming, Laramie, WY, at the address in this notice by April 12, 2017.", "addresses": "Dr. Rick L. Weathermon, Curator, Human Remains Repository, Department 3431, Anthropology, 1000 East University Avenue, University of Wyoming, Laramie, WY 82071, telephone (307) 314-2035, email rikw@uwyo.edu.\\n          ", "signature_dated": "Dated: February 9, 2017.", "signature_name": "Melanie O\\'Brien,", "signature_title": "Manager, National NAGPRA Program. ", "fr_doc": "[FR Doc. 2017-04861 Filed 3-10-17; 8:45 am]", "billing_code": " BILLING CODE 4312-52-P", "supp_info": "SUPPLEMENTARY INFORMATION: \n Notice is here given in accordance with the Native American Graves Protection and Repatriation Act (NAGPRA), 25 U.S.C. 3003, of the completion of an inventory of human remains under the control of the Human Remains Repository, Department of Anthropology, University of Wyoming, Laramie, WY. The human remains were removed from the west side of the Miners Point site (HR330), Kodiak Island, AK. \n This notice is published as part of the National Park Service\\'s administrative responsibilities under NAGPRA, 25 U.S.C. 3003(d)(3). The determinations in this notice are the sole responsibility of the museum, institution, or Federal agency that has control of the Native American human remains. The National Park Service is not responsible for the determinations in this notice. \n Consultation \n A detailed assessment of the human remains was made by the Human Remains Repository, Department of Anthropology, University of Wyoming, professional staff in consultation with representatives of the Native Village of Larsen Bay. \n History and Description of the Remains \n Prior to 1991, human remains representing, at minimum, one individual were removed from the west side of the Miner\\'s Point site (HR330), Kodiak Island, AK, probably by a Rock Springs, WY, physician. By 1991, the human remains had been given to Western Wyoming College in Rock Springs, WY. In October 2016, the University of Wyoming evaluated the NAGPRA status of all human remains in their possession. Following analysis, in December of 2016, the Miner\\'s Point individual (HR330) was formally accessioned into the Human Remains Repository, Department of Anthropology, University of Wyoming. The remains consist of a fragmentary human cranium of a Native American male, over the age of 50. No known individual was identified. No associated funerary objects are present. \n The human remains are of an unknown age. The Alutiiq people assert that they have continuously lived on Kodiak Island and the surrounding areas for at least 7,000 years, which is the entire human history of the location. The human remains exhibit skeletal characteristics consistent with an assessment of Alaskan Native. \n Determinations Made by the Human Remains Repository, Department of Anthropology, University of Wyoming \n Officials of the Human Remains Repository, Department of Anthropology, University of Wyoming have determined that: \n \\xe2\\x80\\xa2 Pursuant to 25 U.S.C. 3001(9), the human remains described in this notice represent the physical remains of one individual of Native American ancestry. \n \\xe2\\x80\\xa2 Pursuant to 25 U.S.C. 3001(3)(A), no objects are present that are reasonably believed to have been placed with or near individual human remains at the time of death or later as part of the death rite or ceremony. \n \\xe2\\x80\\xa2 Pursuant to 25 U.S.C. 3001(2), there is a relationship of shared group identity that can be reasonably traced between the Native American human remains and the Native Village of Larsen Bay. \n Additional Requestors and Disposition \n Lineal descendants or representatives of any Indian tribe or Native Hawaiian organization not identified in this notice that wish to request transfer of control of these human remains should submit a written request with information in support of the request to Dr. Rick L. Weathermon, Curator, Human Remains Repository, Department 3431, Anthropology, 1000 East University Avenue, University of Wyoming, Laramie, WY 82071, telephone (307) 314-2035, email rikw@uwyo.edu.by April 12, 2017. After that date, if no additional requestors have come forward, transfer of control of the human remains to the Native Village of Larsen Bay may proceed. \n The Human Remains Repository, Department of Anthropology, University of Wyoming is responsible for notifying the Native Village of Larsen Bay that this notice has been published. \n ", "consultation": "A detailed assessment of the human remains was made by the Human Remains Repository, Department of Anthropology, University of Wyoming, professional staff in consultation with representatives of the Native Village of Larsen Bay. \n ", "h_d_r": "Prior to 1991, human remains representing, at minimum, one individual were removed from the west side of the Miner\\'s Point site (HR330), Kodiak Island, AK, probably by a Rock Springs, WY, physician. By 1991, the human remains had been given to Western Wyoming College in Rock Springs, WY. In October 2016, the University of Wyoming evaluated the NAGPRA status of all human remains in their possession. Following analysis, in December of 2016, the Miner\\'s Point individual (HR330) was formally accessioned into the Human Remains Repository, Department of Anthropology, University of Wyoming. The remains consist of a fragmentary human cranium of a Native American male, over the age of 50. No known individual was identified. No associated funerary objects are present. \n The human remains are of an unknown age. The Alutiiq people assert that they have continuously lived on Kodiak Island and the surrounding areas for at least 7,000 years, which is the entire human history of the location. The human remains exhibit skeletal characteristics consistent with an assessment of Alaskan Native. \n ", "h_d_ci": "Null", "determinations": "Determinations Made by the Human Remains Repository, Department of Anthropology, University of Wyoming \n Officials of the Human Remains Repository, Department of Anthropology, University of Wyoming have determined that: \n \\xe2\\x80\\xa2 Pursuant to 25 U.S.C. 3001(9), the human remains described in this notice represent the physical remains of one individual of Native American ancestry. \n \\xe2\\x80\\xa2 Pursuant to 25 U.S.C. 3001(3)(A), no objects are present that are reasonably believed to have been placed with or near individual human remains at the time of death or later as part of the death rite or ceremony. \n \\xe2\\x80\\xa2 Pursuant to 25 U.S.C. 3001(2), there is a relationship of shared group identity that can be reasonably traced between the Native American human remains and the Native Village of Larsen Bay. \n ", "a_r_d": "Lineal descendants or representatives of any Indian tribe or Native Hawaiian organization not identified in this notice that wish to request transfer of control of these human remains should submit a written request with information in support of the request to Dr. Rick L. Weathermon, Curator, Human Remains Repository, Department 3431, Anthropology, 1000 East University Avenue, University of Wyoming, Laramie, WY 82071, telephone (307) 314-2035, email rikw@uwyo.edu.by April 12, 2017. After that date, if no additional requestors have come forward, transfer of control of the human remains to the Native Village of Larsen Bay may proceed. \n The Human Remains Repository, Department of Anthropology, University of Wyoming is responsible for notifying the Native Village of Larsen Bay that this notice has been published. \n "}