{"index": "I_46", "messy_full": "\\n      \\n        DEPARTMENT OF THE INTERIOR\\n        National Park Service\\n        [NPS-WASO-NAGPRA-NPS0028402; PPWOCRADN0-PCU00RP14.R50000]\\n        Notice of Inventory Completion: The University of Oregon Museum of Natural and Cultural History, Eugene, OR\\n        \\n          AGENCY:\\n          National Park Service, Interior.\\n        \\n        \\n          ACTION:\\n          Notice.\\n        \\n        \\n          SUMMARY:\\n          The University of Oregon Museum of Natural and Cultural History has completed an inventory of human remains and associated funerary objects, in consultation with the appropriate Indian Tribes or Native Hawaiian organizations, and has determined that there is a cultural affiliation between the human remains and associated funerary objects and present-day Indian Tribes or Native Hawaiian organizations. Lineal descendants or representatives of any Indian Tribe or Native Hawaiian organization not identified in this notice that wish to request transfer of control of these human remains and associated funerary objects should submit a written request to the University of Oregon Museum of Natural and Cultural History. If no additional requestors come forward, transfer of control of the human remains and associated funerary objects to the lineal descendants, Indian Tribes, or Native Hawaiian organizations stated in this notice may proceed.\\n        \\n        \\n          DATES:\\n          Lineal descendants or representatives of any Indian Tribe or Native Hawaiian organization not identified in this notice that wish to request transfer of control of these human remains and associated funerary objects should submit a written request with information in support of the request to the University of Oregon Museum of Natural and Cultural History at the address in this notice by September 4, 2019.\\n        \\n        \\n          ADDRESSES:\\n\\n          Dr. Pamela Endzweig, Director of Collections, Museum of Natural and Cultural History, 1224 University of Oregon, Eugene, OR 97403-1224, telephone (541) 346-5120, email endzweig@uoregon.edu.\\n        \\n      \\n      \\n        SUPPLEMENTARY INFORMATION:\\n        Notice is here given in accordance with the Native American Graves Protection and Repatriation Act (NAGPRA), 25 U.S.C. 3003, of the completion of an inventory of human remains and associated funerary objects under the control of the University of Oregon Museum of Natural and Cultural History, Eugene, OR. The human remains and associated funerary object were removed from Purdy Mound at Bob Creek, Lane County, OR.\\n        This notice is published as part of the National Park Service\\'s administrative responsibilities under NAGPRA, 25 U.S.C. 3003(d)(3). The determinations in this notice are the sole responsibility of the museum, institution, or Federal agency that has control of the Native American human remains and associated funerary objects. The National Park Service is not responsible for the determinations in this notice.\\n        Consultation\\n        A detailed assessment of the human remains was made by the University of Oregon Museum of Natural and Cultural History professional staff in consultation with representatives of the Confederated Tribes of Siletz Indians of Oregon (previously listed as the Confederated Tribes of the Siletz Reservation); Confederated Tribes of the Coos, Lower Umpqua and Siuslaw Indians; Confederated Tribes of the Grand Ronde Community of Oregon; and the Coquille Indian Tribe (previously listed as the Coquille Tribe of Oregon), hereafter referred to as \\xe2\\x80\\x9cThe Consulted Tribes.\\xe2\\x80\\x9d\\n        History and Description of the Remains\\n        In 1950, human remains representing, at minimum, one individual were removed from Purdy Mound at Bob Creek in Lane County, OR. The human remains were removed by a private party and were donated to the museum in 1950 (acc. # 100LC). They belong to an adult male (cat. # 11-262). No known individuals were identified. The two associated funerary objects are one partial bone club and fragments of one elk maxillary.\\n        The human remains are reasonably believed to be of Native American ancestry based on their archeological context. Historical documents, ethnographic sources, and oral history indicate that the Bob Creek site lies near the territorial boundary between the Alsea and the Siuslaw peoples. Both cultural groups have occupied the region since pre-contact times. Based on information obtained through consultation, the human remains are identified as Alsea. The Alsea are members or the Confederated Tribes of Siletz Indians of Oregon.\\n        Determinations Made by the University of Oregon Museum of Natural and Cultural History\\n        Officials of the University of Oregon Museum of Natural and Cultural History have determined that:\\n        \\xe2\\x80\\xa2 Pursuant to 25 U.S.C. 3001(9), the human remains described in this notice represent the physical remains of one individual of Native American ancestry.\\n        \\xe2\\x80\\xa2 Pursuant to 25 U.S.C. 3001(3)(A), the two objects described in this notice are reasonably believed to have been placed with or near individual human remains at the time of death or later as part of the death rite or ceremony.\\n        \\xe2\\x80\\xa2 Pursuant to 25 U.S.C. 3001(2), there is a relationship of shared group identity that can be reasonably traced between the Native American human remains and associated funerary objects and the Confederated Tribes of Siletz Indians of Oregon (previously listed as the Confederated Tribes of the Siletz Reservation).\\n        Additional Requestors and Disposition\\n\\n        Lineal descendants or representatives of any Indian Tribe or Native Hawaiian organization not identified in this notice that wish to request transfer of control of these human remains and associated funerary objects should submit a written request with information in support of the request to Dr. Pamela Endzweig, Director of Collections, Museum of Natural and Cultural History, 1224 University of Oregon, Eugene, OR 97403-1224, telephone (541) 346-5120, email endzweig@uoregon.edu, by September 4, 2019. After that date, if no additional requestors have come forward, transfer of control of the human remains and associated funerary objects to the Confederated Tribes of Siletz Indians of Oregon (previously listed as the Confederated Tribes of the Siletz Reservation) may proceed.\\n        The University of Oregon Museum of Natural and Cultural History is responsible for notifying The Consulted Tribes that this notice has been published.\\n        \\n          Dated: July 9, 2019.\\n          Melanie O\\'Brien,\\n          Manager, National NAGPRA Program.\\n        \\n      \\n      [FR Doc. 2019-16679 Filed 8-2-19; 8:45 am]\\n      BILLING CODE 4312-52-P\\n    ", "agency1": "DEPARTMENT OF THE INTERIOR", "sub_agency1": "National Park Service", "dep_doc": "[NPS-WASO-NAGPRA-NPS0028402; PPWOCRADN0-PCU00RP14.R50000]", "subject": "Notice of Inventory Completion: The University of Oregon Museum of Natural and Cultural History, Eugene, OR", "agency2": "National Park Service, Interior.", "action": "Notice.", "summary": "The University of Oregon Museum of Natural and Cultural History has completed an inventory of human remains and associated funerary objects, in consultation with the appropriate Indian Tribes or Native Hawaiian organizations, and has determined that there is a cultural affiliation between the human remains and associated funerary objects and present-day Indian Tribes or Native Hawaiian organizations. Lineal descendants or representatives of any Indian Tribe or Native Hawaiian organization not identified in this notice that wish to request transfer of control of these human remains and associated funerary objects should submit a written request to the University of Oregon Museum of Natural and Cultural History. If no additional requestors come forward, transfer of control of the human remains and associated funerary objects to the lineal descendants, Indian Tribes, or Native Hawaiian organizations stated in this notice may proceed.", "dates": "Lineal descendants or representatives of any Indian Tribe or Native Hawaiian organization not identified in this notice that wish to request transfer of control of these human remains and associated funerary objects should submit a written request with information in support of the request to the University of Oregon Museum of Natural and Cultural History at the address in this notice by September 4, 2019.", "addresses": "Dr. Pamela Endzweig, Director of Collections, Museum of Natural and Cultural History, 1224 University of Oregon, Eugene, OR 97403-1224, telephone (541) 346-5120, email endzweig@uoregon.edu.", "signature_dated": "Dated: July 9, 2019.", "signature_name": "Melanie O\\'Brien,", "signature_title": "Manager, National NAGPRA Program.", "fr_doc": "[FR Doc. 2019-16679 Filed 8-2-19; 8:45 am]", "billing_code": "BILLING CODE 4312-52-P", "supp_info": "SUPPLEMENTARY INFORMATION: \n Notice is here given in accordance with the Native American Graves Protection and Repatriation Act (NAGPRA), 25 U.S.C. 3003, of the completion of an inventory of human remains and associated funerary objects under the control of the University of Oregon Museum of Natural and Cultural History, Eugene, OR. The human remains and associated funerary object were removed from Purdy Mound at Bob Creek, Lane County, OR. \n This notice is published as part of the National Park Service\\'s administrative responsibilities under NAGPRA, 25 U.S.C. 3003(d)(3). The determinations in this notice are the sole responsibility of the museum, institution, or Federal agency that has control of the Native American human remains and associated funerary objects. The National Park Service is not responsible for the determinations in this notice. \n Consultation \n A detailed assessment of the human remains was made by the University of Oregon Museum of Natural and Cultural History professional staff in consultation with representatives of the Confederated Tribes of Siletz Indians of Oregon (previously listed as the Confederated Tribes of the Siletz Reservation); Confederated Tribes of the Coos, Lower Umpqua and Siuslaw Indians; Confederated Tribes of the Grand Ronde Community of Oregon; and the Coquille Indian Tribe (previously listed as the Coquille Tribe of Oregon), hereafter referred to as \\xe2\\x80\\x9cThe Consulted Tribes.\\xe2\\x80\\x9d \n History and Description of the Remains \n In 1950, human remains representing, at minimum, one individual were removed from Purdy Mound at Bob Creek in Lane County, OR. The human remains were removed by a private party and were donated to the museum in 1950 (acc. # 100LC). They belong to an adult male (cat. # 11-262). No known individuals were identified. The two associated funerary objects are one partial bone club and fragments of one elk maxillary. \n The human remains are reasonably believed to be of Native American ancestry based on their archeological context. Historical documents, ethnographic sources, and oral history indicate that the Bob Creek site lies near the territorial boundary between the Alsea and the Siuslaw peoples. Both cultural groups have occupied the region since pre-contact times. Based on information obtained through consultation, the human remains are identified as Alsea. The Alsea are members or the Confederated Tribes of Siletz Indians of Oregon. \n Determinations Made by the University of Oregon Museum of Natural and Cultural History \n Officials of the University of Oregon Museum of Natural and Cultural History have determined that: \n \\xe2\\x80\\xa2 Pursuant to 25 U.S.C. 3001(9), the human remains described in this notice represent the physical remains of one individual of Native American ancestry. \n \\xe2\\x80\\xa2 Pursuant to 25 U.S.C. 3001(3)(A), the two objects described in this notice are reasonably believed to have been placed with or near individual human remains at the time of death or later as part of the death rite or ceremony. \n \\xe2\\x80\\xa2 Pursuant to 25 U.S.C. 3001(2), there is a relationship of shared group identity that can be reasonably traced between the Native American human remains and associated funerary objects and the Confederated Tribes of Siletz Indians of Oregon (previously listed as the Confederated Tribes of the Siletz Reservation). \n Additional Requestors and Disposition \n Lineal descendants or representatives of any Indian Tribe or Native Hawaiian organization not identified in this notice that wish to request transfer of control of these human remains and associated funerary objects should submit a written request with information in support of the request to Dr. Pamela Endzweig, Director of Collections, Museum of Natural and Cultural History, 1224 University of Oregon, Eugene, OR 97403-1224, telephone (541) 346-5120, email endzweig@uoregon.edu, by September 4, 2019. After that date, if no additional requestors have come forward, transfer of control of the human remains and associated funerary objects to the Confederated Tribes of Siletz Indians of Oregon (previously listed as the Confederated Tribes of the Siletz Reservation) may proceed. \n The University of Oregon Museum of Natural and Cultural History is responsible for notifying The Consulted Tribes that this notice has been published. \n ", "consultation": "A detailed assessment of the human remains was made by the University of Oregon Museum of Natural and Cultural History professional staff in consultation with representatives of the Confederated Tribes of Siletz Indians of Oregon (previously listed as the Confederated Tribes of the Siletz Reservation); Confederated Tribes of the Coos, Lower Umpqua and Siuslaw Indians; Confederated Tribes of the Grand Ronde Community of Oregon; and the Coquille Indian Tribe (previously listed as the Coquille Tribe of Oregon), hereafter referred to as \\xe2\\x80\\x9cThe Consulted Tribes.\\xe2\\x80\\x9d \n ", "h_d_r": "In 1950, human remains representing, at minimum, one individual were removed from Purdy Mound at Bob Creek in Lane County, OR. The human remains were removed by a private party and were donated to the museum in 1950 (acc. # 100LC). They belong to an adult male (cat. # 11-262). No known individuals were identified. The two associated funerary objects are one partial bone club and fragments of one elk maxillary. \n The human remains are reasonably believed to be of Native American ancestry based on their archeological context. Historical documents, ethnographic sources, and oral history indicate that the Bob Creek site lies near the territorial boundary between the Alsea and the Siuslaw peoples. Both cultural groups have occupied the region since pre-contact times. Based on information obtained through consultation, the human remains are identified as Alsea. The Alsea are members or the Confederated Tribes of Siletz Indians of Oregon. \n ", "h_d_ci": "Null", "determinations": "Determinations Made by the University of Oregon Museum of Natural and Cultural History \n Officials of the University of Oregon Museum of Natural and Cultural History have determined that: \n \\xe2\\x80\\xa2 Pursuant to 25 U.S.C. 3001(9), the human remains described in this notice represent the physical remains of one individual of Native American ancestry. \n \\xe2\\x80\\xa2 Pursuant to 25 U.S.C. 3001(3)(A), the two objects described in this notice are reasonably believed to have been placed with or near individual human remains at the time of death or later as part of the death rite or ceremony. \n \\xe2\\x80\\xa2 Pursuant to 25 U.S.C. 3001(2), there is a relationship of shared group identity that can be reasonably traced between the Native American human remains and associated funerary objects and the Confederated Tribes of Siletz Indians of Oregon (previously listed as the Confederated Tribes of the Siletz Reservation). \n ", "a_r_d": "Lineal descendants or representatives of any Indian Tribe or Native Hawaiian organization not identified in this notice that wish to request transfer of control of these human remains and associated funerary objects should submit a written request with information in support of the request to Dr. Pamela Endzweig, Director of Collections, Museum of Natural and Cultural History, 1224 University of Oregon, Eugene, OR 97403-1224, telephone (541) 346-5120, email endzweig@uoregon.edu, by September 4, 2019. After that date, if no additional requestors have come forward, transfer of control of the human remains and associated funerary objects to the Confederated Tribes of Siletz Indians of Oregon (previously listed as the Confederated Tribes of the Siletz Reservation) may proceed. \n The University of Oregon Museum of Natural and Cultural History is responsible for notifying The Consulted Tribes that this notice has been published. \n "}