{"index": "I_471", "messy_full": "\\n      \\n        DEPARTMENT OF THE INTERIOR\\n        National Park Service\\n        [NPS-WASO-NAGPRA-22736; PPWOCRADN0-PCU00RP14.R50000]\\n        Notice of Inventory Completion: Peabody Museum of Natural History, Yale University, New Haven, CT\\n        \\n          AGENCY:\\n          National Park Service, Interior.\\n        \\n        \\n          ACTION:\\n          Notice.\\n        \\n        \\n          SUMMARY:\\n          The Peabody Museum of Natural History has completed an inventory of human remains, in consultation with the appropriate Indian tribes or Native Hawaiian organizations, and has determined that there is a cultural affiliation between the human remains and present-day Indian tribes or Native Hawaiian organizations. Lineal descendants or representatives of any Indian tribe or Native Hawaiian organization not identified in this notice that wish to request transfer of control of these human remains should submit a written request to the Peabody Museum of Natural History. If no additional requestors come forward, transfer of control of the human remains to the lineal descendants, Indian tribes, or Native Hawaiian organizations stated in this notice may proceed.\\n        \\n        \\n          DATES:\\n          Lineal descendants or representatives of any Indian tribe or Native Hawaiian organization not identified in this notice that wish to request transfer of control of these human remains should submit a written request with information in support of the request to the Peabody Museum of Natural History at the address in this notice by March 27, 2017.\\n        \\n        \\n          ADDRESSES:\\n          Professor David Skelly, Director, Yale Peabody Museum of Natural History, P.O. Box 208118, New Haven, CT 06520-8118, telephone (203) 432-3752.\\n        \\n      \\n      \\n        SUPPLEMENTARY INFORMATION:\\n        Notice is here given in accordance with the Native American Graves Protection and Repatriation Act (NAGPRA), 25 U.S.C. 3003, of the completion of an inventory of human remains under the control of the Peabody Museum of Natural History, Yale University, New Haven, CT. The human remains were removed from a site near the Little Medicine Bow River in the Freeze Out Hills, Carbon County, WY.\\n        This notice is published as part of the National Park Service\\'s administrative responsibilities under NAGPRA, 25 U.S.C. 3003(d)(3). The determinations in this notice are the sole responsibility of the museum, institution, or Federal agency that has control of the Native American human remains. The National Park Service is not responsible for the determinations in this notice.\\n        Consultation\\n        A detailed assessment of the human remains was made by the Peabody Museum of Natural History professional staff in consultation with representatives of the Arapaho Tribe of the Wind River Reservation, Wyoming and Cheyenne and Arapaho Tribes, Oklahoma (previously listed as the Cheyenne-Arapaho Tribes of Oklahoma).\\n        History and Description of the Remains\\n        Around 1883, human remains representing, at minimum, three individuals were removed from a site near the Little Medicine Bow River in the Freeze Out Hills in Carbon County, WY, and donated to the Peabody Museum of Natural History in 1925. The human remains represent one adult of indeterminate sex, aged 40-50 years; one adult female, aged 25-35 years; and one subadult, probable female, aged 15-18 years. No known individuals were identified. No associated funerary objects are present.\\n        According to historical documentation, an Arapaho village near the Little Medicine Bow River was attacked in 1846 and the villagers were massacred by a group of trappers from the American and Northwest Fur Companies in retribution for an earlier attack on a wagon train. Around 1883, the site was visited and human remains were removed.\\n        Determinations Made by the Peabody Museum of Natural History\\n        Officials of the Peabody Museum of Natural History have determined that:\\n        \\xe2\\x80\\xa2 Pursuant to 25 U.S.C. 3001(9), the human remains described in this notice represent the physical remains of three individuals of Native American ancestry.\\n        \\xe2\\x80\\xa2 Pursuant to 25 U.S.C. 3001(2), there is a relationship of shared group identity that can be reasonably traced between the Native American human remains and the Arapaho Tribe of the Wind River Reservation, Wyoming, and Cheyenne and Arapaho Tribes, Oklahoma (previously listed as the Cheyenne-Arapaho Tribes of Oklahoma).\\n        Additional Requestors and Disposition\\n        Lineal descendants or representatives of any Indian tribe or Native Hawaiian organization not identified in this notice that wish to request transfer of control of these human remains should submit a written request with information in support of the request to Professor David Skelly, Director, Yale Peabody Museum of Natural History, P.O. Box 208118, New Haven, CT 06520-8118, telephone (203) 432-3752, by March 27, 2017. After that date, if no additional requestors have come forward, transfer of control of the human remains to the Arapaho Tribe of the Wind River Reservation, Wyoming, and Cheyenne and Arapaho Tribes, Oklahoma (previously listed as the Cheyenne-Arapaho Tribes of Oklahoma), may proceed.\\n        The Peabody Museum of Natural History is responsible for notifying the Arapaho Tribe of the Wind River Reservation, Wyoming, and Cheyenne and Arapaho Tribes, Oklahoma (previously listed as the Cheyenne-Arapaho Tribes of Oklahoma), that this notice has been published.\\n        \\n          Dated: January 11, 2017.\\n          Melanie O\\'Brien,\\n          Manager, National NAGPRA Program. \\n        \\n      \\n      [FR Doc. 2017-03636 Filed 2-23-17; 8:45 am]\\n       BILLING CODE 4312-52-P\\n    ", "agency1": "DEPARTMENT OF THE INTERIOR", "sub_agency1": "National Park Service", "dep_doc": "[NPS-WASO-NAGPRA-22736; PPWOCRADN0-PCU00RP14.R50000]", "subject": "Notice of Inventory Completion: Peabody Museum of Natural History, Yale University, New Haven, CT", "agency2": "National Park Service, Interior.", "action": "Notice.", "summary": "The Peabody Museum of Natural History has completed an inventory of human remains, in consultation with the appropriate Indian tribes or Native Hawaiian organizations, and has determined that there is a cultural affiliation between the human remains and present-day Indian tribes or Native Hawaiian organizations. Lineal descendants or representatives of any Indian tribe or Native Hawaiian organization not identified in this notice that wish to request transfer of control of these human remains should submit a written request to the Peabody Museum of Natural History. If no additional requestors come forward, transfer of control of the human remains to the lineal descendants, Indian tribes, or Native Hawaiian organizations stated in this notice may proceed.", "dates": "Lineal descendants or representatives of any Indian tribe or Native Hawaiian organization not identified in this notice that wish to request transfer of control of these human remains should submit a written request with information in support of the request to the Peabody Museum of Natural History at the address in this notice by March 27, 2017.", "addresses": "Professor David Skelly, Director, Yale Peabody Museum of Natural History, P.O. Box 208118, New Haven, CT 06520-8118, telephone (203) 432-3752.", "signature_dated": "Dated: January 11, 2017.", "signature_name": "Melanie O\\'Brien,", "signature_title": "Manager, National NAGPRA Program. ", "fr_doc": "[FR Doc. 2017-03636 Filed 2-23-17; 8:45 am]", "billing_code": " BILLING CODE 4312-52-P", "supp_info": "SUPPLEMENTARY INFORMATION: \n Notice is here given in accordance with the Native American Graves Protection and Repatriation Act (NAGPRA), 25 U.S.C. 3003, of the completion of an inventory of human remains under the control of the Peabody Museum of Natural History, Yale University, New Haven, CT. The human remains were removed from a site near the Little Medicine Bow River in the Freeze Out Hills, Carbon County, WY. \n This notice is published as part of the National Park Service\\'s administrative responsibilities under NAGPRA, 25 U.S.C. 3003(d)(3). The determinations in this notice are the sole responsibility of the museum, institution, or Federal agency that has control of the Native American human remains. The National Park Service is not responsible for the determinations in this notice. \n Consultation \n A detailed assessment of the human remains was made by the Peabody Museum of Natural History professional staff in consultation with representatives of the Arapaho Tribe of the Wind River Reservation, Wyoming and Cheyenne and Arapaho Tribes, Oklahoma (previously listed as the Cheyenne-Arapaho Tribes of Oklahoma). \n History and Description of the Remains \n Around 1883, human remains representing, at minimum, three individuals were removed from a site near the Little Medicine Bow River in the Freeze Out Hills in Carbon County, WY, and donated to the Peabody Museum of Natural History in 1925. The human remains represent one adult of indeterminate sex, aged 40-50 years; one adult female, aged 25-35 years; and one subadult, probable female, aged 15-18 years. No known individuals were identified. No associated funerary objects are present. \n According to historical documentation, an Arapaho village near the Little Medicine Bow River was attacked in 1846 and the villagers were massacred by a group of trappers from the American and Northwest Fur Companies in retribution for an earlier attack on a wagon train. Around 1883, the site was visited and human remains were removed. \n Determinations Made by the Peabody Museum of Natural History \n Officials of the Peabody Museum of Natural History have determined that: \n \\xe2\\x80\\xa2 Pursuant to 25 U.S.C. 3001(9), the human remains described in this notice represent the physical remains of three individuals of Native American ancestry. \n \\xe2\\x80\\xa2 Pursuant to 25 U.S.C. 3001(2), there is a relationship of shared group identity that can be reasonably traced between the Native American human remains and the Arapaho Tribe of the Wind River Reservation, Wyoming, and Cheyenne and Arapaho Tribes, Oklahoma (previously listed as the Cheyenne-Arapaho Tribes of Oklahoma). \n Additional Requestors and Disposition \n Lineal descendants or representatives of any Indian tribe or Native Hawaiian organization not identified in this notice that wish to request transfer of control of these human remains should submit a written request with information in support of the request to Professor David Skelly, Director, Yale Peabody Museum of Natural History, P.O. Box 208118, New Haven, CT 06520-8118, telephone (203) 432-3752, by March 27, 2017. After that date, if no additional requestors have come forward, transfer of control of the human remains to the Arapaho Tribe of the Wind River Reservation, Wyoming, and Cheyenne and Arapaho Tribes, Oklahoma (previously listed as the Cheyenne-Arapaho Tribes of Oklahoma), may proceed. \n The Peabody Museum of Natural History is responsible for notifying the Arapaho Tribe of the Wind River Reservation, Wyoming, and Cheyenne and Arapaho Tribes, Oklahoma (previously listed as the Cheyenne-Arapaho Tribes of Oklahoma), that this notice has been published. \n ", "consultation": "A detailed assessment of the human remains was made by the Peabody Museum of Natural History professional staff in consultation with representatives of the Arapaho Tribe of the Wind River Reservation, Wyoming and Cheyenne and Arapaho Tribes, Oklahoma (previously listed as the Cheyenne-Arapaho Tribes of Oklahoma). \n ", "h_d_r": "Around 1883, human remains representing, at minimum, three individuals were removed from a site near the Little Medicine Bow River in the Freeze Out Hills in Carbon County, WY, and donated to the Peabody Museum of Natural History in 1925. The human remains represent one adult of indeterminate sex, aged 40-50 years; one adult female, aged 25-35 years; and one subadult, probable female, aged 15-18 years. No known individuals were identified. No associated funerary objects are present. \n According to historical documentation, an Arapaho village near the Little Medicine Bow River was attacked in 1846 and the villagers were massacred by a group of trappers from the American and Northwest Fur Companies in retribution for an earlier attack on a wagon train. Around 1883, the site was visited and human remains were removed. \n ", "h_d_ci": "Null", "determinations": "Determinations Made by the Peabody Museum of Natural History \n Officials of the Peabody Museum of Natural History have determined that: \n \\xe2\\x80\\xa2 Pursuant to 25 U.S.C. 3001(9), the human remains described in this notice represent the physical remains of three individuals of Native American ancestry. \n \\xe2\\x80\\xa2 Pursuant to 25 U.S.C. 3001(2), there is a relationship of shared group identity that can be reasonably traced between the Native American human remains and the Arapaho Tribe of the Wind River Reservation, Wyoming, and Cheyenne and Arapaho Tribes, Oklahoma (previously listed as the Cheyenne-Arapaho Tribes of Oklahoma). \n ", "a_r_d": "Lineal descendants or representatives of any Indian tribe or Native Hawaiian organization not identified in this notice that wish to request transfer of control of these human remains should submit a written request with information in support of the request to Professor David Skelly, Director, Yale Peabody Museum of Natural History, P.O. Box 208118, New Haven, CT 06520-8118, telephone (203) 432-3752, by March 27, 2017. After that date, if no additional requestors have come forward, transfer of control of the human remains to the Arapaho Tribe of the Wind River Reservation, Wyoming, and Cheyenne and Arapaho Tribes, Oklahoma (previously listed as the Cheyenne-Arapaho Tribes of Oklahoma), may proceed. \n The Peabody Museum of Natural History is responsible for notifying the Arapaho Tribe of the Wind River Reservation, Wyoming, and Cheyenne and Arapaho Tribes, Oklahoma (previously listed as the Cheyenne-Arapaho Tribes of Oklahoma), that this notice has been published. \n "}