{"index": "I_479", "messy_full": "\\n      \\n        DEPARTMENT OF THE INTERIOR\\n        National Park Service\\n        [NPS-WASO-NAGPRA-22506; PPWOCRADN0-PCU00RP14.R50000]\\n        Notice of Inventory Completion: Office of the State Archaeologist, University of Iowa, Iowa City, IA\\n        \\n          AGENCY:\\n          National Park Service, Interior.\\n        \\n        \\n          ACTION:\\n          Notice.\\n        \\n        \\n          SUMMARY:\\n          The University of Iowa Office of the State Archaeologist Bioarchaeology Program has completed an inventory of human remains, in consultation with the appropriate Indian tribes or Native Hawaiian organizations, and has determined that there is a cultural affiliation between the human remains and present-day Indian tribes or Native Hawaiian organizations. Lineal descendants or representatives of any Indian tribe or Native Hawaiian organization not identified in this notice that wish to request transfer of control of these human remains should submit a written request to the University of Iowa Office of the State Archaeologist Bioarchaeology Program. If no additional requestors come forward, transfer of control of the human remains to the lineal descendants, Indian tribes, or Native Hawaiian organizations stated in this notice may proceed.\\n        \\n        \\n          DATES:\\n          Lineal descendants or representatives of any Indian tribe or Native Hawaiian organization not identified in this notice that wish to request transfer of control of these human remains should submit a written request with information in support of the request to the University of Iowa Office of the State Archaeologist Bioarchaeology Program, at the address in this notice by January 17, 2017.\\n        \\n        \\n          ADDRESSES:\\n\\n          Dr. Lara Noldner, Office of the State Archaeologist Bioarchaeology Program, University of Iowa, 700 S Clinton Street, Iowa City, IA 52242, telephone (319) 384-0740, email lara-noldner@uiowa.edu.\\n          \\n        \\n      \\n      \\n        SUPPLEMENTARY INFORMATION:\\n        Notice is here given in accordance with the Native American Graves Protection and Repatriation Act (NAGPRA), 25 U.S.C. 3003, of the completion of an inventory of human remains under the control of the University of Iowa Office of the State Archaeologist Bioarchaeology Program, Iowa City, IA. The human remains were removed from Woodbury County, IA.\\n        This notice is published as part of the National Park Service\\'s administrative responsibilities under NAGPRA, 25 U.S.C. 3003(d)(3). The determinations in this notice are the sole responsibility of the museum, institution, or Federal agency that has control of the Native American human remains. The National Park Service is not responsible for the determinations in this notice.\\n        Consultation\\n        A detailed assessment of the human remains was made by the University of Iowa Office of the State Archaeologist Bioarchaeology Program professional staff in consultation with representatives of the Assiniboine and Sioux Tribes of the Fort Peck Indian Reservation, Montana; Cheyenne River Sioux Tribe of the Cheyenne River Reservation, South Dakota; Crow Creek Sioux Tribe of the Crow Creek Reservation, South Dakota; Flandreau Santee Sioux Tribe of South Dakota; Lower Brule Sioux Tribe of the Lower Brule Reservation; Lower Sioux Indian Community in the State of Minnesota; Oglala Sioux Tribe; Rosebud Sioux Tribe of the Rosebud Indian Reservation; Santee Sioux Nation, Nebraska; Sisseton-Wahpeton Oyate of the Lake Traverse Reservation, South Dakota; Spirit Lake Tribe; Standing Rock Sioux Tribe; Upper Sioux Community, Minnesota; and the Yankton Sioux Tribe.\\n        History and Description of the Remains\\n        In 1988, human remains representing, at minimum, one individual were removed from the site of the War Eagle Monument (13WD69) in Woodbury County, IA, prior to the monument\\'s relocation. In 1988, erosion caused human remains to be exposed along the upper edge of the bluff. These remains were recovered by personnel from the Office of the State Archaeologist (OSA) and were transferred to the OSA Bioarchaeology Program. An adult of indeterminate age, possibly female, is represented by the lower limb bones (Burial Projects 266 and 648). No known individuals were identified. No associated funerary objects are present.\\n        The number of burials in the vicinity of the War Eagle Monument is unknown. According to various accounts, War Eagle, a Sioux chief, and at least two of his daughters were buried on the bluff. Additionally, some of War Eagle\\'s grandchildren and at least four Euro-American settlers are believed to have been buried in the area. While identification of the individual cannot be determined, based on archival information, the remains represent a Sioux individual.\\n        Determinations Made by the University of Iowa Office of the State Archaeologist Bioarchaeology Program\\n        Officials of the University of Iowa Office of the State Archaeologist Bioarchaeology Program have determined that:\\n        \\xe2\\x80\\xa2 Pursuant to 25 U.S.C. 3001(9), the human remains described in this notice represent the physical remains of one individual of Native American ancestry.\\n        \\xe2\\x80\\xa2 Pursuant to 25 U.S.C. 3001(2), there is a relationship of shared group identity that can be reasonably traced between the Native American human remains and the Assiniboine and Sioux Tribes of the Fort Peck Indian Reservation, Montana; Cheyenne River Sioux Tribe of the Cheyenne River Reservation, South Dakota; Crow Creek Sioux Tribe of the Crow Creek Reservation, South Dakota; Flandreau Santee Sioux Tribe of South Dakota; Lower Brule Sioux Tribe of the Lower Brule Reservation; Lower Sioux Indian Community in the State of Minnesota; Oglala Sioux Tribe; Rosebud Sioux Tribe of the Rosebud Indian Reservation; Santee Sioux Nation, Nebraska; Sisseton-Wahpeton Oyate of the Lake Traverse Reservation, South Dakota; Spirit Lake Tribe; Standing Rock Sioux Tribe; Upper Sioux Community, Minnesota; and the Yankton Sioux Tribe.\\n        Additional Requestors and Disposition\\n\\n        Lineal descendants or representatives of any Indian tribe or Native Hawaiian organization not identified in this notice that wish to request transfer of control of these human remains should submit a written request with information in support of the request to Dr. Lara Noldner, Office of the State Archaeologist Bioarchaeology Program, University of Iowa, 700 S Clinton Street, Iowa City, IA 52242, telephone (319) 384-0740, email lara-noldner@uiowa.edu, by January 17, 2017. After that date, if no additional requestors have come forward, transfer of control of the human remains to the Assiniboine and Sioux Tribes of the Fort Peck Indian Reservation, Montana; Cheyenne River Sioux Tribe of the Cheyenne River Reservation, South Dakota; Crow Creek Sioux Tribe of the Crow Creek Reservation, South Dakota; Flandreau Santee Sioux Tribe of South Dakota; Lower Brule Sioux Tribe of the Lower Brule Reservation; Lower Sioux Indian Community in the State of Minnesota; Oglala Sioux Tribe; Rosebud Sioux Tribe of the Rosebud Indian Reservation; Santee Sioux Nation, Nebraska; Sisseton-Wahpeton Oyate of the Lake Traverse Reservation, South Dakota; Spirit Lake Tribe; Standing Rock Sioux Tribe; Upper Sioux Community, Minnesota; and the Yankton Sioux Tribe may proceed.\\n        The University of Iowa Office of the State Archaeologist Bioarchaeology Program is responsible for notifying the Assiniboine and Sioux Tribes of the Fort Peck Indian Reservation, Montana; Cheyenne River Sioux Tribe of the Cheyenne River Reservation, South Dakota; Crow Creek Sioux Tribe of the Crow Creek Reservation, South Dakota; Flandreau Santee Sioux Tribe of South Dakota; Lower Brule Sioux Tribe of the Lower Brule Reservation; Lower Sioux Indian Community in the State of Minnesota; Oglala Sioux Tribe; Rosebud Sioux Tribe of the Rosebud Indian Reservation; Santee Sioux Nation, Nebraska; Sisseton-Wahpeton Oyate of the Lake Traverse Reservation, South Dakota; Spirit Lake Tribe; Standing Rock Sioux Tribe; Upper Sioux Community, Minnesota; and the Yankton Sioux Tribe that this notice has been published.\\n        \\n          Dated: December 1, 2016.\\n          Melanie O\\'Brien,\\n          Manager, National NAGPRA Program. \\n        \\n      \\n      [FR Doc. 2016-30339 Filed 12-15-16; 8:45 am]\\n       BILLING CODE 4312-52-P\\n    ", "agency1": "DEPARTMENT OF THE INTERIOR", "sub_agency1": "National Park Service", "dep_doc": "[NPS-WASO-NAGPRA-22506; PPWOCRADN0-PCU00RP14.R50000]", "subject": "Notice of Inventory Completion: Office of the State Archaeologist, University of Iowa, Iowa City, IA", "agency2": "National Park Service, Interior.", "action": "Notice.", "summary": "The University of Iowa Office of the State Archaeologist Bioarchaeology Program has completed an inventory of human remains, in consultation with the appropriate Indian tribes or Native Hawaiian organizations, and has determined that there is a cultural affiliation between the human remains and present-day Indian tribes or Native Hawaiian organizations. Lineal descendants or representatives of any Indian tribe or Native Hawaiian organization not identified in this notice that wish to request transfer of control of these human remains should submit a written request to the University of Iowa Office of the State Archaeologist Bioarchaeology Program. If no additional requestors come forward, transfer of control of the human remains to the lineal descendants, Indian tribes, or Native Hawaiian organizations stated in this notice may proceed.", "dates": "Lineal descendants or representatives of any Indian tribe or Native Hawaiian organization not identified in this notice that wish to request transfer of control of these human remains should submit a written request with information in support of the request to the University of Iowa Office of the State Archaeologist Bioarchaeology Program, at the address in this notice by January 17, 2017.", "addresses": "Dr. Lara Noldner, Office of the State Archaeologist Bioarchaeology Program, University of Iowa, 700 S Clinton Street, Iowa City, IA 52242, telephone (319) 384-0740, email lara-noldner@uiowa.edu.\\n          ", "signature_dated": "Dated: December 1, 2016.", "signature_name": "Melanie O\\'Brien,", "signature_title": "Manager, National NAGPRA Program. ", "fr_doc": "[FR Doc. 2016-30339 Filed 12-15-16; 8:45 am]", "billing_code": " BILLING CODE 4312-52-P", "supp_info": "SUPPLEMENTARY INFORMATION: \n Notice is here given in accordance with the Native American Graves Protection and Repatriation Act (NAGPRA), 25 U.S.C. 3003, of the completion of an inventory of human remains under the control of the University of Iowa Office of the State Archaeologist Bioarchaeology Program, Iowa City, IA. The human remains were removed from Woodbury County, IA. \n This notice is published as part of the National Park Service\\'s administrative responsibilities under NAGPRA, 25 U.S.C. 3003(d)(3). The determinations in this notice are the sole responsibility of the museum, institution, or Federal agency that has control of the Native American human remains. The National Park Service is not responsible for the determinations in this notice. \n Consultation \n A detailed assessment of the human remains was made by the University of Iowa Office of the State Archaeologist Bioarchaeology Program professional staff in consultation with representatives of the Assiniboine and Sioux Tribes of the Fort Peck Indian Reservation, Montana; Cheyenne River Sioux Tribe of the Cheyenne River Reservation, South Dakota; Crow Creek Sioux Tribe of the Crow Creek Reservation, South Dakota; Flandreau Santee Sioux Tribe of South Dakota; Lower Brule Sioux Tribe of the Lower Brule Reservation; Lower Sioux Indian Community in the State of Minnesota; Oglala Sioux Tribe; Rosebud Sioux Tribe of the Rosebud Indian Reservation; Santee Sioux Nation, Nebraska; Sisseton-Wahpeton Oyate of the Lake Traverse Reservation, South Dakota; Spirit Lake Tribe; Standing Rock Sioux Tribe; Upper Sioux Community, Minnesota; and the Yankton Sioux Tribe. \n History and Description of the Remains \n In 1988, human remains representing, at minimum, one individual were removed from the site of the War Eagle Monument (13WD69) in Woodbury County, IA, prior to the monument\\'s relocation. In 1988, erosion caused human remains to be exposed along the upper edge of the bluff. These remains were recovered by personnel from the Office of the State Archaeologist (OSA) and were transferred to the OSA Bioarchaeology Program. An adult of indeterminate age, possibly female, is represented by the lower limb bones (Burial Projects 266 and 648). No known individuals were identified. No associated funerary objects are present. \n The number of burials in the vicinity of the War Eagle Monument is unknown. According to various accounts, War Eagle, a Sioux chief, and at least two of his daughters were buried on the bluff. Additionally, some of War Eagle\\'s grandchildren and at least four Euro-American settlers are believed to have been buried in the area. While identification of the individual cannot be determined, based on archival information, the remains represent a Sioux individual. \n Determinations Made by the University of Iowa Office of the State Archaeologist Bioarchaeology Program \n Officials of the University of Iowa Office of the State Archaeologist Bioarchaeology Program have determined that: \n \\xe2\\x80\\xa2 Pursuant to 25 U.S.C. 3001(9), the human remains described in this notice represent the physical remains of one individual of Native American ancestry. \n \\xe2\\x80\\xa2 Pursuant to 25 U.S.C. 3001(2), there is a relationship of shared group identity that can be reasonably traced between the Native American human remains and the Assiniboine and Sioux Tribes of the Fort Peck Indian Reservation, Montana; Cheyenne River Sioux Tribe of the Cheyenne River Reservation, South Dakota; Crow Creek Sioux Tribe of the Crow Creek Reservation, South Dakota; Flandreau Santee Sioux Tribe of South Dakota; Lower Brule Sioux Tribe of the Lower Brule Reservation; Lower Sioux Indian Community in the State of Minnesota; Oglala Sioux Tribe; Rosebud Sioux Tribe of the Rosebud Indian Reservation; Santee Sioux Nation, Nebraska; Sisseton-Wahpeton Oyate of the Lake Traverse Reservation, South Dakota; Spirit Lake Tribe; Standing Rock Sioux Tribe; Upper Sioux Community, Minnesota; and the Yankton Sioux Tribe. \n Additional Requestors and Disposition \n Lineal descendants or representatives of any Indian tribe or Native Hawaiian organization not identified in this notice that wish to request transfer of control of these human remains should submit a written request with information in support of the request to Dr. Lara Noldner, Office of the State Archaeologist Bioarchaeology Program, University of Iowa, 700 S Clinton Street, Iowa City, IA 52242, telephone (319) 384-0740, email lara-noldner@uiowa.edu, by January 17, 2017. After that date, if no additional requestors have come forward, transfer of control of the human remains to the Assiniboine and Sioux Tribes of the Fort Peck Indian Reservation, Montana; Cheyenne River Sioux Tribe of the Cheyenne River Reservation, South Dakota; Crow Creek Sioux Tribe of the Crow Creek Reservation, South Dakota; Flandreau Santee Sioux Tribe of South Dakota; Lower Brule Sioux Tribe of the Lower Brule Reservation; Lower Sioux Indian Community in the State of Minnesota; Oglala Sioux Tribe; Rosebud Sioux Tribe of the Rosebud Indian Reservation; Santee Sioux Nation, Nebraska; Sisseton-Wahpeton Oyate of the Lake Traverse Reservation, South Dakota; Spirit Lake Tribe; Standing Rock Sioux Tribe; Upper Sioux Community, Minnesota; and the Yankton Sioux Tribe may proceed. \n The University of Iowa Office of the State Archaeologist Bioarchaeology Program is responsible for notifying the Assiniboine and Sioux Tribes of the Fort Peck Indian Reservation, Montana; Cheyenne River Sioux Tribe of the Cheyenne River Reservation, South Dakota; Crow Creek Sioux Tribe of the Crow Creek Reservation, South Dakota; Flandreau Santee Sioux Tribe of South Dakota; Lower Brule Sioux Tribe of the Lower Brule Reservation; Lower Sioux Indian Community in the State of Minnesota; Oglala Sioux Tribe; Rosebud Sioux Tribe of the Rosebud Indian Reservation; Santee Sioux Nation, Nebraska; Sisseton-Wahpeton Oyate of the Lake Traverse Reservation, South Dakota; Spirit Lake Tribe; Standing Rock Sioux Tribe; Upper Sioux Community, Minnesota; and the Yankton Sioux Tribe that this notice has been published. \n ", "consultation": "A detailed assessment of the human remains was made by the University of Iowa Office of the State Archaeologist Bioarchaeology Program professional staff in consultation with representatives of the Assiniboine and Sioux Tribes of the Fort Peck Indian Reservation, Montana; Cheyenne River Sioux Tribe of the Cheyenne River Reservation, South Dakota; Crow Creek Sioux Tribe of the Crow Creek Reservation, South Dakota; Flandreau Santee Sioux Tribe of South Dakota; Lower Brule Sioux Tribe of the Lower Brule Reservation; Lower Sioux Indian Community in the State of Minnesota; Oglala Sioux Tribe; Rosebud Sioux Tribe of the Rosebud Indian Reservation; Santee Sioux Nation, Nebraska; Sisseton-Wahpeton Oyate of the Lake Traverse Reservation, South Dakota; Spirit Lake Tribe; Standing Rock Sioux Tribe; Upper Sioux Community, Minnesota; and the Yankton Sioux Tribe. \n ", "h_d_r": "In 1988, human remains representing, at minimum, one individual were removed from the site of the War Eagle Monument (13WD69) in Woodbury County, IA, prior to the monument\\'s relocation. In 1988, erosion caused human remains to be exposed along the upper edge of the bluff. These remains were recovered by personnel from the Office of the State Archaeologist (OSA) and were transferred to the OSA Bioarchaeology Program. An adult of indeterminate age, possibly female, is represented by the lower limb bones (Burial Projects 266 and 648). No known individuals were identified. No associated funerary objects are present. \n The number of burials in the vicinity of the War Eagle Monument is unknown. According to various accounts, War Eagle, a Sioux chief, and at least two of his daughters were buried on the bluff. Additionally, some of War Eagle\\'s grandchildren and at least four Euro-American settlers are believed to have been buried in the area. While identification of the individual cannot be determined, based on archival information, the remains represent a Sioux individual. \n ", "h_d_ci": "Null", "determinations": "Determinations Made by the University of Iowa Office of the State Archaeologist Bioarchaeology Program \n Officials of the University of Iowa Office of the State Archaeologist Bioarchaeology Program have determined that: \n \\xe2\\x80\\xa2 Pursuant to 25 U.S.C. 3001(9), the human remains described in this notice represent the physical remains of one individual of Native American ancestry. \n \\xe2\\x80\\xa2 Pursuant to 25 U.S.C. 3001(2), there is a relationship of shared group identity that can be reasonably traced between the Native American human remains and the Assiniboine and Sioux Tribes of the Fort Peck Indian Reservation, Montana; Cheyenne River Sioux Tribe of the Cheyenne River Reservation, South Dakota; Crow Creek Sioux Tribe of the Crow Creek Reservation, South Dakota; Flandreau Santee Sioux Tribe of South Dakota; Lower Brule Sioux Tribe of the Lower Brule Reservation; Lower Sioux Indian Community in the State of Minnesota; Oglala Sioux Tribe; Rosebud Sioux Tribe of the Rosebud Indian Reservation; Santee Sioux Nation, Nebraska; Sisseton-Wahpeton Oyate of the Lake Traverse Reservation, South Dakota; Spirit Lake Tribe; Standing Rock Sioux Tribe; Upper Sioux Community, Minnesota; and the Yankton Sioux Tribe. \n ", "a_r_d": "Lineal descendants or representatives of any Indian tribe or Native Hawaiian organization not identified in this notice that wish to request transfer of control of these human remains should submit a written request with information in support of the request to Dr. Lara Noldner, Office of the State Archaeologist Bioarchaeology Program, University of Iowa, 700 S Clinton Street, Iowa City, IA 52242, telephone (319) 384-0740, email lara-noldner@uiowa.edu, by January 17, 2017. After that date, if no additional requestors have come forward, transfer of control of the human remains to the Assiniboine and Sioux Tribes of the Fort Peck Indian Reservation, Montana; Cheyenne River Sioux Tribe of the Cheyenne River Reservation, South Dakota; Crow Creek Sioux Tribe of the Crow Creek Reservation, South Dakota; Flandreau Santee Sioux Tribe of South Dakota; Lower Brule Sioux Tribe of the Lower Brule Reservation; Lower Sioux Indian Community in the State of Minnesota; Oglala Sioux Tribe; Rosebud Sioux Tribe of the Rosebud Indian Reservation; Santee Sioux Nation, Nebraska; Sisseton-Wahpeton Oyate of the Lake Traverse Reservation, South Dakota; Spirit Lake Tribe; Standing Rock Sioux Tribe; Upper Sioux Community, Minnesota; and the Yankton Sioux Tribe may proceed. \n The University of Iowa Office of the State Archaeologist Bioarchaeology Program is responsible for notifying the Assiniboine and Sioux Tribes of the Fort Peck Indian Reservation, Montana; Cheyenne River Sioux Tribe of the Cheyenne River Reservation, South Dakota; Crow Creek Sioux Tribe of the Crow Creek Reservation, South Dakota; Flandreau Santee Sioux Tribe of South Dakota; Lower Brule Sioux Tribe of the Lower Brule Reservation; Lower Sioux Indian Community in the State of Minnesota; Oglala Sioux Tribe; Rosebud Sioux Tribe of the Rosebud Indian Reservation; Santee Sioux Nation, Nebraska; Sisseton-Wahpeton Oyate of the Lake Traverse Reservation, South Dakota; Spirit Lake Tribe; Standing Rock Sioux Tribe; Upper Sioux Community, Minnesota; and the Yankton Sioux Tribe that this notice has been published. \n "}