{"index": "I_487", "messy_full": "\\n      \\n        DEPARTMENT OF THE INTERIOR\\n        National Park Service\\n        [NPS-WASO-NAGPRA-22446; PPWOCRADN0-PCU00RP14.R50000]\\n        Notice of Inventory Completion: Peabody Museum of Natural History, Yale University, New Haven, CT\\n        \\n          AGENCY:\\n          National Park Service, Interior.\\n        \\n        \\n          ACTION:\\n          Notice.\\n        \\n        \\n          SUMMARY:\\n          The Peabody Museum of Natural History has completed an inventory of human remains and associated funerary objects, in consultation with the appropriate Indian tribes or Native Hawaiian organizations, and has determined that there is a cultural affiliation between the human remains and associated funerary objects and present-day Indian tribes or Native Hawaiian organizations. Lineal descendants or representatives of any Indian tribe or Native Hawaiian organization not identified in this notice that wish to request transfer of control of these human remains and associated funerary objects should submit a written request to the Peabody Museum of Natural History. If no additional requestors come forward, transfer of control of the human remains and associated funerary objects to the lineal descendants, Indian tribes, or Native Hawaiian organizations stated in this notice may proceed.\\n        \\n        \\n          DATES:\\n          Lineal descendants or representatives of any Indian tribe or Native Hawaiian organization not identified in this notice that wish to request transfer of control of these human remains and associated funerary objects should submit a written request with information in support of the request to the Peabody Museum of Natural History at the address in this notice by January 3, 2017.\\n        \\n        \\n          ADDRESSES:\\n          Professor David Skelly, Director, Yale Peabody Museum of Natural History, P.O. Box 208118, New Haven, CT 06520-8118, telephone (203) 432-3752.\\n        \\n      \\n      \\n        SUPPLEMENTARY INFORMATION:\\n        Notice is here given in accordance with the Native American Graves Protection and Repatriation Act (NAGPRA), 25 U.S.C. 3003, of the completion of an inventory of human remains and associated funerary objects under the control of the Peabody Museum of Natural History, Yale University, New Haven, CT. The human remains and associated funerary objects were removed from Site 16, Chandler Lake, Brooks Range, North Slope Borough, AK.\\n        This notice is published as part of the National Park Service\\'s administrative responsibilities under NAGPRA, 25 U.S.C. 3003(d)(3). The determinations in this notice are the sole responsibility of the museum, institution, or Federal agency that has control of the Native American human remains and associated funerary objects. The National Park Service is not responsible for the determinations in this notice.\\n        Consultation\\n        A detailed assessment of the human remains was made by Peabody Museum of Natural History professional staff in consultation with representatives of the Village of Anaktuvuk Pass.\\n        History and Description of the Remains\\n\\n        In 1956, human remains representing one individual were removed from a Nunamiut burial site identified as Site 16, Chandler Lake, Brooks Range, North Slope Borough, AK and donated to the Peabody Museum of Natural History the same year. The human remains represent one individual identified as a probable male, aged approximately 30-50 years. No known individuals were identified. The 21 associated funerary objects are 3 lots of glass beads, 1 lot of earthen beads, 1 jade pendant, 1 bone implement, 1 iron blade with bone handle, 1 rectangular iron blade, 1 iron implement, 1 metal scissors fragment, 2 iron bracelets, 1 iron wire fragment, 2 iron blades, 2 lots of iron fragments, 1 bone implement fragment, 1 lot of bone fragments, 1 lot of hide fragments, and 1 long bone shaft fragment.\\n        Osteological data as well as the archaeological and geographic contexts identify these human remains as representing an individual of Native American ancestry. A portion of the funerary objects were identified by Campbell as typical of Nunamiut manufacture. The presence of historic trade objects confirms a post-contact date for this burial. The region of Anaktuvuk was, and is, occupied by the Nunamiut people who are today represented by the Village of Anaktuvuk Pass.\\n        Determinations Made by the Peabody Museum of Natural History\\n        Officials of the Peabody Museum of Natural History have determined that:\\n        \\xe2\\x80\\xa2 Pursuant to 25 U.S.C. 3001(9), the human remains described in this notice represent the physical remains of one individual of Native American ancestry.\\n        \\xe2\\x80\\xa2 Pursuant to 25 U.S.C. 3001(3)(A), the 21 objects described in this notice are reasonably believed to have been placed with or near individual human remains at the time of death or later as part of the death rite or ceremony.\\n        \\xe2\\x80\\xa2 Pursuant to 25 U.S.C. 3001(2), there is a relationship of shared group identity that can be reasonably traced between the Native American human remains and associated funerary objects and the Village of Anaktuvuk Pass.\\n        Additional Requestors and Disposition\\n        Lineal descendants or representatives of any Indian tribe or Native Hawaiian organization not identified in this notice that wish to request transfer of control of these human remains and associated funerary objects should submit a written request with information in support of the request to Professor David Skelly, Director, Yale Peabody Museum of Natural History, P.O. Box 208118, New Haven, CT 06520-8118, telephone (203) 432-3752, by January 3, 2017. After that date, if no additional requestors have come forward, transfer of control of the human remains and associated funerary objects to the Village of Anaktuvuk Pass may proceed.\\n        The Peabody Museum of Natural History is responsible for notifying the Village of Anaktuvuk Pass that this notice has been published.\\n        \\n          Dated: November 17, 2016.\\n          Melanie O\\'Brien,\\n          Manager, National NAGPRA Program. \\n        \\n      \\n      [FR Doc. 2016-28951 Filed 12-1-16; 8:45 am]\\n       BILLING CODE 4312-52-P\\n    ", "agency1": "DEPARTMENT OF THE INTERIOR", "sub_agency1": "National Park Service", "dep_doc": "[NPS-WASO-NAGPRA-22446; PPWOCRADN0-PCU00RP14.R50000]", "subject": "Notice of Inventory Completion: Peabody Museum of Natural History, Yale University, New Haven, CT", "agency2": "National Park Service, Interior.", "action": "Notice.", "summary": "The Peabody Museum of Natural History has completed an inventory of human remains and associated funerary objects, in consultation with the appropriate Indian tribes or Native Hawaiian organizations, and has determined that there is a cultural affiliation between the human remains and associated funerary objects and present-day Indian tribes or Native Hawaiian organizations. Lineal descendants or representatives of any Indian tribe or Native Hawaiian organization not identified in this notice that wish to request transfer of control of these human remains and associated funerary objects should submit a written request to the Peabody Museum of Natural History. If no additional requestors come forward, transfer of control of the human remains and associated funerary objects to the lineal descendants, Indian tribes, or Native Hawaiian organizations stated in this notice may proceed.", "dates": "Lineal descendants or representatives of any Indian tribe or Native Hawaiian organization not identified in this notice that wish to request transfer of control of these human remains and associated funerary objects should submit a written request with information in support of the request to the Peabody Museum of Natural History at the address in this notice by January 3, 2017.", "addresses": "Professor David Skelly, Director, Yale Peabody Museum of Natural History, P.O. Box 208118, New Haven, CT 06520-8118, telephone (203) 432-3752.", "signature_dated": "Dated: November 17, 2016.", "signature_name": "Melanie O\\'Brien,", "signature_title": "Manager, National NAGPRA Program. ", "fr_doc": "[FR Doc. 2016-28951 Filed 12-1-16; 8:45 am]", "billing_code": " BILLING CODE 4312-52-P", "supp_info": "SUPPLEMENTARY INFORMATION: \n Notice is here given in accordance with the Native American Graves Protection and Repatriation Act (NAGPRA), 25 U.S.C. 3003, of the completion of an inventory of human remains and associated funerary objects under the control of the Peabody Museum of Natural History, Yale University, New Haven, CT. The human remains and associated funerary objects were removed from Site 16, Chandler Lake, Brooks Range, North Slope Borough, AK. \n This notice is published as part of the National Park Service\\'s administrative responsibilities under NAGPRA, 25 U.S.C. 3003(d)(3). The determinations in this notice are the sole responsibility of the museum, institution, or Federal agency that has control of the Native American human remains and associated funerary objects. The National Park Service is not responsible for the determinations in this notice. \n Consultation \n A detailed assessment of the human remains was made by Peabody Museum of Natural History professional staff in consultation with representatives of the Village of Anaktuvuk Pass. \n History and Description of the Remains \n In 1956, human remains representing one individual were removed from a Nunamiut burial site identified as Site 16, Chandler Lake, Brooks Range, North Slope Borough, AK and donated to the Peabody Museum of Natural History the same year. The human remains represent one individual identified as a probable male, aged approximately 30-50 years. No known individuals were identified. The 21 associated funerary objects are 3 lots of glass beads, 1 lot of earthen beads, 1 jade pendant, 1 bone implement, 1 iron blade with bone handle, 1 rectangular iron blade, 1 iron implement, 1 metal scissors fragment, 2 iron bracelets, 1 iron wire fragment, 2 iron blades, 2 lots of iron fragments, 1 bone implement fragment, 1 lot of bone fragments, 1 lot of hide fragments, and 1 long bone shaft fragment. \n Osteological data as well as the archaeological and geographic contexts identify these human remains as representing an individual of Native American ancestry. A portion of the funerary objects were identified by Campbell as typical of Nunamiut manufacture. The presence of historic trade objects confirms a post-contact date for this burial. The region of Anaktuvuk was, and is, occupied by the Nunamiut people who are today represented by the Village of Anaktuvuk Pass. \n Determinations Made by the Peabody Museum of Natural History \n Officials of the Peabody Museum of Natural History have determined that: \n \\xe2\\x80\\xa2 Pursuant to 25 U.S.C. 3001(9), the human remains described in this notice represent the physical remains of one individual of Native American ancestry. \n \\xe2\\x80\\xa2 Pursuant to 25 U.S.C. 3001(3)(A), the 21 objects described in this notice are reasonably believed to have been placed with or near individual human remains at the time of death or later as part of the death rite or ceremony. \n \\xe2\\x80\\xa2 Pursuant to 25 U.S.C. 3001(2), there is a relationship of shared group identity that can be reasonably traced between the Native American human remains and associated funerary objects and the Village of Anaktuvuk Pass. \n Additional Requestors and Disposition \n Lineal descendants or representatives of any Indian tribe or Native Hawaiian organization not identified in this notice that wish to request transfer of control of these human remains and associated funerary objects should submit a written request with information in support of the request to Professor David Skelly, Director, Yale Peabody Museum of Natural History, P.O. Box 208118, New Haven, CT 06520-8118, telephone (203) 432-3752, by January 3, 2017. After that date, if no additional requestors have come forward, transfer of control of the human remains and associated funerary objects to the Village of Anaktuvuk Pass may proceed. \n The Peabody Museum of Natural History is responsible for notifying the Village of Anaktuvuk Pass that this notice has been published. \n ", "consultation": "A detailed assessment of the human remains was made by Peabody Museum of Natural History professional staff in consultation with representatives of the Village of Anaktuvuk Pass. \n ", "h_d_r": "In 1956, human remains representing one individual were removed from a Nunamiut burial site identified as Site 16, Chandler Lake, Brooks Range, North Slope Borough, AK and donated to the Peabody Museum of Natural History the same year. The human remains represent one individual identified as a probable male, aged approximately 30-50 years. No known individuals were identified. The 21 associated funerary objects are 3 lots of glass beads, 1 lot of earthen beads, 1 jade pendant, 1 bone implement, 1 iron blade with bone handle, 1 rectangular iron blade, 1 iron implement, 1 metal scissors fragment, 2 iron bracelets, 1 iron wire fragment, 2 iron blades, 2 lots of iron fragments, 1 bone implement fragment, 1 lot of bone fragments, 1 lot of hide fragments, and 1 long bone shaft fragment. \n Osteological data as well as the archaeological and geographic contexts identify these human remains as representing an individual of Native American ancestry. A portion of the funerary objects were identified by Campbell as typical of Nunamiut manufacture. The presence of historic trade objects confirms a post-contact date for this burial. The region of Anaktuvuk was, and is, occupied by the Nunamiut people who are today represented by the Village of Anaktuvuk Pass. \n ", "h_d_ci": "Null", "determinations": "Determinations Made by the Peabody Museum of Natural History \n Officials of the Peabody Museum of Natural History have determined that: \n \\xe2\\x80\\xa2 Pursuant to 25 U.S.C. 3001(9), the human remains described in this notice represent the physical remains of one individual of Native American ancestry. \n \\xe2\\x80\\xa2 Pursuant to 25 U.S.C. 3001(3)(A), the 21 objects described in this notice are reasonably believed to have been placed with or near individual human remains at the time of death or later as part of the death rite or ceremony. \n \\xe2\\x80\\xa2 Pursuant to 25 U.S.C. 3001(2), there is a relationship of shared group identity that can be reasonably traced between the Native American human remains and associated funerary objects and the Village of Anaktuvuk Pass. \n ", "a_r_d": "Lineal descendants or representatives of any Indian tribe or Native Hawaiian organization not identified in this notice that wish to request transfer of control of these human remains and associated funerary objects should submit a written request with information in support of the request to Professor David Skelly, Director, Yale Peabody Museum of Natural History, P.O. Box 208118, New Haven, CT 06520-8118, telephone (203) 432-3752, by January 3, 2017. After that date, if no additional requestors have come forward, transfer of control of the human remains and associated funerary objects to the Village of Anaktuvuk Pass may proceed. \n The Peabody Museum of Natural History is responsible for notifying the Village of Anaktuvuk Pass that this notice has been published. \n "}