{"index": "I_488", "messy_full": "\\n      \\n        DEPARTMENT OF THE INTERIOR\\n        National Park Service\\n        [NPS-WASO-NAGPRA-22424; PPWOCRADN0-PCU00RP14.R50000]\\n        Notice of Inventory Completion: U.S. Department of Agriculture, Forest Service, Tongass National Forest, Craig Ranger District, Craig, AK\\n        \\n          AGENCY:\\n          National Park Service, Interior.\\n        \\n        \\n          ACTION:\\n          Notice.\\n        \\n        \\n          SUMMARY:\\n          The U.S. Department of Agriculture, Forest Service (Forest Service) has completed an inventory of human remains and associated funerary objects in consultation with the appropriate Indian tribes or Native Hawaiian organizations, and has determined that there is a cultural affiliation between the human remains and associated funerary objects and present-day Indian tribes or Native Hawaiian organizations. Lineal descendants or representatives of any Indian tribe or Native Hawaiian organization not identified in this notice that wish to request transfer of control of these human remains and associated funerary objects should submit a written request to the Tongass National Forest, Craig Ranger District. If no additional requestors come forward, transfer of control of the human remains and associated funerary objects to the lineal descendants, Indian tribes, or Native Hawaiian organizations stated in this notice may proceed.\\n        \\n        \\n          DATES:\\n          Lineal descendants or representatives of any Indian tribe or Native Hawaiian organization not identified in this notice that wish to request transfer of control of these human remains and associated funerary objects should submit a written request with information in support of the request to the Tongass National Forest at the address in this notice by January 3, 2017.\\n        \\n        \\n          ADDRESSES:\\n\\n          Earl Stewart, Tongass National Forest Supervisor, 648 Mission Street Federal Building, Ketchikan, AK 99901-6591, telephone (907) 225-3101, email estewart@fs.fed.us.\\n          \\n        \\n      \\n      \\n        SUPPLEMENTARY INFORMATION:\\n        Notice is here given in accordance with the Native American Graves Protection and Repatriation Act (NAGPRA), 25 U.S.C. 3003, of the completion of an inventory of human remains and associated funerary objects under the control of the Forest Service, Tongass National Forest, Craig Ranger District. The human remains and associated funerary objects were removed from the Staney Creek area of Prince of Wales Island, AK.\\n        This notice is published as part of the National Park Service\\'s administrative responsibilities under NAGPRA, 25 U.S.C. 3003(d)(3). The determinations in this notice are the sole responsibility of the museum, institution, or Federal agency that has control of the Native American human remains and associated funerary objects. The National Park Service is not responsible for the determinations in this notice.\\n        Consultation\\n\\n        A detailed assessment of the human remains was made by the Forest Service professional staff using details provided from the Canadian Museum of History and in consultation with representatives of Craig Tribal Association (previously listed as the Craig Community Association), Hydaburg Cooperative Association, Klawock Cooperative Association, and the Organized Village of Kasaan.\\n        History and Description of the Remains\\n        In 1973, human remains representing, at minimum, one individual were removed from the Staney Creek area on Prince of Wales Island, AK. The human remains were removed from Forest Service-managed lands by members of the United States Geological Survey, Department of the Interior. In 1974, the human remains were sent to the Canadian Museum of Civilization Corporation for analysis. The analysis indicated the human remains were from 185 to 385 years old. In September of 2014, the Forest Service took possession of the remains and funerary object from the museum and took them to the Craig Ranger District. No known individuals were identified. The one associated funerary object is a piece of wood that was found with the human remains.\\n\\n        Cultural affiliation of the human remains and associated funerary objects was based on multiple lines of evidence, including consultation with the Klawock Cooperative Association and a published source, Haa Aani, Our Land: Tlingit and Haida Land Rights and Use by Walter Goldschmidt and Theodore H. Haas, edited by Thomas F. Thornton, first issued in 1948, reprinted in 1988, by the Sealaska Heritage Association. The human remains were removed from an area defined in Haa Aani and by the tribe as culturally affiliated with the Klawock Cooperative Association.\\n        Determinations Made by the Forest Service, Tongass National Forest\\n        Officials of the Forest Service, Tongass National Forest have determined that:\\n        \\xe2\\x80\\xa2 Pursuant to 25 U.S.C. 3001(9), the human remains described in this notice represent the physical remains of one individual of Native American ancestry.\\n        \\xe2\\x80\\xa2 Pursuant to 25 U.S.C. 3001(3)(A), the one object described in this notice are reasonably believed to have been placed with or near individual human remains at the time of death or later as part of the death rite or ceremony.\\n        \\xe2\\x80\\xa2 Pursuant to 25 U.S.C. 3001(2), there is a relationship of shared group identity that can be reasonably traced between the Native American human remains and associated funerary object and the Klawock Cooperative Association.\\n        Additional Requestors and Disposition\\n\\n        Lineal descendants or representatives of any Indian tribe or Native Hawaiian organization not identified in this notice that wish to request transfer of control of these human remains and associated funerary objects should submit a written request with information in support of the request to Tongass National Forest Supervisor Earl Stewart, 648 Mission Street Federal Building, Ketchikan, AK 99901-6591, phone number (907) 225-3101, email estewart@fs.fed.us, by January 3, 2017. After that date, if no additional requestors have come forward, transfer of control of the human remains and associated funerary objects to Klawock Cooperative Association may proceed.\\n        The Forest Service is responsible for notifying the Craig Tribal Association (previously listed as the Craig Community Association), Klawock Cooperative Association, Hydaburg Cooperative Association, and the Organized Village of Kasaan that this notice has been published.\\n        \\n          Melanie O\\'Brien,\\n          Manager, National NAGPRA Program\\n        \\n      \\n      [FR Doc. 2016-28958 Filed 12-1-16; 8:45 am]\\n       BILLING CODE 4312-52-P\\n    ", "agency1": "DEPARTMENT OF THE INTERIOR", "sub_agency1": "National Park Service", "dep_doc": "[NPS-WASO-NAGPRA-22424; PPWOCRADN0-PCU00RP14.R50000]", "subject": "Notice of Inventory Completion: U.S. Department of Agriculture, Forest Service, Tongass National Forest, Craig Ranger District, Craig, AK", "agency2": "National Park Service, Interior.", "action": "Notice.", "summary": "The U.S. Department of Agriculture, Forest Service (Forest Service) has completed an inventory of human remains and associated funerary objects in consultation with the appropriate Indian tribes or Native Hawaiian organizations, and has determined that there is a cultural affiliation between the human remains and associated funerary objects and present-day Indian tribes or Native Hawaiian organizations. Lineal descendants or representatives of any Indian tribe or Native Hawaiian organization not identified in this notice that wish to request transfer of control of these human remains and associated funerary objects should submit a written request to the Tongass National Forest, Craig Ranger District. If no additional requestors come forward, transfer of control of the human remains and associated funerary objects to the lineal descendants, Indian tribes, or Native Hawaiian organizations stated in this notice may proceed.", "dates": "Lineal descendants or representatives of any Indian tribe or Native Hawaiian organization not identified in this notice that wish to request transfer of control of these human remains and associated funerary objects should submit a written request with information in support of the request to the Tongass National Forest at the address in this notice by January 3, 2017.", "addresses": "Earl Stewart, Tongass National Forest Supervisor, 648 Mission Street Federal Building, Ketchikan, AK 99901-6591, telephone (907) 225-3101, email estewart@fs.fed.us.\\n          ", "signature_dated": "Null", "signature_name": "Melanie O\\'Brien,", "signature_title": "Manager, National NAGPRA Program", "fr_doc": "[FR Doc. 2016-28958 Filed 12-1-16; 8:45 am]", "billing_code": " BILLING CODE 4312-52-P", "supp_info": "SUPPLEMENTARY INFORMATION: \n Notice is here given in accordance with the Native American Graves Protection and Repatriation Act (NAGPRA), 25 U.S.C. 3003, of the completion of an inventory of human remains and associated funerary objects under the control of the Forest Service, Tongass National Forest, Craig Ranger District. The human remains and associated funerary objects were removed from the Staney Creek area of Prince of Wales Island, AK. \n This notice is published as part of the National Park Service\\'s administrative responsibilities under NAGPRA, 25 U.S.C. 3003(d)(3). The determinations in this notice are the sole responsibility of the museum, institution, or Federal agency that has control of the Native American human remains and associated funerary objects. The National Park Service is not responsible for the determinations in this notice. \n Consultation \n A detailed assessment of the human remains was made by the Forest Service professional staff using details provided from the Canadian Museum of History and in consultation with representatives of Craig Tribal Association (previously listed as the Craig Community Association), Hydaburg Cooperative Association, Klawock Cooperative Association, and the Organized Village of Kasaan. \n History and Description of the Remains \n In 1973, human remains representing, at minimum, one individual were removed from the Staney Creek area on Prince of Wales Island, AK. The human remains were removed from Forest Service-managed lands by members of the United States Geological Survey, Department of the Interior. In 1974, the human remains were sent to the Canadian Museum of Civilization Corporation for analysis. The analysis indicated the human remains were from 185 to 385 years old. In September of 2014, the Forest Service took possession of the remains and funerary object from the museum and took them to the Craig Ranger District. No known individuals were identified. The one associated funerary object is a piece of wood that was found with the human remains. \n Cultural affiliation of the human remains and associated funerary objects was based on multiple lines of evidence, including consultation with the Klawock Cooperative Association and a published source, Haa Aani, Our Land: Tlingit and Haida Land Rights and Use by Walter Goldschmidt and Theodore H. Haas, edited by Thomas F. Thornton, first issued in 1948, reprinted in 1988, by the Sealaska Heritage Association. The human remains were removed from an area defined in Haa Aani and by the tribe as culturally affiliated with the Klawock Cooperative Association. \n Determinations Made by the Forest Service, Tongass National Forest \n Officials of the Forest Service, Tongass National Forest have determined that: \n \\xe2\\x80\\xa2 Pursuant to 25 U.S.C. 3001(9), the human remains described in this notice represent the physical remains of one individual of Native American ancestry. \n \\xe2\\x80\\xa2 Pursuant to 25 U.S.C. 3001(3)(A), the one object described in this notice are reasonably believed to have been placed with or near individual human remains at the time of death or later as part of the death rite or ceremony. \n \\xe2\\x80\\xa2 Pursuant to 25 U.S.C. 3001(2), there is a relationship of shared group identity that can be reasonably traced between the Native American human remains and associated funerary object and the Klawock Cooperative Association. \n Additional Requestors and Disposition \n Lineal descendants or representatives of any Indian tribe or Native Hawaiian organization not identified in this notice that wish to request transfer of control of these human remains and associated funerary objects should submit a written request with information in support of the request to Tongass National Forest Supervisor Earl Stewart, 648 Mission Street Federal Building, Ketchikan, AK 99901-6591, phone number (907) 225-3101, email estewart@fs.fed.us, by January 3, 2017. After that date, if no additional requestors have come forward, transfer of control of the human remains and associated funerary objects to Klawock Cooperative Association may proceed. \n The Forest Service is responsible for notifying the Craig Tribal Association (previously listed as the Craig Community Association), Klawock Cooperative Association, Hydaburg Cooperative Association, and the Organized Village of Kasaan that this notice has been published. \n ", "consultation": "A detailed assessment of the human remains was made by the Forest Service professional staff using details provided from the Canadian Museum of History and in consultation with representatives of Craig Tribal Association (previously listed as the Craig Community Association), Hydaburg Cooperative Association, Klawock Cooperative Association, and the Organized Village of Kasaan. \n ", "h_d_r": "In 1973, human remains representing, at minimum, one individual were removed from the Staney Creek area on Prince of Wales Island, AK. The human remains were removed from Forest Service-managed lands by members of the United States Geological Survey, Department of the Interior. In 1974, the human remains were sent to the Canadian Museum of Civilization Corporation for analysis. The analysis indicated the human remains were from 185 to 385 years old. In September of 2014, the Forest Service took possession of the remains and funerary object from the museum and took them to the Craig Ranger District. No known individuals were identified. The one associated funerary object is a piece of wood that was found with the human remains. \n Cultural affiliation of the human remains and associated funerary objects was based on multiple lines of evidence, including consultation with the Klawock Cooperative Association and a published source, Haa Aani, Our Land: Tlingit and Haida Land Rights and Use by Walter Goldschmidt and Theodore H. Haas, edited by Thomas F. Thornton, first issued in 1948, reprinted in 1988, by the Sealaska Heritage Association. The human remains were removed from an area defined in Haa Aani and by the tribe as culturally affiliated with the Klawock Cooperative Association. \n ", "h_d_ci": "Null", "determinations": "Determinations Made by the Forest Service, Tongass National Forest \n Officials of the Forest Service, Tongass National Forest have determined that: \n \\xe2\\x80\\xa2 Pursuant to 25 U.S.C. 3001(9), the human remains described in this notice represent the physical remains of one individual of Native American ancestry. \n \\xe2\\x80\\xa2 Pursuant to 25 U.S.C. 3001(3)(A), the one object described in this notice are reasonably believed to have been placed with or near individual human remains at the time of death or later as part of the death rite or ceremony. \n \\xe2\\x80\\xa2 Pursuant to 25 U.S.C. 3001(2), there is a relationship of shared group identity that can be reasonably traced between the Native American human remains and associated funerary object and the Klawock Cooperative Association. \n ", "a_r_d": "Lineal descendants or representatives of any Indian tribe or Native Hawaiian organization not identified in this notice that wish to request transfer of control of these human remains and associated funerary objects should submit a written request with information in support of the request to Tongass National Forest Supervisor Earl Stewart, 648 Mission Street Federal Building, Ketchikan, AK 99901-6591, phone number (907) 225-3101, email estewart@fs.fed.us, by January 3, 2017. After that date, if no additional requestors have come forward, transfer of control of the human remains and associated funerary objects to Klawock Cooperative Association may proceed. \n The Forest Service is responsible for notifying the Craig Tribal Association (previously listed as the Craig Community Association), Klawock Cooperative Association, Hydaburg Cooperative Association, and the Organized Village of Kasaan that this notice has been published. \n "}