{"index": "I_48", "messy_full": "\\n      \\n        DEPARTMENT OF THE INTERIOR\\n        National Park Service\\n        [NPS-WASO-NAGPRA-NPS0028404; PPWOCRADN0-PCU00RP14.R50000]\\n        Notice of Inventory Completion: Nevada State Museum, Carson City, NV\\n        \\n          AGENCY:\\n          National Park Service, Interior.\\n        \\n        \\n          ACTION:\\n          Notice.\\n        \\n        \\n          SUMMARY:\\n          The Nevada State Museum, Carson City completed an inventory of human remains, in consultation with the appropriate Indian Tribe or Native Hawaiian organizations, and has determined that there is no cultural affiliation between the human remains and any present-day Indian Tribes or Native Hawaiian organizations. Representatives of any Indian Tribe or Native Hawaiian organization not identified in this notice that wish to request transfer of control of these human remains should submit a written request to the Nevada State Museum, Carson City. If no additional requestors come forward, transfer of control of the human remains to the Indian Tribes or Native Hawaiian organizations stated in this notice may proceed.\\n        \\n        \\n          DATES:\\n          Representatives of any Indian Tribe or Native Hawaiian organization not identified in this notice that wish to request transfer of control of these human remains should submit a written request with information in support of their request to the Nevada State Museum, Carson City at the address in this notice by September 4, 2019.\\n        \\n        \\n          ADDRESSES:\\n\\n          Anna J. Camp, Nevada State Museum, 600 North Carson Street, Carson City, NV 89701, telephone (775) 687-4810 Ext. 261, email acamp@nevadaculture.org.\\n          \\n        \\n      \\n      \\n        SUPPLEMENTARY INFORMATION:\\n        Notice is here given in accordance with the Native American Graves Protection and Repatriation Act (NAGPRA), 25 U.S.C. 3003, of completion of an inventory of human remains under the control of the Nevada State Museum, Carson City, NV. The human remains were removed from the area of Mud Lake Creek, Douglas County, NV.\\n        This notice is published as part of the National Park Service\\'s administrative responsibilities under NAGPRA, 25 U.S.C. 3003(d)(3) and 43 CFR 10.11(d). The determinations in this notice are the sole responsibility of the museum, institution, or Federal agency that has control of the Native American human remains. The National Park Service is not responsible for the determinations in this notice.\\n        Consultation\\n        A detailed assessment of the human remains was made by the Nevada State Museum professional staff in consultation with representatives of the Washoe Tribe of Nevada & California (Carson Colony, Dresslerville Colony, Woodfords Community, Stewart Community & Washoe Ranches).\\n        History and Description of the Remains\\n\\n        On November 11, 1996, human remains representing, at minimum, two individuals, were removed from an eroding bank of Mud Lake Creek in Douglas County, NV. The human remains\\xe2\\x80\\x94several rib fragments\\xe2\\x80\\x94were collected by an anonymous private citizen and brought to the Nevada State Museum. They were later discovered in the collections at the Nevada State Museum and rehoused. A note in the file suggests these human remains were found close to an archeological site (26Do524), which contained burials of two adolescent individuals. The excavation of the associated site located nearby was done in conjunction with the Douglas County Sheriff\\'s Department, the Washoe Tribe of Nevada & California, and the Nevada State Museum. No known individuals were identified. No associated funerary objects are present.\\n        Determinations Made by the Nevada State Museum\\n        Officials of the Nevada State Museum have determined that:\\n        \\xe2\\x80\\xa2 Pursuant to 25 U.S.C. 3001(9), human remains described in this notice are Native American based on the age of 1620\\xc2\\xb150 14C B.P. (radiocarbon years before present), and 1490\\xc2\\xb150 14C B.P. The location of the site was also in close proximity to an excavated Native American burial site.\\n        \\xe2\\x80\\xa2 Pursuant to 25 U.S.C. 3001(9), human remains described in this notice represent the physical remains of two individuals of Native American ancestry.\\n        \\xe2\\x80\\xa2 Pursuant to 25 U.S.C. 3001(2), a relationship of shared group identity cannot be reasonably traced between the Native American human remains and any present-day Indian Tribe.\\n        \\xe2\\x80\\xa2 According to final judgments of the Indian Claims Commission or the Court of Federal Claims, the land from which the Native American human remains were removed is the aboriginal land of the Washoe Tribe of Nevada & California (Carson Colony, Dresslerville Colony, Woodfords Community, Stewart Community & Washoe Ranches).\\n        \\xe2\\x80\\xa2 Treaties, Acts of Congress, or Executive Orders, indicate that the land from which these Native American human remains were removed is the aboriginal land of the Washoe Tribe of Nevada & California (Carson Colony, Dresslerville Colony, Woodfords Community, Stewart Community & Washoe Ranches).\\n        \\xe2\\x80\\xa2 Pursuant to 43 CFR 10.11(c)(1), the disposition of the human remains may be to the Washoe Tribe of Nevada & California (Carson Colony, Dresslerville Colony, Woodfords Community, Stewart Community & Washoe Ranches).\\n        Additional Requestors and Disposition\\n\\n        Representatives of any Indian Tribe or Native Hawaiian organization not identified in this notice that wish to request transfer of control of these human remains should submit a written request with information in support of their request to Anna Camp, Nevada State Museum, 600 North Carson Street, NV 89701, telephone (775) 687-4810 Ext. 261, email acamp@nevadaculture.org, by September 4, 2019. After that date, if no additional requestors have come forward, transfer of control of the human remains to the Washoe Tribe of Nevada & California (Carson Colony, Dresslerville Colony, Woodfords Community, Stewart Community & Washoe Ranches) may proceed.\\n        The Nevada State Museum is responsible for notifying the Washoe Tribe of Nevada & California (Carson Colony, Dresslerville Colony, Woodfords Community, Stewart Community & Washoe Ranches) that this notice has been published.\\n        \\n          Dated: July 9, 2019.\\n          Melanie O\\'Brien,\\n          Manager, National NAGPRA Program. \\n        \\n      \\n      [FR Doc. 2019-16681 Filed 8-2-19; 8:45 am]\\n       BILLING CODE 4312-52-P\\n    ", "agency1": "DEPARTMENT OF THE INTERIOR", "sub_agency1": "National Park Service", "dep_doc": "[NPS-WASO-NAGPRA-NPS0028404; PPWOCRADN0-PCU00RP14.R50000]", "subject": "Notice of Inventory Completion: Nevada State Museum, Carson City, NV", "agency2": "National Park Service, Interior.", "action": "Notice.", "summary": "The Nevada State Museum, Carson City completed an inventory of human remains, in consultation with the appropriate Indian Tribe or Native Hawaiian organizations, and has determined that there is no cultural affiliation between the human remains and any present-day Indian Tribes or Native Hawaiian organizations. Representatives of any Indian Tribe or Native Hawaiian organization not identified in this notice that wish to request transfer of control of these human remains should submit a written request to the Nevada State Museum, Carson City. If no additional requestors come forward, transfer of control of the human remains to the Indian Tribes or Native Hawaiian organizations stated in this notice may proceed.", "dates": "Representatives of any Indian Tribe or Native Hawaiian organization not identified in this notice that wish to request transfer of control of these human remains should submit a written request with information in support of their request to the Nevada State Museum, Carson City at the address in this notice by September 4, 2019.", "addresses": "Anna J. Camp, Nevada State Museum, 600 North Carson Street, Carson City, NV 89701, telephone (775) 687-4810 Ext. 261, email acamp@nevadaculture.org.\\n          ", "signature_dated": "Dated: July 9, 2019.", "signature_name": "Melanie O\\'Brien,", "signature_title": "Manager, National NAGPRA Program. ", "fr_doc": "[FR Doc. 2019-16681 Filed 8-2-19; 8:45 am]", "billing_code": " BILLING CODE 4312-52-P", "supp_info": "SUPPLEMENTARY INFORMATION: \n Notice is here given in accordance with the Native American Graves Protection and Repatriation Act (NAGPRA), 25 U.S.C. 3003, of completion of an inventory of human remains under the control of the Nevada State Museum, Carson City, NV. The human remains were removed from the area of Mud Lake Creek, Douglas County, NV. \n This notice is published as part of the National Park Service\\'s administrative responsibilities under NAGPRA, 25 U.S.C. 3003(d)(3) and 43 CFR 10.11(d). The determinations in this notice are the sole responsibility of the museum, institution, or Federal agency that has control of the Native American human remains. The National Park Service is not responsible for the determinations in this notice. \n Consultation \n A detailed assessment of the human remains was made by the Nevada State Museum professional staff in consultation with representatives of the Washoe Tribe of Nevada & California (Carson Colony, Dresslerville Colony, Woodfords Community, Stewart Community & Washoe Ranches). \n History and Description of the Remains \n On November 11, 1996, human remains representing, at minimum, two individuals, were removed from an eroding bank of Mud Lake Creek in Douglas County, NV. The human remains\\xe2\\x80\\x94several rib fragments\\xe2\\x80\\x94were collected by an anonymous private citizen and brought to the Nevada State Museum. They were later discovered in the collections at the Nevada State Museum and rehoused. A note in the file suggests these human remains were found close to an archeological site (26Do524), which contained burials of two adolescent individuals. The excavation of the associated site located nearby was done in conjunction with the Douglas County Sheriff\\'s Department, the Washoe Tribe of Nevada & California, and the Nevada State Museum. No known individuals were identified. No associated funerary objects are present. \n Determinations Made by the Nevada State Museum \n Officials of the Nevada State Museum have determined that: \n \\xe2\\x80\\xa2 Pursuant to 25 U.S.C. 3001(9), human remains described in this notice are Native American based on the age of 1620\\xc2\\xb150 14C B.P. (radiocarbon years before present), and 1490\\xc2\\xb150 14C B.P. The location of the site was also in close proximity to an excavated Native American burial site. \n \\xe2\\x80\\xa2 Pursuant to 25 U.S.C. 3001(9), human remains described in this notice represent the physical remains of two individuals of Native American ancestry. \n \\xe2\\x80\\xa2 Pursuant to 25 U.S.C. 3001(2), a relationship of shared group identity cannot be reasonably traced between the Native American human remains and any present-day Indian Tribe. \n \\xe2\\x80\\xa2 According to final judgments of the Indian Claims Commission or the Court of Federal Claims, the land from which the Native American human remains were removed is the aboriginal land of the Washoe Tribe of Nevada & California (Carson Colony, Dresslerville Colony, Woodfords Community, Stewart Community & Washoe Ranches). \n \\xe2\\x80\\xa2 Treaties, Acts of Congress, or Executive Orders, indicate that the land from which these Native American human remains were removed is the aboriginal land of the Washoe Tribe of Nevada & California (Carson Colony, Dresslerville Colony, Woodfords Community, Stewart Community & Washoe Ranches). \n \\xe2\\x80\\xa2 Pursuant to 43 CFR 10.11(c)(1), the disposition of the human remains may be to the Washoe Tribe of Nevada & California (Carson Colony, Dresslerville Colony, Woodfords Community, Stewart Community & Washoe Ranches). \n Additional Requestors and Disposition \n Representatives of any Indian Tribe or Native Hawaiian organization not identified in this notice that wish to request transfer of control of these human remains should submit a written request with information in support of their request to Anna Camp, Nevada State Museum, 600 North Carson Street, NV 89701, telephone (775) 687-4810 Ext. 261, email acamp@nevadaculture.org, by September 4, 2019. After that date, if no additional requestors have come forward, transfer of control of the human remains to the Washoe Tribe of Nevada & California (Carson Colony, Dresslerville Colony, Woodfords Community, Stewart Community & Washoe Ranches) may proceed. \n The Nevada State Museum is responsible for notifying the Washoe Tribe of Nevada & California (Carson Colony, Dresslerville Colony, Woodfords Community, Stewart Community & Washoe Ranches) that this notice has been published. \n ", "consultation": "A detailed assessment of the human remains was made by the Nevada State Museum professional staff in consultation with representatives of the Washoe Tribe of Nevada & California (Carson Colony, Dresslerville Colony, Woodfords Community, Stewart Community & Washoe Ranches). \n ", "h_d_r": "On November 11, 1996, human remains representing, at minimum, two individuals, were removed from an eroding bank of Mud Lake Creek in Douglas County, NV. The human remains\\xe2\\x80\\x94several rib fragments\\xe2\\x80\\x94were collected by an anonymous private citizen and brought to the Nevada State Museum. They were later discovered in the collections at the Nevada State Museum and rehoused. A note in the file suggests these human remains were found close to an archeological site (26Do524), which contained burials of two adolescent individuals. The excavation of the associated site located nearby was done in conjunction with the Douglas County Sheriff\\'s Department, the Washoe Tribe of Nevada & California, and the Nevada State Museum. No known individuals were identified. No associated funerary objects are present. \n ", "h_d_ci": "Null", "determinations": "Determinations Made by the Nevada State Museum \n Officials of the Nevada State Museum have determined that: \n \\xe2\\x80\\xa2 Pursuant to 25 U.S.C. 3001(9), human remains described in this notice are Native American based on the age of 1620\\xc2\\xb150 14C B.P. (radiocarbon years before present), and 1490\\xc2\\xb150 14C B.P. The location of the site was also in close proximity to an excavated Native American burial site. \n \\xe2\\x80\\xa2 Pursuant to 25 U.S.C. 3001(9), human remains described in this notice represent the physical remains of two individuals of Native American ancestry. \n \\xe2\\x80\\xa2 Pursuant to 25 U.S.C. 3001(2), a relationship of shared group identity cannot be reasonably traced between the Native American human remains and any present-day Indian Tribe. \n \\xe2\\x80\\xa2 According to final judgments of the Indian Claims Commission or the Court of Federal Claims, the land from which the Native American human remains were removed is the aboriginal land of the Washoe Tribe of Nevada & California (Carson Colony, Dresslerville Colony, Woodfords Community, Stewart Community & Washoe Ranches). \n \\xe2\\x80\\xa2 Treaties, Acts of Congress, or Executive Orders, indicate that the land from which these Native American human remains were removed is the aboriginal land of the Washoe Tribe of Nevada & California (Carson Colony, Dresslerville Colony, Woodfords Community, Stewart Community & Washoe Ranches). \n \\xe2\\x80\\xa2 Pursuant to 43 CFR 10.11(c)(1), the disposition of the human remains may be to the Washoe Tribe of Nevada & California (Carson Colony, Dresslerville Colony, Woodfords Community, Stewart Community & Washoe Ranches). \n ", "a_r_d": "Representatives of any Indian Tribe or Native Hawaiian organization not identified in this notice that wish to request transfer of control of these human remains should submit a written request with information in support of their request to Anna Camp, Nevada State Museum, 600 North Carson Street, NV 89701, telephone (775) 687-4810 Ext. 261, email acamp@nevadaculture.org, by September 4, 2019. After that date, if no additional requestors have come forward, transfer of control of the human remains to the Washoe Tribe of Nevada & California (Carson Colony, Dresslerville Colony, Woodfords Community, Stewart Community & Washoe Ranches) may proceed. \n The Nevada State Museum is responsible for notifying the Washoe Tribe of Nevada & California (Carson Colony, Dresslerville Colony, Woodfords Community, Stewart Community & Washoe Ranches) that this notice has been published. \n "}