{"index": "I_498", "messy_full": "\\n      \\n        DEPARTMENT OF THE INTERIOR\\n        National Park Service\\n        [NPS-WASO-NAGPRA-22250; PPWOCRADN0-PCU00RP14.R50000]\\n        Notice of Inventory Completion: Lake County Discovery Museum, Wauconda, IL; Correction\\n        \\n          AGENCY:\\n          National Park Service, Interior.\\n        \\n        \\n          ACTION:\\n          Notice; correction.\\n        \\n        \\n          SUMMARY:\\n\\n          The Lake County Discovery Museum has corrected a Notice of Inventory Completion in the Federal Register on June 8, 2016. This notice corrects the list of The Consulted and Invited Tribes.\\n        \\n        \\n          ADDRESSES:\\n\\n          Diana Dretske, Lake County Discovery Museum, 27277 North Forest Preserve Road, Wauconda, IL 60084, telephone (847) 968-3381, email ddretske@lcfpd.org.\\n          \\n        \\n      \\n      \\n        \\n        SUPPLEMENTARY INFORMATION:\\n        Notice is here given in accordance with the Native American Graves Protection and Repatriation Act (NAGPRA), 25 U.S.C. 3003, of the correction of an inventory of human remains and associated funerary objects under the control of the Lake County Discovery Museum, Wauconda, IL.\\n        This notice is published as part of the National Park Service\\'s administrative responsibilities under NAGPRA, 25 U.S.C. 3003(d)(3). The determinations in this notice are the sole responsibility of the museum, institution, or Federal agency that has control of the Native American human remains and associated funerary objects. The National Park Service is not responsible for the determinations in this notice.\\n        Correction\\n        In the Federal Register (81 FR 36948, June 8, 2016), column 1, paragraph 1 is corrected by substituting the following paragraph:\\n        \\n        \\n          A detailed assessment of the human remains was made by the Lake County Discovery Museum with representatives of the Assiniboine and Sioux Tribes of the Fort Peck Indian Reservation, Montana; Lac Vieux Desert Band of Lake Superior Chippewa Indians of Michigan; Little River Band of Ottawa Indians, Michigan; Match-e-be-nash-she-wish Band of the Pottawatomi Indians of Michigan; Nottawaseppi Huron Band of the Potawatomi, Michigan (previously listed as the Huron Potawatomi, Inc.); Pokagon Band of Potawatomi Indians, Michigan and Indiana; Sac & Fox Nation, Oklahoma; Saginaw Chippewa Indian Tribe of Michigan; and Sault Ste. Marie Tribe of Chippewa Indians, Michigan. The following tribes were invited to consult but did not respond to the invitation: Bad River Band of the Lake Superior Tribe of Chippewa Indians of the Bad River Reservation, Wisconsin; Bay Mills Indian Community, Michigan; Chippewa Cree Indians of the Rocky Boy\\'s Reservation, Montana (previously listed as the Chippewa-Cree Indians of the Rock Boy\\'s Reservation, Montana); Citizen Potawatomi Nation, Oklahoma; Confederate Tribes of the Umatilla Indian Reservation (previously listed as the Confederated Tribes of the Umatilla Reservation, Oregon); Eastern Band of Cherokee Indians; Forest County Potawatomi Community, Wisconsin; Grand Traverse Band of Ottawa and Chippewa Indians, Michigan; Hannahville Indian Community, Michigan; Keweenaw Bay Indian Community, Michigan; Lac Courte Oreilles Band of Lake Superior Chippewa Indians of Wisconsin; Lac du Flambeau Band of Lake Superior Chippewa Indian of the Lac du Flambeau Reservation of Wisconsin; Minnesota Chippewa Tribe, Minnesota (Six component reservations: Bois Forte Band (Nett Lake); Fond du Lac Band; Grand Portage Band; Leech Lake Band; Mille Lacs Band; White Earth Band); Ottawa Tribe of Oklahoma; Prairie Band Potawatomi Nation (previously listed as the Prairie Band of Potawatomi Nation, Kansas); Red Cliff Band of Lake Superior Indians of Wisconsin; Red Lake Band of Chippewa Indians, Minnesota; Sac & Fox Tribe of the Mississippi in Iowa; Sac & Fox Nation of Missouri in Kansas and Nebraska; Sokaogon Chippewa Community, Wisconsin; St. Croix Chippewa Indians of Wisconsin; and the Turtle Mountain Band of Chippewa Indians of North Dakota. All tribes listed above are hereafter referred to as \\xe2\\x80\\x9cThe Consulted and Invited Tribes.\\xe2\\x80\\x9d\\n        \\n        \\n        The Lake County Discovery Museum is responsible for notifying The Consulted and Invited Tribes that this notice has been published.\\n        \\n          Dated: October 24, 2016.\\n          Melanie O\\'Brien,\\n          Manager, National NAGPRA Program.\\n        \\n      \\n      [FR Doc. 2016-26980 Filed 11-8-16; 8:45 am]\\n      BILLING CODE 4312-52-P\\n    ", "agency1": "DEPARTMENT OF THE INTERIOR", "sub_agency1": "National Park Service", "dep_doc": "[NPS-WASO-NAGPRA-22250; PPWOCRADN0-PCU00RP14.R50000]", "subject": "Notice of Inventory Completion: Lake County Discovery Museum, Wauconda, IL; Correction", "agency2": "National Park Service, Interior.", "action": "Notice; correction.", "summary": "The Lake County Discovery Museum has corrected a Notice of Inventory Completion in the Federal Register on June 8, 2016. This notice corrects the list of The Consulted and Invited Tribes.", "dates": "Null", "addresses": "Diana Dretske, Lake County Discovery Museum, 27277 North Forest Preserve Road, Wauconda, IL 60084, telephone (847) 968-3381, email ddretske@lcfpd.org.\\n          ", "signature_dated": "Dated: October 24, 2016.", "signature_name": "Melanie O\\'Brien,", "signature_title": "Manager, National NAGPRA Program.", "fr_doc": "[FR Doc. 2016-26980 Filed 11-8-16; 8:45 am]", "billing_code": "BILLING CODE 4312-52-P", "supp_info": "SUPPLEMENTARY INFORMATION: \n Notice is here given in accordance with the Native American Graves Protection and Repatriation Act (NAGPRA), 25 U.S.C. 3003, of the correction of an inventory of human remains and associated funerary objects under the control of the Lake County Discovery Museum, Wauconda, IL. \n This notice is published as part of the National Park Service\\'s administrative responsibilities under NAGPRA, 25 U.S.C. 3003(d)(3). The determinations in this notice are the sole responsibility of the museum, institution, or Federal agency that has control of the Native American human remains and associated funerary objects. The National Park Service is not responsible for the determinations in this notice. \n Correction \n In the Federal Register (81 FR 36948, June 8, 2016), column 1, paragraph 1 is corrected by substituting the following paragraph: \n The Lake County Discovery Museum is responsible for notifying The Consulted and Invited Tribes that this notice has been published. \n ", "consultation": "Null", "h_d_r": "Null", "h_d_ci": "Null", "determinations": "Null", "a_r_d": "Null"}