{"index": "I_496", "messy_full": "\\n      \\n        DEPARTMENT OF THE INTERIOR\\n        National Park Service\\n        [NPS-WASO-NAGPRA-22420; PPWOCRADN0-PCU00RP14.R50000]\\n        Notice of Inventory Completion: Peabody Museum of Natural History, Yale University, New Haven, CT\\n        \\n          AGENCY:\\n          National Park Service, Interior.\\n        \\n        \\n          ACTION:\\n          Notice.\\n        \\n        \\n          SUMMARY:\\n          The Peabody Museum of Natural History has completed an inventory of human remains, in consultation with the appropriate Alaska Native Tribes, and has determined that there is a cultural affiliation between the human remains and present-day Alaska Native Tribes. Lineal descendants or representatives of any Indian tribe or Native Hawaiian organization not identified in this notice that wish to request transfer of control of these human remains should submit a written request to the Peabody Museum of Natural History. If no additional requestors come forward, transfer of control of the human remains to the Alaska Native Tribes stated in this notice may proceed.\\n        \\n        \\n          DATES:\\n          Lineal descendants or representatives of any Indian tribe or Native Hawaiian organization not identified in this notice that wish to request transfer of control of these human remains should submit a written request with information in support of the request to the Peabody Museum of Natural History at the address in this notice by January 3, 2017.\\n        \\n        \\n          ADDRESSES:\\n          Professor David Skelly, Director, Yale Peabody Museum of Natural History, P.O. Box 208118, New Haven, CT 06520-8118, telephone (203) 432-3752.\\n        \\n      \\n      \\n        SUPPLEMENTARY INFORMATION:\\n        Notice is here given in accordance with the Native American Graves Protection and Repatriation Act (NAGPRA), 25 U.S.C. 3003, of the completion of an inventory of human remains under the control of the Peabody Museum of Natural History, Yale University, New Haven, CT. The human remains were removed from Passage Island, Kenai Peninsula Borough, AK.\\n        This notice is published as part of the National Park Service\\'s administrative responsibilities under NAGPRA, 25 U.S.C. 3003(d)(3). The determinations in this notice are the sole responsibility of the museum, institution, or Federal agency that has control of the Native American human remains. The National Park Service is not responsible for the determinations in this notice.\\n        Consultation\\n        A detailed assessment of the human remains was made by Peabody Museum of Natural History professional staff in consultation with a representative of the Native Village of Chenega (aka Chanega), the Native Village of Eyak (Cordova), the Native Village of Nanwalek (aka English Bay), the Native Village of Port Graham, the Native Village of Tatitlek, and the Chugach Alaska Corporation.\\n        History and Description of the Remains\\n        In 1931, human remains representing one individual were removed from a burial on Passage Island in Kenai Peninsula Borough, AK. According to historical documentation, the burial was uncovered by a local fox farmer and was subsequently collected by the Yale Peabody Alaska Expedition. The human remains represent one individual identified as a probable female, aged approximately 20-25 years. No known individuals were identified. No associated funerary objects are present.\\n        Osteological examination as well as contextual data identify these human remains as representing an individual of Native American ancestry. Archaeologist Frederica de Laguna identifies the Passage Island burial site as a local expression of the Third Period of the Kachemak Bay Tradition. Recent scholars have dated the Kachemak Bay Tradition from circa 1000 B.C. to A.D. 900. Additional scholars have identified the Kachemak Bay Tradition people as Pacific Eskimos. The Pacific Eskimo people are today represented by the Native Village of Chenega, the Native Village of Eyak, the Native Village of Nanwalek, the Native Village of Port Graham, and the Native Village of Tatitlek.\\n        Determinations Made by the Peabody Museum of Natural History, Yale University\\n        Officials of the Peabody Museum of Natural History have determined that:\\n        \\xe2\\x80\\xa2 Pursuant to 25 U.S.C. 3001(9), the human remains described in this notice represent the physical remains of one individual of Native American ancestry.\\n\\n        \\xe2\\x80\\xa2 Pursuant to 25 U.S.C. 3001(2), there is a relationship of shared group identity that can be reasonably traced between the Native American human remains and of the Native Village of Chenega (aka Chanega), the Native Village of Eyak (Cordova), the Native Village of Nanwalek (aka English Bay), the Native Village of Port Graham, and the Native Village of Tatitlek.\\n        \\n        Additional Requestors and Disposition\\n        Lineal descendants or representatives of any Indian tribe or Native Hawaiian organization not identified in this notice that wish to request transfer of control of these human remains should submit a written request with information in support of the request to Professor David Skelly, Director, Yale Peabody Museum of Natural History, P.O. Box 208118, New Haven, CT 06520-8118, telephone (203) 432-3752, by January 3, 2017. After that date, if no additional requestors have come forward, transfer of control of the human remains to the Chugach Alaska Corporation as an agent for the Native Village of Chenega (aka Chanega), the Native Village of Eyak (Cordova), the Native Village of Nanwalek (aka English Bay), the Native Village of Port Graham, and the Native Village of Tatitlek may proceed.\\n        The Peabody Museum of Natural History is responsible for notifying the of the Native Village of Chenega (aka Chanega), the Native Village of Eyak (Cordova), the Native Village of Nanwalek (aka English Bay), the Native Village of Port Graham, the Native Village of Tatitlek, and the Chugach Alaska Corporation that this notice has been published.\\n        \\n          Dated: November 15, 2016.\\n          Melanie O\\'Brien,\\n          Manager, National NAGPRA Program. \\n        \\n      \\n      [FR Doc. 2016-28948 Filed 12-1-16; 8:45 am]\\n       BILLING CODE 4312-52-P\\n    ", "agency1": "DEPARTMENT OF THE INTERIOR", "sub_agency1": "National Park Service", "dep_doc": "[NPS-WASO-NAGPRA-22420; PPWOCRADN0-PCU00RP14.R50000]", "subject": "Notice of Inventory Completion: Peabody Museum of Natural History, Yale University, New Haven, CT", "agency2": "National Park Service, Interior.", "action": "Notice.", "summary": "The Peabody Museum of Natural History has completed an inventory of human remains, in consultation with the appropriate Alaska Native Tribes, and has determined that there is a cultural affiliation between the human remains and present-day Alaska Native Tribes. Lineal descendants or representatives of any Indian tribe or Native Hawaiian organization not identified in this notice that wish to request transfer of control of these human remains should submit a written request to the Peabody Museum of Natural History. If no additional requestors come forward, transfer of control of the human remains to the Alaska Native Tribes stated in this notice may proceed.", "dates": "Lineal descendants or representatives of any Indian tribe or Native Hawaiian organization not identified in this notice that wish to request transfer of control of these human remains should submit a written request with information in support of the request to the Peabody Museum of Natural History at the address in this notice by January 3, 2017.", "addresses": "Professor David Skelly, Director, Yale Peabody Museum of Natural History, P.O. Box 208118, New Haven, CT 06520-8118, telephone (203) 432-3752.", "signature_dated": "Dated: November 15, 2016.", "signature_name": "Melanie O\\'Brien,", "signature_title": "Manager, National NAGPRA Program. ", "fr_doc": "[FR Doc. 2016-28948 Filed 12-1-16; 8:45 am]", "billing_code": " BILLING CODE 4312-52-P", "supp_info": "SUPPLEMENTARY INFORMATION: \n Notice is here given in accordance with the Native American Graves Protection and Repatriation Act (NAGPRA), 25 U.S.C. 3003, of the completion of an inventory of human remains under the control of the Peabody Museum of Natural History, Yale University, New Haven, CT. The human remains were removed from Passage Island, Kenai Peninsula Borough, AK. \n This notice is published as part of the National Park Service\\'s administrative responsibilities under NAGPRA, 25 U.S.C. 3003(d)(3). The determinations in this notice are the sole responsibility of the museum, institution, or Federal agency that has control of the Native American human remains. The National Park Service is not responsible for the determinations in this notice. \n Consultation \n A detailed assessment of the human remains was made by Peabody Museum of Natural History professional staff in consultation with a representative of the Native Village of Chenega (aka Chanega), the Native Village of Eyak (Cordova), the Native Village of Nanwalek (aka English Bay), the Native Village of Port Graham, the Native Village of Tatitlek, and the Chugach Alaska Corporation. \n History and Description of the Remains \n In 1931, human remains representing one individual were removed from a burial on Passage Island in Kenai Peninsula Borough, AK. According to historical documentation, the burial was uncovered by a local fox farmer and was subsequently collected by the Yale Peabody Alaska Expedition. The human remains represent one individual identified as a probable female, aged approximately 20-25 years. No known individuals were identified. No associated funerary objects are present. \n Osteological examination as well as contextual data identify these human remains as representing an individual of Native American ancestry. Archaeologist Frederica de Laguna identifies the Passage Island burial site as a local expression of the Third Period of the Kachemak Bay Tradition. Recent scholars have dated the Kachemak Bay Tradition from circa 1000 B.C. to A.D. 900. Additional scholars have identified the Kachemak Bay Tradition people as Pacific Eskimos. The Pacific Eskimo people are today represented by the Native Village of Chenega, the Native Village of Eyak, the Native Village of Nanwalek, the Native Village of Port Graham, and the Native Village of Tatitlek. \n Determinations Made by the Peabody Museum of Natural History, Yale University \n Officials of the Peabody Museum of Natural History have determined that: \n \\xe2\\x80\\xa2 Pursuant to 25 U.S.C. 3001(9), the human remains described in this notice represent the physical remains of one individual of Native American ancestry. \n \\xe2\\x80\\xa2 Pursuant to 25 U.S.C. 3001(2), there is a relationship of shared group identity that can be reasonably traced between the Native American human remains and of the Native Village of Chenega (aka Chanega), the Native Village of Eyak (Cordova), the Native Village of Nanwalek (aka English Bay), the Native Village of Port Graham, and the Native Village of Tatitlek.\\n         \n Additional Requestors and Disposition \n Lineal descendants or representatives of any Indian tribe or Native Hawaiian organization not identified in this notice that wish to request transfer of control of these human remains should submit a written request with information in support of the request to Professor David Skelly, Director, Yale Peabody Museum of Natural History, P.O. Box 208118, New Haven, CT 06520-8118, telephone (203) 432-3752, by January 3, 2017. After that date, if no additional requestors have come forward, transfer of control of the human remains to the Chugach Alaska Corporation as an agent for the Native Village of Chenega (aka Chanega), the Native Village of Eyak (Cordova), the Native Village of Nanwalek (aka English Bay), the Native Village of Port Graham, and the Native Village of Tatitlek may proceed. \n The Peabody Museum of Natural History is responsible for notifying the of the Native Village of Chenega (aka Chanega), the Native Village of Eyak (Cordova), the Native Village of Nanwalek (aka English Bay), the Native Village of Port Graham, the Native Village of Tatitlek, and the Chugach Alaska Corporation that this notice has been published. \n ", "consultation": "A detailed assessment of the human remains was made by Peabody Museum of Natural History professional staff in consultation with a representative of the Native Village of Chenega (aka Chanega), the Native Village of Eyak (Cordova), the Native Village of Nanwalek (aka English Bay), the Native Village of Port Graham, the Native Village of Tatitlek, and the Chugach Alaska Corporation. \n ", "h_d_r": "In 1931, human remains representing one individual were removed from a burial on Passage Island in Kenai Peninsula Borough, AK. According to historical documentation, the burial was uncovered by a local fox farmer and was subsequently collected by the Yale Peabody Alaska Expedition. The human remains represent one individual identified as a probable female, aged approximately 20-25 years. No known individuals were identified. No associated funerary objects are present. \n Osteological examination as well as contextual data identify these human remains as representing an individual of Native American ancestry. Archaeologist Frederica de Laguna identifies the Passage Island burial site as a local expression of the Third Period of the Kachemak Bay Tradition. Recent scholars have dated the Kachemak Bay Tradition from circa 1000 B.C. to A.D. 900. Additional scholars have identified the Kachemak Bay Tradition people as Pacific Eskimos. The Pacific Eskimo people are today represented by the Native Village of Chenega, the Native Village of Eyak, the Native Village of Nanwalek, the Native Village of Port Graham, and the Native Village of Tatitlek. \n ", "h_d_ci": "Null", "determinations": "Determinations Made by the Peabody Museum of Natural History, Yale University \n Officials of the Peabody Museum of Natural History have determined that: \n \\xe2\\x80\\xa2 Pursuant to 25 U.S.C. 3001(9), the human remains described in this notice represent the physical remains of one individual of Native American ancestry. \n \\xe2\\x80\\xa2 Pursuant to 25 U.S.C. 3001(2), there is a relationship of shared group identity that can be reasonably traced between the Native American human remains and of the Native Village of Chenega (aka Chanega), the Native Village of Eyak (Cordova), the Native Village of Nanwalek (aka English Bay), the Native Village of Port Graham, and the Native Village of Tatitlek.\\n         \n ", "a_r_d": "Lineal descendants or representatives of any Indian tribe or Native Hawaiian organization not identified in this notice that wish to request transfer of control of these human remains should submit a written request with information in support of the request to Professor David Skelly, Director, Yale Peabody Museum of Natural History, P.O. Box 208118, New Haven, CT 06520-8118, telephone (203) 432-3752, by January 3, 2017. After that date, if no additional requestors have come forward, transfer of control of the human remains to the Chugach Alaska Corporation as an agent for the Native Village of Chenega (aka Chanega), the Native Village of Eyak (Cordova), the Native Village of Nanwalek (aka English Bay), the Native Village of Port Graham, and the Native Village of Tatitlek may proceed. \n The Peabody Museum of Natural History is responsible for notifying the of the Native Village of Chenega (aka Chanega), the Native Village of Eyak (Cordova), the Native Village of Nanwalek (aka English Bay), the Native Village of Port Graham, the Native Village of Tatitlek, and the Chugach Alaska Corporation that this notice has been published. \n "}