{"index": "I_497", "messy_full": "\\n      \\n        \\n        DEPARTMENT OF THE INTERIOR\\n        National Park Service\\n        [NPS-WASO-NAGPRA-22329; PPWOCRADN0-PCU00RP14.R50000]\\n        Notice of Inventory Completion: Hood Museum of Art, Dartmouth College, Hanover, NH\\n        \\n          AGENCY:\\n          National Park Service, Interior.\\n        \\n        \\n          ACTION:\\n          Notice.\\n        \\n        \\n          SUMMARY:\\n          The Hood Museum of Art, Dartmouth College has completed an inventory of human remains in consultation with the appropriate Indian tribes or Native Hawaiian organizations, and has determined that there is no cultural affiliation between the human remains and any present-day Indian tribes or Native Hawaiian organizations. Representatives of any Indian tribe or Native Hawaiian organization not identified in this notice that wish to request transfer of control of these human remains should submit a written request to the Hood Museum of Art, Dartmouth College. If no additional requestors come forward, transfer of control of the human remains to the Indian tribes or Native Hawaiian organizations stated in this notice may proceed.\\n        \\n        \\n          DATES:\\n          Representatives of any Indian tribe or Native Hawaiian organization not identified in this notice that wish to request transfer of control of these human remains should submit a written request with information in support of the request to the Hood Museum of Art, Dartmouth College at the address in this notice by December 28, 2016.\\n        \\n        \\n          ADDRESSES:\\n\\n          Kathleen P. O\\'Malley, Hood Museum of Art, Dartmouth College, 6 East Wheelock Street, Hanover, NH 03755, telephone (603) 646-3853, email kathleen.p.omalley@dartmouth.edu.\\n          \\n        \\n      \\n      \\n        SUPPLEMENTARY INFORMATION:\\n        Notice is here given in accordance with the Native American Graves Protection and Repatriation Act (NAGPRA), 25 U.S.C. 3003, of the completion of an inventory of human remains under the control of the Hood Museum of Art, Dartmouth College, Hanover, NH. The human remains were removed from Hood\\'s Landing, Marion County, TN.\\n        This notice is published as part of the National Park Service\\'s administrative responsibilities under NAGPRA, 25 U.S.C. 3003(d)(3) and 43 CFR 10.11(d). The determinations in this notice are the sole responsibility of the museum, institution, or Federal agency that has control of the Native American human remains. The National Park Service is not responsible for the determinations in this notice.\\n        Consultation\\n        A detailed assessment of the human remains was made by the Hood Museum of Art professional staff in consultation with representatives of the Cherokee Nation, Eastern Band of Cherokee Indians, The Chickasaw Nation, The Muscogee (Creek) Nation, and the United Keetoowah Band of Cherokee Indians in Oklahoma.\\n        History and Description of the Remains\\n        In August of 1932, human remains representing, at minimum, one individual were removed from an \\xe2\\x80\\x9cIndian mound\\xe2\\x80\\x9d at Hood\\'s Landing in Marion County, TN, one-quarter mile west of the Oxbow by Robert M. Bear of the Education Department at Dartmouth College. The human remains were donated to the Dartmouth College Museum and subsequently transferred to the Department of Anthropology, Dartmouth College in 1939. In 1993, in compliance with NAGPRA, officials of the Hood Museum of Art took control of the human remains and included them in an Inventory of Native American Human Remains in the Possession of the Hood Museum of Art at Dartmouth College that are considered to be Culturally Unidentifiable. No known individuals were identified. No associated funerary objects are present.\\n        Determinations Made by the Hood Museum of Art, Dartmouth College, Hanover, NH\\n        Officials of the Hood Museum of Art, Dartmouth College have determined that:\\n        \\xe2\\x80\\xa2 Pursuant to 25 U.S.C. 3001(9), the human remains described in this notice are Native American based on osteological evidence as determined by professors in the Physical Anthropology Department at Dartmouth College and collection history.\\n        \\xe2\\x80\\xa2 Pursuant to 25 U.S.C. 3001(9), the human remains described in this notice represent the physical remains of one individual of Native American ancestry.\\n        \\xe2\\x80\\xa2 Pursuant to 25 U.S.C. 3001(2), a relationship of shared group identity cannot be reasonably traced between the Native American human remains and any present-day Indian tribe.\\n        \\xe2\\x80\\xa2 According to final judgments of the Indian Claims Commission or the Court of Federal Claims, the land from which the Native American human remains were removed is the aboriginal land of the Cherokee Nation, Eastern Band of Cherokee Indians, The Chickasaw Nation, and the United Keetoowah Band of Cherokee Indians in Oklahoma.\\n        \\xe2\\x80\\xa2 Treaties, Acts of Congress, or Executive Orders, indicate that the land from which the Native American human remains were removed is the aboriginal land of the Cherokee Nation, Eastern Band of Cherokee Indians, The Chickasaw Nation, and the United Keetoowah Band of Cherokee Indians in Oklahoma.\\n        \\xe2\\x80\\xa2 Pursuant to 43 CFR 10.11(c)(1), the disposition of the human remains may be to the Cherokee Nation, Eastern Band of Cherokee Indians, The Chickasaw Nation, and the United Keetoowah Band of Cherokee Indians in Oklahoma.\\n        Additional Requestors and Disposition\\n\\n        Representatives of any Indian tribe or Native Hawaiian organization not identified in this notice that wish to request transfer of control of these human remains should submit a written request with information in support of the request to Kathleen P. O\\'Malley, Hood Museum of Art, Dartmouth College, 6 East Wheelock Street, Hanover, NH 03755, telephone (603) 646-3853, email kathleen.p.omalley@dartmouth.edu, by December 28, 2016. After that date, if no additional requestors have come forward, transfer of control of the human remains to the Cherokee Nation, Eastern Band of Cherokee Indians, The Chickasaw Nation, and the United Keetoowah Band of Cherokee Indians in Oklahoma may proceed.\\n        The Hood Museum of Art is responsible for notifying the Cherokee Nation, Eastern Band of Cherokee Indians, The Chickasaw Nation, The Muscogee (Creek) Nation, and the United Keetoowah Band of Cherokee Indians in Oklahoma that this notice has been published.\\n        \\n          Dated: November 2, 2016.\\n          Melanie O\\'Brien,\\n          Manager, National NAGPRA Program.\\n        \\n      \\n      [FR Doc. 2016-28511 Filed 11-25-16; 8:45 am]\\n       BILLING CODE 4312-52-P\\n    ", "agency1": "DEPARTMENT OF THE INTERIOR", "sub_agency1": "National Park Service", "dep_doc": "[NPS-WASO-NAGPRA-22329; PPWOCRADN0-PCU00RP14.R50000]", "subject": "Notice of Inventory Completion: Hood Museum of Art, Dartmouth College, Hanover, NH", "agency2": "National Park Service, Interior.", "action": "Notice.", "summary": "The Hood Museum of Art, Dartmouth College has completed an inventory of human remains in consultation with the appropriate Indian tribes or Native Hawaiian organizations, and has determined that there is no cultural affiliation between the human remains and any present-day Indian tribes or Native Hawaiian organizations. Representatives of any Indian tribe or Native Hawaiian organization not identified in this notice that wish to request transfer of control of these human remains should submit a written request to the Hood Museum of Art, Dartmouth College. If no additional requestors come forward, transfer of control of the human remains to the Indian tribes or Native Hawaiian organizations stated in this notice may proceed.", "dates": "Representatives of any Indian tribe or Native Hawaiian organization not identified in this notice that wish to request transfer of control of these human remains should submit a written request with information in support of the request to the Hood Museum of Art, Dartmouth College at the address in this notice by December 28, 2016.", "addresses": "Kathleen P. O\\'Malley, Hood Museum of Art, Dartmouth College, 6 East Wheelock Street, Hanover, NH 03755, telephone (603) 646-3853, email kathleen.p.omalley@dartmouth.edu.\\n          ", "signature_dated": "Dated: November 2, 2016.", "signature_name": "Melanie O\\'Brien,", "signature_title": "Manager, National NAGPRA Program.", "fr_doc": "[FR Doc. 2016-28511 Filed 11-25-16; 8:45 am]", "billing_code": " BILLING CODE 4312-52-P", "supp_info": "SUPPLEMENTARY INFORMATION: \n Notice is here given in accordance with the Native American Graves Protection and Repatriation Act (NAGPRA), 25 U.S.C. 3003, of the completion of an inventory of human remains under the control of the Hood Museum of Art, Dartmouth College, Hanover, NH. The human remains were removed from Hood\\'s Landing, Marion County, TN. \n This notice is published as part of the National Park Service\\'s administrative responsibilities under NAGPRA, 25 U.S.C. 3003(d)(3) and 43 CFR 10.11(d). The determinations in this notice are the sole responsibility of the museum, institution, or Federal agency that has control of the Native American human remains. The National Park Service is not responsible for the determinations in this notice. \n Consultation \n A detailed assessment of the human remains was made by the Hood Museum of Art professional staff in consultation with representatives of the Cherokee Nation, Eastern Band of Cherokee Indians, The Chickasaw Nation, The Muscogee (Creek) Nation, and the United Keetoowah Band of Cherokee Indians in Oklahoma. \n History and Description of the Remains \n In August of 1932, human remains representing, at minimum, one individual were removed from an \\xe2\\x80\\x9cIndian mound\\xe2\\x80\\x9d at Hood\\'s Landing in Marion County, TN, one-quarter mile west of the Oxbow by Robert M. Bear of the Education Department at Dartmouth College. The human remains were donated to the Dartmouth College Museum and subsequently transferred to the Department of Anthropology, Dartmouth College in 1939. In 1993, in compliance with NAGPRA, officials of the Hood Museum of Art took control of the human remains and included them in an Inventory of Native American Human Remains in the Possession of the Hood Museum of Art at Dartmouth College that are considered to be Culturally Unidentifiable. No known individuals were identified. No associated funerary objects are present. \n Determinations Made by the Hood Museum of Art, Dartmouth College, Hanover, NH \n Officials of the Hood Museum of Art, Dartmouth College have determined that: \n \\xe2\\x80\\xa2 Pursuant to 25 U.S.C. 3001(9), the human remains described in this notice are Native American based on osteological evidence as determined by professors in the Physical Anthropology Department at Dartmouth College and collection history. \n \\xe2\\x80\\xa2 Pursuant to 25 U.S.C. 3001(9), the human remains described in this notice represent the physical remains of one individual of Native American ancestry. \n \\xe2\\x80\\xa2 Pursuant to 25 U.S.C. 3001(2), a relationship of shared group identity cannot be reasonably traced between the Native American human remains and any present-day Indian tribe. \n \\xe2\\x80\\xa2 According to final judgments of the Indian Claims Commission or the Court of Federal Claims, the land from which the Native American human remains were removed is the aboriginal land of the Cherokee Nation, Eastern Band of Cherokee Indians, The Chickasaw Nation, and the United Keetoowah Band of Cherokee Indians in Oklahoma. \n \\xe2\\x80\\xa2 Treaties, Acts of Congress, or Executive Orders, indicate that the land from which the Native American human remains were removed is the aboriginal land of the Cherokee Nation, Eastern Band of Cherokee Indians, The Chickasaw Nation, and the United Keetoowah Band of Cherokee Indians in Oklahoma. \n \\xe2\\x80\\xa2 Pursuant to 43 CFR 10.11(c)(1), the disposition of the human remains may be to the Cherokee Nation, Eastern Band of Cherokee Indians, The Chickasaw Nation, and the United Keetoowah Band of Cherokee Indians in Oklahoma. \n Additional Requestors and Disposition \n Representatives of any Indian tribe or Native Hawaiian organization not identified in this notice that wish to request transfer of control of these human remains should submit a written request with information in support of the request to Kathleen P. O\\'Malley, Hood Museum of Art, Dartmouth College, 6 East Wheelock Street, Hanover, NH 03755, telephone (603) 646-3853, email kathleen.p.omalley@dartmouth.edu, by December 28, 2016. After that date, if no additional requestors have come forward, transfer of control of the human remains to the Cherokee Nation, Eastern Band of Cherokee Indians, The Chickasaw Nation, and the United Keetoowah Band of Cherokee Indians in Oklahoma may proceed. \n The Hood Museum of Art is responsible for notifying the Cherokee Nation, Eastern Band of Cherokee Indians, The Chickasaw Nation, The Muscogee (Creek) Nation, and the United Keetoowah Band of Cherokee Indians in Oklahoma that this notice has been published. \n ", "consultation": "A detailed assessment of the human remains was made by the Hood Museum of Art professional staff in consultation with representatives of the Cherokee Nation, Eastern Band of Cherokee Indians, The Chickasaw Nation, The Muscogee (Creek) Nation, and the United Keetoowah Band of Cherokee Indians in Oklahoma. \n ", "h_d_r": "In August of 1932, human remains representing, at minimum, one individual were removed from an \\xe2\\x80\\x9cIndian mound\\xe2\\x80\\x9d at Hood\\'s Landing in Marion County, TN, one-quarter mile west of the Oxbow by Robert M. Bear of the Education Department at Dartmouth College. The human remains were donated to the Dartmouth College Museum and subsequently transferred to the Department of Anthropology, Dartmouth College in 1939. In 1993, in compliance with NAGPRA, officials of the Hood Museum of Art took control of the human remains and included them in an Inventory of Native American Human Remains in the Possession of the Hood Museum of Art at Dartmouth College that are considered to be Culturally Unidentifiable. No known individuals were identified. No associated funerary objects are present. \n ", "h_d_ci": "Null", "determinations": "Determinations Made by the Hood Museum of Art, Dartmouth College, Hanover, NH \n Officials of the Hood Museum of Art, Dartmouth College have determined that: \n \\xe2\\x80\\xa2 Pursuant to 25 U.S.C. 3001(9), the human remains described in this notice are Native American based on osteological evidence as determined by professors in the Physical Anthropology Department at Dartmouth College and collection history. \n \\xe2\\x80\\xa2 Pursuant to 25 U.S.C. 3001(9), the human remains described in this notice represent the physical remains of one individual of Native American ancestry. \n \\xe2\\x80\\xa2 Pursuant to 25 U.S.C. 3001(2), a relationship of shared group identity cannot be reasonably traced between the Native American human remains and any present-day Indian tribe. \n \\xe2\\x80\\xa2 According to final judgments of the Indian Claims Commission or the Court of Federal Claims, the land from which the Native American human remains were removed is the aboriginal land of the Cherokee Nation, Eastern Band of Cherokee Indians, The Chickasaw Nation, and the United Keetoowah Band of Cherokee Indians in Oklahoma. \n \\xe2\\x80\\xa2 Treaties, Acts of Congress, or Executive Orders, indicate that the land from which the Native American human remains were removed is the aboriginal land of the Cherokee Nation, Eastern Band of Cherokee Indians, The Chickasaw Nation, and the United Keetoowah Band of Cherokee Indians in Oklahoma. \n \\xe2\\x80\\xa2 Pursuant to 43 CFR 10.11(c)(1), the disposition of the human remains may be to the Cherokee Nation, Eastern Band of Cherokee Indians, The Chickasaw Nation, and the United Keetoowah Band of Cherokee Indians in Oklahoma. \n ", "a_r_d": "Representatives of any Indian tribe or Native Hawaiian organization not identified in this notice that wish to request transfer of control of these human remains should submit a written request with information in support of the request to Kathleen P. O\\'Malley, Hood Museum of Art, Dartmouth College, 6 East Wheelock Street, Hanover, NH 03755, telephone (603) 646-3853, email kathleen.p.omalley@dartmouth.edu, by December 28, 2016. After that date, if no additional requestors have come forward, transfer of control of the human remains to the Cherokee Nation, Eastern Band of Cherokee Indians, The Chickasaw Nation, and the United Keetoowah Band of Cherokee Indians in Oklahoma may proceed. \n The Hood Museum of Art is responsible for notifying the Cherokee Nation, Eastern Band of Cherokee Indians, The Chickasaw Nation, The Muscogee (Creek) Nation, and the United Keetoowah Band of Cherokee Indians in Oklahoma that this notice has been published. \n "}