{"index": "I_510", "messy_full": "\\n      \\n        DEPARTMENT OF THE INTERIOR\\n        National Park Service\\n        [NPS-WASO-NAGPRA-22016; PPWOCRADN0-PCU00RP14.R50000]\\n        Notice of Inventory Completion: Peabody Museum of Archaeology and Ethnology, Harvard University, Cambridge, MA\\n        \\n          AGENCY:\\n          National Park Service, Interior.\\n        \\n        \\n          ACTION:\\n          Notice.\\n        \\n        \\n          SUMMARY:\\n          The Peabody Museum of Archaeology and Ethnology has completed an inventory of human remains in consultation with the appropriate Indian tribes or Native Hawaiian organizations, and has determined that there is no cultural affiliation between the human remains and any present-day Indian tribes or Native Hawaiian organizations. Representatives of any Indian tribe or Native Hawaiian organization not identified in this notice that wish to request transfer of control of these human remains should submit a written request to the Peabody Museum of Archaeology and Ethnology. If no additional requestors come forward, transfer of control of the human remains to the Indian tribes or Native Hawaiian organizations stated in this notice may proceed.\\n        \\n        \\n          DATES:\\n          Representatives of any Indian tribe or Native Hawaiian organization not identified in this notice that wish to request transfer of control of these human remains should submit a written request with information in support of the request to the Peabody Museum of Archaeology and Ethnology at the address in this notice by November 2, 2016.\\n        \\n        \\n          ADDRESSES:\\n\\n          Patricia Capone, Museum Curator and Director of Research and Repatriation, Peabody Museum of Archaeology and Ethnology, Harvard University, 11 Divinity Avenue, Cambridge, MA 02138, telephone (617) 496-3702, email pcapone@fas.harvard.edu.\\n          \\n        \\n      \\n      \\n        SUPPLEMENTARY INFORMATION:\\n        Notice is here given in accordance with the Native American Graves Protection and Repatriation Act (NAGPRA), 25 U.S.C. 3003, of the completion of an inventory of human remains under the control of the Peabody Museum of Archaeology and Ethnology, Harvard University, Cambridge, MA. The human remains were removed from an unknown location in Michigan.\\n        This notice is published as part of the National Park Service\\'s administrative responsibilities under NAGPRA, 25 U.S.C. 3003(d)(3) and 43 CFR 10.11(d). The determinations in this notice are the sole responsibility of the museum, institution, or Federal agency that has control of the Native American human remains. The National Park Service is not responsible for the determinations in this notice.\\n        Consultation\\n\\n        A detailed assessment of the human remains was made by the Peabody Museum of Archaeology and Ethnology professional staff in consultation with representatives of Bay Mills Indian Community, Michigan; Grand Traverse Band of Ottawa and Chippewa Indians, Michigan; Hannahville Indian Community, Michigan; Keweenaw Bay Indian Community, Michigan; Lac Vieux Desert Band of Lake Superior Chippewa Indians of Michigan; Little River Band of Ottawa Indians, Michigan; Little Traverse Bay Bands of Odawa Indians, Michigan; Match-e-be-nash-she-wish Band of Pottawatomi Indians of Michigan; Nottawaseppi Huron Band of the Potawatomi, Michigan (previously listed as the Huron Potawatomi, Inc.); Pokagon Band of Potawatomi Indians, Michigan and Indiana; Saginaw Chippewa Indian Tribe of Michigan; and Sault Ste. Marie Tribe of Chippewa Indians, Michigan. Additional requests for consultation were sent to the Absentee-Shawnee Tribe of Indians of Oklahoma; Bad River Band of the Lake Superior Tribe of Chippewa Indians of the Bad River Reservation, Wisconsin; Bois Forte Band (Nett Lake) of the Minnesota Chippewa Tribe, Minnesota; Chippewa Cree Indians of the Rocky Boy\\'s Reservation, Montana (previously listed as the Chippewa-Cree Indians of the Rocky Boy\\'s Reservation, Montana); Citizen Potawatomi Nation, Oklahoma; Delaware Nation, Oklahoma; Delaware Tribe of Indians; Fond du Lac Band of the Minnesota Chippewa Tribe, Minnesota; Forest County Potawatomi Community, Wisconsin; Grand Portage Band of the Minnesota Chippewa Tribe, Minnesota; Ho-Chunk Nation of Wisconsin; Kickapoo Traditional Tribe of Texas; Kickapoo Tribe of Indians of the Kickapoo Reservation in Kansas; Kickapoo Tribe of Oklahoma; Lac Courte Oreilles Band of Lake Superior Chippewa Indians of Wisconsin; Lac du Flambeau Band of Lake Superior Chippewa Indians of the Lac du Flambeau Reservation of Wisconsin; Leech Lake Band of the Minnesota Chippewa Tribe, Minnesota; Menominee Indian Tribe of Wisconsin; Miami Tribe of Oklahoma; Mille Lacs Band of the Minnesota Chippewa Tribe, Minnesota; Oneida Nation (previously listed as the Oneida Tribe of Indians of Wisconsin); Ottawa Tribe of Oklahoma; Peoria Tribe of Indians of Oklahoma; Prairie Band Potawatomi Nation (previously listed as the Prairie Band of Potawatomi Nation, Kansas); Red Cliff Band of Lake Superior Chippewa Indians of Wisconsin; Red Lake Band of Chippewa Indians, Minnesota; Sac & Fox Nation of Missouri in Kansas and Nebraska; Sac & Fox Nation, Oklahoma; Sac & Fox Tribe of the Mississippi in Iowa; Seneca Nation of Indians (previously listed as the Seneca Nation of Indians, New York); Seneca-Cayuga Nation (previously listed as the Seneca-Cayuga Tribe of Oklahoma); Shawnee Tribe; Sokaogon Chippewa Community, Wisconsin; St. Croix Chippewa Indians of Wisconsin; Stockbridge Munsee Community, Wisconsin; Tonawanda Band of Seneca (previously listed as the Tonawanda Band of Seneca of New York); Turtle Mountain Band of Chippewa Indians of North Dakota; White Earth Band of Minnesota Chippewa Tribe, Minnesota; and the Wyandotte Nation (hereinafter referred to as \\xe2\\x80\\x9cThe Invited and Consulted Tribes\\xe2\\x80\\x9d).\\n        History and Description of the Remains\\n        At an unknown time, human remains representing, at minimum, 1 individual were removed an unknown location in Michigan. The circumstances of acquisition are unknown. No known individuals were identified.\\n        Determinations Made by the Peabody Museum of Archaeology and Ethnology\\n        Officials of the Peabody Museum of Archaeology and Ethnology have determined that:\\n        \\xe2\\x80\\xa2 Pursuant to 25 U.S.C. 3001(9), the human remains described in this notice are Native American based on museum context.\\n        \\xe2\\x80\\xa2 Pursuant to 25 U.S.C. 3001(9), the human remains described in this notice represent the physical remains of one individuals of Native American ancestry.\\n        \\xe2\\x80\\xa2 Pursuant to 25 U.S.C. 3001(2), a relationship of shared group identity cannot be reasonably traced between the Native American human remains and any present-day Indian tribe.\\n        \\xe2\\x80\\xa2 According to final judgments of the Indian Claims Commission or the Court of Federal Claims, Treaties, Acts of Congress, or Executive Orders, the land from which the Native American human remains were removed is the aboriginal land of The Invited and Consulted Tribes.\\n        \\xe2\\x80\\xa2 Pursuant to 43 CFR 10.11(c)(1), the disposition of the human remains may be to The Invited and Consulted Tribes.\\n        Additional Requestors and Disposition\\n\\n        Representatives of any Indian tribe or Native Hawaiian organization not identified in this notice that wish to request transfer of control of these human remains should submit a written request with information in support of the request to Patricia Capone, Museum Curator and Director of Research and Repatriation, Peabody Museum of Archaeology and Ethnology, Harvard University, 11 Divinity Avenue, Cambridge, MA 02138, telephone (617) 496-3702, email pcapone@fas.harvard.edu by November 2, 2016. After that date, if no additional requestors have come forward, transfer of control of the human remains to The Invited and Consulted Tribes may proceed.\\n        The Peabody Museum of Archaeology and Ethnology is responsible for notifying The Invited and Consulted Tribes that this notice has been published.\\n        \\n          Dated: September 19, 2016.\\n          Melanie O\\'Brien,\\n          Manager, National NAGPRA Program.\\n        \\n      \\n      [FR Doc. 2016-23811 Filed 9-30-16; 8:45 am]\\n       BILLING CODE 4312-52-P\\n    ", "agency1": "DEPARTMENT OF THE INTERIOR", "sub_agency1": "National Park Service", "dep_doc": "[NPS-WASO-NAGPRA-22016; PPWOCRADN0-PCU00RP14.R50000]", "subject": "Notice of Inventory Completion: Peabody Museum of Archaeology and Ethnology, Harvard University, Cambridge, MA", "agency2": "National Park Service, Interior.", "action": "Notice.", "summary": "The Peabody Museum of Archaeology and Ethnology has completed an inventory of human remains in consultation with the appropriate Indian tribes or Native Hawaiian organizations, and has determined that there is no cultural affiliation between the human remains and any present-day Indian tribes or Native Hawaiian organizations. Representatives of any Indian tribe or Native Hawaiian organization not identified in this notice that wish to request transfer of control of these human remains should submit a written request to the Peabody Museum of Archaeology and Ethnology. If no additional requestors come forward, transfer of control of the human remains to the Indian tribes or Native Hawaiian organizations stated in this notice may proceed.", "dates": "Representatives of any Indian tribe or Native Hawaiian organization not identified in this notice that wish to request transfer of control of these human remains should submit a written request with information in support of the request to the Peabody Museum of Archaeology and Ethnology at the address in this notice by November 2, 2016.", "addresses": "Patricia Capone, Museum Curator and Director of Research and Repatriation, Peabody Museum of Archaeology and Ethnology, Harvard University, 11 Divinity Avenue, Cambridge, MA 02138, telephone (617) 496-3702, email pcapone@fas.harvard.edu.\\n          ", "signature_dated": "Dated: September 19, 2016.", "signature_name": "Melanie O\\'Brien,", "signature_title": "Manager, National NAGPRA Program.", "fr_doc": "[FR Doc. 2016-23811 Filed 9-30-16; 8:45 am]", "billing_code": " BILLING CODE 4312-52-P", "supp_info": "SUPPLEMENTARY INFORMATION: \n Notice is here given in accordance with the Native American Graves Protection and Repatriation Act (NAGPRA), 25 U.S.C. 3003, of the completion of an inventory of human remains under the control of the Peabody Museum of Archaeology and Ethnology, Harvard University, Cambridge, MA. The human remains were removed from an unknown location in Michigan. \n This notice is published as part of the National Park Service\\'s administrative responsibilities under NAGPRA, 25 U.S.C. 3003(d)(3) and 43 CFR 10.11(d). The determinations in this notice are the sole responsibility of the museum, institution, or Federal agency that has control of the Native American human remains. The National Park Service is not responsible for the determinations in this notice. \n Consultation \n A detailed assessment of the human remains was made by the Peabody Museum of Archaeology and Ethnology professional staff in consultation with representatives of Bay Mills Indian Community, Michigan; Grand Traverse Band of Ottawa and Chippewa Indians, Michigan; Hannahville Indian Community, Michigan; Keweenaw Bay Indian Community, Michigan; Lac Vieux Desert Band of Lake Superior Chippewa Indians of Michigan; Little River Band of Ottawa Indians, Michigan; Little Traverse Bay Bands of Odawa Indians, Michigan; Match-e-be-nash-she-wish Band of Pottawatomi Indians of Michigan; Nottawaseppi Huron Band of the Potawatomi, Michigan (previously listed as the Huron Potawatomi, Inc.); Pokagon Band of Potawatomi Indians, Michigan and Indiana; Saginaw Chippewa Indian Tribe of Michigan; and Sault Ste. Marie Tribe of Chippewa Indians, Michigan. Additional requests for consultation were sent to the Absentee-Shawnee Tribe of Indians of Oklahoma; Bad River Band of the Lake Superior Tribe of Chippewa Indians of the Bad River Reservation, Wisconsin; Bois Forte Band (Nett Lake) of the Minnesota Chippewa Tribe, Minnesota; Chippewa Cree Indians of the Rocky Boy\\'s Reservation, Montana (previously listed as the Chippewa-Cree Indians of the Rocky Boy\\'s Reservation, Montana); Citizen Potawatomi Nation, Oklahoma; Delaware Nation, Oklahoma; Delaware Tribe of Indians; Fond du Lac Band of the Minnesota Chippewa Tribe, Minnesota; Forest County Potawatomi Community, Wisconsin; Grand Portage Band of the Minnesota Chippewa Tribe, Minnesota; Ho-Chunk Nation of Wisconsin; Kickapoo Traditional Tribe of Texas; Kickapoo Tribe of Indians of the Kickapoo Reservation in Kansas; Kickapoo Tribe of Oklahoma; Lac Courte Oreilles Band of Lake Superior Chippewa Indians of Wisconsin; Lac du Flambeau Band of Lake Superior Chippewa Indians of the Lac du Flambeau Reservation of Wisconsin; Leech Lake Band of the Minnesota Chippewa Tribe, Minnesota; Menominee Indian Tribe of Wisconsin; Miami Tribe of Oklahoma; Mille Lacs Band of the Minnesota Chippewa Tribe, Minnesota; Oneida Nation (previously listed as the Oneida Tribe of Indians of Wisconsin); Ottawa Tribe of Oklahoma; Peoria Tribe of Indians of Oklahoma; Prairie Band Potawatomi Nation (previously listed as the Prairie Band of Potawatomi Nation, Kansas); Red Cliff Band of Lake Superior Chippewa Indians of Wisconsin; Red Lake Band of Chippewa Indians, Minnesota; Sac & Fox Nation of Missouri in Kansas and Nebraska; Sac & Fox Nation, Oklahoma; Sac & Fox Tribe of the Mississippi in Iowa; Seneca Nation of Indians (previously listed as the Seneca Nation of Indians, New York); Seneca-Cayuga Nation (previously listed as the Seneca-Cayuga Tribe of Oklahoma); Shawnee Tribe; Sokaogon Chippewa Community, Wisconsin; St. Croix Chippewa Indians of Wisconsin; Stockbridge Munsee Community, Wisconsin; Tonawanda Band of Seneca (previously listed as the Tonawanda Band of Seneca of New York); Turtle Mountain Band of Chippewa Indians of North Dakota; White Earth Band of Minnesota Chippewa Tribe, Minnesota; and the Wyandotte Nation (hereinafter referred to as \\xe2\\x80\\x9cThe Invited and Consulted Tribes\\xe2\\x80\\x9d). \n History and Description of the Remains \n At an unknown time, human remains representing, at minimum, 1 individual were removed an unknown location in Michigan. The circumstances of acquisition are unknown. No known individuals were identified. \n Determinations Made by the Peabody Museum of Archaeology and Ethnology \n Officials of the Peabody Museum of Archaeology and Ethnology have determined that: \n \\xe2\\x80\\xa2 Pursuant to 25 U.S.C. 3001(9), the human remains described in this notice are Native American based on museum context. \n \\xe2\\x80\\xa2 Pursuant to 25 U.S.C. 3001(9), the human remains described in this notice represent the physical remains of one individuals of Native American ancestry. \n \\xe2\\x80\\xa2 Pursuant to 25 U.S.C. 3001(2), a relationship of shared group identity cannot be reasonably traced between the Native American human remains and any present-day Indian tribe. \n \\xe2\\x80\\xa2 According to final judgments of the Indian Claims Commission or the Court of Federal Claims, Treaties, Acts of Congress, or Executive Orders, the land from which the Native American human remains were removed is the aboriginal land of The Invited and Consulted Tribes. \n \\xe2\\x80\\xa2 Pursuant to 43 CFR 10.11(c)(1), the disposition of the human remains may be to The Invited and Consulted Tribes. \n Additional Requestors and Disposition \n Representatives of any Indian tribe or Native Hawaiian organization not identified in this notice that wish to request transfer of control of these human remains should submit a written request with information in support of the request to Patricia Capone, Museum Curator and Director of Research and Repatriation, Peabody Museum of Archaeology and Ethnology, Harvard University, 11 Divinity Avenue, Cambridge, MA 02138, telephone (617) 496-3702, email pcapone@fas.harvard.edu by November 2, 2016. After that date, if no additional requestors have come forward, transfer of control of the human remains to The Invited and Consulted Tribes may proceed. \n The Peabody Museum of Archaeology and Ethnology is responsible for notifying The Invited and Consulted Tribes that this notice has been published. \n ", "consultation": "A detailed assessment of the human remains was made by the Peabody Museum of Archaeology and Ethnology professional staff in consultation with representatives of Bay Mills Indian Community, Michigan; Grand Traverse Band of Ottawa and Chippewa Indians, Michigan; Hannahville Indian Community, Michigan; Keweenaw Bay Indian Community, Michigan; Lac Vieux Desert Band of Lake Superior Chippewa Indians of Michigan; Little River Band of Ottawa Indians, Michigan; Little Traverse Bay Bands of Odawa Indians, Michigan; Match-e-be-nash-she-wish Band of Pottawatomi Indians of Michigan; Nottawaseppi Huron Band of the Potawatomi, Michigan (previously listed as the Huron Potawatomi, Inc.); Pokagon Band of Potawatomi Indians, Michigan and Indiana; Saginaw Chippewa Indian Tribe of Michigan; and Sault Ste. Marie Tribe of Chippewa Indians, Michigan. Additional requests for consultation were sent to the Absentee-Shawnee Tribe of Indians of Oklahoma; Bad River Band of the Lake Superior Tribe of Chippewa Indians of the Bad River Reservation, Wisconsin; Bois Forte Band (Nett Lake) of the Minnesota Chippewa Tribe, Minnesota; Chippewa Cree Indians of the Rocky Boy\\'s Reservation, Montana (previously listed as the Chippewa-Cree Indians of the Rocky Boy\\'s Reservation, Montana); Citizen Potawatomi Nation, Oklahoma; Delaware Nation, Oklahoma; Delaware Tribe of Indians; Fond du Lac Band of the Minnesota Chippewa Tribe, Minnesota; Forest County Potawatomi Community, Wisconsin; Grand Portage Band of the Minnesota Chippewa Tribe, Minnesota; Ho-Chunk Nation of Wisconsin; Kickapoo Traditional Tribe of Texas; Kickapoo Tribe of Indians of the Kickapoo Reservation in Kansas; Kickapoo Tribe of Oklahoma; Lac Courte Oreilles Band of Lake Superior Chippewa Indians of Wisconsin; Lac du Flambeau Band of Lake Superior Chippewa Indians of the Lac du Flambeau Reservation of Wisconsin; Leech Lake Band of the Minnesota Chippewa Tribe, Minnesota; Menominee Indian Tribe of Wisconsin; Miami Tribe of Oklahoma; Mille Lacs Band of the Minnesota Chippewa Tribe, Minnesota; Oneida Nation (previously listed as the Oneida Tribe of Indians of Wisconsin); Ottawa Tribe of Oklahoma; Peoria Tribe of Indians of Oklahoma; Prairie Band Potawatomi Nation (previously listed as the Prairie Band of Potawatomi Nation, Kansas); Red Cliff Band of Lake Superior Chippewa Indians of Wisconsin; Red Lake Band of Chippewa Indians, Minnesota; Sac & Fox Nation of Missouri in Kansas and Nebraska; Sac & Fox Nation, Oklahoma; Sac & Fox Tribe of the Mississippi in Iowa; Seneca Nation of Indians (previously listed as the Seneca Nation of Indians, New York); Seneca-Cayuga Nation (previously listed as the Seneca-Cayuga Tribe of Oklahoma); Shawnee Tribe; Sokaogon Chippewa Community, Wisconsin; St. Croix Chippewa Indians of Wisconsin; Stockbridge Munsee Community, Wisconsin; Tonawanda Band of Seneca (previously listed as the Tonawanda Band of Seneca of New York); Turtle Mountain Band of Chippewa Indians of North Dakota; White Earth Band of Minnesota Chippewa Tribe, Minnesota; and the Wyandotte Nation (hereinafter referred to as \\xe2\\x80\\x9cThe Invited and Consulted Tribes\\xe2\\x80\\x9d). \n ", "h_d_r": "At an unknown time, human remains representing, at minimum, 1 individual were removed an unknown location in Michigan. The circumstances of acquisition are unknown. No known individuals were identified. \n ", "h_d_ci": "Null", "determinations": "Determinations Made by the Peabody Museum of Archaeology and Ethnology \n Officials of the Peabody Museum of Archaeology and Ethnology have determined that: \n \\xe2\\x80\\xa2 Pursuant to 25 U.S.C. 3001(9), the human remains described in this notice are Native American based on museum context. \n \\xe2\\x80\\xa2 Pursuant to 25 U.S.C. 3001(9), the human remains described in this notice represent the physical remains of one individuals of Native American ancestry. \n \\xe2\\x80\\xa2 Pursuant to 25 U.S.C. 3001(2), a relationship of shared group identity cannot be reasonably traced between the Native American human remains and any present-day Indian tribe. \n \\xe2\\x80\\xa2 According to final judgments of the Indian Claims Commission or the Court of Federal Claims, Treaties, Acts of Congress, or Executive Orders, the land from which the Native American human remains were removed is the aboriginal land of The Invited and Consulted Tribes. \n \\xe2\\x80\\xa2 Pursuant to 43 CFR 10.11(c)(1), the disposition of the human remains may be to The Invited and Consulted Tribes. \n ", "a_r_d": "Representatives of any Indian tribe or Native Hawaiian organization not identified in this notice that wish to request transfer of control of these human remains should submit a written request with information in support of the request to Patricia Capone, Museum Curator and Director of Research and Repatriation, Peabody Museum of Archaeology and Ethnology, Harvard University, 11 Divinity Avenue, Cambridge, MA 02138, telephone (617) 496-3702, email pcapone@fas.harvard.edu by November 2, 2016. After that date, if no additional requestors have come forward, transfer of control of the human remains to The Invited and Consulted Tribes may proceed. \n The Peabody Museum of Archaeology and Ethnology is responsible for notifying The Invited and Consulted Tribes that this notice has been published. \n "}