{"index": "I_56", "messy_full": "\\n      \\n        \\n        DEPARTMENT OF THE INTERIOR\\n        National Park Service\\n        [NPS-WASO-NAGPRA-NPS0028308; PPWOCRADN0-PCU00RP14.R50000]\\n        Notice of Inventory Completion: Department of Anthropology, University of Alaska Anchorage, Anchorage, AK\\n        \\n          AGENCY:\\n          National Park Service, Interior.\\n        \\n        \\n          ACTION:\\n          Notice.\\n        \\n        \\n          SUMMARY:\\n          The Department of Anthropology, University of Alaska Anchorage has completed an inventory of human remains, in consultation with the appropriate Indian Tribes or Native Hawaiian organizations, and has determined that there is a cultural affiliation between the human remains and present-day Indian Tribes or Native Hawaiian organizations. Lineal descendants or representatives of any Indian Tribe or Native Hawaiian organization not identified in this notice that wish to request transfer of control of these human remains should submit a written request to the Department of Anthropology, University of Alaska Anchorage. If no additional requestors come forward, transfer of control of the human remains to the lineal descendants, Indian Tribes, or Native Hawaiian organizations stated in this notice may proceed.\\n        \\n        \\n          DATES:\\n          Lineal descendants or representatives of any Indian Tribe or Native Hawaiian organization not identified in this notice that wish to request transfer of control of these human remains should submit a written request with information in support of the request to the Department of Anthropology, University of Alaska Anchorage at the address in this notice by August 19, 2019.\\n        \\n        \\n          ADDRESSES:\\n\\n          Dr. John Stalvey, Interim Provost, University of Alaska Anchorage, 3211 Providence Drive, Anchorage, AK 99508, telephone (907) 786-1050, email Jstalvey@alaska.edu.\\n          \\n        \\n      \\n      \\n        SUPPLEMENTARY INFORMATION:\\n        Notice is here given in accordance with the Native American Graves Protection and Repatriation Act (NAGPRA), 25 U.S.C. 3003, of the completion of an inventory of human remains under the control of the Department of Anthropology, University of Alaska Anchorage, Anchorage, AK. The human remains were removed from Amook Island, Uyak Bay, and Larsen Bay (KAR-029), Kodiak Island, Kodiak Island Borough, AK.\\n        This notice is published as part of the National Park Service\\'s administrative responsibilities under NAGPRA, 25 U.S.C. 3003(d)(3). The determinations in this notice are the sole responsibility of the museum, institution, or Federal agency that has control of the Alaska Native human remains. The National Park Service is not responsible for the determinations in this notice.\\n        Consultation\\n        A detailed assessment of the human remains was made by the Department of Anthropology, University of Alaska Anchorage professional staff in consultation with representatives of the Native Village of Larsen Bay.\\n        History and Description of the Remains\\n        In 1980, human remains representing, at minimum, one individual were removed from the tip of Amook (\\xe2\\x80\\x9cAmok\\xe2\\x80\\x9d) Island, Uyak Bay, in northwestern Kodiak Island, AK, by an unknown individual, and were donated to the Department of Anthropology Laboratory. No known individuals were identified. No associated funerary objects are present.\\n        The human remains are associated with either the Kachemak tradition or the late prehistoric Koniag occupation of Kodiak. The Alutiiq (Sugpiaq) people of the Kodiak Island archipelago are the only present-day descendants of the people who occupied the region before European Contact. They still live within their traditional region.\\n        In 1987, human remains representing, at minimum, four individuals were removed from Larsen Bay (KAR-029) in Kodiak Island Borough, AK. Four individuals (two adults and two juveniles) were excavated from two locations at the site. Two of them are identified as males. The human remains were excavated by Bureau of Indian Affairs archeologists with the support and approval of both the Kodiak Area Native Association and the land owner. The site has a Late Kachemak tradition, a transitional Koniag, and a Koniag phase occupation. Seven radiocarbon dates range between 1310\\xc2\\xb170 and 450\\xc2\\xb170 BP. Although the recovered skeletal remains cannot be unambiguously sorted by phase, certain characteristics such as scattered bones, the absence of skulls, and burned bone are more typical of the late Kachemak tradition than the Koniag phase. No known individuals were identified. No associated funerary objects are present.\\n        The Alutiiq (Sugpiaq) people of Kodiak Island archipelago are the only present-day descendants of the people who lived in the region before European Contact. They still live within their traditional region.\\n        Determinations Made by the Department of Anthropology, University of Alaska Anchorage\\n        Officials of the Department of Anthropology, University of Alaska Anchorage have determined that:\\n        \\xe2\\x80\\xa2 Pursuant to 25 U.S.C. 3001(9), the human remains described in this notice represent the physical remains of five individual of Alaska Native ancestry.\\n        \\xe2\\x80\\xa2 Pursuant to 25 U.S.C. 3001(2), there is a relationship of shared group identity that can be reasonably traced between the Alaska Native human remains and the Native Village of Larsen Bay.\\n        Additional Requestors and Disposition\\n\\n        Lineal descendants or representatives of any Indian Tribe or Native Hawaiian organization not identified in this notice that wish to request transfer of control of these human remains should submit a written request with information in support of the request to Dr. John Stalvey, Interim Provost, University of Alaska Anchorage, 3211 Providence Drive, Anchorage, AK 99508, telephone (907) 786-1050, email Jstalvey@alaska.edu, by August 19, 2019. After that date, if no additional requestors have come forward, transfer of control of the human remains to the Native Village of Larsen Bay may proceed.\\n        The Department of Anthropology, University of Alaska Anchorage is responsible for notifying the Native Village of Larsen Bay that this notice has been published.\\n        \\n          Dated: June 25, 2019.\\n          Melanie O\\'Brien,\\n          Manager, National NAGPRA Program.\\n        \\n      \\n      [FR Doc. 2019-15435 Filed 7-18-19; 8:45 am]\\n      BILLING CODE 4312-52-P\\n    ", "agency1": "DEPARTMENT OF THE INTERIOR", "sub_agency1": "National Park Service", "dep_doc": "[NPS-WASO-NAGPRA-NPS0028308; PPWOCRADN0-PCU00RP14.R50000]", "subject": "Notice of Inventory Completion: Department of Anthropology, University of Alaska Anchorage, Anchorage, AK", "agency2": "National Park Service, Interior.", "action": "Notice.", "summary": "The Department of Anthropology, University of Alaska Anchorage has completed an inventory of human remains, in consultation with the appropriate Indian Tribes or Native Hawaiian organizations, and has determined that there is a cultural affiliation between the human remains and present-day Indian Tribes or Native Hawaiian organizations. Lineal descendants or representatives of any Indian Tribe or Native Hawaiian organization not identified in this notice that wish to request transfer of control of these human remains should submit a written request to the Department of Anthropology, University of Alaska Anchorage. If no additional requestors come forward, transfer of control of the human remains to the lineal descendants, Indian Tribes, or Native Hawaiian organizations stated in this notice may proceed.", "dates": "Lineal descendants or representatives of any Indian Tribe or Native Hawaiian organization not identified in this notice that wish to request transfer of control of these human remains should submit a written request with information in support of the request to the Department of Anthropology, University of Alaska Anchorage at the address in this notice by August 19, 2019.", "addresses": "Dr. John Stalvey, Interim Provost, University of Alaska Anchorage, 3211 Providence Drive, Anchorage, AK 99508, telephone (907) 786-1050, email Jstalvey@alaska.edu.\\n          ", "signature_dated": "Dated: June 25, 2019.", "signature_name": "Melanie O\\'Brien,", "signature_title": "Manager, National NAGPRA Program.", "fr_doc": "[FR Doc. 2019-15435 Filed 7-18-19; 8:45 am]", "billing_code": "BILLING CODE 4312-52-P", "supp_info": "SUPPLEMENTARY INFORMATION: \n Notice is here given in accordance with the Native American Graves Protection and Repatriation Act (NAGPRA), 25 U.S.C. 3003, of the completion of an inventory of human remains under the control of the Department of Anthropology, University of Alaska Anchorage, Anchorage, AK. The human remains were removed from Amook Island, Uyak Bay, and Larsen Bay (KAR-029), Kodiak Island, Kodiak Island Borough, AK. \n This notice is published as part of the National Park Service\\'s administrative responsibilities under NAGPRA, 25 U.S.C. 3003(d)(3). The determinations in this notice are the sole responsibility of the museum, institution, or Federal agency that has control of the Alaska Native human remains. The National Park Service is not responsible for the determinations in this notice. \n Consultation \n A detailed assessment of the human remains was made by the Department of Anthropology, University of Alaska Anchorage professional staff in consultation with representatives of the Native Village of Larsen Bay. \n History and Description of the Remains \n In 1980, human remains representing, at minimum, one individual were removed from the tip of Amook (\\xe2\\x80\\x9cAmok\\xe2\\x80\\x9d) Island, Uyak Bay, in northwestern Kodiak Island, AK, by an unknown individual, and were donated to the Department of Anthropology Laboratory. No known individuals were identified. No associated funerary objects are present. \n The human remains are associated with either the Kachemak tradition or the late prehistoric Koniag occupation of Kodiak. The Alutiiq (Sugpiaq) people of the Kodiak Island archipelago are the only present-day descendants of the people who occupied the region before European Contact. They still live within their traditional region. \n In 1987, human remains representing, at minimum, four individuals were removed from Larsen Bay (KAR-029) in Kodiak Island Borough, AK. Four individuals (two adults and two juveniles) were excavated from two locations at the site. Two of them are identified as males. The human remains were excavated by Bureau of Indian Affairs archeologists with the support and approval of both the Kodiak Area Native Association and the land owner. The site has a Late Kachemak tradition, a transitional Koniag, and a Koniag phase occupation. Seven radiocarbon dates range between 1310\\xc2\\xb170 and 450\\xc2\\xb170 BP. Although the recovered skeletal remains cannot be unambiguously sorted by phase, certain characteristics such as scattered bones, the absence of skulls, and burned bone are more typical of the late Kachemak tradition than the Koniag phase. No known individuals were identified. No associated funerary objects are present. \n The Alutiiq (Sugpiaq) people of Kodiak Island archipelago are the only present-day descendants of the people who lived in the region before European Contact. They still live within their traditional region. \n Determinations Made by the Department of Anthropology, University of Alaska Anchorage \n Officials of the Department of Anthropology, University of Alaska Anchorage have determined that: \n \\xe2\\x80\\xa2 Pursuant to 25 U.S.C. 3001(9), the human remains described in this notice represent the physical remains of five individual of Alaska Native ancestry. \n \\xe2\\x80\\xa2 Pursuant to 25 U.S.C. 3001(2), there is a relationship of shared group identity that can be reasonably traced between the Alaska Native human remains and the Native Village of Larsen Bay. \n Additional Requestors and Disposition \n Lineal descendants or representatives of any Indian Tribe or Native Hawaiian organization not identified in this notice that wish to request transfer of control of these human remains should submit a written request with information in support of the request to Dr. John Stalvey, Interim Provost, University of Alaska Anchorage, 3211 Providence Drive, Anchorage, AK 99508, telephone (907) 786-1050, email Jstalvey@alaska.edu, by August 19, 2019. After that date, if no additional requestors have come forward, transfer of control of the human remains to the Native Village of Larsen Bay may proceed. \n The Department of Anthropology, University of Alaska Anchorage is responsible for notifying the Native Village of Larsen Bay that this notice has been published. \n ", "consultation": "A detailed assessment of the human remains was made by the Department of Anthropology, University of Alaska Anchorage professional staff in consultation with representatives of the Native Village of Larsen Bay. \n ", "h_d_r": "In 1980, human remains representing, at minimum, one individual were removed from the tip of Amook (\\xe2\\x80\\x9cAmok\\xe2\\x80\\x9d) Island, Uyak Bay, in northwestern Kodiak Island, AK, by an unknown individual, and were donated to the Department of Anthropology Laboratory. No known individuals were identified. No associated funerary objects are present. \n The human remains are associated with either the Kachemak tradition or the late prehistoric Koniag occupation of Kodiak. The Alutiiq (Sugpiaq) people of the Kodiak Island archipelago are the only present-day descendants of the people who occupied the region before European Contact. They still live within their traditional region. \n In 1987, human remains representing, at minimum, four individuals were removed from Larsen Bay (KAR-029) in Kodiak Island Borough, AK. Four individuals (two adults and two juveniles) were excavated from two locations at the site. Two of them are identified as males. The human remains were excavated by Bureau of Indian Affairs archeologists with the support and approval of both the Kodiak Area Native Association and the land owner. The site has a Late Kachemak tradition, a transitional Koniag, and a Koniag phase occupation. Seven radiocarbon dates range between 1310\\xc2\\xb170 and 450\\xc2\\xb170 BP. Although the recovered skeletal remains cannot be unambiguously sorted by phase, certain characteristics such as scattered bones, the absence of skulls, and burned bone are more typical of the late Kachemak tradition than the Koniag phase. No known individuals were identified. No associated funerary objects are present. \n The Alutiiq (Sugpiaq) people of Kodiak Island archipelago are the only present-day descendants of the people who lived in the region before European Contact. They still live within their traditional region. \n ", "h_d_ci": "Null", "determinations": "Determinations Made by the Department of Anthropology, University of Alaska Anchorage \n Officials of the Department of Anthropology, University of Alaska Anchorage have determined that: \n \\xe2\\x80\\xa2 Pursuant to 25 U.S.C. 3001(9), the human remains described in this notice represent the physical remains of five individual of Alaska Native ancestry. \n \\xe2\\x80\\xa2 Pursuant to 25 U.S.C. 3001(2), there is a relationship of shared group identity that can be reasonably traced between the Alaska Native human remains and the Native Village of Larsen Bay. \n ", "a_r_d": "Lineal descendants or representatives of any Indian Tribe or Native Hawaiian organization not identified in this notice that wish to request transfer of control of these human remains should submit a written request with information in support of the request to Dr. John Stalvey, Interim Provost, University of Alaska Anchorage, 3211 Providence Drive, Anchorage, AK 99508, telephone (907) 786-1050, email Jstalvey@alaska.edu, by August 19, 2019. After that date, if no additional requestors have come forward, transfer of control of the human remains to the Native Village of Larsen Bay may proceed. \n The Department of Anthropology, University of Alaska Anchorage is responsible for notifying the Native Village of Larsen Bay that this notice has been published. \n "}