{"index": "I_577", "messy_full": "\\n      \\n        DEPARTMENT OF THE INTERIOR\\n        National Park Service\\n        [NPS-WASO-NAGPRA-20401; PPWOCRADN0-PCU00RP14.R50000]\\n        Notice of Inventory Completion: Sheriff\\'s Office, Berrien County, Saint Joseph, MI\\n        \\n          AGENCY:\\n          National Park Service, Interior.\\n        \\n        \\n          ACTION:\\n          Notice.\\n        \\n        \\n          SUMMARY:\\n\\n          The Sheriff\\'s Office of Berrien County, MI has completed an inventory of human remains, in consultation with the appropriate Indian tribes or Native Hawaiian organizations, and has determined that there is no cultural affiliation between the human remains and any present-day Indian tribes or Native Hawaiian organizations. Representatives of any Indian tribe or Native Hawaiian organization not identified in this notice that wish to request transfer of control of these human remains should submit a written request to the Berrien County Sheriff\\'s Office. If no additional requestors come forward, transfer of control of the human remains to the Indian tribes or Native Hawaiian organizations stated in this notice may proceed.\\n        \\n        \\n          DATES:\\n          Representatives of any Indian tribe or Native Hawaiian organization not identified in this notice that wish to request transfer of control of these human remains should submit a written request with information in support of the request to the Berrien County Sheriff\\'s Office at the address in this notice by April 29, 2016.\\n        \\n        \\n          ADDRESSES:\\n\\n          Berrien County Sheriff\\'s Office, Attention Chief Deputy Michael Bradley, 919 Port Street, Saint Joseph, MI 49085, email mbradley@berriencounty.org.\\n          \\n        \\n      \\n      \\n        SUPPLEMENTARY INFORMATION:\\n        Notice is here given in accordance with the Native American Graves Protection and Repatriation Act (NAGPRA), 25 U.S.C. 3003, of the completion of an inventory of human remains under the control of the Berrien County Sheriff\\'s Office. The human remains were removed from Galien River in New Buffalo, MI.\\n        This notice is published as part of the National Park Service\\'s administrative responsibilities under NAGPRA, 25 U.S.C. 3003(d)(3) and 43 CFR 10.11(d). The determinations in this notice are the sole responsibility of the museum, institution, or Federal agency that has control of the Native American human remains. The National Park Service is not responsible for the determinations in this notice.\\n        \\n          Consultation: A detailed assessment of the human remains was made by the Berrien County Sheriff\\'s office and the Michigan State University Anthropology Department professional staff in consultation with representatives of the Absentee-Shawnee Tribe of Indians of Oklahoma; Bad River Band of the Lake Superior Tribe of Chippewa Indians of the Bad River Reservation, Wisconsin; Bay Mills Indian Community, Michigan; Bois Forte Band (Nett Lake) of the Minnesota Chippewa Tribe, Minnesota; Chippewa-Cree Indians of the Rocky Boy\\'s Reservation, Montana (previously listed as the Chippewa-Cree Indians of the Rocky Boy\\'s Reservation, Montana); Citizen Potowatomi Nation, Oklahoma; Delaware Nation, Oklahoma; Eastern Shawnee Tribe of Oklahoma; Fond du Lac Band of the Minnesota Chippewa Tribe, Minnesota; Forest County Potowatomi Community, Wisconsin; Grand Portage Band of the Minnesota Chippewa Tribe, Minnesota; Grand Traverse Band of the Ottawa and the Chippewa Indians, Michigan; Hannahville Indian Community, Michigan; Ho-Chunk Nation of Wisconsin; Keweenaw Bay Indian Community, Michigan; Kickapoo Tribe of Indians of the Kickapoo Reservation in Kansas; Kickapoo Tribe of Oklahoma; Lac Courte Oreilles Band of Lake Superior Chippewa Indians of Wisconsin; Lac Vieux Desert Band of Lake Superior Chippewa Indians of Michigan; Leech Lake Band of the Minnesota Chippewa Tribe, Minnesota; Little River Band of Ottawa Indians, Michigan; Little Traverse Bay Bands of Odawa Indians, Michigan; Match-e-be-nash-she-wish Band of Pottowatomi Indians of Michigan; Miami Tribe of Oklahoma; Mille Lacs Band of the Minnesota Chippewa Tribe, Minnesota; Nottawaseppi Huron Band of the Potawatomi, Michigan (previously listed as the Huron Potawatomi, Inc.); Ottawa Tribe of Oklahoma; Peoria Tribe of Indians of Oklahoma; Pokagon Band of Potawatomi Indians, Michigan and Indiana; Prairie Band of Potowatomi Nation (previously listed as the Prairie Band of Potowatomi Nation, Kansas); Red Cliff Band of Lake Superior Chippewa Indians of Wisconsin; Red Lake Band of Chippewa Indians, Minnesota; Sac and Fox Tribe of the Mississippi in Iowa; Sac and Fox Nation of Missouri in Kansas and Nebraska, Sac and Fox Nation, Oklahoma; Saginaw Chippewa Indian Tribe of Michigan; Sault Ste. Marie Tribe of Chippewa Indians, Michigan; Shawnee Tribe; Sokaogon Chippewa Community, Wisconsin; St. Croix Chippewa Indians of Wisconsin; Turtle Mountain Band of Chippewa Indians of North Dakota; White Earth Band of Minnesota Chippewa Tribe, Minnesota; Winnebago Tribe of Nebraska; and the Wyandotte Nation (hereafter The Consulted Tribes).\\n        History and Description of the Remains\\n        In April 2011, human remains representing, at minimum, one individual were removed from Galien River in Berrien County, MI. In early April of 2011 a minor was fishing in the Galien River in new Buffalo Township, MI. After casting into the center of the river the youth reeled in what appeared to be a large bone. The youth took the bone to his high school science teacher who contacted the Berrien County Sheriff\\'s Office.\\n        The Sheriff\\'s Office\\'s Dive Team responded by searching a section of the river approximately eight feet square, where they found additional skeletonized human remains. All of the human remains, including the original bone found by the minor, were transported to the Anthropology Department at Michigan State University and examined by Dr. Norman Sauer. The human remains were found to be \\xe2\\x80\\x9cadult prehistoric Native American\\xe2\\x80\\x9d of indeterminate gender, and returned to the Berrien County Sheriff\\'s Office. No known individuals were identified. No associated funerary objects are present.\\n        At the time of the excavation and removal of these human remains, the land from which the remains were removed was not the tribal land of any Indian tribe or Native Hawaiian organization.\\n        Determinations Made by the Berrien County Sheriff\\'s Office\\n        Officials of the Berrien County Sheriff\\'s Office have determined that:\\n        \\xe2\\x80\\xa2 Pursuant to 25 U.S.C. 3001(9), the human remains described in this notice are Native American based on osteological evidence.\\n        \\xe2\\x80\\xa2 Pursuant to 25 U.S.C. 3001(9), the human remains described in this notice represent the physical remains of one individual of Native American ancestry.\\n        \\xe2\\x80\\xa2 Pursuant to 25 U.S.C. 3001(2), a relationship of shared group identity cannot be reasonably traced between the Native American human remains and any present-day Indian tribe.\\n        \\xe2\\x80\\xa2 According to final judgments of the Indian Claims Commission or the Court of Federal Claims, the land from which the Native American human remains were removed is the aboriginal land of The Consulted Tribes\\n        \\xe2\\x80\\xa2 Pursuant to 43 CFR 10.11(c)(2)(i), the disposition of the human remains may be to The Consulted Tribes.\\n        Additional Requestors and Disposition\\n\\n        Representatives of any Indian tribe or Native Hawaiian organization not identified in this notice that wish to request transfer of control of these human remains should submit a written request with information in support of the request to the Berrien County Sheriff\\'s Office, Attention Chief Deputy Michael Bradley, 919 Port Street, Saint Joseph, MI 49085, email mbradley@berriencounty.org by April 29, 2016.\\n        After that date, if no additional requestors have come forward, transfer of control of the human remains to The Consulted Tribes may proceed.\\n        The Berrien County Sheriff\\'s Office is responsible for informing The Consulted Tribes that this notice has been published:\\n        \\n          Dated: February 18, 2016.\\n          Melanie O\\'Brien,\\n          Manager, National NAGPRA Program.\\n        \\n      \\n      [FR Doc. 2016-07106 Filed 3-29-16; 8:45 am]\\n       BILLING CODE 4312-50-P\\n    ", "agency1": "DEPARTMENT OF THE INTERIOR", "sub_agency1": "National Park Service", "dep_doc": "[NPS-WASO-NAGPRA-20401; PPWOCRADN0-PCU00RP14.R50000]", "subject": "Notice of Inventory Completion: Sheriff\\'s Office, Berrien County, Saint Joseph, MI", "agency2": "National Park Service, Interior.", "action": "Notice.", "summary": "The Sheriff\\'s Office of Berrien County, MI has completed an inventory of human remains, in consultation with the appropriate Indian tribes or Native Hawaiian organizations, and has determined that there is no cultural affiliation between the human remains and any present-day Indian tribes or Native Hawaiian organizations. Representatives of any Indian tribe or Native Hawaiian organization not identified in this notice that wish to request transfer of control of these human remains should submit a written request to the Berrien County Sheriff\\'s Office. If no additional requestors come forward, transfer of control of the human remains to the Indian tribes or Native Hawaiian organizations stated in this notice may proceed.", "dates": "Representatives of any Indian tribe or Native Hawaiian organization not identified in this notice that wish to request transfer of control of these human remains should submit a written request with information in support of the request to the Berrien County Sheriff\\'s Office at the address in this notice by April 29, 2016.", "addresses": "Berrien County Sheriff\\'s Office, Attention Chief Deputy Michael Bradley, 919 Port Street, Saint Joseph, MI 49085, email mbradley@berriencounty.org.\\n          ", "signature_dated": "Dated: February 18, 2016.", "signature_name": "Melanie O\\'Brien,", "signature_title": "Manager, National NAGPRA Program.", "fr_doc": "[FR Doc. 2016-07106 Filed 3-29-16; 8:45 am]", "billing_code": " BILLING CODE 4312-50-P", "supp_info": "SUPPLEMENTARY INFORMATION: \n Notice is here given in accordance with the Native American Graves Protection and Repatriation Act (NAGPRA), 25 U.S.C. 3003, of the completion of an inventory of human remains under the control of the Berrien County Sheriff\\'s Office. The human remains were removed from Galien River in New Buffalo, MI. \n This notice is published as part of the National Park Service\\'s administrative responsibilities under NAGPRA, 25 U.S.C. 3003(d)(3) and 43 CFR 10.11(d). The determinations in this notice are the sole responsibility of the museum, institution, or Federal agency that has control of the Native American human remains. The National Park Service is not responsible for the determinations in this notice. \n \\n          Consultation: A detailed assessment of the human remains was made by the Berrien County Sheriff\\'s office and the Michigan State University Anthropology Department professional staff in consultation with representatives of the Absentee-Shawnee Tribe of Indians of Oklahoma; Bad River Band of the Lake Superior Tribe of Chippewa Indians of the Bad River Reservation, Wisconsin; Bay Mills Indian Community, Michigan; Bois Forte Band (Nett Lake) of the Minnesota Chippewa Tribe, Minnesota; Chippewa-Cree Indians of the Rocky Boy\\'s Reservation, Montana (previously listed as the Chippewa-Cree Indians of the Rocky Boy\\'s Reservation, Montana); Citizen Potowatomi Nation, Oklahoma; Delaware Nation, Oklahoma; Eastern Shawnee Tribe of Oklahoma; Fond du Lac Band of the Minnesota Chippewa Tribe, Minnesota; Forest County Potowatomi Community, Wisconsin; Grand Portage Band of the Minnesota Chippewa Tribe, Minnesota; Grand Traverse Band of the Ottawa and the Chippewa Indians, Michigan; Hannahville Indian Community, Michigan; Ho-Chunk Nation of Wisconsin; Keweenaw Bay Indian Community, Michigan; Kickapoo Tribe of Indians of the Kickapoo Reservation in Kansas; Kickapoo Tribe of Oklahoma; Lac Courte Oreilles Band of Lake Superior Chippewa Indians of Wisconsin; Lac Vieux Desert Band of Lake Superior Chippewa Indians of Michigan; Leech Lake Band of the Minnesota Chippewa Tribe, Minnesota; Little River Band of Ottawa Indians, Michigan; Little Traverse Bay Bands of Odawa Indians, Michigan; Match-e-be-nash-she-wish Band of Pottowatomi Indians of Michigan; Miami Tribe of Oklahoma; Mille Lacs Band of the Minnesota Chippewa Tribe, Minnesota; Nottawaseppi Huron Band of the Potawatomi, Michigan (previously listed as the Huron Potawatomi, Inc.); Ottawa Tribe of Oklahoma; Peoria Tribe of Indians of Oklahoma; Pokagon Band of Potawatomi Indians, Michigan and Indiana; Prairie Band of Potowatomi Nation (previously listed as the Prairie Band of Potowatomi Nation, Kansas); Red Cliff Band of Lake Superior Chippewa Indians of Wisconsin; Red Lake Band of Chippewa Indians, Minnesota; Sac and Fox Tribe of the Mississippi in Iowa; Sac and Fox Nation of Missouri in Kansas and Nebraska, Sac and Fox Nation, Oklahoma; Saginaw Chippewa Indian Tribe of Michigan; Sault Ste. Marie Tribe of Chippewa Indians, Michigan; Shawnee Tribe; Sokaogon Chippewa Community, Wisconsin; St. Croix Chippewa Indians of Wisconsin; Turtle Mountain Band of Chippewa Indians of North Dakota; White Earth Band of Minnesota Chippewa Tribe, Minnesota; Winnebago Tribe of Nebraska; and the Wyandotte Nation (hereafter The Consulted Tribes). \n History and Description of the Remains \n In April 2011, human remains representing, at minimum, one individual were removed from Galien River in Berrien County, MI. In early April of 2011 a minor was fishing in the Galien River in new Buffalo Township, MI. After casting into the center of the river the youth reeled in what appeared to be a large bone. The youth took the bone to his high school science teacher who contacted the Berrien County Sheriff\\'s Office. \n The Sheriff\\'s Office\\'s Dive Team responded by searching a section of the river approximately eight feet square, where they found additional skeletonized human remains. All of the human remains, including the original bone found by the minor, were transported to the Anthropology Department at Michigan State University and examined by Dr. Norman Sauer. The human remains were found to be \\xe2\\x80\\x9cadult prehistoric Native American\\xe2\\x80\\x9d of indeterminate gender, and returned to the Berrien County Sheriff\\'s Office. No known individuals were identified. No associated funerary objects are present. \n At the time of the excavation and removal of these human remains, the land from which the remains were removed was not the tribal land of any Indian tribe or Native Hawaiian organization. \n Determinations Made by the Berrien County Sheriff\\'s Office \n Officials of the Berrien County Sheriff\\'s Office have determined that: \n \\xe2\\x80\\xa2 Pursuant to 25 U.S.C. 3001(9), the human remains described in this notice are Native American based on osteological evidence. \n \\xe2\\x80\\xa2 Pursuant to 25 U.S.C. 3001(9), the human remains described in this notice represent the physical remains of one individual of Native American ancestry. \n \\xe2\\x80\\xa2 Pursuant to 25 U.S.C. 3001(2), a relationship of shared group identity cannot be reasonably traced between the Native American human remains and any present-day Indian tribe. \n \\xe2\\x80\\xa2 According to final judgments of the Indian Claims Commission or the Court of Federal Claims, the land from which the Native American human remains were removed is the aboriginal land of The Consulted Tribes \n \\xe2\\x80\\xa2 Pursuant to 43 CFR 10.11(c)(2)(i), the disposition of the human remains may be to The Consulted Tribes. \n Additional Requestors and Disposition \n Representatives of any Indian tribe or Native Hawaiian organization not identified in this notice that wish to request transfer of control of these human remains should submit a written request with information in support of the request to the Berrien County Sheriff\\'s Office, Attention Chief Deputy Michael Bradley, 919 Port Street, Saint Joseph, MI 49085, email mbradley@berriencounty.org by April 29, 2016. \n After that date, if no additional requestors have come forward, transfer of control of the human remains to The Consulted Tribes may proceed. \n The Berrien County Sheriff\\'s Office is responsible for informing The Consulted Tribes that this notice has been published: \n ", "consultation": "Null", "h_d_r": "In April 2011, human remains representing, at minimum, one individual were removed from Galien River in Berrien County, MI. In early April of 2011 a minor was fishing in the Galien River in new Buffalo Township, MI. After casting into the center of the river the youth reeled in what appeared to be a large bone. The youth took the bone to his high school science teacher who contacted the Berrien County Sheriff\\'s Office. \n The Sheriff\\'s Office\\'s Dive Team responded by searching a section of the river approximately eight feet square, where they found additional skeletonized human remains. All of the human remains, including the original bone found by the minor, were transported to the Anthropology Department at Michigan State University and examined by Dr. Norman Sauer. The human remains were found to be \\xe2\\x80\\x9cadult prehistoric Native American\\xe2\\x80\\x9d of indeterminate gender, and returned to the Berrien County Sheriff\\'s Office. No known individuals were identified. No associated funerary objects are present. \n At the time of the excavation and removal of these human remains, the land from which the remains were removed was not the tribal land of any Indian tribe or Native Hawaiian organization. \n ", "h_d_ci": "Null", "determinations": "Determinations Made by the Berrien County Sheriff\\'s Office \n Officials of the Berrien County Sheriff\\'s Office have determined that: \n \\xe2\\x80\\xa2 Pursuant to 25 U.S.C. 3001(9), the human remains described in this notice are Native American based on osteological evidence. \n \\xe2\\x80\\xa2 Pursuant to 25 U.S.C. 3001(9), the human remains described in this notice represent the physical remains of one individual of Native American ancestry. \n \\xe2\\x80\\xa2 Pursuant to 25 U.S.C. 3001(2), a relationship of shared group identity cannot be reasonably traced between the Native American human remains and any present-day Indian tribe. \n \\xe2\\x80\\xa2 According to final judgments of the Indian Claims Commission or the Court of Federal Claims, the land from which the Native American human remains were removed is the aboriginal land of The Consulted Tribes \n \\xe2\\x80\\xa2 Pursuant to 43 CFR 10.11(c)(2)(i), the disposition of the human remains may be to The Consulted Tribes. \n ", "a_r_d": "Representatives of any Indian tribe or Native Hawaiian organization not identified in this notice that wish to request transfer of control of these human remains should submit a written request with information in support of the request to the Berrien County Sheriff\\'s Office, Attention Chief Deputy Michael Bradley, 919 Port Street, Saint Joseph, MI 49085, email mbradley@berriencounty.org by April 29, 2016. \n After that date, if no additional requestors have come forward, transfer of control of the human remains to The Consulted Tribes may proceed. \n The Berrien County Sheriff\\'s Office is responsible for informing The Consulted Tribes that this notice has been published: \n "}