{"index": "I_584", "messy_full": "\\n      \\n        DEPARTMENT OF THE INTERIOR\\n        National Park Service\\n        [NPS-WASO-NAGPRA-20127; PPWOCRADN0-PCU00RP14.R50000]\\n        Notice of Inventory Completion: Thomas Burke Memorial Washington State Museum, University of Washington, Seattle, WA\\n        \\n          AGENCY:\\n          National Park Service, Interior.\\n        \\n        \\n          ACTION:\\n          Notice.\\n        \\n        \\n          SUMMARY:\\n          The Thomas Burke Memorial Washington State Museum (Burke Museum) has completed an inventory of human remains, in consultation with the appropriate Indian tribes or Native Hawaiian organizations, and has determined that there is no cultural affiliation between the human remains and any present-day Indian tribes or Native Hawaiian organizations. Representatives of any Indian tribe or Native Hawaiian organization not identified in this notice that wish to request transfer of control of these human remains should submit a written request to the Burke Museum. If no additional requestors come forward, transfer of control of the human remains to the Indian tribes or Native Hawaiian organizations stated in this notice may proceed.\\n        \\n        \\n          DATES:\\n          Representatives of any Indian tribe or Native Hawaiian organization not identified in this notice that wish to request transfer of control of these human remains should submit a written request with information in support of the request to the Burke Museum at the address in this notice by March 21, 2016.\\n        \\n        \\n          ADDRESSES:\\n\\n          Peter Lape, Burke Museum, University of Washington, Box 353010, Seattle, WA 98195, telephone (206) 685-3849x2, plape@uw.edu.\\n          \\n        \\n      \\n      \\n        SUPPLEMENTARY INFORMATION:\\n        Notice is here given in accordance with the Native American Graves Protection and Repatriation Act (NAGPRA), 25 U.S.C. 3003, of the completion of an inventory of human remains under the control of the Burke Museum, University of Washington, Seattle, WA. The human remains were possibly removed from the San Juan Islands, San Juan Island County, WA.\\n\\n        This notice is published as part of the National Park Service\\'s administrative responsibilities under NAGPRA, 25 U.S.C. 3003(d)(3) and 43 CFR 10.11(d). The determinations in this notice are the sole responsibility of the museum, institution, or Federal agency that has control of the Native American human remains. The National Park Service is not responsible for the determinations in this notice.\\n        Consultation\\n        A detailed assessment of the human remains was made by the Burke Museum professional staff in consultation with representatives of Lummi Tribe of the Lummi Reservation; Muckleshoot Indian Tribe (previously listed as the Muckleshoot Indian Tribe of the Muckleshoot Reservation, Washington); Nooksack Indian Tribe; Samish Indian Nation (previously listed as the Samish Indian Tribe, Washington); Sauk-Suiattle Indian Tribe; Snoqualmie Indian Tribe (previously listed as the Snoqualmie Tribe, Washington); Stillaguamish Tribe of Indians of Washington (previously listed as the Stillaguamish Tribe of Washington); Suquamish Indian Tribe of the Port Madison Reservation; Swinomish Indian Tribal Community (previously listed as the Swinomish Indians of the Swinomish Reservation of Washington); Tulalip Tribes of Washington (previously listed as the Tulalip Tribes of the Tulalip Reservation, Washington); and Upper Skagit Indian Tribe, (all hereafter referred to as the \\xe2\\x80\\x9cThe Tribes\\xe2\\x80\\x9d).\\n        History and Description of the Remains\\n        On an unknown date prior to 1995, human remains representing, at minimum, one individual were possibly removed from San Juan Islands, San Juan Island County, Washington. These remains were identified in 1995 while completing an inventory for NAGPRA compliance. These human remains were located in a box of material marked \\xe2\\x80\\x9cAnian Island Burial 3F.\\xe2\\x80\\x9d The human remains were in a paper-bag marked \\xe2\\x80\\x9cBurial 3\\xe2\\x80\\x9d. Also written on the bag in the same pencil, but crossed out, is, \\xe2\\x80\\x9cSJ-1, Finds, 7/18/46.\\xe2\\x80\\x9d. These human remains to do not match any of the records for the Anian Island burial. They also do not match \\xe2\\x80\\x9cBurial 3\\xe2\\x80\\x9d from Arden King\\'s 1946 excavations at 45-SJ-1 and there is no mention of burials being found on 7/18/1946 in the field documents. The condition of these human remains is consistent with other burials in shell middens from this area. Additional information provided during consultation indicated this individual was likely buried on the San Juan Islands. The Burke Museum is unable to make a cultural affiliation due to the lack of contextual and exact location information from which the burial was removed. No known individuals were identified. No associated funerary objects are present.\\n        Determinations Made by the Burke Museum\\n        Officials of the Burke Museum have determined that:\\n        \\xe2\\x80\\xa2 Pursuant to 25 U.S.C. 3001(9), the human remains described in this notice are Native American based on osteological evidence and museum collecting and accessioning history.\\n        \\xe2\\x80\\xa2 Pursuant to 25 U.S.C. 3001(9), the human remains described in this notice represent the physical remains of one individual of Native American ancestry.\\n        \\xe2\\x80\\xa2 Pursuant to 25 U.S.C. 3001(2), a relationship of shared group identity cannot be reasonably traced between the Native American human remains and any present-day Indian tribe.\\n        \\xe2\\x80\\xa2 Treaties, Acts of Congress, or Executive Orders, indicate that the land from which the Native American human remains were removed is the aboriginal land of The Tribes. The Treaty of Point Elliot was signed on January 22, 1855 by representatives from The Tribes, and ceded aboriginal land included the San Juan Islands region.\\n        \\xe2\\x80\\xa2 Pursuant to 43 CFR 10.11(c)(1), the disposition of the human remains may be to The Tribes.\\n        Additional Requestors and Disposition\\n\\n        Representatives of any Indian tribe or Native Hawaiian organization not identified in this notice that wish to request transfer of control of these human remains should submit a written request with information in support of the request to Peter Lape, Burke Museum, University of Washington, Box 353010, Seattle, WA 98195, telephone (206) 685-3849 x2, plape@uw.edu, by March 21, 2016. After that date, if no additional requestors have come forward, transfer of control of the human remains to The Tribes may proceed.\\n        The Burke Museum is responsible for notifying The Tribes that this notice has been published.\\n        \\n          Dated: January 15, 2016.\\n          David Tarler,\\n          Acting Manager, National NAGPRA Program.\\n        \\n      \\n      [FR Doc. 2016-03412 Filed 2-17-16; 8:45 am]\\n       BILLING CODE 4312-50-P\\n    ", "agency1": "DEPARTMENT OF THE INTERIOR", "sub_agency1": "National Park Service", "dep_doc": "[NPS-WASO-NAGPRA-20127; PPWOCRADN0-PCU00RP14.R50000]", "subject": "Notice of Inventory Completion: Thomas Burke Memorial Washington State Museum, University of Washington, Seattle, WA", "agency2": "National Park Service, Interior.", "action": "Notice.", "summary": "The Thomas Burke Memorial Washington State Museum (Burke Museum) has completed an inventory of human remains, in consultation with the appropriate Indian tribes or Native Hawaiian organizations, and has determined that there is no cultural affiliation between the human remains and any present-day Indian tribes or Native Hawaiian organizations. Representatives of any Indian tribe or Native Hawaiian organization not identified in this notice that wish to request transfer of control of these human remains should submit a written request to the Burke Museum. If no additional requestors come forward, transfer of control of the human remains to the Indian tribes or Native Hawaiian organizations stated in this notice may proceed.", "dates": "Representatives of any Indian tribe or Native Hawaiian organization not identified in this notice that wish to request transfer of control of these human remains should submit a written request with information in support of the request to the Burke Museum at the address in this notice by March 21, 2016.", "addresses": "Peter Lape, Burke Museum, University of Washington, Box 353010, Seattle, WA 98195, telephone (206) 685-3849x2, plape@uw.edu.\\n          ", "signature_dated": "Dated: January 15, 2016.", "signature_name": "David Tarler,", "signature_title": "Acting Manager, National NAGPRA Program.", "fr_doc": "[FR Doc. 2016-03412 Filed 2-17-16; 8:45 am]", "billing_code": " BILLING CODE 4312-50-P", "supp_info": "SUPPLEMENTARY INFORMATION: \n Notice is here given in accordance with the Native American Graves Protection and Repatriation Act (NAGPRA), 25 U.S.C. 3003, of the completion of an inventory of human remains under the control of the Burke Museum, University of Washington, Seattle, WA. The human remains were possibly removed from the San Juan Islands, San Juan Island County, WA. \n This notice is published as part of the National Park Service\\'s administrative responsibilities under NAGPRA, 25 U.S.C. 3003(d)(3) and 43 CFR 10.11(d). The determinations in this notice are the sole responsibility of the museum, institution, or Federal agency that has control of the Native American human remains. The National Park Service is not responsible for the determinations in this notice. \n Consultation \n A detailed assessment of the human remains was made by the Burke Museum professional staff in consultation with representatives of Lummi Tribe of the Lummi Reservation; Muckleshoot Indian Tribe (previously listed as the Muckleshoot Indian Tribe of the Muckleshoot Reservation, Washington); Nooksack Indian Tribe; Samish Indian Nation (previously listed as the Samish Indian Tribe, Washington); Sauk-Suiattle Indian Tribe; Snoqualmie Indian Tribe (previously listed as the Snoqualmie Tribe, Washington); Stillaguamish Tribe of Indians of Washington (previously listed as the Stillaguamish Tribe of Washington); Suquamish Indian Tribe of the Port Madison Reservation; Swinomish Indian Tribal Community (previously listed as the Swinomish Indians of the Swinomish Reservation of Washington); Tulalip Tribes of Washington (previously listed as the Tulalip Tribes of the Tulalip Reservation, Washington); and Upper Skagit Indian Tribe, (all hereafter referred to as the \\xe2\\x80\\x9cThe Tribes\\xe2\\x80\\x9d). \n History and Description of the Remains \n On an unknown date prior to 1995, human remains representing, at minimum, one individual were possibly removed from San Juan Islands, San Juan Island County, Washington. These remains were identified in 1995 while completing an inventory for NAGPRA compliance. These human remains were located in a box of material marked \\xe2\\x80\\x9cAnian Island Burial 3F.\\xe2\\x80\\x9d The human remains were in a paper-bag marked \\xe2\\x80\\x9cBurial 3\\xe2\\x80\\x9d. Also written on the bag in the same pencil, but crossed out, is, \\xe2\\x80\\x9cSJ-1, Finds, 7/18/46.\\xe2\\x80\\x9d. These human remains to do not match any of the records for the Anian Island burial. They also do not match \\xe2\\x80\\x9cBurial 3\\xe2\\x80\\x9d from Arden King\\'s 1946 excavations at 45-SJ-1 and there is no mention of burials being found on 7/18/1946 in the field documents. The condition of these human remains is consistent with other burials in shell middens from this area. Additional information provided during consultation indicated this individual was likely buried on the San Juan Islands. The Burke Museum is unable to make a cultural affiliation due to the lack of contextual and exact location information from which the burial was removed. No known individuals were identified. No associated funerary objects are present. \n Determinations Made by the Burke Museum \n Officials of the Burke Museum have determined that: \n \\xe2\\x80\\xa2 Pursuant to 25 U.S.C. 3001(9), the human remains described in this notice are Native American based on osteological evidence and museum collecting and accessioning history. \n \\xe2\\x80\\xa2 Pursuant to 25 U.S.C. 3001(9), the human remains described in this notice represent the physical remains of one individual of Native American ancestry. \n \\xe2\\x80\\xa2 Pursuant to 25 U.S.C. 3001(2), a relationship of shared group identity cannot be reasonably traced between the Native American human remains and any present-day Indian tribe. \n \\xe2\\x80\\xa2 Treaties, Acts of Congress, or Executive Orders, indicate that the land from which the Native American human remains were removed is the aboriginal land of The Tribes. The Treaty of Point Elliot was signed on January 22, 1855 by representatives from The Tribes, and ceded aboriginal land included the San Juan Islands region. \n \\xe2\\x80\\xa2 Pursuant to 43 CFR 10.11(c)(1), the disposition of the human remains may be to The Tribes. \n Additional Requestors and Disposition \n Representatives of any Indian tribe or Native Hawaiian organization not identified in this notice that wish to request transfer of control of these human remains should submit a written request with information in support of the request to Peter Lape, Burke Museum, University of Washington, Box 353010, Seattle, WA 98195, telephone (206) 685-3849 x2, plape@uw.edu, by March 21, 2016. After that date, if no additional requestors have come forward, transfer of control of the human remains to The Tribes may proceed. \n The Burke Museum is responsible for notifying The Tribes that this notice has been published. \n ", "consultation": "A detailed assessment of the human remains was made by the Burke Museum professional staff in consultation with representatives of Lummi Tribe of the Lummi Reservation; Muckleshoot Indian Tribe (previously listed as the Muckleshoot Indian Tribe of the Muckleshoot Reservation, Washington); Nooksack Indian Tribe; Samish Indian Nation (previously listed as the Samish Indian Tribe, Washington); Sauk-Suiattle Indian Tribe; Snoqualmie Indian Tribe (previously listed as the Snoqualmie Tribe, Washington); Stillaguamish Tribe of Indians of Washington (previously listed as the Stillaguamish Tribe of Washington); Suquamish Indian Tribe of the Port Madison Reservation; Swinomish Indian Tribal Community (previously listed as the Swinomish Indians of the Swinomish Reservation of Washington); Tulalip Tribes of Washington (previously listed as the Tulalip Tribes of the Tulalip Reservation, Washington); and Upper Skagit Indian Tribe, (all hereafter referred to as the \\xe2\\x80\\x9cThe Tribes\\xe2\\x80\\x9d). \n ", "h_d_r": "On an unknown date prior to 1995, human remains representing, at minimum, one individual were possibly removed from San Juan Islands, San Juan Island County, Washington. These remains were identified in 1995 while completing an inventory for NAGPRA compliance. These human remains were located in a box of material marked \\xe2\\x80\\x9cAnian Island Burial 3F.\\xe2\\x80\\x9d The human remains were in a paper-bag marked \\xe2\\x80\\x9cBurial 3\\xe2\\x80\\x9d. Also written on the bag in the same pencil, but crossed out, is, \\xe2\\x80\\x9cSJ-1, Finds, 7/18/46.\\xe2\\x80\\x9d. These human remains to do not match any of the records for the Anian Island burial. They also do not match \\xe2\\x80\\x9cBurial 3\\xe2\\x80\\x9d from Arden King\\'s 1946 excavations at 45-SJ-1 and there is no mention of burials being found on 7/18/1946 in the field documents. The condition of these human remains is consistent with other burials in shell middens from this area. Additional information provided during consultation indicated this individual was likely buried on the San Juan Islands. The Burke Museum is unable to make a cultural affiliation due to the lack of contextual and exact location information from which the burial was removed. No known individuals were identified. No associated funerary objects are present. \n ", "h_d_ci": "Null", "determinations": "Determinations Made by the Burke Museum \n Officials of the Burke Museum have determined that: \n \\xe2\\x80\\xa2 Pursuant to 25 U.S.C. 3001(9), the human remains described in this notice are Native American based on osteological evidence and museum collecting and accessioning history. \n \\xe2\\x80\\xa2 Pursuant to 25 U.S.C. 3001(9), the human remains described in this notice represent the physical remains of one individual of Native American ancestry. \n \\xe2\\x80\\xa2 Pursuant to 25 U.S.C. 3001(2), a relationship of shared group identity cannot be reasonably traced between the Native American human remains and any present-day Indian tribe. \n \\xe2\\x80\\xa2 Treaties, Acts of Congress, or Executive Orders, indicate that the land from which the Native American human remains were removed is the aboriginal land of The Tribes. The Treaty of Point Elliot was signed on January 22, 1855 by representatives from The Tribes, and ceded aboriginal land included the San Juan Islands region. \n \\xe2\\x80\\xa2 Pursuant to 43 CFR 10.11(c)(1), the disposition of the human remains may be to The Tribes. \n ", "a_r_d": "Representatives of any Indian tribe or Native Hawaiian organization not identified in this notice that wish to request transfer of control of these human remains should submit a written request with information in support of the request to Peter Lape, Burke Museum, University of Washington, Box 353010, Seattle, WA 98195, telephone (206) 685-3849 x2, plape@uw.edu, by March 21, 2016. After that date, if no additional requestors have come forward, transfer of control of the human remains to The Tribes may proceed. \n The Burke Museum is responsible for notifying The Tribes that this notice has been published. \n "}