{"index": "I_608", "messy_full": "\\n      \\n        DEPARTMENT OF THE INTERIOR\\n        National Park Service\\n        [NPS-WASO-NAGPRA-19928; PPWOCRADN0-PCU00RP14.R50000]\\n        Notice of Inventory Completion: University of Oregon Museum of Natural and Cultural History, Eugene, OR\\n        \\n          AGENCY:\\n          National Park Service, Interior.\\n        \\n        \\n          ACTION:\\n          Notice.\\n        \\n        \\n          SUMMARY:\\n\\n          The University of Oregon Museum of Natural and Cultural History has completed an inventory of human remains, in consultation with the appropriate Indian tribes or Native Hawaiian organizations, and has determined that there is a cultural affiliation between the human remains and present-day Indian tribes or Native Hawaiian organizations. Lineal descendants or representatives of any Indian tribe or Native Hawaiian organization not identified in this notice that wish to request transfer of control of these human remains should submit a written request to the University of Oregon Museum of Natural and Cultural History. If no additional requestors come forward, transfer of control of the human remains to the lineal descendants, Indian tribes, or Native Hawaiian organizations stated in this notice may proceed.\\n        \\n        \\n          DATES:\\n          Lineal descendants or representatives of any Indian tribe or Native Hawaiian organization not identified in this notice that wish to request transfer of control of these human remains and associated funerary objects should submit a written request with information in support of the request to the University of Oregon Museum of Natural and Cultural History at the address in this notice by February 8, 2016.\\n        \\n        \\n          ADDRESSES:\\n          Dr. Pamela Endzweig, Director of Collections, Museum of Natural and Cultural History, 1224 University of Oregon, Eugene, OR 97403-1224, telephone (541) 346-5120.\\n        \\n      \\n      \\n        SUPPLEMENTARY INFORMATION:\\n        Notice is here given in accordance with the Native American Graves Protection and Repatriation Act (NAGPRA), 25 U.S.C. 3003, of the completion of an inventory of human remains and associated funerary objects under the control of the University of Oregon Museum of Natural and Cultural History, Eugene, OR. The human remains and associated funerary objects were removed from Knik Arm, near Anchorage, AK.\\n        This notice is published as part of the National Park Service\\'s administrative responsibilities under NAGPRA, 25 U.S.C. 3003(d)(3). The determinations in this notice are the sole responsibility of the museum, institution, or Federal agency that has control of the Native American human remains. The National Park Service is not responsible for the determinations in this notice.\\n        Consultation\\n        A detailed assessment of the human remains was made by University of Oregon Museum of Natural and Cultural History professional staff in consultation with representatives of the Knik Tribal Council, Alaska.\\n        History and Description of the Remains\\n        In 1966, human remains representing, at minimum, one individual were removed from the Fisher-Hong Site, about a mile south of the village of Knik, on the edge of an unnamed creek draining White Lake, Alaska, during legally authorized excavations by archeologists from the University of Oregon. No known individual was identified. No associated funerary objects are present.\\n        Based on archeological context and skeletal morphology, the individual described above is determined to be Native American. Based on provenience, the Native American human remains are reasonably believed to be affiliated with the Knik Tribe. Historical documents, ethnographic sources, and oral history indicate that the Knik people have occupied Knik Arm since pre-contact times.\\n        Determinations Made by the University of Oregon Museum of Natural and Cultural History\\n        Officials of the University of Oregon Museum of Natural and Cultural History have determined that:\\n        \\xe2\\x80\\xa2 Pursuant to 25 U.S.C. 3001(9), the human remains described in this notice represent the physical remains of one individual of Native American ancestry.\\n        \\xe2\\x80\\xa2 Pursuant to 25 U.S.C. 3001(2), there is a relationship of shared group identity that can be reasonably traced between the Native American human remains and the Knik Tribe, Alaska.\\n        Additional Requestors and Disposition\\n        Lineal descendants or representatives of any Indian tribe or Native Hawaiian organization not identified in this notice that wish to request transfer of control of these human remains should submit a written request with information in support of the request to Dr. Pamela Endzweig, Director of Collections, University of Oregon Museum of Natural and Cultural History, 1224 University of Oregon, Eugene, OR 97403-1224, telephone (541) 346-5120, by February 8, 2016. After that date, if no additional requestors have come forward, transfer of control of the human remains to the Knik Tribe, Alaska, may proceed.\\n        The University of Oregon Museum of Natural and Cultural History is responsible for notifying the Knik Tribe, Alaska, that this notice has been published.\\n        \\n          Dated: December 8, 2015.\\n          Amberleigh Malone,\\n          Acting Manager, National NAGPRA Program. \\n        \\n      \\n      [FR Doc. 2016-00073 Filed 1-6-16; 8:45 am]\\n       BILLING CODE 4312-50-P\\n    ", "agency1": "DEPARTMENT OF THE INTERIOR", "sub_agency1": "National Park Service", "dep_doc": "[NPS-WASO-NAGPRA-19928; PPWOCRADN0-PCU00RP14.R50000]", "subject": "Notice of Inventory Completion: University of Oregon Museum of Natural and Cultural History, Eugene, OR", "agency2": "National Park Service, Interior.", "action": "Notice.", "summary": "The University of Oregon Museum of Natural and Cultural History has completed an inventory of human remains, in consultation with the appropriate Indian tribes or Native Hawaiian organizations, and has determined that there is a cultural affiliation between the human remains and present-day Indian tribes or Native Hawaiian organizations. Lineal descendants or representatives of any Indian tribe or Native Hawaiian organization not identified in this notice that wish to request transfer of control of these human remains should submit a written request to the University of Oregon Museum of Natural and Cultural History. If no additional requestors come forward, transfer of control of the human remains to the lineal descendants, Indian tribes, or Native Hawaiian organizations stated in this notice may proceed.", "dates": "Lineal descendants or representatives of any Indian tribe or Native Hawaiian organization not identified in this notice that wish to request transfer of control of these human remains and associated funerary objects should submit a written request with information in support of the request to the University of Oregon Museum of Natural and Cultural History at the address in this notice by February 8, 2016.", "addresses": "Dr. Pamela Endzweig, Director of Collections, Museum of Natural and Cultural History, 1224 University of Oregon, Eugene, OR 97403-1224, telephone (541) 346-5120.", "signature_dated": "Dated: December 8, 2015.", "signature_name": "Amberleigh Malone,", "signature_title": "Acting Manager, National NAGPRA Program. ", "fr_doc": "[FR Doc. 2016-00073 Filed 1-6-16; 8:45 am]", "billing_code": " BILLING CODE 4312-50-P", "supp_info": "SUPPLEMENTARY INFORMATION: \n Notice is here given in accordance with the Native American Graves Protection and Repatriation Act (NAGPRA), 25 U.S.C. 3003, of the completion of an inventory of human remains and associated funerary objects under the control of the University of Oregon Museum of Natural and Cultural History, Eugene, OR. The human remains and associated funerary objects were removed from Knik Arm, near Anchorage, AK. \n This notice is published as part of the National Park Service\\'s administrative responsibilities under NAGPRA, 25 U.S.C. 3003(d)(3). The determinations in this notice are the sole responsibility of the museum, institution, or Federal agency that has control of the Native American human remains. The National Park Service is not responsible for the determinations in this notice. \n Consultation \n A detailed assessment of the human remains was made by University of Oregon Museum of Natural and Cultural History professional staff in consultation with representatives of the Knik Tribal Council, Alaska. \n History and Description of the Remains \n In 1966, human remains representing, at minimum, one individual were removed from the Fisher-Hong Site, about a mile south of the village of Knik, on the edge of an unnamed creek draining White Lake, Alaska, during legally authorized excavations by archeologists from the University of Oregon. No known individual was identified. No associated funerary objects are present. \n Based on archeological context and skeletal morphology, the individual described above is determined to be Native American. Based on provenience, the Native American human remains are reasonably believed to be affiliated with the Knik Tribe. Historical documents, ethnographic sources, and oral history indicate that the Knik people have occupied Knik Arm since pre-contact times. \n Determinations Made by the University of Oregon Museum of Natural and Cultural History \n Officials of the University of Oregon Museum of Natural and Cultural History have determined that: \n \\xe2\\x80\\xa2 Pursuant to 25 U.S.C. 3001(9), the human remains described in this notice represent the physical remains of one individual of Native American ancestry. \n \\xe2\\x80\\xa2 Pursuant to 25 U.S.C. 3001(2), there is a relationship of shared group identity that can be reasonably traced between the Native American human remains and the Knik Tribe, Alaska. \n Additional Requestors and Disposition \n Lineal descendants or representatives of any Indian tribe or Native Hawaiian organization not identified in this notice that wish to request transfer of control of these human remains should submit a written request with information in support of the request to Dr. Pamela Endzweig, Director of Collections, University of Oregon Museum of Natural and Cultural History, 1224 University of Oregon, Eugene, OR 97403-1224, telephone (541) 346-5120, by February 8, 2016. After that date, if no additional requestors have come forward, transfer of control of the human remains to the Knik Tribe, Alaska, may proceed. \n The University of Oregon Museum of Natural and Cultural History is responsible for notifying the Knik Tribe, Alaska, that this notice has been published. \n ", "consultation": "A detailed assessment of the human remains was made by University of Oregon Museum of Natural and Cultural History professional staff in consultation with representatives of the Knik Tribal Council, Alaska. \n ", "h_d_r": "In 1966, human remains representing, at minimum, one individual were removed from the Fisher-Hong Site, about a mile south of the village of Knik, on the edge of an unnamed creek draining White Lake, Alaska, during legally authorized excavations by archeologists from the University of Oregon. No known individual was identified. No associated funerary objects are present. \n Based on archeological context and skeletal morphology, the individual described above is determined to be Native American. Based on provenience, the Native American human remains are reasonably believed to be affiliated with the Knik Tribe. Historical documents, ethnographic sources, and oral history indicate that the Knik people have occupied Knik Arm since pre-contact times. \n ", "h_d_ci": "Null", "determinations": "Determinations Made by the University of Oregon Museum of Natural and Cultural History \n Officials of the University of Oregon Museum of Natural and Cultural History have determined that: \n \\xe2\\x80\\xa2 Pursuant to 25 U.S.C. 3001(9), the human remains described in this notice represent the physical remains of one individual of Native American ancestry. \n \\xe2\\x80\\xa2 Pursuant to 25 U.S.C. 3001(2), there is a relationship of shared group identity that can be reasonably traced between the Native American human remains and the Knik Tribe, Alaska. \n ", "a_r_d": "Lineal descendants or representatives of any Indian tribe or Native Hawaiian organization not identified in this notice that wish to request transfer of control of these human remains should submit a written request with information in support of the request to Dr. Pamela Endzweig, Director of Collections, University of Oregon Museum of Natural and Cultural History, 1224 University of Oregon, Eugene, OR 97403-1224, telephone (541) 346-5120, by February 8, 2016. After that date, if no additional requestors have come forward, transfer of control of the human remains to the Knik Tribe, Alaska, may proceed. \n The University of Oregon Museum of Natural and Cultural History is responsible for notifying the Knik Tribe, Alaska, that this notice has been published. \n "}