{"index": "I_606", "messy_full": "\\n      \\n        DEPARTMENT OF THE INTERIOR\\n        National Park Service\\n        [NPS-WASO-NAGPRA-19772; PPWOCRADN0-PCU00RP14.R50000]\\n        Notice of Inventory Completion: History Colorado (Formerly Colorado Historical Society), Denver, CO\\n        \\n          AGENCY:\\n          National Park Service, Interior.\\n        \\n        \\n          ACTION:\\n          Notice.\\n        \\n        \\n          SUMMARY:\\n          History Colorado has completed an inventory of human remains in consultation with the appropriate Indian tribes or Native Hawaiian organizations, and has determined that there is a cultural affiliation between the human remains and present-day Indian tribes or Native Hawaiian organizations. Lineal descendants or representatives of any Indian tribe or Native Hawaiian organization not identified in this notice that wish to request transfer of control of these human remains should submit a written request to History Colorado. If no additional requestors come forward, transfer of control of the human remains to the lineal descendants, Indian tribes, or Native Hawaiian organizations stated in this notice may proceed.\\n        \\n        \\n          DATES:\\n          Lineal descendants or representatives of any Indian tribe or Native Hawaiian organization not identified in this notice that wish to request transfer of control of these human remains should submit a written request with information in support of the request to History Colorado at the address in this notice by February 8, 2016.\\n        \\n        \\n          ADDRESSES:\\n\\n          Sheila Goff, History Colorado, 1200 Broadway, Denver, CO 80203, telephone (303) 866-4531, email sheila.goff@state.co.us.\\n          \\n        \\n      \\n      \\n        SUPPLEMENTARY INFORMATION:\\n        Notice is here given in accordance with the Native American Graves Protection and Repatriation Act (NAGPRA), 25 U.S.C. 3003, of the completion of an inventory of human remains under the control of History Colorado, Denver, CO. The human remains were removed from San Miguel Island, Channel Islands in Santa Barbara County, CA.\\n        This notice is published as part of the National Park Service\\'s administrative responsibilities under NAGPRA, 25 U.S.C. 3003(d)(3). The determinations in this notice are the sole responsibility of the museum, institution, or Federal agency that has control of the Native American human remains. The National Park Service is not responsible for the determinations in this notice.\\n        Consultation\\n        A detailed assessment of the human remains was made by History Colorado professional staff in consultation with representatives of the Santa Ynez Band of Chumash Mission Indians of the Santa Ynez Reservation, California.\\n        History and Description of the Remains\\n        In 1913, human remains representing, at minimum, one individual were removed from San Miguel Island, Channel Islands, in Santa Barbara County, CA. Museum documentation does not list a specific site from which the human remains were removed. They were anonymously donated to the museum in 1930. No known individuals were identified. No associated funerary objects are present.\\n        Osteological analysis conducted at the Metropolitan State University Human Identification Laboratory concludes that the remains are of an adult female of Native American ancestry. Archaeological evidence and oral history indicate San Miguel Island is traditional territory of the Santa Ynez Band of Chumash Mission Indians of the Santa Ynez Reservation, California. Historical and archaeological findings support the continuous occupation of the island by the Chumash dating back several thousand years, and their relocation to the mainland to Spanish missions by 19th century. In 1855, the Santa Ynez Reservation was created for the Chumash and the Santa Ynez Band of Chumash was federally recognized in 1901.\\n        Determinations Made by History Colorado\\n        Officials of History Colorado have determined that:\\n        \\xe2\\x80\\xa2 Pursuant to 25 U.S.C. 3001(9), the human remains described in this notice represent the physical remains of one individual of Native American ancestry.\\n        \\xe2\\x80\\xa2 Pursuant to 25 U.S.C. 3001(2), there is a relationship of shared group identity that can be reasonably traced between the Native American human remains and the Santa Ynez Band of Chumash Mission Indians of the Santa Ynez Reservation, California.\\n        Additional Requestors and Disposition\\n\\n        Lineal descendants or representatives of any Indian tribe or Native Hawaiian organization not identified in this notice that wish to request transfer of control of these human remains should submit a written request with information in support of the request to Sheila Goff, History Colorado, 1200 Broadway, Denver, CO 80203, (303) 866-4531, email sheila.goff@state.co.us by February 8, 2016. After that date, if no additional requestors have come forward, transfer of control of the human remains to may proceed.\\n        History Colorado is responsible for notifying the Santa Ynez Band of Chumash Mission Indians of the Santa Ynez Reservation, California that this notice has been published.\\n        \\n          Dated: November 12, 2015.\\n          Melanie O\\'Brien,\\n          Manager, National NAGPRA Program. \\n        \\n      \\n      [FR Doc. 2016-00070 Filed 1-6-16; 8:45 am]\\n      BILLING CODE 4312-50-P\\n    ", "agency1": "DEPARTMENT OF THE INTERIOR", "sub_agency1": "National Park Service", "dep_doc": "[NPS-WASO-NAGPRA-19772; PPWOCRADN0-PCU00RP14.R50000]", "subject": "Notice of Inventory Completion: History Colorado (Formerly Colorado Historical Society), Denver, CO", "agency2": "National Park Service, Interior.", "action": "Notice.", "summary": "History Colorado has completed an inventory of human remains in consultation with the appropriate Indian tribes or Native Hawaiian organizations, and has determined that there is a cultural affiliation between the human remains and present-day Indian tribes or Native Hawaiian organizations. Lineal descendants or representatives of any Indian tribe or Native Hawaiian organization not identified in this notice that wish to request transfer of control of these human remains should submit a written request to History Colorado. If no additional requestors come forward, transfer of control of the human remains to the lineal descendants, Indian tribes, or Native Hawaiian organizations stated in this notice may proceed.", "dates": "Lineal descendants or representatives of any Indian tribe or Native Hawaiian organization not identified in this notice that wish to request transfer of control of these human remains should submit a written request with information in support of the request to History Colorado at the address in this notice by February 8, 2016.", "addresses": "Sheila Goff, History Colorado, 1200 Broadway, Denver, CO 80203, telephone (303) 866-4531, email sheila.goff@state.co.us.\\n          ", "signature_dated": "Dated: November 12, 2015.", "signature_name": "Melanie O\\'Brien,", "signature_title": "Manager, National NAGPRA Program. ", "fr_doc": "[FR Doc. 2016-00070 Filed 1-6-16; 8:45 am]", "billing_code": "BILLING CODE 4312-50-P", "supp_info": "SUPPLEMENTARY INFORMATION: \n Notice is here given in accordance with the Native American Graves Protection and Repatriation Act (NAGPRA), 25 U.S.C. 3003, of the completion of an inventory of human remains under the control of History Colorado, Denver, CO. The human remains were removed from San Miguel Island, Channel Islands in Santa Barbara County, CA. \n This notice is published as part of the National Park Service\\'s administrative responsibilities under NAGPRA, 25 U.S.C. 3003(d)(3). The determinations in this notice are the sole responsibility of the museum, institution, or Federal agency that has control of the Native American human remains. The National Park Service is not responsible for the determinations in this notice. \n Consultation \n A detailed assessment of the human remains was made by History Colorado professional staff in consultation with representatives of the Santa Ynez Band of Chumash Mission Indians of the Santa Ynez Reservation, California. \n History and Description of the Remains \n In 1913, human remains representing, at minimum, one individual were removed from San Miguel Island, Channel Islands, in Santa Barbara County, CA. Museum documentation does not list a specific site from which the human remains were removed. They were anonymously donated to the museum in 1930. No known individuals were identified. No associated funerary objects are present. \n Osteological analysis conducted at the Metropolitan State University Human Identification Laboratory concludes that the remains are of an adult female of Native American ancestry. Archaeological evidence and oral history indicate San Miguel Island is traditional territory of the Santa Ynez Band of Chumash Mission Indians of the Santa Ynez Reservation, California. Historical and archaeological findings support the continuous occupation of the island by the Chumash dating back several thousand years, and their relocation to the mainland to Spanish missions by 19th century. In 1855, the Santa Ynez Reservation was created for the Chumash and the Santa Ynez Band of Chumash was federally recognized in 1901. \n Determinations Made by History Colorado \n Officials of History Colorado have determined that: \n \\xe2\\x80\\xa2 Pursuant to 25 U.S.C. 3001(9), the human remains described in this notice represent the physical remains of one individual of Native American ancestry. \n \\xe2\\x80\\xa2 Pursuant to 25 U.S.C. 3001(2), there is a relationship of shared group identity that can be reasonably traced between the Native American human remains and the Santa Ynez Band of Chumash Mission Indians of the Santa Ynez Reservation, California. \n Additional Requestors and Disposition \n Lineal descendants or representatives of any Indian tribe or Native Hawaiian organization not identified in this notice that wish to request transfer of control of these human remains should submit a written request with information in support of the request to Sheila Goff, History Colorado, 1200 Broadway, Denver, CO 80203, (303) 866-4531, email sheila.goff@state.co.us by February 8, 2016. After that date, if no additional requestors have come forward, transfer of control of the human remains to may proceed. \n History Colorado is responsible for notifying the Santa Ynez Band of Chumash Mission Indians of the Santa Ynez Reservation, California that this notice has been published. \n ", "consultation": "A detailed assessment of the human remains was made by History Colorado professional staff in consultation with representatives of the Santa Ynez Band of Chumash Mission Indians of the Santa Ynez Reservation, California. \n ", "h_d_r": "In 1913, human remains representing, at minimum, one individual were removed from San Miguel Island, Channel Islands, in Santa Barbara County, CA. Museum documentation does not list a specific site from which the human remains were removed. They were anonymously donated to the museum in 1930. No known individuals were identified. No associated funerary objects are present. \n Osteological analysis conducted at the Metropolitan State University Human Identification Laboratory concludes that the remains are of an adult female of Native American ancestry. Archaeological evidence and oral history indicate San Miguel Island is traditional territory of the Santa Ynez Band of Chumash Mission Indians of the Santa Ynez Reservation, California. Historical and archaeological findings support the continuous occupation of the island by the Chumash dating back several thousand years, and their relocation to the mainland to Spanish missions by 19th century. In 1855, the Santa Ynez Reservation was created for the Chumash and the Santa Ynez Band of Chumash was federally recognized in 1901. \n ", "h_d_ci": "Null", "determinations": "Determinations Made by History Colorado \n Officials of History Colorado have determined that: \n \\xe2\\x80\\xa2 Pursuant to 25 U.S.C. 3001(9), the human remains described in this notice represent the physical remains of one individual of Native American ancestry. \n \\xe2\\x80\\xa2 Pursuant to 25 U.S.C. 3001(2), there is a relationship of shared group identity that can be reasonably traced between the Native American human remains and the Santa Ynez Band of Chumash Mission Indians of the Santa Ynez Reservation, California. \n ", "a_r_d": "Lineal descendants or representatives of any Indian tribe or Native Hawaiian organization not identified in this notice that wish to request transfer of control of these human remains should submit a written request with information in support of the request to Sheila Goff, History Colorado, 1200 Broadway, Denver, CO 80203, (303) 866-4531, email sheila.goff@state.co.us by February 8, 2016. After that date, if no additional requestors have come forward, transfer of control of the human remains to may proceed. \n History Colorado is responsible for notifying the Santa Ynez Band of Chumash Mission Indians of the Santa Ynez Reservation, California that this notice has been published. \n "}