{"index": "I_607", "messy_full": "\\n      \\n        DEPARTMENT OF THE INTERIOR\\n        National Park Service\\n        [NPS-WASO-NAGPRA-19769; PPWOCRADN0-PCU00RP14.R50000]\\n        Notice of Inventory Completion: University of Hawaii at Hilo, Hilo, HI\\n        \\n          AGENCY:\\n          National Park Service, Interior.\\n        \\n        \\n          ACTION:\\n          Notice.\\n        \\n        \\n          SUMMARY:\\n          The University of Hawaii at Hilo has completed an inventory of human remains in consultation with the appropriate Indian tribes or Native Hawaiian organizations and has determined that there is a cultural affiliation between the human remains and present-day Indian tribes or Native Hawaiian organizations. Lineal descendants or representatives of any Indian tribe or Native Hawaiian organization not identified in this notice that wish to request transfer of control of these human remains should submit a written request to the University of Hawaii at Hilo. If no additional requestors come forward, transfer of control of the human remains to the lineal descendants, Indian tribes, or Native Hawaiian organizations stated in this notice may proceed.\\n        \\n        \\n          DATES:\\n          Lineal descendants or representatives of any Indian tribe or Native Hawaiian organization not identified in this notice that wish to request transfer of control of these human remains should submit a written request with information in support of the request to the University of Hawaii at Hilo at the address in this notice by February 8, 2016.\\n        \\n        \\n          ADDRESSES:\\n          Peter R. Mills, Department of Anthropology, Social Sciences Division, 200 W. Kawili Street, Hilo, HI 96720-4091.\\n        \\n      \\n      \\n        SUPPLEMENTARY INFORMATION:\\n        Notice is here given in accordance with the Native American Graves Protection and Repatriation Act (NAGPRA), 25 U.S.C. 3003, of the completion of an inventory of human remains under the control of the University of Hawaii at Hilo, Hilo, HI. The human remains were removed from Kam\\xc4\\x81\\'oa Pu\\'u\\'eo, Ka\\xc5\\xab District, Hawai\\'i Island, HI.\\n        This notice is published as part of the National Park Service\\'s administrative responsibilities under NAGPRA, 25 U.S.C. 3003(d)(3). The determinations in this notice are the sole responsibility of the museum, institution, or Federal agency that has control of the Native American human remains. The National Park Service is not responsible for the determinations in this notice.\\n        Consultation\\n        A detailed assessment of the human remains was made by the University of Hawaii at Hilo professional staff, in consultation with representatives of The Hawai\\'i Island Burial Council, Department of Hawaiian Homelands, Office of Hawaiian Affairs, Hui Malama i N\\xc4\\x81 K\\xc5\\xabpuna o Hawai\\'i Nei, Aha Moku Advisory Committee, and the Hawaiian Civic Club of Ka\\'\\xc5\\xab.\\n        History and Description of the Remains\\n        In the 1950s, human remains representing, at minimum, three individuals were removed from the Pu\\'u Ali\\'i Sand Dune Site (site H1) in Kamau\\'oa Pu\\'u\\'eo ahupua\\'a, in the district of Ka\\'\\xc5\\xab, Hawai\\'i Island, State of Hawai\\'i, under the direction of Professor William Bonk at the University of Hawaii at Hilo. These human remains were identified in bags of midden deposit in the summer of 2014, which had been stored with the other excavated material from the site at University of Hawaii at Hilo until the present time. No known individuals were identified. No associated funerary objects are present.\\n        The Pu\\'u Ali\\'i Sand Dune site is a Native Hawaiian fishing village and cemetery dating to pre-European contact.\\n        Determinations Made by the University of Hawaii at Hilo\\n        Officials of the University of Hawaii at Hilo have determined that:\\n        \\xe2\\x80\\xa2 Pursuant to 25 U.S.C. 3001(9), the human remains described in this notice represent the physical remains of three individuals of Native American ancestry.\\n        \\xe2\\x80\\xa2 Pursuant to 25 U.S.C. 3001(2), there is a relationship of shared group identity that can be reasonably traced between the Native American human remains and Aha Moku Advisory Committee (Moku o Keawe), the Hawaiian Civic Club of Ka\\'\\xc5\\xab, and the Office of Hawaiian Affairs.\\n        Additional Requestors and Disposition\\n\\n        Lineal descendants or representatives of any Indian tribe or Native Hawaiian organization not identified in this notice that wish to request transfer of control of these human remains should submit a written request with information in support of the request to Peter R. Mills, Department of Anthropology, Social Sciences Division, 200 W. Kawili Street, Hilo, HI 96720-4091, by February 8, 2016. After that date, if no additional requestors have come forward, transfer of control of the human remains to Aha Moku Advisory Committee (Moku o Keawe), the Hawaiian Civic Club of Ka\\'\\xc5\\xab, and the Office of Hawaiian Affairs may proceed.\\n        The University of Hawaii at Hilo is responsible for notifying the The Hawai\\'i Island Burial Council, Department of Hawaiian Homelands, Office of Hawaiian Affairs, Aha Moku Advisory Committee, and the Hawaiian Civic Club of Ka\\'\\xc5\\xab that this notice has been published.\\n        \\n          Dated: December 11, 2015.\\n          Amberleigh Malone,\\n          Acting Manager, National NAGPRA Program. \\n        \\n      \\n      [FR Doc. 2016-00055 Filed 1-6-16; 8:45 am]\\n      BILLING CODE 4312-50-P\\n    ", "agency1": "DEPARTMENT OF THE INTERIOR", "sub_agency1": "National Park Service", "dep_doc": "[NPS-WASO-NAGPRA-19769; PPWOCRADN0-PCU00RP14.R50000]", "subject": "Notice of Inventory Completion: University of Hawaii at Hilo, Hilo, HI", "agency2": "National Park Service, Interior.", "action": "Notice.", "summary": "The University of Hawaii at Hilo has completed an inventory of human remains in consultation with the appropriate Indian tribes or Native Hawaiian organizations and has determined that there is a cultural affiliation between the human remains and present-day Indian tribes or Native Hawaiian organizations. Lineal descendants or representatives of any Indian tribe or Native Hawaiian organization not identified in this notice that wish to request transfer of control of these human remains should submit a written request to the University of Hawaii at Hilo. If no additional requestors come forward, transfer of control of the human remains to the lineal descendants, Indian tribes, or Native Hawaiian organizations stated in this notice may proceed.", "dates": "Lineal descendants or representatives of any Indian tribe or Native Hawaiian organization not identified in this notice that wish to request transfer of control of these human remains should submit a written request with information in support of the request to the University of Hawaii at Hilo at the address in this notice by February 8, 2016.", "addresses": "Peter R. Mills, Department of Anthropology, Social Sciences Division, 200 W. Kawili Street, Hilo, HI 96720-4091.", "signature_dated": "Dated: December 11, 2015.", "signature_name": "Amberleigh Malone,", "signature_title": "Acting Manager, National NAGPRA Program. ", "fr_doc": "[FR Doc. 2016-00055 Filed 1-6-16; 8:45 am]", "billing_code": "BILLING CODE 4312-50-P", "supp_info": "SUPPLEMENTARY INFORMATION: \n Notice is here given in accordance with the Native American Graves Protection and Repatriation Act (NAGPRA), 25 U.S.C. 3003, of the completion of an inventory of human remains under the control of the University of Hawaii at Hilo, Hilo, HI. The human remains were removed from Kam\\xc4\\x81\\'oa Pu\\'u\\'eo, Ka\\xc5\\xab District, Hawai\\'i Island, HI. \n This notice is published as part of the National Park Service\\'s administrative responsibilities under NAGPRA, 25 U.S.C. 3003(d)(3). The determinations in this notice are the sole responsibility of the museum, institution, or Federal agency that has control of the Native American human remains. The National Park Service is not responsible for the determinations in this notice. \n Consultation \n A detailed assessment of the human remains was made by the University of Hawaii at Hilo professional staff, in consultation with representatives of The Hawai\\'i Island Burial Council, Department of Hawaiian Homelands, Office of Hawaiian Affairs, Hui Malama i N\\xc4\\x81 K\\xc5\\xabpuna o Hawai\\'i Nei, Aha Moku Advisory Committee, and the Hawaiian Civic Club of Ka\\'\\xc5\\xab. \n History and Description of the Remains \n In the 1950s, human remains representing, at minimum, three individuals were removed from the Pu\\'u Ali\\'i Sand Dune Site (site H1) in Kamau\\'oa Pu\\'u\\'eo ahupua\\'a, in the district of Ka\\'\\xc5\\xab, Hawai\\'i Island, State of Hawai\\'i, under the direction of Professor William Bonk at the University of Hawaii at Hilo. These human remains were identified in bags of midden deposit in the summer of 2014, which had been stored with the other excavated material from the site at University of Hawaii at Hilo until the present time. No known individuals were identified. No associated funerary objects are present. \n The Pu\\'u Ali\\'i Sand Dune site is a Native Hawaiian fishing village and cemetery dating to pre-European contact. \n Determinations Made by the University of Hawaii at Hilo \n Officials of the University of Hawaii at Hilo have determined that: \n \\xe2\\x80\\xa2 Pursuant to 25 U.S.C. 3001(9), the human remains described in this notice represent the physical remains of three individuals of Native American ancestry. \n \\xe2\\x80\\xa2 Pursuant to 25 U.S.C. 3001(2), there is a relationship of shared group identity that can be reasonably traced between the Native American human remains and Aha Moku Advisory Committee (Moku o Keawe), the Hawaiian Civic Club of Ka\\'\\xc5\\xab, and the Office of Hawaiian Affairs. \n Additional Requestors and Disposition \n Lineal descendants or representatives of any Indian tribe or Native Hawaiian organization not identified in this notice that wish to request transfer of control of these human remains should submit a written request with information in support of the request to Peter R. Mills, Department of Anthropology, Social Sciences Division, 200 W. Kawili Street, Hilo, HI 96720-4091, by February 8, 2016. After that date, if no additional requestors have come forward, transfer of control of the human remains to Aha Moku Advisory Committee (Moku o Keawe), the Hawaiian Civic Club of Ka\\'\\xc5\\xab, and the Office of Hawaiian Affairs may proceed. \n The University of Hawaii at Hilo is responsible for notifying the The Hawai\\'i Island Burial Council, Department of Hawaiian Homelands, Office of Hawaiian Affairs, Aha Moku Advisory Committee, and the Hawaiian Civic Club of Ka\\'\\xc5\\xab that this notice has been published. \n ", "consultation": "A detailed assessment of the human remains was made by the University of Hawaii at Hilo professional staff, in consultation with representatives of The Hawai\\'i Island Burial Council, Department of Hawaiian Homelands, Office of Hawaiian Affairs, Hui Malama i N\\xc4\\x81 K\\xc5\\xabpuna o Hawai\\'i Nei, Aha Moku Advisory Committee, and the Hawaiian Civic Club of Ka\\'\\xc5\\xab. \n ", "h_d_r": "In the 1950s, human remains representing, at minimum, three individuals were removed from the Pu\\'u Ali\\'i Sand Dune Site (site H1) in Kamau\\'oa Pu\\'u\\'eo ahupua\\'a, in the district of Ka\\'\\xc5\\xab, Hawai\\'i Island, State of Hawai\\'i, under the direction of Professor William Bonk at the University of Hawaii at Hilo. These human remains were identified in bags of midden deposit in the summer of 2014, which had been stored with the other excavated material from the site at University of Hawaii at Hilo until the present time. No known individuals were identified. No associated funerary objects are present. \n The Pu\\'u Ali\\'i Sand Dune site is a Native Hawaiian fishing village and cemetery dating to pre-European contact. \n ", "h_d_ci": "Null", "determinations": "Determinations Made by the University of Hawaii at Hilo \n Officials of the University of Hawaii at Hilo have determined that: \n \\xe2\\x80\\xa2 Pursuant to 25 U.S.C. 3001(9), the human remains described in this notice represent the physical remains of three individuals of Native American ancestry. \n \\xe2\\x80\\xa2 Pursuant to 25 U.S.C. 3001(2), there is a relationship of shared group identity that can be reasonably traced between the Native American human remains and Aha Moku Advisory Committee (Moku o Keawe), the Hawaiian Civic Club of Ka\\'\\xc5\\xab, and the Office of Hawaiian Affairs. \n ", "a_r_d": "Lineal descendants or representatives of any Indian tribe or Native Hawaiian organization not identified in this notice that wish to request transfer of control of these human remains should submit a written request with information in support of the request to Peter R. Mills, Department of Anthropology, Social Sciences Division, 200 W. Kawili Street, Hilo, HI 96720-4091, by February 8, 2016. After that date, if no additional requestors have come forward, transfer of control of the human remains to Aha Moku Advisory Committee (Moku o Keawe), the Hawaiian Civic Club of Ka\\'\\xc5\\xab, and the Office of Hawaiian Affairs may proceed. \n The University of Hawaii at Hilo is responsible for notifying the The Hawai\\'i Island Burial Council, Department of Hawaiian Homelands, Office of Hawaiian Affairs, Aha Moku Advisory Committee, and the Hawaiian Civic Club of Ka\\'\\xc5\\xab that this notice has been published. \n "}