{"index": "I_611", "messy_full": "\\n      \\n        DEPARTMENT OF THE INTERIOR\\n        National Park Service\\n        [NPS-WASO-NAGPRA-19846; PCU00RP14.R50000-PPWOCRDN0]\\n        Notice of Inventory Completion: U.S. Department of the Interior, Bureau of Indian Affairs, Washington, DC\\n        \\n          AGENCY:\\n          National Park Service, Interior.\\n        \\n        \\n          ACTION:\\n          Notice.\\n        \\n        \\n          SUMMARY:\\n          The U.S. Department of the Interior, Bureau of Indian Affairs has completed an inventory of human remains, in consultation with the appropriate Indian tribes or Native Hawaiian organizations, and has determined that there is no cultural affiliation between the human remains and any present-day Indian tribes or Native Hawaiian organizations. Representatives of any Indian tribe or Native Hawaiian organization not identified in this notice that wish to request transfer of control of these human remains should submit a written request to the Bureau of Indian Affairs. If no additional requestors come forward, transfer of control of the human remains to the Indian tribes or Native Hawaiian organizations stated in this notice may proceed.\\n        \\n        \\n          DATES:\\n          Representatives of any Indian tribe or Native Hawaiian organization not identified in this notice that wish to request transfer of control of these human remains should submit a written request with information in support of the request to the Bureau of Indian Affairs at the address in this notice by February 8, 2016.\\n        \\n        \\n          ADDRESSES:\\n\\n          Anna Pardo, Museum Program Manager/NAGPRA Coordinator, U.S. Department of the Interior, Bureau of Indian Affairs, 12220 Sunrise Valley Drive, Room 6084, Reston, VA 20191, telephone (703) 390-6343, email Anna.Pardo@bia.gov.\\n          \\n        \\n      \\n      \\n        SUPPLEMENTARY INFORMATION:\\n        Notice is here given in accordance with the Native American Graves Protection and Repatriation Act (NAGPRA), 25 U.S.C. 3003, of the completion of an inventory of human remains under the control of the U.S. Department of the Interior, Bureau of Indian Affairs, Washington, DC, and in the physical custody of the Arizona State Museum, Tucson, AZ. The human remains were removed from areas around Pyramid Lake, Washoe County, NV.\\n        This notice is published as part of the National Park Service\\'s administrative responsibilities under NAGPRA, 25 U.S.C. 3003(d)(3) and 43 CFR 10.11(d). The determinations in this notice are the sole responsibility of the museum, institution, or Federal agency that has control of the Native American human remains. The National Park Service is not responsible for the determinations in this notice.\\n        Consultation\\n        A detailed assessment of the human remains was made by the U.S. Department of the Interior, Bureau of Indian Affairs professional staff in consultation with representatives of the Pyramid Lake Paiute Tribe of the Pyramid Lake Reservation, Nevada.\\n        History and Description of the Remains\\n        In 1959, human remains representing, at minimum, three individuals were removed from a site located on the Northwest corner of Pyramid Lake in Washoe County, NV, by F.A. Riddell (State of California Division of Beaches and Parks) and H. Norcross, and donated to the Phoebe A. Hearst Museum of Anthropology. At the request of the Pyramid Lake Paiute Tribe of the Pyramid Lake Reservation, Nevada, and the Bureau of Indian Affairs, these human remains were transferred to the Arizona State Museum in 2013 for documentation and temporary custody. No known individuals were identified. No associated funerary objects are present.\\n        At an unknown date prior to 1955, human remains representing, at minimum, one individual were removed from a small cave in \\xe2\\x80\\x9cPaul Bunyan\\'s Corral\\xe2\\x80\\x9d located on the east side of Pyramid Lake in Washoe County, NV. They were donated by M. Wheat to the Phoebe A. Hearst Museum of Anthropology in 1955. At the request of the Pyramid Lake Paiute Tribe of the Pyramid Lake Reservation, Nevada, and the Bureau of Indian Affairs, these human remains were transferred to the Arizona State Museum in 2013 for documentation and temporary custody. No known individuals were identified. No associated funerary objects are present.\\n        At an unknown date prior to 1922, human remains representing, at minimum, two individuals were removed from the east side of Pyramid Lake in Washoe County, NV, by Peterson Pancho and donated to the Phoebe A. Hearst Museum of Anthropology in 1922. At the request of the Pyramid Lake Paiute Tribe of the Pyramid Lake Reservation, Nevada, and the Bureau of Indian Affairs, these human remains were transferred to the Arizona State Museum in 2013 for documentation and temporary custody. No known individuals were identified. No associated funerary objects are present.\\n        At an unknown date prior to 1923, human remains representing, at minimum, five individuals were removed from south of Pyramid Lake in Washoe County, NV, by Peterson Pancho and donated to the Phoebe A. Hearst Museum of Anthropology in 1923. At the request of the Pyramid Lake Paiute Tribe of the Pyramid Lake Reservation, Nevada, and the Bureau of Indian Affairs, these human remains were transferred to the Arizona State Museum in 2013 for documentation and temporary custody. No known individuals were identified. No associated funerary objects are present.\\n        Determinations Made by the U.S. Department of the Interior, Bureau of Indian Affairs\\n        Officials of the U.S. Department of the Interior, Bureau of Indian Affairs have determined that:\\n        \\xe2\\x80\\xa2 Pursuant to 25 U.S.C. 3001(9), the human remains described in this notice are Native American based on physical characteristics including cranial and dental morphology.\\n\\n        \\xe2\\x80\\xa2 Pursuant to 25 U.S.C. 3001(9), the human remains described in this notice represent the physical remains of 11 individuals of Native American ancestry.\\n        \\xe2\\x80\\xa2 Pursuant to 25 U.S.C. 3001(2), a relationship of shared group identity cannot be reasonably traced between the Native American human remains and any present-day Indian tribe.\\n        \\xe2\\x80\\xa2 Pursuant to 25 U.S.C. 3001 (15), the land from which the Native American human remains were removed is the tribal land of the Pyramid Lake Paiute Tribe of the Pyramid Lake Reservation, Nevada.\\n        \\xe2\\x80\\xa2 Pursuant to 43 CFR 10.11(c)(1), the disposition of the human remains may be to the Pyramid Lake Paiute Tribe of the Pyramid Lake Reservation, Nevada.\\n        Additional Requestors and Disposition\\n\\n        Representatives of any Indian tribe or Native Hawaiian organization not identified in this notice that wish to request transfer of control of these human remains should submit a written request with information in support of the request to Anna Pardo, Museum Program Manager/NAGPRA Coordinator, U.S. Department of the Interior, Bureau of Indian Affairs, 12220 Sunrise Valley Drive, Room 6084, Reston, VA 20191, telephone (703) 390-6343, email Anna.Pardo@bia.gov, by February 8, 2016. After that date, if no additional requestors have come forward, transfer of control of the human remains to the Pyramid Lake Paiute Tribe of the Pyramid Lake Reservation, Nevada, may proceed.\\n        The U.S. Department of the Interior, Bureau of Indian Affairs is responsible for notifying the Pyramid Lake Paiute Tribe of the Pyramid Lake Reservation, Nevada, that this notice has been published.\\n        \\n          Dated: November 23, 2015.\\n          Amberleigh Malone,\\n          Acting Manager, National NAGPRA Program. \\n        \\n      \\n      [FR Doc. 2016-00067 Filed 1-6-16; 8:45 am]\\n      BILLING CODE 4312-50-P\\n    ", "agency1": "DEPARTMENT OF THE INTERIOR", "sub_agency1": "National Park Service", "dep_doc": "[NPS-WASO-NAGPRA-19846; PCU00RP14.R50000-PPWOCRDN0]", "subject": "Notice of Inventory Completion: U.S. Department of the Interior, Bureau of Indian Affairs, Washington, DC", "agency2": "National Park Service, Interior.", "action": "Notice.", "summary": "The U.S. Department of the Interior, Bureau of Indian Affairs has completed an inventory of human remains, in consultation with the appropriate Indian tribes or Native Hawaiian organizations, and has determined that there is no cultural affiliation between the human remains and any present-day Indian tribes or Native Hawaiian organizations. Representatives of any Indian tribe or Native Hawaiian organization not identified in this notice that wish to request transfer of control of these human remains should submit a written request to the Bureau of Indian Affairs. If no additional requestors come forward, transfer of control of the human remains to the Indian tribes or Native Hawaiian organizations stated in this notice may proceed.", "dates": "Representatives of any Indian tribe or Native Hawaiian organization not identified in this notice that wish to request transfer of control of these human remains should submit a written request with information in support of the request to the Bureau of Indian Affairs at the address in this notice by February 8, 2016.", "addresses": "Anna Pardo, Museum Program Manager/NAGPRA Coordinator, U.S. Department of the Interior, Bureau of Indian Affairs, 12220 Sunrise Valley Drive, Room 6084, Reston, VA 20191, telephone (703) 390-6343, email Anna.Pardo@bia.gov.\\n          ", "signature_dated": "Dated: November 23, 2015.", "signature_name": "Amberleigh Malone,", "signature_title": "Acting Manager, National NAGPRA Program. ", "fr_doc": "[FR Doc. 2016-00067 Filed 1-6-16; 8:45 am]", "billing_code": "BILLING CODE 4312-50-P", "supp_info": "SUPPLEMENTARY INFORMATION: \n Notice is here given in accordance with the Native American Graves Protection and Repatriation Act (NAGPRA), 25 U.S.C. 3003, of the completion of an inventory of human remains under the control of the U.S. Department of the Interior, Bureau of Indian Affairs, Washington, DC, and in the physical custody of the Arizona State Museum, Tucson, AZ. The human remains were removed from areas around Pyramid Lake, Washoe County, NV. \n This notice is published as part of the National Park Service\\'s administrative responsibilities under NAGPRA, 25 U.S.C. 3003(d)(3) and 43 CFR 10.11(d). The determinations in this notice are the sole responsibility of the museum, institution, or Federal agency that has control of the Native American human remains. The National Park Service is not responsible for the determinations in this notice. \n Consultation \n A detailed assessment of the human remains was made by the U.S. Department of the Interior, Bureau of Indian Affairs professional staff in consultation with representatives of the Pyramid Lake Paiute Tribe of the Pyramid Lake Reservation, Nevada. \n History and Description of the Remains \n In 1959, human remains representing, at minimum, three individuals were removed from a site located on the Northwest corner of Pyramid Lake in Washoe County, NV, by F.A. Riddell (State of California Division of Beaches and Parks) and H. Norcross, and donated to the Phoebe A. Hearst Museum of Anthropology. At the request of the Pyramid Lake Paiute Tribe of the Pyramid Lake Reservation, Nevada, and the Bureau of Indian Affairs, these human remains were transferred to the Arizona State Museum in 2013 for documentation and temporary custody. No known individuals were identified. No associated funerary objects are present. \n At an unknown date prior to 1955, human remains representing, at minimum, one individual were removed from a small cave in \\xe2\\x80\\x9cPaul Bunyan\\'s Corral\\xe2\\x80\\x9d located on the east side of Pyramid Lake in Washoe County, NV. They were donated by M. Wheat to the Phoebe A. Hearst Museum of Anthropology in 1955. At the request of the Pyramid Lake Paiute Tribe of the Pyramid Lake Reservation, Nevada, and the Bureau of Indian Affairs, these human remains were transferred to the Arizona State Museum in 2013 for documentation and temporary custody. No known individuals were identified. No associated funerary objects are present. \n At an unknown date prior to 1922, human remains representing, at minimum, two individuals were removed from the east side of Pyramid Lake in Washoe County, NV, by Peterson Pancho and donated to the Phoebe A. Hearst Museum of Anthropology in 1922. At the request of the Pyramid Lake Paiute Tribe of the Pyramid Lake Reservation, Nevada, and the Bureau of Indian Affairs, these human remains were transferred to the Arizona State Museum in 2013 for documentation and temporary custody. No known individuals were identified. No associated funerary objects are present. \n At an unknown date prior to 1923, human remains representing, at minimum, five individuals were removed from south of Pyramid Lake in Washoe County, NV, by Peterson Pancho and donated to the Phoebe A. Hearst Museum of Anthropology in 1923. At the request of the Pyramid Lake Paiute Tribe of the Pyramid Lake Reservation, Nevada, and the Bureau of Indian Affairs, these human remains were transferred to the Arizona State Museum in 2013 for documentation and temporary custody. No known individuals were identified. No associated funerary objects are present. \n Determinations Made by the U.S. Department of the Interior, Bureau of Indian Affairs \n Officials of the U.S. Department of the Interior, Bureau of Indian Affairs have determined that: \n \\xe2\\x80\\xa2 Pursuant to 25 U.S.C. 3001(9), the human remains described in this notice are Native American based on physical characteristics including cranial and dental morphology. \n \\xe2\\x80\\xa2 Pursuant to 25 U.S.C. 3001(9), the human remains described in this notice represent the physical remains of 11 individuals of Native American ancestry. \n \\xe2\\x80\\xa2 Pursuant to 25 U.S.C. 3001(2), a relationship of shared group identity cannot be reasonably traced between the Native American human remains and any present-day Indian tribe. \n \\xe2\\x80\\xa2 Pursuant to 25 U.S.C. 3001 (15), the land from which the Native American human remains were removed is the tribal land of the Pyramid Lake Paiute Tribe of the Pyramid Lake Reservation, Nevada. \n \\xe2\\x80\\xa2 Pursuant to 43 CFR 10.11(c)(1), the disposition of the human remains may be to the Pyramid Lake Paiute Tribe of the Pyramid Lake Reservation, Nevada. \n Additional Requestors and Disposition \n Representatives of any Indian tribe or Native Hawaiian organization not identified in this notice that wish to request transfer of control of these human remains should submit a written request with information in support of the request to Anna Pardo, Museum Program Manager/NAGPRA Coordinator, U.S. Department of the Interior, Bureau of Indian Affairs, 12220 Sunrise Valley Drive, Room 6084, Reston, VA 20191, telephone (703) 390-6343, email Anna.Pardo@bia.gov, by February 8, 2016. After that date, if no additional requestors have come forward, transfer of control of the human remains to the Pyramid Lake Paiute Tribe of the Pyramid Lake Reservation, Nevada, may proceed. \n The U.S. Department of the Interior, Bureau of Indian Affairs is responsible for notifying the Pyramid Lake Paiute Tribe of the Pyramid Lake Reservation, Nevada, that this notice has been published. \n ", "consultation": "A detailed assessment of the human remains was made by the U.S. Department of the Interior, Bureau of Indian Affairs professional staff in consultation with representatives of the Pyramid Lake Paiute Tribe of the Pyramid Lake Reservation, Nevada. \n ", "h_d_r": "In 1959, human remains representing, at minimum, three individuals were removed from a site located on the Northwest corner of Pyramid Lake in Washoe County, NV, by F.A. Riddell (State of California Division of Beaches and Parks) and H. Norcross, and donated to the Phoebe A. Hearst Museum of Anthropology. At the request of the Pyramid Lake Paiute Tribe of the Pyramid Lake Reservation, Nevada, and the Bureau of Indian Affairs, these human remains were transferred to the Arizona State Museum in 2013 for documentation and temporary custody. No known individuals were identified. No associated funerary objects are present. \n At an unknown date prior to 1955, human remains representing, at minimum, one individual were removed from a small cave in \\xe2\\x80\\x9cPaul Bunyan\\'s Corral\\xe2\\x80\\x9d located on the east side of Pyramid Lake in Washoe County, NV. They were donated by M. Wheat to the Phoebe A. Hearst Museum of Anthropology in 1955. At the request of the Pyramid Lake Paiute Tribe of the Pyramid Lake Reservation, Nevada, and the Bureau of Indian Affairs, these human remains were transferred to the Arizona State Museum in 2013 for documentation and temporary custody. No known individuals were identified. No associated funerary objects are present. \n At an unknown date prior to 1922, human remains representing, at minimum, two individuals were removed from the east side of Pyramid Lake in Washoe County, NV, by Peterson Pancho and donated to the Phoebe A. Hearst Museum of Anthropology in 1922. At the request of the Pyramid Lake Paiute Tribe of the Pyramid Lake Reservation, Nevada, and the Bureau of Indian Affairs, these human remains were transferred to the Arizona State Museum in 2013 for documentation and temporary custody. No known individuals were identified. No associated funerary objects are present. \n At an unknown date prior to 1923, human remains representing, at minimum, five individuals were removed from south of Pyramid Lake in Washoe County, NV, by Peterson Pancho and donated to the Phoebe A. Hearst Museum of Anthropology in 1923. At the request of the Pyramid Lake Paiute Tribe of the Pyramid Lake Reservation, Nevada, and the Bureau of Indian Affairs, these human remains were transferred to the Arizona State Museum in 2013 for documentation and temporary custody. No known individuals were identified. No associated funerary objects are present. \n ", "h_d_ci": "Null", "determinations": "Determinations Made by the U.S. Department of the Interior, Bureau of Indian Affairs \n Officials of the U.S. Department of the Interior, Bureau of Indian Affairs have determined that: \n \\xe2\\x80\\xa2 Pursuant to 25 U.S.C. 3001(9), the human remains described in this notice are Native American based on physical characteristics including cranial and dental morphology. \n \\xe2\\x80\\xa2 Pursuant to 25 U.S.C. 3001(9), the human remains described in this notice represent the physical remains of 11 individuals of Native American ancestry. \n \\xe2\\x80\\xa2 Pursuant to 25 U.S.C. 3001(2), a relationship of shared group identity cannot be reasonably traced between the Native American human remains and any present-day Indian tribe. \n \\xe2\\x80\\xa2 Pursuant to 25 U.S.C. 3001 (15), the land from which the Native American human remains were removed is the tribal land of the Pyramid Lake Paiute Tribe of the Pyramid Lake Reservation, Nevada. \n \\xe2\\x80\\xa2 Pursuant to 43 CFR 10.11(c)(1), the disposition of the human remains may be to the Pyramid Lake Paiute Tribe of the Pyramid Lake Reservation, Nevada. \n ", "a_r_d": "Representatives of any Indian tribe or Native Hawaiian organization not identified in this notice that wish to request transfer of control of these human remains should submit a written request with information in support of the request to Anna Pardo, Museum Program Manager/NAGPRA Coordinator, U.S. Department of the Interior, Bureau of Indian Affairs, 12220 Sunrise Valley Drive, Room 6084, Reston, VA 20191, telephone (703) 390-6343, email Anna.Pardo@bia.gov, by February 8, 2016. After that date, if no additional requestors have come forward, transfer of control of the human remains to the Pyramid Lake Paiute Tribe of the Pyramid Lake Reservation, Nevada, may proceed. \n The U.S. Department of the Interior, Bureau of Indian Affairs is responsible for notifying the Pyramid Lake Paiute Tribe of the Pyramid Lake Reservation, Nevada, that this notice has been published. \n "}