{"index": "I_639", "messy_full": "\\n      \\n        DEPARTMENT OF THE INTERIOR\\n        National Park Service\\n        [NPS-WASO-NAGPRA-19371; PPWOCRADN0-PCU00RP14.R50000]\\n        Notice of Inventory Completion: University of Michigan, Ann Arbor, MI\\n        \\n          AGENCY:\\n          National Park Service, Interior.\\n        \\n        \\n          ACTION:\\n          Notice.\\n        \\n        \\n          SUMMARY:\\n          The University of Michigan has completed an inventory of human remains and associated funerary objects, in consultation with the appropriate Indian tribes or Native Hawaiian organizations, and has determined that there is no cultural affiliation between the human remains and associated funerary objects and any present-day Indian tribes or Native Hawaiian organizations. Representatives of any Indian tribe or Native Hawaiian organization not identified in this notice that wish to request transfer of control of these human remains and associated funerary objects should submit a written request to the University of Michigan. If no additional requestors come forward, transfer of control of the human remains and associated funerary objects to the Indian tribes or Native Hawaiian organizations stated in this notice may proceed.\\n        \\n        \\n          DATES:\\n          Representatives of any Indian tribe or Native Hawaiian organization not identified in this notice that wish to request transfer of control of these human remains and associated funerary objects should submit a written request with information in support of the request to the University of Michigan at the address in this notice by November 16, 2015.\\n        \\n        \\n          ADDRESSES:\\n\\n          Dr. Ben Secunda, NAGPRA Project Manager, University of Michigan Office of Research, 4080 Fleming Building, 503 S. Thompson Street, Ann Arbor, MI 48109-1340, telephone (734) 647-9085, email bsecunda@umich.edu.\\n          \\n        \\n      \\n      \\n        SUPPLEMENTARY INFORMATION:\\n        Notice is here given in accordance with the Native American Graves Protection and Repatriation Act (NAGPRA), 25 U.S.C. 3003, of the completion of an inventory of human remains and associated funerary objects under the control of the University of Michigan, Ann Arbor, MI. The human remains and associated funerary objects were removed from Bay and Saginaw Counties, MI.\\n        This notice is published as part of the National Park Service\\'s administrative responsibilities under NAGPRA, 25 U.S.C. 3003(d)(3) and 43 CFR 10.11(d). The determinations in this notice are the sole responsibility of the museum, institution, or Federal agency that has control of the Native American human remains and associated funerary objects. The National Park Service is not responsible for the determinations in this notice.\\n        Consultation\\n        A detailed assessment of the human remains and associated funerary objects was made by the University of Michigan Museum of Anthropological Archaeology (UMMAA) professional staff in consultation with representatives of the Bay Mills Indian Community, Michigan; Chippewa Cree Indians of the Rocky Boy\\'s Reservation, Montana; Grand Traverse Band of Ottawa and Chippewa Indians, Michigan; Keweenaw Bay Indian Community, Michigan; Lac Vieux Desert Band of Lake Superior Chippewa Indians, Michigan; Saginaw Chippewa Indian Tribe of Michigan; and the Sault Ste. Marie Tribe of Chippewa Indians, Michigan.\\n        Additional requests for consultation were sent to the Bad River Band of the Lake Superior Tribe of Chippewa Indians of the Bad River Reservation, Wisconsin; Bois Forte Band (Nett Lake) of the Minnesota Chippewa Tribe, Minnesota; Fond du Lac Band of the Minnesota Chippewa Tribe, Minnesota; Grand Portage Band of the Minnesota Chippewa Tribe, Minnesota; Kickapoo Traditional Tribe of Texas; Kickapoo Tribe of Indians of the Kickapoo Reservation in Kansas; Kickapoo Tribe of Oklahoma; Lac Courte Oreilles Band of Lake Superior Chippewa Indians of Wisconsin; Lac du Flambeau Band of Lake Superior Chippewa Indians of the Lac du Flambeau Reservation of Wisconsin; Leech Lake Band of the Minnesota Chippewa Tribe, Minnesota; Mille Lacs Band of the Minnesota Chippewa Tribe, Minnesota; Red Cliff Band of Lake Superior Chippewa Indians of Wisconsin; Red Lake Band of Chippewa Indians, Minnesota; Sac & Fox Nation of Missouri in Kansas and Nebraska; Sac & Fox Nation, Oklahoma; Sac & Fox Tribe of the Mississippi in Iowa; Sokaogon Chippewa Community, Wisconsin; St. Croix Chippewa Indians of Wisconsin; Turtle Mountain Band of Chippewa Indians of North Dakota; and the White Earth Band of the Minnesota Chippewa Tribe, Minnesota.\\n        Hereafter, all tribes listed in this section are referred to as \\xe2\\x80\\x9cThe Invited and Consulted Tribes.\\xe2\\x80\\x9d\\n        History and Description of the Remains\\n        In July 1965, human remains representing, at minimum, one individual were removed from the Butterfield site (20BY29) in Bay County, MI. UMMAA archeologists conducted a test excavation of the site. They collected a single juvenile tooth cap from a fire pit that also contained fire cracked rock and lithics. The human remains were dated to the Late Woodland Period (A.D. 500-1400) based on diagnostic artifacts from other areas of the site. No known individuals were identified. No associated funerary objects are present.\\n\\n        From June 20-28, 1966, human remains representing, at minimum, one individual were removed from the Kantzler site (20BY30) in Bay County, MI. Members of the Saginaw Valley Chapter of the Michigan Archaeological Society originally excavated the site in 1965. They noted multiple archeological components and evidence of occupation from the Archaic to Post-Contact Periods. No human remains were found during this excavation. UMMAA archeologists also conducted an excavation of the site in 1966. They collected the human remains of a child, buried in a tightly flexed position, along with turtle and fish bones. No date or time period could be established for the human remains. No known individuals were identified. The 1 associated funerary object present is 1 lot of turtle and fish bones.\\n        In 1923, human remains representing, at minimum, four individuals were removed from the Schmidt 2-4 site (20BY1) in Bay County, MI. A landowner donated these human remains and objects to the UMMAA on an unknown date. The human remains are of 1 child, 1 adolescent possibly male, 1 young adult female, and 1 adult male. No date or time period could be established for the human remains. No known individuals were identified. The 1 associated funerary object present is 1 lot of unworked stones, fossil coral, and animal bone.\\n        In the summer of 1963, human remains representing, at minimum, two individuals were removed from the Mahoney Property site (20SA193) in Saginaw County, MI. UMMAA archeologists collected the human remains as part of a survey project conducted in the area. The human remains are sun-bleached and highly weathered, and are from 1 adult and 1 cremated adult. No date or time period could be established for the human remains. No known individuals were identified. No associated funerary objects are present.\\n        Determinations Made by the University of Michigan\\n        Officials of the University of Michigan have determined that:\\n        \\xe2\\x80\\xa2 Pursuant to 25 U.S.C. 3001(9), the human remains described in this notice are Native American based on cranial morphology, dental traits, archeological context, and accession documentation.\\n        \\xe2\\x80\\xa2 Pursuant to 25 U.S.C. 3001(9), the human remains described in this notice represent the physical remains of eight individuals of Native American ancestry.\\n        \\xe2\\x80\\xa2 Pursuant to 25 U.S.C. 3001(3)(A), the 2 objects described in this notice is reasonably believed to have been placed with or near individual human remains at the time of death or later as part of the death rite or ceremony.\\n        \\xe2\\x80\\xa2 Pursuant to 25 U.S.C. 3001(2), a relationship of shared group identity cannot be reasonably traced between the Native American human remains and associated funerary objects and any present-day Indian tribe.\\n        \\xe2\\x80\\xa2 According to final judgments of the Indian Claims Commission or the Court of Federal Claims, the land from which the Native American human remains and associated funerary objects were removed is the aboriginal land of the Saginaw Chippewa Indian Tribe of Michigan.\\n        \\xe2\\x80\\xa2 Treaties, Acts of Congress, or Executive Orders, indicate that the land from which the Native American human remains and associated funerary objects were removed is the aboriginal land of The Invited and Consulted Tribes.\\n        \\xe2\\x80\\xa2 Pursuant to 43 CFR 10.11(c)(1), the disposition of the human remains and associated funerary objects may be to The Invited and Consulted Tribes.\\n        Additional Requestors and Disposition\\n\\n        Representatives of any Indian tribe or Native Hawaiian organization not identified in this notice that wish to request transfer of control of these human remains and associated funerary objects should submit a written request with information in support of the request to Dr. Ben Secunda, NAGPRA Project Manager, University of Michigan Office of Research, 4080 Fleming Building, 503 S. Thompson Street, Ann Arbor, MI 48109-1340, telephone (734) 647-9085, email bsecunda@umich.edu, by November 16, 2015. After that date, if no additional requestors have come forward, transfer of control of the human remains and associated funerary objects to The Invited and Consulted Tribes may proceed.\\n        The University of Michigan is responsible for notifying The Invited and Consulted Tribes that this notice has been published.\\n        \\n          Dated: September 22, 2015.\\n          Melanie O\\'Brien,\\n          Manager, National NAGPRA Program. \\n        \\n      \\n      [FR Doc. 2015-26293 Filed 10-14-15; 8:45 am]\\n      BILLING CODE 4312-50-P\\n    ", "agency1": "DEPARTMENT OF THE INTERIOR", "sub_agency1": "National Park Service", "dep_doc": "[NPS-WASO-NAGPRA-19371; PPWOCRADN0-PCU00RP14.R50000]", "subject": "Notice of Inventory Completion: University of Michigan, Ann Arbor, MI", "agency2": "National Park Service, Interior.", "action": "Notice.", "summary": "The University of Michigan has completed an inventory of human remains and associated funerary objects, in consultation with the appropriate Indian tribes or Native Hawaiian organizations, and has determined that there is no cultural affiliation between the human remains and associated funerary objects and any present-day Indian tribes or Native Hawaiian organizations. Representatives of any Indian tribe or Native Hawaiian organization not identified in this notice that wish to request transfer of control of these human remains and associated funerary objects should submit a written request to the University of Michigan. If no additional requestors come forward, transfer of control of the human remains and associated funerary objects to the Indian tribes or Native Hawaiian organizations stated in this notice may proceed.", "dates": "Representatives of any Indian tribe or Native Hawaiian organization not identified in this notice that wish to request transfer of control of these human remains and associated funerary objects should submit a written request with information in support of the request to the University of Michigan at the address in this notice by November 16, 2015.", "addresses": "Dr. Ben Secunda, NAGPRA Project Manager, University of Michigan Office of Research, 4080 Fleming Building, 503 S. Thompson Street, Ann Arbor, MI 48109-1340, telephone (734) 647-9085, email bsecunda@umich.edu.\\n          ", "signature_dated": "Dated: September 22, 2015.", "signature_name": "Melanie O\\'Brien,", "signature_title": "Manager, National NAGPRA Program. ", "fr_doc": "[FR Doc. 2015-26293 Filed 10-14-15; 8:45 am]", "billing_code": "BILLING CODE 4312-50-P", "supp_info": "SUPPLEMENTARY INFORMATION: \n Notice is here given in accordance with the Native American Graves Protection and Repatriation Act (NAGPRA), 25 U.S.C. 3003, of the completion of an inventory of human remains and associated funerary objects under the control of the University of Michigan, Ann Arbor, MI. The human remains and associated funerary objects were removed from Bay and Saginaw Counties, MI. \n This notice is published as part of the National Park Service\\'s administrative responsibilities under NAGPRA, 25 U.S.C. 3003(d)(3) and 43 CFR 10.11(d). The determinations in this notice are the sole responsibility of the museum, institution, or Federal agency that has control of the Native American human remains and associated funerary objects. The National Park Service is not responsible for the determinations in this notice. \n Consultation \n A detailed assessment of the human remains and associated funerary objects was made by the University of Michigan Museum of Anthropological Archaeology (UMMAA) professional staff in consultation with representatives of the Bay Mills Indian Community, Michigan; Chippewa Cree Indians of the Rocky Boy\\'s Reservation, Montana; Grand Traverse Band of Ottawa and Chippewa Indians, Michigan; Keweenaw Bay Indian Community, Michigan; Lac Vieux Desert Band of Lake Superior Chippewa Indians, Michigan; Saginaw Chippewa Indian Tribe of Michigan; and the Sault Ste. Marie Tribe of Chippewa Indians, Michigan. \n Additional requests for consultation were sent to the Bad River Band of the Lake Superior Tribe of Chippewa Indians of the Bad River Reservation, Wisconsin; Bois Forte Band (Nett Lake) of the Minnesota Chippewa Tribe, Minnesota; Fond du Lac Band of the Minnesota Chippewa Tribe, Minnesota; Grand Portage Band of the Minnesota Chippewa Tribe, Minnesota; Kickapoo Traditional Tribe of Texas; Kickapoo Tribe of Indians of the Kickapoo Reservation in Kansas; Kickapoo Tribe of Oklahoma; Lac Courte Oreilles Band of Lake Superior Chippewa Indians of Wisconsin; Lac du Flambeau Band of Lake Superior Chippewa Indians of the Lac du Flambeau Reservation of Wisconsin; Leech Lake Band of the Minnesota Chippewa Tribe, Minnesota; Mille Lacs Band of the Minnesota Chippewa Tribe, Minnesota; Red Cliff Band of Lake Superior Chippewa Indians of Wisconsin; Red Lake Band of Chippewa Indians, Minnesota; Sac & Fox Nation of Missouri in Kansas and Nebraska; Sac & Fox Nation, Oklahoma; Sac & Fox Tribe of the Mississippi in Iowa; Sokaogon Chippewa Community, Wisconsin; St. Croix Chippewa Indians of Wisconsin; Turtle Mountain Band of Chippewa Indians of North Dakota; and the White Earth Band of the Minnesota Chippewa Tribe, Minnesota. \n Hereafter, all tribes listed in this section are referred to as \\xe2\\x80\\x9cThe Invited and Consulted Tribes.\\xe2\\x80\\x9d \n History and Description of the Remains \n In July 1965, human remains representing, at minimum, one individual were removed from the Butterfield site (20BY29) in Bay County, MI. UMMAA archeologists conducted a test excavation of the site. They collected a single juvenile tooth cap from a fire pit that also contained fire cracked rock and lithics. The human remains were dated to the Late Woodland Period (A.D. 500-1400) based on diagnostic artifacts from other areas of the site. No known individuals were identified. No associated funerary objects are present. \n From June 20-28, 1966, human remains representing, at minimum, one individual were removed from the Kantzler site (20BY30) in Bay County, MI. Members of the Saginaw Valley Chapter of the Michigan Archaeological Society originally excavated the site in 1965. They noted multiple archeological components and evidence of occupation from the Archaic to Post-Contact Periods. No human remains were found during this excavation. UMMAA archeologists also conducted an excavation of the site in 1966. They collected the human remains of a child, buried in a tightly flexed position, along with turtle and fish bones. No date or time period could be established for the human remains. No known individuals were identified. The 1 associated funerary object present is 1 lot of turtle and fish bones. \n In 1923, human remains representing, at minimum, four individuals were removed from the Schmidt 2-4 site (20BY1) in Bay County, MI. A landowner donated these human remains and objects to the UMMAA on an unknown date. The human remains are of 1 child, 1 adolescent possibly male, 1 young adult female, and 1 adult male. No date or time period could be established for the human remains. No known individuals were identified. The 1 associated funerary object present is 1 lot of unworked stones, fossil coral, and animal bone. \n In the summer of 1963, human remains representing, at minimum, two individuals were removed from the Mahoney Property site (20SA193) in Saginaw County, MI. UMMAA archeologists collected the human remains as part of a survey project conducted in the area. The human remains are sun-bleached and highly weathered, and are from 1 adult and 1 cremated adult. No date or time period could be established for the human remains. No known individuals were identified. No associated funerary objects are present. \n Determinations Made by the University of Michigan \n Officials of the University of Michigan have determined that: \n \\xe2\\x80\\xa2 Pursuant to 25 U.S.C. 3001(9), the human remains described in this notice are Native American based on cranial morphology, dental traits, archeological context, and accession documentation. \n \\xe2\\x80\\xa2 Pursuant to 25 U.S.C. 3001(9), the human remains described in this notice represent the physical remains of eight individuals of Native American ancestry. \n \\xe2\\x80\\xa2 Pursuant to 25 U.S.C. 3001(3)(A), the 2 objects described in this notice is reasonably believed to have been placed with or near individual human remains at the time of death or later as part of the death rite or ceremony. \n \\xe2\\x80\\xa2 Pursuant to 25 U.S.C. 3001(2), a relationship of shared group identity cannot be reasonably traced between the Native American human remains and associated funerary objects and any present-day Indian tribe. \n \\xe2\\x80\\xa2 According to final judgments of the Indian Claims Commission or the Court of Federal Claims, the land from which the Native American human remains and associated funerary objects were removed is the aboriginal land of the Saginaw Chippewa Indian Tribe of Michigan. \n \\xe2\\x80\\xa2 Treaties, Acts of Congress, or Executive Orders, indicate that the land from which the Native American human remains and associated funerary objects were removed is the aboriginal land of The Invited and Consulted Tribes. \n \\xe2\\x80\\xa2 Pursuant to 43 CFR 10.11(c)(1), the disposition of the human remains and associated funerary objects may be to The Invited and Consulted Tribes. \n Additional Requestors and Disposition \n Representatives of any Indian tribe or Native Hawaiian organization not identified in this notice that wish to request transfer of control of these human remains and associated funerary objects should submit a written request with information in support of the request to Dr. Ben Secunda, NAGPRA Project Manager, University of Michigan Office of Research, 4080 Fleming Building, 503 S. Thompson Street, Ann Arbor, MI 48109-1340, telephone (734) 647-9085, email bsecunda@umich.edu, by November 16, 2015. After that date, if no additional requestors have come forward, transfer of control of the human remains and associated funerary objects to The Invited and Consulted Tribes may proceed. \n The University of Michigan is responsible for notifying The Invited and Consulted Tribes that this notice has been published. \n ", "consultation": "A detailed assessment of the human remains and associated funerary objects was made by the University of Michigan Museum of Anthropological Archaeology (UMMAA) professional staff in consultation with representatives of the Bay Mills Indian Community, Michigan; Chippewa Cree Indians of the Rocky Boy\\'s Reservation, Montana; Grand Traverse Band of Ottawa and Chippewa Indians, Michigan; Keweenaw Bay Indian Community, Michigan; Lac Vieux Desert Band of Lake Superior Chippewa Indians, Michigan; Saginaw Chippewa Indian Tribe of Michigan; and the Sault Ste. Marie Tribe of Chippewa Indians, Michigan. \n Additional requests for consultation were sent to the Bad River Band of the Lake Superior Tribe of Chippewa Indians of the Bad River Reservation, Wisconsin; Bois Forte Band (Nett Lake) of the Minnesota Chippewa Tribe, Minnesota; Fond du Lac Band of the Minnesota Chippewa Tribe, Minnesota; Grand Portage Band of the Minnesota Chippewa Tribe, Minnesota; Kickapoo Traditional Tribe of Texas; Kickapoo Tribe of Indians of the Kickapoo Reservation in Kansas; Kickapoo Tribe of Oklahoma; Lac Courte Oreilles Band of Lake Superior Chippewa Indians of Wisconsin; Lac du Flambeau Band of Lake Superior Chippewa Indians of the Lac du Flambeau Reservation of Wisconsin; Leech Lake Band of the Minnesota Chippewa Tribe, Minnesota; Mille Lacs Band of the Minnesota Chippewa Tribe, Minnesota; Red Cliff Band of Lake Superior Chippewa Indians of Wisconsin; Red Lake Band of Chippewa Indians, Minnesota; Sac & Fox Nation of Missouri in Kansas and Nebraska; Sac & Fox Nation, Oklahoma; Sac & Fox Tribe of the Mississippi in Iowa; Sokaogon Chippewa Community, Wisconsin; St. Croix Chippewa Indians of Wisconsin; Turtle Mountain Band of Chippewa Indians of North Dakota; and the White Earth Band of the Minnesota Chippewa Tribe, Minnesota. \n Hereafter, all tribes listed in this section are referred to as \\xe2\\x80\\x9cThe Invited and Consulted Tribes.\\xe2\\x80\\x9d \n ", "h_d_r": "In July 1965, human remains representing, at minimum, one individual were removed from the Butterfield site (20BY29) in Bay County, MI. UMMAA archeologists conducted a test excavation of the site. They collected a single juvenile tooth cap from a fire pit that also contained fire cracked rock and lithics. The human remains were dated to the Late Woodland Period (A.D. 500-1400) based on diagnostic artifacts from other areas of the site. No known individuals were identified. No associated funerary objects are present. \n From June 20-28, 1966, human remains representing, at minimum, one individual were removed from the Kantzler site (20BY30) in Bay County, MI. Members of the Saginaw Valley Chapter of the Michigan Archaeological Society originally excavated the site in 1965. They noted multiple archeological components and evidence of occupation from the Archaic to Post-Contact Periods. No human remains were found during this excavation. UMMAA archeologists also conducted an excavation of the site in 1966. They collected the human remains of a child, buried in a tightly flexed position, along with turtle and fish bones. No date or time period could be established for the human remains. No known individuals were identified. The 1 associated funerary object present is 1 lot of turtle and fish bones. \n In 1923, human remains representing, at minimum, four individuals were removed from the Schmidt 2-4 site (20BY1) in Bay County, MI. A landowner donated these human remains and objects to the UMMAA on an unknown date. The human remains are of 1 child, 1 adolescent possibly male, 1 young adult female, and 1 adult male. No date or time period could be established for the human remains. No known individuals were identified. The 1 associated funerary object present is 1 lot of unworked stones, fossil coral, and animal bone. \n In the summer of 1963, human remains representing, at minimum, two individuals were removed from the Mahoney Property site (20SA193) in Saginaw County, MI. UMMAA archeologists collected the human remains as part of a survey project conducted in the area. The human remains are sun-bleached and highly weathered, and are from 1 adult and 1 cremated adult. No date or time period could be established for the human remains. No known individuals were identified. No associated funerary objects are present. \n ", "h_d_ci": "Null", "determinations": "Determinations Made by the University of Michigan \n Officials of the University of Michigan have determined that: \n \\xe2\\x80\\xa2 Pursuant to 25 U.S.C. 3001(9), the human remains described in this notice are Native American based on cranial morphology, dental traits, archeological context, and accession documentation. \n \\xe2\\x80\\xa2 Pursuant to 25 U.S.C. 3001(9), the human remains described in this notice represent the physical remains of eight individuals of Native American ancestry. \n \\xe2\\x80\\xa2 Pursuant to 25 U.S.C. 3001(3)(A), the 2 objects described in this notice is reasonably believed to have been placed with or near individual human remains at the time of death or later as part of the death rite or ceremony. \n \\xe2\\x80\\xa2 Pursuant to 25 U.S.C. 3001(2), a relationship of shared group identity cannot be reasonably traced between the Native American human remains and associated funerary objects and any present-day Indian tribe. \n \\xe2\\x80\\xa2 According to final judgments of the Indian Claims Commission or the Court of Federal Claims, the land from which the Native American human remains and associated funerary objects were removed is the aboriginal land of the Saginaw Chippewa Indian Tribe of Michigan. \n \\xe2\\x80\\xa2 Treaties, Acts of Congress, or Executive Orders, indicate that the land from which the Native American human remains and associated funerary objects were removed is the aboriginal land of The Invited and Consulted Tribes. \n \\xe2\\x80\\xa2 Pursuant to 43 CFR 10.11(c)(1), the disposition of the human remains and associated funerary objects may be to The Invited and Consulted Tribes. \n ", "a_r_d": "Representatives of any Indian tribe or Native Hawaiian organization not identified in this notice that wish to request transfer of control of these human remains and associated funerary objects should submit a written request with information in support of the request to Dr. Ben Secunda, NAGPRA Project Manager, University of Michigan Office of Research, 4080 Fleming Building, 503 S. Thompson Street, Ann Arbor, MI 48109-1340, telephone (734) 647-9085, email bsecunda@umich.edu, by November 16, 2015. After that date, if no additional requestors have come forward, transfer of control of the human remains and associated funerary objects to The Invited and Consulted Tribes may proceed. \n The University of Michigan is responsible for notifying The Invited and Consulted Tribes that this notice has been published. \n "}