{"index": "I_637", "messy_full": "\\n      \\n        DEPARTMENT OF THE INTERIOR\\n        National Park Service\\n        [NPS-WASO-NAGPRA-19370; PPWOCRADN0-PCU00RP14.R50000]\\n        Notice of Inventory Completion: University of Michigan, Ann Arbor, MI\\n        \\n          AGENCY:\\n          National Park Service, Interior.\\n        \\n        \\n          ACTION:\\n          Notice.\\n        \\n        \\n          SUMMARY:\\n          The University of Michigan has completed an inventory of human remains, in consultation with the appropriate Indian tribes or Native Hawaiian organizations, and has determined that there is no cultural affiliation between the human remains and any present-day Indian tribes or Native Hawaiian organizations. Representatives of any Indian tribe or Native Hawaiian organization not identified in this notice that wish to request transfer of control of these human remains should submit a written request to the University of Michigan. If no additional requestors come forward, transfer of control of the human remains to the Indian tribes or Native Hawaiian organizations stated in this notice may proceed.\\n        \\n        \\n          DATES:\\n          Representatives of any Indian tribe or Native Hawaiian organization not identified in this notice that wish to request transfer of control of these human remains should submit a written request with information in support of the request to the University of Michigan at the address in this notice by November 16, 2015.\\n        \\n        \\n          ADDRESSES:\\n\\n          Dr. Ben Secunda, NAGPRA Project Manager, University of Michigan Office of Research, 4080 Fleming Building, 503 S. Thompson Street, Ann Arbor, MI 48109-1340, telephone (734) 647-9085, email bsecunda@umich.edu.\\n          \\n        \\n      \\n      \\n        SUPPLEMENTARY INFORMATION:\\n        Notice is here given in accordance with the Native American Graves Protection and Repatriation Act (NAGPRA), 25 U.S.C. 3003, of the completion of an inventory of human remains under the control of the University of Michigan, Ann Arbor, MI. The human remains were removed from Clinton County, MI.\\n        This notice is published as part of the National Park Service\\'s administrative responsibilities under NAGPRA, 25 U.S.C. 3003(d)(3) and 43 CFR 10.11(d). The determinations in this notice are the sole responsibility of the museum, institution, or Federal agency that has control of the Native American human remains. The National Park Service is not responsible for the determinations in this notice.\\n        Consultation\\n        A detailed assessment of the human remains was made by the University of Michigan Museum of Anthropological Archaeology (UMMAA) professional staff in consultation with representatives of the Bay Mills Indian Community, Michigan; Chippewa Cree Indians of the Rocky Boy\\'s Reservation, Montana; Grand Traverse Band of Ottawa and Chippewa Indians, Michigan; Keweenaw Bay Indian Community, Michigan; Lac Vieux Desert Band of Lake Superior Chippewa Indians, Michigan; Saginaw Chippewa Indian Tribe of Michigan; and the Sault Ste. Marie Tribe of Chippewa Indians, Michigan.\\n\\n        Additional requests for consultation were sent to the Bad River Band of the Lake Superior Tribe of Chippewa Indians of the Bad River Reservation, Wisconsin; Bois Forte Band (Nett Lake) of the Minnesota Chippewa Tribe, Minnesota; Fond du Lac Band of the Minnesota Chippewa Tribe, Minnesota; Grand Portage Band of the Minnesota Chippewa Tribe, Minnesota; Lac Courte Oreilles Band of Lake Superior Chippewa Indians of Wisconsin; Lac du Flambeau Band of Lake Superior Chippewa Indians of the Lac du Flambeau Reservation of Wisconsin; Leech Lake Band of the Minnesota Chippewa Tribe, Minnesota; Mille Lacs Band of the Minnesota Chippewa Tribe, Minnesota; Red Cliff Band of Lake Superior Chippewa Indians of Wisconsin; Red Lake Band of Chippewa Indians, Minnesota; Sokaogon Chippewa Community, Wisconsin; St. Croix Chippewa Indians of Wisconsin; Turtle Mountain Band of Chippewa Indians of North Dakota; and the White Earth Band of the Minnesota Chippewa Tribe, Minnesota.\\n        Hereafter, all tribes listed in this section are referred to as \\xe2\\x80\\x9cThe Invited and Consulted Tribes.\\xe2\\x80\\x9d\\n        History and Description of the Remains\\n        In April 1951, human remains representing, at minimum, four individuals were removed from the Steinbower site (20CL04) in Clinton County, MI. Workers unearthed human remains at the site while conducting gravel removal operations. They contacted the Clinton County Sherriff who collected the human remains and donated them to the UMMAA on April 24, 1951. The human remains are from 1 juvenile, 1 young adult, and 2 adults. The human remains are dated to the Glacial Kame Period, or Late Archaic to Early Woodland Periods (1000-500 B.C.), based on a conch shell collected from the site, although the shell was not donated to the UMMAA. No known individuals were identified. No associated funerary objects are present.\\n        Determinations Made by the University of Michigan\\n        Officials of the University of Michigan have determined that:\\n        \\xe2\\x80\\xa2 Pursuant to 25 U.S.C. 3001(9), the human remains described in this notice are Native American based on cranial morphology, dental traits, archeological context, and accession documentation.\\n        \\xe2\\x80\\xa2 Pursuant to 25 U.S.C. 3001(9), the human remains described in this notice represent the physical remains of four individuals of Native American ancestry.\\n        \\xe2\\x80\\xa2 Pursuant to 25 U.S.C. 3001(2), a relationship of shared group identity cannot be reasonably traced between the Native American human remains and any present-day Indian tribe.\\n        \\xe2\\x80\\xa2 According to final judgments of the Indian Claims Commission or the Court of Federal Claims, the land from which the Native American human remains were removed is the aboriginal land of the Saginaw Chippewa Indian Tribe of Michigan.\\n        \\xe2\\x80\\xa2 Treaties, Acts of Congress, or Executive Orders, indicate that the land from which the Native American human remains were removed is the aboriginal land of The Invited and Consulted Tribes.\\n        \\xe2\\x80\\xa2 Pursuant to 43 CFR 10.11(c)(1), the disposition of the human remains may be to The Invited and Consulted Tribes.\\n        Additional Requestors and Disposition\\n\\n        Representatives of any Indian tribe or Native Hawaiian organization not identified in this notice that wish to request transfer of control of these human remains should submit a written request with information in support of the request to Dr. Ben Secunda, NAGPRA Project Manager, University of Michigan Office of Research, 4080 Fleming Building, 503 S. Thompson Street, Ann Arbor, MI 48109-1340, telephone (734) 647-9085, email bsecunda@umich.edu, by November 16, 2015. After that date, if no additional requestors have come forward, transfer of control of the human remains to The Invited and Consulted Tribes may proceed.\\n        The University of Michigan is responsible for notifying The Invited and Consulted Tribes that this notice has been published.\\n        \\n          Dated: September 22, 2015.\\n          Melanie O\\'Brien,\\n          Manager, National NAGPRA Program. \\n        \\n      \\n      [FR Doc. 2015-26286 Filed 10-14-15; 8:45 am]\\n       BILLING CODE 4312-50-P\\n    ", "agency1": "DEPARTMENT OF THE INTERIOR", "sub_agency1": "National Park Service", "dep_doc": "[NPS-WASO-NAGPRA-19370; PPWOCRADN0-PCU00RP14.R50000]", "subject": "Notice of Inventory Completion: University of Michigan, Ann Arbor, MI", "agency2": "National Park Service, Interior.", "action": "Notice.", "summary": "The University of Michigan has completed an inventory of human remains, in consultation with the appropriate Indian tribes or Native Hawaiian organizations, and has determined that there is no cultural affiliation between the human remains and any present-day Indian tribes or Native Hawaiian organizations. Representatives of any Indian tribe or Native Hawaiian organization not identified in this notice that wish to request transfer of control of these human remains should submit a written request to the University of Michigan. If no additional requestors come forward, transfer of control of the human remains to the Indian tribes or Native Hawaiian organizations stated in this notice may proceed.", "dates": "Representatives of any Indian tribe or Native Hawaiian organization not identified in this notice that wish to request transfer of control of these human remains should submit a written request with information in support of the request to the University of Michigan at the address in this notice by November 16, 2015.", "addresses": "Dr. Ben Secunda, NAGPRA Project Manager, University of Michigan Office of Research, 4080 Fleming Building, 503 S. Thompson Street, Ann Arbor, MI 48109-1340, telephone (734) 647-9085, email bsecunda@umich.edu.\\n          ", "signature_dated": "Dated: September 22, 2015.", "signature_name": "Melanie O\\'Brien,", "signature_title": "Manager, National NAGPRA Program. ", "fr_doc": "[FR Doc. 2015-26286 Filed 10-14-15; 8:45 am]", "billing_code": " BILLING CODE 4312-50-P", "supp_info": "SUPPLEMENTARY INFORMATION: \n Notice is here given in accordance with the Native American Graves Protection and Repatriation Act (NAGPRA), 25 U.S.C. 3003, of the completion of an inventory of human remains under the control of the University of Michigan, Ann Arbor, MI. The human remains were removed from Clinton County, MI. \n This notice is published as part of the National Park Service\\'s administrative responsibilities under NAGPRA, 25 U.S.C. 3003(d)(3) and 43 CFR 10.11(d). The determinations in this notice are the sole responsibility of the museum, institution, or Federal agency that has control of the Native American human remains. The National Park Service is not responsible for the determinations in this notice. \n Consultation \n A detailed assessment of the human remains was made by the University of Michigan Museum of Anthropological Archaeology (UMMAA) professional staff in consultation with representatives of the Bay Mills Indian Community, Michigan; Chippewa Cree Indians of the Rocky Boy\\'s Reservation, Montana; Grand Traverse Band of Ottawa and Chippewa Indians, Michigan; Keweenaw Bay Indian Community, Michigan; Lac Vieux Desert Band of Lake Superior Chippewa Indians, Michigan; Saginaw Chippewa Indian Tribe of Michigan; and the Sault Ste. Marie Tribe of Chippewa Indians, Michigan. \n Additional requests for consultation were sent to the Bad River Band of the Lake Superior Tribe of Chippewa Indians of the Bad River Reservation, Wisconsin; Bois Forte Band (Nett Lake) of the Minnesota Chippewa Tribe, Minnesota; Fond du Lac Band of the Minnesota Chippewa Tribe, Minnesota; Grand Portage Band of the Minnesota Chippewa Tribe, Minnesota; Lac Courte Oreilles Band of Lake Superior Chippewa Indians of Wisconsin; Lac du Flambeau Band of Lake Superior Chippewa Indians of the Lac du Flambeau Reservation of Wisconsin; Leech Lake Band of the Minnesota Chippewa Tribe, Minnesota; Mille Lacs Band of the Minnesota Chippewa Tribe, Minnesota; Red Cliff Band of Lake Superior Chippewa Indians of Wisconsin; Red Lake Band of Chippewa Indians, Minnesota; Sokaogon Chippewa Community, Wisconsin; St. Croix Chippewa Indians of Wisconsin; Turtle Mountain Band of Chippewa Indians of North Dakota; and the White Earth Band of the Minnesota Chippewa Tribe, Minnesota. \n Hereafter, all tribes listed in this section are referred to as \\xe2\\x80\\x9cThe Invited and Consulted Tribes.\\xe2\\x80\\x9d \n History and Description of the Remains \n In April 1951, human remains representing, at minimum, four individuals were removed from the Steinbower site (20CL04) in Clinton County, MI. Workers unearthed human remains at the site while conducting gravel removal operations. They contacted the Clinton County Sherriff who collected the human remains and donated them to the UMMAA on April 24, 1951. The human remains are from 1 juvenile, 1 young adult, and 2 adults. The human remains are dated to the Glacial Kame Period, or Late Archaic to Early Woodland Periods (1000-500 B.C.), based on a conch shell collected from the site, although the shell was not donated to the UMMAA. No known individuals were identified. No associated funerary objects are present. \n Determinations Made by the University of Michigan \n Officials of the University of Michigan have determined that: \n \\xe2\\x80\\xa2 Pursuant to 25 U.S.C. 3001(9), the human remains described in this notice are Native American based on cranial morphology, dental traits, archeological context, and accession documentation. \n \\xe2\\x80\\xa2 Pursuant to 25 U.S.C. 3001(9), the human remains described in this notice represent the physical remains of four individuals of Native American ancestry. \n \\xe2\\x80\\xa2 Pursuant to 25 U.S.C. 3001(2), a relationship of shared group identity cannot be reasonably traced between the Native American human remains and any present-day Indian tribe. \n \\xe2\\x80\\xa2 According to final judgments of the Indian Claims Commission or the Court of Federal Claims, the land from which the Native American human remains were removed is the aboriginal land of the Saginaw Chippewa Indian Tribe of Michigan. \n \\xe2\\x80\\xa2 Treaties, Acts of Congress, or Executive Orders, indicate that the land from which the Native American human remains were removed is the aboriginal land of The Invited and Consulted Tribes. \n \\xe2\\x80\\xa2 Pursuant to 43 CFR 10.11(c)(1), the disposition of the human remains may be to The Invited and Consulted Tribes. \n Additional Requestors and Disposition \n Representatives of any Indian tribe or Native Hawaiian organization not identified in this notice that wish to request transfer of control of these human remains should submit a written request with information in support of the request to Dr. Ben Secunda, NAGPRA Project Manager, University of Michigan Office of Research, 4080 Fleming Building, 503 S. Thompson Street, Ann Arbor, MI 48109-1340, telephone (734) 647-9085, email bsecunda@umich.edu, by November 16, 2015. After that date, if no additional requestors have come forward, transfer of control of the human remains to The Invited and Consulted Tribes may proceed. \n The University of Michigan is responsible for notifying The Invited and Consulted Tribes that this notice has been published. \n ", "consultation": "A detailed assessment of the human remains was made by the University of Michigan Museum of Anthropological Archaeology (UMMAA) professional staff in consultation with representatives of the Bay Mills Indian Community, Michigan; Chippewa Cree Indians of the Rocky Boy\\'s Reservation, Montana; Grand Traverse Band of Ottawa and Chippewa Indians, Michigan; Keweenaw Bay Indian Community, Michigan; Lac Vieux Desert Band of Lake Superior Chippewa Indians, Michigan; Saginaw Chippewa Indian Tribe of Michigan; and the Sault Ste. Marie Tribe of Chippewa Indians, Michigan. \n Additional requests for consultation were sent to the Bad River Band of the Lake Superior Tribe of Chippewa Indians of the Bad River Reservation, Wisconsin; Bois Forte Band (Nett Lake) of the Minnesota Chippewa Tribe, Minnesota; Fond du Lac Band of the Minnesota Chippewa Tribe, Minnesota; Grand Portage Band of the Minnesota Chippewa Tribe, Minnesota; Lac Courte Oreilles Band of Lake Superior Chippewa Indians of Wisconsin; Lac du Flambeau Band of Lake Superior Chippewa Indians of the Lac du Flambeau Reservation of Wisconsin; Leech Lake Band of the Minnesota Chippewa Tribe, Minnesota; Mille Lacs Band of the Minnesota Chippewa Tribe, Minnesota; Red Cliff Band of Lake Superior Chippewa Indians of Wisconsin; Red Lake Band of Chippewa Indians, Minnesota; Sokaogon Chippewa Community, Wisconsin; St. Croix Chippewa Indians of Wisconsin; Turtle Mountain Band of Chippewa Indians of North Dakota; and the White Earth Band of the Minnesota Chippewa Tribe, Minnesota. \n Hereafter, all tribes listed in this section are referred to as \\xe2\\x80\\x9cThe Invited and Consulted Tribes.\\xe2\\x80\\x9d \n ", "h_d_r": "In April 1951, human remains representing, at minimum, four individuals were removed from the Steinbower site (20CL04) in Clinton County, MI. Workers unearthed human remains at the site while conducting gravel removal operations. They contacted the Clinton County Sherriff who collected the human remains and donated them to the UMMAA on April 24, 1951. The human remains are from 1 juvenile, 1 young adult, and 2 adults. The human remains are dated to the Glacial Kame Period, or Late Archaic to Early Woodland Periods (1000-500 B.C.), based on a conch shell collected from the site, although the shell was not donated to the UMMAA. No known individuals were identified. No associated funerary objects are present. \n ", "h_d_ci": "Null", "determinations": "Determinations Made by the University of Michigan \n Officials of the University of Michigan have determined that: \n \\xe2\\x80\\xa2 Pursuant to 25 U.S.C. 3001(9), the human remains described in this notice are Native American based on cranial morphology, dental traits, archeological context, and accession documentation. \n \\xe2\\x80\\xa2 Pursuant to 25 U.S.C. 3001(9), the human remains described in this notice represent the physical remains of four individuals of Native American ancestry. \n \\xe2\\x80\\xa2 Pursuant to 25 U.S.C. 3001(2), a relationship of shared group identity cannot be reasonably traced between the Native American human remains and any present-day Indian tribe. \n \\xe2\\x80\\xa2 According to final judgments of the Indian Claims Commission or the Court of Federal Claims, the land from which the Native American human remains were removed is the aboriginal land of the Saginaw Chippewa Indian Tribe of Michigan. \n \\xe2\\x80\\xa2 Treaties, Acts of Congress, or Executive Orders, indicate that the land from which the Native American human remains were removed is the aboriginal land of The Invited and Consulted Tribes. \n \\xe2\\x80\\xa2 Pursuant to 43 CFR 10.11(c)(1), the disposition of the human remains may be to The Invited and Consulted Tribes. \n ", "a_r_d": "Representatives of any Indian tribe or Native Hawaiian organization not identified in this notice that wish to request transfer of control of these human remains should submit a written request with information in support of the request to Dr. Ben Secunda, NAGPRA Project Manager, University of Michigan Office of Research, 4080 Fleming Building, 503 S. Thompson Street, Ann Arbor, MI 48109-1340, telephone (734) 647-9085, email bsecunda@umich.edu, by November 16, 2015. After that date, if no additional requestors have come forward, transfer of control of the human remains to The Invited and Consulted Tribes may proceed. \n The University of Michigan is responsible for notifying The Invited and Consulted Tribes that this notice has been published. \n "}