{"index": "I_642", "messy_full": "\\n      \\n        DEPARTMENT OF THE INTERIOR\\n        National Park Service\\n        [NPS-WASO-NAGPRA-19125: PPWOCRADN0-PCU00RP14.R50000]\\n        Notice of Inventory Completion: U.S. Department of the Interior, National Park Service, Hubbell Trading Post National Historic Site, Ganado, AZ; Correction\\n        \\n          AGENCY:\\n          National Park Service, Interior.\\n        \\n        \\n          ACTION:\\n          Notice; correction.\\n        \\n        \\n          SUMMARY:\\n\\n          The U.S. Department of the Interior, National Park Service, Hubbell Trading Post National Historic Site has corrected an inventory of human remains, published in a Notice of Inventory Completion in the Federal Register on July 28, 2014. This notice corrects the disposition determination and clarifies when one set of remains was collected. Representatives of any Indian tribe or Native Hawaiian organization not identified in this notice that wish to request transfer of control of these human remains should submit a written request to Hubbell Trading Post National Historic Site. If no additional requestors come forward, transfer of control of the human remains to the Indian tribes or Native Hawaiian organizations stated in this notice may proceed.\\n        \\n        \\n          DATES:\\n          Representatives of any Indian tribe or Native Hawaiian organization not identified in this notice that wish to request transfer of control of these human remains should submit a written request with information in support of the request to Hubbell Trading Post National Historic Site at the address in this notice by November 2, 2015.\\n        \\n        \\n          ADDRESSES:\\n\\n          Lloyd Masayumptewa, Superintendent, Hubbell Trading Post National Historic Site, P.O. Box 150, Ganado, AZ 86505-0150, telephone (928) 755-3475, email lloyd_masayumptewa@nps.gov.\\n          \\n        \\n      \\n      \\n        SUPPLEMENTARY INFORMATION:\\n        Notice is here given in accordance with the Native American Graves Protection and Repatriation Act (NAGPRA), 25 U.S.C. 3003, of the correction of an inventory of human remains under the control of the U.S. Department of the Interior, National Park Service, Hubbell Trading Post National Historic Site, Ganado, AZ. The human remains were removed from Hubbell Trading Post National Historic Site, Apache County, AZ.\\n        This notice is published as part of the National Park Service\\'s administrative responsibilities under NAGPRA, 25 U.S.C. 3003(d)(3). The determinations in this notice are the sole responsibility of the Superintendent, Hubbell Trading Post National Historic Site.\\n\\n        This notice corrects the disposition determination and clarifies one removal date published in a Notice of Inventory Completion in the Federal Register (79 FR 43776-43778, July 28, 2014). The published notice recognized several Indian tribes as aboriginal to the area from which the human remains were removed. Upon further review, Hubbell Trading Post National Historic Site has determined that the land from which the human remains were removed is considered tribal land as defined at 25 U.S.C. 3001(15). Transfer of control of the items in this correction notice has not occurred.\\n        Correction\\n        In the Federal Register (79 FR 43776-43778, July 28, 2014), paragraph 8, sentence 1 is corrected by substituting the following sentences:\\n        \\n        \\n          At an unknown date, likely after 1887, human remains representing, at minimum, one individual were removed from an unknown site, likely within the boundaries of Hubbell Trading Post National Historic Site. The remains were donated to the Trading Post at an unknown date by the Hubbell family.\\n          \\n        \\n        In the Federal Register (79 FR 43776-43778, July 28, 2014), paragraphs 14, 15, and 16 are deleted.\\n        In the Federal Register (79 FR 43776-43778, July 28, 2014), the following paragraph is inserted immediately before paragraph 17:\\n        \\xe2\\x80\\xa2 Pursuant to 25 U.S.C. 3001(15), the land from which the Native American human remains were removed is the tribal land of the Navajo Nation, Arizona, New Mexico & Utah.\\n        In the Federal Register (79 FR 43776-43778, July 28, 2014), paragraph 17 is corrected by substituting the following paragraph:\\n        \\xe2\\x80\\xa2 Pursuant to 43 CFR 10.11(c)(1)(i), the disposition of the human remains will be to the Navajo Nation, Arizona, New Mexico & Utah.\\n        In the Federal Register (79 FR 43776-43778, July 28, 2014), paragraph 18, sentence 2 is corrected by substituting the following sentence:\\n        \\n        \\n          After that date, if no additional requestors have come forward, transfer of control of the human remains to the Navajo Nation, Arizona, New Mexico & Utah may proceed.\\n        \\n        Additional Requestors and Disposition\\n\\n        Representatives of any Indian tribe or Native Hawaiian organization not identified in this notice that wish to request transfer of control of these human remains should submit a written request with information in support of the request to Lloyd Masayumptewa, Superintendent, Hubbell Trading Post National Historic Site, P.O. Box 150, Ganado, AZ 86505-0150, telephone (928) 755-3475, email lloyd_masayumptewa@nps.gov, by November 2, 2015. After that date, if no additional requestors have come forward, transfer of control of the human remains to the Navajo Nation, Arizona, New Mexico & Utah may proceed.\\n        Hubbell Trading Post National Historic Site is responsible for notifying The Consulted Tribes and The Invited Tribes that this notice has been published.\\n        \\n          Dated: August 25, 2015.\\n          Melanie O\\'Brien,\\n          Manager, National NAGPRA Program.\\n        \\n      \\n      [FR Doc. 2015-25047 Filed 9-30-15; 8:45 am]\\n      BILLING CODE 4312-50-P\\n    ", "agency1": "DEPARTMENT OF THE INTERIOR", "sub_agency1": "National Park Service", "dep_doc": "[NPS-WASO-NAGPRA-19125: PPWOCRADN0-PCU00RP14.R50000]", "subject": "Notice of Inventory Completion: U.S. Department of the Interior, National Park Service, Hubbell Trading Post National Historic Site, Ganado, AZ; Correction", "agency2": "National Park Service, Interior.", "action": "Notice; correction.", "summary": "The U.S. Department of the Interior, National Park Service, Hubbell Trading Post National Historic Site has corrected an inventory of human remains, published in a Notice of Inventory Completion in the Federal Register on July 28, 2014. This notice corrects the disposition determination and clarifies when one set of remains was collected. Representatives of any Indian tribe or Native Hawaiian organization not identified in this notice that wish to request transfer of control of these human remains should submit a written request to Hubbell Trading Post National Historic Site. If no additional requestors come forward, transfer of control of the human remains to the Indian tribes or Native Hawaiian organizations stated in this notice may proceed.", "dates": "Representatives of any Indian tribe or Native Hawaiian organization not identified in this notice that wish to request transfer of control of these human remains should submit a written request with information in support of the request to Hubbell Trading Post National Historic Site at the address in this notice by November 2, 2015.", "addresses": "Lloyd Masayumptewa, Superintendent, Hubbell Trading Post National Historic Site, P.O. Box 150, Ganado, AZ 86505-0150, telephone (928) 755-3475, email lloyd_masayumptewa@nps.gov.\\n          ", "signature_dated": "Dated: August 25, 2015.", "signature_name": "Melanie O\\'Brien,", "signature_title": "Manager, National NAGPRA Program.", "fr_doc": "[FR Doc. 2015-25047 Filed 9-30-15; 8:45 am]", "billing_code": "BILLING CODE 4312-50-P", "supp_info": "SUPPLEMENTARY INFORMATION: \n Notice is here given in accordance with the Native American Graves Protection and Repatriation Act (NAGPRA), 25 U.S.C. 3003, of the correction of an inventory of human remains under the control of the U.S. Department of the Interior, National Park Service, Hubbell Trading Post National Historic Site, Ganado, AZ. The human remains were removed from Hubbell Trading Post National Historic Site, Apache County, AZ. \n This notice is published as part of the National Park Service\\'s administrative responsibilities under NAGPRA, 25 U.S.C. 3003(d)(3). The determinations in this notice are the sole responsibility of the Superintendent, Hubbell Trading Post National Historic Site. \n This notice corrects the disposition determination and clarifies one removal date published in a Notice of Inventory Completion in the Federal Register (79 FR 43776-43778, July 28, 2014). The published notice recognized several Indian tribes as aboriginal to the area from which the human remains were removed. Upon further review, Hubbell Trading Post National Historic Site has determined that the land from which the human remains were removed is considered tribal land as defined at 25 U.S.C. 3001(15). Transfer of control of the items in this correction notice has not occurred. \n Correction \n In the Federal Register (79 FR 43776-43778, July 28, 2014), paragraph 8, sentence 1 is corrected by substituting the following sentences: \n In the Federal Register (79 FR 43776-43778, July 28, 2014), paragraphs 14, 15, and 16 are deleted. \n In the Federal Register (79 FR 43776-43778, July 28, 2014), the following paragraph is inserted immediately before paragraph 17: \n \\xe2\\x80\\xa2 Pursuant to 25 U.S.C. 3001(15), the land from which the Native American human remains were removed is the tribal land of the Navajo Nation, Arizona, New Mexico & Utah. \n In the Federal Register (79 FR 43776-43778, July 28, 2014), paragraph 17 is corrected by substituting the following paragraph: \n \\xe2\\x80\\xa2 Pursuant to 43 CFR 10.11(c)(1)(i), the disposition of the human remains will be to the Navajo Nation, Arizona, New Mexico & Utah. \n In the Federal Register (79 FR 43776-43778, July 28, 2014), paragraph 18, sentence 2 is corrected by substituting the following sentence: \n Additional Requestors and Disposition \n Representatives of any Indian tribe or Native Hawaiian organization not identified in this notice that wish to request transfer of control of these human remains should submit a written request with information in support of the request to Lloyd Masayumptewa, Superintendent, Hubbell Trading Post National Historic Site, P.O. Box 150, Ganado, AZ 86505-0150, telephone (928) 755-3475, email lloyd_masayumptewa@nps.gov, by November 2, 2015. After that date, if no additional requestors have come forward, transfer of control of the human remains to the Navajo Nation, Arizona, New Mexico & Utah may proceed. \n Hubbell Trading Post National Historic Site is responsible for notifying The Consulted Tribes and The Invited Tribes that this notice has been published. \n ", "consultation": "Null", "h_d_r": "Null", "h_d_ci": "Null", "determinations": "Null", "a_r_d": "Representatives of any Indian tribe or Native Hawaiian organization not identified in this notice that wish to request transfer of control of these human remains should submit a written request with information in support of the request to Lloyd Masayumptewa, Superintendent, Hubbell Trading Post National Historic Site, P.O. Box 150, Ganado, AZ 86505-0150, telephone (928) 755-3475, email lloyd_masayumptewa@nps.gov, by November 2, 2015. After that date, if no additional requestors have come forward, transfer of control of the human remains to the Navajo Nation, Arizona, New Mexico & Utah may proceed. \n Hubbell Trading Post National Historic Site is responsible for notifying The Consulted Tribes and The Invited Tribes that this notice has been published. \n "}