{"index": "I_668", "messy_full": "\\n      \\n        DEPARTMENT OF THE INTERIOR\\n        National Park Service\\n        [NPS-WASO-NAGPRA-18025; PPWOCRADN0-PCU00RP15.R50000]\\n        Notice of Inventory Completion: The American Museum of Natural History, New York, NY; Correction\\n        \\n          AGENCY:\\n          National Park Service, Interior.\\n        \\n        \\n          ACTION:\\n          Notice; correction.\\n        \\n        \\n          SUMMARY:\\n\\n          The American Museum of Natural History has revised a Notice of Inventory Completion that was published in the Federal Register on February 4, 2015. This notice revises the listing of Indian tribes who are recognized as aboriginal to the area from which Native American human remains were removed.\\n        \\n        \\n          ADDRESSES:\\n\\n          Nell Murphy, Director of Cultural Resources, American Museum of Natural History, Central Park West at 79th Street, New York, NY 10024, telephone (212) 769-5837, email nmurphy@amnh.org.\\n        \\n      \\n      \\n        SUPPLEMENTARY INFORMATION:\\n        Notice is here given in accordance with the Native American Graves Protection and Repatriation Act (NAGPRA), 25 U.S.C. 3003, of the revision of a Notice of Inventory Completion for human remains under the control of the American Museum of Natural History, New York, NY. The human remains were removed from the Grand Hotel vicinity, Mackinac Island, Mackinac County, MI.\\n        This notice is published as part of the National Park Service\\'s administrative responsibilities under NAGPRA, 25 U.S.C. 3003(d)(3). The determinations in this notice are the sole responsibility of the museum, institution, or Federal agency that has control of the Native American human remains. The National Park Service is not responsible for the determinations in this notice.\\n\\n        This notice revises the listing of Indian tribes who are recognized as aboriginal to the area from which Native American human remains were removed. These remains were described in a Notice of Inventory Completion published in the Federal Register (80 FR 6120-6121, February 4, 2015).\\n        \\n        In the Federal Register (80 FR 6121, February 4, 2015), paragraph 13, sentence 1 has been revised by substituting the following sentence:\\n        \\n        \\n          According to final judgments of the Indian Claims Commission or the Court of Federal Claims, or indicated by Treaties, Acts of Congress, or Executive Orders, the land from which the Native American human remains were removed is the aboriginal land of The Tribes.\\n        \\n        \\n        In the Federal Register (80 FR 6120-6121, February 4, 2015), paragraph 14 is revised by deleting the entire paragraph.\\n        The American Museum of Natural History is responsible for notifying The Tribes that this notice has been published.\\n        \\n          Dated: April 22, 2015.\\n          Mariah Soriano,\\n          Acting Manager, National NAGPRA Program.\\n        \\n      \\n      [FR Doc. 2015-12532 Filed 5-21-15; 8:45 am]\\n      BILLING CODE 4312-50-P\\n    ", "agency1": "DEPARTMENT OF THE INTERIOR", "sub_agency1": "National Park Service", "dep_doc": "[NPS-WASO-NAGPRA-18025; PPWOCRADN0-PCU00RP15.R50000]", "subject": "Notice of Inventory Completion: The American Museum of Natural History, New York, NY; Correction", "agency2": "National Park Service, Interior.", "action": "Notice; correction.", "summary": "The American Museum of Natural History has revised a Notice of Inventory Completion that was published in the Federal Register on February 4, 2015. This notice revises the listing of Indian tribes who are recognized as aboriginal to the area from which Native American human remains were removed.", "dates": "Null", "addresses": "Nell Murphy, Director of Cultural Resources, American Museum of Natural History, Central Park West at 79th Street, New York, NY 10024, telephone (212) 769-5837, email nmurphy@amnh.org.", "signature_dated": "Dated: April 22, 2015.", "signature_name": "Mariah Soriano,", "signature_title": "Acting Manager, National NAGPRA Program.", "fr_doc": "[FR Doc. 2015-12532 Filed 5-21-15; 8:45 am]", "billing_code": "BILLING CODE 4312-50-P", "supp_info": "SUPPLEMENTARY INFORMATION: \n Notice is here given in accordance with the Native American Graves Protection and Repatriation Act (NAGPRA), 25 U.S.C. 3003, of the revision of a Notice of Inventory Completion for human remains under the control of the American Museum of Natural History, New York, NY. The human remains were removed from the Grand Hotel vicinity, Mackinac Island, Mackinac County, MI. \n This notice is published as part of the National Park Service\\'s administrative responsibilities under NAGPRA, 25 U.S.C. 3003(d)(3). The determinations in this notice are the sole responsibility of the museum, institution, or Federal agency that has control of the Native American human remains. The National Park Service is not responsible for the determinations in this notice. \n This notice revises the listing of Indian tribes who are recognized as aboriginal to the area from which Native American human remains were removed. These remains were described in a Notice of Inventory Completion published in the Federal Register (80 FR 6120-6121, February 4, 2015).\\n         \n In the Federal Register (80 FR 6121, February 4, 2015), paragraph 13, sentence 1 has been revised by substituting the following sentence: \n In the Federal Register (80 FR 6120-6121, February 4, 2015), paragraph 14 is revised by deleting the entire paragraph. \n The American Museum of Natural History is responsible for notifying The Tribes that this notice has been published. \n ", "consultation": "Null", "h_d_r": "Null", "h_d_ci": "Null", "determinations": "Null", "a_r_d": "Null"}