{"index": "I_660", "messy_full": "\\n      \\n        DEPARTMENT OF THE INTERIOR\\n        National Park Service\\n        [NPS-WASO-NAGPRA-18278; PPWOCRADN0-PCU00RP15.R50000]\\n        Notice of Inventory Completion: Museum of Anthropology at Washington State University, Pullman, WA\\n        \\n          AGENCY:\\n          National Park Service, Interior.\\n        \\n        \\n          ACTION:\\n          Notice.\\n        \\n        \\n          SUMMARY:\\n          The Museum of Anthropology at Washington State University has completed an inventory of human remains, in consultation with the appropriate Indian tribes or Native Hawaiian organizations, and has determined that there is a cultural affiliation between the human remains and present-day Indian tribes or Native Hawaiian organizations. Lineal descendants or representatives of any Indian tribe or Native Hawaiian organization not identified in this notice that wish to request transfer of control of these human remains should submit a written request to the Museum of Anthropology at Washington State University. If no additional requestors come forward, transfer of control of the human remains to the lineal descendants, Indian tribes, or Native Hawaiian organizations stated in this notice may proceed.\\n        \\n        \\n          DATES:\\n          Lineal descendants or representatives of any Indian tribe or Native Hawaiian organization not identified in this notice that wish to request transfer of control of these human remains should submit a written request with information in support of the request to the Museum of Anthropology at Washington State University at the address in this notice by September 4, 2015.\\n        \\n        \\n          ADDRESSES:\\n\\n          Mary Collins, Director Emeritus, Museum of Anthropology Washington State University, Pullman, WA 99164-4910, telephone (509) 592-6929, email collinsm@wsu.edu.\\n          \\n        \\n      \\n      \\n        SUPPLEMENTARY INFORMATION:\\n        Notice is here given in accordance with the Native American Graves Protection and Repatriation Act (NAGPRA), 25 U.S.C. 3003, of the completion of an inventory of human remains under the control of the Museum of Anthropology at Washington State University Pullman, WA. The human remains were removed from near the mouth of Crab Creek in Grant County, WA.\\n        This notice is published as part of the National Park Service\\'s administrative responsibilities under NAGPRA, 25 U.S.C. 3003(d)(3). The determinations in this notice are the sole responsibility of the museum, institution, or Federal agency that has control of the Native American human remains. The National Park Service is not responsible for the determinations in this notice.\\n        Consultation\\n        A detailed assessment of the human remains was made by the Museum of Anthropology at Washington State University professional staff in consultation with representatives of the Confederated Tribes and Bands of the Yakama Nation, Confederated Tribes of the Colville Reservation, and the Wanapum Band, a non-federally recognized Indian group.\\n        History and Description of the Remains\\n        In 1957, human remains representing, at minimum, one individual were removed from near the mouth of Crab Creek in Grant County, WA. No information about why or how the human remains were collected has been located. No known individuals were identified. No associated funerary objects are present. The human remains consist of a single lot of sand, ash, charcoal, and fragmentary human remains and are believed to be the remnants of a cremation feature. The human remains were found in a box labeled with the date and location from which the human remains were removed and the names of two students who are presumed to have done the removal. Attempts to locate and communicate with the students were not successful. Although not the most common form of burial, cremation was practiced by a number of Native American groups along the Columbia River from very ancient to relatively recent times.\\n        Determinations Made by the Museum of Anthropology at Washington State University\\n        Officials of the Museum of Anthropology at Washington State University have determined that:\\n        \\xe2\\x80\\xa2 Pursuant to 25 U.S.C. 3001(9), the human remains described in this notice represent the physical remains of one individual of Native American ancestry.\\n        \\xe2\\x80\\xa2 Pursuant to 25 U.S.C. 3001(2), there is a relationship of shared group identity that can be reasonably traced between the Native American human remains and the Confederated Tribes and Bands of the Yakama Nation and the Confederated Tribes of the Colville Reservation. Additionally, a cultural relationship is determined to exist between the human remains and the Wanapum Band, a non-federally recognized Indian group.\\n        Additional Requestors and Disposition\\n\\n        Lineal descendants or representatives of any Indian tribe or Native Hawaiian organization not identified in this notice that wish to request transfer of control of these human remains should submit a written request with information in support of the request to Mary Collins, Director Emeritus, Museum of Anthropology at Washington State University, Pullman, WA 99164-4910, telephone (509) 592-6929, email collinsm@wsu.edu, by September 4, 2015. After that date, if no additional requestors have come forward, transfer of control of the human remains to the Confederated Tribes and Bands of the Yakama Nation, the Confederated Tribes of the Colville Reservation, and, if joined to one or more of the culturally affiliated tribes, the Wanapum Band, a non-federally recognized Indian group, may proceed.\\n        The Museum of Anthropology at Washington State University is responsible for notifying the Confederated Tribes and Bands of the Yakama Nation, Confederated Tribes of the Colville Reservation, and the Wanapum Band, a non-federally recognized Indian group, that this notice has been published.\\n        \\n          Dated: May 11, 2015.\\n          Mariah Soriano,\\n          Acting Manager, National NAGPRA Program. \\n        \\n      \\n      [FR Doc. 2015-19271 Filed 8-4-15; 8:45 am]\\n       BILLING CODE 4312-50-P\\n    ", "agency1": "DEPARTMENT OF THE INTERIOR", "sub_agency1": "National Park Service", "dep_doc": "[NPS-WASO-NAGPRA-18278; PPWOCRADN0-PCU00RP15.R50000]", "subject": "Notice of Inventory Completion: Museum of Anthropology at Washington State University, Pullman, WA", "agency2": "National Park Service, Interior.", "action": "Notice.", "summary": "The Museum of Anthropology at Washington State University has completed an inventory of human remains, in consultation with the appropriate Indian tribes or Native Hawaiian organizations, and has determined that there is a cultural affiliation between the human remains and present-day Indian tribes or Native Hawaiian organizations. Lineal descendants or representatives of any Indian tribe or Native Hawaiian organization not identified in this notice that wish to request transfer of control of these human remains should submit a written request to the Museum of Anthropology at Washington State University. If no additional requestors come forward, transfer of control of the human remains to the lineal descendants, Indian tribes, or Native Hawaiian organizations stated in this notice may proceed.", "dates": "Lineal descendants or representatives of any Indian tribe or Native Hawaiian organization not identified in this notice that wish to request transfer of control of these human remains should submit a written request with information in support of the request to the Museum of Anthropology at Washington State University at the address in this notice by September 4, 2015.", "addresses": "Mary Collins, Director Emeritus, Museum of Anthropology Washington State University, Pullman, WA 99164-4910, telephone (509) 592-6929, email collinsm@wsu.edu.\\n          ", "signature_dated": "Dated: May 11, 2015.", "signature_name": "Mariah Soriano,", "signature_title": "Acting Manager, National NAGPRA Program. ", "fr_doc": "[FR Doc. 2015-19271 Filed 8-4-15; 8:45 am]", "billing_code": " BILLING CODE 4312-50-P", "supp_info": "SUPPLEMENTARY INFORMATION: \n Notice is here given in accordance with the Native American Graves Protection and Repatriation Act (NAGPRA), 25 U.S.C. 3003, of the completion of an inventory of human remains under the control of the Museum of Anthropology at Washington State University Pullman, WA. The human remains were removed from near the mouth of Crab Creek in Grant County, WA. \n This notice is published as part of the National Park Service\\'s administrative responsibilities under NAGPRA, 25 U.S.C. 3003(d)(3). The determinations in this notice are the sole responsibility of the museum, institution, or Federal agency that has control of the Native American human remains. The National Park Service is not responsible for the determinations in this notice. \n Consultation \n A detailed assessment of the human remains was made by the Museum of Anthropology at Washington State University professional staff in consultation with representatives of the Confederated Tribes and Bands of the Yakama Nation, Confederated Tribes of the Colville Reservation, and the Wanapum Band, a non-federally recognized Indian group. \n History and Description of the Remains \n In 1957, human remains representing, at minimum, one individual were removed from near the mouth of Crab Creek in Grant County, WA. No information about why or how the human remains were collected has been located. No known individuals were identified. No associated funerary objects are present. The human remains consist of a single lot of sand, ash, charcoal, and fragmentary human remains and are believed to be the remnants of a cremation feature. The human remains were found in a box labeled with the date and location from which the human remains were removed and the names of two students who are presumed to have done the removal. Attempts to locate and communicate with the students were not successful. Although not the most common form of burial, cremation was practiced by a number of Native American groups along the Columbia River from very ancient to relatively recent times. \n Determinations Made by the Museum of Anthropology at Washington State University \n Officials of the Museum of Anthropology at Washington State University have determined that: \n \\xe2\\x80\\xa2 Pursuant to 25 U.S.C. 3001(9), the human remains described in this notice represent the physical remains of one individual of Native American ancestry. \n \\xe2\\x80\\xa2 Pursuant to 25 U.S.C. 3001(2), there is a relationship of shared group identity that can be reasonably traced between the Native American human remains and the Confederated Tribes and Bands of the Yakama Nation and the Confederated Tribes of the Colville Reservation. Additionally, a cultural relationship is determined to exist between the human remains and the Wanapum Band, a non-federally recognized Indian group. \n Additional Requestors and Disposition \n Lineal descendants or representatives of any Indian tribe or Native Hawaiian organization not identified in this notice that wish to request transfer of control of these human remains should submit a written request with information in support of the request to Mary Collins, Director Emeritus, Museum of Anthropology at Washington State University, Pullman, WA 99164-4910, telephone (509) 592-6929, email collinsm@wsu.edu, by September 4, 2015. After that date, if no additional requestors have come forward, transfer of control of the human remains to the Confederated Tribes and Bands of the Yakama Nation, the Confederated Tribes of the Colville Reservation, and, if joined to one or more of the culturally affiliated tribes, the Wanapum Band, a non-federally recognized Indian group, may proceed. \n The Museum of Anthropology at Washington State University is responsible for notifying the Confederated Tribes and Bands of the Yakama Nation, Confederated Tribes of the Colville Reservation, and the Wanapum Band, a non-federally recognized Indian group, that this notice has been published. \n ", "consultation": "A detailed assessment of the human remains was made by the Museum of Anthropology at Washington State University professional staff in consultation with representatives of the Confederated Tribes and Bands of the Yakama Nation, Confederated Tribes of the Colville Reservation, and the Wanapum Band, a non-federally recognized Indian group. \n ", "h_d_r": "In 1957, human remains representing, at minimum, one individual were removed from near the mouth of Crab Creek in Grant County, WA. No information about why or how the human remains were collected has been located. No known individuals were identified. No associated funerary objects are present. The human remains consist of a single lot of sand, ash, charcoal, and fragmentary human remains and are believed to be the remnants of a cremation feature. The human remains were found in a box labeled with the date and location from which the human remains were removed and the names of two students who are presumed to have done the removal. Attempts to locate and communicate with the students were not successful. Although not the most common form of burial, cremation was practiced by a number of Native American groups along the Columbia River from very ancient to relatively recent times. \n ", "h_d_ci": "Null", "determinations": "Determinations Made by the Museum of Anthropology at Washington State University \n Officials of the Museum of Anthropology at Washington State University have determined that: \n \\xe2\\x80\\xa2 Pursuant to 25 U.S.C. 3001(9), the human remains described in this notice represent the physical remains of one individual of Native American ancestry. \n \\xe2\\x80\\xa2 Pursuant to 25 U.S.C. 3001(2), there is a relationship of shared group identity that can be reasonably traced between the Native American human remains and the Confederated Tribes and Bands of the Yakama Nation and the Confederated Tribes of the Colville Reservation. Additionally, a cultural relationship is determined to exist between the human remains and the Wanapum Band, a non-federally recognized Indian group. \n ", "a_r_d": "Lineal descendants or representatives of any Indian tribe or Native Hawaiian organization not identified in this notice that wish to request transfer of control of these human remains should submit a written request with information in support of the request to Mary Collins, Director Emeritus, Museum of Anthropology at Washington State University, Pullman, WA 99164-4910, telephone (509) 592-6929, email collinsm@wsu.edu, by September 4, 2015. After that date, if no additional requestors have come forward, transfer of control of the human remains to the Confederated Tribes and Bands of the Yakama Nation, the Confederated Tribes of the Colville Reservation, and, if joined to one or more of the culturally affiliated tribes, the Wanapum Band, a non-federally recognized Indian group, may proceed. \n The Museum of Anthropology at Washington State University is responsible for notifying the Confederated Tribes and Bands of the Yakama Nation, Confederated Tribes of the Colville Reservation, and the Wanapum Band, a non-federally recognized Indian group, that this notice has been published. \n "}