{"index": "I_719", "messy_full": "\\n      \\n        DEPARTMENT OF THE INTERIOR\\n        National Park Service\\n        [NPS-WASO-NAGPRA-17372; PPWOCRADN0-PCU00RP14.R50000]\\n        Notice of Inventory Completion: The American Museum of Natural History, New York, NY\\n        \\n          AGENCY:\\n          National Park Service, Interior.\\n        \\n        \\n          ACTION:\\n          Notice.\\n        \\n        \\n          SUMMARY:\\n          The American Museum of Natural History has completed an inventory of human remains in consultation with the appropriate Indian tribes or Native Hawaiian organizations, and has determined that there is no cultural affiliation between the human remains and any present-day Indian tribes or Native Hawaiian organizations. Representatives of any Indian tribe or Native Hawaiian organization not identified in this notice that wish to request transfer of control of these human remains should submit a written request to the American Museum of Natural History. If no additional requestors come forward, transfer of control of the human remains to the Indian tribes or Native Hawaiian organizations stated in this notice may proceed.\\n        \\n        \\n          \\n          DATES:\\n          Representatives of any Indian tribe or Native Hawaiian organization not identified in this notice that wish to request transfer of control of these human remains should submit a written request with information in support of the request to the American Museum of Natural History at the address in this notice by March 6, 2015.\\n        \\n        \\n          ADDRESSES:\\n\\n          Nell Murphy, Director of Cultural Resources, American Museum of Natural History, Central Park West at 79th Street, New York, NY 10024, telephone (212) 769-5837, email nmurphy@amnh.org.\\n          \\n        \\n      \\n      \\n        SUPPLEMENTARY INFORMATION:\\n        Notice is here given in accordance with the Native American Graves Protection and Repatriation Act (NAGPRA), 25 U.S.C. 3003, of the completion of an inventory of human remains under the control of the American Museum of Natural History, New York, NY. The human remains were removed from an unidentified mound in an unknown county in MI.\\n        This notice is published as part of the National Park Service\\'s administrative responsibilities under NAGPRA, 25 U.S.C. 3003(d)(3) and 43 CFR 10.11(d). The determinations in this notice are the sole responsibility of the museum, institution, or Federal agency that has control of the Native American human remains. The National Park Service is not responsible for the determinations in this notice.\\n        Consultation\\n        A detailed assessment of the human remains was made by the American Museum of Natural History professional staff in consultation with representatives of the Absentee-Shawnee Tribe of Indians of Oklahoma; Bad River Band of the Lake Superior Tribe of Chippewa Indians of the Bad River Reservation, Wisconsin; Bay Mills Indian Community, Michigan; Bois Forte Band (Nett Lake) of the Minnesota Chippewa Tribe, Minnesota; Chippewa-Cree Indians of the Rocky Boy\\'s Reservation, Montana; Citizen Potawatomi Nation, Oklahoma; Delaware Nation, Oklahoma; Delaware Tribe of Indians, Oklahoma; Eastern Shawnee Tribe of Oklahoma; Fond du Lac Band of the Minnesota Chippewa Tribe, Minnesota; Forest County Potawatomi Community, Wisconsin; Grand Portage Band of the Minnesota Chippewa Tribe, Minnesota; Grand Traverse Band of Ottawa and Chippewa Indians, Michigan; Hannahville Indian Community, Michigan; Keweenaw Bay Indian Community, Michigan; Kickapoo Traditional Tribe of Texas; Kickapoo Tribe of Indians of the Kickapoo Reservation in Kansas; Kickapoo Tribe of Oklahoma; Lac Courte Oreilles Band of Lake Superior Chippewa Indians of Wisconsin; Lac du Flambeau Band of Lake Superior Chippewa Indians of the Lac du Flambeau Reservation of Wisconsin; Lac Vieux Desert Band of Lake Superior Chippewa Indians, Michigan; Leech Lake Band of the Minnesota Chippewa Tribe, Minnesota; Little River Band of Ottawa Indians, Michigan; Little Traverse Bay Band of Odawa Indians, Michigan; Match-e-be-nash-she-wish Band of Pottawatomi Indians of Michigan; Menominee Indian Tribe of Wisconsin; Miami Tribe of Oklahoma; Mille Lacs Band of the Minnesota Chippewa Tribe, Minnesota; Nottawaseppi Huron Band of the Potawatomi, Michigan (previously listed as the Huron Potawatomi, Inc.); Ottawa Tribe of Oklahoma; Peoria Tribe of Indians of Oklahoma; Pokagon Band of Potawatomi Indians, Michigan and Indiana; Prairie Band Potawatomi Nation (previously listed as the Prairie Band of Potawatomi Nation, Kansas); Red Cliff Band of Lake Superior Chippewa Indians of Wisconsin; Red Lake Band of Chippewa Indians, Minnesota; Sac and Fox Nation of Missouri in Kansas and Nebraska; Sac & Fox Nation, Oklahoma; Sac & Fox Tribe of the Mississippi in Iowa; Saginaw Chippewa Indian Tribe of Michigan; Sault Ste. Marie Tribe of Chippewa Indians, Michigan; Seneca Nation of Indians (previously listed as the Seneca Nation of New York); Seneca-Cayuga Tribe of Oklahoma; Shawnee Tribe; Sokaogon Chippewa Community, Wisconsin; St. Croix Chippewa Indians of Wisconsin; Tonawanda Band of Seneca (previously listed as the Tonawanda Band of Seneca Indians of New York); Turtle Mountain Band of Chippewa Indians of North Dakota; White Earth Band of Minnesota Chippewa Tribe, Minnesota; Wyandotte Nation (hereinafter referred to as \\xe2\\x80\\x9cThe Tribes\\xe2\\x80\\x9d).\\n        History and Description of the Remains\\n        In an unknown year, human remains representing, at minimum, one adult male individual were removed from a mound in Michigan by an unknown individual. These remains were in the possession of the American Institute of Phrenology and the American Museum of Natural History does not have any information regarding how theses remains were acquired. The American Museum of Natural History acquired these remains as a gift in 1929 as part of the Phrenology Collection from Jesse Y. Loomis, in the name of Ernest Yates Loomis. No known individual was identified.\\n        Determinations Made by the American Museum of Natural History\\n        Officials of the American Museum of Natural History have determined that:\\n        \\xe2\\x80\\xa2 Pursuant to 25 U.S.C. 3001(9), the human remains described in this notice are Native American based on archaeological context and the presence of cranial deformation.\\n        \\xe2\\x80\\xa2 Pursuant to 25 U.S.C. 3001(9), the human remains described in this notice represent the physical remains of one individual of Native American ancestry.\\n        \\xe2\\x80\\xa2 Pursuant to 25 U.S.C. 3001(2), a relationship of shared group identity cannot be reasonably traced between the Native American human remains and any present-day Indian tribe.\\n        \\xe2\\x80\\xa2 According to final judgments of the Indian Claims Commission, the land from which the Native American human remains were removed is the unknown aboriginal land of The Tribes.\\n        \\xe2\\x80\\xa2 Treaties, Acts of Congress, or Executive Orders indicate that the land from which the Native American human remains were removed is the aboriginal land of The Tribes.\\n        \\xe2\\x80\\xa2 Pursuant to 43 CFR 10.11(c)(1), the disposition of the human remains may be to The Tribes.\\n        Additional Requestors and Disposition\\n\\n        Representatives of any Indian tribe or Native Hawaiian organization not identified in this notice that wish to request transfer of control of these human remains should submit a written request with information in support of the request to Nell Murphy, Director of Cultural Resources, American Museum of Natural History, Central Park West at 79th Street, NY, NY 10024, telephone 212-769-5837, email nmurphy@amnh.org, by March 6, 2015. After that date, if no additional requestors have come forward, transfer of control of the human remains to The Tribes may proceed.\\n        The American Museum of Natural History is responsible for notifying The Tribes that this notice has been published.\\n        \\n          Dated: December 19, 2014.\\n          Melanie O\\'Brien,\\n          Acting Manager, National NAGPRA Program.\\n        \\n      \\n      [FR Doc. 2015-02187 Filed 2-3-15; 8:45 am]\\n      BILLING CODE 4310-70-P\\n    ", "agency1": "DEPARTMENT OF THE INTERIOR", "sub_agency1": "National Park Service", "dep_doc": "[NPS-WASO-NAGPRA-17372; PPWOCRADN0-PCU00RP14.R50000]", "subject": "Notice of Inventory Completion: The American Museum of Natural History, New York, NY", "agency2": "National Park Service, Interior.", "action": "Notice.", "summary": "The American Museum of Natural History has completed an inventory of human remains in consultation with the appropriate Indian tribes or Native Hawaiian organizations, and has determined that there is no cultural affiliation between the human remains and any present-day Indian tribes or Native Hawaiian organizations. Representatives of any Indian tribe or Native Hawaiian organization not identified in this notice that wish to request transfer of control of these human remains should submit a written request to the American Museum of Natural History. If no additional requestors come forward, transfer of control of the human remains to the Indian tribes or Native Hawaiian organizations stated in this notice may proceed.", "dates": "Representatives of any Indian tribe or Native Hawaiian organization not identified in this notice that wish to request transfer of control of these human remains should submit a written request with information in support of the request to the American Museum of Natural History at the address in this notice by March 6, 2015.", "addresses": "Nell Murphy, Director of Cultural Resources, American Museum of Natural History, Central Park West at 79th Street, New York, NY 10024, telephone (212) 769-5837, email nmurphy@amnh.org.\\n          ", "signature_dated": "Dated: December 19, 2014.", "signature_name": "Melanie O\\'Brien,", "signature_title": "Acting Manager, National NAGPRA Program.", "fr_doc": "[FR Doc. 2015-02187 Filed 2-3-15; 8:45 am]", "billing_code": "BILLING CODE 4310-70-P", "supp_info": "SUPPLEMENTARY INFORMATION: \n Notice is here given in accordance with the Native American Graves Protection and Repatriation Act (NAGPRA), 25 U.S.C. 3003, of the completion of an inventory of human remains under the control of the American Museum of Natural History, New York, NY. The human remains were removed from an unidentified mound in an unknown county in MI. \n This notice is published as part of the National Park Service\\'s administrative responsibilities under NAGPRA, 25 U.S.C. 3003(d)(3) and 43 CFR 10.11(d). The determinations in this notice are the sole responsibility of the museum, institution, or Federal agency that has control of the Native American human remains. The National Park Service is not responsible for the determinations in this notice. \n Consultation \n A detailed assessment of the human remains was made by the American Museum of Natural History professional staff in consultation with representatives of the Absentee-Shawnee Tribe of Indians of Oklahoma; Bad River Band of the Lake Superior Tribe of Chippewa Indians of the Bad River Reservation, Wisconsin; Bay Mills Indian Community, Michigan; Bois Forte Band (Nett Lake) of the Minnesota Chippewa Tribe, Minnesota; Chippewa-Cree Indians of the Rocky Boy\\'s Reservation, Montana; Citizen Potawatomi Nation, Oklahoma; Delaware Nation, Oklahoma; Delaware Tribe of Indians, Oklahoma; Eastern Shawnee Tribe of Oklahoma; Fond du Lac Band of the Minnesota Chippewa Tribe, Minnesota; Forest County Potawatomi Community, Wisconsin; Grand Portage Band of the Minnesota Chippewa Tribe, Minnesota; Grand Traverse Band of Ottawa and Chippewa Indians, Michigan; Hannahville Indian Community, Michigan; Keweenaw Bay Indian Community, Michigan; Kickapoo Traditional Tribe of Texas; Kickapoo Tribe of Indians of the Kickapoo Reservation in Kansas; Kickapoo Tribe of Oklahoma; Lac Courte Oreilles Band of Lake Superior Chippewa Indians of Wisconsin; Lac du Flambeau Band of Lake Superior Chippewa Indians of the Lac du Flambeau Reservation of Wisconsin; Lac Vieux Desert Band of Lake Superior Chippewa Indians, Michigan; Leech Lake Band of the Minnesota Chippewa Tribe, Minnesota; Little River Band of Ottawa Indians, Michigan; Little Traverse Bay Band of Odawa Indians, Michigan; Match-e-be-nash-she-wish Band of Pottawatomi Indians of Michigan; Menominee Indian Tribe of Wisconsin; Miami Tribe of Oklahoma; Mille Lacs Band of the Minnesota Chippewa Tribe, Minnesota; Nottawaseppi Huron Band of the Potawatomi, Michigan (previously listed as the Huron Potawatomi, Inc.); Ottawa Tribe of Oklahoma; Peoria Tribe of Indians of Oklahoma; Pokagon Band of Potawatomi Indians, Michigan and Indiana; Prairie Band Potawatomi Nation (previously listed as the Prairie Band of Potawatomi Nation, Kansas); Red Cliff Band of Lake Superior Chippewa Indians of Wisconsin; Red Lake Band of Chippewa Indians, Minnesota; Sac and Fox Nation of Missouri in Kansas and Nebraska; Sac & Fox Nation, Oklahoma; Sac & Fox Tribe of the Mississippi in Iowa; Saginaw Chippewa Indian Tribe of Michigan; Sault Ste. Marie Tribe of Chippewa Indians, Michigan; Seneca Nation of Indians (previously listed as the Seneca Nation of New York); Seneca-Cayuga Tribe of Oklahoma; Shawnee Tribe; Sokaogon Chippewa Community, Wisconsin; St. Croix Chippewa Indians of Wisconsin; Tonawanda Band of Seneca (previously listed as the Tonawanda Band of Seneca Indians of New York); Turtle Mountain Band of Chippewa Indians of North Dakota; White Earth Band of Minnesota Chippewa Tribe, Minnesota; Wyandotte Nation (hereinafter referred to as \\xe2\\x80\\x9cThe Tribes\\xe2\\x80\\x9d). \n History and Description of the Remains \n In an unknown year, human remains representing, at minimum, one adult male individual were removed from a mound in Michigan by an unknown individual. These remains were in the possession of the American Institute of Phrenology and the American Museum of Natural History does not have any information regarding how theses remains were acquired. The American Museum of Natural History acquired these remains as a gift in 1929 as part of the Phrenology Collection from Jesse Y. Loomis, in the name of Ernest Yates Loomis. No known individual was identified. \n Determinations Made by the American Museum of Natural History \n Officials of the American Museum of Natural History have determined that: \n \\xe2\\x80\\xa2 Pursuant to 25 U.S.C. 3001(9), the human remains described in this notice are Native American based on archaeological context and the presence of cranial deformation. \n \\xe2\\x80\\xa2 Pursuant to 25 U.S.C. 3001(9), the human remains described in this notice represent the physical remains of one individual of Native American ancestry. \n \\xe2\\x80\\xa2 Pursuant to 25 U.S.C. 3001(2), a relationship of shared group identity cannot be reasonably traced between the Native American human remains and any present-day Indian tribe. \n \\xe2\\x80\\xa2 According to final judgments of the Indian Claims Commission, the land from which the Native American human remains were removed is the unknown aboriginal land of The Tribes. \n \\xe2\\x80\\xa2 Treaties, Acts of Congress, or Executive Orders indicate that the land from which the Native American human remains were removed is the aboriginal land of The Tribes. \n \\xe2\\x80\\xa2 Pursuant to 43 CFR 10.11(c)(1), the disposition of the human remains may be to The Tribes. \n Additional Requestors and Disposition \n Representatives of any Indian tribe or Native Hawaiian organization not identified in this notice that wish to request transfer of control of these human remains should submit a written request with information in support of the request to Nell Murphy, Director of Cultural Resources, American Museum of Natural History, Central Park West at 79th Street, NY, NY 10024, telephone 212-769-5837, email nmurphy@amnh.org, by March 6, 2015. After that date, if no additional requestors have come forward, transfer of control of the human remains to The Tribes may proceed. \n The American Museum of Natural History is responsible for notifying The Tribes that this notice has been published. \n ", "consultation": "A detailed assessment of the human remains was made by the American Museum of Natural History professional staff in consultation with representatives of the Absentee-Shawnee Tribe of Indians of Oklahoma; Bad River Band of the Lake Superior Tribe of Chippewa Indians of the Bad River Reservation, Wisconsin; Bay Mills Indian Community, Michigan; Bois Forte Band (Nett Lake) of the Minnesota Chippewa Tribe, Minnesota; Chippewa-Cree Indians of the Rocky Boy\\'s Reservation, Montana; Citizen Potawatomi Nation, Oklahoma; Delaware Nation, Oklahoma; Delaware Tribe of Indians, Oklahoma; Eastern Shawnee Tribe of Oklahoma; Fond du Lac Band of the Minnesota Chippewa Tribe, Minnesota; Forest County Potawatomi Community, Wisconsin; Grand Portage Band of the Minnesota Chippewa Tribe, Minnesota; Grand Traverse Band of Ottawa and Chippewa Indians, Michigan; Hannahville Indian Community, Michigan; Keweenaw Bay Indian Community, Michigan; Kickapoo Traditional Tribe of Texas; Kickapoo Tribe of Indians of the Kickapoo Reservation in Kansas; Kickapoo Tribe of Oklahoma; Lac Courte Oreilles Band of Lake Superior Chippewa Indians of Wisconsin; Lac du Flambeau Band of Lake Superior Chippewa Indians of the Lac du Flambeau Reservation of Wisconsin; Lac Vieux Desert Band of Lake Superior Chippewa Indians, Michigan; Leech Lake Band of the Minnesota Chippewa Tribe, Minnesota; Little River Band of Ottawa Indians, Michigan; Little Traverse Bay Band of Odawa Indians, Michigan; Match-e-be-nash-she-wish Band of Pottawatomi Indians of Michigan; Menominee Indian Tribe of Wisconsin; Miami Tribe of Oklahoma; Mille Lacs Band of the Minnesota Chippewa Tribe, Minnesota; Nottawaseppi Huron Band of the Potawatomi, Michigan (previously listed as the Huron Potawatomi, Inc.); Ottawa Tribe of Oklahoma; Peoria Tribe of Indians of Oklahoma; Pokagon Band of Potawatomi Indians, Michigan and Indiana; Prairie Band Potawatomi Nation (previously listed as the Prairie Band of Potawatomi Nation, Kansas); Red Cliff Band of Lake Superior Chippewa Indians of Wisconsin; Red Lake Band of Chippewa Indians, Minnesota; Sac and Fox Nation of Missouri in Kansas and Nebraska; Sac & Fox Nation, Oklahoma; Sac & Fox Tribe of the Mississippi in Iowa; Saginaw Chippewa Indian Tribe of Michigan; Sault Ste. Marie Tribe of Chippewa Indians, Michigan; Seneca Nation of Indians (previously listed as the Seneca Nation of New York); Seneca-Cayuga Tribe of Oklahoma; Shawnee Tribe; Sokaogon Chippewa Community, Wisconsin; St. Croix Chippewa Indians of Wisconsin; Tonawanda Band of Seneca (previously listed as the Tonawanda Band of Seneca Indians of New York); Turtle Mountain Band of Chippewa Indians of North Dakota; White Earth Band of Minnesota Chippewa Tribe, Minnesota; Wyandotte Nation (hereinafter referred to as \\xe2\\x80\\x9cThe Tribes\\xe2\\x80\\x9d). \n ", "h_d_r": "In an unknown year, human remains representing, at minimum, one adult male individual were removed from a mound in Michigan by an unknown individual. These remains were in the possession of the American Institute of Phrenology and the American Museum of Natural History does not have any information regarding how theses remains were acquired. The American Museum of Natural History acquired these remains as a gift in 1929 as part of the Phrenology Collection from Jesse Y. Loomis, in the name of Ernest Yates Loomis. No known individual was identified. \n ", "h_d_ci": "Null", "determinations": "Determinations Made by the American Museum of Natural History \n Officials of the American Museum of Natural History have determined that: \n \\xe2\\x80\\xa2 Pursuant to 25 U.S.C. 3001(9), the human remains described in this notice are Native American based on archaeological context and the presence of cranial deformation. \n \\xe2\\x80\\xa2 Pursuant to 25 U.S.C. 3001(9), the human remains described in this notice represent the physical remains of one individual of Native American ancestry. \n \\xe2\\x80\\xa2 Pursuant to 25 U.S.C. 3001(2), a relationship of shared group identity cannot be reasonably traced between the Native American human remains and any present-day Indian tribe. \n \\xe2\\x80\\xa2 According to final judgments of the Indian Claims Commission, the land from which the Native American human remains were removed is the unknown aboriginal land of The Tribes. \n \\xe2\\x80\\xa2 Treaties, Acts of Congress, or Executive Orders indicate that the land from which the Native American human remains were removed is the aboriginal land of The Tribes. \n \\xe2\\x80\\xa2 Pursuant to 43 CFR 10.11(c)(1), the disposition of the human remains may be to The Tribes. \n ", "a_r_d": "Representatives of any Indian tribe or Native Hawaiian organization not identified in this notice that wish to request transfer of control of these human remains should submit a written request with information in support of the request to Nell Murphy, Director of Cultural Resources, American Museum of Natural History, Central Park West at 79th Street, NY, NY 10024, telephone 212-769-5837, email nmurphy@amnh.org, by March 6, 2015. After that date, if no additional requestors have come forward, transfer of control of the human remains to The Tribes may proceed. \n The American Museum of Natural History is responsible for notifying The Tribes that this notice has been published. \n "}