{"index": "I_720", "messy_full": "\\n      \\n        DEPARTMENT OF THE INTERIOR\\n        National Park Service\\n        [NPS-WASO-NAGPRA-17464; PPWOCRADN0-PCU00RP14.R50000]\\n        Notice of Inventory Completion; U.S. Department of the Interior, National Park Service, Horseshoe Bend National Military Park, Daviston, AL\\n        \\n          AGENCY:\\n          National Park Service, Interior.\\n        \\n        \\n          ACTION:\\n          Notice.\\n        \\n        \\n          SUMMARY:\\n          The U.S. Department of the Interior, National Park Service, Horseshoe Bend National Military Park has completed an inventory of an associated funerary object, in consultation with the appropriate Indian tribes or Native Hawaiian organizations, and has determined that there is a cultural affiliation between the associated funerary object and present-day Indian tribes or Native Hawaiian organizations. Lineal descendants or representatives of any Indian tribe or Native Hawaiian organization not identified in this notice that wish to request transfer of control of this associated funerary object should submit a written request to Horseshoe Bend National Military Park. If no additional requestors come forward, transfer of control of the associated funerary object to the lineal descendants, Indian tribes, or Native Hawaiian organizations stated in this notice may proceed.\\n        \\n        \\n          DATES:\\n          Lineal descendants or representatives of any Indian tribe or Native Hawaiian organization not identified in this notice that wish to request transfer of control of this associated funerary object should submit a written request with information in support of the request to Horseshoe Bend National Military Park at the address in this notice by March 6, 2015.\\n        \\n        \\n          ADDRESSES:\\n\\n          Doyle Sapp, Superintendent, Horseshoe Bend National Military Park, 11288 Horseshoe Bend Road, Daviston, AL 36256, telephone (256) 234-7111, x226, email doyle_sapp@nps.gov.\\n        \\n      \\n      \\n        SUPPLEMENTARY INFORMATION:\\n        Notice is here given in accordance with the Native American Graves Protection and Repatriation Act (NAGPRA), 25 U.S.C. 3003, of the completion of an inventory of an associated funerary object under the control of the U.S. Department of the Interior, National Park Service, Horseshoe Bend National Military Park, Daviston, AL. The associated funerary object was removed from the Taskigi site, Elmore County, AL.\\n        This notice is published as part of the National Park Service\\'s administrative responsibilities under NAGPRA, 25 U.S.C. 3003(d)(3). The determinations in this notice are the sole responsibility of Horseshoe Bend National Military Park.\\n        Consultation\\n        A detailed assessment of the associated funerary object was made by Horseshoe Bend National Military Park professional staff in consultation with representatives of the Alabama-Coushatta Tribe of Texas (previously listed as the Alabama-Coushatta Tribes of Texas); Alabama-Quassarte Tribal Town; Coushatta Tribe of Louisiana; Kialegee Tribal Town; Poarch Band of Creeks (previously listed as the Poarch Band of Creek Indians of Alabama); The Muscogee (Creek) Nation; and Thlopthlocco Tribal Town (hereafter referred to as \\xe2\\x80\\x9cThe Tribes\\xe2\\x80\\x9d).\\n        History and Description of the Remains\\n        At an unknown date, a ceramic vessel was removed from the Taskigi site in Elmore County, AL by Dr. Peter A. Brannon. In 1963, Dr. Brannon donated the vessel to Horseshoe Bend National Military Park. Dr. Brannon\\'s documentation indicates the vessel is a funerary urn, and it is morphologically similar to other funerary vessels from the Taskigi site. There are no human remains associated with the vessel, but the vessel is believed to have been made exclusively for burial purposes or to contain human remains. The one associated funerary object is a funerary urn.\\n        The occupation of the Taskigi site has been dated from ca. A.D. 1600-1650. Documentary evidence links the site to \\xe2\\x80\\x9cTuskegee,\\xe2\\x80\\x9d the historic Creek Nation tribal town. Tuskegee residents were removed to Indian Territory with other members of the Creek Nation in the 19th century. Descendants of this group now are members of several Indian tribes including Kialegee Tribal Town, Poarch Band of Creeks (previously listed as the Poarch Band of Creek Indians of Alabama), The Muscogee (Creek) Nation, and Thlopthlocco Tribal Town. The area was also historically occupied by Alabama and Coushatta peoples, who were later members of the Creek Confederacy and shared many cultural traditions with the Creek. Descendants of these groups now are members of the Alabama-Coushatta Tribe of Texas (previously listed as the Alabama-Coushatta Tribes of Texas), Alabama-Quassarte Tribal Town, and Coushatta Tribe of Louisiana.\\n        Determinations Made by Horseshoe Bend National Military Park\\n        Officials of Horseshoe Bend National Military Park have determined that:\\n        \\xe2\\x80\\xa2 Pursuant to 25 U.S.C. 3001(3)(A), the one object described in this notice is reasonably believed to have been placed with or near individual human remains at the time of death or later as part of the death rite or ceremony and is reasonably believed to have been made exclusively for burial purposes or to contain human remains.\\n        \\xe2\\x80\\xa2 Pursuant to 25 U.S.C. 3001(2), there is a relationship of shared group identity that can be reasonably traced between the associated funerary object and The Tribes.\\n        Additional Requestors and Disposition\\n\\n        Lineal descendants or representatives of any Indian tribe or Native Hawaiian organization not identified in this notice that wish to request transfer of control of this associated funerary object should submit a written request with information in support of the request to Doyle Sapp, Superintendent, Horseshoe Bend National Military Park, 11288 Horseshoe Bend Road, Daviston, AL 36256, telephone (256) 234-7111 x226, email doyle_sapp@nps.gov, by March 6, 2015. After that date, if no additional requestors have come forward, transfer of control of the associated funerary object to The Tribes may proceed.\\n\\n        Horseshoe Bend National Military Park is responsible for notifying The Tribes that this notice has been published.\\n        \\n          Dated: January 9, 2015.\\n          Melanie O\\'Brien,\\n          Acting Manager, National NAGPRA Program. \\n        \\n      \\n      [FR Doc. 2015-02190 Filed 2-3-15; 8:45 am]\\n      BILLING CODE 4312-50-P\\n    ", "agency1": "DEPARTMENT OF THE INTERIOR", "sub_agency1": "National Park Service", "dep_doc": "[NPS-WASO-NAGPRA-17464; PPWOCRADN0-PCU00RP14.R50000]", "subject": "Notice of Inventory Completion; U.S. Department of the Interior, National Park Service, Horseshoe Bend National Military Park, Daviston, AL", "agency2": "National Park Service, Interior.", "action": "Notice.", "summary": "The U.S. Department of the Interior, National Park Service, Horseshoe Bend National Military Park has completed an inventory of an associated funerary object, in consultation with the appropriate Indian tribes or Native Hawaiian organizations, and has determined that there is a cultural affiliation between the associated funerary object and present-day Indian tribes or Native Hawaiian organizations. Lineal descendants or representatives of any Indian tribe or Native Hawaiian organization not identified in this notice that wish to request transfer of control of this associated funerary object should submit a written request to Horseshoe Bend National Military Park. If no additional requestors come forward, transfer of control of the associated funerary object to the lineal descendants, Indian tribes, or Native Hawaiian organizations stated in this notice may proceed.", "dates": "Lineal descendants or representatives of any Indian tribe or Native Hawaiian organization not identified in this notice that wish to request transfer of control of this associated funerary object should submit a written request with information in support of the request to Horseshoe Bend National Military Park at the address in this notice by March 6, 2015.", "addresses": "Doyle Sapp, Superintendent, Horseshoe Bend National Military Park, 11288 Horseshoe Bend Road, Daviston, AL 36256, telephone (256) 234-7111, x226, email doyle_sapp@nps.gov.", "signature_dated": "Dated: January 9, 2015.", "signature_name": "Melanie O\\'Brien,", "signature_title": "Acting Manager, National NAGPRA Program. ", "fr_doc": "[FR Doc. 2015-02190 Filed 2-3-15; 8:45 am]", "billing_code": "BILLING CODE 4312-50-P", "supp_info": "SUPPLEMENTARY INFORMATION: \n Notice is here given in accordance with the Native American Graves Protection and Repatriation Act (NAGPRA), 25 U.S.C. 3003, of the completion of an inventory of an associated funerary object under the control of the U.S. Department of the Interior, National Park Service, Horseshoe Bend National Military Park, Daviston, AL. The associated funerary object was removed from the Taskigi site, Elmore County, AL. \n This notice is published as part of the National Park Service\\'s administrative responsibilities under NAGPRA, 25 U.S.C. 3003(d)(3). The determinations in this notice are the sole responsibility of Horseshoe Bend National Military Park. \n Consultation \n A detailed assessment of the associated funerary object was made by Horseshoe Bend National Military Park professional staff in consultation with representatives of the Alabama-Coushatta Tribe of Texas (previously listed as the Alabama-Coushatta Tribes of Texas); Alabama-Quassarte Tribal Town; Coushatta Tribe of Louisiana; Kialegee Tribal Town; Poarch Band of Creeks (previously listed as the Poarch Band of Creek Indians of Alabama); The Muscogee (Creek) Nation; and Thlopthlocco Tribal Town (hereafter referred to as \\xe2\\x80\\x9cThe Tribes\\xe2\\x80\\x9d). \n History and Description of the Remains \n At an unknown date, a ceramic vessel was removed from the Taskigi site in Elmore County, AL by Dr. Peter A. Brannon. In 1963, Dr. Brannon donated the vessel to Horseshoe Bend National Military Park. Dr. Brannon\\'s documentation indicates the vessel is a funerary urn, and it is morphologically similar to other funerary vessels from the Taskigi site. There are no human remains associated with the vessel, but the vessel is believed to have been made exclusively for burial purposes or to contain human remains. The one associated funerary object is a funerary urn. \n The occupation of the Taskigi site has been dated from ca. A.D. 1600-1650. Documentary evidence links the site to \\xe2\\x80\\x9cTuskegee,\\xe2\\x80\\x9d the historic Creek Nation tribal town. Tuskegee residents were removed to Indian Territory with other members of the Creek Nation in the 19th century. Descendants of this group now are members of several Indian tribes including Kialegee Tribal Town, Poarch Band of Creeks (previously listed as the Poarch Band of Creek Indians of Alabama), The Muscogee (Creek) Nation, and Thlopthlocco Tribal Town. The area was also historically occupied by Alabama and Coushatta peoples, who were later members of the Creek Confederacy and shared many cultural traditions with the Creek. Descendants of these groups now are members of the Alabama-Coushatta Tribe of Texas (previously listed as the Alabama-Coushatta Tribes of Texas), Alabama-Quassarte Tribal Town, and Coushatta Tribe of Louisiana. \n Determinations Made by Horseshoe Bend National Military Park \n Officials of Horseshoe Bend National Military Park have determined that: \n \\xe2\\x80\\xa2 Pursuant to 25 U.S.C. 3001(3)(A), the one object described in this notice is reasonably believed to have been placed with or near individual human remains at the time of death or later as part of the death rite or ceremony and is reasonably believed to have been made exclusively for burial purposes or to contain human remains. \n \\xe2\\x80\\xa2 Pursuant to 25 U.S.C. 3001(2), there is a relationship of shared group identity that can be reasonably traced between the associated funerary object and The Tribes. \n Additional Requestors and Disposition \n Lineal descendants or representatives of any Indian tribe or Native Hawaiian organization not identified in this notice that wish to request transfer of control of this associated funerary object should submit a written request with information in support of the request to Doyle Sapp, Superintendent, Horseshoe Bend National Military Park, 11288 Horseshoe Bend Road, Daviston, AL 36256, telephone (256) 234-7111 x226, email doyle_sapp@nps.gov, by March 6, 2015. After that date, if no additional requestors have come forward, transfer of control of the associated funerary object to The Tribes may proceed. \n Horseshoe Bend National Military Park is responsible for notifying The Tribes that this notice has been published. \n ", "consultation": "A detailed assessment of the associated funerary object was made by Horseshoe Bend National Military Park professional staff in consultation with representatives of the Alabama-Coushatta Tribe of Texas (previously listed as the Alabama-Coushatta Tribes of Texas); Alabama-Quassarte Tribal Town; Coushatta Tribe of Louisiana; Kialegee Tribal Town; Poarch Band of Creeks (previously listed as the Poarch Band of Creek Indians of Alabama); The Muscogee (Creek) Nation; and Thlopthlocco Tribal Town (hereafter referred to as \\xe2\\x80\\x9cThe Tribes\\xe2\\x80\\x9d). \n ", "h_d_r": "At an unknown date, a ceramic vessel was removed from the Taskigi site in Elmore County, AL by Dr. Peter A. Brannon. In 1963, Dr. Brannon donated the vessel to Horseshoe Bend National Military Park. Dr. Brannon\\'s documentation indicates the vessel is a funerary urn, and it is morphologically similar to other funerary vessels from the Taskigi site. There are no human remains associated with the vessel, but the vessel is believed to have been made exclusively for burial purposes or to contain human remains. The one associated funerary object is a funerary urn. \n The occupation of the Taskigi site has been dated from ca. A.D. 1600-1650. Documentary evidence links the site to \\xe2\\x80\\x9cTuskegee,\\xe2\\x80\\x9d the historic Creek Nation tribal town. Tuskegee residents were removed to Indian Territory with other members of the Creek Nation in the 19th century. Descendants of this group now are members of several Indian tribes including Kialegee Tribal Town, Poarch Band of Creeks (previously listed as the Poarch Band of Creek Indians of Alabama), The Muscogee (Creek) Nation, and Thlopthlocco Tribal Town. The area was also historically occupied by Alabama and Coushatta peoples, who were later members of the Creek Confederacy and shared many cultural traditions with the Creek. Descendants of these groups now are members of the Alabama-Coushatta Tribe of Texas (previously listed as the Alabama-Coushatta Tribes of Texas), Alabama-Quassarte Tribal Town, and Coushatta Tribe of Louisiana. \n ", "h_d_ci": "Null", "determinations": "Determinations Made by Horseshoe Bend National Military Park \n Officials of Horseshoe Bend National Military Park have determined that: \n \\xe2\\x80\\xa2 Pursuant to 25 U.S.C. 3001(3)(A), the one object described in this notice is reasonably believed to have been placed with or near individual human remains at the time of death or later as part of the death rite or ceremony and is reasonably believed to have been made exclusively for burial purposes or to contain human remains. \n \\xe2\\x80\\xa2 Pursuant to 25 U.S.C. 3001(2), there is a relationship of shared group identity that can be reasonably traced between the associated funerary object and The Tribes. \n ", "a_r_d": "Lineal descendants or representatives of any Indian tribe or Native Hawaiian organization not identified in this notice that wish to request transfer of control of this associated funerary object should submit a written request with information in support of the request to Doyle Sapp, Superintendent, Horseshoe Bend National Military Park, 11288 Horseshoe Bend Road, Daviston, AL 36256, telephone (256) 234-7111 x226, email doyle_sapp@nps.gov, by March 6, 2015. After that date, if no additional requestors have come forward, transfer of control of the associated funerary object to The Tribes may proceed. \n Horseshoe Bend National Military Park is responsible for notifying The Tribes that this notice has been published. \n "}