{"index": "I_724", "messy_full": "\\n      \\n        DEPARTMENT OF THE INTERIOR\\n        National Park Service\\n        [NPS-WASO-NAGPRA-17105; PPWOCRADN0-PCU00RP14.R50000]\\n        Notice of Inventory Completion: History Colorado, formerly Colorado Historical Society, Denver, CO\\n        \\n          AGENCY:\\n          National Park Service, Interior.\\n        \\n        \\n          ACTION:\\n          Notice.\\n        \\n        \\n          SUMMARY:\\n\\n          History Colorado has completed an inventory of human remains, in consultation with the appropriate Indian tribes or Native Hawaiian organizations, and has determined that there is no cultural affiliation between the human remains and any present-day Indian tribes or Native Hawaiian organizations. Representatives of any Indian tribe or Native Hawaiian organization not identified in this notice that wish to request transfer of control of these human remains should submit a written request to History Colorado. If no additional requestors come forward, transfer of control of the human remains to the Indian tribes or Native Hawaiian organizations stated in this notice may proceed.\\n        \\n        \\n          DATES:\\n          Representatives of any Indian tribe or Native Hawaiian organization not identified in this notice that wish to request transfer of control of these human remains should submit a written request with information in support of the request to History Colorado at the address in this notice by January 21, 2015.\\n        \\n        \\n          ADDRESSES:\\n\\n          Sheila Goff, History Colorado, 1200 Broadway, Denver, CO 80203, telephone (303) 866-4531, email sheila.goff@state.co.us.\\n        \\n      \\n      \\n        SUPPLEMENTARY INFORMATION:\\n        Notice is here given in accordance with the Native American Graves Protection and Repatriation Act (NAGPRA), 25 U.S.C. 3003, of the completion of an inventory of human remains under the control of History Colorado, Denver, CO. The human remains were removed from Mora County, NM.\\n        This notice is published as part of the National Park Service\\'s administrative responsibilities under NAGPRA, 25 U.S.C. 3003(d)(3) and 43 CFR 10.11(d). The determinations in this notice are the sole responsibility of the museum, institution, or Federal agency that has control of the Native American human remains. The National Park Service is not responsible for the determinations in this notice.\\n        Consultation\\n        A detailed assessment of the human remains was made between 2010 and 2014 by History Colorado professional staff in consultation with representatives of the Arapaho Tribe of the Wind River Reservation, Wyoming; Cheyenne and Arapaho Tribes of Oklahoma (formerly the Cheyenne-Arapaho Tribes of Oklahoma); Comanche Nation, Oklahoma; Crow Tribe of Montana; Fort Sill Apache Tribe of Oklahoma; Hopi Tribe of Arizona; Jicarilla Apache Nation, New Mexico; Mescalero Apache Tribe of the Mescalero Reservation, New Mexico; Navajo Nation, Arizona, New Mexico & Utah; Northern Cheyenne Tribe of the Northern Cheyenne Indian Reservation, Montana; Ohkay Owingeh, New Mexico (formerly the Pueblo of San Juan); Paiute Indian Tribe of Utah (Cedar Band of Paiutes, Kanosh Band of Paiutes, Koosharem Band of Paiutes, Indian Peaks Band of Paiutes, and Shivwits Band of Paiutes) (formerly the Paiute Indian Tribe of Utah (Cedar City Band of Paiutes, Kanosh Band of Paiutes, Koosharem Band of Paiutes, Indian Peaks Band of Paiutes, and Shivwits Band of Paiutes)); Pawnee Nation of Oklahoma; Pueblo of Acoma, New Mexico; Pueblo of Cochiti, New Mexico; Pueblo of Isleta, New Mexico; Pueblo of Jemez, New Mexico; Pueblo of Laguna, New Mexico; Pueblo of Nambe, New Mexico; Pueblo of Pojoaque, New Mexico; Pueblo of San Ildefonso, New Mexico; Pueblo of Santa Ana, New Mexico; Pueblo of Santa Clara, New Mexico; Pueblo of Tesuque, New Mexico; Rosebud Sioux Tribe of the Rosebud Indian Reservation, South Dakota; San Carlos Apache Tribe of the San Carlos Reservation, Arizona; Shoshone Tribe of the Wind River Reservation, Wyoming; Southern Ute Indian Tribe of the Southern Ute Reservation, Colorado; Tonto Apache Tribe of Arizona; Ute Indian Tribe of the Uintah & Ouray Reservation, Utah; Ute Mountain Tribe of the Ute Mountain Reservation, Colorado, New Mexico & Utah; White Mountain Apache Tribe of the Fort Apache Reservation, Arizona; Ysleta Del Sur Pueblo of Texas; and the Zuni Tribe of the Zuni Reservation, New Mexico. The Apache Tribe of Oklahoma; Kewa Pueblo, New Mexico (formerly the Pueblo of Santo Domingo); Kiowa Indian Tribe of Oklahoma; Oglala Sioux Tribe of the Pine Ridge Reservation, South Dakota; Pueblo of Picuris, New Mexico; Pueblo of Sandia, New Mexico; Pueblo of San Felipe, New Mexico; Pueblo of Taos, New Mexico; Pueblo of Zia, New Mexico; Shoshone-Bannock Tribes of the Fort Hall Reservation; Standing Rock Sioux Tribe of North & South Dakota; Three Affiliated Tribes of the Fort Berthold Reservation, North Dakota; and Wichita and Affiliated Tribes (Wichita, Keechi, Waco & Tawakonie) were invited to consult but did not participate.\\n        History and Description of the Remains\\n        In the mid-1800s, human remains representing, at minimum, one individual were removed from the vicinity of Fort Union in Mora County, NM. The remains are represented by a scalp lock. Museum records indicate that Josiah Perkins Clark obtained it while he was in U.S. Government service, building and locating forts in the mid-1800s. It was donated to History Colorado (formerly Colorado Historical Society) in 1960 by Clark\\'s daughter, who reported Clark worked in the area of Fort Union and the remains were of the son of a chief who was caught stealing horses there. No known individuals were identified. No associated funerary objects are present.\\n        Determinations Made by History Colorado\\n        Officials of History Colorado have determined that:\\n        \\xe2\\x80\\xa2 Pursuant to 25 U.S.C. 3001(9), the human remains described in this notice are Native American based on examination by physical anthropologist Dr. Catherine Gaither.\\n        \\xe2\\x80\\xa2 Pursuant to 25 U.S.C. 3001(9), the human remains described in this notice represent the physical remains of one individual of Native American ancestry.\\n        \\xe2\\x80\\xa2 Pursuant to 25 U.S.C. 3001(2), a relationship of shared group identity cannot be reasonably traced between the Native American human remains and any present-day Indian tribe.\\n        \\xe2\\x80\\xa2 According to final judgments of the Indian Claims Commission or the Court of Federal Claims, the land from which the Native American human remains were removed is the aboriginal land of the Jicarilla Apache Nation, New Mexico.\\n        \\xe2\\x80\\xa2 Treaties, Acts of Congress, or Executive Orders, indicate that the land from which the Native American human remains were removed is the aboriginal land of the Apache Tribe of Oklahoma; Fort Sill Tribe of Oklahoma; Mescalero Apache Tribe of the Mescalero Reservation, New Mexico; San Carlos Apache Tribe of the San Carlos Reservation, Arizona; Tonto Apache Tribe of Arizona; and White Mountain Apache Tribe of the Fort Apache Reservation, Arizona.\\n        \\xe2\\x80\\xa2 Pursuant to 43 CFR 10.11(c)(1), the disposition of the human remains may be to the Apache Tribe of Oklahoma; Fort Sill Apache Tribe of Oklahoma; Jicarilla Apache Nation, New Mexico; Mescalero Apache Tribe of the Mescalero Reservation, New Mexico; San Carlos Apache Tribe of the San Carlos Reservation, Arizona; Tonto Apache Tribe of Arizona; and White Mountain Apache Tribe of the Fort Apache Reservation, Arizona.\\n        Additional Requestors and Disposition\\n\\n        Representatives of any Indian tribe or Native Hawaiian organization not identified in this notice that wish to request transfer of control of these human remains should submit a written request with information in support of the request to Sheila Goff, History Colorado, 1200 Broadway, Denver, CO 80203, telephone (303) 866-4531, email sheila.goff@state.co.us, by January 21, 2015. After that date, if no additional requestors have come forward, transfer of control of the human remains to the Apache Tribe of Oklahoma; Fort Sill Apache Tribe of Oklahoma; Jicarilla Apache Nation, New Mexico; Mescalero Apache Tribe of the Mescalero Reservation, New Mexico; San Carlos Apache Tribe of the San Carlos Reservation, Arizona; Tonto Apache Tribe of Arizona; and White Mountain Apache Tribe of the Fort Apache Reservation, Arizona, may proceed.\\n        History Colorado is responsible for notifying the Apache Tribe of Oklahoma; Fort Sill Apache Tribe of Oklahoma; Jicarilla Apache Nation, New Mexico; Mescalero Apache Tribe of the Mescalero Reservation, New Mexico; San Carlos Apache Tribe of the San Carlos Reservation, Arizona; Tonto Apache Tribe of Arizona; and the White Mountain Apache Tribe of the Fort Apache Reservation, Arizona, that this notice has been published.\\n        \\n          Dated: November 3, 2014.\\n          Melanie O\\'Brien,\\n          Acting Manager, National NAGPRA Program. \\n        \\n      \\n      [FR Doc. 2014-29888 Filed 12-19-14; 8:45 am]\\n      BILLING CODE 4312-50-P\\n    ", "agency1": "DEPARTMENT OF THE INTERIOR", "sub_agency1": "National Park Service", "dep_doc": "[NPS-WASO-NAGPRA-17105; PPWOCRADN0-PCU00RP14.R50000]", "subject": "Notice of Inventory Completion: History Colorado, formerly Colorado Historical Society, Denver, CO", "agency2": "National Park Service, Interior.", "action": "Notice.", "summary": "History Colorado has completed an inventory of human remains, in consultation with the appropriate Indian tribes or Native Hawaiian organizations, and has determined that there is no cultural affiliation between the human remains and any present-day Indian tribes or Native Hawaiian organizations. Representatives of any Indian tribe or Native Hawaiian organization not identified in this notice that wish to request transfer of control of these human remains should submit a written request to History Colorado. If no additional requestors come forward, transfer of control of the human remains to the Indian tribes or Native Hawaiian organizations stated in this notice may proceed.", "dates": "Representatives of any Indian tribe or Native Hawaiian organization not identified in this notice that wish to request transfer of control of these human remains should submit a written request with information in support of the request to History Colorado at the address in this notice by January 21, 2015.", "addresses": "Sheila Goff, History Colorado, 1200 Broadway, Denver, CO 80203, telephone (303) 866-4531, email sheila.goff@state.co.us.", "signature_dated": "Dated: November 3, 2014.", "signature_name": "Melanie O\\'Brien,", "signature_title": "Acting Manager, National NAGPRA Program. ", "fr_doc": "[FR Doc. 2014-29888 Filed 12-19-14; 8:45 am]", "billing_code": "BILLING CODE 4312-50-P", "supp_info": "SUPPLEMENTARY INFORMATION: \n Notice is here given in accordance with the Native American Graves Protection and Repatriation Act (NAGPRA), 25 U.S.C. 3003, of the completion of an inventory of human remains under the control of History Colorado, Denver, CO. The human remains were removed from Mora County, NM. \n This notice is published as part of the National Park Service\\'s administrative responsibilities under NAGPRA, 25 U.S.C. 3003(d)(3) and 43 CFR 10.11(d). The determinations in this notice are the sole responsibility of the museum, institution, or Federal agency that has control of the Native American human remains. The National Park Service is not responsible for the determinations in this notice. \n Consultation \n A detailed assessment of the human remains was made between 2010 and 2014 by History Colorado professional staff in consultation with representatives of the Arapaho Tribe of the Wind River Reservation, Wyoming; Cheyenne and Arapaho Tribes of Oklahoma (formerly the Cheyenne-Arapaho Tribes of Oklahoma); Comanche Nation, Oklahoma; Crow Tribe of Montana; Fort Sill Apache Tribe of Oklahoma; Hopi Tribe of Arizona; Jicarilla Apache Nation, New Mexico; Mescalero Apache Tribe of the Mescalero Reservation, New Mexico; Navajo Nation, Arizona, New Mexico & Utah; Northern Cheyenne Tribe of the Northern Cheyenne Indian Reservation, Montana; Ohkay Owingeh, New Mexico (formerly the Pueblo of San Juan); Paiute Indian Tribe of Utah (Cedar Band of Paiutes, Kanosh Band of Paiutes, Koosharem Band of Paiutes, Indian Peaks Band of Paiutes, and Shivwits Band of Paiutes) (formerly the Paiute Indian Tribe of Utah (Cedar City Band of Paiutes, Kanosh Band of Paiutes, Koosharem Band of Paiutes, Indian Peaks Band of Paiutes, and Shivwits Band of Paiutes)); Pawnee Nation of Oklahoma; Pueblo of Acoma, New Mexico; Pueblo of Cochiti, New Mexico; Pueblo of Isleta, New Mexico; Pueblo of Jemez, New Mexico; Pueblo of Laguna, New Mexico; Pueblo of Nambe, New Mexico; Pueblo of Pojoaque, New Mexico; Pueblo of San Ildefonso, New Mexico; Pueblo of Santa Ana, New Mexico; Pueblo of Santa Clara, New Mexico; Pueblo of Tesuque, New Mexico; Rosebud Sioux Tribe of the Rosebud Indian Reservation, South Dakota; San Carlos Apache Tribe of the San Carlos Reservation, Arizona; Shoshone Tribe of the Wind River Reservation, Wyoming; Southern Ute Indian Tribe of the Southern Ute Reservation, Colorado; Tonto Apache Tribe of Arizona; Ute Indian Tribe of the Uintah & Ouray Reservation, Utah; Ute Mountain Tribe of the Ute Mountain Reservation, Colorado, New Mexico & Utah; White Mountain Apache Tribe of the Fort Apache Reservation, Arizona; Ysleta Del Sur Pueblo of Texas; and the Zuni Tribe of the Zuni Reservation, New Mexico. The Apache Tribe of Oklahoma; Kewa Pueblo, New Mexico (formerly the Pueblo of Santo Domingo); Kiowa Indian Tribe of Oklahoma; Oglala Sioux Tribe of the Pine Ridge Reservation, South Dakota; Pueblo of Picuris, New Mexico; Pueblo of Sandia, New Mexico; Pueblo of San Felipe, New Mexico; Pueblo of Taos, New Mexico; Pueblo of Zia, New Mexico; Shoshone-Bannock Tribes of the Fort Hall Reservation; Standing Rock Sioux Tribe of North & South Dakota; Three Affiliated Tribes of the Fort Berthold Reservation, North Dakota; and Wichita and Affiliated Tribes (Wichita, Keechi, Waco & Tawakonie) were invited to consult but did not participate. \n History and Description of the Remains \n In the mid-1800s, human remains representing, at minimum, one individual were removed from the vicinity of Fort Union in Mora County, NM. The remains are represented by a scalp lock. Museum records indicate that Josiah Perkins Clark obtained it while he was in U.S. Government service, building and locating forts in the mid-1800s. It was donated to History Colorado (formerly Colorado Historical Society) in 1960 by Clark\\'s daughter, who reported Clark worked in the area of Fort Union and the remains were of the son of a chief who was caught stealing horses there. No known individuals were identified. No associated funerary objects are present. \n Determinations Made by History Colorado \n Officials of History Colorado have determined that: \n \\xe2\\x80\\xa2 Pursuant to 25 U.S.C. 3001(9), the human remains described in this notice are Native American based on examination by physical anthropologist Dr. Catherine Gaither. \n \\xe2\\x80\\xa2 Pursuant to 25 U.S.C. 3001(9), the human remains described in this notice represent the physical remains of one individual of Native American ancestry. \n \\xe2\\x80\\xa2 Pursuant to 25 U.S.C. 3001(2), a relationship of shared group identity cannot be reasonably traced between the Native American human remains and any present-day Indian tribe. \n \\xe2\\x80\\xa2 According to final judgments of the Indian Claims Commission or the Court of Federal Claims, the land from which the Native American human remains were removed is the aboriginal land of the Jicarilla Apache Nation, New Mexico. \n \\xe2\\x80\\xa2 Treaties, Acts of Congress, or Executive Orders, indicate that the land from which the Native American human remains were removed is the aboriginal land of the Apache Tribe of Oklahoma; Fort Sill Tribe of Oklahoma; Mescalero Apache Tribe of the Mescalero Reservation, New Mexico; San Carlos Apache Tribe of the San Carlos Reservation, Arizona; Tonto Apache Tribe of Arizona; and White Mountain Apache Tribe of the Fort Apache Reservation, Arizona. \n \\xe2\\x80\\xa2 Pursuant to 43 CFR 10.11(c)(1), the disposition of the human remains may be to the Apache Tribe of Oklahoma; Fort Sill Apache Tribe of Oklahoma; Jicarilla Apache Nation, New Mexico; Mescalero Apache Tribe of the Mescalero Reservation, New Mexico; San Carlos Apache Tribe of the San Carlos Reservation, Arizona; Tonto Apache Tribe of Arizona; and White Mountain Apache Tribe of the Fort Apache Reservation, Arizona. \n Additional Requestors and Disposition \n Representatives of any Indian tribe or Native Hawaiian organization not identified in this notice that wish to request transfer of control of these human remains should submit a written request with information in support of the request to Sheila Goff, History Colorado, 1200 Broadway, Denver, CO 80203, telephone (303) 866-4531, email sheila.goff@state.co.us, by January 21, 2015. After that date, if no additional requestors have come forward, transfer of control of the human remains to the Apache Tribe of Oklahoma; Fort Sill Apache Tribe of Oklahoma; Jicarilla Apache Nation, New Mexico; Mescalero Apache Tribe of the Mescalero Reservation, New Mexico; San Carlos Apache Tribe of the San Carlos Reservation, Arizona; Tonto Apache Tribe of Arizona; and White Mountain Apache Tribe of the Fort Apache Reservation, Arizona, may proceed. \n History Colorado is responsible for notifying the Apache Tribe of Oklahoma; Fort Sill Apache Tribe of Oklahoma; Jicarilla Apache Nation, New Mexico; Mescalero Apache Tribe of the Mescalero Reservation, New Mexico; San Carlos Apache Tribe of the San Carlos Reservation, Arizona; Tonto Apache Tribe of Arizona; and the White Mountain Apache Tribe of the Fort Apache Reservation, Arizona, that this notice has been published. \n ", "consultation": "A detailed assessment of the human remains was made between 2010 and 2014 by History Colorado professional staff in consultation with representatives of the Arapaho Tribe of the Wind River Reservation, Wyoming; Cheyenne and Arapaho Tribes of Oklahoma (formerly the Cheyenne-Arapaho Tribes of Oklahoma); Comanche Nation, Oklahoma; Crow Tribe of Montana; Fort Sill Apache Tribe of Oklahoma; Hopi Tribe of Arizona; Jicarilla Apache Nation, New Mexico; Mescalero Apache Tribe of the Mescalero Reservation, New Mexico; Navajo Nation, Arizona, New Mexico & Utah; Northern Cheyenne Tribe of the Northern Cheyenne Indian Reservation, Montana; Ohkay Owingeh, New Mexico (formerly the Pueblo of San Juan); Paiute Indian Tribe of Utah (Cedar Band of Paiutes, Kanosh Band of Paiutes, Koosharem Band of Paiutes, Indian Peaks Band of Paiutes, and Shivwits Band of Paiutes) (formerly the Paiute Indian Tribe of Utah (Cedar City Band of Paiutes, Kanosh Band of Paiutes, Koosharem Band of Paiutes, Indian Peaks Band of Paiutes, and Shivwits Band of Paiutes)); Pawnee Nation of Oklahoma; Pueblo of Acoma, New Mexico; Pueblo of Cochiti, New Mexico; Pueblo of Isleta, New Mexico; Pueblo of Jemez, New Mexico; Pueblo of Laguna, New Mexico; Pueblo of Nambe, New Mexico; Pueblo of Pojoaque, New Mexico; Pueblo of San Ildefonso, New Mexico; Pueblo of Santa Ana, New Mexico; Pueblo of Santa Clara, New Mexico; Pueblo of Tesuque, New Mexico; Rosebud Sioux Tribe of the Rosebud Indian Reservation, South Dakota; San Carlos Apache Tribe of the San Carlos Reservation, Arizona; Shoshone Tribe of the Wind River Reservation, Wyoming; Southern Ute Indian Tribe of the Southern Ute Reservation, Colorado; Tonto Apache Tribe of Arizona; Ute Indian Tribe of the Uintah & Ouray Reservation, Utah; Ute Mountain Tribe of the Ute Mountain Reservation, Colorado, New Mexico & Utah; White Mountain Apache Tribe of the Fort Apache Reservation, Arizona; Ysleta Del Sur Pueblo of Texas; and the Zuni Tribe of the Zuni Reservation, New Mexico. The Apache Tribe of Oklahoma; Kewa Pueblo, New Mexico (formerly the Pueblo of Santo Domingo); Kiowa Indian Tribe of Oklahoma; Oglala Sioux Tribe of the Pine Ridge Reservation, South Dakota; Pueblo of Picuris, New Mexico; Pueblo of Sandia, New Mexico; Pueblo of San Felipe, New Mexico; Pueblo of Taos, New Mexico; Pueblo of Zia, New Mexico; Shoshone-Bannock Tribes of the Fort Hall Reservation; Standing Rock Sioux Tribe of North & South Dakota; Three Affiliated Tribes of the Fort Berthold Reservation, North Dakota; and Wichita and Affiliated Tribes (Wichita, Keechi, Waco & Tawakonie) were invited to consult but did not participate. \n ", "h_d_r": "In the mid-1800s, human remains representing, at minimum, one individual were removed from the vicinity of Fort Union in Mora County, NM. The remains are represented by a scalp lock. Museum records indicate that Josiah Perkins Clark obtained it while he was in U.S. Government service, building and locating forts in the mid-1800s. It was donated to History Colorado (formerly Colorado Historical Society) in 1960 by Clark\\'s daughter, who reported Clark worked in the area of Fort Union and the remains were of the son of a chief who was caught stealing horses there. No known individuals were identified. No associated funerary objects are present. \n ", "h_d_ci": "Null", "determinations": "Determinations Made by History Colorado \n Officials of History Colorado have determined that: \n \\xe2\\x80\\xa2 Pursuant to 25 U.S.C. 3001(9), the human remains described in this notice are Native American based on examination by physical anthropologist Dr. Catherine Gaither. \n \\xe2\\x80\\xa2 Pursuant to 25 U.S.C. 3001(9), the human remains described in this notice represent the physical remains of one individual of Native American ancestry. \n \\xe2\\x80\\xa2 Pursuant to 25 U.S.C. 3001(2), a relationship of shared group identity cannot be reasonably traced between the Native American human remains and any present-day Indian tribe. \n \\xe2\\x80\\xa2 According to final judgments of the Indian Claims Commission or the Court of Federal Claims, the land from which the Native American human remains were removed is the aboriginal land of the Jicarilla Apache Nation, New Mexico. \n \\xe2\\x80\\xa2 Treaties, Acts of Congress, or Executive Orders, indicate that the land from which the Native American human remains were removed is the aboriginal land of the Apache Tribe of Oklahoma; Fort Sill Tribe of Oklahoma; Mescalero Apache Tribe of the Mescalero Reservation, New Mexico; San Carlos Apache Tribe of the San Carlos Reservation, Arizona; Tonto Apache Tribe of Arizona; and White Mountain Apache Tribe of the Fort Apache Reservation, Arizona. \n \\xe2\\x80\\xa2 Pursuant to 43 CFR 10.11(c)(1), the disposition of the human remains may be to the Apache Tribe of Oklahoma; Fort Sill Apache Tribe of Oklahoma; Jicarilla Apache Nation, New Mexico; Mescalero Apache Tribe of the Mescalero Reservation, New Mexico; San Carlos Apache Tribe of the San Carlos Reservation, Arizona; Tonto Apache Tribe of Arizona; and White Mountain Apache Tribe of the Fort Apache Reservation, Arizona. \n ", "a_r_d": "Representatives of any Indian tribe or Native Hawaiian organization not identified in this notice that wish to request transfer of control of these human remains should submit a written request with information in support of the request to Sheila Goff, History Colorado, 1200 Broadway, Denver, CO 80203, telephone (303) 866-4531, email sheila.goff@state.co.us, by January 21, 2015. After that date, if no additional requestors have come forward, transfer of control of the human remains to the Apache Tribe of Oklahoma; Fort Sill Apache Tribe of Oklahoma; Jicarilla Apache Nation, New Mexico; Mescalero Apache Tribe of the Mescalero Reservation, New Mexico; San Carlos Apache Tribe of the San Carlos Reservation, Arizona; Tonto Apache Tribe of Arizona; and White Mountain Apache Tribe of the Fort Apache Reservation, Arizona, may proceed. \n History Colorado is responsible for notifying the Apache Tribe of Oklahoma; Fort Sill Apache Tribe of Oklahoma; Jicarilla Apache Nation, New Mexico; Mescalero Apache Tribe of the Mescalero Reservation, New Mexico; San Carlos Apache Tribe of the San Carlos Reservation, Arizona; Tonto Apache Tribe of Arizona; and the White Mountain Apache Tribe of the Fort Apache Reservation, Arizona, that this notice has been published. \n "}