{"index": "I_763", "messy_full": "\\n      \\n        DEPARTMENT OF THE INTERIOR\\n        National Park Service\\n        [NPS-WASO-NAGPRA-16312; PPWOCRADN0-PCU00RP14.R50000]\\n        Notice of Inventory Completion: State Historical Society of Wisconsin, Madison, WI\\n        \\n          AGENCY:\\n          National Park Service, Interior.\\n        \\n        \\n          ACTION:\\n          Notice.\\n        \\n        \\n          SUMMARY:\\n          The State Historical Society of Wisconsin has completed an inventory of human remains, in consultation with the appropriate Indian tribes or Native Hawaiian organizations, and has determined that there is no cultural affiliation between the human remains and any present-day Indian tribes or Native Hawaiian organizations. Representatives of any Indian tribe or Native Hawaiian organization not identified in this notice that wish to request transfer of control of these human remains should submit a written request to the State Historical Society of Wisconsin. If no additional requestors come forward, transfer of control of the human remains to the Indian tribes or Native Hawaiian organizations stated in this notice may proceed.\\n        \\n        \\n          DATES:\\n          Representatives of any Indian tribe or Native Hawaiian organization not identified in this notice that wish to request transfer of control of these human remains should submit a written request with information in support of the request to the State Historical Society of Wisconsin at the address in this notice by October 10, 2014.\\n        \\n        \\n          ADDRESSES:\\n\\n          Jennifer Kolb, Wisconsin Historical Museum, 30 North Carroll Street, Madison, WI 53703, telephone (608) 261-2461, email Jennifer.Kolb@wisconsinhistory.org.\\n          \\n        \\n      \\n      \\n        SUPPLEMENTARY INFORMATION:\\n        Notice is here given in accordance with the Native American Graves Protection and Repatriation Act (NAGPRA), 25 U.S.C. 3003, of the completion of an inventory of human remains under the control of the State Historical Society of Wisconsin, Madison, WI. The human remains were removed from the Cooper\\'s Shores site, Rock County, WI.\\n        This notice is published as part of the National Park Service\\'s administrative responsibilities under NAGPRA, 25 U.S.C. 3003(d)(3) and 43 CFR 10.11(d). The determinations in this notice are the sole responsibility of the museum, institution, or Federal agency that has control of the Native American human remains. The National Park Service is not responsible for the determinations in this notice.\\n        Consultation\\n        A detailed assessment of the human remains was made by the State Historical Society of Wisconsin professional staff in consultation with representatives of the Forest County Potawatomi Community, Wisconsin; Ho-Chunk Nation of Wisconsin; and the Menominee Indian Tribe of Wisconsin.\\n        History and Description of the Remains\\n        In 1930, human remains representing, at minimum, five individuals (F1996.2.1 and F1996.2.2) were removed from the Cooper\\'s Shores site (47-RO-0002) in Rock County, WI. The human remains were disturbed by the land owner during a construction project on the north shore of the Rock River at the point where it flows into Lake Koshkonong. The land owner removed the human remains and contacted Charles E. Brown of the Historical Society, who investigated the site and took possession of the human remains. The human remains were determined to be those of an adult female, two adult males, and two children of indeterminate sex. No known individuals were identified. No associated funerary objects are present.\\n        Determinations Made by the State Historical Society of Wisconsin\\n\\n        Officials of the State Historical Society of Wisconsin have determined that:\\n        \\n        \\xe2\\x80\\xa2 Pursuant to 25 U.S.C. 3001(9), the human remains described in this notice are Native American based on the location and context of the burials, objects found with the burials (not in the collection), and State Historical Society records.\\n        \\xe2\\x80\\xa2 Pursuant to 25 U.S.C. 3001(9), the human remains described in this notice represent the physical remains of five individuals of Native American ancestry.\\n        \\xe2\\x80\\xa2 Pursuant to 25 U.S.C. 3001(2), a relationship of shared group identity cannot be reasonably traced between the Native American human remains and any present-day Indian tribe.\\n        \\xe2\\x80\\xa2 According to final judgments of the Indian Claims Commission or the Court of Federal Claims, the land from which the Native American human remains were removed is the aboriginal land of the Citizen Potawatomi Nation, Oklahoma; Forest County Potawatomi Community, Wisconsin; Hannahville Indian Community, Michigan; Match-e-be-nash-she-wish Band of Pottawatomi Indians of Michigan; Nottawaseppi Huron Band of the Potawatomi, Michigan (previously listed as the Huron Potawatomi, Inc.); Pokagon Band of Potawatomi Indians, Michigan and Indiana; Prairie Band Potawatomi Nation (previously listed as the Prairie Band of Potawatomi Nation, Kansas); and the Quechan Tribe of Fort Yuma Indian Reservation, California & Arizona.\\n        \\xe2\\x80\\xa2 Treaties, Acts of Congress, or Executive Orders, indicate that the land from which the Native American human remains were removed is the aboriginal land of the Bad River Band of the Lake Superior Tribe of Chippewa Indians of the Bad River Reservation, Wisconsin; Bay Mills Indian Community, Michigan; Bois Forte Band (Nett Lake) of the Minnesota Chippewa Tribe, Minnesota; Chippewa-Cree Indians of the Rocky Boy\\'s Reservation, Montana; Citizen Potawatomi Nation, Oklahoma; Fond du Lac Band of the Minnesota Chippewa Tribe, Minnesota; Forest County Potawatomi Community, Wisconsin; Grand Portage Band of the Minnesota Chippewa Tribe, Minnesota; Grand Traverse Band of Ottawa and Chippewa Indians, Michigan; Hannahville Indian Community, Michigan; Keweenaw Bay Indian Community, Michigan; Lac Courte Oreilles Band of Lake Superior Chippewa Indians of Wisconsin; Lac du Flambeau Band of Lake Superior Chippewa Indians of the Lac du Flambeau Reservation of Wisconsin; Lac Vieux Desert Band of Lake Superior Chippewa Indians of Michigan; Leech Lake Band of the Minnesota Chippewa Tribe, Minnesota; Match-e-be-nash-she-wish Band of Pottawatomi Indians of Michigan; Mille Lacs Band of the Minnesota Chippewa Tribe, Minnesota; Minnesota Chippewa Tribe, Minnesota; Nottawaseppi Huron Band of the Potawatomi, Michigan (previously listed as the Huron Potawatomi, Inc.); Ottawa Tribe of Oklahoma; Pokagon Band of Potawatomi Indians, Michigan and Indiana; Prairie Band Potawatomi Nation (previously listed as the Prairie Band of Potawatomi Nation, Kansas); Quechan Tribe of the Fort Yuma Indian Reservation, California & Arizona; Red Cliff Band of Lake Superior Chippewa Indians of Wisconsin; Red Lake Band of Chippewa Indians, Minnesota; Saginaw Chippewa Indian Tribe of Michigan; Sault Ste. Marie Tribe of Chippewa Indians, Michigan; Sokaogon Chippewa Community, Wisconsin; St. Croix Chippewa Indians of Wisconsin; Turtle Mountain Band of Chippewa Indians of North Dakota; and the White Earth Band of the Minnesota Chippewa Tribe, Minnesota (hereafter referred to as \\xe2\\x80\\x9cThe Aboriginal Land Tribes\\xe2\\x80\\x9d).\\n        \\xe2\\x80\\xa2 Pursuant to 43 CFR 10.11(c)(1), the disposition of the human remains may be to The Aboriginal Land Tribes.\\n        Additional Requestors and Disposition\\n\\n        Representatives of any Indian tribe or Native Hawaiian organization not identified in this notice that wish to request transfer of control of these human remains should submit a written request with information in support of the request to Jennifer Kolb, Wisconsin Historical Museum, 30 North Carroll Street, Madison, WI 53703, telephone (608) 261-2461, email Jennifer.Kolb@wisconsinhistory.org, by October 10, 2014. After that date, if no additional requestors have come forward, transfer of control of the human remains to The Aboriginal Land Tribes may proceed.\\n        The State Historical Society of Wisconsin is responsible for notifying The Aboriginal Land Tribes that this notice has been published.\\n        \\n          Dated: July 24, 2014.\\n          Melanie O\\'Brien,\\n          Acting Manager, National NAGPRA Program. \\n        \\n      \\n      [FR Doc. 2014-21502 Filed 9-9-14; 8:45 am]\\n      BILLING CODE 4312-50-P\\n    ", "agency1": "DEPARTMENT OF THE INTERIOR", "sub_agency1": "National Park Service", "dep_doc": "[NPS-WASO-NAGPRA-16312; PPWOCRADN0-PCU00RP14.R50000]", "subject": "Notice of Inventory Completion: State Historical Society of Wisconsin, Madison, WI", "agency2": "National Park Service, Interior.", "action": "Notice.", "summary": "The State Historical Society of Wisconsin has completed an inventory of human remains, in consultation with the appropriate Indian tribes or Native Hawaiian organizations, and has determined that there is no cultural affiliation between the human remains and any present-day Indian tribes or Native Hawaiian organizations. Representatives of any Indian tribe or Native Hawaiian organization not identified in this notice that wish to request transfer of control of these human remains should submit a written request to the State Historical Society of Wisconsin. If no additional requestors come forward, transfer of control of the human remains to the Indian tribes or Native Hawaiian organizations stated in this notice may proceed.", "dates": "Representatives of any Indian tribe or Native Hawaiian organization not identified in this notice that wish to request transfer of control of these human remains should submit a written request with information in support of the request to the State Historical Society of Wisconsin at the address in this notice by October 10, 2014.", "addresses": "Jennifer Kolb, Wisconsin Historical Museum, 30 North Carroll Street, Madison, WI 53703, telephone (608) 261-2461, email Jennifer.Kolb@wisconsinhistory.org.\\n          ", "signature_dated": "Dated: July 24, 2014.", "signature_name": "Melanie O\\'Brien,", "signature_title": "Acting Manager, National NAGPRA Program. ", "fr_doc": "[FR Doc. 2014-21502 Filed 9-9-14; 8:45 am]", "billing_code": "BILLING CODE 4312-50-P", "supp_info": "SUPPLEMENTARY INFORMATION: \n Notice is here given in accordance with the Native American Graves Protection and Repatriation Act (NAGPRA), 25 U.S.C. 3003, of the completion of an inventory of human remains under the control of the State Historical Society of Wisconsin, Madison, WI. The human remains were removed from the Cooper\\'s Shores site, Rock County, WI. \n This notice is published as part of the National Park Service\\'s administrative responsibilities under NAGPRA, 25 U.S.C. 3003(d)(3) and 43 CFR 10.11(d). The determinations in this notice are the sole responsibility of the museum, institution, or Federal agency that has control of the Native American human remains. The National Park Service is not responsible for the determinations in this notice. \n Consultation \n A detailed assessment of the human remains was made by the State Historical Society of Wisconsin professional staff in consultation with representatives of the Forest County Potawatomi Community, Wisconsin; Ho-Chunk Nation of Wisconsin; and the Menominee Indian Tribe of Wisconsin. \n History and Description of the Remains \n In 1930, human remains representing, at minimum, five individuals (F1996.2.1 and F1996.2.2) were removed from the Cooper\\'s Shores site (47-RO-0002) in Rock County, WI. The human remains were disturbed by the land owner during a construction project on the north shore of the Rock River at the point where it flows into Lake Koshkonong. The land owner removed the human remains and contacted Charles E. Brown of the Historical Society, who investigated the site and took possession of the human remains. The human remains were determined to be those of an adult female, two adult males, and two children of indeterminate sex. No known individuals were identified. No associated funerary objects are present. \n Determinations Made by the State Historical Society of Wisconsin \n Officials of the State Historical Society of Wisconsin have determined that:\\n         \n \\xe2\\x80\\xa2 Pursuant to 25 U.S.C. 3001(9), the human remains described in this notice are Native American based on the location and context of the burials, objects found with the burials (not in the collection), and State Historical Society records. \n \\xe2\\x80\\xa2 Pursuant to 25 U.S.C. 3001(9), the human remains described in this notice represent the physical remains of five individuals of Native American ancestry. \n \\xe2\\x80\\xa2 Pursuant to 25 U.S.C. 3001(2), a relationship of shared group identity cannot be reasonably traced between the Native American human remains and any present-day Indian tribe. \n \\xe2\\x80\\xa2 According to final judgments of the Indian Claims Commission or the Court of Federal Claims, the land from which the Native American human remains were removed is the aboriginal land of the Citizen Potawatomi Nation, Oklahoma; Forest County Potawatomi Community, Wisconsin; Hannahville Indian Community, Michigan; Match-e-be-nash-she-wish Band of Pottawatomi Indians of Michigan; Nottawaseppi Huron Band of the Potawatomi, Michigan (previously listed as the Huron Potawatomi, Inc.); Pokagon Band of Potawatomi Indians, Michigan and Indiana; Prairie Band Potawatomi Nation (previously listed as the Prairie Band of Potawatomi Nation, Kansas); and the Quechan Tribe of Fort Yuma Indian Reservation, California & Arizona. \n \\xe2\\x80\\xa2 Treaties, Acts of Congress, or Executive Orders, indicate that the land from which the Native American human remains were removed is the aboriginal land of the Bad River Band of the Lake Superior Tribe of Chippewa Indians of the Bad River Reservation, Wisconsin; Bay Mills Indian Community, Michigan; Bois Forte Band (Nett Lake) of the Minnesota Chippewa Tribe, Minnesota; Chippewa-Cree Indians of the Rocky Boy\\'s Reservation, Montana; Citizen Potawatomi Nation, Oklahoma; Fond du Lac Band of the Minnesota Chippewa Tribe, Minnesota; Forest County Potawatomi Community, Wisconsin; Grand Portage Band of the Minnesota Chippewa Tribe, Minnesota; Grand Traverse Band of Ottawa and Chippewa Indians, Michigan; Hannahville Indian Community, Michigan; Keweenaw Bay Indian Community, Michigan; Lac Courte Oreilles Band of Lake Superior Chippewa Indians of Wisconsin; Lac du Flambeau Band of Lake Superior Chippewa Indians of the Lac du Flambeau Reservation of Wisconsin; Lac Vieux Desert Band of Lake Superior Chippewa Indians of Michigan; Leech Lake Band of the Minnesota Chippewa Tribe, Minnesota; Match-e-be-nash-she-wish Band of Pottawatomi Indians of Michigan; Mille Lacs Band of the Minnesota Chippewa Tribe, Minnesota; Minnesota Chippewa Tribe, Minnesota; Nottawaseppi Huron Band of the Potawatomi, Michigan (previously listed as the Huron Potawatomi, Inc.); Ottawa Tribe of Oklahoma; Pokagon Band of Potawatomi Indians, Michigan and Indiana; Prairie Band Potawatomi Nation (previously listed as the Prairie Band of Potawatomi Nation, Kansas); Quechan Tribe of the Fort Yuma Indian Reservation, California & Arizona; Red Cliff Band of Lake Superior Chippewa Indians of Wisconsin; Red Lake Band of Chippewa Indians, Minnesota; Saginaw Chippewa Indian Tribe of Michigan; Sault Ste. Marie Tribe of Chippewa Indians, Michigan; Sokaogon Chippewa Community, Wisconsin; St. Croix Chippewa Indians of Wisconsin; Turtle Mountain Band of Chippewa Indians of North Dakota; and the White Earth Band of the Minnesota Chippewa Tribe, Minnesota (hereafter referred to as \\xe2\\x80\\x9cThe Aboriginal Land Tribes\\xe2\\x80\\x9d). \n \\xe2\\x80\\xa2 Pursuant to 43 CFR 10.11(c)(1), the disposition of the human remains may be to The Aboriginal Land Tribes. \n Additional Requestors and Disposition \n Representatives of any Indian tribe or Native Hawaiian organization not identified in this notice that wish to request transfer of control of these human remains should submit a written request with information in support of the request to Jennifer Kolb, Wisconsin Historical Museum, 30 North Carroll Street, Madison, WI 53703, telephone (608) 261-2461, email Jennifer.Kolb@wisconsinhistory.org, by October 10, 2014. After that date, if no additional requestors have come forward, transfer of control of the human remains to The Aboriginal Land Tribes may proceed. \n The State Historical Society of Wisconsin is responsible for notifying The Aboriginal Land Tribes that this notice has been published. \n ", "consultation": "A detailed assessment of the human remains was made by the State Historical Society of Wisconsin professional staff in consultation with representatives of the Forest County Potawatomi Community, Wisconsin; Ho-Chunk Nation of Wisconsin; and the Menominee Indian Tribe of Wisconsin. \n ", "h_d_r": "In 1930, human remains representing, at minimum, five individuals (F1996.2.1 and F1996.2.2) were removed from the Cooper\\'s Shores site (47-RO-0002) in Rock County, WI. The human remains were disturbed by the land owner during a construction project on the north shore of the Rock River at the point where it flows into Lake Koshkonong. The land owner removed the human remains and contacted Charles E. Brown of the Historical Society, who investigated the site and took possession of the human remains. The human remains were determined to be those of an adult female, two adult males, and two children of indeterminate sex. No known individuals were identified. No associated funerary objects are present. \n ", "h_d_ci": "Null", "determinations": "Determinations Made by the State Historical Society of Wisconsin \n Officials of the State Historical Society of Wisconsin have determined that:\\n         \n \\xe2\\x80\\xa2 Pursuant to 25 U.S.C. 3001(9), the human remains described in this notice are Native American based on the location and context of the burials, objects found with the burials (not in the collection), and State Historical Society records. \n \\xe2\\x80\\xa2 Pursuant to 25 U.S.C. 3001(9), the human remains described in this notice represent the physical remains of five individuals of Native American ancestry. \n \\xe2\\x80\\xa2 Pursuant to 25 U.S.C. 3001(2), a relationship of shared group identity cannot be reasonably traced between the Native American human remains and any present-day Indian tribe. \n \\xe2\\x80\\xa2 According to final judgments of the Indian Claims Commission or the Court of Federal Claims, the land from which the Native American human remains were removed is the aboriginal land of the Citizen Potawatomi Nation, Oklahoma; Forest County Potawatomi Community, Wisconsin; Hannahville Indian Community, Michigan; Match-e-be-nash-she-wish Band of Pottawatomi Indians of Michigan; Nottawaseppi Huron Band of the Potawatomi, Michigan (previously listed as the Huron Potawatomi, Inc.); Pokagon Band of Potawatomi Indians, Michigan and Indiana; Prairie Band Potawatomi Nation (previously listed as the Prairie Band of Potawatomi Nation, Kansas); and the Quechan Tribe of Fort Yuma Indian Reservation, California & Arizona. \n \\xe2\\x80\\xa2 Treaties, Acts of Congress, or Executive Orders, indicate that the land from which the Native American human remains were removed is the aboriginal land of the Bad River Band of the Lake Superior Tribe of Chippewa Indians of the Bad River Reservation, Wisconsin; Bay Mills Indian Community, Michigan; Bois Forte Band (Nett Lake) of the Minnesota Chippewa Tribe, Minnesota; Chippewa-Cree Indians of the Rocky Boy\\'s Reservation, Montana; Citizen Potawatomi Nation, Oklahoma; Fond du Lac Band of the Minnesota Chippewa Tribe, Minnesota; Forest County Potawatomi Community, Wisconsin; Grand Portage Band of the Minnesota Chippewa Tribe, Minnesota; Grand Traverse Band of Ottawa and Chippewa Indians, Michigan; Hannahville Indian Community, Michigan; Keweenaw Bay Indian Community, Michigan; Lac Courte Oreilles Band of Lake Superior Chippewa Indians of Wisconsin; Lac du Flambeau Band of Lake Superior Chippewa Indians of the Lac du Flambeau Reservation of Wisconsin; Lac Vieux Desert Band of Lake Superior Chippewa Indians of Michigan; Leech Lake Band of the Minnesota Chippewa Tribe, Minnesota; Match-e-be-nash-she-wish Band of Pottawatomi Indians of Michigan; Mille Lacs Band of the Minnesota Chippewa Tribe, Minnesota; Minnesota Chippewa Tribe, Minnesota; Nottawaseppi Huron Band of the Potawatomi, Michigan (previously listed as the Huron Potawatomi, Inc.); Ottawa Tribe of Oklahoma; Pokagon Band of Potawatomi Indians, Michigan and Indiana; Prairie Band Potawatomi Nation (previously listed as the Prairie Band of Potawatomi Nation, Kansas); Quechan Tribe of the Fort Yuma Indian Reservation, California & Arizona; Red Cliff Band of Lake Superior Chippewa Indians of Wisconsin; Red Lake Band of Chippewa Indians, Minnesota; Saginaw Chippewa Indian Tribe of Michigan; Sault Ste. Marie Tribe of Chippewa Indians, Michigan; Sokaogon Chippewa Community, Wisconsin; St. Croix Chippewa Indians of Wisconsin; Turtle Mountain Band of Chippewa Indians of North Dakota; and the White Earth Band of the Minnesota Chippewa Tribe, Minnesota (hereafter referred to as \\xe2\\x80\\x9cThe Aboriginal Land Tribes\\xe2\\x80\\x9d). \n \\xe2\\x80\\xa2 Pursuant to 43 CFR 10.11(c)(1), the disposition of the human remains may be to The Aboriginal Land Tribes. \n ", "a_r_d": "Representatives of any Indian tribe or Native Hawaiian organization not identified in this notice that wish to request transfer of control of these human remains should submit a written request with information in support of the request to Jennifer Kolb, Wisconsin Historical Museum, 30 North Carroll Street, Madison, WI 53703, telephone (608) 261-2461, email Jennifer.Kolb@wisconsinhistory.org, by October 10, 2014. After that date, if no additional requestors have come forward, transfer of control of the human remains to The Aboriginal Land Tribes may proceed. \n The State Historical Society of Wisconsin is responsible for notifying The Aboriginal Land Tribes that this notice has been published. \n "}