{"index": "I_761", "messy_full": "\\n      \\n        DEPARTMENT OF THE INTERIOR\\n        National Park Service\\n        [NPS-WASO-NAGPRA-16443; PPWOCRADN0-PCU00RP14.R50000]\\n        Notice of Inventory Completion: University of Pennsylvania Museum of Archaeology and Anthropology, Philadelphia, PA\\n        \\n          AGENCY:\\n          National Park Service, Interior.\\n        \\n        \\n          ACTION:\\n          Notice.\\n        \\n        \\n          SUMMARY:\\n          The University of Pennsylvania Museum of Archaeology and Anthropology has completed an inventory of human remains, in consultation with the appropriate Indian tribes or Native Hawaiian organizations, and has determined that there is a cultural affiliation between the human remains and present-day Indian tribes or Native Hawaiian organizations. Lineal descendants or representatives of any Indian tribe or Native Hawaiian organization not identified in this notice that wish to request transfer of control of these human remains should submit a written request to the University of Pennsylvania Museum of Archaeology and Anthropology. If no additional requestors come forward, transfer of control of the human remains to the lineal descendants, Indian tribes, or Native Hawaiian organizations stated in this notice may proceed.\\n        \\n        \\n          DATES:\\n          Lineal descendants or representatives of any Indian tribe or Native Hawaiian organization not identified in this notice that wish to request transfer of control of these human remains should submit a written request with information in support of the request to the University of Pennsylvania Museum of Archaeology and Anthropology at the address in this notice by October 10, 2014.\\n        \\n        \\n          ADDRESSES:\\n          Dr. Julian Siggers, University of Pennsylvania Museum of Archaeology and Anthropology, Philadelphia, PA 19104, telephone (215) 898-4050.\\n        \\n      \\n      \\n        SUPPLEMENTARY INFORMATION:\\n        Notice is here given in accordance with the Native American Graves Protection and Repatriation Act (NAGPRA), 25 U.S.C. 3003, of the completion of an inventory of human remains under the control of the University of Pennsylvania Museum Archaeology and Anthropology, Philadelphia, PA. The human remains were removed from an unknown grave in Pequaming, Baraga County, MI.\\n        This notice is published as part of the National Park Service\\'s administrative responsibilities under NAGPRA, 25 U.S.C. 3003(d)(3). The determinations in this notice are the sole responsibility of the museum, institution, or Federal agency that has control of the Native American human remains. The National Park Service is not responsible for the determinations in this notice.\\n        Consultation\\n\\n        A detailed assessment of the human remains was made by the University of Pennsylvania Museum of Archaeology and Anthropology professional staff in consultation with representatives of Bay Mills Indian Community, Michigan; Grand Traverse Band of Ottawa and Chippewa Indians, Michigan; Hannahville Indian Community, Michigan; Keweenaw Bay Indian Community; Lac Courte Oreilles Band of Lake Superior Chippewa Indians of Wisconsin; Lac Vieux Desert Band of Lake Superior Chippewa Indians of Michigan; Little River Band of Ottawa Indians, Michigan; Little Traverse Bay Bands of Odawa Indians, Michigan; Match-e-be-nash-she-wish Band of Pottawatomi Indians of Michigan; Minnesota Chippewa Tribe, Minnesota (Six components reservations: Bois Forte Band (Nett Lake); Fond du Lac Band; Grand Portage Band; Leech Lake Band; Mille Lacs Band; White Earth Band); Nottawaseppi Huron Band of the Potawatomi, Michigan (previously listed as the Huron Potawatomi, Inc.); Pokagon Band of Potawatomi Indians, Michigan and Indiana; Red Cliff Band of Lake Superior Chippewa Indians of Wisconsin; Saginaw Chippewa Indian Tribe of Michigan; and Sault Ste. Marie Tribe of Chippewa Indians, Michigan. The Bad River Band of the Lake Superior Tribe of Chippewa Indians of the Bad River Reservation, Wisconsin; Lac du Flambeau Band of Lake Superior Chippewa Indians of the Lac du Flambeau Reservation of Wisconsin; Sokaogon Chippewa Community, Wisconsin; and St. Croix Chippewa Indians of Wisconsin were invited to consult, but did not respond.\\n        History and Description of the Remains\\n        At an unknown date prior to 1921, human remains representing, at minimum, one individual were removed from an unknown grave in Pequaming in Baraga County, MI, by Mr. Morgan Hebard, a summer resident of Pequaming. Hebard subsequently donated the human remains to the Academy of Natural Sciences of Philadelphia in 1921. In 1936, the human remains were loaned to the University of Pennsylvania Museum of Archaeology and Anthropology. In 1997, the remains were formally gifted to the University of Pennsylvania. The human remains consist of three cranial fragments (temporal, parietal, and occipital bones) of one adult male. No known individuals were identified. No associated funerary objects are present.\\n        Museum and collector documentation indicate that the human remains have been dated to the early Historic Period. Consultation, published information, and land cessions associated with Baraga County indicate that the geographic location from which the remains were removed is aboriginal to the Chippewa tribe or people.\\n        Determinations Made by the University of Pennsylvania Museum of Archaeology and Anthropology\\n        Officials of the University of Pennsylvania Museum of Archaeology and Anthropology have determined that:\\n        \\xe2\\x80\\xa2 Pursuant to 25 U.S.C. 3001(9), the human remains described in this notice represent the physical remains of one individual of Native American ancestry.\\n        \\xe2\\x80\\xa2 Pursuant to 25 U.S.C. 3001(2), there is a relationship of shared group identity that can be reasonably traced between the Native American human remains and Bad River Band of the Lake Superior Tribe of Chippewa Indians of the Bad River Reservation, Wisconsin; Keweenaw Bay Indian Community; Lac Courte Oreilles Band of Lake Superior Chippewa Indians of Wisconsin; Lac Vieux Desert Band of Lake Superior Chippewa Indians of Michigan; Minnesota Chippewa Tribe, Minnesota (Leech Lake Band; Mille Lacs Band; White Earth Band); and Red Cliff Band of Lake Superior Chippewa Indians of Wisconsin.\\n        Additional Requestors and Disposition\\n        Lineal descendants or representatives of any Indian tribe or Native Hawaiian organization not identified in this notice that wish to request transfer of control of these human remains should submit a written request with information in support of the request to Dr. Julian Siggers, Director, University of Pennsylvania Museum of Archaeology and Anthropology, University of Pennsylvania, 3260 South Street, Philadelphia, PA 19104, telephone (215) 898-4050, by October 10, 2014. After that date, if no additional requestors have come forward, transfer of control of the human remains to the Bad River Band of the Lake Superior Tribe of Chippewa Indians of the Bad River Reservation, Wisconsin; Keweenaw Bay Indian Community; Lac Courte Oreilles Band of Lake Superior Chippewa Indians of Wisconsin; Lac Vieux Desert Band of Lake Superior Chippewa Indians of Michigan; Minnesota Chippewa Tribe, Minnesota (Leech Lake Band; Mille Lacs Band; White Earth Band); and Red Cliff Band of Lake Superior Chippewa Indians of Wisconsin may proceed.\\n        The University of Pennsylvania Museum of Archaeology and Anthropology is responsible for notifying the Bad River Band of the Lake Superior Tribe of Chippewa Indians of the Bad River Reservation, Wisconsin; Bay Mills Indian Community, Michigan; Grand Traverse Band of Ottawa and Chippewa Indians, Michigan; Hannahville Indian Community, Michigan; Keweenaw Bay Indian Community; Lac Courte Oreilles Band of Lake Superior Chippewa Indians of Wisconsin; Lac du Flambeau Band of Lake Superior Chippewa Indians of the Lac du Flambeau Reservation of Wisconsin; Lac Vieux Desert Band of Lake Superior Chippewa Indians of Michigan; Little River Band of Ottawa Indians, Michigan; Little Traverse Bay Bands of Odawa Indians, Michigan; Match-e-be-nash-she-wish Band of Pottawatomi Indians of Michigan; Minnesota Chippewa Tribe, Minnesota (Six components reservations: Bois Forte Band (Nett Lake); Fond du Lac Band; Grand Portage Band; Leech Lake Band; Mille Lacs Band; White Earth Band); Nottawaseppi Huron Band of the Potawatomi, Michigan (previously listed as the Huron Potawatomi, Inc.); Pokagon Band of Potawatomi Indians, Michigan and Indiana; Red Cliff Band of Lake Superior Chippewa Indians of Wisconsin; Saginaw Chippewa Indian Tribe of Michigan; Sault Ste. Marie Tribe of Chippewa Indians, Michigan; Sokaogon Chippewa Community, Wisconsin; and St. Croix Chippewa Indians of Wisconsin that this notice has been published.\\n        \\n          Dated: August 7, 2014.\\n          Melanie O\\'Brien,\\n          Acting Manager, National NAGPRA Program.\\n        \\n      \\n      [FR Doc. 2014-21516 Filed 9-9-14; 8:45 am]\\n      BILLING CODE 4312-50-P\\n    ", "agency1": "DEPARTMENT OF THE INTERIOR", "sub_agency1": "National Park Service", "dep_doc": "[NPS-WASO-NAGPRA-16443; PPWOCRADN0-PCU00RP14.R50000]", "subject": "Notice of Inventory Completion: University of Pennsylvania Museum of Archaeology and Anthropology, Philadelphia, PA", "agency2": "National Park Service, Interior.", "action": "Notice.", "summary": "The University of Pennsylvania Museum of Archaeology and Anthropology has completed an inventory of human remains, in consultation with the appropriate Indian tribes or Native Hawaiian organizations, and has determined that there is a cultural affiliation between the human remains and present-day Indian tribes or Native Hawaiian organizations. Lineal descendants or representatives of any Indian tribe or Native Hawaiian organization not identified in this notice that wish to request transfer of control of these human remains should submit a written request to the University of Pennsylvania Museum of Archaeology and Anthropology. If no additional requestors come forward, transfer of control of the human remains to the lineal descendants, Indian tribes, or Native Hawaiian organizations stated in this notice may proceed.", "dates": "Lineal descendants or representatives of any Indian tribe or Native Hawaiian organization not identified in this notice that wish to request transfer of control of these human remains should submit a written request with information in support of the request to the University of Pennsylvania Museum of Archaeology and Anthropology at the address in this notice by October 10, 2014.", "addresses": "Dr. Julian Siggers, University of Pennsylvania Museum of Archaeology and Anthropology, Philadelphia, PA 19104, telephone (215) 898-4050.", "signature_dated": "Dated: August 7, 2014.", "signature_name": "Melanie O\\'Brien,", "signature_title": "Acting Manager, National NAGPRA Program.", "fr_doc": "[FR Doc. 2014-21516 Filed 9-9-14; 8:45 am]", "billing_code": "BILLING CODE 4312-50-P", "supp_info": "SUPPLEMENTARY INFORMATION: \n Notice is here given in accordance with the Native American Graves Protection and Repatriation Act (NAGPRA), 25 U.S.C. 3003, of the completion of an inventory of human remains under the control of the University of Pennsylvania Museum Archaeology and Anthropology, Philadelphia, PA. The human remains were removed from an unknown grave in Pequaming, Baraga County, MI. \n This notice is published as part of the National Park Service\\'s administrative responsibilities under NAGPRA, 25 U.S.C. 3003(d)(3). The determinations in this notice are the sole responsibility of the museum, institution, or Federal agency that has control of the Native American human remains. The National Park Service is not responsible for the determinations in this notice. \n Consultation \n A detailed assessment of the human remains was made by the University of Pennsylvania Museum of Archaeology and Anthropology professional staff in consultation with representatives of Bay Mills Indian Community, Michigan; Grand Traverse Band of Ottawa and Chippewa Indians, Michigan; Hannahville Indian Community, Michigan; Keweenaw Bay Indian Community; Lac Courte Oreilles Band of Lake Superior Chippewa Indians of Wisconsin; Lac Vieux Desert Band of Lake Superior Chippewa Indians of Michigan; Little River Band of Ottawa Indians, Michigan; Little Traverse Bay Bands of Odawa Indians, Michigan; Match-e-be-nash-she-wish Band of Pottawatomi Indians of Michigan; Minnesota Chippewa Tribe, Minnesota (Six components reservations: Bois Forte Band (Nett Lake); Fond du Lac Band; Grand Portage Band; Leech Lake Band; Mille Lacs Band; White Earth Band); Nottawaseppi Huron Band of the Potawatomi, Michigan (previously listed as the Huron Potawatomi, Inc.); Pokagon Band of Potawatomi Indians, Michigan and Indiana; Red Cliff Band of Lake Superior Chippewa Indians of Wisconsin; Saginaw Chippewa Indian Tribe of Michigan; and Sault Ste. Marie Tribe of Chippewa Indians, Michigan. The Bad River Band of the Lake Superior Tribe of Chippewa Indians of the Bad River Reservation, Wisconsin; Lac du Flambeau Band of Lake Superior Chippewa Indians of the Lac du Flambeau Reservation of Wisconsin; Sokaogon Chippewa Community, Wisconsin; and St. Croix Chippewa Indians of Wisconsin were invited to consult, but did not respond. \n History and Description of the Remains \n At an unknown date prior to 1921, human remains representing, at minimum, one individual were removed from an unknown grave in Pequaming in Baraga County, MI, by Mr. Morgan Hebard, a summer resident of Pequaming. Hebard subsequently donated the human remains to the Academy of Natural Sciences of Philadelphia in 1921. In 1936, the human remains were loaned to the University of Pennsylvania Museum of Archaeology and Anthropology. In 1997, the remains were formally gifted to the University of Pennsylvania. The human remains consist of three cranial fragments (temporal, parietal, and occipital bones) of one adult male. No known individuals were identified. No associated funerary objects are present. \n Museum and collector documentation indicate that the human remains have been dated to the early Historic Period. Consultation, published information, and land cessions associated with Baraga County indicate that the geographic location from which the remains were removed is aboriginal to the Chippewa tribe or people. \n Determinations Made by the University of Pennsylvania Museum of Archaeology and Anthropology \n Officials of the University of Pennsylvania Museum of Archaeology and Anthropology have determined that: \n \\xe2\\x80\\xa2 Pursuant to 25 U.S.C. 3001(9), the human remains described in this notice represent the physical remains of one individual of Native American ancestry. \n \\xe2\\x80\\xa2 Pursuant to 25 U.S.C. 3001(2), there is a relationship of shared group identity that can be reasonably traced between the Native American human remains and Bad River Band of the Lake Superior Tribe of Chippewa Indians of the Bad River Reservation, Wisconsin; Keweenaw Bay Indian Community; Lac Courte Oreilles Band of Lake Superior Chippewa Indians of Wisconsin; Lac Vieux Desert Band of Lake Superior Chippewa Indians of Michigan; Minnesota Chippewa Tribe, Minnesota (Leech Lake Band; Mille Lacs Band; White Earth Band); and Red Cliff Band of Lake Superior Chippewa Indians of Wisconsin. \n Additional Requestors and Disposition \n Lineal descendants or representatives of any Indian tribe or Native Hawaiian organization not identified in this notice that wish to request transfer of control of these human remains should submit a written request with information in support of the request to Dr. Julian Siggers, Director, University of Pennsylvania Museum of Archaeology and Anthropology, University of Pennsylvania, 3260 South Street, Philadelphia, PA 19104, telephone (215) 898-4050, by October 10, 2014. After that date, if no additional requestors have come forward, transfer of control of the human remains to the Bad River Band of the Lake Superior Tribe of Chippewa Indians of the Bad River Reservation, Wisconsin; Keweenaw Bay Indian Community; Lac Courte Oreilles Band of Lake Superior Chippewa Indians of Wisconsin; Lac Vieux Desert Band of Lake Superior Chippewa Indians of Michigan; Minnesota Chippewa Tribe, Minnesota (Leech Lake Band; Mille Lacs Band; White Earth Band); and Red Cliff Band of Lake Superior Chippewa Indians of Wisconsin may proceed. \n The University of Pennsylvania Museum of Archaeology and Anthropology is responsible for notifying the Bad River Band of the Lake Superior Tribe of Chippewa Indians of the Bad River Reservation, Wisconsin; Bay Mills Indian Community, Michigan; Grand Traverse Band of Ottawa and Chippewa Indians, Michigan; Hannahville Indian Community, Michigan; Keweenaw Bay Indian Community; Lac Courte Oreilles Band of Lake Superior Chippewa Indians of Wisconsin; Lac du Flambeau Band of Lake Superior Chippewa Indians of the Lac du Flambeau Reservation of Wisconsin; Lac Vieux Desert Band of Lake Superior Chippewa Indians of Michigan; Little River Band of Ottawa Indians, Michigan; Little Traverse Bay Bands of Odawa Indians, Michigan; Match-e-be-nash-she-wish Band of Pottawatomi Indians of Michigan; Minnesota Chippewa Tribe, Minnesota (Six components reservations: Bois Forte Band (Nett Lake); Fond du Lac Band; Grand Portage Band; Leech Lake Band; Mille Lacs Band; White Earth Band); Nottawaseppi Huron Band of the Potawatomi, Michigan (previously listed as the Huron Potawatomi, Inc.); Pokagon Band of Potawatomi Indians, Michigan and Indiana; Red Cliff Band of Lake Superior Chippewa Indians of Wisconsin; Saginaw Chippewa Indian Tribe of Michigan; Sault Ste. Marie Tribe of Chippewa Indians, Michigan; Sokaogon Chippewa Community, Wisconsin; and St. Croix Chippewa Indians of Wisconsin that this notice has been published. \n ", "consultation": "A detailed assessment of the human remains was made by the University of Pennsylvania Museum of Archaeology and Anthropology professional staff in consultation with representatives of Bay Mills Indian Community, Michigan; Grand Traverse Band of Ottawa and Chippewa Indians, Michigan; Hannahville Indian Community, Michigan; Keweenaw Bay Indian Community; Lac Courte Oreilles Band of Lake Superior Chippewa Indians of Wisconsin; Lac Vieux Desert Band of Lake Superior Chippewa Indians of Michigan; Little River Band of Ottawa Indians, Michigan; Little Traverse Bay Bands of Odawa Indians, Michigan; Match-e-be-nash-she-wish Band of Pottawatomi Indians of Michigan; Minnesota Chippewa Tribe, Minnesota (Six components reservations: Bois Forte Band (Nett Lake); Fond du Lac Band; Grand Portage Band; Leech Lake Band; Mille Lacs Band; White Earth Band); Nottawaseppi Huron Band of the Potawatomi, Michigan (previously listed as the Huron Potawatomi, Inc.); Pokagon Band of Potawatomi Indians, Michigan and Indiana; Red Cliff Band of Lake Superior Chippewa Indians of Wisconsin; Saginaw Chippewa Indian Tribe of Michigan; and Sault Ste. Marie Tribe of Chippewa Indians, Michigan. The Bad River Band of the Lake Superior Tribe of Chippewa Indians of the Bad River Reservation, Wisconsin; Lac du Flambeau Band of Lake Superior Chippewa Indians of the Lac du Flambeau Reservation of Wisconsin; Sokaogon Chippewa Community, Wisconsin; and St. Croix Chippewa Indians of Wisconsin were invited to consult, but did not respond. \n ", "h_d_r": "At an unknown date prior to 1921, human remains representing, at minimum, one individual were removed from an unknown grave in Pequaming in Baraga County, MI, by Mr. Morgan Hebard, a summer resident of Pequaming. Hebard subsequently donated the human remains to the Academy of Natural Sciences of Philadelphia in 1921. In 1936, the human remains were loaned to the University of Pennsylvania Museum of Archaeology and Anthropology. In 1997, the remains were formally gifted to the University of Pennsylvania. The human remains consist of three cranial fragments (temporal, parietal, and occipital bones) of one adult male. No known individuals were identified. No associated funerary objects are present. \n Museum and collector documentation indicate that the human remains have been dated to the early Historic Period. Consultation, published information, and land cessions associated with Baraga County indicate that the geographic location from which the remains were removed is aboriginal to the Chippewa tribe or people. \n ", "h_d_ci": "Null", "determinations": "Determinations Made by the University of Pennsylvania Museum of Archaeology and Anthropology \n Officials of the University of Pennsylvania Museum of Archaeology and Anthropology have determined that: \n \\xe2\\x80\\xa2 Pursuant to 25 U.S.C. 3001(9), the human remains described in this notice represent the physical remains of one individual of Native American ancestry. \n \\xe2\\x80\\xa2 Pursuant to 25 U.S.C. 3001(2), there is a relationship of shared group identity that can be reasonably traced between the Native American human remains and Bad River Band of the Lake Superior Tribe of Chippewa Indians of the Bad River Reservation, Wisconsin; Keweenaw Bay Indian Community; Lac Courte Oreilles Band of Lake Superior Chippewa Indians of Wisconsin; Lac Vieux Desert Band of Lake Superior Chippewa Indians of Michigan; Minnesota Chippewa Tribe, Minnesota (Leech Lake Band; Mille Lacs Band; White Earth Band); and Red Cliff Band of Lake Superior Chippewa Indians of Wisconsin. \n ", "a_r_d": "Lineal descendants or representatives of any Indian tribe or Native Hawaiian organization not identified in this notice that wish to request transfer of control of these human remains should submit a written request with information in support of the request to Dr. Julian Siggers, Director, University of Pennsylvania Museum of Archaeology and Anthropology, University of Pennsylvania, 3260 South Street, Philadelphia, PA 19104, telephone (215) 898-4050, by October 10, 2014. After that date, if no additional requestors have come forward, transfer of control of the human remains to the Bad River Band of the Lake Superior Tribe of Chippewa Indians of the Bad River Reservation, Wisconsin; Keweenaw Bay Indian Community; Lac Courte Oreilles Band of Lake Superior Chippewa Indians of Wisconsin; Lac Vieux Desert Band of Lake Superior Chippewa Indians of Michigan; Minnesota Chippewa Tribe, Minnesota (Leech Lake Band; Mille Lacs Band; White Earth Band); and Red Cliff Band of Lake Superior Chippewa Indians of Wisconsin may proceed. \n The University of Pennsylvania Museum of Archaeology and Anthropology is responsible for notifying the Bad River Band of the Lake Superior Tribe of Chippewa Indians of the Bad River Reservation, Wisconsin; Bay Mills Indian Community, Michigan; Grand Traverse Band of Ottawa and Chippewa Indians, Michigan; Hannahville Indian Community, Michigan; Keweenaw Bay Indian Community; Lac Courte Oreilles Band of Lake Superior Chippewa Indians of Wisconsin; Lac du Flambeau Band of Lake Superior Chippewa Indians of the Lac du Flambeau Reservation of Wisconsin; Lac Vieux Desert Band of Lake Superior Chippewa Indians of Michigan; Little River Band of Ottawa Indians, Michigan; Little Traverse Bay Bands of Odawa Indians, Michigan; Match-e-be-nash-she-wish Band of Pottawatomi Indians of Michigan; Minnesota Chippewa Tribe, Minnesota (Six components reservations: Bois Forte Band (Nett Lake); Fond du Lac Band; Grand Portage Band; Leech Lake Band; Mille Lacs Band; White Earth Band); Nottawaseppi Huron Band of the Potawatomi, Michigan (previously listed as the Huron Potawatomi, Inc.); Pokagon Band of Potawatomi Indians, Michigan and Indiana; Red Cliff Band of Lake Superior Chippewa Indians of Wisconsin; Saginaw Chippewa Indian Tribe of Michigan; Sault Ste. Marie Tribe of Chippewa Indians, Michigan; Sokaogon Chippewa Community, Wisconsin; and St. Croix Chippewa Indians of Wisconsin that this notice has been published. \n "}