{"index": "I_774", "messy_full": "\\n      \\n        DEPARTMENT OF THE INTERIOR\\n        National Park Service\\n        [NPS-WASO-NAGPRA-16317; PPWOCRADN0-PCU00RP14.R50000]\\n        Notice of Inventory Completion: State Historical Society of Wisconsin, Madison, WI\\n        \\n          AGENCY:\\n          National Park Service, Interior.\\n        \\n        \\n          ACTION:\\n          Notice.\\n        \\n        \\n          SUMMARY:\\n          The State Historical Society of Wisconsin has completed an inventory of human remains and associated funerary objects, in consultation with the appropriate Indian tribes or Native Hawaiian organizations, and has determined that there is no cultural affiliation between the human remains and associated funerary objects and any present-day Indian tribes or Native Hawaiian organizations. Representatives of any Indian tribe or Native Hawaiian organization not identified in this notice that wish to request transfer of control of these human remains and associated funerary objects should submit a written request to the State Historical Society of Wisconsin. If no additional requestors come forward, transfer of control of the human remains and associated funerary objects to the Indian tribes or Native Hawaiian organizations stated in this notice may proceed.\\n        \\n        \\n          DATES:\\n          Representatives of any Indian tribe or Native Hawaiian organization not identified in this notice that wish to request transfer of control of these human remains and associated funerary objects should submit a written request with information in support of the request to the State Historical Society of Wisconsin at the address in this notice by October 10, 2014.\\n        \\n        \\n          ADDRESSES:\\n\\n          Jennifer Kolb, Wisconsin Historical Museum, 30 North Carroll Street, Madison, WI 53703, telephone (608) 261-2461, email Jennifer.Kolb@wisconsinhistory.org.\\n          \\n        \\n      \\n      \\n        SUPPLEMENTARY INFORMATION:\\n        Notice is here given in accordance with the Native American Graves Protection and Repatriation Act (NAGPRA), 25 U.S.C. 3003, of the completion of an inventory of human remains and associated funerary objects under the control of the State Historical Society of Wisconsin, Madison, WI. The human remains and associated funerary objects were removed from two sites in Waukesha County, WI.\\n        This notice is published as part of the National Park Service\\'s administrative responsibilities under NAGPRA, 25 U.S.C. 3003(d)(3) and 43 CFR 10.11(d). The determinations in this notice are the sole responsibility of the museum, institution, or Federal agency that has control of the Native American human remains and associated funerary objects. The National Park Service is not responsible for the determinations in this notice.\\n        Consultation\\n\\n        A detailed assessment of the human remains was made by the State Historical Society of Wisconsin professional staff in consultation with representatives of the Forest County Potawatomi Community, Wisconsin; Ho-Chunk Nation of Wisconsin; and the Menominee Indian Tribe of Wisconsin.\\n        \\n        History and Description of the Remains\\n        In 1992, human remains representing, at minimum, two individuals (HP.WK-0498.1) were removed from Nick\\'s Site (47-WK-0498) in Waukesha County, WI. The human remains were discovered during construction of a retaining wall near Bark River in the town of Delafield. The homeowners reported the human remains to the Delafield police. An archeologist from the University of Wisconsin-Madison, Department of Anthropology, initially investigated the site and collected some of the human remains. Archeologists from the State Historical Society\\'s Burial Sites Preservation Office took possession of these human remains and then excavated the rest of the burial. The human remains were determined to represent an adult female over the age of fifty and a child between the ages of three and five. No known individuals were identified. The five associated funerary objects are two pointed bone awls (HP.WK-0498.2 & HP.WK-0498.3), two flint spear points (HP.WK-0498.4 & HP.WK-0498.5), and one fragmentary clam shell (HP.WK-0498.6)\\n        At an unknown date, human remains representing, at minimum, one individual (A01960) were removed from Hudley Gravel Pit Burial (47-WK-0500) in Waukesha County, WI. A cranium stained with red ochre was uncovered by J. B. Hudley from a small gravel pit at the western edge of Pewaukee Lake. Mr. Hudley gave the cranium to Paul Joers, and Joers donated it to the State Historical Society in 1912. The human remains were determined to represent an adult male. No known individuals were identified. No associated funerary objects are present.\\n        Determinations Made by the State Historical Society of Wisconsin\\n        Officials of the State Historical Society of Wisconsin have determined that:\\n        \\xe2\\x80\\xa2 Pursuant to 25 U.S.C. 3001(9), the human remains described in this notice are Native American based on the location and context of the burial and State Historical Society records.\\n        \\xe2\\x80\\xa2 Pursuant to 25 U.S.C. 3001(9), the human remains described in this notice represent the physical remains of three individuals of Native American ancestry.\\n        \\xe2\\x80\\xa2 Pursuant to 25 U.S.C. 3001(3)(A), the five objects described in this notice are reasonably believed to have been placed with or near individual human remains at the time of death or later as part of the death rite or ceremony.\\n        \\xe2\\x80\\xa2 Pursuant to 25 U.S.C. 3001(2), a relationship of shared group identity cannot be reasonably traced between the Native American human remains and associated funerary objects and any present-day Indian tribe.\\n        \\xe2\\x80\\xa2 According to final judgments of the Indian Claims Commission or the Court of Federal Claims, the land from which the Native American human remains and associated funerary objects were removed is the aboriginal land of the Citizen Potawatomi Nation, Oklahoma; Forest County Potawatomi Community, Wisconsin; Hannahville Indian Community, Michigan; Match-e-be-nash-she-wish Band of Pottawatomi Indians of Michigan; Nottawaseppi Huron Band of the Potawatomi, Michigan (previously listed as the Huron Potawatomi, Inc.); Pokagon Band of Potawatomi Indians, Michigan and Indiana; Prairie Band Potawatomi Nation (previously listed as the Prairie Band of Potawatomi Nation, Kansas); and the Quechan Tribe of Fort Yuma Indian Reservation, California & Arizona.\\n        \\xe2\\x80\\xa2 Treaties, Acts of Congress, or Executive Orders, indicate that the land from which the Native American human remains and associated funerary objects were removed is the aboriginal land of the Bad River Band of the Lake Superior Tribe of Chippewa Indians of the Bad River Reservation, Wisconsin; Bay Mills Indian Community, Michigan; Bois Forte Band (Nett Lake) of the Minnesota Chippewa Tribe, Minnesota; Chippewa-Cree Indians of the Rocky Boy\\'s Reservation, Montana; Citizen Potawatomi Nation, Oklahoma; Fond du Lac Band of the Minnesota Chippewa Tribe, Minnesota; Forest County Potawatomi Community, Wisconsin; Grand Portage Band of the Minnesota Chippewa Tribe, Minnesota; Grand Traverse Band of Ottawa and Chippewa Indians, Michigan; Hannahville Indian Community, Michigan; Keweenaw Bay Indian Community, Michigan; Lac Courte Oreilles Band of Lake Superior Chippewa Indians of Wisconsin; Lac du Flambeau Band of Lake Superior Chippewa Indians of the Lac du Flambeau Reservation of Wisconsin; Lac Vieux Desert Band of Lake Superior Chippewa Indians of Michigan; Leech Lake Band of the Minnesota Chippewa Tribe, Minnesota; Match-e-be-nash-she-wish Band of Pottawatomi Indians of Michigan; Mille Lacs Band of the Minnesota Chippewa Tribe, Minnesota; Minnesota Chippewa Tribe, Minnesota; Nottawaseppi Huron Band of the Potawatomi, Michigan (previously listed as the Huron Potawatomi, Inc.); Ottawa Tribe of Oklahoma; Pokagon Band of Potawatomi Indians, Michigan and Indiana; Prairie Band Potawatomi Nation (previously listed as the Prairie Band of Potawatomi Nation, Kansas); Quechan Tribe of the Fort Yuma Indian Reservation, California & Arizona; Red Cliff Band of Lake Superior Chippewa Indians of Wisconsin; Red Lake Band of Chippewa Indians, Minnesota; Saginaw Chippewa Indian Tribe of Michigan; Sault Ste. Marie Tribe of Chippewa Indians, Michigan; Sokaogon Chippewa Community, Wisconsin; St. Croix Chippewa Indians of Wisconsin; Turtle Mountain Band of Chippewa Indians of North Dakota; and the White Earth Band of the Minnesota Chippewa Tribe, Minnesota (hereafter referred to as \\xe2\\x80\\x9cThe Aboriginal Land Tribes\\xe2\\x80\\x9d).\\n        \\xe2\\x80\\xa2 Pursuant to 43 CFR 10.11(c)(1), the disposition of the human remains and associated funerary objects may be to The Aboriginal Land Tribes.\\n        Additional Requestors and Disposition\\n\\n        Representatives of any Indian tribe or Native Hawaiian organization not identified in this notice that wish to request transfer of control of these human remains and associated funerary objects should submit a written request with information in support of the request to Jennifer Kolb, Wisconsin Historical Museum, 30 North Carroll Street, Madison, WI 53703, telephone (608) 261-2461, email Jennifer.Kolb@wisconsinhistory.org, by October 10, 2014. After that date, if no additional requestors have come forward, transfer of control of the human remains and associated funerary objects to The Aboriginal Land Tribes may proceed.\\n        The State Historical Society of Wisconsin is responsible for notifying The Aboriginal Land Tribes that this notice has been published.\\n        \\n          Dated: July 24, 2014.\\n          Melanie O\\'Brien,\\n          Acting Manager, National NAGPRA Program. \\n        \\n      \\n      [FR Doc. 2014-21450 Filed 9-9-14; 8:45 am]\\n      BILLING CODE 4312-50-P\\n    ", "agency1": "DEPARTMENT OF THE INTERIOR", "sub_agency1": "National Park Service", "dep_doc": "[NPS-WASO-NAGPRA-16317; PPWOCRADN0-PCU00RP14.R50000]", "subject": "Notice of Inventory Completion: State Historical Society of Wisconsin, Madison, WI", "agency2": "National Park Service, Interior.", "action": "Notice.", "summary": "The State Historical Society of Wisconsin has completed an inventory of human remains and associated funerary objects, in consultation with the appropriate Indian tribes or Native Hawaiian organizations, and has determined that there is no cultural affiliation between the human remains and associated funerary objects and any present-day Indian tribes or Native Hawaiian organizations. Representatives of any Indian tribe or Native Hawaiian organization not identified in this notice that wish to request transfer of control of these human remains and associated funerary objects should submit a written request to the State Historical Society of Wisconsin. If no additional requestors come forward, transfer of control of the human remains and associated funerary objects to the Indian tribes or Native Hawaiian organizations stated in this notice may proceed.", "dates": "Representatives of any Indian tribe or Native Hawaiian organization not identified in this notice that wish to request transfer of control of these human remains and associated funerary objects should submit a written request with information in support of the request to the State Historical Society of Wisconsin at the address in this notice by October 10, 2014.", "addresses": "Jennifer Kolb, Wisconsin Historical Museum, 30 North Carroll Street, Madison, WI 53703, telephone (608) 261-2461, email Jennifer.Kolb@wisconsinhistory.org.\\n          ", "signature_dated": "Dated: July 24, 2014.", "signature_name": "Melanie O\\'Brien,", "signature_title": "Acting Manager, National NAGPRA Program. ", "fr_doc": "[FR Doc. 2014-21450 Filed 9-9-14; 8:45 am]", "billing_code": "BILLING CODE 4312-50-P", "supp_info": "SUPPLEMENTARY INFORMATION: \n Notice is here given in accordance with the Native American Graves Protection and Repatriation Act (NAGPRA), 25 U.S.C. 3003, of the completion of an inventory of human remains and associated funerary objects under the control of the State Historical Society of Wisconsin, Madison, WI. The human remains and associated funerary objects were removed from two sites in Waukesha County, WI. \n This notice is published as part of the National Park Service\\'s administrative responsibilities under NAGPRA, 25 U.S.C. 3003(d)(3) and 43 CFR 10.11(d). The determinations in this notice are the sole responsibility of the museum, institution, or Federal agency that has control of the Native American human remains and associated funerary objects. The National Park Service is not responsible for the determinations in this notice. \n Consultation \n A detailed assessment of the human remains was made by the State Historical Society of Wisconsin professional staff in consultation with representatives of the Forest County Potawatomi Community, Wisconsin; Ho-Chunk Nation of Wisconsin; and the Menominee Indian Tribe of Wisconsin.\\n         \n History and Description of the Remains \n In 1992, human remains representing, at minimum, two individuals (HP.WK-0498.1) were removed from Nick\\'s Site (47-WK-0498) in Waukesha County, WI. The human remains were discovered during construction of a retaining wall near Bark River in the town of Delafield. The homeowners reported the human remains to the Delafield police. An archeologist from the University of Wisconsin-Madison, Department of Anthropology, initially investigated the site and collected some of the human remains. Archeologists from the State Historical Society\\'s Burial Sites Preservation Office took possession of these human remains and then excavated the rest of the burial. The human remains were determined to represent an adult female over the age of fifty and a child between the ages of three and five. No known individuals were identified. The five associated funerary objects are two pointed bone awls (HP.WK-0498.2 & HP.WK-0498.3), two flint spear points (HP.WK-0498.4 & HP.WK-0498.5), and one fragmentary clam shell (HP.WK-0498.6) \n At an unknown date, human remains representing, at minimum, one individual (A01960) were removed from Hudley Gravel Pit Burial (47-WK-0500) in Waukesha County, WI. A cranium stained with red ochre was uncovered by J. B. Hudley from a small gravel pit at the western edge of Pewaukee Lake. Mr. Hudley gave the cranium to Paul Joers, and Joers donated it to the State Historical Society in 1912. The human remains were determined to represent an adult male. No known individuals were identified. No associated funerary objects are present. \n Determinations Made by the State Historical Society of Wisconsin \n Officials of the State Historical Society of Wisconsin have determined that: \n \\xe2\\x80\\xa2 Pursuant to 25 U.S.C. 3001(9), the human remains described in this notice are Native American based on the location and context of the burial and State Historical Society records. \n \\xe2\\x80\\xa2 Pursuant to 25 U.S.C. 3001(9), the human remains described in this notice represent the physical remains of three individuals of Native American ancestry. \n \\xe2\\x80\\xa2 Pursuant to 25 U.S.C. 3001(3)(A), the five objects described in this notice are reasonably believed to have been placed with or near individual human remains at the time of death or later as part of the death rite or ceremony. \n \\xe2\\x80\\xa2 Pursuant to 25 U.S.C. 3001(2), a relationship of shared group identity cannot be reasonably traced between the Native American human remains and associated funerary objects and any present-day Indian tribe. \n \\xe2\\x80\\xa2 According to final judgments of the Indian Claims Commission or the Court of Federal Claims, the land from which the Native American human remains and associated funerary objects were removed is the aboriginal land of the Citizen Potawatomi Nation, Oklahoma; Forest County Potawatomi Community, Wisconsin; Hannahville Indian Community, Michigan; Match-e-be-nash-she-wish Band of Pottawatomi Indians of Michigan; Nottawaseppi Huron Band of the Potawatomi, Michigan (previously listed as the Huron Potawatomi, Inc.); Pokagon Band of Potawatomi Indians, Michigan and Indiana; Prairie Band Potawatomi Nation (previously listed as the Prairie Band of Potawatomi Nation, Kansas); and the Quechan Tribe of Fort Yuma Indian Reservation, California & Arizona. \n \\xe2\\x80\\xa2 Treaties, Acts of Congress, or Executive Orders, indicate that the land from which the Native American human remains and associated funerary objects were removed is the aboriginal land of the Bad River Band of the Lake Superior Tribe of Chippewa Indians of the Bad River Reservation, Wisconsin; Bay Mills Indian Community, Michigan; Bois Forte Band (Nett Lake) of the Minnesota Chippewa Tribe, Minnesota; Chippewa-Cree Indians of the Rocky Boy\\'s Reservation, Montana; Citizen Potawatomi Nation, Oklahoma; Fond du Lac Band of the Minnesota Chippewa Tribe, Minnesota; Forest County Potawatomi Community, Wisconsin; Grand Portage Band of the Minnesota Chippewa Tribe, Minnesota; Grand Traverse Band of Ottawa and Chippewa Indians, Michigan; Hannahville Indian Community, Michigan; Keweenaw Bay Indian Community, Michigan; Lac Courte Oreilles Band of Lake Superior Chippewa Indians of Wisconsin; Lac du Flambeau Band of Lake Superior Chippewa Indians of the Lac du Flambeau Reservation of Wisconsin; Lac Vieux Desert Band of Lake Superior Chippewa Indians of Michigan; Leech Lake Band of the Minnesota Chippewa Tribe, Minnesota; Match-e-be-nash-she-wish Band of Pottawatomi Indians of Michigan; Mille Lacs Band of the Minnesota Chippewa Tribe, Minnesota; Minnesota Chippewa Tribe, Minnesota; Nottawaseppi Huron Band of the Potawatomi, Michigan (previously listed as the Huron Potawatomi, Inc.); Ottawa Tribe of Oklahoma; Pokagon Band of Potawatomi Indians, Michigan and Indiana; Prairie Band Potawatomi Nation (previously listed as the Prairie Band of Potawatomi Nation, Kansas); Quechan Tribe of the Fort Yuma Indian Reservation, California & Arizona; Red Cliff Band of Lake Superior Chippewa Indians of Wisconsin; Red Lake Band of Chippewa Indians, Minnesota; Saginaw Chippewa Indian Tribe of Michigan; Sault Ste. Marie Tribe of Chippewa Indians, Michigan; Sokaogon Chippewa Community, Wisconsin; St. Croix Chippewa Indians of Wisconsin; Turtle Mountain Band of Chippewa Indians of North Dakota; and the White Earth Band of the Minnesota Chippewa Tribe, Minnesota (hereafter referred to as \\xe2\\x80\\x9cThe Aboriginal Land Tribes\\xe2\\x80\\x9d). \n \\xe2\\x80\\xa2 Pursuant to 43 CFR 10.11(c)(1), the disposition of the human remains and associated funerary objects may be to The Aboriginal Land Tribes. \n Additional Requestors and Disposition \n Representatives of any Indian tribe or Native Hawaiian organization not identified in this notice that wish to request transfer of control of these human remains and associated funerary objects should submit a written request with information in support of the request to Jennifer Kolb, Wisconsin Historical Museum, 30 North Carroll Street, Madison, WI 53703, telephone (608) 261-2461, email Jennifer.Kolb@wisconsinhistory.org, by October 10, 2014. After that date, if no additional requestors have come forward, transfer of control of the human remains and associated funerary objects to The Aboriginal Land Tribes may proceed. \n The State Historical Society of Wisconsin is responsible for notifying The Aboriginal Land Tribes that this notice has been published. \n ", "consultation": "A detailed assessment of the human remains was made by the State Historical Society of Wisconsin professional staff in consultation with representatives of the Forest County Potawatomi Community, Wisconsin; Ho-Chunk Nation of Wisconsin; and the Menominee Indian Tribe of Wisconsin.\\n         \n ", "h_d_r": "In 1992, human remains representing, at minimum, two individuals (HP.WK-0498.1) were removed from Nick\\'s Site (47-WK-0498) in Waukesha County, WI. The human remains were discovered during construction of a retaining wall near Bark River in the town of Delafield. The homeowners reported the human remains to the Delafield police. An archeologist from the University of Wisconsin-Madison, Department of Anthropology, initially investigated the site and collected some of the human remains. Archeologists from the State Historical Society\\'s Burial Sites Preservation Office took possession of these human remains and then excavated the rest of the burial. The human remains were determined to represent an adult female over the age of fifty and a child between the ages of three and five. No known individuals were identified. The five associated funerary objects are two pointed bone awls (HP.WK-0498.2 & HP.WK-0498.3), two flint spear points (HP.WK-0498.4 & HP.WK-0498.5), and one fragmentary clam shell (HP.WK-0498.6) \n At an unknown date, human remains representing, at minimum, one individual (A01960) were removed from Hudley Gravel Pit Burial (47-WK-0500) in Waukesha County, WI. A cranium stained with red ochre was uncovered by J. B. Hudley from a small gravel pit at the western edge of Pewaukee Lake. Mr. Hudley gave the cranium to Paul Joers, and Joers donated it to the State Historical Society in 1912. The human remains were determined to represent an adult male. No known individuals were identified. No associated funerary objects are present. \n ", "h_d_ci": "Null", "determinations": "Determinations Made by the State Historical Society of Wisconsin \n Officials of the State Historical Society of Wisconsin have determined that: \n \\xe2\\x80\\xa2 Pursuant to 25 U.S.C. 3001(9), the human remains described in this notice are Native American based on the location and context of the burial and State Historical Society records. \n \\xe2\\x80\\xa2 Pursuant to 25 U.S.C. 3001(9), the human remains described in this notice represent the physical remains of three individuals of Native American ancestry. \n \\xe2\\x80\\xa2 Pursuant to 25 U.S.C. 3001(3)(A), the five objects described in this notice are reasonably believed to have been placed with or near individual human remains at the time of death or later as part of the death rite or ceremony. \n \\xe2\\x80\\xa2 Pursuant to 25 U.S.C. 3001(2), a relationship of shared group identity cannot be reasonably traced between the Native American human remains and associated funerary objects and any present-day Indian tribe. \n \\xe2\\x80\\xa2 According to final judgments of the Indian Claims Commission or the Court of Federal Claims, the land from which the Native American human remains and associated funerary objects were removed is the aboriginal land of the Citizen Potawatomi Nation, Oklahoma; Forest County Potawatomi Community, Wisconsin; Hannahville Indian Community, Michigan; Match-e-be-nash-she-wish Band of Pottawatomi Indians of Michigan; Nottawaseppi Huron Band of the Potawatomi, Michigan (previously listed as the Huron Potawatomi, Inc.); Pokagon Band of Potawatomi Indians, Michigan and Indiana; Prairie Band Potawatomi Nation (previously listed as the Prairie Band of Potawatomi Nation, Kansas); and the Quechan Tribe of Fort Yuma Indian Reservation, California & Arizona. \n \\xe2\\x80\\xa2 Treaties, Acts of Congress, or Executive Orders, indicate that the land from which the Native American human remains and associated funerary objects were removed is the aboriginal land of the Bad River Band of the Lake Superior Tribe of Chippewa Indians of the Bad River Reservation, Wisconsin; Bay Mills Indian Community, Michigan; Bois Forte Band (Nett Lake) of the Minnesota Chippewa Tribe, Minnesota; Chippewa-Cree Indians of the Rocky Boy\\'s Reservation, Montana; Citizen Potawatomi Nation, Oklahoma; Fond du Lac Band of the Minnesota Chippewa Tribe, Minnesota; Forest County Potawatomi Community, Wisconsin; Grand Portage Band of the Minnesota Chippewa Tribe, Minnesota; Grand Traverse Band of Ottawa and Chippewa Indians, Michigan; Hannahville Indian Community, Michigan; Keweenaw Bay Indian Community, Michigan; Lac Courte Oreilles Band of Lake Superior Chippewa Indians of Wisconsin; Lac du Flambeau Band of Lake Superior Chippewa Indians of the Lac du Flambeau Reservation of Wisconsin; Lac Vieux Desert Band of Lake Superior Chippewa Indians of Michigan; Leech Lake Band of the Minnesota Chippewa Tribe, Minnesota; Match-e-be-nash-she-wish Band of Pottawatomi Indians of Michigan; Mille Lacs Band of the Minnesota Chippewa Tribe, Minnesota; Minnesota Chippewa Tribe, Minnesota; Nottawaseppi Huron Band of the Potawatomi, Michigan (previously listed as the Huron Potawatomi, Inc.); Ottawa Tribe of Oklahoma; Pokagon Band of Potawatomi Indians, Michigan and Indiana; Prairie Band Potawatomi Nation (previously listed as the Prairie Band of Potawatomi Nation, Kansas); Quechan Tribe of the Fort Yuma Indian Reservation, California & Arizona; Red Cliff Band of Lake Superior Chippewa Indians of Wisconsin; Red Lake Band of Chippewa Indians, Minnesota; Saginaw Chippewa Indian Tribe of Michigan; Sault Ste. Marie Tribe of Chippewa Indians, Michigan; Sokaogon Chippewa Community, Wisconsin; St. Croix Chippewa Indians of Wisconsin; Turtle Mountain Band of Chippewa Indians of North Dakota; and the White Earth Band of the Minnesota Chippewa Tribe, Minnesota (hereafter referred to as \\xe2\\x80\\x9cThe Aboriginal Land Tribes\\xe2\\x80\\x9d). \n \\xe2\\x80\\xa2 Pursuant to 43 CFR 10.11(c)(1), the disposition of the human remains and associated funerary objects may be to The Aboriginal Land Tribes. \n ", "a_r_d": "Representatives of any Indian tribe or Native Hawaiian organization not identified in this notice that wish to request transfer of control of these human remains and associated funerary objects should submit a written request with information in support of the request to Jennifer Kolb, Wisconsin Historical Museum, 30 North Carroll Street, Madison, WI 53703, telephone (608) 261-2461, email Jennifer.Kolb@wisconsinhistory.org, by October 10, 2014. After that date, if no additional requestors have come forward, transfer of control of the human remains and associated funerary objects to The Aboriginal Land Tribes may proceed. \n The State Historical Society of Wisconsin is responsible for notifying The Aboriginal Land Tribes that this notice has been published. \n "}