{"index": "I_775", "messy_full": "\\n      \\n        DEPARTMENT OF THE INTERIOR\\n        National Park Service\\n        [NPS-WASO-NAGPRA-16306; PPWOCRADN0-PCU00RP14.R50000]\\n        Notice of Inventory Completion: U.S. Department of Defense, Army, Fort Sill National Historic Landmark and Museum, Fort Sill, OK\\n        \\n          AGENCY:\\n          National Park Service, Interior.\\n        \\n        \\n          ACTION:\\n          Notice.\\n        \\n        \\n          SUMMARY:\\n\\n          The Fort Sill National Historic Landmark and Museum has completed an inventory of human remains and associated funerary objects, in consultation with the appropriate Indian tribes or Native Hawaiian organizations, and has determined that there is a cultural affiliation between the human remains and associated funerary objects and present-day Indian tribes or Native Hawaiian organizations. Lineal descendants or representatives of any Indian tribe or Native Hawaiian organization not identified in this notice that wish to request transfer of control of these human remains and associated funerary objects should submit a written request to the Fort Sill National Historic Landmark and Museum. If no additional requestors come forward, transfer of control of the human remains and associated funerary objects to the lineal descendants, Indian tribes, or Native Hawaiian organizations stated in this notice may proceed.\\n        \\n        \\n          DATES:\\n          Lineal descendants or representatives of any Indian tribe or Native Hawaiian organization not identified in this notice that wish to request transfer of control of these human remains and associated funerary objects should submit a written request with information in support of the request to the Fort Sill National Historic Landmark and Museum at the address in this notice by October 10, 2014.\\n        \\n        \\n          ADDRESSES:\\n\\n          Dr. Scott A. Neel, Director, Fort Sill National Historic Landmark and Museum, U.S. Army Fires Center of Excellence, Fort Sill, OK 73503, telephone (580) 442-6570, email scott.a.neel2.civ@mail.mil.\\n          \\n        \\n      \\n      \\n        SUPPLEMENTARY INFORMATION:\\n        Notice is here given in accordance with the Native American Graves Protection and Repatriation Act (NAGPRA), 25 U.S.C. 3003, of the completion of an inventory of human remains and associated funerary objects under the control of the Fort Sill National Historic Landmark and Museum, Fort Sill, OK.\\n        This notice is published as part of the National Park Service\\'s administrative responsibilities under NAGPRA, 25 U.S.C. 3003(d)(3). The determinations in this notice are the sole responsibility of the museum, institution, or Federal agency that has control of the Native American human remains and associated funerary objects. The National Park Service is not responsible for the determinations in this notice.\\n        Consultation\\n        A detailed assessment of the human remains was made by the Fort Sill National Historic Landmark and Museum and Fort Sill Environmental Quality Division professional staff in consultation with representatives of the Apache Tribe of Oklahoma; Caddo Nation of Oklahoma; Cheyenne and Arapaho Tribes, Oklahoma (previously listed as Cheyenne-Arapaho Tribes of Oklahoma); Comanche Nation, Oklahoma; Delaware Nation, Oklahoma; Fort Sill Apache Tribe of Oklahoma; Kiowa Indian Tribe of Oklahoma; The Chickasaw Nation; and the Wichita and Affiliated Tribes (Wichita, Keechi, Waco & Tawakonie), Oklahoma.\\n        History and Description of the Remains\\n        In 1966, Morgan Otis died in a car accident in California, and he was interred in the Fort Sill Post Cemetery shortly thereafter. A collection of items were recovered from the vehicle and later sent to the Fort Sill Museum where Morgan Otis was a volunteer honorary associate curator. There is no documentary evidence concerning how and when these items entered the museum\\'s collections. Human teeth representing, at minimum, one individual were included in the collection. Morgan Otis was the great nephew of Chief Big-Bow, a Kiowa Chief, and documentation records his ancestry as Kiowa. Historical records also indicate that he was also related to Spotted Wolf, who was Southern Arapaho. No lineal descendents have been identified. The 322 associated funerary objects consist of 311 beads of various types and colors, 1 ceramic disk, 1 metal key, 2 buttons, 2 metal tokens, 3 copper rings and 2 copper bracelets.\\n        Determinations Made by the Fort Sill National Historic Landmark and Museum\\n        Officials of the Fort Sill National Historic Landmark and Museum have determined that:\\n        \\xe2\\x80\\xa2 Pursuant to 25 U.S.C. 3001(9), the human remains described in this notice represent the physical remains of one individual of Native American ancestry.\\n        \\xe2\\x80\\xa2 Pursuant to 25 U.S.C. 3001(3)(A), the 322 objects described in this notice are reasonably believed to have been placed with or near individual human remains at the time of death or later as part of the death rite or ceremony.\\n        \\xe2\\x80\\xa2 Pursuant to 25 U.S.C. 3001(2), there is a relationship of shared group identity that can be reasonably traced between the Native American human remains and associated funerary objects and the Cheyenne and Arapaho Tribes, Oklahoma (previously listed as Cheyenne-Arapaho Tribes of Oklahoma) and the Kiowa Indian Tribe of Oklahoma.\\n        Additional Requestors and Disposition\\n\\n        Lineal descendants or representatives of any Indian tribe or Native Hawaiian organization not identified in this notice that wish to request transfer of control of these human remains and associated funerary objects should submit a written request with information in support of the request to Dr. Scott A. Neel, Director, Fort Sill National Historic Landmark and Museum, U.S. Army Fires Center of Excellence, Fort Sill, OK 73503, telephone (580) 442-6570, email scott.a.neel2.civ@mail.mil, by October 10, 2014. After that date, if no additional requestors have come forward, transfer of control of the human remains and associated funerary objects to the Cheyenne and Arapaho Tribes, Oklahoma (previously listed as Cheyenne-Arapaho Tribes of Oklahoma) and the Kiowa Indian Tribe of Oklahoma may proceed.\\n        The Fort Sill National Historic Landmark and Museum is responsible for notifying the Apache Tribe of Oklahoma; Caddo Nation of Oklahoma; Cheyenne and Arapaho Tribes, Oklahoma (previously listed as Cheyenne-Arapaho Tribes of Oklahoma); Comanche Nation, Oklahoma; Delaware Nation, Oklahoma; Fort Sill Apache Tribe of Oklahoma; Kiowa Indian Tribe of Oklahoma; The Chickasaw Nation; and the Wichita and Affiliated Tribes (Wichita, Keechi, Waco & Tawakonie), Oklahoma, that this notice has been published.\\n        \\n          Dated: July 17, 2014.\\n          Melanie O\\'Brien,\\n          Acting Manager, National NAGPRA Program. \\n        \\n      \\n      [FR Doc. 2014-21531 Filed 9-9-14; 8:45 am]\\n      BILLING CODE 4312-50-P\\n    ", "agency1": "DEPARTMENT OF THE INTERIOR", "sub_agency1": "National Park Service", "dep_doc": "[NPS-WASO-NAGPRA-16306; PPWOCRADN0-PCU00RP14.R50000]", "subject": "Notice of Inventory Completion: U.S. Department of Defense, Army, Fort Sill National Historic Landmark and Museum, Fort Sill, OK", "agency2": "National Park Service, Interior.", "action": "Notice.", "summary": "The Fort Sill National Historic Landmark and Museum has completed an inventory of human remains and associated funerary objects, in consultation with the appropriate Indian tribes or Native Hawaiian organizations, and has determined that there is a cultural affiliation between the human remains and associated funerary objects and present-day Indian tribes or Native Hawaiian organizations. Lineal descendants or representatives of any Indian tribe or Native Hawaiian organization not identified in this notice that wish to request transfer of control of these human remains and associated funerary objects should submit a written request to the Fort Sill National Historic Landmark and Museum. If no additional requestors come forward, transfer of control of the human remains and associated funerary objects to the lineal descendants, Indian tribes, or Native Hawaiian organizations stated in this notice may proceed.", "dates": "Lineal descendants or representatives of any Indian tribe or Native Hawaiian organization not identified in this notice that wish to request transfer of control of these human remains and associated funerary objects should submit a written request with information in support of the request to the Fort Sill National Historic Landmark and Museum at the address in this notice by October 10, 2014.", "addresses": "Dr. Scott A. Neel, Director, Fort Sill National Historic Landmark and Museum, U.S. Army Fires Center of Excellence, Fort Sill, OK 73503, telephone (580) 442-6570, email scott.a.neel2.civ@mail.mil.\\n          ", "signature_dated": "Dated: July 17, 2014.", "signature_name": "Melanie O\\'Brien,", "signature_title": "Acting Manager, National NAGPRA Program. ", "fr_doc": "[FR Doc. 2014-21531 Filed 9-9-14; 8:45 am]", "billing_code": "BILLING CODE 4312-50-P", "supp_info": "SUPPLEMENTARY INFORMATION: \n Notice is here given in accordance with the Native American Graves Protection and Repatriation Act (NAGPRA), 25 U.S.C. 3003, of the completion of an inventory of human remains and associated funerary objects under the control of the Fort Sill National Historic Landmark and Museum, Fort Sill, OK. \n This notice is published as part of the National Park Service\\'s administrative responsibilities under NAGPRA, 25 U.S.C. 3003(d)(3). The determinations in this notice are the sole responsibility of the museum, institution, or Federal agency that has control of the Native American human remains and associated funerary objects. The National Park Service is not responsible for the determinations in this notice. \n Consultation \n A detailed assessment of the human remains was made by the Fort Sill National Historic Landmark and Museum and Fort Sill Environmental Quality Division professional staff in consultation with representatives of the Apache Tribe of Oklahoma; Caddo Nation of Oklahoma; Cheyenne and Arapaho Tribes, Oklahoma (previously listed as Cheyenne-Arapaho Tribes of Oklahoma); Comanche Nation, Oklahoma; Delaware Nation, Oklahoma; Fort Sill Apache Tribe of Oklahoma; Kiowa Indian Tribe of Oklahoma; The Chickasaw Nation; and the Wichita and Affiliated Tribes (Wichita, Keechi, Waco & Tawakonie), Oklahoma. \n History and Description of the Remains \n In 1966, Morgan Otis died in a car accident in California, and he was interred in the Fort Sill Post Cemetery shortly thereafter. A collection of items were recovered from the vehicle and later sent to the Fort Sill Museum where Morgan Otis was a volunteer honorary associate curator. There is no documentary evidence concerning how and when these items entered the museum\\'s collections. Human teeth representing, at minimum, one individual were included in the collection. Morgan Otis was the great nephew of Chief Big-Bow, a Kiowa Chief, and documentation records his ancestry as Kiowa. Historical records also indicate that he was also related to Spotted Wolf, who was Southern Arapaho. No lineal descendents have been identified. The 322 associated funerary objects consist of 311 beads of various types and colors, 1 ceramic disk, 1 metal key, 2 buttons, 2 metal tokens, 3 copper rings and 2 copper bracelets. \n Determinations Made by the Fort Sill National Historic Landmark and Museum \n Officials of the Fort Sill National Historic Landmark and Museum have determined that: \n \\xe2\\x80\\xa2 Pursuant to 25 U.S.C. 3001(9), the human remains described in this notice represent the physical remains of one individual of Native American ancestry. \n \\xe2\\x80\\xa2 Pursuant to 25 U.S.C. 3001(3)(A), the 322 objects described in this notice are reasonably believed to have been placed with or near individual human remains at the time of death or later as part of the death rite or ceremony. \n \\xe2\\x80\\xa2 Pursuant to 25 U.S.C. 3001(2), there is a relationship of shared group identity that can be reasonably traced between the Native American human remains and associated funerary objects and the Cheyenne and Arapaho Tribes, Oklahoma (previously listed as Cheyenne-Arapaho Tribes of Oklahoma) and the Kiowa Indian Tribe of Oklahoma. \n Additional Requestors and Disposition \n Lineal descendants or representatives of any Indian tribe or Native Hawaiian organization not identified in this notice that wish to request transfer of control of these human remains and associated funerary objects should submit a written request with information in support of the request to Dr. Scott A. Neel, Director, Fort Sill National Historic Landmark and Museum, U.S. Army Fires Center of Excellence, Fort Sill, OK 73503, telephone (580) 442-6570, email scott.a.neel2.civ@mail.mil, by October 10, 2014. After that date, if no additional requestors have come forward, transfer of control of the human remains and associated funerary objects to the Cheyenne and Arapaho Tribes, Oklahoma (previously listed as Cheyenne-Arapaho Tribes of Oklahoma) and the Kiowa Indian Tribe of Oklahoma may proceed. \n The Fort Sill National Historic Landmark and Museum is responsible for notifying the Apache Tribe of Oklahoma; Caddo Nation of Oklahoma; Cheyenne and Arapaho Tribes, Oklahoma (previously listed as Cheyenne-Arapaho Tribes of Oklahoma); Comanche Nation, Oklahoma; Delaware Nation, Oklahoma; Fort Sill Apache Tribe of Oklahoma; Kiowa Indian Tribe of Oklahoma; The Chickasaw Nation; and the Wichita and Affiliated Tribes (Wichita, Keechi, Waco & Tawakonie), Oklahoma, that this notice has been published. \n ", "consultation": "A detailed assessment of the human remains was made by the Fort Sill National Historic Landmark and Museum and Fort Sill Environmental Quality Division professional staff in consultation with representatives of the Apache Tribe of Oklahoma; Caddo Nation of Oklahoma; Cheyenne and Arapaho Tribes, Oklahoma (previously listed as Cheyenne-Arapaho Tribes of Oklahoma); Comanche Nation, Oklahoma; Delaware Nation, Oklahoma; Fort Sill Apache Tribe of Oklahoma; Kiowa Indian Tribe of Oklahoma; The Chickasaw Nation; and the Wichita and Affiliated Tribes (Wichita, Keechi, Waco & Tawakonie), Oklahoma. \n ", "h_d_r": "In 1966, Morgan Otis died in a car accident in California, and he was interred in the Fort Sill Post Cemetery shortly thereafter. A collection of items were recovered from the vehicle and later sent to the Fort Sill Museum where Morgan Otis was a volunteer honorary associate curator. There is no documentary evidence concerning how and when these items entered the museum\\'s collections. Human teeth representing, at minimum, one individual were included in the collection. Morgan Otis was the great nephew of Chief Big-Bow, a Kiowa Chief, and documentation records his ancestry as Kiowa. Historical records also indicate that he was also related to Spotted Wolf, who was Southern Arapaho. No lineal descendents have been identified. The 322 associated funerary objects consist of 311 beads of various types and colors, 1 ceramic disk, 1 metal key, 2 buttons, 2 metal tokens, 3 copper rings and 2 copper bracelets. \n ", "h_d_ci": "Null", "determinations": "Determinations Made by the Fort Sill National Historic Landmark and Museum \n Officials of the Fort Sill National Historic Landmark and Museum have determined that: \n \\xe2\\x80\\xa2 Pursuant to 25 U.S.C. 3001(9), the human remains described in this notice represent the physical remains of one individual of Native American ancestry. \n \\xe2\\x80\\xa2 Pursuant to 25 U.S.C. 3001(3)(A), the 322 objects described in this notice are reasonably believed to have been placed with or near individual human remains at the time of death or later as part of the death rite or ceremony. \n \\xe2\\x80\\xa2 Pursuant to 25 U.S.C. 3001(2), there is a relationship of shared group identity that can be reasonably traced between the Native American human remains and associated funerary objects and the Cheyenne and Arapaho Tribes, Oklahoma (previously listed as Cheyenne-Arapaho Tribes of Oklahoma) and the Kiowa Indian Tribe of Oklahoma. \n ", "a_r_d": "Lineal descendants or representatives of any Indian tribe or Native Hawaiian organization not identified in this notice that wish to request transfer of control of these human remains and associated funerary objects should submit a written request with information in support of the request to Dr. Scott A. Neel, Director, Fort Sill National Historic Landmark and Museum, U.S. Army Fires Center of Excellence, Fort Sill, OK 73503, telephone (580) 442-6570, email scott.a.neel2.civ@mail.mil, by October 10, 2014. After that date, if no additional requestors have come forward, transfer of control of the human remains and associated funerary objects to the Cheyenne and Arapaho Tribes, Oklahoma (previously listed as Cheyenne-Arapaho Tribes of Oklahoma) and the Kiowa Indian Tribe of Oklahoma may proceed. \n The Fort Sill National Historic Landmark and Museum is responsible for notifying the Apache Tribe of Oklahoma; Caddo Nation of Oklahoma; Cheyenne and Arapaho Tribes, Oklahoma (previously listed as Cheyenne-Arapaho Tribes of Oklahoma); Comanche Nation, Oklahoma; Delaware Nation, Oklahoma; Fort Sill Apache Tribe of Oklahoma; Kiowa Indian Tribe of Oklahoma; The Chickasaw Nation; and the Wichita and Affiliated Tribes (Wichita, Keechi, Waco & Tawakonie), Oklahoma, that this notice has been published. \n "}