{"index": "I_77", "messy_full": "\\n      \\n        \\n        DEPARTMENT OF THE INTERIOR\\n        National Park Service\\n        [NPS-WASO-NAGPRA-NPS0028045; PPWOCRADN0-PCU00RP14.R50000]\\n        Notice of Inventory Completion: Department of Anthropology, Southern Methodist University, Dallas, TX\\n        \\n          AGENCY:\\n          National Park Service, Interior.\\n        \\n        \\n          ACTION:\\n          Notice.\\n        \\n        \\n          SUMMARY:\\n          The Department of Anthropology, Southern Methodist University has completed an inventory of human remains, in consultation with the appropriate Indian Tribes or Native Hawaiian organizations, and has determined that there is a cultural affiliation between the human remains and present-day Indian Tribes or Native Hawaiian organizations. Lineal descendants or representatives of any Indian Tribe or Native Hawaiian organization not identified in this notice that wish to request transfer of control of these human remains should submit a written request to the Department of Anthropology, Southern Methodist University. If no additional requestors come forward, transfer of control of the human remains to the lineal descendants, Indian Tribes, or Native Hawaiian organizations stated in this notice may proceed.\\n        \\n        \\n          DATES:\\n          Lineal descendants or representatives of any Indian Tribe or Native Hawaiian organization not identified in this notice that wish to request transfer of control of these human remains should submit a written request with information in support of the request to the Department of Anthropology, Southern Methodist University at the address in this notice by July 15, 2019.\\n        \\n        \\n          ADDRESSES:\\n\\n          B. Sunday Eiselt, Department of Anthropology, Southern Methodist University, 3225 Daniel Avenue, Heroy Hall #450, Dallas, TX 75205, telephone (214) 768-2915, email seiselt@smu.edu.\\n          \\n        \\n      \\n      \\n        SUPPLEMENTARY INFORMATION:\\n        Notice is here given in accordance with the Native American Graves Protection and Repatriation Act (NAGPRA), 25 U.S.C. 3003, of the completion of an inventory of human remains under the control of the Department of Anthropology, Southern Methodist University, Dallas, TX. The human remains were removed from the Upper Tucker Site (X41MU17/41MU17), in Montague County, TX.\\n        This notice is published as part of the National Park Service\\'s administrative responsibilities under NAGPRA, 25 U.S.C. 3003(d)(3). The determinations in this notice are the sole responsibility of the museum, institution, or Federal agency that has control of the Native American human remains. The National Park Service is not responsible for the determinations in this notice.\\n        Consultation\\n        A detailed assessment of the human remains was made by the Department of Anthropology, Southern Methodist University professional staff in consultation with representatives of the Wichita and Affiliated Tribes (Wichita, Keechi, Waco & Tawakonie), Oklahoma.\\n        History and Description of the Remains\\n        In 1965, human remains representing, at minimum, one individual were removed from the Upper Tucker Site, in Montague County, TX, as part of the Wichita Project excavation. Although no burials or human remains were reported for this site in any of the associated documentation, including the official published report, one human tooth is attributed to this site No known individuals were identified. No associated funerary objects are present.\\n        The Upper Tucker Site is dated to the late 18th century. Cultural affiliation is with the Wichita and Affiliated Tribes.\\n        Determinations Made by the Department of Anthropology, Southern Methodist University\\n        Officials of the Department of Anthropology, Southern Methodist University have determined that:\\n        \\xe2\\x80\\xa2 Pursuant to 25 U.S.C. 3001(9), the human remains described in this notice represent the physical remains of one individual of Native American ancestry.\\n        \\xe2\\x80\\xa2 Pursuant to 25 U.S.C. 3001(2), there is a relationship of shared group identity that can be reasonably traced between the Native American human remains and the  Wichita and Affiliated Tribes (Wichita, Keechi, Waco & Tawakonie), Oklahoma.\\n        Additional Requestors and Disposition\\n\\n        Lineal descendants or representatives of any Indian Tribe or Native Hawaiian organization not identified in this notice that wish to request transfer of control of these human remains should submit a written request with information in support of the request to B. Sunday Eiselt, Department of Anthropology, Southern Methodist University, 3225 Daniel Avenue, Heroy Hall #450, Dallas, TX 75205, telephone (214) 768-2915, email seiselt@smu.edu, by July 15, 2019. After that date, if no additional requestors have come forward, transfer of control of the human remains to the  Wichita and Affiliated Tribes (Wichita, Keechi, Waco & Tawakonie), Oklahoma may proceed.\\n        The Department of Anthropology, Southern Methodist University is responsible for notifying the Wichita and Affiliated Tribes (Wichita, Keechi, Waco & Tawakonie), Oklahoma that this notice has been published.\\n        \\n          Dated: May 28, 2019.\\n          Melanie O\\'Brien,\\n          Manager, National NAGPRA Program.\\n        \\n      \\n      [FR Doc. 2019-12466 Filed 6-12-19; 8:45 am]\\n       BILLING CODE 4312-52-P\\n    ", "agency1": "DEPARTMENT OF THE INTERIOR", "sub_agency1": "National Park Service", "dep_doc": "[NPS-WASO-NAGPRA-NPS0028045; PPWOCRADN0-PCU00RP14.R50000]", "subject": "Notice of Inventory Completion: Department of Anthropology, Southern Methodist University, Dallas, TX", "agency2": "National Park Service, Interior.", "action": "Notice.", "summary": "The Department of Anthropology, Southern Methodist University has completed an inventory of human remains, in consultation with the appropriate Indian Tribes or Native Hawaiian organizations, and has determined that there is a cultural affiliation between the human remains and present-day Indian Tribes or Native Hawaiian organizations. Lineal descendants or representatives of any Indian Tribe or Native Hawaiian organization not identified in this notice that wish to request transfer of control of these human remains should submit a written request to the Department of Anthropology, Southern Methodist University. If no additional requestors come forward, transfer of control of the human remains to the lineal descendants, Indian Tribes, or Native Hawaiian organizations stated in this notice may proceed.", "dates": "Lineal descendants or representatives of any Indian Tribe or Native Hawaiian organization not identified in this notice that wish to request transfer of control of these human remains should submit a written request with information in support of the request to the Department of Anthropology, Southern Methodist University at the address in this notice by July 15, 2019.", "addresses": "B. Sunday Eiselt, Department of Anthropology, Southern Methodist University, 3225 Daniel Avenue, Heroy Hall #450, Dallas, TX 75205, telephone (214) 768-2915, email seiselt@smu.edu.\\n          ", "signature_dated": "Dated: May 28, 2019.", "signature_name": "Melanie O\\'Brien,", "signature_title": "Manager, National NAGPRA Program.", "fr_doc": "[FR Doc. 2019-12466 Filed 6-12-19; 8:45 am]", "billing_code": " BILLING CODE 4312-52-P", "supp_info": "SUPPLEMENTARY INFORMATION: \n Notice is here given in accordance with the Native American Graves Protection and Repatriation Act (NAGPRA), 25 U.S.C. 3003, of the completion of an inventory of human remains under the control of the Department of Anthropology, Southern Methodist University, Dallas, TX. The human remains were removed from the Upper Tucker Site (X41MU17/41MU17), in Montague County, TX. \n This notice is published as part of the National Park Service\\'s administrative responsibilities under NAGPRA, 25 U.S.C. 3003(d)(3). The determinations in this notice are the sole responsibility of the museum, institution, or Federal agency that has control of the Native American human remains. The National Park Service is not responsible for the determinations in this notice. \n Consultation \n A detailed assessment of the human remains was made by the Department of Anthropology, Southern Methodist University professional staff in consultation with representatives of the Wichita and Affiliated Tribes (Wichita, Keechi, Waco & Tawakonie), Oklahoma. \n History and Description of the Remains \n In 1965, human remains representing, at minimum, one individual were removed from the Upper Tucker Site, in Montague County, TX, as part of the Wichita Project excavation. Although no burials or human remains were reported for this site in any of the associated documentation, including the official published report, one human tooth is attributed to this site No known individuals were identified. No associated funerary objects are present. \n The Upper Tucker Site is dated to the late 18th century. Cultural affiliation is with the Wichita and Affiliated Tribes. \n Determinations Made by the Department of Anthropology, Southern Methodist University \n Officials of the Department of Anthropology, Southern Methodist University have determined that: \n \\xe2\\x80\\xa2 Pursuant to 25 U.S.C. 3001(9), the human remains described in this notice represent the physical remains of one individual of Native American ancestry. \n \\xe2\\x80\\xa2 Pursuant to 25 U.S.C. 3001(2), there is a relationship of shared group identity that can be reasonably traced between the Native American human remains and the  Wichita and Affiliated Tribes (Wichita, Keechi, Waco & Tawakonie), Oklahoma. \n Additional Requestors and Disposition \n Lineal descendants or representatives of any Indian Tribe or Native Hawaiian organization not identified in this notice that wish to request transfer of control of these human remains should submit a written request with information in support of the request to B. Sunday Eiselt, Department of Anthropology, Southern Methodist University, 3225 Daniel Avenue, Heroy Hall #450, Dallas, TX 75205, telephone (214) 768-2915, email seiselt@smu.edu, by July 15, 2019. After that date, if no additional requestors have come forward, transfer of control of the human remains to the  Wichita and Affiliated Tribes (Wichita, Keechi, Waco & Tawakonie), Oklahoma may proceed. \n The Department of Anthropology, Southern Methodist University is responsible for notifying the Wichita and Affiliated Tribes (Wichita, Keechi, Waco & Tawakonie), Oklahoma that this notice has been published. \n ", "consultation": "A detailed assessment of the human remains was made by the Department of Anthropology, Southern Methodist University professional staff in consultation with representatives of the Wichita and Affiliated Tribes (Wichita, Keechi, Waco & Tawakonie), Oklahoma. \n ", "h_d_r": "In 1965, human remains representing, at minimum, one individual were removed from the Upper Tucker Site, in Montague County, TX, as part of the Wichita Project excavation. Although no burials or human remains were reported for this site in any of the associated documentation, including the official published report, one human tooth is attributed to this site No known individuals were identified. No associated funerary objects are present. \n The Upper Tucker Site is dated to the late 18th century. Cultural affiliation is with the Wichita and Affiliated Tribes. \n ", "h_d_ci": "Null", "determinations": "Determinations Made by the Department of Anthropology, Southern Methodist University \n Officials of the Department of Anthropology, Southern Methodist University have determined that: \n \\xe2\\x80\\xa2 Pursuant to 25 U.S.C. 3001(9), the human remains described in this notice represent the physical remains of one individual of Native American ancestry. \n \\xe2\\x80\\xa2 Pursuant to 25 U.S.C. 3001(2), there is a relationship of shared group identity that can be reasonably traced between the Native American human remains and the  Wichita and Affiliated Tribes (Wichita, Keechi, Waco & Tawakonie), Oklahoma. \n ", "a_r_d": "Lineal descendants or representatives of any Indian Tribe or Native Hawaiian organization not identified in this notice that wish to request transfer of control of these human remains should submit a written request with information in support of the request to B. Sunday Eiselt, Department of Anthropology, Southern Methodist University, 3225 Daniel Avenue, Heroy Hall #450, Dallas, TX 75205, telephone (214) 768-2915, email seiselt@smu.edu, by July 15, 2019. After that date, if no additional requestors have come forward, transfer of control of the human remains to the  Wichita and Affiliated Tribes (Wichita, Keechi, Waco & Tawakonie), Oklahoma may proceed. \n The Department of Anthropology, Southern Methodist University is responsible for notifying the Wichita and Affiliated Tribes (Wichita, Keechi, Waco & Tawakonie), Oklahoma that this notice has been published. \n "}