{"index": "I_781", "messy_full": "\\n      \\n        DEPARTMENT OF THE INTERIOR\\n        National Park Service\\n        [NPS-WASO-CR-16552; PPWOCRADI0, PCU00RP14.R50000]\\n        Information Collection Request Sent to the Office of Management and Budget (OMB) for Approval; Procedures for State, Tribal, and Local Government Historic Preservation Programs\\n        \\n          AGENCY:\\n          National Park Service, Interior.\\n        \\n        \\n          ACTION:\\n          Notice; request for comments.\\n        \\n        \\n          SUMMARY:\\n          We (National Park Service) have sent an Information Collection Request (ICR) to OMB for review and approval. We summarize the ICR below and describe the nature of the collection and the estimated burden and cost. This information collection is scheduled to expire on August 31, 2014. We may not conduct or sponsor and a person is not required to respond to a collection of information unless it displays a currently valid OMB control number. However, under OMB regulations, we may continue to conduct or sponsor this information collection while it is pending at OMB.\\n        \\n        \\n          DATES:\\n          You must submit comments on or before September 29, 2014.\\n        \\n        \\n          ADDRESSES:\\n\\n          Send your comments and suggestions on this information collection to the Desk Officer for the Department of the Interior at OMB\\xe2\\x80\\x94OIRA at (202) 395-5806 (fax) or OIRA_Submission@omb.eop.gov (email). Please provide a copy of your comments to Madonna L. Baucum, Information Collection Clearance Officer, National Park Service, 1849 C Street NW. (2601), Washington, DC 20240 (mail); or madonna_baucum@nps.gov (email). Please include \\xe2\\x80\\x9c1024-0038\\xe2\\x80\\x9d in the subject line of your comments.\\n        \\n        \\n          FOR FURTHER INFORMATION CONTACT:\\n\\n          To request additional information about this ICR, contact John Renaud at John_Renaud@nps.gov (email) or at (202) 371-1961 (fax). You may review the ICR online at http://www.reginfo.gov. Follow the instructions to review Department of the Interior collections under review by OMB.\\n        \\n      \\n      \\n        SUPPLEMENTARY INFORMATION:\\n        \\n        \\n          OMB Control Number: 1024-0038.\\n        \\n          Title: Procedures for State, Tribal, and Local Government Historic Preservation Programs, 36 CFR 61.\\n        \\n          Service Form Number(s): None.\\n        \\n          Type of Request: Revision of a currently approved collection.\\n        \\n          Description of Respondents: State, tribal, and local governments.\\n        \\n          Respondent\\'s Obligation: Required to obtain or retain a benefit.\\n        \\n          Frequency of Collection: Annually or on occasion.\\n        \\n          \\xe2\\x80\\x83\\n          \\n            Activity\\n            Annualnumber of\\n              responses\\n            \\n            Completion time perresponse\\n              (hours)\\n            \\n            Total annual burden hours\\n          \\n          \\n            Local Government Certification Application/Agreement\\n            40\\n            39.75\\n            1,590\\n          \\n          \\n            Certified Local Government Monitoring\\n            1,860\\n            7.25\\n            13,485\\n          \\n          \\n            Certified Local Government Evaluations\\n            465\\n            12.00\\n            5,580\\n          \\n          \\n            Baseline Questionnaire for CLGs\\n            250\\n            6.00\\n            1,500\\n          \\n          \\n            Annual Achievements Report for CLGs\\n            1,000\\n            2.00\\n            2,000\\n          \\n          \\n            State Inventory Maintenance\\n            26,904\\n            .25\\n            6,726\\n          \\n          \\n            State Technical Assistance to Federal Agencies (Review & Compliance)\\n            25,370\\n            .25\\n            6,343\\n          \\n          \\n            Statewide Historic Preservation Plan\\n            14\\n            797.00\\n            11,158\\n          \\n          \\n            State Program Review\\n            15\\n            90.00\\n            1,350\\n          \\n          \\n            State Cumulative Products Table\\n            89\\n            10.00\\n            890\\n          \\n          \\n            State Organization Chart and Staffing Summary\\n            30\\n            2.00\\n            60\\n          \\n          \\n            State Anticipated Activities List\\n            30\\n            5.75\\n            173\\n          \\n          \\n            State Project Notification\\n            59\\n            1.50\\n            89\\n          \\n          \\n            State Final Project Report\\n            59\\n            1.00\\n            59\\n          \\n          \\n            State Project/Activity Database Report\\n            59\\n            18.25\\n            1,077\\n          \\n          \\n            State Sources of Non-Federal Matching Share Report\\n            52\\n            2.25\\n            117\\n          \\n          \\n            State Significant Preservation Accomplishments Summary\\n            59\\n            3.75\\n            221\\n          \\n          \\n            Annual Achievements Report for States\\n            25\\n            2.25\\n            56\\n          \\n          \\n            Tribal Historic Preservation Office (THPO) Grants Product Summary Page\\n            150\\n            15.50\\n            2,325\\n          \\n          \\n            THPO Annual Report\\n            150\\n            23.00\\n            3,450\\n          \\n          \\n            Total\\n            56,680\\n            \\n            58,249\\n          \\n        \\n        \\n          Estimated Annual Nonhour Burden Cost: $90,836.\\n        Comments:\\n        On April 17, 2014, we published in the Federal Register (79 FR 21792) a notice of our intent to request that OMB renew approval for this information collection. In that notice, we solicited comments for 60 days, ending on June 16, 2014. We did not receive any comments in response to this notice.\\n        We again invite comments concerning this information collection on:\\n        \\xe2\\x80\\xa2 Whether or not the collection of information is necessary, including whether or not the information will have practical utility;\\n        \\xe2\\x80\\xa2 The accuracy of our estimate of the burden for this collection of information;\\n        \\xe2\\x80\\xa2 Ways to enhance the quality, utility, and clarity of the information to be collected; and\\n        \\xe2\\x80\\xa2 Ways to minimize the burden of the collection of information on respondents.\\n        Comments that you submit in response to this notice are a matter of public record. Before including your address, phone number, email address, or other personal identifying information in your comment, you should be aware that your entire comment, including your personal identifying information, may be made publicly available at any time. While you can ask OMB in your comment to withhold your personal identifying information from public review, we cannot guarantee that it will be done.\\n        \\n          Dated: August 25, 2014.\\n          Madonna L. Baucum,\\n          Information Collection Clearance Officer, National Park Service.\\n        \\n      \\n      [FR Doc. 2014-20621 Filed 8-28-14; 8:45 am]\\n      BILLING CODE 4310-EH-P\\n    ", "agency1": "DEPARTMENT OF THE INTERIOR", "sub_agency1": "National Park Service", "dep_doc": "[NPS-WASO-CR-16552; PPWOCRADI0, PCU00RP14.R50000]", "subject": "Information Collection Request Sent to the Office of Management and Budget (OMB) for Approval; Procedures for State, Tribal, and Local Government Historic Preservation Programs", "agency2": "National Park Service, Interior.", "action": "Notice; request for comments.", "summary": "We (National Park Service) have sent an Information Collection Request (ICR) to OMB for review and approval. We summarize the ICR below and describe the nature of the collection and the estimated burden and cost. This information collection is scheduled to expire on August 31, 2014. We may not conduct or sponsor and a person is not required to respond to a collection of information unless it displays a currently valid OMB control number. However, under OMB regulations, we may continue to conduct or sponsor this information collection while it is pending at OMB.", "dates": "You must submit comments on or before September 29, 2014.", "addresses": "Send your comments and suggestions on this information collection to the Desk Officer for the Department of the Interior at OMB\\xe2\\x80\\x94OIRA at (202) 395-5806 (fax) or OIRA_Submission@omb.eop.gov (email). Please provide a copy of your comments to Madonna L. Baucum, Information Collection Clearance Officer, National Park Service, 1849 C Street NW. (2601), Washington, DC 20240 (mail); or madonna_baucum@nps.gov (email). Please include \\xe2\\x80\\x9c1024-0038\\xe2\\x80\\x9d in the subject line of your comments.", "signature_dated": "Dated: August 25, 2014.", "signature_name": "Madonna L. Baucum,", "signature_title": "Information Collection Clearance Officer, National Park Service.", "fr_doc": "[FR Doc. 2014-20621 Filed 8-28-14; 8:45 am]", "billing_code": "BILLING CODE 4310-EH-P", "supp_info": "SUPPLEMENTARY INFORMATION: \n  \n \\n          OMB Control Number: 1024-0038. \n \\n          Title: Procedures for State, Tribal, and Local Government Historic Preservation Programs, 36 CFR 61. \n \\n          Service Form Number(s): None. \n \\n          Type of Request: Revision of a currently approved collection. \n \\n          Description of Respondents: State, tribal, and local governments. \n \\n          Respondent\\'s Obligation: Required to obtain or retain a benefit. \n \\n          Frequency of Collection: Annually or on occasion. \n \\n          Estimated Annual Nonhour Burden Cost: $90,836. \n Comments: \n On April 17, 2014, we published in the Federal Register (79 FR 21792) a notice of our intent to request that OMB renew approval for this information collection. In that notice, we solicited comments for 60 days, ending on June 16, 2014. We did not receive any comments in response to this notice. \n We again invite comments concerning this information collection on: \n \\xe2\\x80\\xa2 Whether or not the collection of information is necessary, including whether or not the information will have practical utility; \n \\xe2\\x80\\xa2 The accuracy of our estimate of the burden for this collection of information; \n \\xe2\\x80\\xa2 Ways to enhance the quality, utility, and clarity of the information to be collected; and \n \\xe2\\x80\\xa2 Ways to minimize the burden of the collection of information on respondents. \n Comments that you submit in response to this notice are a matter of public record. Before including your address, phone number, email address, or other personal identifying information in your comment, you should be aware that your entire comment, including your personal identifying information, may be made publicly available at any time. While you can ask OMB in your comment to withhold your personal identifying information from public review, we cannot guarantee that it will be done. \n ", "consultation": "Null", "h_d_r": "Null", "h_d_ci": "Null", "determinations": "Null", "a_r_d": "Null"}