{"index": "I_816", "messy_full": "\\n      \\n        DEPARTMENT OF THE INTERIOR\\n        National Park Service\\n        [NPS-WASO-NAGPRA-15676; PPWOCRADN0-PCU00RP14.R50000]\\n        Notice of Inventory Completion: State Historical Society of Wisconsin, Madison, WI\\n        \\n          AGENCY:\\n          National Park Service, Interior.\\n        \\n        \\n          ACTION:\\n          Notice.\\n        \\n        \\n          SUMMARY:\\n          The State Historical Society of Wisconsin has completed an inventory of human remains, in consultation with the appropriate Indian tribes or Native Hawaiian organizations, and has determined that there is no cultural affiliation between the human remains and any present-day Indian tribes or Native Hawaiian organizations. Representatives of any Indian tribe or Native Hawaiian organization not identified in this notice that wish to request transfer of control of these human remains should submit a written request to the State Historical Society of Wisconsin. If no additional requestors come forward, transfer of control of the human remains to the Indian tribes or Native Hawaiian organizations stated in this notice may proceed.\\n        \\n        \\n          DATES:\\n          Representatives of any Indian tribe or Native Hawaiian organization not identified in this notice that wish to request transfer of control of these human remains should submit a written request with information in support of the request to the State Historical Society of Wisconsin at the address in this notice by July 9, 2014.\\n        \\n        \\n          ADDRESSES:\\n\\n          Jennifer Kolb, Wisconsin Historical Museum, 30 North Carroll Street, Madison, WI 53703, telephone (608) 261-2461, email Jennifer.Kolb@wisconsinhistory.org.\\n          \\n        \\n      \\n      \\n        SUPPLEMENTARY INFORMATION:\\n        Notice is here given in accordance with the Native American Graves Protection and Repatriation Act (NAGPRA), 25 U.S.C. 3003, of the completion of an inventory of human remains under the control of the State Historical Society of Wisconsin, Madison, WI. The human remains were removed from the Point Sauble site, Brown County, WI.\\n        This notice is published as part of the National Park Service\\'s administrative responsibilities under NAGPRA, 25 U.S.C. 3003(d)(3) and 43 CFR 10.11(d). The determinations in this notice are the sole responsibility of the museum, institution, or Federal agency that has control of the Native American human remains. The National Park Service is not responsible for the determinations in this notice.\\n        Consultation\\n        A detailed assessment of the human remains was made by the State Historical Society of Wisconsin professional staff in consultation with representatives of the Forest County Potawatomi Community, Wisconsin; Ho-Chunk Nation of Wisconsin; and the Menominee Indian Tribe of Wisconsin.\\n        History and Description of the Remains\\n        In 1990, human remains representing, at minimum, one individual (HP.BR-0101.1) were removed from the Point Sauble site (47-BR-0101) in Brown County, WI. The remains were discovered in a backfill pile of a sewer line installation during the State Highway 57 Improvement Project. An archeological consultant, the Brown County Sheriff\\'s Department, and the Brown County Coroner were contacted. The human remains were transferred to the State Historical Society\\'s Burial Sites Office. The human remains were determined to represent a young adult Native American male. No known individuals were identified. No associated funerary objects are present.\\n        Determinations Made by the State Historical Society of Wisconsin\\n        Officials of the State Historical Society of Wisconsin have determined that:\\n        \\xe2\\x80\\xa2 Pursuant to 25 U.S.C. 3001(9), the human remains described in this notice are Native American based on State Historical Society records, location and context of the burial sites, and skeletal analysis.\\n        \\xe2\\x80\\xa2 Pursuant to 25 U.S.C. 3001(9), the human remains described in this notice represent the physical remains of one individual of Native American ancestry.\\n        \\xe2\\x80\\xa2 Pursuant to 25 U.S.C. 3001(2), a relationship of shared group identity cannot be reasonably traced between the Native American human remains and any present-day Indian tribe.\\n        \\xe2\\x80\\xa2 According to final judgments of the Indian Claims Commission or the Court of Federal Claims, the land from which the Native American human remains were removed is the aboriginal land of the Forest County Potawatomi Community, Wisconsin.\\n        \\xe2\\x80\\xa2 Treaties, Acts of Congress, or Executive Orders, indicate that the land from which the Native American human remains were removed is the aboriginal land of the Bad River Band of the Lake Superior Tribe of Chippewa Indians of the Bad River Reservation, Wisconsin; Bay Mills Indian Community, Michigan; Bois Forte Band (Nett Lake) of the Minnesota Chippewa Tribe, Minnesota; Cayuga Nation; Chippewa-Cree Indians of the Rocky Boy\\'s Reservation, Montana; Fond du Lac Band of the Minnesota Chippewa Tribe, Minnesota; Grand Portage Band of the Minnesota Chippewa Tribe, Minnesota; Grand Traverse Band of Ottawa and Chippewa Indians, Michigan; Ho-Chunk Nation of Wisconsin; Keweenaw Bay Indian Community, Michigan; Lac Courte Oreilles Band of Lake Superior Chippewa Indians of Wisconsin; Lac du Flambeau Band of Lake Superior Chippewa Indians of the Lac du Flambeau Reservation of Wisconsin; Lac Vieux Desert Band of Lake Superior Chippewa Indians of Michigan; Leech Lake Band of the Minnesota Chippewa Tribe, Minnesota; Menominee Indian Tribe of Wisconsin; Mille Lacs Band of the Minnesota Chippewa Tribe, Minnesota; Minnesota Chippewa Tribe, Minnesota; Oneida Nation of New York; Onondago Nation; Red Cliff Band of Lake Superior Chippewa Indians of Wisconsin; Red Lake Band of Chippewa Indians, Minnesota; Saginaw Chippewa Indian Tribe of Michigan; Saint Regis Mohawk Tribe (previously listed as the St. Regis Band of Mohawk Indians of New York); Sault Ste. Marie Tribe of Chippewa Indians, Michigan; Seneca Nation of Indians (previously listed as the Seneca Nation of New York); Sokaogon Chippewa Community, Wisconsin; St. Croix Chippewa Indians of Wisconsin; Tonawanda Band of Seneca (previously listed as the Tonawanda Band of Seneca Indians of New York); Turtle Mountain Band of Chippewa Indians of North Dakota; Tuscarora Nation; White Earth Band of the Minnesota Chippewa Tribe, Minnesota; and the Winnebago Tribe of Nebraska (hereafter, with the Forest County Potawatomi Community, Wisconsin, referred to as \\xe2\\x80\\x9cThe Aboriginal Land Tribes\\xe2\\x80\\x9d).\\n        \\xe2\\x80\\xa2 Pursuant to 43 CFR 10.11(c)(1), the disposition of the human remains may be to The Aboriginal Land Tribes.\\n        Additional Requestors and Disposition\\n\\n        Representatives of any Indian tribe or Native Hawaiian organization not identified in this notice that wish to request transfer of control of these human remains should submit a written request with information in support of the request to Jennifer Kolb, Wisconsin Historical Museum, 30 North Carroll Street, Madison, WI 53703, telephone (608) 261-2461, email Jennifer.Kolb@wisconsinhistory.org, by July 9, 2014. After that date, if no additional requestors have come forward, transfer of control of the human remains to The Aboriginal Land Tribes may proceed.\\n        The State Historical Society of Wisconsin is responsible for notifying The Aboriginal Land Tribes that this notice has been published.\\n        \\n          Dated: April 24, 2014\\n          David Tarler,\\n          Acting Manager, National NAGPRA Program.\\n        \\n      \\n      [FR Doc. 2014-13361 Filed 6-6-14; 8:45 am]\\n      BILLING CODE 4312-50-P\\n    ", "agency1": "DEPARTMENT OF THE INTERIOR", "sub_agency1": "National Park Service", "dep_doc": "[NPS-WASO-NAGPRA-15676; PPWOCRADN0-PCU00RP14.R50000]", "subject": "Notice of Inventory Completion: State Historical Society of Wisconsin, Madison, WI", "agency2": "National Park Service, Interior.", "action": "Notice.", "summary": "The State Historical Society of Wisconsin has completed an inventory of human remains, in consultation with the appropriate Indian tribes or Native Hawaiian organizations, and has determined that there is no cultural affiliation between the human remains and any present-day Indian tribes or Native Hawaiian organizations. Representatives of any Indian tribe or Native Hawaiian organization not identified in this notice that wish to request transfer of control of these human remains should submit a written request to the State Historical Society of Wisconsin. If no additional requestors come forward, transfer of control of the human remains to the Indian tribes or Native Hawaiian organizations stated in this notice may proceed.", "dates": "Representatives of any Indian tribe or Native Hawaiian organization not identified in this notice that wish to request transfer of control of these human remains should submit a written request with information in support of the request to the State Historical Society of Wisconsin at the address in this notice by July 9, 2014.", "addresses": "Jennifer Kolb, Wisconsin Historical Museum, 30 North Carroll Street, Madison, WI 53703, telephone (608) 261-2461, email Jennifer.Kolb@wisconsinhistory.org.\\n          ", "signature_dated": "Dated: April 24, 2014", "signature_name": "David Tarler,", "signature_title": "Acting Manager, National NAGPRA Program.", "fr_doc": "[FR Doc. 2014-13361 Filed 6-6-14; 8:45 am]", "billing_code": "BILLING CODE 4312-50-P", "supp_info": "SUPPLEMENTARY INFORMATION: \n Notice is here given in accordance with the Native American Graves Protection and Repatriation Act (NAGPRA), 25 U.S.C. 3003, of the completion of an inventory of human remains under the control of the State Historical Society of Wisconsin, Madison, WI. The human remains were removed from the Point Sauble site, Brown County, WI. \n This notice is published as part of the National Park Service\\'s administrative responsibilities under NAGPRA, 25 U.S.C. 3003(d)(3) and 43 CFR 10.11(d). The determinations in this notice are the sole responsibility of the museum, institution, or Federal agency that has control of the Native American human remains. The National Park Service is not responsible for the determinations in this notice. \n Consultation \n A detailed assessment of the human remains was made by the State Historical Society of Wisconsin professional staff in consultation with representatives of the Forest County Potawatomi Community, Wisconsin; Ho-Chunk Nation of Wisconsin; and the Menominee Indian Tribe of Wisconsin. \n History and Description of the Remains \n In 1990, human remains representing, at minimum, one individual (HP.BR-0101.1) were removed from the Point Sauble site (47-BR-0101) in Brown County, WI. The remains were discovered in a backfill pile of a sewer line installation during the State Highway 57 Improvement Project. An archeological consultant, the Brown County Sheriff\\'s Department, and the Brown County Coroner were contacted. The human remains were transferred to the State Historical Society\\'s Burial Sites Office. The human remains were determined to represent a young adult Native American male. No known individuals were identified. No associated funerary objects are present. \n Determinations Made by the State Historical Society of Wisconsin \n Officials of the State Historical Society of Wisconsin have determined that: \n \\xe2\\x80\\xa2 Pursuant to 25 U.S.C. 3001(9), the human remains described in this notice are Native American based on State Historical Society records, location and context of the burial sites, and skeletal analysis. \n \\xe2\\x80\\xa2 Pursuant to 25 U.S.C. 3001(9), the human remains described in this notice represent the physical remains of one individual of Native American ancestry. \n \\xe2\\x80\\xa2 Pursuant to 25 U.S.C. 3001(2), a relationship of shared group identity cannot be reasonably traced between the Native American human remains and any present-day Indian tribe. \n \\xe2\\x80\\xa2 According to final judgments of the Indian Claims Commission or the Court of Federal Claims, the land from which the Native American human remains were removed is the aboriginal land of the Forest County Potawatomi Community, Wisconsin. \n \\xe2\\x80\\xa2 Treaties, Acts of Congress, or Executive Orders, indicate that the land from which the Native American human remains were removed is the aboriginal land of the Bad River Band of the Lake Superior Tribe of Chippewa Indians of the Bad River Reservation, Wisconsin; Bay Mills Indian Community, Michigan; Bois Forte Band (Nett Lake) of the Minnesota Chippewa Tribe, Minnesota; Cayuga Nation; Chippewa-Cree Indians of the Rocky Boy\\'s Reservation, Montana; Fond du Lac Band of the Minnesota Chippewa Tribe, Minnesota; Grand Portage Band of the Minnesota Chippewa Tribe, Minnesota; Grand Traverse Band of Ottawa and Chippewa Indians, Michigan; Ho-Chunk Nation of Wisconsin; Keweenaw Bay Indian Community, Michigan; Lac Courte Oreilles Band of Lake Superior Chippewa Indians of Wisconsin; Lac du Flambeau Band of Lake Superior Chippewa Indians of the Lac du Flambeau Reservation of Wisconsin; Lac Vieux Desert Band of Lake Superior Chippewa Indians of Michigan; Leech Lake Band of the Minnesota Chippewa Tribe, Minnesota; Menominee Indian Tribe of Wisconsin; Mille Lacs Band of the Minnesota Chippewa Tribe, Minnesota; Minnesota Chippewa Tribe, Minnesota; Oneida Nation of New York; Onondago Nation; Red Cliff Band of Lake Superior Chippewa Indians of Wisconsin; Red Lake Band of Chippewa Indians, Minnesota; Saginaw Chippewa Indian Tribe of Michigan; Saint Regis Mohawk Tribe (previously listed as the St. Regis Band of Mohawk Indians of New York); Sault Ste. Marie Tribe of Chippewa Indians, Michigan; Seneca Nation of Indians (previously listed as the Seneca Nation of New York); Sokaogon Chippewa Community, Wisconsin; St. Croix Chippewa Indians of Wisconsin; Tonawanda Band of Seneca (previously listed as the Tonawanda Band of Seneca Indians of New York); Turtle Mountain Band of Chippewa Indians of North Dakota; Tuscarora Nation; White Earth Band of the Minnesota Chippewa Tribe, Minnesota; and the Winnebago Tribe of Nebraska (hereafter, with the Forest County Potawatomi Community, Wisconsin, referred to as \\xe2\\x80\\x9cThe Aboriginal Land Tribes\\xe2\\x80\\x9d). \n \\xe2\\x80\\xa2 Pursuant to 43 CFR 10.11(c)(1), the disposition of the human remains may be to The Aboriginal Land Tribes. \n Additional Requestors and Disposition \n Representatives of any Indian tribe or Native Hawaiian organization not identified in this notice that wish to request transfer of control of these human remains should submit a written request with information in support of the request to Jennifer Kolb, Wisconsin Historical Museum, 30 North Carroll Street, Madison, WI 53703, telephone (608) 261-2461, email Jennifer.Kolb@wisconsinhistory.org, by July 9, 2014. After that date, if no additional requestors have come forward, transfer of control of the human remains to The Aboriginal Land Tribes may proceed. \n The State Historical Society of Wisconsin is responsible for notifying The Aboriginal Land Tribes that this notice has been published. \n ", "consultation": "A detailed assessment of the human remains was made by the State Historical Society of Wisconsin professional staff in consultation with representatives of the Forest County Potawatomi Community, Wisconsin; Ho-Chunk Nation of Wisconsin; and the Menominee Indian Tribe of Wisconsin. \n ", "h_d_r": "In 1990, human remains representing, at minimum, one individual (HP.BR-0101.1) were removed from the Point Sauble site (47-BR-0101) in Brown County, WI. The remains were discovered in a backfill pile of a sewer line installation during the State Highway 57 Improvement Project. An archeological consultant, the Brown County Sheriff\\'s Department, and the Brown County Coroner were contacted. The human remains were transferred to the State Historical Society\\'s Burial Sites Office. The human remains were determined to represent a young adult Native American male. No known individuals were identified. No associated funerary objects are present. \n ", "h_d_ci": "Null", "determinations": "Determinations Made by the State Historical Society of Wisconsin \n Officials of the State Historical Society of Wisconsin have determined that: \n \\xe2\\x80\\xa2 Pursuant to 25 U.S.C. 3001(9), the human remains described in this notice are Native American based on State Historical Society records, location and context of the burial sites, and skeletal analysis. \n \\xe2\\x80\\xa2 Pursuant to 25 U.S.C. 3001(9), the human remains described in this notice represent the physical remains of one individual of Native American ancestry. \n \\xe2\\x80\\xa2 Pursuant to 25 U.S.C. 3001(2), a relationship of shared group identity cannot be reasonably traced between the Native American human remains and any present-day Indian tribe. \n \\xe2\\x80\\xa2 According to final judgments of the Indian Claims Commission or the Court of Federal Claims, the land from which the Native American human remains were removed is the aboriginal land of the Forest County Potawatomi Community, Wisconsin. \n \\xe2\\x80\\xa2 Treaties, Acts of Congress, or Executive Orders, indicate that the land from which the Native American human remains were removed is the aboriginal land of the Bad River Band of the Lake Superior Tribe of Chippewa Indians of the Bad River Reservation, Wisconsin; Bay Mills Indian Community, Michigan; Bois Forte Band (Nett Lake) of the Minnesota Chippewa Tribe, Minnesota; Cayuga Nation; Chippewa-Cree Indians of the Rocky Boy\\'s Reservation, Montana; Fond du Lac Band of the Minnesota Chippewa Tribe, Minnesota; Grand Portage Band of the Minnesota Chippewa Tribe, Minnesota; Grand Traverse Band of Ottawa and Chippewa Indians, Michigan; Ho-Chunk Nation of Wisconsin; Keweenaw Bay Indian Community, Michigan; Lac Courte Oreilles Band of Lake Superior Chippewa Indians of Wisconsin; Lac du Flambeau Band of Lake Superior Chippewa Indians of the Lac du Flambeau Reservation of Wisconsin; Lac Vieux Desert Band of Lake Superior Chippewa Indians of Michigan; Leech Lake Band of the Minnesota Chippewa Tribe, Minnesota; Menominee Indian Tribe of Wisconsin; Mille Lacs Band of the Minnesota Chippewa Tribe, Minnesota; Minnesota Chippewa Tribe, Minnesota; Oneida Nation of New York; Onondago Nation; Red Cliff Band of Lake Superior Chippewa Indians of Wisconsin; Red Lake Band of Chippewa Indians, Minnesota; Saginaw Chippewa Indian Tribe of Michigan; Saint Regis Mohawk Tribe (previously listed as the St. Regis Band of Mohawk Indians of New York); Sault Ste. Marie Tribe of Chippewa Indians, Michigan; Seneca Nation of Indians (previously listed as the Seneca Nation of New York); Sokaogon Chippewa Community, Wisconsin; St. Croix Chippewa Indians of Wisconsin; Tonawanda Band of Seneca (previously listed as the Tonawanda Band of Seneca Indians of New York); Turtle Mountain Band of Chippewa Indians of North Dakota; Tuscarora Nation; White Earth Band of the Minnesota Chippewa Tribe, Minnesota; and the Winnebago Tribe of Nebraska (hereafter, with the Forest County Potawatomi Community, Wisconsin, referred to as \\xe2\\x80\\x9cThe Aboriginal Land Tribes\\xe2\\x80\\x9d). \n \\xe2\\x80\\xa2 Pursuant to 43 CFR 10.11(c)(1), the disposition of the human remains may be to The Aboriginal Land Tribes. \n ", "a_r_d": "Representatives of any Indian tribe or Native Hawaiian organization not identified in this notice that wish to request transfer of control of these human remains should submit a written request with information in support of the request to Jennifer Kolb, Wisconsin Historical Museum, 30 North Carroll Street, Madison, WI 53703, telephone (608) 261-2461, email Jennifer.Kolb@wisconsinhistory.org, by July 9, 2014. After that date, if no additional requestors have come forward, transfer of control of the human remains to The Aboriginal Land Tribes may proceed. \n The State Historical Society of Wisconsin is responsible for notifying The Aboriginal Land Tribes that this notice has been published. \n "}