{"index": "I_823", "messy_full": "\\n      \\n        DEPARTMENT OF THE INTERIOR\\n        National Park Service\\n        [NPS-WASO-NAGPRA-15410]; [PPWOCRADN0-PCU00RP14.R50000]\\n        Notice of Inventory Completion: University of Wisconsin-Madison, Department of Anthropology, Madison, WI\\n        \\n          AGENCY:\\n          National Park Service, Interior.\\n        \\n        \\n          ACTION:\\n          Notice.\\n        \\n        \\n          SUMMARY:\\n          The University of Wisconsin-Madison Department of Anthropology has completed an inventory of human remains and associated funerary objects, in consultation with the appropriate Indian tribes or Native Hawaiian organizations, and has determined that there is no cultural affiliation between the human remains and associated funerary objects and any present-day Indian tribes or Native Hawaiian organizations. Representatives of any Indian tribe or Native Hawaiian organization not identified in this notice that wish to request transfer of control of these human remains and associated funerary objects should submit a written request to the University of Wisconsin-Madison Department of Anthropology. If no additional requestors come forward, transfer of control of the human remains and associated funerary objects to the Indian tribes or Native Hawaiian organizations stated in this notice may proceed.\\n        \\n        \\n          DATES:\\n          Representatives of any Indian tribe or Native Hawaiian organization not identified in this notice that wish to request transfer of control of these human remains and associated funerary objects should submit a written request with information in support of the request to the University of Wisconsin-Madison Department of Anthropology at the address in this notice by June 16, 2014.\\n        \\n        \\n          ADDRESSES:\\n\\n          Sissel Schroeder, University of Wisconsin-Madison, Department of Anthropology, 1180 Observatory Drive, 5240 Social Sciences Building, Madison, WI 53706, telephone (608) 262-0317, email sschroeder2@wisc.edu.\\n          \\n        \\n      \\n      \\n        SUPPLEMENTARY INFORMATION:\\n        Notice is here given in accordance with the Native American Graves Protection and Repatriation Act (NAGPRA), 25 U.S.C. 3003, of the completion of an inventory of human remains and associated funerary objects under the control of the University of Wisconsin-Madison Department of Anthropology, Madison, WI. The human remains and associated funerary objects were removed from Waupaca County, WI.\\n        This notice is published as part of the National Park Service\\'s administrative responsibilities under NAGPRA, 25 U.S.C. 3003(d)(3) and 43 CFR 10.11(d). The determinations in this notice are the sole responsibility of the museum, institution, or Federal agency that has control of the Native American human remains and associated funerary objects. The National Park Service is not responsible for the determinations in this notice.\\n        Consultation\\n\\n        A detailed assessment of the human remains was made by the University of Wisconsin-Madison Department of Anthropology professional staff in consultation with representatives of the Forest County Potawatomi Community, Wisconsin; Ho-Chunk Nation of Wisconsin; Lac Courte Oreilles Band of Lake Superior Chippewa Indians of Wisconsin; Lac du Flambeau Band of Lake Superior Chippewa Indians of the Lac du Flambeau Reservation of Wisconsin; Menominee Indian Tribe of Wisconsin; Sokaogon Chippewa Community, Wisconsin; and the Stockbridge Munsee Community, Wisconsin.\\n        \\n        History and Description of the Remains\\n        In 1965, human remains representing, at minimum, one individual were removed from the Sanders site I, in Waupaca County, WI, by William Hurley, a graduate student at the University of Wisconsin-Madison. The human remains were identified in Mound 3 and represent the fragmentary remains of one probably female adult. No known individuals were identified. No associated funerary objects are present. The site dates from the Late Woodland Period, based on an associated radiocarbon date of A.D. 800 \\xc2\\xb1 70.\\n        In 1966, human remains representing, at minimum, two individuals were removed from the Sanders site III, in Waupaca County, WI, by William Hurley. The human remains were removed from House 1 and represent a mid to old age adult and a child. No known individuals were identified. The associated funerary objects are 1 lot of anculosa shells located on the child\\'s forehead.\\n        Determinations Made by the University of Wisconsin-Madison Department of Anthropology\\n        Officials of the University of Wisconsin-Madison Department of Anthropology have determined that:\\n        \\xe2\\x80\\xa2 Pursuant to 25 U.S.C. 3001(9), the human remains described in this notice are Native American based on their examination by a physical anthropologist, their recovery from known archeological sites, their well-documented provenience in the field records, and associated radiocarbon dates.\\n        \\xe2\\x80\\xa2 Pursuant to 25 U.S.C. 3001(9), the human remains described in this notice represent the physical remains of three individuals of Native American ancestry.\\n        \\xe2\\x80\\xa2 Pursuant to 25 U.S.C. 3001(3)(A), the one lot of objects described in this notice are reasonably believed to have been placed with or near individual human remains at the time of death or later as part of the death rite or ceremony.\\n        \\xe2\\x80\\xa2 Pursuant to 25 U.S.C. 3001(2), a relationship of shared group identity cannot be reasonably traced between the Native American human remains and associated funerary objects and any present-day Indian tribe.\\n        \\xe2\\x80\\xa2 Treaties, Acts of Congress, or Executive Orders, indicate that the land from which the Native American human remains and associated funerary objects were removed is the aboriginal land of the Menominee Indian Tribe of Wisconsin.\\n        \\xe2\\x80\\xa2 Pursuant to 43 CFR 10.11(c)(1), the disposition of the human remains and associated funerary objects may be to the Menominee Indian Tribe of Wisconsin.\\n        Additional Requestors and Disposition\\n\\n        Representatives of any Indian tribe or Native Hawaiian organization not identified in this notice that wish to request transfer of control of these human remains and associated funerary objects should submit a written request with information in support of the request to Sissel Schroeder, University of Wisconsin-Madison, Department of Anthropology, 1180 Observatory Drive, 5240 Social Sciences Building, Madison, WI 53706, telephone (608) 262-0317, email sschroeder2@wisc.edu, by June 16, 2014. After that date, if no additional requestors have come forward, transfer of control of the human remains and associated funerary objects to the Menominee Indian Tribe of Wisconsin may proceed.\\n        The University of Wisconsin-Madison Department of Anthropology is responsible for notifying the Menominee Indian Tribe of Wisconsin that this notice has been published.\\n        \\n          Dated: March 31, 2014.\\n          Sherry Hutt,\\n          Manager, National NAGPRA Program.\\n        \\n      \\n      [FR Doc. 2014-11274 Filed 5-14-14; 8:45 am]\\n      BILLING CODE 4312-50-P\\n    ", "agency1": "DEPARTMENT OF THE INTERIOR", "sub_agency1": "National Park Service", "dep_doc": "[NPS-WASO-NAGPRA-15410]; [PPWOCRADN0-PCU00RP14.R50000]", "subject": "Notice of Inventory Completion: University of Wisconsin-Madison, Department of Anthropology, Madison, WI", "agency2": "National Park Service, Interior.", "action": "Notice.", "summary": "The University of Wisconsin-Madison Department of Anthropology has completed an inventory of human remains and associated funerary objects, in consultation with the appropriate Indian tribes or Native Hawaiian organizations, and has determined that there is no cultural affiliation between the human remains and associated funerary objects and any present-day Indian tribes or Native Hawaiian organizations. Representatives of any Indian tribe or Native Hawaiian organization not identified in this notice that wish to request transfer of control of these human remains and associated funerary objects should submit a written request to the University of Wisconsin-Madison Department of Anthropology. If no additional requestors come forward, transfer of control of the human remains and associated funerary objects to the Indian tribes or Native Hawaiian organizations stated in this notice may proceed.", "dates": "Representatives of any Indian tribe or Native Hawaiian organization not identified in this notice that wish to request transfer of control of these human remains and associated funerary objects should submit a written request with information in support of the request to the University of Wisconsin-Madison Department of Anthropology at the address in this notice by June 16, 2014.", "addresses": "Sissel Schroeder, University of Wisconsin-Madison, Department of Anthropology, 1180 Observatory Drive, 5240 Social Sciences Building, Madison, WI 53706, telephone (608) 262-0317, email sschroeder2@wisc.edu.\\n          ", "signature_dated": "Dated: March 31, 2014.", "signature_name": "Sherry Hutt,", "signature_title": "Manager, National NAGPRA Program.", "fr_doc": "[FR Doc. 2014-11274 Filed 5-14-14; 8:45 am]", "billing_code": "BILLING CODE 4312-50-P", "supp_info": "SUPPLEMENTARY INFORMATION: \n Notice is here given in accordance with the Native American Graves Protection and Repatriation Act (NAGPRA), 25 U.S.C. 3003, of the completion of an inventory of human remains and associated funerary objects under the control of the University of Wisconsin-Madison Department of Anthropology, Madison, WI. The human remains and associated funerary objects were removed from Waupaca County, WI. \n This notice is published as part of the National Park Service\\'s administrative responsibilities under NAGPRA, 25 U.S.C. 3003(d)(3) and 43 CFR 10.11(d). The determinations in this notice are the sole responsibility of the museum, institution, or Federal agency that has control of the Native American human remains and associated funerary objects. The National Park Service is not responsible for the determinations in this notice. \n Consultation \n A detailed assessment of the human remains was made by the University of Wisconsin-Madison Department of Anthropology professional staff in consultation with representatives of the Forest County Potawatomi Community, Wisconsin; Ho-Chunk Nation of Wisconsin; Lac Courte Oreilles Band of Lake Superior Chippewa Indians of Wisconsin; Lac du Flambeau Band of Lake Superior Chippewa Indians of the Lac du Flambeau Reservation of Wisconsin; Menominee Indian Tribe of Wisconsin; Sokaogon Chippewa Community, Wisconsin; and the Stockbridge Munsee Community, Wisconsin.\\n         \n History and Description of the Remains \n In 1965, human remains representing, at minimum, one individual were removed from the Sanders site I, in Waupaca County, WI, by William Hurley, a graduate student at the University of Wisconsin-Madison. The human remains were identified in Mound 3 and represent the fragmentary remains of one probably female adult. No known individuals were identified. No associated funerary objects are present. The site dates from the Late Woodland Period, based on an associated radiocarbon date of A.D. 800 \\xc2\\xb1 70. \n In 1966, human remains representing, at minimum, two individuals were removed from the Sanders site III, in Waupaca County, WI, by William Hurley. The human remains were removed from House 1 and represent a mid to old age adult and a child. No known individuals were identified. The associated funerary objects are 1 lot of anculosa shells located on the child\\'s forehead. \n Determinations Made by the University of Wisconsin-Madison Department of Anthropology \n Officials of the University of Wisconsin-Madison Department of Anthropology have determined that: \n \\xe2\\x80\\xa2 Pursuant to 25 U.S.C. 3001(9), the human remains described in this notice are Native American based on their examination by a physical anthropologist, their recovery from known archeological sites, their well-documented provenience in the field records, and associated radiocarbon dates. \n \\xe2\\x80\\xa2 Pursuant to 25 U.S.C. 3001(9), the human remains described in this notice represent the physical remains of three individuals of Native American ancestry. \n \\xe2\\x80\\xa2 Pursuant to 25 U.S.C. 3001(3)(A), the one lot of objects described in this notice are reasonably believed to have been placed with or near individual human remains at the time of death or later as part of the death rite or ceremony. \n \\xe2\\x80\\xa2 Pursuant to 25 U.S.C. 3001(2), a relationship of shared group identity cannot be reasonably traced between the Native American human remains and associated funerary objects and any present-day Indian tribe. \n \\xe2\\x80\\xa2 Treaties, Acts of Congress, or Executive Orders, indicate that the land from which the Native American human remains and associated funerary objects were removed is the aboriginal land of the Menominee Indian Tribe of Wisconsin. \n \\xe2\\x80\\xa2 Pursuant to 43 CFR 10.11(c)(1), the disposition of the human remains and associated funerary objects may be to the Menominee Indian Tribe of Wisconsin. \n Additional Requestors and Disposition \n Representatives of any Indian tribe or Native Hawaiian organization not identified in this notice that wish to request transfer of control of these human remains and associated funerary objects should submit a written request with information in support of the request to Sissel Schroeder, University of Wisconsin-Madison, Department of Anthropology, 1180 Observatory Drive, 5240 Social Sciences Building, Madison, WI 53706, telephone (608) 262-0317, email sschroeder2@wisc.edu, by June 16, 2014. After that date, if no additional requestors have come forward, transfer of control of the human remains and associated funerary objects to the Menominee Indian Tribe of Wisconsin may proceed. \n The University of Wisconsin-Madison Department of Anthropology is responsible for notifying the Menominee Indian Tribe of Wisconsin that this notice has been published. \n ", "consultation": "A detailed assessment of the human remains was made by the University of Wisconsin-Madison Department of Anthropology professional staff in consultation with representatives of the Forest County Potawatomi Community, Wisconsin; Ho-Chunk Nation of Wisconsin; Lac Courte Oreilles Band of Lake Superior Chippewa Indians of Wisconsin; Lac du Flambeau Band of Lake Superior Chippewa Indians of the Lac du Flambeau Reservation of Wisconsin; Menominee Indian Tribe of Wisconsin; Sokaogon Chippewa Community, Wisconsin; and the Stockbridge Munsee Community, Wisconsin.\\n         \n ", "h_d_r": "In 1965, human remains representing, at minimum, one individual were removed from the Sanders site I, in Waupaca County, WI, by William Hurley, a graduate student at the University of Wisconsin-Madison. The human remains were identified in Mound 3 and represent the fragmentary remains of one probably female adult. No known individuals were identified. No associated funerary objects are present. The site dates from the Late Woodland Period, based on an associated radiocarbon date of A.D. 800 \\xc2\\xb1 70. \n In 1966, human remains representing, at minimum, two individuals were removed from the Sanders site III, in Waupaca County, WI, by William Hurley. The human remains were removed from House 1 and represent a mid to old age adult and a child. No known individuals were identified. The associated funerary objects are 1 lot of anculosa shells located on the child\\'s forehead. \n ", "h_d_ci": "Null", "determinations": "Determinations Made by the University of Wisconsin-Madison Department of Anthropology \n Officials of the University of Wisconsin-Madison Department of Anthropology have determined that: \n \\xe2\\x80\\xa2 Pursuant to 25 U.S.C. 3001(9), the human remains described in this notice are Native American based on their examination by a physical anthropologist, their recovery from known archeological sites, their well-documented provenience in the field records, and associated radiocarbon dates. \n \\xe2\\x80\\xa2 Pursuant to 25 U.S.C. 3001(9), the human remains described in this notice represent the physical remains of three individuals of Native American ancestry. \n \\xe2\\x80\\xa2 Pursuant to 25 U.S.C. 3001(3)(A), the one lot of objects described in this notice are reasonably believed to have been placed with or near individual human remains at the time of death or later as part of the death rite or ceremony. \n \\xe2\\x80\\xa2 Pursuant to 25 U.S.C. 3001(2), a relationship of shared group identity cannot be reasonably traced between the Native American human remains and associated funerary objects and any present-day Indian tribe. \n \\xe2\\x80\\xa2 Treaties, Acts of Congress, or Executive Orders, indicate that the land from which the Native American human remains and associated funerary objects were removed is the aboriginal land of the Menominee Indian Tribe of Wisconsin. \n \\xe2\\x80\\xa2 Pursuant to 43 CFR 10.11(c)(1), the disposition of the human remains and associated funerary objects may be to the Menominee Indian Tribe of Wisconsin. \n ", "a_r_d": "Representatives of any Indian tribe or Native Hawaiian organization not identified in this notice that wish to request transfer of control of these human remains and associated funerary objects should submit a written request with information in support of the request to Sissel Schroeder, University of Wisconsin-Madison, Department of Anthropology, 1180 Observatory Drive, 5240 Social Sciences Building, Madison, WI 53706, telephone (608) 262-0317, email sschroeder2@wisc.edu, by June 16, 2014. After that date, if no additional requestors have come forward, transfer of control of the human remains and associated funerary objects to the Menominee Indian Tribe of Wisconsin may proceed. \n The University of Wisconsin-Madison Department of Anthropology is responsible for notifying the Menominee Indian Tribe of Wisconsin that this notice has been published. \n "}