{"index": "I_826", "messy_full": "\\n      \\n        DEPARTMENT OF THE INTERIOR\\n        National Park Service\\n        [NPS-WASO-NAGPRA-15404; PPWOCRADN0-PCU00RP14.R50000]\\n        Notice of Inventory Completion: University of Wisconsin-Madison, Department of Anthropology, Madison, WI\\n        \\n          AGENCY:\\n          National Park Service, Interior.\\n        \\n        \\n          ACTION:\\n          Notice.\\n        \\n        \\n          SUMMARY:\\n          The University of Wisconsin-Madison Department of Anthropology has completed an inventory of human remains, in consultation with the appropriate Indian tribes or Native Hawaiian organizations, and has determined that there is no cultural affiliation between the human remains and any present-day Indian tribes or Native Hawaiian organizations. Representatives of any Indian tribe or Native Hawaiian organization not identified in this notice that wish to request transfer of control of these human remains should submit a written request to the University of Wisconsin-Madison Department of Anthropology. If no additional requestors come forward, transfer of control of the human remains to the Indian tribes or Native Hawaiian organizations stated in this notice may proceed.\\n        \\n        \\n          DATES:\\n          Representatives of any Indian tribe or Native Hawaiian organization not identified in this notice that wish to request transfer of control of these human remains should submit a written request with information in support of the request to the University of Wisconsin-Madison Department of Anthropology at the address in this notice by June 16, 2014.\\n        \\n        \\n          ADDRESSES:\\n\\n          Sissel Schroeder, University of Wisconsin-Madison, Department of Anthropology, 1180 Observatory Drive, 5240 Social Sciences Building, Madison, WI 53706, telephone (608) 262-0317, email sschroeder2@wisc.edu.\\n          \\n        \\n      \\n      \\n        SUPPLEMENTARY INFORMATION:\\n        Notice is here given in accordance with the Native American Graves Protection and Repatriation Act (NAGPRA), 25 U.S.C. 3003, of the completion of an inventory of human remains under the control of the University of Wisconsin-Madison Department of Anthropology, Madison, WI. The human remains were removed from Fond du Lac County, WI.\\n        This notice is published as part of the National Park Service\\'s administrative responsibilities under NAGPRA, 25 U.S.C. 3003(d)(3) and 43 CFR 10.11(d). The determinations in this notice are the sole responsibility of the museum, institution, or Federal agency that has control of the Native American human remains. The National Park Service is not responsible for the determinations in this notice.\\n        Consultation\\n        A detailed assessment of the human remains was made by the University of Wisconsin-Madison Department of Anthropology professional staff in consultation with representatives of the Forest County Potawatomi Community, Wisconsin; Ho-Chunk Nation of Wisconsin; Lac Courte Oreilles Band of Lake Superior Chippewa Indians of Wisconsin; Lac du Flambeau Band of Lake Superior Chippewa Indians of the Lac du Flambeau Reservation of Wisconsin; Menominee Indian Tribe of Wisconsin; Sokaogon Chippewa Community, Wisconsin; and the Stockbridge Munsee Community, Wisconsin. The following tribes were invited to consult but did not participate: the Citizen Potawatomi Nation, Oklahoma; Hannahville Indian Community, Michigan; Prairie Band Potawatomi Nation (previously listed as the Prairie Band of Potawatomi Nation, Kansas); and the Winnebago Tribe of Nebraska.\\n        History and Description of the Remains\\n\\n        In 1953, human remains representing, at minimum, 18 individuals were removed from the Zimmerman (Schmitz) site, in Fond du Lac County, WI, by the Wisconsin Archaeological Survey after gravel operations disturbed the site. The site contained four conical mounds located on the eastern shore of Lake Winnebago and was documented as early as 1907, and again in 1915, but without mention of any excavations. Disturbances were previously reported for three of the mounds, and all of the mounds were affected by cultivation activities. The human remains have been identified as follows: Two infants; four children; three adolescents; four middle-aged adults; and five old age adults. No known individuals were identified. No associated funerary objects are present. The site dates from the Middle Woodland Period (ca. A.D. 100-400).\\n        Determinations Made by the University of Wisconsin-Madison Department of Anthropology\\n        Officials of the University of Wisconsin-Madison Department of Anthropology have determined that:\\n        \\xe2\\x80\\xa2 Pursuant to 25 U.S.C. 3001(9), the human remains described in this notice are Native American based on their examination by a physical anthropologist, their recovery from a known archeological site, and their documented provenience in the field records.\\n        \\xe2\\x80\\xa2 Pursuant to 25 U.S.C. 3001(9), the human remains described in this notice represent the physical remains of 18 individuals of Native American ancestry.\\n        \\xe2\\x80\\xa2 Pursuant to 25 U.S.C. 3001(2), a relationship of shared group identity cannot be reasonably traced between the Native American human remains and any present-day Indian tribe.\\n        \\xe2\\x80\\xa2 Treaties, Acts of Congress, or Executive Orders, indicate that the land from which the Native American human remains were removed is the aboriginal land of the Bad River Band of the Lake Superior Tribe of Chippewa Indians of the Bad River Reservation, Wisconsin; Bay Mills Indian Community, Michigan; Bois Forte Band (Nett Lake) of the Minnesota Chippewa Tribe, Minnesota; Chippewa-Cree Indians of the Rocky Boy\\'s Reservation, Montana; Citizen Potawatomi Nation, Oklahoma; Fond du Lac Band of the Minnesota Chippewa Tribe, Minnesota; Forest County Potawatomi Community, Wisconsin; Grand Portage Band of the Minnesota Chippewa Tribe, Minnesota; Grand Traverse Band of Ottawa and Chippewa Indians, Michigan; Hannahville Indian Community, Michigan; Ho-Chunk Nation of Wisconsin; Keweenaw Bay Indian Community, Michigan; Lac Courte Oreilles Band of Lake Superior Chippewa Indians of Wisconsin; Lac du Flambeau Band of Lake Superior Chippewa Indians of the Lac du Flambeau Reservation of Wisconsin; Lac Vieux Desert Band of Lake Superior Chippewa Indians of Michigan; Leech Lake Band of the Minnesota Chippewa Tribe, Minnesota; Match-e-be-nash-she-wish Band of Pottawatomi Indians of Michigan; Menominee Indian Tribe of Wisconsin; Mille Lacs Band of the Minnesota Chippewa Tribe, Minnesota; Minnesota Chippewa Tribe, Minnesota; Nottawaseppi Huron Band of the Potawatomi, Michigan (previously listed as the Huron Potawatomi, Inc.); Ottawa Tribe of Oklahoma; Pokagon Band of Potawatomi Indians, Michigan and Indiana; Prairie Band Potawatomi Nation (previously listed as the Prairie Band of Potawatomi Nation, Kansas); Quechan Tribe of the Fort Yuma Indian Reservation, California & Arizona; Red Cliff Band of Lake Superior Chippewa Indians of Wisconsin; Red Lake Band of Chippewa Indians, Minnesota; Saginaw Chippewa Indian Tribe of Michigan; Sault Ste. Marie Tribe of Chippewa Indians, Michigan; Sokaogon Chippewa Community, Wisconsin; St. Croix Chippewa Indians of Wisconsin; Turtle Mountain Band of Chippewa Indians of North Dakota; White Earth Band of Minnesota Chippewa Tribe, Minnesota; and the Winnebago Tribe of Nebraska (hereafter referred to as \\xe2\\x80\\x9cThe Tribes\\xe2\\x80\\x9d).\\n        \\xe2\\x80\\xa2 Pursuant to 43 CFR 10.11(c)(1), the disposition of the human remains may be to The Tribes.\\n        Additional Requestors and Disposition\\n\\n        Representatives of any Indian tribe or Native Hawaiian organization not identified in this notice that wish to request transfer of control of these human remains should submit a written request with information in support of the request to Sissel Schroeder, University of Wisconsin-Madison, Department of Anthropology, 1180 Observatory Drive, 5240 Social Sciences Building, Madison, WI 53706, telephone (608) 262-0317, email sschroeder2@wisc.edu, by June 16, 2014. After that date, if no additional requestors have come forward, transfer of control of the human remains to The Tribes may proceed.\\n        The University of Wisconsin-Madison Department of Anthropology is responsible for notifying The Tribes that this notice has been published.\\n        \\n          Dated: March 31, 2014.\\n          Sherry Hutt,\\n          Manager, National NAGPRA Program. \\n        \\n      \\n      [FR Doc. 2014-11236 Filed 5-14-14; 8:45 am]\\n      BILLING CODE 4312-50-P\\n    ", "agency1": "DEPARTMENT OF THE INTERIOR", "sub_agency1": "National Park Service", "dep_doc": "[NPS-WASO-NAGPRA-15404; PPWOCRADN0-PCU00RP14.R50000]", "subject": "Notice of Inventory Completion: University of Wisconsin-Madison, Department of Anthropology, Madison, WI", "agency2": "National Park Service, Interior.", "action": "Notice.", "summary": "The University of Wisconsin-Madison Department of Anthropology has completed an inventory of human remains, in consultation with the appropriate Indian tribes or Native Hawaiian organizations, and has determined that there is no cultural affiliation between the human remains and any present-day Indian tribes or Native Hawaiian organizations. Representatives of any Indian tribe or Native Hawaiian organization not identified in this notice that wish to request transfer of control of these human remains should submit a written request to the University of Wisconsin-Madison Department of Anthropology. If no additional requestors come forward, transfer of control of the human remains to the Indian tribes or Native Hawaiian organizations stated in this notice may proceed.", "dates": "Representatives of any Indian tribe or Native Hawaiian organization not identified in this notice that wish to request transfer of control of these human remains should submit a written request with information in support of the request to the University of Wisconsin-Madison Department of Anthropology at the address in this notice by June 16, 2014.", "addresses": "Sissel Schroeder, University of Wisconsin-Madison, Department of Anthropology, 1180 Observatory Drive, 5240 Social Sciences Building, Madison, WI 53706, telephone (608) 262-0317, email sschroeder2@wisc.edu.\\n          ", "signature_dated": "Dated: March 31, 2014.", "signature_name": "Sherry Hutt,", "signature_title": "Manager, National NAGPRA Program. ", "fr_doc": "[FR Doc. 2014-11236 Filed 5-14-14; 8:45 am]", "billing_code": "BILLING CODE 4312-50-P", "supp_info": "SUPPLEMENTARY INFORMATION: \n Notice is here given in accordance with the Native American Graves Protection and Repatriation Act (NAGPRA), 25 U.S.C. 3003, of the completion of an inventory of human remains under the control of the University of Wisconsin-Madison Department of Anthropology, Madison, WI. The human remains were removed from Fond du Lac County, WI. \n This notice is published as part of the National Park Service\\'s administrative responsibilities under NAGPRA, 25 U.S.C. 3003(d)(3) and 43 CFR 10.11(d). The determinations in this notice are the sole responsibility of the museum, institution, or Federal agency that has control of the Native American human remains. The National Park Service is not responsible for the determinations in this notice. \n Consultation \n A detailed assessment of the human remains was made by the University of Wisconsin-Madison Department of Anthropology professional staff in consultation with representatives of the Forest County Potawatomi Community, Wisconsin; Ho-Chunk Nation of Wisconsin; Lac Courte Oreilles Band of Lake Superior Chippewa Indians of Wisconsin; Lac du Flambeau Band of Lake Superior Chippewa Indians of the Lac du Flambeau Reservation of Wisconsin; Menominee Indian Tribe of Wisconsin; Sokaogon Chippewa Community, Wisconsin; and the Stockbridge Munsee Community, Wisconsin. The following tribes were invited to consult but did not participate: the Citizen Potawatomi Nation, Oklahoma; Hannahville Indian Community, Michigan; Prairie Band Potawatomi Nation (previously listed as the Prairie Band of Potawatomi Nation, Kansas); and the Winnebago Tribe of Nebraska. \n History and Description of the Remains \n In 1953, human remains representing, at minimum, 18 individuals were removed from the Zimmerman (Schmitz) site, in Fond du Lac County, WI, by the Wisconsin Archaeological Survey after gravel operations disturbed the site. The site contained four conical mounds located on the eastern shore of Lake Winnebago and was documented as early as 1907, and again in 1915, but without mention of any excavations. Disturbances were previously reported for three of the mounds, and all of the mounds were affected by cultivation activities. The human remains have been identified as follows: Two infants; four children; three adolescents; four middle-aged adults; and five old age adults. No known individuals were identified. No associated funerary objects are present. The site dates from the Middle Woodland Period (ca. A.D. 100-400). \n Determinations Made by the University of Wisconsin-Madison Department of Anthropology \n Officials of the University of Wisconsin-Madison Department of Anthropology have determined that: \n \\xe2\\x80\\xa2 Pursuant to 25 U.S.C. 3001(9), the human remains described in this notice are Native American based on their examination by a physical anthropologist, their recovery from a known archeological site, and their documented provenience in the field records. \n \\xe2\\x80\\xa2 Pursuant to 25 U.S.C. 3001(9), the human remains described in this notice represent the physical remains of 18 individuals of Native American ancestry. \n \\xe2\\x80\\xa2 Pursuant to 25 U.S.C. 3001(2), a relationship of shared group identity cannot be reasonably traced between the Native American human remains and any present-day Indian tribe. \n \\xe2\\x80\\xa2 Treaties, Acts of Congress, or Executive Orders, indicate that the land from which the Native American human remains were removed is the aboriginal land of the Bad River Band of the Lake Superior Tribe of Chippewa Indians of the Bad River Reservation, Wisconsin; Bay Mills Indian Community, Michigan; Bois Forte Band (Nett Lake) of the Minnesota Chippewa Tribe, Minnesota; Chippewa-Cree Indians of the Rocky Boy\\'s Reservation, Montana; Citizen Potawatomi Nation, Oklahoma; Fond du Lac Band of the Minnesota Chippewa Tribe, Minnesota; Forest County Potawatomi Community, Wisconsin; Grand Portage Band of the Minnesota Chippewa Tribe, Minnesota; Grand Traverse Band of Ottawa and Chippewa Indians, Michigan; Hannahville Indian Community, Michigan; Ho-Chunk Nation of Wisconsin; Keweenaw Bay Indian Community, Michigan; Lac Courte Oreilles Band of Lake Superior Chippewa Indians of Wisconsin; Lac du Flambeau Band of Lake Superior Chippewa Indians of the Lac du Flambeau Reservation of Wisconsin; Lac Vieux Desert Band of Lake Superior Chippewa Indians of Michigan; Leech Lake Band of the Minnesota Chippewa Tribe, Minnesota; Match-e-be-nash-she-wish Band of Pottawatomi Indians of Michigan; Menominee Indian Tribe of Wisconsin; Mille Lacs Band of the Minnesota Chippewa Tribe, Minnesota; Minnesota Chippewa Tribe, Minnesota; Nottawaseppi Huron Band of the Potawatomi, Michigan (previously listed as the Huron Potawatomi, Inc.); Ottawa Tribe of Oklahoma; Pokagon Band of Potawatomi Indians, Michigan and Indiana; Prairie Band Potawatomi Nation (previously listed as the Prairie Band of Potawatomi Nation, Kansas); Quechan Tribe of the Fort Yuma Indian Reservation, California & Arizona; Red Cliff Band of Lake Superior Chippewa Indians of Wisconsin; Red Lake Band of Chippewa Indians, Minnesota; Saginaw Chippewa Indian Tribe of Michigan; Sault Ste. Marie Tribe of Chippewa Indians, Michigan; Sokaogon Chippewa Community, Wisconsin; St. Croix Chippewa Indians of Wisconsin; Turtle Mountain Band of Chippewa Indians of North Dakota; White Earth Band of Minnesota Chippewa Tribe, Minnesota; and the Winnebago Tribe of Nebraska (hereafter referred to as \\xe2\\x80\\x9cThe Tribes\\xe2\\x80\\x9d). \n \\xe2\\x80\\xa2 Pursuant to 43 CFR 10.11(c)(1), the disposition of the human remains may be to The Tribes. \n Additional Requestors and Disposition \n Representatives of any Indian tribe or Native Hawaiian organization not identified in this notice that wish to request transfer of control of these human remains should submit a written request with information in support of the request to Sissel Schroeder, University of Wisconsin-Madison, Department of Anthropology, 1180 Observatory Drive, 5240 Social Sciences Building, Madison, WI 53706, telephone (608) 262-0317, email sschroeder2@wisc.edu, by June 16, 2014. After that date, if no additional requestors have come forward, transfer of control of the human remains to The Tribes may proceed. \n The University of Wisconsin-Madison Department of Anthropology is responsible for notifying The Tribes that this notice has been published. \n ", "consultation": "A detailed assessment of the human remains was made by the University of Wisconsin-Madison Department of Anthropology professional staff in consultation with representatives of the Forest County Potawatomi Community, Wisconsin; Ho-Chunk Nation of Wisconsin; Lac Courte Oreilles Band of Lake Superior Chippewa Indians of Wisconsin; Lac du Flambeau Band of Lake Superior Chippewa Indians of the Lac du Flambeau Reservation of Wisconsin; Menominee Indian Tribe of Wisconsin; Sokaogon Chippewa Community, Wisconsin; and the Stockbridge Munsee Community, Wisconsin. The following tribes were invited to consult but did not participate: the Citizen Potawatomi Nation, Oklahoma; Hannahville Indian Community, Michigan; Prairie Band Potawatomi Nation (previously listed as the Prairie Band of Potawatomi Nation, Kansas); and the Winnebago Tribe of Nebraska. \n ", "h_d_r": "In 1953, human remains representing, at minimum, 18 individuals were removed from the Zimmerman (Schmitz) site, in Fond du Lac County, WI, by the Wisconsin Archaeological Survey after gravel operations disturbed the site. The site contained four conical mounds located on the eastern shore of Lake Winnebago and was documented as early as 1907, and again in 1915, but without mention of any excavations. Disturbances were previously reported for three of the mounds, and all of the mounds were affected by cultivation activities. The human remains have been identified as follows: Two infants; four children; three adolescents; four middle-aged adults; and five old age adults. No known individuals were identified. No associated funerary objects are present. The site dates from the Middle Woodland Period (ca. A.D. 100-400). \n ", "h_d_ci": "Null", "determinations": "Determinations Made by the University of Wisconsin-Madison Department of Anthropology \n Officials of the University of Wisconsin-Madison Department of Anthropology have determined that: \n \\xe2\\x80\\xa2 Pursuant to 25 U.S.C. 3001(9), the human remains described in this notice are Native American based on their examination by a physical anthropologist, their recovery from a known archeological site, and their documented provenience in the field records. \n \\xe2\\x80\\xa2 Pursuant to 25 U.S.C. 3001(9), the human remains described in this notice represent the physical remains of 18 individuals of Native American ancestry. \n \\xe2\\x80\\xa2 Pursuant to 25 U.S.C. 3001(2), a relationship of shared group identity cannot be reasonably traced between the Native American human remains and any present-day Indian tribe. \n \\xe2\\x80\\xa2 Treaties, Acts of Congress, or Executive Orders, indicate that the land from which the Native American human remains were removed is the aboriginal land of the Bad River Band of the Lake Superior Tribe of Chippewa Indians of the Bad River Reservation, Wisconsin; Bay Mills Indian Community, Michigan; Bois Forte Band (Nett Lake) of the Minnesota Chippewa Tribe, Minnesota; Chippewa-Cree Indians of the Rocky Boy\\'s Reservation, Montana; Citizen Potawatomi Nation, Oklahoma; Fond du Lac Band of the Minnesota Chippewa Tribe, Minnesota; Forest County Potawatomi Community, Wisconsin; Grand Portage Band of the Minnesota Chippewa Tribe, Minnesota; Grand Traverse Band of Ottawa and Chippewa Indians, Michigan; Hannahville Indian Community, Michigan; Ho-Chunk Nation of Wisconsin; Keweenaw Bay Indian Community, Michigan; Lac Courte Oreilles Band of Lake Superior Chippewa Indians of Wisconsin; Lac du Flambeau Band of Lake Superior Chippewa Indians of the Lac du Flambeau Reservation of Wisconsin; Lac Vieux Desert Band of Lake Superior Chippewa Indians of Michigan; Leech Lake Band of the Minnesota Chippewa Tribe, Minnesota; Match-e-be-nash-she-wish Band of Pottawatomi Indians of Michigan; Menominee Indian Tribe of Wisconsin; Mille Lacs Band of the Minnesota Chippewa Tribe, Minnesota; Minnesota Chippewa Tribe, Minnesota; Nottawaseppi Huron Band of the Potawatomi, Michigan (previously listed as the Huron Potawatomi, Inc.); Ottawa Tribe of Oklahoma; Pokagon Band of Potawatomi Indians, Michigan and Indiana; Prairie Band Potawatomi Nation (previously listed as the Prairie Band of Potawatomi Nation, Kansas); Quechan Tribe of the Fort Yuma Indian Reservation, California & Arizona; Red Cliff Band of Lake Superior Chippewa Indians of Wisconsin; Red Lake Band of Chippewa Indians, Minnesota; Saginaw Chippewa Indian Tribe of Michigan; Sault Ste. Marie Tribe of Chippewa Indians, Michigan; Sokaogon Chippewa Community, Wisconsin; St. Croix Chippewa Indians of Wisconsin; Turtle Mountain Band of Chippewa Indians of North Dakota; White Earth Band of Minnesota Chippewa Tribe, Minnesota; and the Winnebago Tribe of Nebraska (hereafter referred to as \\xe2\\x80\\x9cThe Tribes\\xe2\\x80\\x9d). \n \\xe2\\x80\\xa2 Pursuant to 43 CFR 10.11(c)(1), the disposition of the human remains may be to The Tribes. \n ", "a_r_d": "Representatives of any Indian tribe or Native Hawaiian organization not identified in this notice that wish to request transfer of control of these human remains should submit a written request with information in support of the request to Sissel Schroeder, University of Wisconsin-Madison, Department of Anthropology, 1180 Observatory Drive, 5240 Social Sciences Building, Madison, WI 53706, telephone (608) 262-0317, email sschroeder2@wisc.edu, by June 16, 2014. After that date, if no additional requestors have come forward, transfer of control of the human remains to The Tribes may proceed. \n The University of Wisconsin-Madison Department of Anthropology is responsible for notifying The Tribes that this notice has been published. \n "}