{"index": "I_858", "messy_full": "\\n      \\n        DEPARTMENT OF THE INTERIOR\\n        National Park Service\\n        [NPS-WASO-NAGPRA-14794; PPWOCRADN0-PCU00RP14.R50000]\\n        Notice of Inventory Completion: U.S. Department of the Interior, National Park Service, Lake Roosevelt National Recreation Area, Coulee Dam, WA\\n        \\n          AGENCY:\\n          National Park Service, Interior.\\n        \\n        \\n          ACTION:\\n          Notice.\\n        \\n        \\n          SUMMARY:\\n          The U.S. Department of the Interior, National Park Service, Lake Roosevelt National Recreation Area has completed an inventory of human remains and associated funerary objects, in consultation with the appropriate Indian tribes or Native Hawaiian organizations, and has determined that there is a cultural affiliation between the human remains and associated funerary objects and present-day Indian tribes or Native Hawaiian organizations. Lineal descendants or representatives of any Indian tribe or Native Hawaiian organization not identified in this notice that wish to request transfer of control of these human remains and associated funerary objects should submit a written request to Lake Roosevelt National Recreation Area. If no additional requestors come forward, transfer of control of the human remains and associated funerary objects to the lineal descendants, Indian tribes, or Native Hawaiian organizations stated in this notice may proceed.\\n        \\n        \\n          DATES:\\n          Lineal descendants or representatives of any Indian tribe or Native Hawaiian organization not identified in this notice that wish to request transfer of control of these human remains and associated funerary objects should submit a written request with information in support of the request to Lake Roosevelt National Recreation Area at the address in this notice by March 7, 2014.\\n        \\n        \\n          ADDRESSES:\\n\\n          Dan A. Foster, Superintendent, Lake Roosevelt National Recreation Area, 1008 Crest Drive, Coulee Dam, WA 99116, telephone (509) 754-7812, email Dan_A_Foster@nps.gov.\\n          \\n        \\n      \\n      \\n        SUPPLEMENTARY INFORMATION:\\n        Notice is here given in accordance with the Native American Graves Protection and Repatriation Act (NAGPRA), 25 U.S.C. 3003, of the completion of an inventory of human remains and associated funerary objects under the control of the U.S. Department of the Interior, National Park Service, Lake Roosevelt National Recreation Area, Coulee Dam, WA, and in the physical custody of the Museum of Anthropology at Washington State University, Pullman, WA. The human remains and associated funerary objects were removed from Lincoln County, WA.\\n        This notice is published as part of the National Park Service\\'s administrative responsibilities under NAGPRA, 25 U.S.C. 3003(d)(3). The determinations in this notice are the sole responsibility of the Superintendent, Lake Roosevelt National Recreation Area.\\n        Consultation\\n        A detailed assessment of the human remains was made by Lake Roosevelt National Recreation Area professional staff in consultation with representatives of the Spokane Tribe of the Spokane Reservation.\\n        History and Description of the Remains\\n\\n        In 1967, human remains representing, at minimum, one individual were removed from a heavily disturbed area at site 45LI06 in Lincoln County, WA, by Roderick Sprague of the University of Idaho. The remains were housed at the University of Idaho until 2000, when they were transferred to the Museum of Anthropology at Washington State University. No known individuals were identified. The 20 associated funerary objects are 1 pestle fragment, 1 flaked stone spall, 3 projectile points, 1 stone flake, 2 projectile point tip fragments, 3 crockery fragments, 2 glass bottle fragments, 6 ceramic fragments, and 1 lot of burned grave marker post fragments.\\n        Archeological data indicate that site 45LI06 was a major village, fishing location, and burial site, which was occupied from approximately 5000-600 B.P. The site is part of a complex along the Spokane River that includes named Spokane Indian villages, camps, procurement sites, and burial sites. Ethnohistorical data indicate that this area of the river was occupied by a group that researchers termed the Middle Spokane (sq\\xc3\\xa5si\\'\\xc5\\x82ni), named after an early contact village located upstream of site 45LI06. The Middle Spokane was one of three major groups that make up the Spokane Tribe of the Spokane Reservation. Oral tradition also documents that this area of the Spokane River was occupied by the ancestors of the Spokane Tribe of the Spokane Reservation.\\n        Determinations Made by Lake Roosevelt National Recreation Area\\n        Officials of Lake Roosevelt National Recreation Area have determined that:\\n        \\xe2\\x80\\xa2 Pursuant to 25 U.S.C. 3001(9), the human remains described in this notice represent the physical remains of one individual of Native American ancestry.\\n        \\xe2\\x80\\xa2 Pursuant to 25 U.S.C. 3001(3)(A), the 20 objects described in this notice are reasonably believed to have been placed with or near individual human remains at the time of death or later as part of the death rite or ceremony.\\n        \\xe2\\x80\\xa2 Pursuant to 25 U.S.C. 3001(2), there is a relationship of shared group identity that can be reasonably traced between the Native American human remains and associated funerary objects and the Spokane Tribe of the Spokane Reservation.\\n        Additional Requestors and Disposition\\n\\n        Lineal descendants or representatives of any Indian tribe or Native Hawaiian organization not identified in this notice that wish to request transfer of control of these human remains and associated funerary objects should submit a written request with information in support of the request to Dan A. Foster, Superintendent, Lake Roosevelt National Recreation Area, 1008 Crest Drive, Coulee Dam, WA 99116, telephone (509) 754-7812, email Dan_A_Foster@nps.gov, by March 7, 2014. After that date, if no additional requestors have come forward, transfer of control of the human remains and associated funerary objects to the Spokane Tribe of the Spokane Reservation may proceed.\\n        Lake Roosevelt National Recreation Area is responsible for notifying the Spokane Tribe of the Spokane Reservation that this notice has been published.\\n        \\n          Dated: January 9, 2014.\\n          Melanie O\\'Brien,\\n          Acting Manager, National NAGPRA Program.\\n        \\n      \\n      [FR Doc. 2014-02308 Filed 2-4-14; 8:45 am]\\n      BILLING CODE 4312-50-P\\n    ", "agency1": "DEPARTMENT OF THE INTERIOR", "sub_agency1": "National Park Service", "dep_doc": "[NPS-WASO-NAGPRA-14794; PPWOCRADN0-PCU00RP14.R50000]", "subject": "Notice of Inventory Completion: U.S. Department of the Interior, National Park Service, Lake Roosevelt National Recreation Area, Coulee Dam, WA", "agency2": "National Park Service, Interior.", "action": "Notice.", "summary": "The U.S. Department of the Interior, National Park Service, Lake Roosevelt National Recreation Area has completed an inventory of human remains and associated funerary objects, in consultation with the appropriate Indian tribes or Native Hawaiian organizations, and has determined that there is a cultural affiliation between the human remains and associated funerary objects and present-day Indian tribes or Native Hawaiian organizations. Lineal descendants or representatives of any Indian tribe or Native Hawaiian organization not identified in this notice that wish to request transfer of control of these human remains and associated funerary objects should submit a written request to Lake Roosevelt National Recreation Area. If no additional requestors come forward, transfer of control of the human remains and associated funerary objects to the lineal descendants, Indian tribes, or Native Hawaiian organizations stated in this notice may proceed.", "dates": "Lineal descendants or representatives of any Indian tribe or Native Hawaiian organization not identified in this notice that wish to request transfer of control of these human remains and associated funerary objects should submit a written request with information in support of the request to Lake Roosevelt National Recreation Area at the address in this notice by March 7, 2014.", "addresses": "Dan A. Foster, Superintendent, Lake Roosevelt National Recreation Area, 1008 Crest Drive, Coulee Dam, WA 99116, telephone (509) 754-7812, email Dan_A_Foster@nps.gov.\\n          ", "signature_dated": "Dated: January 9, 2014.", "signature_name": "Melanie O\\'Brien,", "signature_title": "Acting Manager, National NAGPRA Program.", "fr_doc": "[FR Doc. 2014-02308 Filed 2-4-14; 8:45 am]", "billing_code": "BILLING CODE 4312-50-P", "supp_info": "SUPPLEMENTARY INFORMATION: \n Notice is here given in accordance with the Native American Graves Protection and Repatriation Act (NAGPRA), 25 U.S.C. 3003, of the completion of an inventory of human remains and associated funerary objects under the control of the U.S. Department of the Interior, National Park Service, Lake Roosevelt National Recreation Area, Coulee Dam, WA, and in the physical custody of the Museum of Anthropology at Washington State University, Pullman, WA. The human remains and associated funerary objects were removed from Lincoln County, WA. \n This notice is published as part of the National Park Service\\'s administrative responsibilities under NAGPRA, 25 U.S.C. 3003(d)(3). The determinations in this notice are the sole responsibility of the Superintendent, Lake Roosevelt National Recreation Area. \n Consultation \n A detailed assessment of the human remains was made by Lake Roosevelt National Recreation Area professional staff in consultation with representatives of the Spokane Tribe of the Spokane Reservation. \n History and Description of the Remains \n In 1967, human remains representing, at minimum, one individual were removed from a heavily disturbed area at site 45LI06 in Lincoln County, WA, by Roderick Sprague of the University of Idaho. The remains were housed at the University of Idaho until 2000, when they were transferred to the Museum of Anthropology at Washington State University. No known individuals were identified. The 20 associated funerary objects are 1 pestle fragment, 1 flaked stone spall, 3 projectile points, 1 stone flake, 2 projectile point tip fragments, 3 crockery fragments, 2 glass bottle fragments, 6 ceramic fragments, and 1 lot of burned grave marker post fragments. \n Archeological data indicate that site 45LI06 was a major village, fishing location, and burial site, which was occupied from approximately 5000-600 B.P. The site is part of a complex along the Spokane River that includes named Spokane Indian villages, camps, procurement sites, and burial sites. Ethnohistorical data indicate that this area of the river was occupied by a group that researchers termed the Middle Spokane (sq\\xc3\\xa5si\\'\\xc5\\x82ni), named after an early contact village located upstream of site 45LI06. The Middle Spokane was one of three major groups that make up the Spokane Tribe of the Spokane Reservation. Oral tradition also documents that this area of the Spokane River was occupied by the ancestors of the Spokane Tribe of the Spokane Reservation. \n Determinations Made by Lake Roosevelt National Recreation Area \n Officials of Lake Roosevelt National Recreation Area have determined that: \n \\xe2\\x80\\xa2 Pursuant to 25 U.S.C. 3001(9), the human remains described in this notice represent the physical remains of one individual of Native American ancestry. \n \\xe2\\x80\\xa2 Pursuant to 25 U.S.C. 3001(3)(A), the 20 objects described in this notice are reasonably believed to have been placed with or near individual human remains at the time of death or later as part of the death rite or ceremony. \n \\xe2\\x80\\xa2 Pursuant to 25 U.S.C. 3001(2), there is a relationship of shared group identity that can be reasonably traced between the Native American human remains and associated funerary objects and the Spokane Tribe of the Spokane Reservation. \n Additional Requestors and Disposition \n Lineal descendants or representatives of any Indian tribe or Native Hawaiian organization not identified in this notice that wish to request transfer of control of these human remains and associated funerary objects should submit a written request with information in support of the request to Dan A. Foster, Superintendent, Lake Roosevelt National Recreation Area, 1008 Crest Drive, Coulee Dam, WA 99116, telephone (509) 754-7812, email Dan_A_Foster@nps.gov, by March 7, 2014. After that date, if no additional requestors have come forward, transfer of control of the human remains and associated funerary objects to the Spokane Tribe of the Spokane Reservation may proceed. \n Lake Roosevelt National Recreation Area is responsible for notifying the Spokane Tribe of the Spokane Reservation that this notice has been published. \n ", "consultation": "A detailed assessment of the human remains was made by Lake Roosevelt National Recreation Area professional staff in consultation with representatives of the Spokane Tribe of the Spokane Reservation. \n ", "h_d_r": "In 1967, human remains representing, at minimum, one individual were removed from a heavily disturbed area at site 45LI06 in Lincoln County, WA, by Roderick Sprague of the University of Idaho. The remains were housed at the University of Idaho until 2000, when they were transferred to the Museum of Anthropology at Washington State University. No known individuals were identified. The 20 associated funerary objects are 1 pestle fragment, 1 flaked stone spall, 3 projectile points, 1 stone flake, 2 projectile point tip fragments, 3 crockery fragments, 2 glass bottle fragments, 6 ceramic fragments, and 1 lot of burned grave marker post fragments. \n Archeological data indicate that site 45LI06 was a major village, fishing location, and burial site, which was occupied from approximately 5000-600 B.P. The site is part of a complex along the Spokane River that includes named Spokane Indian villages, camps, procurement sites, and burial sites. Ethnohistorical data indicate that this area of the river was occupied by a group that researchers termed the Middle Spokane (sq\\xc3\\xa5si\\'\\xc5\\x82ni), named after an early contact village located upstream of site 45LI06. The Middle Spokane was one of three major groups that make up the Spokane Tribe of the Spokane Reservation. Oral tradition also documents that this area of the Spokane River was occupied by the ancestors of the Spokane Tribe of the Spokane Reservation. \n ", "h_d_ci": "Null", "determinations": "Determinations Made by Lake Roosevelt National Recreation Area \n Officials of Lake Roosevelt National Recreation Area have determined that: \n \\xe2\\x80\\xa2 Pursuant to 25 U.S.C. 3001(9), the human remains described in this notice represent the physical remains of one individual of Native American ancestry. \n \\xe2\\x80\\xa2 Pursuant to 25 U.S.C. 3001(3)(A), the 20 objects described in this notice are reasonably believed to have been placed with or near individual human remains at the time of death or later as part of the death rite or ceremony. \n \\xe2\\x80\\xa2 Pursuant to 25 U.S.C. 3001(2), there is a relationship of shared group identity that can be reasonably traced between the Native American human remains and associated funerary objects and the Spokane Tribe of the Spokane Reservation. \n ", "a_r_d": "Lineal descendants or representatives of any Indian tribe or Native Hawaiian organization not identified in this notice that wish to request transfer of control of these human remains and associated funerary objects should submit a written request with information in support of the request to Dan A. Foster, Superintendent, Lake Roosevelt National Recreation Area, 1008 Crest Drive, Coulee Dam, WA 99116, telephone (509) 754-7812, email Dan_A_Foster@nps.gov, by March 7, 2014. After that date, if no additional requestors have come forward, transfer of control of the human remains and associated funerary objects to the Spokane Tribe of the Spokane Reservation may proceed. \n Lake Roosevelt National Recreation Area is responsible for notifying the Spokane Tribe of the Spokane Reservation that this notice has been published. \n "}