{"index": "I_891", "messy_full": "\\n      \\n        DEPARTMENT OF THE INTERIOR\\n        National Park Service\\n        [NPS-WASO-NAGPRA-14040; PPWOCRADN0-PCU00RP14.R50000]\\n        Notice of Inventory Completion: University of Michigan, Ann Arbor, MI\\n        \\n          AGENCY:\\n          National Park Service, Interior.\\n        \\n        \\n          ACTION:\\n          Notice.\\n        \\n        \\n          SUMMARY:\\n          The University of Michigan has completed an inventory of human remains, in consultation with the appropriate Indian tribes or Native Hawaiian organizations, and has determined that there is no cultural affiliation between the human remains and any present-day Indian tribes or Native Hawaiian organizations. Representatives of any Indian tribe or Native Hawaiian organization not identified in this notice that wish to request transfer of control of these human remains should submit a written request to the University of Michigan. If no additional requestors come forward, transfer of control of the human remains to the Indian tribes or Native Hawaiian organizations stated in this notice may proceed.\\n        \\n        \\n          DATES:\\n          Representatives of any Indian tribe or Native Hawaiian organization not identified in this notice that wish to request transfer of control of these human remains should submit a written request with information in support of the request to the University of Michigan at the address in this notice by December 2, 2013.\\n        \\n        \\n          ADDRESSES:\\n\\n          Dr. Ben Secunda, NAGPRA Project Manager, University of Michigan, Office of the Vice President for Research, 4080 Fleming Building, 503 Thompson St., Ann Arbor, MI 48109-1340, telephone (734) 647-9085, email bsecunda@umich.edu.\\n          \\n        \\n      \\n      \\n        SUPPLEMENTARY INFORMATION:\\n        Notice is here given in accordance with the Native American Graves Protection and Repatriation Act (NAGPRA), 25 U.S.C. 3003, of the completion of an inventory of human remains under the control of the University of Michigan, Ann Arbor, MI. The human remains were removed from Saginaw County, MI.\\n\\n        This notice is published as part of the National Park Service\\'s administrative responsibilities under NAGPRA, 25 U.S.C. 3003(d)(3) and 43 CFR 10.11(d). The determinations in this notice are the sole responsibility of the museum, institution, or Federal agency that has control of the Native American human remains. The National Park Service is not responsible for the determinations in this notice.\\n        Consultation\\n        A detailed assessment of the human remains was made by the University of Michigan Museum of Anthropology professional staff in consultation with representatives of the Bay Mills Indian Community, Michigan; Chippewa-Cree Indians of the Rocky Boy\\'s Reservation, Montana; Grand Traverse Band of Ottawa and Chippewa Indians, Michigan; Keweenaw Bay Indian Community, Michigan; Lac Vieux Desert Band of Lake Superior Chippewa Indians of Michigan; Saginaw Chippewa Indian Tribe of Michigan; and the Sault Ste. Marie Tribe of Chippewa Indians, Michigan.\\n        Additional requests for consultation were sent to the Bad River Band of the Lake Superior Tribe of Chippewa Indians of the Bad River Reservation, Wisconsin; Bois Forte Band (Nett Lake) of the Minnesota Chippewa Tribe, Minnesota; Fond du Lac Band of the Minnesota Chippewa Tribe, Minnesota; Grand Portage Band of the Minnesota Chippewa Tribe, Minnesota; Kickapoo Traditional Tribe of Texas; Kickapoo Tribe of Indians of the Kickapoo Reservation in Kansas; Kickapoo Tribe of Oklahoma; Lac Courte Oreilles Band of Lake Superior Chippewa Indians of Wisconsin; Lac du Flambeau Band of Lake Superior Chippewa Indians of the Lac du Flambeau Reservation of Wisconsin; Leech Lake Band of the Minnesota Chippewa Tribe, Minnesota; Mille Lacs Band of the Minnesota Chippewa Tribe, Minnesota; Red Cliff Band of Lake Superior Chippewa Indians of Wisconsin; Red Lake Band of Chippewa Indians, Minnesota; Sac & Fox Nation of Missouri in Kansas and Nebraska; Sac & Fox Nation, Oklahoma; Sac & Fox Tribe of the Mississippi in Iowa; Sokaogon Chippewa Community, Wisconsin; St. Croix Chippewa Indians of Wisconsin; Turtle Mountain Band of Chippewa Indians of North Dakota; and the White Earth Band of the Minnesota Chippewa Tribe, Minnesota.\\n        Hereafter, all tribes listed in this section are referred to as \\xe2\\x80\\x9cThe Tribes.\\xe2\\x80\\x9d\\n        History and Description of the Remains\\n        On an unknown date between 1915 and 1950, human remains representing, at minimum, 5 individuals were removed from the Green Point site (20SA1) in Saginaw County, MI. An amateur archeologist collected the commingled remains of five adults from the surface of the ground and donated them to the University of Michigan Museum of Anthropology (UMMA). One cranium shows evidence of cradle boarding. No date or time period for the human remains could be established. No known individuals were identified. No associated funerary objects are present.\\n        On an unknown date in the 1930s, human remains representing, at minimum, 1 individual were removed from the Vogelaar site (20SA330) in Saginaw County, MI. An amateur archeologist collected the remains of an infant from the surface of the ground as part of an archeological survey in a plowed agricultural field. He donated the human remains to the UMMA in 1978. During the 1960s, archaeologists from the UMMA conducted excavations in the area of this site and found evidence of a Native American habitation area, but no human remains were discovered. The infant\\'s remains are believed to be associated with the habitation area. The human remains are believed to date to the Middle-to-Late Woodland Period (300 B.C.-1400 A.D.) based on diagnostic artifacts collected from the associated habitation area. No known individuals were identified. No associated funerary objects are present.\\n        On an unknown date between 1915 and 1950, human remains representing, at minimum, 1 individual were removed from the Cavanaugh site (20SA19) in Saginaw County, MI. An amateur archeologist collected the remains of one adult from the surface of the ground near Gratiot Road and donated them to the UMMA in 1957. No date or time period for the human remains could be established. No known individuals were identified. No associated funerary objects are present.\\n        On an unknown date between 1915 and 1950, human remains representing, at minimum, 1 individual, were removed from the Mound Hill site (20SA26) in Saginaw County, MI. An amateur archeologist collected an adult foot phalanx from the surface of the ground. On an unknown date between 1950 and November 13, 1990, these human remains were donated to the UMMA. The human remains date to the Pre-Contact Period (9150 B.C.-1640 A.D.) based on documentation of a mound at the site. No known individuals were identified. No associated funerary objects are present.\\n        On an unknown date prior to 1941, human remains representing, at minimum, 1 individual were removed from the Fisher site (20SA29) in Saginaw County, MI. A local resident collected the remains of one adult from the surface at a location in Bridgeport Township. The human remains were given to an amateur archeologist in 1950, who subsequently donated them to the UMMA. No date or time period for the human remains could be established. No known individuals were identified. No associated funerary objects are present.\\n        In 1913, human remains representing, at minimum, 1 individual were removed from the Huron Valley Cemetery site (20SA36) in Saginaw County, MI. A local farmer and his sons collected the remains of a middle-aged female from the surface of the ground in one of their agricultural fields somewhere near the Cass River. They gave the human remains to an amateur archeologist who subsequently donated them to the UMMA in 1932. A projectile point was found embedded on the anterior blade of the female\\'s right ilium. The projectile point is still present and will be kept with the human remains, but it is not believed to be an associated funerary object. The human remains date to the Late Woodland Period (500-1400 A.D.) based on the projectile point. No known individuals were identified. No associated funerary objects are present.\\n        On an unknown date between 1915 and 1950, human remains representing, at minimum, 1 individual were removed from the Letterman site (20SA41) in Saginaw County, MI. An amateur archaeologist collected the remains of one adult from the surface of the ground near the Cass River and donated them to the UMMA. No date or time period for the human remains could be established. No known individuals were identified. No associated funerary objects are present.\\n        On an unknown date between 1915 and 1950, human remains representing, at minimum, 1 individual were removed from the Sand Ridge site (20SA69) in Saginaw County, MI. An amateur archeologist collected the remains of one adult (probably female) from the surface of the ground near the Pere Marquette Railroad and donated them to the UMMA. Grave looters were known to have visited the area frequently. The human remains date to the Pre-Contact Period (9150 B.C.-1400 A.D.) based on diagnostic artifacts that are not in the UMMA\\'s collections, but are known to have come from the site. No known individuals were identified. No associated funerary objects are present.\\n\\n        On an unknown date in the 1920s, human remains representing, at minimum, 1 individual was removed from the Dead Creek site (20SA34) in Saginaw County, MI. An amateur archeologist collected the remains of one adult on the surface near Dead Creek in Frankenmuth Township and donated them to the UMMA in 1932. He reported finding evidence of a Native American village in the vicinity, also located near Dead Creek. Researcher H.I. Smith also reported a Pre-Contact Period cemetery, designated as the Simons Cemetery, located in the vicinity. The human remains date to the Pre-Contact Period (8500 B.C.-1400 A.D.) based on the Smith reference. No known individuals were identified. No associated funerary objects are present.\\n        On an unknown date, human remains representing, at minimum, 4 individuals were removed from Near Saginaw site in Saginaw County, MI. The remains were found among the UMMA\\'s collections in 1993 during NAGPRA compliance activities. The remains of two adults, one adolescent, and one child were determined to be Native American based on cranial morphology. No date or time period could be established. No known individuals were identified. No associated funerary objects are present.\\n        On an unknown date in the 1930s, human remains representing, at minimum, 1 individual were removed from the Nason Hill site (20SA121) in Saginaw County, MI. An amateur archeologist collected the human remains, found among a mixture of surface assemblages with no archeological contexts, and donated them to the UMMA in 1978. No date or time period for the human remains could be established. No known individuals were identified. No associated funerary objects are present.\\n        Determinations Made by the University of Michigan Museum of Anthropology\\n        Officials of the University of Michigan Museum of Anthropology have determined that:\\n        \\xe2\\x80\\xa2 Pursuant to 25 U.S.C. 3001(9), the human remains described in this notice are Native American based on cranial morphology, dental traits, accession documentation, and archeological context.\\n        \\xe2\\x80\\xa2 Pursuant to 25 U.S.C. 3001(9), the human remains described in this notice represent the physical remains of 18 individuals of Native American ancestry.\\n        \\xe2\\x80\\xa2 Pursuant to 25 U.S.C. 3001(2), a relationship of shared group identity cannot be reasonably traced between the Native American human remains and any present-day Indian tribe.\\n        \\xe2\\x80\\xa2 According to final judgments of the Indian Claims Commission or the Court of Federal Claims, the land from which the Native American human remains were removed is the aboriginal land of the Saginaw Chippewa Indian Tribe of Michigan.\\n        \\xe2\\x80\\xa2 Treaties, Acts of Congress, or Executive Orders, indicate that the land from which the Native American human remains were removed is the aboriginal land of The Tribes.\\n        \\xe2\\x80\\xa2 Pursuant to 43 CFR 10.11(c)(1), the disposition of the human remains may be to The Tribes.\\n        Additional Requestors and Disposition\\n\\n        Representatives of any Indian tribe or Native Hawaiian organization not identified in this notice that wish to request transfer of control of these human remains should submit a written request with information in support of the request to Dr. Ben Secunda, NAGPRA Project Manager, University of Michigan, Office of the Vice President for Research, 4080 Fleming Building, 503 Thompson St., Ann Arbor, MI 48109-1340, telephone (734) 647-9085, email bsecunda@umich.edu, by December 2, 2013. After that date, if no additional requestors have come forward, transfer of control of the human remains to The Tribes may proceed.\\n        The University of Michigan is responsible for notifying The Tribes that this notice has been published.\\n        \\n          Dated: September 16, 2013.\\n          Sherry Hutt,\\n          Manager, National NAGPRA Program.\\n        \\n      \\n      [FR Doc. 2013-25983 Filed 10-30-13; 8:45 am]\\n      BILLING CODE 4312-50-P\\n    ", "agency1": "DEPARTMENT OF THE INTERIOR", "sub_agency1": "National Park Service", "dep_doc": "[NPS-WASO-NAGPRA-14040; PPWOCRADN0-PCU00RP14.R50000]", "subject": "Notice of Inventory Completion: University of Michigan, Ann Arbor, MI", "agency2": "National Park Service, Interior.", "action": "Notice.", "summary": "The University of Michigan has completed an inventory of human remains, in consultation with the appropriate Indian tribes or Native Hawaiian organizations, and has determined that there is no cultural affiliation between the human remains and any present-day Indian tribes or Native Hawaiian organizations. Representatives of any Indian tribe or Native Hawaiian organization not identified in this notice that wish to request transfer of control of these human remains should submit a written request to the University of Michigan. If no additional requestors come forward, transfer of control of the human remains to the Indian tribes or Native Hawaiian organizations stated in this notice may proceed.", "dates": "Representatives of any Indian tribe or Native Hawaiian organization not identified in this notice that wish to request transfer of control of these human remains should submit a written request with information in support of the request to the University of Michigan at the address in this notice by December 2, 2013.", "addresses": "Dr. Ben Secunda, NAGPRA Project Manager, University of Michigan, Office of the Vice President for Research, 4080 Fleming Building, 503 Thompson St., Ann Arbor, MI 48109-1340, telephone (734) 647-9085, email bsecunda@umich.edu.\\n          ", "signature_dated": "Dated: September 16, 2013.", "signature_name": "Sherry Hutt,", "signature_title": "Manager, National NAGPRA Program.", "fr_doc": "[FR Doc. 2013-25983 Filed 10-30-13; 8:45 am]", "billing_code": "BILLING CODE 4312-50-P", "supp_info": "SUPPLEMENTARY INFORMATION: \n Notice is here given in accordance with the Native American Graves Protection and Repatriation Act (NAGPRA), 25 U.S.C. 3003, of the completion of an inventory of human remains under the control of the University of Michigan, Ann Arbor, MI. The human remains were removed from Saginaw County, MI. \n This notice is published as part of the National Park Service\\'s administrative responsibilities under NAGPRA, 25 U.S.C. 3003(d)(3) and 43 CFR 10.11(d). The determinations in this notice are the sole responsibility of the museum, institution, or Federal agency that has control of the Native American human remains. The National Park Service is not responsible for the determinations in this notice. \n Consultation \n A detailed assessment of the human remains was made by the University of Michigan Museum of Anthropology professional staff in consultation with representatives of the Bay Mills Indian Community, Michigan; Chippewa-Cree Indians of the Rocky Boy\\'s Reservation, Montana; Grand Traverse Band of Ottawa and Chippewa Indians, Michigan; Keweenaw Bay Indian Community, Michigan; Lac Vieux Desert Band of Lake Superior Chippewa Indians of Michigan; Saginaw Chippewa Indian Tribe of Michigan; and the Sault Ste. Marie Tribe of Chippewa Indians, Michigan. \n Additional requests for consultation were sent to the Bad River Band of the Lake Superior Tribe of Chippewa Indians of the Bad River Reservation, Wisconsin; Bois Forte Band (Nett Lake) of the Minnesota Chippewa Tribe, Minnesota; Fond du Lac Band of the Minnesota Chippewa Tribe, Minnesota; Grand Portage Band of the Minnesota Chippewa Tribe, Minnesota; Kickapoo Traditional Tribe of Texas; Kickapoo Tribe of Indians of the Kickapoo Reservation in Kansas; Kickapoo Tribe of Oklahoma; Lac Courte Oreilles Band of Lake Superior Chippewa Indians of Wisconsin; Lac du Flambeau Band of Lake Superior Chippewa Indians of the Lac du Flambeau Reservation of Wisconsin; Leech Lake Band of the Minnesota Chippewa Tribe, Minnesota; Mille Lacs Band of the Minnesota Chippewa Tribe, Minnesota; Red Cliff Band of Lake Superior Chippewa Indians of Wisconsin; Red Lake Band of Chippewa Indians, Minnesota; Sac & Fox Nation of Missouri in Kansas and Nebraska; Sac & Fox Nation, Oklahoma; Sac & Fox Tribe of the Mississippi in Iowa; Sokaogon Chippewa Community, Wisconsin; St. Croix Chippewa Indians of Wisconsin; Turtle Mountain Band of Chippewa Indians of North Dakota; and the White Earth Band of the Minnesota Chippewa Tribe, Minnesota. \n Hereafter, all tribes listed in this section are referred to as \\xe2\\x80\\x9cThe Tribes.\\xe2\\x80\\x9d \n History and Description of the Remains \n On an unknown date between 1915 and 1950, human remains representing, at minimum, 5 individuals were removed from the Green Point site (20SA1) in Saginaw County, MI. An amateur archeologist collected the commingled remains of five adults from the surface of the ground and donated them to the University of Michigan Museum of Anthropology (UMMA). One cranium shows evidence of cradle boarding. No date or time period for the human remains could be established. No known individuals were identified. No associated funerary objects are present. \n On an unknown date in the 1930s, human remains representing, at minimum, 1 individual were removed from the Vogelaar site (20SA330) in Saginaw County, MI. An amateur archeologist collected the remains of an infant from the surface of the ground as part of an archeological survey in a plowed agricultural field. He donated the human remains to the UMMA in 1978. During the 1960s, archaeologists from the UMMA conducted excavations in the area of this site and found evidence of a Native American habitation area, but no human remains were discovered. The infant\\'s remains are believed to be associated with the habitation area. The human remains are believed to date to the Middle-to-Late Woodland Period (300 B.C.-1400 A.D.) based on diagnostic artifacts collected from the associated habitation area. No known individuals were identified. No associated funerary objects are present. \n On an unknown date between 1915 and 1950, human remains representing, at minimum, 1 individual were removed from the Cavanaugh site (20SA19) in Saginaw County, MI. An amateur archeologist collected the remains of one adult from the surface of the ground near Gratiot Road and donated them to the UMMA in 1957. No date or time period for the human remains could be established. No known individuals were identified. No associated funerary objects are present. \n On an unknown date between 1915 and 1950, human remains representing, at minimum, 1 individual, were removed from the Mound Hill site (20SA26) in Saginaw County, MI. An amateur archeologist collected an adult foot phalanx from the surface of the ground. On an unknown date between 1950 and November 13, 1990, these human remains were donated to the UMMA. The human remains date to the Pre-Contact Period (9150 B.C.-1640 A.D.) based on documentation of a mound at the site. No known individuals were identified. No associated funerary objects are present. \n On an unknown date prior to 1941, human remains representing, at minimum, 1 individual were removed from the Fisher site (20SA29) in Saginaw County, MI. A local resident collected the remains of one adult from the surface at a location in Bridgeport Township. The human remains were given to an amateur archeologist in 1950, who subsequently donated them to the UMMA. No date or time period for the human remains could be established. No known individuals were identified. No associated funerary objects are present. \n In 1913, human remains representing, at minimum, 1 individual were removed from the Huron Valley Cemetery site (20SA36) in Saginaw County, MI. A local farmer and his sons collected the remains of a middle-aged female from the surface of the ground in one of their agricultural fields somewhere near the Cass River. They gave the human remains to an amateur archeologist who subsequently donated them to the UMMA in 1932. A projectile point was found embedded on the anterior blade of the female\\'s right ilium. The projectile point is still present and will be kept with the human remains, but it is not believed to be an associated funerary object. The human remains date to the Late Woodland Period (500-1400 A.D.) based on the projectile point. No known individuals were identified. No associated funerary objects are present. \n On an unknown date between 1915 and 1950, human remains representing, at minimum, 1 individual were removed from the Letterman site (20SA41) in Saginaw County, MI. An amateur archaeologist collected the remains of one adult from the surface of the ground near the Cass River and donated them to the UMMA. No date or time period for the human remains could be established. No known individuals were identified. No associated funerary objects are present. \n On an unknown date between 1915 and 1950, human remains representing, at minimum, 1 individual were removed from the Sand Ridge site (20SA69) in Saginaw County, MI. An amateur archeologist collected the remains of one adult (probably female) from the surface of the ground near the Pere Marquette Railroad and donated them to the UMMA. Grave looters were known to have visited the area frequently. The human remains date to the Pre-Contact Period (9150 B.C.-1400 A.D.) based on diagnostic artifacts that are not in the UMMA\\'s collections, but are known to have come from the site. No known individuals were identified. No associated funerary objects are present. \n On an unknown date in the 1920s, human remains representing, at minimum, 1 individual was removed from the Dead Creek site (20SA34) in Saginaw County, MI. An amateur archeologist collected the remains of one adult on the surface near Dead Creek in Frankenmuth Township and donated them to the UMMA in 1932. He reported finding evidence of a Native American village in the vicinity, also located near Dead Creek. Researcher H.I. Smith also reported a Pre-Contact Period cemetery, designated as the Simons Cemetery, located in the vicinity. The human remains date to the Pre-Contact Period (8500 B.C.-1400 A.D.) based on the Smith reference. No known individuals were identified. No associated funerary objects are present. \n On an unknown date, human remains representing, at minimum, 4 individuals were removed from Near Saginaw site in Saginaw County, MI. The remains were found among the UMMA\\'s collections in 1993 during NAGPRA compliance activities. The remains of two adults, one adolescent, and one child were determined to be Native American based on cranial morphology. No date or time period could be established. No known individuals were identified. No associated funerary objects are present. \n On an unknown date in the 1930s, human remains representing, at minimum, 1 individual were removed from the Nason Hill site (20SA121) in Saginaw County, MI. An amateur archeologist collected the human remains, found among a mixture of surface assemblages with no archeological contexts, and donated them to the UMMA in 1978. No date or time period for the human remains could be established. No known individuals were identified. No associated funerary objects are present. \n Determinations Made by the University of Michigan Museum of Anthropology \n Officials of the University of Michigan Museum of Anthropology have determined that: \n \\xe2\\x80\\xa2 Pursuant to 25 U.S.C. 3001(9), the human remains described in this notice are Native American based on cranial morphology, dental traits, accession documentation, and archeological context. \n \\xe2\\x80\\xa2 Pursuant to 25 U.S.C. 3001(9), the human remains described in this notice represent the physical remains of 18 individuals of Native American ancestry. \n \\xe2\\x80\\xa2 Pursuant to 25 U.S.C. 3001(2), a relationship of shared group identity cannot be reasonably traced between the Native American human remains and any present-day Indian tribe. \n \\xe2\\x80\\xa2 According to final judgments of the Indian Claims Commission or the Court of Federal Claims, the land from which the Native American human remains were removed is the aboriginal land of the Saginaw Chippewa Indian Tribe of Michigan. \n \\xe2\\x80\\xa2 Treaties, Acts of Congress, or Executive Orders, indicate that the land from which the Native American human remains were removed is the aboriginal land of The Tribes. \n \\xe2\\x80\\xa2 Pursuant to 43 CFR 10.11(c)(1), the disposition of the human remains may be to The Tribes. \n Additional Requestors and Disposition \n Representatives of any Indian tribe or Native Hawaiian organization not identified in this notice that wish to request transfer of control of these human remains should submit a written request with information in support of the request to Dr. Ben Secunda, NAGPRA Project Manager, University of Michigan, Office of the Vice President for Research, 4080 Fleming Building, 503 Thompson St., Ann Arbor, MI 48109-1340, telephone (734) 647-9085, email bsecunda@umich.edu, by December 2, 2013. After that date, if no additional requestors have come forward, transfer of control of the human remains to The Tribes may proceed. \n The University of Michigan is responsible for notifying The Tribes that this notice has been published. \n ", "consultation": "A detailed assessment of the human remains was made by the University of Michigan Museum of Anthropology professional staff in consultation with representatives of the Bay Mills Indian Community, Michigan; Chippewa-Cree Indians of the Rocky Boy\\'s Reservation, Montana; Grand Traverse Band of Ottawa and Chippewa Indians, Michigan; Keweenaw Bay Indian Community, Michigan; Lac Vieux Desert Band of Lake Superior Chippewa Indians of Michigan; Saginaw Chippewa Indian Tribe of Michigan; and the Sault Ste. Marie Tribe of Chippewa Indians, Michigan. \n Additional requests for consultation were sent to the Bad River Band of the Lake Superior Tribe of Chippewa Indians of the Bad River Reservation, Wisconsin; Bois Forte Band (Nett Lake) of the Minnesota Chippewa Tribe, Minnesota; Fond du Lac Band of the Minnesota Chippewa Tribe, Minnesota; Grand Portage Band of the Minnesota Chippewa Tribe, Minnesota; Kickapoo Traditional Tribe of Texas; Kickapoo Tribe of Indians of the Kickapoo Reservation in Kansas; Kickapoo Tribe of Oklahoma; Lac Courte Oreilles Band of Lake Superior Chippewa Indians of Wisconsin; Lac du Flambeau Band of Lake Superior Chippewa Indians of the Lac du Flambeau Reservation of Wisconsin; Leech Lake Band of the Minnesota Chippewa Tribe, Minnesota; Mille Lacs Band of the Minnesota Chippewa Tribe, Minnesota; Red Cliff Band of Lake Superior Chippewa Indians of Wisconsin; Red Lake Band of Chippewa Indians, Minnesota; Sac & Fox Nation of Missouri in Kansas and Nebraska; Sac & Fox Nation, Oklahoma; Sac & Fox Tribe of the Mississippi in Iowa; Sokaogon Chippewa Community, Wisconsin; St. Croix Chippewa Indians of Wisconsin; Turtle Mountain Band of Chippewa Indians of North Dakota; and the White Earth Band of the Minnesota Chippewa Tribe, Minnesota. \n Hereafter, all tribes listed in this section are referred to as \\xe2\\x80\\x9cThe Tribes.\\xe2\\x80\\x9d \n ", "h_d_r": "On an unknown date between 1915 and 1950, human remains representing, at minimum, 5 individuals were removed from the Green Point site (20SA1) in Saginaw County, MI. An amateur archeologist collected the commingled remains of five adults from the surface of the ground and donated them to the University of Michigan Museum of Anthropology (UMMA). One cranium shows evidence of cradle boarding. No date or time period for the human remains could be established. No known individuals were identified. No associated funerary objects are present. \n On an unknown date in the 1930s, human remains representing, at minimum, 1 individual were removed from the Vogelaar site (20SA330) in Saginaw County, MI. An amateur archeologist collected the remains of an infant from the surface of the ground as part of an archeological survey in a plowed agricultural field. He donated the human remains to the UMMA in 1978. During the 1960s, archaeologists from the UMMA conducted excavations in the area of this site and found evidence of a Native American habitation area, but no human remains were discovered. The infant\\'s remains are believed to be associated with the habitation area. The human remains are believed to date to the Middle-to-Late Woodland Period (300 B.C.-1400 A.D.) based on diagnostic artifacts collected from the associated habitation area. No known individuals were identified. No associated funerary objects are present. \n On an unknown date between 1915 and 1950, human remains representing, at minimum, 1 individual were removed from the Cavanaugh site (20SA19) in Saginaw County, MI. An amateur archeologist collected the remains of one adult from the surface of the ground near Gratiot Road and donated them to the UMMA in 1957. No date or time period for the human remains could be established. No known individuals were identified. No associated funerary objects are present. \n On an unknown date between 1915 and 1950, human remains representing, at minimum, 1 individual, were removed from the Mound Hill site (20SA26) in Saginaw County, MI. An amateur archeologist collected an adult foot phalanx from the surface of the ground. On an unknown date between 1950 and November 13, 1990, these human remains were donated to the UMMA. The human remains date to the Pre-Contact Period (9150 B.C.-1640 A.D.) based on documentation of a mound at the site. No known individuals were identified. No associated funerary objects are present. \n On an unknown date prior to 1941, human remains representing, at minimum, 1 individual were removed from the Fisher site (20SA29) in Saginaw County, MI. A local resident collected the remains of one adult from the surface at a location in Bridgeport Township. The human remains were given to an amateur archeologist in 1950, who subsequently donated them to the UMMA. No date or time period for the human remains could be established. No known individuals were identified. No associated funerary objects are present. \n In 1913, human remains representing, at minimum, 1 individual were removed from the Huron Valley Cemetery site (20SA36) in Saginaw County, MI. A local farmer and his sons collected the remains of a middle-aged female from the surface of the ground in one of their agricultural fields somewhere near the Cass River. They gave the human remains to an amateur archeologist who subsequently donated them to the UMMA in 1932. A projectile point was found embedded on the anterior blade of the female\\'s right ilium. The projectile point is still present and will be kept with the human remains, but it is not believed to be an associated funerary object. The human remains date to the Late Woodland Period (500-1400 A.D.) based on the projectile point. No known individuals were identified. No associated funerary objects are present. \n On an unknown date between 1915 and 1950, human remains representing, at minimum, 1 individual were removed from the Letterman site (20SA41) in Saginaw County, MI. An amateur archaeologist collected the remains of one adult from the surface of the ground near the Cass River and donated them to the UMMA. No date or time period for the human remains could be established. No known individuals were identified. No associated funerary objects are present. \n On an unknown date between 1915 and 1950, human remains representing, at minimum, 1 individual were removed from the Sand Ridge site (20SA69) in Saginaw County, MI. An amateur archeologist collected the remains of one adult (probably female) from the surface of the ground near the Pere Marquette Railroad and donated them to the UMMA. Grave looters were known to have visited the area frequently. The human remains date to the Pre-Contact Period (9150 B.C.-1400 A.D.) based on diagnostic artifacts that are not in the UMMA\\'s collections, but are known to have come from the site. No known individuals were identified. No associated funerary objects are present. \n On an unknown date in the 1920s, human remains representing, at minimum, 1 individual was removed from the Dead Creek site (20SA34) in Saginaw County, MI. An amateur archeologist collected the remains of one adult on the surface near Dead Creek in Frankenmuth Township and donated them to the UMMA in 1932. He reported finding evidence of a Native American village in the vicinity, also located near Dead Creek. Researcher H.I. Smith also reported a Pre-Contact Period cemetery, designated as the Simons Cemetery, located in the vicinity. The human remains date to the Pre-Contact Period (8500 B.C.-1400 A.D.) based on the Smith reference. No known individuals were identified. No associated funerary objects are present. \n On an unknown date, human remains representing, at minimum, 4 individuals were removed from Near Saginaw site in Saginaw County, MI. The remains were found among the UMMA\\'s collections in 1993 during NAGPRA compliance activities. The remains of two adults, one adolescent, and one child were determined to be Native American based on cranial morphology. No date or time period could be established. No known individuals were identified. No associated funerary objects are present. \n On an unknown date in the 1930s, human remains representing, at minimum, 1 individual were removed from the Nason Hill site (20SA121) in Saginaw County, MI. An amateur archeologist collected the human remains, found among a mixture of surface assemblages with no archeological contexts, and donated them to the UMMA in 1978. No date or time period for the human remains could be established. No known individuals were identified. No associated funerary objects are present. \n ", "h_d_ci": "Null", "determinations": "Determinations Made by the University of Michigan Museum of Anthropology \n Officials of the University of Michigan Museum of Anthropology have determined that: \n \\xe2\\x80\\xa2 Pursuant to 25 U.S.C. 3001(9), the human remains described in this notice are Native American based on cranial morphology, dental traits, accession documentation, and archeological context. \n \\xe2\\x80\\xa2 Pursuant to 25 U.S.C. 3001(9), the human remains described in this notice represent the physical remains of 18 individuals of Native American ancestry. \n \\xe2\\x80\\xa2 Pursuant to 25 U.S.C. 3001(2), a relationship of shared group identity cannot be reasonably traced between the Native American human remains and any present-day Indian tribe. \n \\xe2\\x80\\xa2 According to final judgments of the Indian Claims Commission or the Court of Federal Claims, the land from which the Native American human remains were removed is the aboriginal land of the Saginaw Chippewa Indian Tribe of Michigan. \n \\xe2\\x80\\xa2 Treaties, Acts of Congress, or Executive Orders, indicate that the land from which the Native American human remains were removed is the aboriginal land of The Tribes. \n \\xe2\\x80\\xa2 Pursuant to 43 CFR 10.11(c)(1), the disposition of the human remains may be to The Tribes. \n ", "a_r_d": "Representatives of any Indian tribe or Native Hawaiian organization not identified in this notice that wish to request transfer of control of these human remains should submit a written request with information in support of the request to Dr. Ben Secunda, NAGPRA Project Manager, University of Michigan, Office of the Vice President for Research, 4080 Fleming Building, 503 Thompson St., Ann Arbor, MI 48109-1340, telephone (734) 647-9085, email bsecunda@umich.edu, by December 2, 2013. After that date, if no additional requestors have come forward, transfer of control of the human remains to The Tribes may proceed. \n The University of Michigan is responsible for notifying The Tribes that this notice has been published. \n "}