{"index": "I_904", "messy_full": "\\n      \\n        DEPARTMENT OF THE INTERIOR\\n        National Park Service\\n        [NPS-WASO-NAGPRA-13893; PPWOCRADN0-PCU00RP14.R50000]\\n        Notice of Inventory Completion: U.S. Department of the Interior, National Park Service, Tumacacori National Historical Park, Tumacacori, AZ; Correction\\n        \\n          AGENCY:\\n          National Park Service, Interior.\\n        \\n        \\n          ACTION:\\n          Notice; correction.\\n        \\n        \\n          SUMMARY:\\n\\n          The U.S. Department of the Interior, National Park Service, Tumacacori National Historical Park has corrected an inventory of human remains and associated funerary objects published in a Notice of Inventory Completion in the Federal Register on July 7, 2009. This notice corrects the number of associated funerary objects. Transfer of control of the items in this correction notice has occurred.\\n        \\n        \\n          ADDRESSES:\\n\\n          Bob Love, Superintendent, Tumacacori National Historical Park, P.O. Box 8067, Tumacacori, AZ 85640, telephone (520) 398-2341 Ext. 52, email bob_love@nps.gov.\\n          \\n        \\n      \\n      \\n        SUPPLEMENTARY INFORMATION:\\n        Notice is here given in accordance with the Native American Graves Protection and Repatriation Act (NAGPRA), 25 U.S.C. 3003, of the correction of an inventory of human remains and associated funerary objects under the control of Tumacacori National Historical Park, Tumacacori, AZ. The human remains and associated funerary objects were removed from areas near Tumacacori Mission, Santa Cruz County, AZ.\\n        This notice is published as part of the National Park Service\\'s administrative responsibilities under NAGPRA, 25 U.S.C. 3003(d)(3). The determinations in this notice are the sole responsibility of the Superintendent, Tumacacori National Historical Park.\\n\\n        This notice corrects the number of associated funerary objects published in a Notice of Inventory Completion in the Federal Register (74, FR 32184-32185, July 7, 2009). After publication, one additional associated funerary object was found. Transfer of control of the items in this correction notice has occurred.\\n        Correction\\n        In the Federal Register (74, FR 32184-32185, July 7, 2009), the following paragraph is inserted after paragraph six:\\n        \\n        \\n          In the 1930s, one cremation jar was removed from an unknown location near Tumacacori in Santa Cruz County, AZ by custodian George Boundey. It is believed that this jar was associated with the individuals removed in 1934 and 1935 described above.\\n        \\n        \\n        In the Federal Register (74, FR 32184-32185, July 7, 2009), paragraph 13, sentence 2 is corrected by substituting the following sentence:\\n        \\n        \\n          Officials of Tumacacori National Historical Park also have determined that, pursuant to 25 U.S.C. 3001 (3)(A), the 84 objects described above are reasonably believed to have been placed with or near individual human remains at the time of death or later as part of the death rite or ceremony.\\n        \\n        \\n        Additional Requestors and Disposition\\n\\n        Transfer of control of the human remains and associated funerary objects occurred after the 30 day waiting period expired for the original July 7, 2009 Notice of Inventory Completion. For questions related to this notice, contact Bob Love, Superintendent, Tumacacori National Historical Park, P.O. Box 8067, Tumacacori, AZ 85640, telephone (520) 398-2341 Ext. 52, email bob_love@nps.gov.\\n        \\n        Tumacacori National Historical Park is responsible for notifying the Ak Chin Indian Community of the Maricopa (Ak Chin) Indian Reservation, Arizona; Fort Sill Apache Tribe of Oklahoma; Gila River Indian Community of the Gila River Indian Reservation, Arizona; Hopi Tribe of Arizona; Jicarilla Apache Nation, New Mexico; Mescalero Apache Tribe of the Mescalero Reservation, New Mexico; Pascua Yaqui Tribe of Arizona; Salt River Pima-Maricopa Indian Community of the Salt River Reservation, Arizona; San Carlos Apache Tribe of the San Carlos Reservation, Arizona; Tohono O\\'odham Nation of Arizona; Tonto Apache Tribe of Arizona; White Mountain Apache Tribe of the Fort Apache Reservation, Arizona; and Zuni Tribe of the Zuni Reservation, New Mexico that this notice has been published.\\n        \\n          Dated: August 21, 2013.\\n          Sherry Hutt,\\n          Manager, National NAGPRA Program. \\n        \\n      \\n      [FR Doc. 2013-23797 Filed 9-27-13; 8:45 am]\\n      BILLING CODE 4312-50-P\\n    ", "agency1": "DEPARTMENT OF THE INTERIOR", "sub_agency1": "National Park Service", "dep_doc": "[NPS-WASO-NAGPRA-13893; PPWOCRADN0-PCU00RP14.R50000]", "subject": "Notice of Inventory Completion: U.S. Department of the Interior, National Park Service, Tumacacori National Historical Park, Tumacacori, AZ; Correction", "agency2": "National Park Service, Interior.", "action": "Notice; correction.", "summary": "The U.S. Department of the Interior, National Park Service, Tumacacori National Historical Park has corrected an inventory of human remains and associated funerary objects published in a Notice of Inventory Completion in the Federal Register on July 7, 2009. This notice corrects the number of associated funerary objects. Transfer of control of the items in this correction notice has occurred.", "dates": "Null", "addresses": "Bob Love, Superintendent, Tumacacori National Historical Park, P.O. Box 8067, Tumacacori, AZ 85640, telephone (520) 398-2341 Ext. 52, email bob_love@nps.gov.\\n          ", "signature_dated": "Dated: August 21, 2013.", "signature_name": "Sherry Hutt,", "signature_title": "Manager, National NAGPRA Program. ", "fr_doc": "[FR Doc. 2013-23797 Filed 9-27-13; 8:45 am]", "billing_code": "BILLING CODE 4312-50-P", "supp_info": "SUPPLEMENTARY INFORMATION: \n Notice is here given in accordance with the Native American Graves Protection and Repatriation Act (NAGPRA), 25 U.S.C. 3003, of the correction of an inventory of human remains and associated funerary objects under the control of Tumacacori National Historical Park, Tumacacori, AZ. The human remains and associated funerary objects were removed from areas near Tumacacori Mission, Santa Cruz County, AZ. \n This notice is published as part of the National Park Service\\'s administrative responsibilities under NAGPRA, 25 U.S.C. 3003(d)(3). The determinations in this notice are the sole responsibility of the Superintendent, Tumacacori National Historical Park. \n This notice corrects the number of associated funerary objects published in a Notice of Inventory Completion in the Federal Register (74, FR 32184-32185, July 7, 2009). After publication, one additional associated funerary object was found. Transfer of control of the items in this correction notice has occurred. \n Correction \n In the Federal Register (74, FR 32184-32185, July 7, 2009), the following paragraph is inserted after paragraph six: \n In the Federal Register (74, FR 32184-32185, July 7, 2009), paragraph 13, sentence 2 is corrected by substituting the following sentence: \n Additional Requestors and Disposition \n Transfer of control of the human remains and associated funerary objects occurred after the 30 day waiting period expired for the original July 7, 2009 Notice of Inventory Completion. For questions related to this notice, contact Bob Love, Superintendent, Tumacacori National Historical Park, P.O. Box 8067, Tumacacori, AZ 85640, telephone (520) 398-2341 Ext. 52, email bob_love@nps.gov.\\n         \n Tumacacori National Historical Park is responsible for notifying the Ak Chin Indian Community of the Maricopa (Ak Chin) Indian Reservation, Arizona; Fort Sill Apache Tribe of Oklahoma; Gila River Indian Community of the Gila River Indian Reservation, Arizona; Hopi Tribe of Arizona; Jicarilla Apache Nation, New Mexico; Mescalero Apache Tribe of the Mescalero Reservation, New Mexico; Pascua Yaqui Tribe of Arizona; Salt River Pima-Maricopa Indian Community of the Salt River Reservation, Arizona; San Carlos Apache Tribe of the San Carlos Reservation, Arizona; Tohono O\\'odham Nation of Arizona; Tonto Apache Tribe of Arizona; White Mountain Apache Tribe of the Fort Apache Reservation, Arizona; and Zuni Tribe of the Zuni Reservation, New Mexico that this notice has been published. \n ", "consultation": "Null", "h_d_r": "Null", "h_d_ci": "Null", "determinations": "Null", "a_r_d": "Transfer of control of the human remains and associated funerary objects occurred after the 30 day waiting period expired for the original July 7, 2009 Notice of Inventory Completion. For questions related to this notice, contact Bob Love, Superintendent, Tumacacori National Historical Park, P.O. Box 8067, Tumacacori, AZ 85640, telephone (520) 398-2341 Ext. 52, email bob_love@nps.gov.\\n         \n Tumacacori National Historical Park is responsible for notifying the Ak Chin Indian Community of the Maricopa (Ak Chin) Indian Reservation, Arizona; Fort Sill Apache Tribe of Oklahoma; Gila River Indian Community of the Gila River Indian Reservation, Arizona; Hopi Tribe of Arizona; Jicarilla Apache Nation, New Mexico; Mescalero Apache Tribe of the Mescalero Reservation, New Mexico; Pascua Yaqui Tribe of Arizona; Salt River Pima-Maricopa Indian Community of the Salt River Reservation, Arizona; San Carlos Apache Tribe of the San Carlos Reservation, Arizona; Tohono O\\'odham Nation of Arizona; Tonto Apache Tribe of Arizona; White Mountain Apache Tribe of the Fort Apache Reservation, Arizona; and Zuni Tribe of the Zuni Reservation, New Mexico that this notice has been published. \n "}