{"index": "I_905", "messy_full": "\\n      \\n        \\n        DEPARTMENT OF THE INTERIOR\\n        National Park Service\\n        [NPS-WASO-NAGPRA-13941; PPWOCRADN0-PCU00RP14.R50000]\\n        Notice of Inventory Completion: Fort Lewis College, Durango, CO; Correction\\n        \\n          AGENCY:\\n          National Park Service, Interior.\\n        \\n        \\n          ACTION:\\n          Notice; correction.\\n        \\n        \\n          SUMMARY:\\n\\n          The Fort Lewis College has corrected an inventory of human remains and associated funerary objects, published in a Notice of Inventory Completion in the Federal Register on October 11, 2011. This notice corrects the number of associated funerary objects.\\n        \\n        \\n          ADDRESSES:\\n\\n          Dawn Mulhern, Department of Anthropology, Fort Lewis College, 1000 Rim Dr., Durango, CO 81301, telephone (970) 247-7500, email MULHERN_D@fortlewis.edu\\n          \\n        \\n      \\n      \\n        SUPPLEMENTARY INFORMATION:\\n        Notice is here given in accordance with the Native American Graves Protection and Repatriation Act (NAGPRA), 25 U.S.C. 3003, of the correction of an inventory of human remains and associated funerary objects under the control of the Fort Lewis College. The human remains and associated funerary objects were removed from La Plata, CO.\\n        This notice is published as part of the National Park Service\\'s administrative responsibilities under NAGPRA, 25 U.S.C. 3003(d)(3). The determinations in this notice are the sole responsibility of the museum, institution, or Federal agency that has control of the Native American human remains and associated funerary objects. The National Park Service is not responsible for the determinations in this notice.\\n\\n        This notice corrects the number of associated funerary objects published in a Notice of Inventory Completion in the Federal Register (76 FR 62835-62838, October 11, 2011). The number of associated funerary objects was incorrectly reported in the original notice. Transfer of control of the items in this correction notice has occurred.\\n        Correction\\n        In the Federal Register (76 FR 62835-62838, October 11, 2011), paragraph 29, sentence five is corrected by substituting the following sentence:\\n        \\n        \\n          The six associated funerary objects are 1 Chapin grey pitcher, 1 greyware jar, 1 Chapin black-on-white bowl, 1 Piedra black-on-white bowl, 1 lot of shell beads, and 1 Chapin grey jar.\\n        \\n        \\n        In the Federal Register (76 FR 62835-62838, October 11, 2011), paragraph 56 is corrected by substituting the following sentence:\\n        \\n        \\n          Pursuant to 25 U.S.C. 3001(3)(A), the 151 objects described above are reasonably believed to have been placed with or near individual human remains at the time of death or later as part of the death rite or ceremony.\\n        \\n        \\n        The Fort Lewis College is responsible for notifying the Hopi Tribe of Arizona; Kewa Pueblo, New Mexico; Ohkay Owingeh, New Mexico; Pueblo of Acoma, New Mexico; Pueblo of Cochiti, New Mexico; Pueblo of Jemez, New Mexico; Pueblo of Isleta, New Mexico; Pueblo of Laguna, New Mexico; Pueblo of Nambe, New Mexico; Pueblo of Picuris, New Mexico; Pueblo of Pojoaque, New Mexico; Pueblo of San Felipe, New Mexico; Pueblo of San Ildefonso, New Mexico; Pueblo of Sandia, New Mexico; Pueblo of Santa Ana, New Mexico; Pueblo of Santa Clara, New Mexico; Pueblo of Taos, New Mexico; Pueblo of Tesuque, New Mexico; Pueblo of Zia, New Mexico; Ysleta Del Sur Pueblo of Texas; and the Zuni Tribe of the Zuni Reservation, New Mexico that this notice has been published.\\n        \\n          Dated: August 27, 2013.\\n          David Tarler,\\n          Acting Manager, National NAGPRA Program. \\n        \\n      \\n      [FR Doc. 2013-23816 Filed 9-27-13; 8:45 am]\\n      BILLING CODE 4312-50-P\\n    ", "agency1": "DEPARTMENT OF THE INTERIOR", "sub_agency1": "National Park Service", "dep_doc": "[NPS-WASO-NAGPRA-13941; PPWOCRADN0-PCU00RP14.R50000]", "subject": "Notice of Inventory Completion: Fort Lewis College, Durango, CO; Correction", "agency2": "National Park Service, Interior.", "action": "Notice; correction.", "summary": "The Fort Lewis College has corrected an inventory of human remains and associated funerary objects, published in a Notice of Inventory Completion in the Federal Register on October 11, 2011. This notice corrects the number of associated funerary objects.", "dates": "Null", "addresses": "Dawn Mulhern, Department of Anthropology, Fort Lewis College, 1000 Rim Dr., Durango, CO 81301, telephone (970) 247-7500, email MULHERN_D@fortlewis.edu\\n          ", "signature_dated": "Dated: August 27, 2013.", "signature_name": "David Tarler,", "signature_title": "Acting Manager, National NAGPRA Program. ", "fr_doc": "[FR Doc. 2013-23816 Filed 9-27-13; 8:45 am]", "billing_code": "BILLING CODE 4312-50-P", "supp_info": "SUPPLEMENTARY INFORMATION: \n Notice is here given in accordance with the Native American Graves Protection and Repatriation Act (NAGPRA), 25 U.S.C. 3003, of the correction of an inventory of human remains and associated funerary objects under the control of the Fort Lewis College. The human remains and associated funerary objects were removed from La Plata, CO. \n This notice is published as part of the National Park Service\\'s administrative responsibilities under NAGPRA, 25 U.S.C. 3003(d)(3). The determinations in this notice are the sole responsibility of the museum, institution, or Federal agency that has control of the Native American human remains and associated funerary objects. The National Park Service is not responsible for the determinations in this notice. \n This notice corrects the number of associated funerary objects published in a Notice of Inventory Completion in the Federal Register (76 FR 62835-62838, October 11, 2011). The number of associated funerary objects was incorrectly reported in the original notice. Transfer of control of the items in this correction notice has occurred. \n Correction \n In the Federal Register (76 FR 62835-62838, October 11, 2011), paragraph 29, sentence five is corrected by substituting the following sentence: \n In the Federal Register (76 FR 62835-62838, October 11, 2011), paragraph 56 is corrected by substituting the following sentence: \n The Fort Lewis College is responsible for notifying the Hopi Tribe of Arizona; Kewa Pueblo, New Mexico; Ohkay Owingeh, New Mexico; Pueblo of Acoma, New Mexico; Pueblo of Cochiti, New Mexico; Pueblo of Jemez, New Mexico; Pueblo of Isleta, New Mexico; Pueblo of Laguna, New Mexico; Pueblo of Nambe, New Mexico; Pueblo of Picuris, New Mexico; Pueblo of Pojoaque, New Mexico; Pueblo of San Felipe, New Mexico; Pueblo of San Ildefonso, New Mexico; Pueblo of Sandia, New Mexico; Pueblo of Santa Ana, New Mexico; Pueblo of Santa Clara, New Mexico; Pueblo of Taos, New Mexico; Pueblo of Tesuque, New Mexico; Pueblo of Zia, New Mexico; Ysleta Del Sur Pueblo of Texas; and the Zuni Tribe of the Zuni Reservation, New Mexico that this notice has been published. \n ", "consultation": "Null", "h_d_r": "Null", "h_d_ci": "Null", "determinations": "Null", "a_r_d": "Null"}