{"index": "I_916", "messy_full": "\\n      \\n        DEPARTMENT OF THE INTERIOR\\n        National Park Service\\n        [NPS-WASO-NAGPRA-13951; PPWOCRADN0-PCU00RP14.R50000]\\n        Notice of Inventory Completion: Michigan State Police, Mount Pleasant Post, Mount Pleasant, MI\\n        \\n          AGENCY:\\n          National Park Service, Interior.\\n        \\n        \\n          ACTION:\\n          Notice.\\n        \\n        \\n          SUMMARY:\\n          The Michigan State Police, Mount Pleasant Post, has completed an inventory of human remains, in consultation with the appropriate Indian tribes or Native Hawaiian organizations, and has determined that there is a cultural affiliation between the human remains and present-day Indian tribes or Native Hawaiian organizations. Lineal descendants or representatives of any Indian tribe or Native Hawaiian organization not identified in this notice that wish to request transfer of control of the human remains should submit a written request to the Michigan State Police, Mount Pleasant Post. If no additional requestors come forward, transfer of control of the human remains to the lineal descendants, Indian tribes, or Native Hawaiian organizations stated in this notice may proceed.\\n        \\n        \\n          DATES:\\n          Lineal descendants or representatives of any Indian tribe or Native Hawaiian organization not identified in this notice that wish to request transfer of control of these human remains should submit a written request with information in support of the request to the Michigan State Police, Mount Pleasant Post, at the address in this notice by October 30, 2013.\\n        \\n        \\n          ADDRESSES:\\n\\n          Detective Sergeant Gary Green; Michigan State Police, Mount Pleasant Post, 3580 S. Isabella Road, Mount Pleasant, MI 48858; telephone (989) 773-5951; email GreenG1@Michigan.gov.\\n          \\n        \\n      \\n      \\n        SUPPLEMENTARY INFORMATION:\\n\\n        Notice is here given in accordance with the Native American Graves Protection and Repatriation Act (NAGPRA), 25 U.S.C. 3003, of the completion of an inventory of human remains under the control of the Michigan State Police; Mount Pleasant, MI. The human remains were removed from Montcalm County, MI.\\n        This notice is published as part of the National Park Service\\'s administrative responsibilities under NAGPRA, 25 U.S.C. 3003(d)(3). The determinations in this notice are the sole responsibility of the museum, institution, or Federal agency that has control of the Native American human remains. The National Park Service is not responsible for the determinations in this notice.\\n        Consultation\\n        A detailed assessment of the human remains was made by the Michigan State Police professional staff in consultation with representatives of the Saginaw Chippewa Indian Tribe of Michigan.\\n        History and Description of the Remains\\n        On April 4, 1999, human remains representing, at minimum, one individual were removed from the northwest corner of Section 14, near Kohler Road and M-46 Highway, in Montcalm County, MI. The remains were located during an excavation at a located on private property. The remains were buried approximately four feet under the surface of the ground. No known individuals were identified. No associated funerary objects are present.\\n        The Michigan State University Anthropology Lab determined that the remains are those of a \\xe2\\x80\\x9cPre-modern Native American\\xe2\\x80\\x9d male between the age of 30 and 50 years old. The location the remains were found is near the current location of the Saginaw Chippewa Indian Tribe of Michigan. Based on geographic location and consultation, the remains are most likely the remains of a member of that tribe.\\n        Determinations Made by the Michigan State Police, Mount Pleasant Post\\n        Officials of the Michigan State Police, Mount Pleasant Post have determined that:\\n        \\xe2\\x80\\xa2 Pursuant to 25 U.S.C. 3001(9), the human remains described in this notice represent the physical remains of one individual of Native American ancestry.\\n        \\xe2\\x80\\xa2 Pursuant to 25 U.S.C. 3001(2), there is a relationship of shared group identity that can be reasonably traced between the Native American human remains and Saginaw Chippewa Indian Tribe of Michigan.\\n        Additional Requestors and Disposition\\n\\n        Lineal descendants or representatives of any Indian tribe or Native Hawaiian organization not identified in this notice that wish to request transfer of control of these human remains should submit a written request with information in support of the request to Detective Sergeant Gary Green; Michigan State Police, Mount Pleasant Post, 3580 S. Isabella Road, Mount Pleasant, MI 48858; telephone (989) 773-5951; email GreenG1@Michigan.gov, by October 30, 2013. After that date, if no additional requestors have come forward, transfer of control of the human remains to the Saginaw Chippewa Indian Tribe of Michigan may proceed.\\n        The Michigan State Police is responsible for notifying the Saginaw Chippewa Indian Tribe of Michigan that this notice has been published.\\n        \\n          Dated: August 28, 2013.\\n          Melanie O\\'Brien,\\n          Acting Manager, National NAGPRA Program. \\n        \\n      \\n      [FR Doc. 2013-23814 Filed 9-27-13; 8:45 am]\\n      BILLING CODE 4312-50-P\\n    ", "agency1": "DEPARTMENT OF THE INTERIOR", "sub_agency1": "National Park Service", "dep_doc": "[NPS-WASO-NAGPRA-13951; PPWOCRADN0-PCU00RP14.R50000]", "subject": "Notice of Inventory Completion: Michigan State Police, Mount Pleasant Post, Mount Pleasant, MI", "agency2": "National Park Service, Interior.", "action": "Notice.", "summary": "The Michigan State Police, Mount Pleasant Post, has completed an inventory of human remains, in consultation with the appropriate Indian tribes or Native Hawaiian organizations, and has determined that there is a cultural affiliation between the human remains and present-day Indian tribes or Native Hawaiian organizations. Lineal descendants or representatives of any Indian tribe or Native Hawaiian organization not identified in this notice that wish to request transfer of control of the human remains should submit a written request to the Michigan State Police, Mount Pleasant Post. If no additional requestors come forward, transfer of control of the human remains to the lineal descendants, Indian tribes, or Native Hawaiian organizations stated in this notice may proceed.", "dates": "Lineal descendants or representatives of any Indian tribe or Native Hawaiian organization not identified in this notice that wish to request transfer of control of these human remains should submit a written request with information in support of the request to the Michigan State Police, Mount Pleasant Post, at the address in this notice by October 30, 2013.", "addresses": "Detective Sergeant Gary Green; Michigan State Police, Mount Pleasant Post, 3580 S. Isabella Road, Mount Pleasant, MI 48858; telephone (989) 773-5951; email GreenG1@Michigan.gov.\\n          ", "signature_dated": "Dated: August 28, 2013.", "signature_name": "Melanie O\\'Brien,", "signature_title": "Acting Manager, National NAGPRA Program. ", "fr_doc": "[FR Doc. 2013-23814 Filed 9-27-13; 8:45 am]", "billing_code": "BILLING CODE 4312-50-P", "supp_info": "SUPPLEMENTARY INFORMATION: \n Notice is here given in accordance with the Native American Graves Protection and Repatriation Act (NAGPRA), 25 U.S.C. 3003, of the completion of an inventory of human remains under the control of the Michigan State Police; Mount Pleasant, MI. The human remains were removed from Montcalm County, MI. \n This notice is published as part of the National Park Service\\'s administrative responsibilities under NAGPRA, 25 U.S.C. 3003(d)(3). The determinations in this notice are the sole responsibility of the museum, institution, or Federal agency that has control of the Native American human remains. The National Park Service is not responsible for the determinations in this notice. \n Consultation \n A detailed assessment of the human remains was made by the Michigan State Police professional staff in consultation with representatives of the Saginaw Chippewa Indian Tribe of Michigan. \n History and Description of the Remains \n On April 4, 1999, human remains representing, at minimum, one individual were removed from the northwest corner of Section 14, near Kohler Road and M-46 Highway, in Montcalm County, MI. The remains were located during an excavation at a located on private property. The remains were buried approximately four feet under the surface of the ground. No known individuals were identified. No associated funerary objects are present. \n The Michigan State University Anthropology Lab determined that the remains are those of a \\xe2\\x80\\x9cPre-modern Native American\\xe2\\x80\\x9d male between the age of 30 and 50 years old. The location the remains were found is near the current location of the Saginaw Chippewa Indian Tribe of Michigan. Based on geographic location and consultation, the remains are most likely the remains of a member of that tribe. \n Determinations Made by the Michigan State Police, Mount Pleasant Post \n Officials of the Michigan State Police, Mount Pleasant Post have determined that: \n \\xe2\\x80\\xa2 Pursuant to 25 U.S.C. 3001(9), the human remains described in this notice represent the physical remains of one individual of Native American ancestry. \n \\xe2\\x80\\xa2 Pursuant to 25 U.S.C. 3001(2), there is a relationship of shared group identity that can be reasonably traced between the Native American human remains and Saginaw Chippewa Indian Tribe of Michigan. \n Additional Requestors and Disposition \n Lineal descendants or representatives of any Indian tribe or Native Hawaiian organization not identified in this notice that wish to request transfer of control of these human remains should submit a written request with information in support of the request to Detective Sergeant Gary Green; Michigan State Police, Mount Pleasant Post, 3580 S. Isabella Road, Mount Pleasant, MI 48858; telephone (989) 773-5951; email GreenG1@Michigan.gov, by October 30, 2013. After that date, if no additional requestors have come forward, transfer of control of the human remains to the Saginaw Chippewa Indian Tribe of Michigan may proceed. \n The Michigan State Police is responsible for notifying the Saginaw Chippewa Indian Tribe of Michigan that this notice has been published. \n ", "consultation": "A detailed assessment of the human remains was made by the Michigan State Police professional staff in consultation with representatives of the Saginaw Chippewa Indian Tribe of Michigan. \n ", "h_d_r": "On April 4, 1999, human remains representing, at minimum, one individual were removed from the northwest corner of Section 14, near Kohler Road and M-46 Highway, in Montcalm County, MI. The remains were located during an excavation at a located on private property. The remains were buried approximately four feet under the surface of the ground. No known individuals were identified. No associated funerary objects are present. \n The Michigan State University Anthropology Lab determined that the remains are those of a \\xe2\\x80\\x9cPre-modern Native American\\xe2\\x80\\x9d male between the age of 30 and 50 years old. The location the remains were found is near the current location of the Saginaw Chippewa Indian Tribe of Michigan. Based on geographic location and consultation, the remains are most likely the remains of a member of that tribe. \n ", "h_d_ci": "Null", "determinations": "Determinations Made by the Michigan State Police, Mount Pleasant Post \n Officials of the Michigan State Police, Mount Pleasant Post have determined that: \n \\xe2\\x80\\xa2 Pursuant to 25 U.S.C. 3001(9), the human remains described in this notice represent the physical remains of one individual of Native American ancestry. \n \\xe2\\x80\\xa2 Pursuant to 25 U.S.C. 3001(2), there is a relationship of shared group identity that can be reasonably traced between the Native American human remains and Saginaw Chippewa Indian Tribe of Michigan. \n ", "a_r_d": "Lineal descendants or representatives of any Indian tribe or Native Hawaiian organization not identified in this notice that wish to request transfer of control of these human remains should submit a written request with information in support of the request to Detective Sergeant Gary Green; Michigan State Police, Mount Pleasant Post, 3580 S. Isabella Road, Mount Pleasant, MI 48858; telephone (989) 773-5951; email GreenG1@Michigan.gov, by October 30, 2013. After that date, if no additional requestors have come forward, transfer of control of the human remains to the Saginaw Chippewa Indian Tribe of Michigan may proceed. \n The Michigan State Police is responsible for notifying the Saginaw Chippewa Indian Tribe of Michigan that this notice has been published. \n "}