{"index": "I_91", "messy_full": "\\n      \\n        DEPARTMENT OF THE INTERIOR\\n        National Park Service\\n        [NPS-WASO-NAGPRA-NPS0027722; PCU00RP14.R50000-PPWOCRDN0]\\n        Notice of Inventory Completion: U.S. Department of the Interior, Bureau of Indian Affairs, Washington, DC\\n        \\n          AGENCY:\\n          National Park Service, Interior.\\n        \\n        \\n          ACTION:\\n          Notice.\\n        \\n        \\n          SUMMARY:\\n          The U.S. Department of the Interior, Bureau of Indian Affairs has completed an inventory of human remains and associated funerary objects, in consultation with the appropriate Indian Tribes or Native Hawaiian organizations, and has determined that there is no cultural affiliation between the human remains and associated funerary objects and any present-day Indian Tribes or Native Hawaiian organizations. Representatives of any Indian Tribe or Native Hawaiian organization not identified in this notice that wish to request transfer of control of these human remains and associated funerary objects should submit a written request to the Bureau of Indian Affairs. If no additional requestors come forward, transfer of control of the human remains and associated funerary objects to the Indian Tribes or Native Hawaiian organizations stated in this notice may proceed.\\n        \\n        \\n          DATES:\\n          Representatives of any Indian Tribe or Native Hawaiian organization not identified in this notice that wish to request transfer of control of these human remains and associated funerary objects should submit a written request with information in support of the request to the Bureau of Indian Affairs at the address in this notice by June 6, 2019.\\n        \\n        \\n          ADDRESSES:\\n\\n          Anna Pardo, Museum Program Manager/NAGPRA Coordinator, U.S. Department of the Interior, Bureau of Indian Affairs, 12220 Sunrise Valley Drive, Room 6084, Reston, VA 20191, telephone (703) 390-6343, email Anna.Pardo@bia.gov.\\n          \\n        \\n      \\n      \\n        SUPPLEMENTARY INFORMATION:\\n        Notice is here given in accordance with the Native American Graves Protection and Repatriation Act (NAGPRA), 25 U.S.C. 3003, of the completion of an inventory of human remains and associated funerary objects under the control of the U.S. Department of the Interior, Bureau of Indian Affairs, Washington, DC. The human remains and associated funerary objects were removed from Pyramid Lake in Washoe County, NV.\\n        This notice is published as part of the National Park Service\\'s administrative responsibilities under NAGPRA, 25 U.S.C. 3003(d)(3) and 43 CFR 10.11(d). The determinations in this notice are the sole responsibility of the museum, institution, or Federal agency that has control of the Native American human remains and associated funerary objects. The National Park Service is not responsible for the determinations in this notice.\\n        Consultation\\n        A detailed assessment of the human remains was made by the U.S. Department of the Interior, Bureau of Indian Affairs professional staff in consultation with representatives of the Pyramid Lake Paiute Tribe of the Pyramid Lake Reservation, Nevada.\\n        History and Description of the Remains\\n\\n        In February 1968, human remains representing, at minimum, two individuals were removed from the shoreline of Pyramid Lake in Washoe County, NV. The human remains and associated funerary objects were housed at the University of Nevada, Reno, Department of Anthropology until sometime between April and August 1993, when they were moved to the Nevada State Museum in Carson City, NV. The human remains and associated funerary objects were returned to the University of Nevada, Reno, Department of Anthropology in February 2011, where they have continued to be housed. No known individuals were identified. The five associated funerary objects are two bird bones, one pelican bone, one mammal rib, and one piece of basalt.\\n        Determinations Made by the U.S. Department of the Interior, Bureau of Indian Affairs\\n        Officials of the U.S. Department of the Interior, Bureau of Indian Affairs have determined that:\\n        \\xe2\\x80\\xa2 Pursuant to 25 U.S.C. 3001(9), the human remains described in this notice are Native American based on studies conducted by physical anthropologists.\\n        \\xe2\\x80\\xa2 Pursuant to 25 U.S.C. 3001(9), the human remains described in this notice represent the physical remains of two individuals of Native American ancestry.\\n        \\xe2\\x80\\xa2 Pursuant to 25 U.S.C. 3001(3)(A), the five objects described in this notice are reasonably believed to have been placed with or near individual human remains at the time of death or later as part of the death rite or ceremony.\\n        \\xe2\\x80\\xa2 Pursuant to 25 U.S.C. 3001(2), a relationship of shared group identity cannot be reasonably traced between the Native American human remains and associated funerary objects and any present-day Indian Tribe.\\n        \\xe2\\x80\\xa2 Pursuant to 25 U.S.C. 3001(15), the land from which the Native American human remains and associated funerary objects were removed is the tribal land of the Pyramid Lake Paiute Tribe of the Pyramid Lake Reservation, Nevada.\\n        \\xe2\\x80\\xa2 Pursuant to 43 CFR 10.11(c)(1), the disposition of the human remains and associated funerary objects may be to the Pyramid Lake Paiute Tribe of the Pyramid Lake Reservation, Nevada.\\n        Additional Requestors and Disposition\\n\\n        Representatives of any Indian Tribe or Native Hawaiian organization not identified in this notice that wish to request transfer of control of these human remains and associated funerary objects should submit a written request with information in support of the request to Anna Pardo, Museum Program Manager/NAGPRA Coordinator, U.S. Department of the Interior, Bureau of Indian Affairs, 12220 Sunrise Valley Drive, Room 6084, Reston, VA 20191, telephone (703) 390-6343, email Anna.Pardo@bia.gov, by June 6, 2019. After that date, if no additional requestors have come forward, transfer of control of the human remains and associated funerary objects to the Pyramid Lake Paiute Tribe of the Pyramid Lake Reservation, Nevada may proceed.\\n        The U.S. Department of the Interior, Bureau of Indian Affairs is responsible for notifying the Pyramid Lake Paiute Tribe of the Pyramid Lake Reservation, Nevada that this notice has been published.\\n        \\n          Dated: April 16, 2019.\\n          Melanie O\\'Brien,\\n          Manager, National NAGPRA Program. \\n        \\n      \\n      [FR Doc. 2019-09308 Filed 5-6-19; 8:45 am]\\n       BILLING CODE 4312-52-P\\n    ", "agency1": "DEPARTMENT OF THE INTERIOR", "sub_agency1": "National Park Service", "dep_doc": "[NPS-WASO-NAGPRA-NPS0027722; PCU00RP14.R50000-PPWOCRDN0]", "subject": "Notice of Inventory Completion: U.S. Department of the Interior, Bureau of Indian Affairs, Washington, DC", "agency2": "National Park Service, Interior.", "action": "Notice.", "summary": "The U.S. Department of the Interior, Bureau of Indian Affairs has completed an inventory of human remains and associated funerary objects, in consultation with the appropriate Indian Tribes or Native Hawaiian organizations, and has determined that there is no cultural affiliation between the human remains and associated funerary objects and any present-day Indian Tribes or Native Hawaiian organizations. Representatives of any Indian Tribe or Native Hawaiian organization not identified in this notice that wish to request transfer of control of these human remains and associated funerary objects should submit a written request to the Bureau of Indian Affairs. If no additional requestors come forward, transfer of control of the human remains and associated funerary objects to the Indian Tribes or Native Hawaiian organizations stated in this notice may proceed.", "dates": "Representatives of any Indian Tribe or Native Hawaiian organization not identified in this notice that wish to request transfer of control of these human remains and associated funerary objects should submit a written request with information in support of the request to the Bureau of Indian Affairs at the address in this notice by June 6, 2019.", "addresses": "Anna Pardo, Museum Program Manager/NAGPRA Coordinator, U.S. Department of the Interior, Bureau of Indian Affairs, 12220 Sunrise Valley Drive, Room 6084, Reston, VA 20191, telephone (703) 390-6343, email Anna.Pardo@bia.gov.\\n          ", "signature_dated": "Dated: April 16, 2019.", "signature_name": "Melanie O\\'Brien,", "signature_title": "Manager, National NAGPRA Program. ", "fr_doc": "[FR Doc. 2019-09308 Filed 5-6-19; 8:45 am]", "billing_code": " BILLING CODE 4312-52-P", "supp_info": "SUPPLEMENTARY INFORMATION: \n Notice is here given in accordance with the Native American Graves Protection and Repatriation Act (NAGPRA), 25 U.S.C. 3003, of the completion of an inventory of human remains and associated funerary objects under the control of the U.S. Department of the Interior, Bureau of Indian Affairs, Washington, DC. The human remains and associated funerary objects were removed from Pyramid Lake in Washoe County, NV. \n This notice is published as part of the National Park Service\\'s administrative responsibilities under NAGPRA, 25 U.S.C. 3003(d)(3) and 43 CFR 10.11(d). The determinations in this notice are the sole responsibility of the museum, institution, or Federal agency that has control of the Native American human remains and associated funerary objects. The National Park Service is not responsible for the determinations in this notice. \n Consultation \n A detailed assessment of the human remains was made by the U.S. Department of the Interior, Bureau of Indian Affairs professional staff in consultation with representatives of the Pyramid Lake Paiute Tribe of the Pyramid Lake Reservation, Nevada. \n History and Description of the Remains \n In February 1968, human remains representing, at minimum, two individuals were removed from the shoreline of Pyramid Lake in Washoe County, NV. The human remains and associated funerary objects were housed at the University of Nevada, Reno, Department of Anthropology until sometime between April and August 1993, when they were moved to the Nevada State Museum in Carson City, NV. The human remains and associated funerary objects were returned to the University of Nevada, Reno, Department of Anthropology in February 2011, where they have continued to be housed. No known individuals were identified. The five associated funerary objects are two bird bones, one pelican bone, one mammal rib, and one piece of basalt. \n Determinations Made by the U.S. Department of the Interior, Bureau of Indian Affairs \n Officials of the U.S. Department of the Interior, Bureau of Indian Affairs have determined that: \n \\xe2\\x80\\xa2 Pursuant to 25 U.S.C. 3001(9), the human remains described in this notice are Native American based on studies conducted by physical anthropologists. \n \\xe2\\x80\\xa2 Pursuant to 25 U.S.C. 3001(9), the human remains described in this notice represent the physical remains of two individuals of Native American ancestry. \n \\xe2\\x80\\xa2 Pursuant to 25 U.S.C. 3001(3)(A), the five objects described in this notice are reasonably believed to have been placed with or near individual human remains at the time of death or later as part of the death rite or ceremony. \n \\xe2\\x80\\xa2 Pursuant to 25 U.S.C. 3001(2), a relationship of shared group identity cannot be reasonably traced between the Native American human remains and associated funerary objects and any present-day Indian Tribe. \n \\xe2\\x80\\xa2 Pursuant to 25 U.S.C. 3001(15), the land from which the Native American human remains and associated funerary objects were removed is the tribal land of the Pyramid Lake Paiute Tribe of the Pyramid Lake Reservation, Nevada. \n \\xe2\\x80\\xa2 Pursuant to 43 CFR 10.11(c)(1), the disposition of the human remains and associated funerary objects may be to the Pyramid Lake Paiute Tribe of the Pyramid Lake Reservation, Nevada. \n Additional Requestors and Disposition \n Representatives of any Indian Tribe or Native Hawaiian organization not identified in this notice that wish to request transfer of control of these human remains and associated funerary objects should submit a written request with information in support of the request to Anna Pardo, Museum Program Manager/NAGPRA Coordinator, U.S. Department of the Interior, Bureau of Indian Affairs, 12220 Sunrise Valley Drive, Room 6084, Reston, VA 20191, telephone (703) 390-6343, email Anna.Pardo@bia.gov, by June 6, 2019. After that date, if no additional requestors have come forward, transfer of control of the human remains and associated funerary objects to the Pyramid Lake Paiute Tribe of the Pyramid Lake Reservation, Nevada may proceed. \n The U.S. Department of the Interior, Bureau of Indian Affairs is responsible for notifying the Pyramid Lake Paiute Tribe of the Pyramid Lake Reservation, Nevada that this notice has been published. \n ", "consultation": "A detailed assessment of the human remains was made by the U.S. Department of the Interior, Bureau of Indian Affairs professional staff in consultation with representatives of the Pyramid Lake Paiute Tribe of the Pyramid Lake Reservation, Nevada. \n ", "h_d_r": "In February 1968, human remains representing, at minimum, two individuals were removed from the shoreline of Pyramid Lake in Washoe County, NV. The human remains and associated funerary objects were housed at the University of Nevada, Reno, Department of Anthropology until sometime between April and August 1993, when they were moved to the Nevada State Museum in Carson City, NV. The human remains and associated funerary objects were returned to the University of Nevada, Reno, Department of Anthropology in February 2011, where they have continued to be housed. No known individuals were identified. The five associated funerary objects are two bird bones, one pelican bone, one mammal rib, and one piece of basalt. \n ", "h_d_ci": "Null", "determinations": "Determinations Made by the U.S. Department of the Interior, Bureau of Indian Affairs \n Officials of the U.S. Department of the Interior, Bureau of Indian Affairs have determined that: \n \\xe2\\x80\\xa2 Pursuant to 25 U.S.C. 3001(9), the human remains described in this notice are Native American based on studies conducted by physical anthropologists. \n \\xe2\\x80\\xa2 Pursuant to 25 U.S.C. 3001(9), the human remains described in this notice represent the physical remains of two individuals of Native American ancestry. \n \\xe2\\x80\\xa2 Pursuant to 25 U.S.C. 3001(3)(A), the five objects described in this notice are reasonably believed to have been placed with or near individual human remains at the time of death or later as part of the death rite or ceremony. \n \\xe2\\x80\\xa2 Pursuant to 25 U.S.C. 3001(2), a relationship of shared group identity cannot be reasonably traced between the Native American human remains and associated funerary objects and any present-day Indian Tribe. \n \\xe2\\x80\\xa2 Pursuant to 25 U.S.C. 3001(15), the land from which the Native American human remains and associated funerary objects were removed is the tribal land of the Pyramid Lake Paiute Tribe of the Pyramid Lake Reservation, Nevada. \n \\xe2\\x80\\xa2 Pursuant to 43 CFR 10.11(c)(1), the disposition of the human remains and associated funerary objects may be to the Pyramid Lake Paiute Tribe of the Pyramid Lake Reservation, Nevada. \n ", "a_r_d": "Representatives of any Indian Tribe or Native Hawaiian organization not identified in this notice that wish to request transfer of control of these human remains and associated funerary objects should submit a written request with information in support of the request to Anna Pardo, Museum Program Manager/NAGPRA Coordinator, U.S. Department of the Interior, Bureau of Indian Affairs, 12220 Sunrise Valley Drive, Room 6084, Reston, VA 20191, telephone (703) 390-6343, email Anna.Pardo@bia.gov, by June 6, 2019. After that date, if no additional requestors have come forward, transfer of control of the human remains and associated funerary objects to the Pyramid Lake Paiute Tribe of the Pyramid Lake Reservation, Nevada may proceed. \n The U.S. Department of the Interior, Bureau of Indian Affairs is responsible for notifying the Pyramid Lake Paiute Tribe of the Pyramid Lake Reservation, Nevada that this notice has been published. \n "}