{"index": "I_928", "messy_full": "\\n      \\n        DEPARTMENT OF THE INTERIOR\\n        National Park Service\\n        [NPS-WASO-NAGPRA-13660; PPWOCRADN0-PCU00RP14.R50000]\\n        Notice of Inventory Completion: St. Joseph County Sheriff\\'s Department, Centreville, MI\\n        \\n          AGENCY:\\n          National Park Service, Interior.\\n        \\n        \\n          ACTION:\\n          Notice.\\n        \\n        \\n          SUMMARY:\\n          The St. Joseph County Sheriff\\'s Department has completed an inventory of human remains, in consultation with the appropriate Indian tribes or Native Hawaiian organizations, and has determined that there is no cultural affiliation between the human remains and any present-day Indian tribes or Native Hawaiian organizations. Representatives of any Indian tribe or Native Hawaiian organization not identified in this notice that wish to request transfer of control of these human remains should submit a written request to the St. Joseph County Sheriff\\'s Department. If no additional requestors come forward, transfer of control of the human remains to the Indian tribes or Native Hawaiian organizations stated in this notice may proceed.\\n        \\n        \\n          DATES:\\n          Representatives of any Indian tribe or Native Hawaiian organization not identified in this notice that wish to request transfer of control of these human remains should submit a written request with information in support of the request to the St. Joseph County Sheriff\\'s Department at the address in this notice by September 16, 2013.\\n        \\n        \\n          ADDRESSES:\\n          Undersheriff Mark Lillywhite, St. Joseph County Sheriff\\'s Department, 650 East Main Street, Centreville, MI 49032, telephone (269) 467-9045.\\n        \\n      \\n      \\n        SUPPLEMENTARY INFORMATION:\\n\\n        Notice is here given in accordance with the Native American Graves Protection and Repatriation Act (NAGPRA), 25 U.S.C. 3003, of the completion of an inventory of human remains under the control of the St. Joseph County Sheriff\\'s Department. The human remains were removed from Section 27, Leonidas Township, St. Joseph County, MI.\\n        This notice is published as part of the National Park Service\\'s administrative responsibilities under NAGPRA, 25 U.S.C. 3003(d)(3) and 43 CFR 10.11(d). The determinations in this notice are the sole responsibility of the museum, institution, or Federal agency that has control of the Native American human remains The National Park Service is not responsible for the determinations in this notice.\\n        Consultation\\n        A detailed assessment of the human remains was made by the Michigan State University Forensic Anthropology Department professional staff on behalf of the St. Joseph County Sheriff\\'s Department with representatives of the Nottawaseppi Huron Band of the Potawatomi, Michigan (previously listed as the Huron Potawatomi, Inc.).\\n        History and Description of the Remains\\n        In December 1970, human remains representing, at minimum, one individual were removed from Section 27, Leonidas Township, in St. Joseph County, MI. The remains were transferred to the Michigan State University Forensic Anthropology Department where they were identified and transferred back to the St. Joseph County Sheriff\\'s Department on June 26, 2013. The human remains were identified as a 30-40 year old Native American female from a pre-20th century population. No known individual was identified. No associated funerary objects are present.\\n        Determinations Made by the St. Joseph County Sheriff\\'s Department\\n        Officials of the St. Joseph County Sheriff\\'s Department have determined that:\\n        \\xe2\\x80\\xa2 Pursuant to 25 U.S.C. 3001(9), the human remains described in this notice are Native American based on evaluation by the Michigan State University Forensic Anthropology Department.\\n        \\xe2\\x80\\xa2 Pursuant to 25 U.S.C. 3001(9), the human remains described in this notice represent the physical remains of one individual of Native American ancestry.\\n        \\xe2\\x80\\xa2 Pursuant to 25 U.S.C. 3001(2), a relationship of shared group identity cannot be reasonably traced between the Native American human remains and any present-day Indian tribe.\\n        \\xe2\\x80\\xa2 Pursuant to 25 U.S.C. 3001(15), the land from which the Native American human remains were removed is the near the tribal land of the Nottawaseppi Huron Band of the Potawatomi, Michigan (previously listed as the Huron Potawatomi, Inc.).\\n        \\xe2\\x80\\xa2 Pursuant to 43 CFR 10.11(c)(1), the disposition of the human remains may be to the Nottawaseppi Huron Band of the Potawatomi, Michigan (previously listed as the Huron Potawatomi, Inc.).\\n        Additional Requestors and Disposition\\n        Representatives of any Indian tribe or Native Hawaiian organization not identified in this notice that wish to request transfer of control of these human remains should submit a written request with information in support of the request to Undersheriff Mark Lilywhite, St. Joseph County Sheriff\\'s Department, 650 East Main Street, Centreville, MI 49032, telephone (269) 467-9045, by September 16, 2013. After that date, if no additional requestors have come forward, transfer of control of the human remains to the Nottawaseppi Huron Band of the Potawatomi, Michigan (previously listed as the Huron Potawatomi, Inc.) may proceed.\\n        The St. Joseph County Sheriff\\'s Department is responsible for notifying the Nottawaseppi Huron Band of the Potawatomi, Michigan (previously listed as the Huron Potawatomi, Inc.) that this notice has been published.\\n        \\n          Dated: July 30, 2013.\\n          Sherry Hutt,\\n          Manager, National NAGPRA Program. \\n        \\n      \\n      [FR Doc. 2013-20001 Filed 8-15-13; 8:45 am]\\n      BILLING CODE 4312-50-P\\n    ", "agency1": "DEPARTMENT OF THE INTERIOR", "sub_agency1": "National Park Service", "dep_doc": "[NPS-WASO-NAGPRA-13660; PPWOCRADN0-PCU00RP14.R50000]", "subject": "Notice of Inventory Completion: St. Joseph County Sheriff\\'s Department, Centreville, MI", "agency2": "National Park Service, Interior.", "action": "Notice.", "summary": "The St. Joseph County Sheriff\\'s Department has completed an inventory of human remains, in consultation with the appropriate Indian tribes or Native Hawaiian organizations, and has determined that there is no cultural affiliation between the human remains and any present-day Indian tribes or Native Hawaiian organizations. Representatives of any Indian tribe or Native Hawaiian organization not identified in this notice that wish to request transfer of control of these human remains should submit a written request to the St. Joseph County Sheriff\\'s Department. If no additional requestors come forward, transfer of control of the human remains to the Indian tribes or Native Hawaiian organizations stated in this notice may proceed.", "dates": "Representatives of any Indian tribe or Native Hawaiian organization not identified in this notice that wish to request transfer of control of these human remains should submit a written request with information in support of the request to the St. Joseph County Sheriff\\'s Department at the address in this notice by September 16, 2013.", "addresses": "Undersheriff Mark Lillywhite, St. Joseph County Sheriff\\'s Department, 650 East Main Street, Centreville, MI 49032, telephone (269) 467-9045.", "signature_dated": "Dated: July 30, 2013.", "signature_name": "Sherry Hutt,", "signature_title": "Manager, National NAGPRA Program. ", "fr_doc": "[FR Doc. 2013-20001 Filed 8-15-13; 8:45 am]", "billing_code": "BILLING CODE 4312-50-P", "supp_info": "SUPPLEMENTARY INFORMATION: \n Notice is here given in accordance with the Native American Graves Protection and Repatriation Act (NAGPRA), 25 U.S.C. 3003, of the completion of an inventory of human remains under the control of the St. Joseph County Sheriff\\'s Department. The human remains were removed from Section 27, Leonidas Township, St. Joseph County, MI. \n This notice is published as part of the National Park Service\\'s administrative responsibilities under NAGPRA, 25 U.S.C. 3003(d)(3) and 43 CFR 10.11(d). The determinations in this notice are the sole responsibility of the museum, institution, or Federal agency that has control of the Native American human remains The National Park Service is not responsible for the determinations in this notice. \n Consultation \n A detailed assessment of the human remains was made by the Michigan State University Forensic Anthropology Department professional staff on behalf of the St. Joseph County Sheriff\\'s Department with representatives of the Nottawaseppi Huron Band of the Potawatomi, Michigan (previously listed as the Huron Potawatomi, Inc.). \n History and Description of the Remains \n In December 1970, human remains representing, at minimum, one individual were removed from Section 27, Leonidas Township, in St. Joseph County, MI. The remains were transferred to the Michigan State University Forensic Anthropology Department where they were identified and transferred back to the St. Joseph County Sheriff\\'s Department on June 26, 2013. The human remains were identified as a 30-40 year old Native American female from a pre-20th century population. No known individual was identified. No associated funerary objects are present. \n Determinations Made by the St. Joseph County Sheriff\\'s Department \n Officials of the St. Joseph County Sheriff\\'s Department have determined that: \n \\xe2\\x80\\xa2 Pursuant to 25 U.S.C. 3001(9), the human remains described in this notice are Native American based on evaluation by the Michigan State University Forensic Anthropology Department. \n \\xe2\\x80\\xa2 Pursuant to 25 U.S.C. 3001(9), the human remains described in this notice represent the physical remains of one individual of Native American ancestry. \n \\xe2\\x80\\xa2 Pursuant to 25 U.S.C. 3001(2), a relationship of shared group identity cannot be reasonably traced between the Native American human remains and any present-day Indian tribe. \n \\xe2\\x80\\xa2 Pursuant to 25 U.S.C. 3001(15), the land from which the Native American human remains were removed is the near the tribal land of the Nottawaseppi Huron Band of the Potawatomi, Michigan (previously listed as the Huron Potawatomi, Inc.). \n \\xe2\\x80\\xa2 Pursuant to 43 CFR 10.11(c)(1), the disposition of the human remains may be to the Nottawaseppi Huron Band of the Potawatomi, Michigan (previously listed as the Huron Potawatomi, Inc.). \n Additional Requestors and Disposition \n Representatives of any Indian tribe or Native Hawaiian organization not identified in this notice that wish to request transfer of control of these human remains should submit a written request with information in support of the request to Undersheriff Mark Lilywhite, St. Joseph County Sheriff\\'s Department, 650 East Main Street, Centreville, MI 49032, telephone (269) 467-9045, by September 16, 2013. After that date, if no additional requestors have come forward, transfer of control of the human remains to the Nottawaseppi Huron Band of the Potawatomi, Michigan (previously listed as the Huron Potawatomi, Inc.) may proceed. \n The St. Joseph County Sheriff\\'s Department is responsible for notifying the Nottawaseppi Huron Band of the Potawatomi, Michigan (previously listed as the Huron Potawatomi, Inc.) that this notice has been published. \n ", "consultation": "A detailed assessment of the human remains was made by the Michigan State University Forensic Anthropology Department professional staff on behalf of the St. Joseph County Sheriff\\'s Department with representatives of the Nottawaseppi Huron Band of the Potawatomi, Michigan (previously listed as the Huron Potawatomi, Inc.). \n ", "h_d_r": "In December 1970, human remains representing, at minimum, one individual were removed from Section 27, Leonidas Township, in St. Joseph County, MI. The remains were transferred to the Michigan State University Forensic Anthropology Department where they were identified and transferred back to the St. Joseph County Sheriff\\'s Department on June 26, 2013. The human remains were identified as a 30-40 year old Native American female from a pre-20th century population. No known individual was identified. No associated funerary objects are present. \n ", "h_d_ci": "Null", "determinations": "Determinations Made by the St. Joseph County Sheriff\\'s Department \n Officials of the St. Joseph County Sheriff\\'s Department have determined that: \n \\xe2\\x80\\xa2 Pursuant to 25 U.S.C. 3001(9), the human remains described in this notice are Native American based on evaluation by the Michigan State University Forensic Anthropology Department. \n \\xe2\\x80\\xa2 Pursuant to 25 U.S.C. 3001(9), the human remains described in this notice represent the physical remains of one individual of Native American ancestry. \n \\xe2\\x80\\xa2 Pursuant to 25 U.S.C. 3001(2), a relationship of shared group identity cannot be reasonably traced between the Native American human remains and any present-day Indian tribe. \n \\xe2\\x80\\xa2 Pursuant to 25 U.S.C. 3001(15), the land from which the Native American human remains were removed is the near the tribal land of the Nottawaseppi Huron Band of the Potawatomi, Michigan (previously listed as the Huron Potawatomi, Inc.). \n \\xe2\\x80\\xa2 Pursuant to 43 CFR 10.11(c)(1), the disposition of the human remains may be to the Nottawaseppi Huron Band of the Potawatomi, Michigan (previously listed as the Huron Potawatomi, Inc.). \n ", "a_r_d": "Representatives of any Indian tribe or Native Hawaiian organization not identified in this notice that wish to request transfer of control of these human remains should submit a written request with information in support of the request to Undersheriff Mark Lilywhite, St. Joseph County Sheriff\\'s Department, 650 East Main Street, Centreville, MI 49032, telephone (269) 467-9045, by September 16, 2013. After that date, if no additional requestors have come forward, transfer of control of the human remains to the Nottawaseppi Huron Band of the Potawatomi, Michigan (previously listed as the Huron Potawatomi, Inc.) may proceed. \n The St. Joseph County Sheriff\\'s Department is responsible for notifying the Nottawaseppi Huron Band of the Potawatomi, Michigan (previously listed as the Huron Potawatomi, Inc.) that this notice has been published. \n "}