{"index": "I_938", "messy_full": "\\n      \\n        \\n        DEPARTMENT OF THE INTERIOR\\n        National Park Service\\n        [NPS-WASO-NAGPRA-13408; PPWOCRADN0-PCU00RP14.R50000]\\n        Notice of Inventory Completion: State Historical Society of Wisconsin, Madison, WI\\n        \\n          AGENCY:\\n          National Park Service, Interior.\\n        \\n        \\n          ACTION:\\n          Notice.\\n        \\n        \\n          SUMMARY:\\n          The State Historical Society of Wisconsin has completed an inventory of human remains and associated funerary objects, in consultation with the appropriate Indian tribes or Native Hawaiian organizations, and has determined that there is no cultural affiliation between the human remains and associated funerary objects and any present-day Indian tribes or Native Hawaiian organizations. Representatives of any Indian tribe or Native Hawaiian organization not identified in this notice that wish to request transfer of control of these human remains and associated funerary objects should submit a written request to the State Historical Society of Wisconsin. If no additional requestors come forward, transfer of control of the human remains and associated funerary objects to the Indian tribes or Native Hawaiian organizations stated in this notice may proceed.\\n        \\n        \\n          DATES:\\n          Representatives of any Indian tribe or Native Hawaiian organization not identified in this notice that wish to request transfer of control of these human remains and associated funerary objects should submit a written request with information in support of the request to the State Historical Society of Wisconsin at the address in this notice by August 23, 2013.\\n        \\n        \\n          ADDRESSES:\\n\\n          Jennifer Kolb, Wisconsin Historical Museum, 30 North Carroll Street, Madison, WI 53703, telephone (608) 261-2461, email Jennifer.Kolb@wisconsinhistory.org.\\n        \\n      \\n      \\n        SUPPLEMENTARY INFORMATION:\\n        Notice is here given in accordance with the Native American Graves Protection and Repatriation Act (NAGPRA), 25 U.S.C. 3003, of the completion of an inventory of human remains and associated funerary objects under the control of the State Historical Society of Wisconsin, Madison, WI. The human remains and associated funerary objects were removed from Waupaca County, WI.\\n        This notice is published as part of the National Park Service\\'s administrative responsibilities under NAGPRA, 25 U.S.C. 3003(d)(3) and 43 CFR 10.11(d). The determinations in this notice are the sole responsibility of the museum, institution, or Federal agency that has control of the Native American human remains and associated funerary objects. The National Park Service is not responsible for the determinations in this notice.\\n        Consultation\\n        A detailed assessment of the human remains was made by the State Historical Society of Wisconsin professional staff in consultation with representatives of the Forest County Potawatomi Community, Wisconsin; Ho-Chunk Nation of Wisconsin; and the Menominee Indian Tribe of Wisconsin.\\n        History and Description of the Remains\\n        In1963, human remains representing, at minimum, one individual were removed from a burial located just below the plow zone at Riverbend 1 Site in Waupaca County, WI. The fragmentary human remains were excavated by the State Historical Society of Wisconsin and the Wisconsin Department of Transportation. As the burial had been partially disturbed by plowing, some of the remains were recovered during a surface survey prior to the excavation. The human remains were determined to be those of an adult Native American female. No known individuals were identified. The two associated funerary objects are a quartz shatter and a quartzite flake.\\n        Determinations Made by the State Historical Society of Wisconsin\\n        Officials of the State Historical Society of Wisconsin have determined that:\\n        \\xe2\\x80\\xa2 Pursuant to 25 U.S.C. 3001(9), the human remains described in this notice are Native American based on skeletal analysis.\\n        \\xe2\\x80\\xa2 Pursuant to 25 U.S.C. 3001(9), the human remains described in this notice represent the physical remains of one individual of Native American ancestry.\\n        \\xe2\\x80\\xa2 Treaties, Acts of Congress, or Executive Orders, indicate that the land from which the Native American human remains were removed is the aboriginal land of the Menominee Indian Tribe of Wisconsin.\\n        \\xe2\\x80\\xa2 Pursuant to 43 CFR 10.11(c)(1), the disposition of the human remains may be to the Menominee Indian Tribe of Wisconsin.\\n        Additional Requestors and Disposition\\n\\n        Representatives of any Indian tribe or Native Hawaiian organization not identified in this notice that wish to request transfer of control of these human remains should submit a written request with information in support of the request to Jennifer Kolb, Wisconsin Historical Museum, 30 North Carroll Street, Madison, WI 53703, telephone (608) 261-2461, email Jennifer.Kolb@wisconsinhistory.org, by August 23, 2013. After that date, if no additional requestors have come forward, transfer of control of the human remains to the Menominee Tribe of Wisconsin may proceed.\\n        The State Historical Society of Wisconsin is responsible for notifying the Forest County Potawatomi Community, Wisconsin; Ho-Chunk Nation of Wisconsin; and the Menominee Tribe of Wisconsin that this notice has been published.\\n        \\n          Dated: June 27, 2013.\\n          Melanie O\\'Brien,\\n          Acting Manager, National NAGPRA Program.\\n        \\n      \\n      [FR Doc. 2013-17716 Filed 7-23-13; 8:45 am]\\n      BILLING CODE 4312-50-P\\n    ", "agency1": "DEPARTMENT OF THE INTERIOR", "sub_agency1": "National Park Service", "dep_doc": "[NPS-WASO-NAGPRA-13408; PPWOCRADN0-PCU00RP14.R50000]", "subject": "Notice of Inventory Completion: State Historical Society of Wisconsin, Madison, WI", "agency2": "National Park Service, Interior.", "action": "Notice.", "summary": "The State Historical Society of Wisconsin has completed an inventory of human remains and associated funerary objects, in consultation with the appropriate Indian tribes or Native Hawaiian organizations, and has determined that there is no cultural affiliation between the human remains and associated funerary objects and any present-day Indian tribes or Native Hawaiian organizations. Representatives of any Indian tribe or Native Hawaiian organization not identified in this notice that wish to request transfer of control of these human remains and associated funerary objects should submit a written request to the State Historical Society of Wisconsin. If no additional requestors come forward, transfer of control of the human remains and associated funerary objects to the Indian tribes or Native Hawaiian organizations stated in this notice may proceed.", "dates": "Representatives of any Indian tribe or Native Hawaiian organization not identified in this notice that wish to request transfer of control of these human remains and associated funerary objects should submit a written request with information in support of the request to the State Historical Society of Wisconsin at the address in this notice by August 23, 2013.", "addresses": "Jennifer Kolb, Wisconsin Historical Museum, 30 North Carroll Street, Madison, WI 53703, telephone (608) 261-2461, email Jennifer.Kolb@wisconsinhistory.org.", "signature_dated": "Dated: June 27, 2013.", "signature_name": "Melanie O\\'Brien,", "signature_title": "Acting Manager, National NAGPRA Program.", "fr_doc": "[FR Doc. 2013-17716 Filed 7-23-13; 8:45 am]", "billing_code": "BILLING CODE 4312-50-P", "supp_info": "SUPPLEMENTARY INFORMATION: \n Notice is here given in accordance with the Native American Graves Protection and Repatriation Act (NAGPRA), 25 U.S.C. 3003, of the completion of an inventory of human remains and associated funerary objects under the control of the State Historical Society of Wisconsin, Madison, WI. The human remains and associated funerary objects were removed from Waupaca County, WI. \n This notice is published as part of the National Park Service\\'s administrative responsibilities under NAGPRA, 25 U.S.C. 3003(d)(3) and 43 CFR 10.11(d). The determinations in this notice are the sole responsibility of the museum, institution, or Federal agency that has control of the Native American human remains and associated funerary objects. The National Park Service is not responsible for the determinations in this notice. \n Consultation \n A detailed assessment of the human remains was made by the State Historical Society of Wisconsin professional staff in consultation with representatives of the Forest County Potawatomi Community, Wisconsin; Ho-Chunk Nation of Wisconsin; and the Menominee Indian Tribe of Wisconsin. \n History and Description of the Remains \n In1963, human remains representing, at minimum, one individual were removed from a burial located just below the plow zone at Riverbend 1 Site in Waupaca County, WI. The fragmentary human remains were excavated by the State Historical Society of Wisconsin and the Wisconsin Department of Transportation. As the burial had been partially disturbed by plowing, some of the remains were recovered during a surface survey prior to the excavation. The human remains were determined to be those of an adult Native American female. No known individuals were identified. The two associated funerary objects are a quartz shatter and a quartzite flake. \n Determinations Made by the State Historical Society of Wisconsin \n Officials of the State Historical Society of Wisconsin have determined that: \n \\xe2\\x80\\xa2 Pursuant to 25 U.S.C. 3001(9), the human remains described in this notice are Native American based on skeletal analysis. \n \\xe2\\x80\\xa2 Pursuant to 25 U.S.C. 3001(9), the human remains described in this notice represent the physical remains of one individual of Native American ancestry. \n \\xe2\\x80\\xa2 Treaties, Acts of Congress, or Executive Orders, indicate that the land from which the Native American human remains were removed is the aboriginal land of the Menominee Indian Tribe of Wisconsin. \n \\xe2\\x80\\xa2 Pursuant to 43 CFR 10.11(c)(1), the disposition of the human remains may be to the Menominee Indian Tribe of Wisconsin. \n Additional Requestors and Disposition \n Representatives of any Indian tribe or Native Hawaiian organization not identified in this notice that wish to request transfer of control of these human remains should submit a written request with information in support of the request to Jennifer Kolb, Wisconsin Historical Museum, 30 North Carroll Street, Madison, WI 53703, telephone (608) 261-2461, email Jennifer.Kolb@wisconsinhistory.org, by August 23, 2013. After that date, if no additional requestors have come forward, transfer of control of the human remains to the Menominee Tribe of Wisconsin may proceed. \n The State Historical Society of Wisconsin is responsible for notifying the Forest County Potawatomi Community, Wisconsin; Ho-Chunk Nation of Wisconsin; and the Menominee Tribe of Wisconsin that this notice has been published. \n ", "consultation": "A detailed assessment of the human remains was made by the State Historical Society of Wisconsin professional staff in consultation with representatives of the Forest County Potawatomi Community, Wisconsin; Ho-Chunk Nation of Wisconsin; and the Menominee Indian Tribe of Wisconsin. \n ", "h_d_r": "In1963, human remains representing, at minimum, one individual were removed from a burial located just below the plow zone at Riverbend 1 Site in Waupaca County, WI. The fragmentary human remains were excavated by the State Historical Society of Wisconsin and the Wisconsin Department of Transportation. As the burial had been partially disturbed by plowing, some of the remains were recovered during a surface survey prior to the excavation. The human remains were determined to be those of an adult Native American female. No known individuals were identified. The two associated funerary objects are a quartz shatter and a quartzite flake. \n ", "h_d_ci": "Null", "determinations": "Determinations Made by the State Historical Society of Wisconsin \n Officials of the State Historical Society of Wisconsin have determined that: \n \\xe2\\x80\\xa2 Pursuant to 25 U.S.C. 3001(9), the human remains described in this notice are Native American based on skeletal analysis. \n \\xe2\\x80\\xa2 Pursuant to 25 U.S.C. 3001(9), the human remains described in this notice represent the physical remains of one individual of Native American ancestry. \n \\xe2\\x80\\xa2 Treaties, Acts of Congress, or Executive Orders, indicate that the land from which the Native American human remains were removed is the aboriginal land of the Menominee Indian Tribe of Wisconsin. \n \\xe2\\x80\\xa2 Pursuant to 43 CFR 10.11(c)(1), the disposition of the human remains may be to the Menominee Indian Tribe of Wisconsin. \n ", "a_r_d": "Representatives of any Indian tribe or Native Hawaiian organization not identified in this notice that wish to request transfer of control of these human remains should submit a written request with information in support of the request to Jennifer Kolb, Wisconsin Historical Museum, 30 North Carroll Street, Madison, WI 53703, telephone (608) 261-2461, email Jennifer.Kolb@wisconsinhistory.org, by August 23, 2013. After that date, if no additional requestors have come forward, transfer of control of the human remains to the Menominee Tribe of Wisconsin may proceed. \n The State Historical Society of Wisconsin is responsible for notifying the Forest County Potawatomi Community, Wisconsin; Ho-Chunk Nation of Wisconsin; and the Menominee Tribe of Wisconsin that this notice has been published. \n "}