{"index": "I_943", "messy_full": "\\n      \\n        DEPARTMENT OF THE INTERIOR\\n        National Park Service\\n        [NPS-WASO-NAGPRA-13089; PPWOCRADN0-PCU00RP14.R50000]\\n        Notice of Inventory Completion: University of Oregon Museum of Natural and Cultural History, Eugene, OR\\n        \\n          AGENCY:\\n          National Park Service, Interior.\\n        \\n        \\n          ACTION:\\n          Notice.\\n        \\n        \\n          SUMMARY:\\n          The University of Oregon Museum of Natural and Cultural History has completed an inventory of human remains and associated funerary objects, in consultation with the appropriate Indian tribes or Native Hawaiian organizations, and has determined that there is a cultural affiliation between the human remains and associated funerary objects and present-day Indian tribes or Native Hawaiian organizations. Lineal descendants or representatives of any Indian tribe or Native Hawaiian organization not identified in this notice that wish to request transfer of control of these human remains and associated funerary objects should submit a written request to the University of Oregon Museum of Natural and Cultural History. If no additional requestors come forward, transfer of control of the human remains and associated funerary objects to the lineal descendants, Indian tribes, or Native Hawaiian organizations stated in this notice may proceed.\\n        \\n        \\n          DATES:\\n          Lineal descendants or representatives of any Indian tribe or Native Hawaiian organization not identified in this notice that wish to request transfer of control of these human remains and associated funerary objects should submit a written request with information in support of the request to the University of Oregon Museum of Natural and Cultural History at the address in this notice by July 17, 2013.\\n        \\n        \\n          ADDRESSES:\\n          Dr. Pamela Endzweig, Director of Collections, Museum of Natural and Cultural History, 1224 University of Oregon, Eugene, OR 97403-1224, telephone (541) 346-5120.\\n        \\n      \\n      \\n        SUPPLEMENTARY INFORMATION:\\n        Notice is here given in accordance with the Native American Graves Protection and Repatriation Act (NAGPRA), 25 U.S.C. 3003, of the completion of an inventory of human remains and associated funerary objects under the control of the University of Oregon Museum of Natural and Cultural History, Eugene, OR. The human remains and associated funerary objects were removed from Gilliam, Sherman, Wasco, and Wheeler Counties, OR.\\n        This notice is published as part of the National Park Service\\'s administrative responsibilities under NAGPRA, 25 U.S.C. 3003(d)(3). The determinations in this notice are the sole responsibility of the museum, institution, or Federal agency that has control of the Native American human remains and associated funerary objects. The National Park Service is not responsible for the determinations in this notice.\\n        Consultation\\n        A detailed assessment of the human remains was made by University of Oregon Museum of Natural and Cultural History professional staff in consultation with representatives of the Confederated Tribes of the Warm Springs Reservation of Oregon.\\n        History and Description of the Remains\\n\\n        In 1938, human remains representing, at minimum, one individual were removed from Pine Hollow Cave #1, along a tributary of the John Day River, in Sherman County, OR, during legally authorized excavations by archeologists from the University of Oregon. No known individual was identified. No associated funerary objects are present.\\n        In 1938, human remains representing, at minimum, four individuals were removed from Courthouse Rock, near Antelope, in Wasco County, OR, during legally authorized excavations by archeologists from the University of Oregon. No known individuals were identified. The 26 associated funerary objects are 13 points, 9 scrapers, 1 blade, 1 bone awl, 1 pumice block, and 1 lot of pigment samples.\\n        In 1946, human remains representing, at minimum, one individual were removed from Butte Creek Cave (site 35WH1), in Wheeler County, OR, during legally authorized excavations by archeologists from the University of Oregon. Objects removed from the site during a previous excavation in 1938 were subsequently found to be associated with this individual. No known individual was identified. The 25 associated funerary objects are 1 basket, 5 basket fragments, 7 scrapers, 1 piece of wolverine fur, 1 fragmentary cape or blanket of twined rabbit skin strips, 1 dog skeleton, 2 pieces of matting, 5 pieces of cordage, 1 piece of felt, and 1 slag.\\n        In 1946, human remains representing, at minimum, one individual were removed from a cremation in the vicinity of Hoover Creek, near Fossil, in Wheeler County, OR, during legally authorized excavations by archeologists from the University of Oregon. No known individual was identified. The 12 associated funerary objects are 1 scraper fragment, 1 copper pendant, 1 pipe in fragments, 2 worked tuff, 1 worked bone, 1 dentalium shell, 1 bird bone, 1 pestle, 1 worked chert, and 2 bone fragments.\\n        In 1951, human remains representing, at minimum, one individual were removed from the Condon Lumber Company mill, near Lonerock, in Gilliam County, OR, by the Gilliam County coroner and transferred to the University of Oregon Museum of Natural and Cultural History. No known individual was identified. No associated funerary objects are present.\\n        Based on archeological context, the individuals described above are determined to be Native American. Based on provenience, the Native American human remains are reasonably believed to be affiliated with the Tenino people. Historical documents, ethnographic sources, and oral history indicate that Tenino people have occupied north-central Oregon since pre-contact times. The Tenino people are one of the tribes that compose the Confederated Tribes of the Warm Springs Reservation of Oregon.\\n        Determinations Made by the University of Oregon Museum of Natural and Cultural History\\n        Officials of the University of Oregon Museum of Natural and Cultural History have determined that:\\n        \\xe2\\x80\\xa2 Pursuant to 25 U.S.C. 3001(9), the human remains described in this notice represent the physical remains of eight individuals of Native American ancestry.\\n        \\xe2\\x80\\xa2 Pursuant to 25 U.S.C. 3001(3)(A), the 63 objects described in this notice are reasonably believed to have been placed with or near individual human remains at the time of death or later as part of the death rite or ceremony.\\n        \\xe2\\x80\\xa2 Pursuant to 25 U.S.C. 3001(2), there is a relationship of shared group identity that can be reasonably traced between the Native American human remains and associated funerary objects and the Confederated Tribes of the Warm Springs Reservation of Oregon.\\n        Additional Requestors and Disposition\\n        Lineal descendants or representatives of any Indian tribe or Native Hawaiian organization not identified in this notice that wish to request transfer of control of these human remains and associated funerary objects should submit a written request with information in support of the request to Dr. Pamela Endzweig, Director of Collections, University of Oregon Museum of Natural and Cultural History 1224 University of Oregon, Eugene, OR 97403-1224, telephone (541) 346-5120, by July 17, 2013. After that date, if no additional requestors have come forward, transfer of control of the human remains and associated funerary objects to the Confederated Tribes of the Warm Springs Reservation of Oregon may proceed.\\n        The University of Oregon Museum of Natural and Cultural History is responsible for notifying the Confederated Tribes of the Warm Springs Reservation of Oregon that this notice has been published.\\n        \\n          Dated: May 10, 2013.\\n          Sherry Hutt,\\n          Manager, National NAGPRA Program.\\n        \\n      \\n      [FR Doc. 2013-14330 Filed 6-14-13; 8:45 am]\\n      BILLING CODE 4312-50-P\\n    ", "agency1": "DEPARTMENT OF THE INTERIOR", "sub_agency1": "National Park Service", "dep_doc": "[NPS-WASO-NAGPRA-13089; PPWOCRADN0-PCU00RP14.R50000]", "subject": "Notice of Inventory Completion: University of Oregon Museum of Natural and Cultural History, Eugene, OR", "agency2": "National Park Service, Interior.", "action": "Notice.", "summary": "The University of Oregon Museum of Natural and Cultural History has completed an inventory of human remains and associated funerary objects, in consultation with the appropriate Indian tribes or Native Hawaiian organizations, and has determined that there is a cultural affiliation between the human remains and associated funerary objects and present-day Indian tribes or Native Hawaiian organizations. Lineal descendants or representatives of any Indian tribe or Native Hawaiian organization not identified in this notice that wish to request transfer of control of these human remains and associated funerary objects should submit a written request to the University of Oregon Museum of Natural and Cultural History. If no additional requestors come forward, transfer of control of the human remains and associated funerary objects to the lineal descendants, Indian tribes, or Native Hawaiian organizations stated in this notice may proceed.", "dates": "Lineal descendants or representatives of any Indian tribe or Native Hawaiian organization not identified in this notice that wish to request transfer of control of these human remains and associated funerary objects should submit a written request with information in support of the request to the University of Oregon Museum of Natural and Cultural History at the address in this notice by July 17, 2013.", "addresses": "Dr. Pamela Endzweig, Director of Collections, Museum of Natural and Cultural History, 1224 University of Oregon, Eugene, OR 97403-1224, telephone (541) 346-5120.", "signature_dated": "Dated: May 10, 2013.", "signature_name": "Sherry Hutt,", "signature_title": "Manager, National NAGPRA Program.", "fr_doc": "[FR Doc. 2013-14330 Filed 6-14-13; 8:45 am]", "billing_code": "BILLING CODE 4312-50-P", "supp_info": "SUPPLEMENTARY INFORMATION: \n Notice is here given in accordance with the Native American Graves Protection and Repatriation Act (NAGPRA), 25 U.S.C. 3003, of the completion of an inventory of human remains and associated funerary objects under the control of the University of Oregon Museum of Natural and Cultural History, Eugene, OR. The human remains and associated funerary objects were removed from Gilliam, Sherman, Wasco, and Wheeler Counties, OR. \n This notice is published as part of the National Park Service\\'s administrative responsibilities under NAGPRA, 25 U.S.C. 3003(d)(3). The determinations in this notice are the sole responsibility of the museum, institution, or Federal agency that has control of the Native American human remains and associated funerary objects. The National Park Service is not responsible for the determinations in this notice. \n Consultation \n A detailed assessment of the human remains was made by University of Oregon Museum of Natural and Cultural History professional staff in consultation with representatives of the Confederated Tribes of the Warm Springs Reservation of Oregon. \n History and Description of the Remains \n In 1938, human remains representing, at minimum, one individual were removed from Pine Hollow Cave #1, along a tributary of the John Day River, in Sherman County, OR, during legally authorized excavations by archeologists from the University of Oregon. No known individual was identified. No associated funerary objects are present. \n In 1938, human remains representing, at minimum, four individuals were removed from Courthouse Rock, near Antelope, in Wasco County, OR, during legally authorized excavations by archeologists from the University of Oregon. No known individuals were identified. The 26 associated funerary objects are 13 points, 9 scrapers, 1 blade, 1 bone awl, 1 pumice block, and 1 lot of pigment samples. \n In 1946, human remains representing, at minimum, one individual were removed from Butte Creek Cave (site 35WH1), in Wheeler County, OR, during legally authorized excavations by archeologists from the University of Oregon. Objects removed from the site during a previous excavation in 1938 were subsequently found to be associated with this individual. No known individual was identified. The 25 associated funerary objects are 1 basket, 5 basket fragments, 7 scrapers, 1 piece of wolverine fur, 1 fragmentary cape or blanket of twined rabbit skin strips, 1 dog skeleton, 2 pieces of matting, 5 pieces of cordage, 1 piece of felt, and 1 slag. \n In 1946, human remains representing, at minimum, one individual were removed from a cremation in the vicinity of Hoover Creek, near Fossil, in Wheeler County, OR, during legally authorized excavations by archeologists from the University of Oregon. No known individual was identified. The 12 associated funerary objects are 1 scraper fragment, 1 copper pendant, 1 pipe in fragments, 2 worked tuff, 1 worked bone, 1 dentalium shell, 1 bird bone, 1 pestle, 1 worked chert, and 2 bone fragments. \n In 1951, human remains representing, at minimum, one individual were removed from the Condon Lumber Company mill, near Lonerock, in Gilliam County, OR, by the Gilliam County coroner and transferred to the University of Oregon Museum of Natural and Cultural History. No known individual was identified. No associated funerary objects are present. \n Based on archeological context, the individuals described above are determined to be Native American. Based on provenience, the Native American human remains are reasonably believed to be affiliated with the Tenino people. Historical documents, ethnographic sources, and oral history indicate that Tenino people have occupied north-central Oregon since pre-contact times. The Tenino people are one of the tribes that compose the Confederated Tribes of the Warm Springs Reservation of Oregon. \n Determinations Made by the University of Oregon Museum of Natural and Cultural History \n Officials of the University of Oregon Museum of Natural and Cultural History have determined that: \n \\xe2\\x80\\xa2 Pursuant to 25 U.S.C. 3001(9), the human remains described in this notice represent the physical remains of eight individuals of Native American ancestry. \n \\xe2\\x80\\xa2 Pursuant to 25 U.S.C. 3001(3)(A), the 63 objects described in this notice are reasonably believed to have been placed with or near individual human remains at the time of death or later as part of the death rite or ceremony. \n \\xe2\\x80\\xa2 Pursuant to 25 U.S.C. 3001(2), there is a relationship of shared group identity that can be reasonably traced between the Native American human remains and associated funerary objects and the Confederated Tribes of the Warm Springs Reservation of Oregon. \n Additional Requestors and Disposition \n Lineal descendants or representatives of any Indian tribe or Native Hawaiian organization not identified in this notice that wish to request transfer of control of these human remains and associated funerary objects should submit a written request with information in support of the request to Dr. Pamela Endzweig, Director of Collections, University of Oregon Museum of Natural and Cultural History 1224 University of Oregon, Eugene, OR 97403-1224, telephone (541) 346-5120, by July 17, 2013. After that date, if no additional requestors have come forward, transfer of control of the human remains and associated funerary objects to the Confederated Tribes of the Warm Springs Reservation of Oregon may proceed. \n The University of Oregon Museum of Natural and Cultural History is responsible for notifying the Confederated Tribes of the Warm Springs Reservation of Oregon that this notice has been published. \n ", "consultation": "A detailed assessment of the human remains was made by University of Oregon Museum of Natural and Cultural History professional staff in consultation with representatives of the Confederated Tribes of the Warm Springs Reservation of Oregon. \n ", "h_d_r": "In 1938, human remains representing, at minimum, one individual were removed from Pine Hollow Cave #1, along a tributary of the John Day River, in Sherman County, OR, during legally authorized excavations by archeologists from the University of Oregon. No known individual was identified. No associated funerary objects are present. \n In 1938, human remains representing, at minimum, four individuals were removed from Courthouse Rock, near Antelope, in Wasco County, OR, during legally authorized excavations by archeologists from the University of Oregon. No known individuals were identified. The 26 associated funerary objects are 13 points, 9 scrapers, 1 blade, 1 bone awl, 1 pumice block, and 1 lot of pigment samples. \n In 1946, human remains representing, at minimum, one individual were removed from Butte Creek Cave (site 35WH1), in Wheeler County, OR, during legally authorized excavations by archeologists from the University of Oregon. Objects removed from the site during a previous excavation in 1938 were subsequently found to be associated with this individual. No known individual was identified. The 25 associated funerary objects are 1 basket, 5 basket fragments, 7 scrapers, 1 piece of wolverine fur, 1 fragmentary cape or blanket of twined rabbit skin strips, 1 dog skeleton, 2 pieces of matting, 5 pieces of cordage, 1 piece of felt, and 1 slag. \n In 1946, human remains representing, at minimum, one individual were removed from a cremation in the vicinity of Hoover Creek, near Fossil, in Wheeler County, OR, during legally authorized excavations by archeologists from the University of Oregon. No known individual was identified. The 12 associated funerary objects are 1 scraper fragment, 1 copper pendant, 1 pipe in fragments, 2 worked tuff, 1 worked bone, 1 dentalium shell, 1 bird bone, 1 pestle, 1 worked chert, and 2 bone fragments. \n In 1951, human remains representing, at minimum, one individual were removed from the Condon Lumber Company mill, near Lonerock, in Gilliam County, OR, by the Gilliam County coroner and transferred to the University of Oregon Museum of Natural and Cultural History. No known individual was identified. No associated funerary objects are present. \n Based on archeological context, the individuals described above are determined to be Native American. Based on provenience, the Native American human remains are reasonably believed to be affiliated with the Tenino people. Historical documents, ethnographic sources, and oral history indicate that Tenino people have occupied north-central Oregon since pre-contact times. The Tenino people are one of the tribes that compose the Confederated Tribes of the Warm Springs Reservation of Oregon. \n ", "h_d_ci": "Null", "determinations": "Determinations Made by the University of Oregon Museum of Natural and Cultural History \n Officials of the University of Oregon Museum of Natural and Cultural History have determined that: \n \\xe2\\x80\\xa2 Pursuant to 25 U.S.C. 3001(9), the human remains described in this notice represent the physical remains of eight individuals of Native American ancestry. \n \\xe2\\x80\\xa2 Pursuant to 25 U.S.C. 3001(3)(A), the 63 objects described in this notice are reasonably believed to have been placed with or near individual human remains at the time of death or later as part of the death rite or ceremony. \n \\xe2\\x80\\xa2 Pursuant to 25 U.S.C. 3001(2), there is a relationship of shared group identity that can be reasonably traced between the Native American human remains and associated funerary objects and the Confederated Tribes of the Warm Springs Reservation of Oregon. \n ", "a_r_d": "Lineal descendants or representatives of any Indian tribe or Native Hawaiian organization not identified in this notice that wish to request transfer of control of these human remains and associated funerary objects should submit a written request with information in support of the request to Dr. Pamela Endzweig, Director of Collections, University of Oregon Museum of Natural and Cultural History 1224 University of Oregon, Eugene, OR 97403-1224, telephone (541) 346-5120, by July 17, 2013. After that date, if no additional requestors have come forward, transfer of control of the human remains and associated funerary objects to the Confederated Tribes of the Warm Springs Reservation of Oregon may proceed. \n The University of Oregon Museum of Natural and Cultural History is responsible for notifying the Confederated Tribes of the Warm Springs Reservation of Oregon that this notice has been published. \n "}