{"index": "I_959", "messy_full": "\\n      \\n        DEPARTMENT OF THE INTERIOR\\n        National Park Service\\n        [NPS-WASO-NAGPRA-12562; PPWOCRADN0-PCU00RP14.R50000]\\n        Notice of Inventory Completion: U.S. Department of the Interior, Bureau of Indian Affairs, Washington, DC, and U.S. Department of the Interior, National Park Service, Mesa Verde National Park, Mesa Verde, CO; Correction\\n        \\n          AGENCY:\\n          National Park Service, Interior.\\n        \\n        \\n          ACTION:\\n          Notice; correction.\\n        \\n        \\n          SUMMARY:\\n\\n          The U.S. Department of the Interior, Bureau of Indian Affairs has corrected an inventory of human remains and associated funerary objects, published in a Notice of Inventory Completion in the Federal Register on March 15, 2011. This notice corrects the cultural affiliation of the human remains and associated funerary objects in that inventory. Lineal descendants or representatives of any Indian tribe or Native Hawaiian organization not identified in this notice that wish to request transfer of control of these human remains and associated funerary objects should submit a written request to the U.S. Department of the Interior, Bureau of Indian Affairs. If no additional requestors come forward, transfer of control of the human remains and associated funerary objects to the lineal descendants, Indian tribes, or Native Hawaiian organizations stated in this notice may proceed.\\n        \\n        \\n          DATES:\\n          Lineal descendants or representatives of any Indian tribe or Native Hawaiian organization not identified in this notice that wish to request transfer of control of these human remains and associated funerary objects should submit a written request with information in support of the request to the U.S. Department of the Interior, Bureau of Indian Affairs at the address below by May 28, 2013.\\n        \\n        \\n          ADDRESSES:\\n\\n          Anna Pardo, Museum Program Manager/NAGPRA Coordinator, U.S. Department of the Interior, Indian Affairs, 12220 Sunrise Valley Drive, Room 6084, Reston, VA 20191, telephone (703) 390-6343, email Anna.Pardo@bia.gov.\\n          \\n        \\n      \\n      \\n        SUPPLEMENTARY INFORMATION:\\n        Notice is here given in accordance with the Native American Graves Protection and Repatriation Act (NAGPRA), 25 U.S.C. 3003, of the correction of an inventory of human remains and associated funerary objects under the control of the U.S. Department of the Interior, Bureau of Indian Affairs, Washington, DC. The human remains and associated funerary objects were removed from sites on the Ute Mountain Ute Reservation, CO.\\n        This notice is published as part of the National Park Service\\'s administrative responsibilities under NAGPRA, 25 U.S.C. 3003(d)(3). The determinations in this notice are the sole responsibility of the museum, institution, or Federal agency that has control of the Native American human remains and associated funerary objects. The National Park Service is not responsible for the determinations in this notice.\\n\\n        This notice corrects the cultural affiliation determination published in a Notice of Inventory Completion in the Federal Register (78 FR 14060-14061, March 15, 2011). After additional research and consultation with subject matter experts, the Bureau of Indian Affairs has reassessed cultural affiliation. Transfer of control of the items in this notice has not occurred.\\n        Correction\\n        In the Federal Register (78 FR 14060, March 15, 2011), paragraph 3, sentence one is corrected by deleting the words \\xe2\\x80\\x9c(hereinafter referred to as \\xe2\\x80\\x9cThe Tribes.\\xe2\\x80\\x9d).\\xe2\\x80\\x9d\\n        In the Federal Register (78 FR 14060-14061, March 15, 2011), paragraph 10 is corrected by substituting the following paragraph:\\n        \\n        \\n          Based on the preponderance of evidence, including geographical, kinship, biological, archeological, anthropological, linguistic, folklore, oral tradition, historical, and expert opinion, officials of the Bureau of Indian Affairs have reasonably determined that the Native American human remains are ancestral Puebloan. Descendants of ancestral Puebloan culture are members of the present-day tribes of the Hopi Tribe of Arizona; Kewa Pueblo, New Mexico (previously listed as the Pueblo of Santo Domingo); Ohkay Owingeh, New Mexico (previously listed as the Pueblo of San Juan); Pueblo of Acoma, New Mexico; Pueblo of Cochiti, New Mexico; Pueblo of Isleta, New Mexico; Pueblo of Jemez, New Mexico; Pueblo of Laguna, New Mexico; Pueblo of Nambe, New Mexico; Pueblo of Picuris, New Mexico; Pueblo of Pojoaque, New Mexico; Pueblo of San Felipe, New Mexico; Pueblo of San Ildefonso, New Mexico; Pueblo of Sandia, New Mexico; Pueblo of Santa Ana, New Mexico; Pueblo of Santa Clara, New Mexico; Pueblo of Taos, New Mexico; Pueblo of Tesuque, New Mexico; Pueblo of Zia, New Mexico; Ysleta Del Sur Pueblo of Texas; and Zuni Tribe of the Zuni Reservation, New Mexico (hereafter referred to as \\xe2\\x80\\x9cThe Tribes\\xe2\\x80\\x9d).\\n        \\n        \\n        In the Federal Register (78 FR 14060-14061, March 15, 2011), the last sentence of paragraph 11 is corrected by substituting the following sentence:\\n        \\n        \\n          Lastly, the officials of the Bureau of Indian Affairs have determined, pursuant to 25 U.S.C. 3001(2), that there is a relationship of shared group identity that can be reasonably traced between the Native American human remains and associated funerary objects and The Tribes.\\n        \\n        \\n        Additional Requestors and Disposition\\n\\n        Lineal descendants or representatives of any Indian tribe or Native Hawaiian organization not identified in this notice that wish to request transfer of control of these human remains and associated funerary objects should submit a written request with information in support of the request to Anna Pardo, Museum Program Manager/NAGPRA Coordinator, U.S. Department of the Interior, Indian Affairs, 12220 Sunrise Valley Drive, Room 6084, Reston, VA 20191, telephone (703) 390-6343, email Anna.Pardo@bia.gov, by May 28, 2013. After that date, if no additional requestors have come forward, transfer of control of the human remains and associated funerary objects to the Hopi Tribe of Arizona; Kewa Pueblo, New Mexico (previously listed as the Pueblo of Santo Domingo); Ohkay Owingeh, New Mexico (previously listed as the Pueblo of San Juan); Pueblo of Acoma, New Mexico; Pueblo of Cochiti, New Mexico; Pueblo of Isleta, New Mexico; Pueblo of Jemez, New Mexico; Pueblo of Laguna, New Mexico; Pueblo of Nambe, New Mexico; Pueblo of Picuris, New Mexico; Pueblo of Pojoaque, New Mexico; Pueblo of San Felipe, New Mexico; Pueblo of San Ildefonso, New Mexico; Pueblo of Sandia, New Mexico; Pueblo of Santa Ana, New Mexico; Pueblo of Santa Clara, New Mexico; Pueblo of Taos, New Mexico; Pueblo of Tesuque, New Mexico; Pueblo of Zia, New Mexico; Ysleta Del Sur Pueblo of Texas; and Zuni Tribe of the Zuni Reservation, New Mexico, may proceed.\\n\\n        The U.S. Department of the Interior, Bureau of Indian Affairs is responsible for notifying the Hopi Tribe of Arizona; Kewa Pueblo, New Mexico (previously listed as the Pueblo of Santo Domingo); Navajo Nation, Arizona, New Mexico & Utah; Ohkay Owingeh, New Mexico (previously listed as the Pueblo of San Juan); Pueblo of Acoma, New Mexico; Pueblo of Cochiti, New Mexico; Pueblo of Isleta, New Mexico; Pueblo of Jemez, New Mexico; Pueblo of Laguna, New Mexico; Pueblo of Nambe, New Mexico; Pueblo of Picuris, New Mexico; Pueblo of Pojoaque, New Mexico; Pueblo of San Felipe, New Mexico; Pueblo of San Ildefonso, New Mexico; Pueblo of Sandia, New Mexico; Pueblo of Santa Ana, New Mexico; Pueblo of Santa Clara, New Mexico; Pueblo of Taos, New Mexico; Pueblo of Tesuque, New Mexico; Pueblo of Zia, New Mexico; Southern Ute Indian Tribe of the Southern Ute Reservation, Colorado; Ute Mountain Tribe of the Ute Mountain Reservation, Colorado, New Mexico & Utah; Ysleta Del Sur Pueblo of Texas; and Zuni Tribe of the Zuni Reservation, New Mexico, that this notice has been published.\\n        \\n          Dated: March 13, 2013.\\n          Sherry Hutt,\\n          Manager, National NAGPRA Program. \\n        \\n      \\n      [FR Doc. 2013-09746 Filed 4-24-13; 8:45 am]\\n      BILLING CODE 4312-50-P\\n    ", "agency1": "DEPARTMENT OF THE INTERIOR", "sub_agency1": "National Park Service", "dep_doc": "[NPS-WASO-NAGPRA-12562; PPWOCRADN0-PCU00RP14.R50000]", "subject": "Notice of Inventory Completion: U.S. Department of the Interior, Bureau of Indian Affairs, Washington, DC, and U.S. Department of the Interior, National Park Service, Mesa Verde National Park, Mesa Verde, CO; Correction", "agency2": "National Park Service, Interior.", "action": "Notice; correction.", "summary": "The U.S. Department of the Interior, Bureau of Indian Affairs has corrected an inventory of human remains and associated funerary objects, published in a Notice of Inventory Completion in the Federal Register on March 15, 2011. This notice corrects the cultural affiliation of the human remains and associated funerary objects in that inventory. Lineal descendants or representatives of any Indian tribe or Native Hawaiian organization not identified in this notice that wish to request transfer of control of these human remains and associated funerary objects should submit a written request to the U.S. Department of the Interior, Bureau of Indian Affairs. If no additional requestors come forward, transfer of control of the human remains and associated funerary objects to the lineal descendants, Indian tribes, or Native Hawaiian organizations stated in this notice may proceed.", "dates": "Lineal descendants or representatives of any Indian tribe or Native Hawaiian organization not identified in this notice that wish to request transfer of control of these human remains and associated funerary objects should submit a written request with information in support of the request to the U.S. Department of the Interior, Bureau of Indian Affairs at the address below by May 28, 2013.", "addresses": "Anna Pardo, Museum Program Manager/NAGPRA Coordinator, U.S. Department of the Interior, Indian Affairs, 12220 Sunrise Valley Drive, Room 6084, Reston, VA 20191, telephone (703) 390-6343, email Anna.Pardo@bia.gov.\\n          ", "signature_dated": "Dated: March 13, 2013.", "signature_name": "Sherry Hutt,", "signature_title": "Manager, National NAGPRA Program. ", "fr_doc": "[FR Doc. 2013-09746 Filed 4-24-13; 8:45 am]", "billing_code": "BILLING CODE 4312-50-P", "supp_info": "SUPPLEMENTARY INFORMATION: \n Notice is here given in accordance with the Native American Graves Protection and Repatriation Act (NAGPRA), 25 U.S.C. 3003, of the correction of an inventory of human remains and associated funerary objects under the control of the U.S. Department of the Interior, Bureau of Indian Affairs, Washington, DC. The human remains and associated funerary objects were removed from sites on the Ute Mountain Ute Reservation, CO. \n This notice is published as part of the National Park Service\\'s administrative responsibilities under NAGPRA, 25 U.S.C. 3003(d)(3). The determinations in this notice are the sole responsibility of the museum, institution, or Federal agency that has control of the Native American human remains and associated funerary objects. The National Park Service is not responsible for the determinations in this notice. \n This notice corrects the cultural affiliation determination published in a Notice of Inventory Completion in the Federal Register (78 FR 14060-14061, March 15, 2011). After additional research and consultation with subject matter experts, the Bureau of Indian Affairs has reassessed cultural affiliation. Transfer of control of the items in this notice has not occurred. \n Correction \n In the Federal Register (78 FR 14060, March 15, 2011), paragraph 3, sentence one is corrected by deleting the words \\xe2\\x80\\x9c(hereinafter referred to as \\xe2\\x80\\x9cThe Tribes.\\xe2\\x80\\x9d).\\xe2\\x80\\x9d \n In the Federal Register (78 FR 14060-14061, March 15, 2011), paragraph 10 is corrected by substituting the following paragraph: \n In the Federal Register (78 FR 14060-14061, March 15, 2011), the last sentence of paragraph 11 is corrected by substituting the following sentence: \n Additional Requestors and Disposition \n Lineal descendants or representatives of any Indian tribe or Native Hawaiian organization not identified in this notice that wish to request transfer of control of these human remains and associated funerary objects should submit a written request with information in support of the request to Anna Pardo, Museum Program Manager/NAGPRA Coordinator, U.S. Department of the Interior, Indian Affairs, 12220 Sunrise Valley Drive, Room 6084, Reston, VA 20191, telephone (703) 390-6343, email Anna.Pardo@bia.gov, by May 28, 2013. After that date, if no additional requestors have come forward, transfer of control of the human remains and associated funerary objects to the Hopi Tribe of Arizona; Kewa Pueblo, New Mexico (previously listed as the Pueblo of Santo Domingo); Ohkay Owingeh, New Mexico (previously listed as the Pueblo of San Juan); Pueblo of Acoma, New Mexico; Pueblo of Cochiti, New Mexico; Pueblo of Isleta, New Mexico; Pueblo of Jemez, New Mexico; Pueblo of Laguna, New Mexico; Pueblo of Nambe, New Mexico; Pueblo of Picuris, New Mexico; Pueblo of Pojoaque, New Mexico; Pueblo of San Felipe, New Mexico; Pueblo of San Ildefonso, New Mexico; Pueblo of Sandia, New Mexico; Pueblo of Santa Ana, New Mexico; Pueblo of Santa Clara, New Mexico; Pueblo of Taos, New Mexico; Pueblo of Tesuque, New Mexico; Pueblo of Zia, New Mexico; Ysleta Del Sur Pueblo of Texas; and Zuni Tribe of the Zuni Reservation, New Mexico, may proceed. \n The U.S. Department of the Interior, Bureau of Indian Affairs is responsible for notifying the Hopi Tribe of Arizona; Kewa Pueblo, New Mexico (previously listed as the Pueblo of Santo Domingo); Navajo Nation, Arizona, New Mexico & Utah; Ohkay Owingeh, New Mexico (previously listed as the Pueblo of San Juan); Pueblo of Acoma, New Mexico; Pueblo of Cochiti, New Mexico; Pueblo of Isleta, New Mexico; Pueblo of Jemez, New Mexico; Pueblo of Laguna, New Mexico; Pueblo of Nambe, New Mexico; Pueblo of Picuris, New Mexico; Pueblo of Pojoaque, New Mexico; Pueblo of San Felipe, New Mexico; Pueblo of San Ildefonso, New Mexico; Pueblo of Sandia, New Mexico; Pueblo of Santa Ana, New Mexico; Pueblo of Santa Clara, New Mexico; Pueblo of Taos, New Mexico; Pueblo of Tesuque, New Mexico; Pueblo of Zia, New Mexico; Southern Ute Indian Tribe of the Southern Ute Reservation, Colorado; Ute Mountain Tribe of the Ute Mountain Reservation, Colorado, New Mexico & Utah; Ysleta Del Sur Pueblo of Texas; and Zuni Tribe of the Zuni Reservation, New Mexico, that this notice has been published. \n ", "consultation": "Null", "h_d_r": "Null", "h_d_ci": "Null", "determinations": "Null", "a_r_d": "Lineal descendants or representatives of any Indian tribe or Native Hawaiian organization not identified in this notice that wish to request transfer of control of these human remains and associated funerary objects should submit a written request with information in support of the request to Anna Pardo, Museum Program Manager/NAGPRA Coordinator, U.S. Department of the Interior, Indian Affairs, 12220 Sunrise Valley Drive, Room 6084, Reston, VA 20191, telephone (703) 390-6343, email Anna.Pardo@bia.gov, by May 28, 2013. After that date, if no additional requestors have come forward, transfer of control of the human remains and associated funerary objects to the Hopi Tribe of Arizona; Kewa Pueblo, New Mexico (previously listed as the Pueblo of Santo Domingo); Ohkay Owingeh, New Mexico (previously listed as the Pueblo of San Juan); Pueblo of Acoma, New Mexico; Pueblo of Cochiti, New Mexico; Pueblo of Isleta, New Mexico; Pueblo of Jemez, New Mexico; Pueblo of Laguna, New Mexico; Pueblo of Nambe, New Mexico; Pueblo of Picuris, New Mexico; Pueblo of Pojoaque, New Mexico; Pueblo of San Felipe, New Mexico; Pueblo of San Ildefonso, New Mexico; Pueblo of Sandia, New Mexico; Pueblo of Santa Ana, New Mexico; Pueblo of Santa Clara, New Mexico; Pueblo of Taos, New Mexico; Pueblo of Tesuque, New Mexico; Pueblo of Zia, New Mexico; Ysleta Del Sur Pueblo of Texas; and Zuni Tribe of the Zuni Reservation, New Mexico, may proceed. \n The U.S. Department of the Interior, Bureau of Indian Affairs is responsible for notifying the Hopi Tribe of Arizona; Kewa Pueblo, New Mexico (previously listed as the Pueblo of Santo Domingo); Navajo Nation, Arizona, New Mexico & Utah; Ohkay Owingeh, New Mexico (previously listed as the Pueblo of San Juan); Pueblo of Acoma, New Mexico; Pueblo of Cochiti, New Mexico; Pueblo of Isleta, New Mexico; Pueblo of Jemez, New Mexico; Pueblo of Laguna, New Mexico; Pueblo of Nambe, New Mexico; Pueblo of Picuris, New Mexico; Pueblo of Pojoaque, New Mexico; Pueblo of San Felipe, New Mexico; Pueblo of San Ildefonso, New Mexico; Pueblo of Sandia, New Mexico; Pueblo of Santa Ana, New Mexico; Pueblo of Santa Clara, New Mexico; Pueblo of Taos, New Mexico; Pueblo of Tesuque, New Mexico; Pueblo of Zia, New Mexico; Southern Ute Indian Tribe of the Southern Ute Reservation, Colorado; Ute Mountain Tribe of the Ute Mountain Reservation, Colorado, New Mexico & Utah; Ysleta Del Sur Pueblo of Texas; and Zuni Tribe of the Zuni Reservation, New Mexico, that this notice has been published. \n "}