{"index": "I_95", "messy_full": "\\n      \\n        DEPARTMENT OF THE INTERIOR\\n        National Park Service\\n        [NPS-WASO-NAGPRA-NPS0027628; PPWOCRADN0-PCU00RP14.R50000]\\n        Notice of Inventory Completion for Native American Human Remains and Associated Funerary Objects in the Possession of the University of Denver Department of Anthropology and Museum of Anthropology, Denver Colorado, CO; Correction; Correction\\n        \\n          AGENCY:\\n          National Park Service, Interior.\\n        \\n        \\n          ACTION:\\n          Notice; correction.\\n        \\n        \\n          SUMMARY:\\n\\n          The University of Denver Museum of Anthropology has corrected an inventory of human remains and associated funerary objects, published in a Notice of Inventory Completion in the Federal Register on November 13, 2000. This notice corrects the cultural affiliation. Lineal descendants or representatives of any Indian Tribe or Native Hawaiian organization not identified in this notice that wish to request transfer of control of these human remains and associated funerary objects should submit a written request to the University of Denver Museum of Anthropology. If no additional requestors come forward, transfer of control of the human remains and associated funerary objects to the lineal descendants, Indian Tribes, or Native Hawaiian organizations stated in this notice may proceed.\\n        \\n        \\n          DATES:\\n          Lineal descendants or representatives of any Indian Tribe or Native Hawaiian organization not identified in this notice that wish to request transfer of control of these human remains and associated funerary objects should submit a written request with information in support of the request to the University of Denver Museum of Anthropology at the address in this notice by May 30, 2019.\\n        \\n        \\n          ADDRESSES:\\n\\n          Anne Amati, University of Denver Museum of Anthropology, 2000 East Asbury Avenue, Sturm Hall Room 146, Denver, CO 80208, telephone (303) 871-2687, email anne.amati@du.edu.\\n          \\n        \\n      \\n      \\n        SUPPLEMENTARY INFORMATION:\\n        Notice is here given in accordance with the Native American Graves Protection and Repatriation Act (NAGPRA), 25 U.S.C. 3003, of the correction of an inventory of human remains and associated funerary objects under the control of the University of Denver Museum of Anthropology, Denver, CO. The human remains and associated funerary objects were removed from Pueblo Blanco, Santa Fe County, NM.\\n        This notice is published as part of the National Park Service\\'s administrative responsibilities under NAGPRA, 25 U.S.C. 3003(d)(3). The determinations in this notice are the sole responsibility of the museum, institution, or Federal agency that has control of the Native American human remains and associated funerary objects. The National Park Service is not responsible for the determinations in this notice.\\n\\n        This notice corrects the cultural affiliation published in a Notice of Inventory Completion in the Federal Register (65 FR 67757-67758, November 13, 2000). This correction is being made following additional consultation that provided new evidence of cultural affiliation. Transfer of control of the items in this correction notice has not occurred.\\n        Correction\\n        In the Federal Register (65 FR 67757, November 13, 2000), column 3, paragraph 3, sentence 1 is corrected by substituting the following sentence:\\n        \\n        \\n          A detailed assessment of the human remains was made by University of Denver Department of Anthropology and Museum of Anthropology professional staff, a contract physical anthropologist, and the New Mexico State Archaeologist in consultation with representatives of the Colorado River Indian Tribes of the Colorado River Indian Reservation, Arizona and California; Hopi Tribe of Arizona; Kewa Pueblo, New Mexico (previously listed as the Pueblo of Santo Domingo); Ohkay Owingeh, New Mexico (previously listed as the Pueblo of San Juan); Pueblo of Pojoaque, New Mexico; and Pueblo of Tesuque, New Mexico (hereafter referred to as \\xe2\\x80\\x9cThe Consulted Tribes\\xe2\\x80\\x9d).\\n        \\n        \\n        In the Federal Register (65 FR 67757, November 13, 2000), column 3, paragraph 5, sentences 1-4 are corrected by substituting the following sentences:\\n        \\n        \\n          Pueblo Blanco (site LA 40) is a large Pueblo IV-period Ancestral Pueblo village on the west side of the Galisteo Basin. The evidence presented in consultations with the Hopi Tribe of Arizona; Kewa Pueblo, New Mexico (previously listed as the Pueblo of Santo Domingo); Ohkay Owingeh, New Mexico (previously listed as the Pueblo of San Juan); Pueblo of Pojoaque, New Mexico; and Pueblo of Tesuque, New Mexico, supported by the ethnohistoric record and geographical and archeological evidence, demonstrates a cultural affiliation between Pueblo Blanco and the present day Pueblos who are the descendants of Ancestral Puebloan groups.\\n        \\n        \\n        In the Federal Register (65 FR 67758, November 13, 2000), column 1, paragraph 1, sentence 3 is corrected by substituting the following sentence:\\n        \\n        \\n          Lastly, officials of the University of Denver Department of Anthropology and Museum of Anthropology have determined that, pursuant to 43 CFR 10.2 (e), there is a relationship of shared group identity that can be reasonably traced between the Native American human remains and associated funerary objects and the Hopi Tribe of Arizona; Kewa Pueblo, New Mexico (previously listed as the Pueblo of Santo Domingo); Ohkay Owingeh, New Mexico (previously listed as the Pueblo of San Juan); Pueblo of Acoma, New Mexico; Pueblo of Cochiti, New Mexico; Pueblo of Isleta, New Mexico; Pueblo of Jemez, New Mexico; Pueblo of Laguna, New Mexico; Pueblo of Nambe, New Mexico; Pueblo of Picuris, New Mexico; Pueblo of Pojoaque, New Mexico; Pueblo of San Felipe, New Mexico; Pueblo of San Ildefonso, New Mexico; Pueblo of Sandia, New Mexico; Pueblo of Santa Ana, New Mexico; Pueblo of Santa Clara, New Mexico; Pueblo of Taos, New Mexico; Pueblo of Tesuque, New Mexico; Pueblo of Zia, New Mexico; Ysleta del Sur Pueblo (previously listed as the Ysleta Del Sur Pueblo of Texas); and the Zuni Tribe of the Zuni Reservation, New Mexico (hereafter referred to as \\xe2\\x80\\x9cThe Affiliated Tribes\\xe2\\x80\\x9d).\\n        \\n        \\n        Additional Requestors and Disposition\\n\\n        Lineal descendants or representatives of any Indian Tribe or Native Hawaiian organization not identified in this notice that wish to request transfer of control of these human remains and associated funerary objects should submit a written request with information in support of the request to Anne Amati, University of Denver Museum of Anthropology, 2000 E Asbury Avenue, Denver, CO 80208, telephone (303) 871-2687, email anne.amati@du.edu, by May 30, 2019. After that date, if no additional requestors have come forward, transfer of control of the human remains and associated funerary objects to The Affiliated Tribes may proceed.\\n        The University of Denver Museum of Anthropology is responsible for notifying The Consulted Tribes and The Affiliated Tribes that this notice has been published.\\n        \\n          Dated: April 4, 2019.\\n          Melanie O\\'Brien,\\n          Manager, National NAGPRA Program. \\n        \\n      \\n      [FR Doc. 2019-08741 Filed 4-29-19; 8:45 am]\\n       BILLING CODE 4312-52-P\\n    ", "agency1": "DEPARTMENT OF THE INTERIOR", "sub_agency1": "National Park Service", "dep_doc": "[NPS-WASO-NAGPRA-NPS0027628; PPWOCRADN0-PCU00RP14.R50000]", "subject": "Notice of Inventory Completion for Native American Human Remains and Associated Funerary Objects in the Possession of the University of Denver Department of Anthropology and Museum of Anthropology, Denver Colorado, CO; Correction; Correction", "agency2": "National Park Service, Interior.", "action": "Notice; correction.", "summary": "The University of Denver Museum of Anthropology has corrected an inventory of human remains and associated funerary objects, published in a Notice of Inventory Completion in the Federal Register on November 13, 2000. This notice corrects the cultural affiliation. Lineal descendants or representatives of any Indian Tribe or Native Hawaiian organization not identified in this notice that wish to request transfer of control of these human remains and associated funerary objects should submit a written request to the University of Denver Museum of Anthropology. If no additional requestors come forward, transfer of control of the human remains and associated funerary objects to the lineal descendants, Indian Tribes, or Native Hawaiian organizations stated in this notice may proceed.", "dates": "Lineal descendants or representatives of any Indian Tribe or Native Hawaiian organization not identified in this notice that wish to request transfer of control of these human remains and associated funerary objects should submit a written request with information in support of the request to the University of Denver Museum of Anthropology at the address in this notice by May 30, 2019.", "addresses": "Anne Amati, University of Denver Museum of Anthropology, 2000 East Asbury Avenue, Sturm Hall Room 146, Denver, CO 80208, telephone (303) 871-2687, email anne.amati@du.edu.\\n          ", "signature_dated": "Dated: April 4, 2019.", "signature_name": "Melanie O\\'Brien,", "signature_title": "Manager, National NAGPRA Program. ", "fr_doc": "[FR Doc. 2019-08741 Filed 4-29-19; 8:45 am]", "billing_code": " BILLING CODE 4312-52-P", "supp_info": "SUPPLEMENTARY INFORMATION: \n Notice is here given in accordance with the Native American Graves Protection and Repatriation Act (NAGPRA), 25 U.S.C. 3003, of the correction of an inventory of human remains and associated funerary objects under the control of the University of Denver Museum of Anthropology, Denver, CO. The human remains and associated funerary objects were removed from Pueblo Blanco, Santa Fe County, NM. \n This notice is published as part of the National Park Service\\'s administrative responsibilities under NAGPRA, 25 U.S.C. 3003(d)(3). The determinations in this notice are the sole responsibility of the museum, institution, or Federal agency that has control of the Native American human remains and associated funerary objects. The National Park Service is not responsible for the determinations in this notice. \n This notice corrects the cultural affiliation published in a Notice of Inventory Completion in the Federal Register (65 FR 67757-67758, November 13, 2000). This correction is being made following additional consultation that provided new evidence of cultural affiliation. Transfer of control of the items in this correction notice has not occurred. \n Correction \n In the Federal Register (65 FR 67757, November 13, 2000), column 3, paragraph 3, sentence 1 is corrected by substituting the following sentence: \n In the Federal Register (65 FR 67757, November 13, 2000), column 3, paragraph 5, sentences 1-4 are corrected by substituting the following sentences: \n In the Federal Register (65 FR 67758, November 13, 2000), column 1, paragraph 1, sentence 3 is corrected by substituting the following sentence: \n Additional Requestors and Disposition \n Lineal descendants or representatives of any Indian Tribe or Native Hawaiian organization not identified in this notice that wish to request transfer of control of these human remains and associated funerary objects should submit a written request with information in support of the request to Anne Amati, University of Denver Museum of Anthropology, 2000 E Asbury Avenue, Denver, CO 80208, telephone (303) 871-2687, email anne.amati@du.edu, by May 30, 2019. After that date, if no additional requestors have come forward, transfer of control of the human remains and associated funerary objects to The Affiliated Tribes may proceed. \n The University of Denver Museum of Anthropology is responsible for notifying The Consulted Tribes and The Affiliated Tribes that this notice has been published. \n ", "consultation": "Null", "h_d_r": "Null", "h_d_ci": "Null", "determinations": "Null", "a_r_d": "Lineal descendants or representatives of any Indian Tribe or Native Hawaiian organization not identified in this notice that wish to request transfer of control of these human remains and associated funerary objects should submit a written request with information in support of the request to Anne Amati, University of Denver Museum of Anthropology, 2000 E Asbury Avenue, Denver, CO 80208, telephone (303) 871-2687, email anne.amati@du.edu, by May 30, 2019. After that date, if no additional requestors have come forward, transfer of control of the human remains and associated funerary objects to The Affiliated Tribes may proceed. \n The University of Denver Museum of Anthropology is responsible for notifying The Consulted Tribes and The Affiliated Tribes that this notice has been published. \n "}