{"index": "I_997", "messy_full": "\\n      \\n        DEPARTMENT OF THE INTERIOR\\n        National Park Service\\n        [NPS-WASO-NAGPRA-11157; 2200-1100-665]\\n        Notice of Inventory Completion: U.S. Department of the Interior, National Park Service, Wupatki National Monument, Flagstaff, AZ\\n        \\n          AGENCY:\\n          National Park Service, Interior.\\n        \\n        \\n          ACTION:\\n          Notice.\\n        \\n        \\n          SUMMARY:\\n\\n          The U.S. Department of the Interior, National Park Service, Wupatki National Monument, has completed an inventory of human remains and associated funerary objects in consultation with the appropriate Indian tribes, and has determined that there is no cultural affiliation between the remains and any present-day tribe. Representatives of any Indian tribe that believes itself to be culturally affiliated with the human remains may contact Wupatki National Monument. Disposition of the human remains and associated funerary objects to the tribes stated below may occur if no additional requestors come forward.\\n        \\n        \\n          DATES:\\n          Representatives of any Indian tribe that believes it has a cultural affiliation with the human remains should contact Wupatki National Monument at the address below by October 29, 2012.\\n        \\n        \\n          ADDRESSES:\\n          Diane Chung, Superintendent, Wupatki National Monument, 6400 N. Hwy 89, Flagstaff, AZ 86004, telephone (928) 526-1157 ext. 227.\\n        \\n      \\n      \\n        SUPPLEMENTARY INFORMATION:\\n        Notice is here given in accordance with the Native American Graves Protection and Repatriation Act (NAGPRA), 25 U.S.C. 3003, of the completion of an inventory of human remains and associated funerary objects in the possession of Wupatki National Monument, Flagstaff, AZ. The human remains and associated funerary objects were removed from within the boundaries of Wupatki National Monument in Coconino County, AZ.\\n        This notice is published as part of the National Park Service\\'s administrative responsibilities under NAGPRA, 25 U.S.C. 3003(d)(3) and 43 CFR 10.11(d). The determinations in this notice are the sole responsibility of the Superintendent, Wupatki National Monument.\\n        Consultation\\n        A detailed assessment of the human remains was made by Wupatki National Monument professional staff in consultation with representatives of the Fort McDowell Yavapai Nation, Arizona; Havasupai Tribe of the Havasupai Reservation, Arizona; Hopi Tribe of Arizona; Hualapai Indian Tribe of the Hualapai Indian Reservation, Arizona; Jicarilla Apache Nation, New Mexico; Kaibab Band of Paiute Indians of the Kaibab Indian Reservation, Arizona; Kewa Pueblo, New Mexico (formerly the Pueblo of Santo Domingo); Mescalero Apache Tribe of the Mescalero Reservation, New Mexico; Navajo Nation, Arizona, New Mexico & Utah; Ohkay Owingeh, New Mexico (formerly the Pueblo of San Juan); Pueblo of Acoma, New Mexico; Pueblo of Cochiti, New Mexico; Pueblo of Isleta, New Mexico; Pueblo of Jemez, New Mexico; Pueblo of Laguna, New Mexico; Pueblo of Nambe, New Mexico; Pueblo of Picuris, New Mexico; Pueblo of Pojoaque, New Mexico; Pueblo of San Ildefonso, New Mexico; Pueblo of Sandia, New Mexico; Pueblo of Santa Ana, New Mexico; Pueblo of Santa Clara, New Mexico; Pueblo of Taos, New Mexico; Pueblo of Tesuque, New Mexico; Pueblo of Zia, New Mexico; San Carlos Apache Tribe of the San Carlos Reservation, Arizona; San Juan Southern Paiute Tribe of Arizona; Tonto Apache Tribe of Arizona; White Mountain Apache Tribe of the Fort Apache Reservation, Arizona; Yavapai-Apache Nation of the Camp Verde Indian Reservation, Arizona; Yavapai-Prescott Tribe of the Yavapai Reservation, Arizona; Ysleta del Sur Pueblo of Texas; and Zuni Tribe of the Zuni Reservation, New Mexico. The Pueblo of San Felipe, New Mexico, was contacted, but did not have an internal process to address the issue of repatriation. Hereafter, all tribes listed above are referred to as \\xe2\\x80\\x9cThe Tribes.\\xe2\\x80\\x9d\\n        History and Description of the Remains\\n        In 1956, human remains representing a minimum of one individual were removed from NA404 in Coconino County, AZ, during a stabilization inventory conducted prior to the construction of the Sunset Crater-Wupatki loop road. No known individuals were identified. No associated funerary objects are present.\\n        In 1963, human remains representing a minimum of one individual were removed from NA2222 in Coconino County, AZ, by a National Park Service archeologist in an authorized emergency excavation. The site is a 30-room pueblo dated to A.D. 700-1200. No known individuals were identified. The 11 associated funerary objects are 2 Sunset Red bowls, 1 Dogozshi Black-on-White jar, 1 redware sherd, 2 Medicine Black-on-Red sherds, 4 turquoise beads, and 1 fragment of juniper bark matting.\\n        In 1982, human remains representing a minimum of one individual were removed from NA2222 in Coconino County, AZ, by a National Park Service archeologist in an authorized emergency excavation. No known individuals were identified. The 11 associated funerary objects are sherds.\\n        In 1989, human remains representing a minimum of two individuals were removed from NA1755 in Coconino County, AZ, during an authorized field school led by Northern Arizona University. No known individuals were identified. No associated funerary objects are present.\\n        At an unknown date, human remains representing a minimum of one individual were removed from an unknown location within the boundaries of Wupatki National Monument, Coconino County, AZ. No known individuals were identified. The four associated funerary objects are three black on white sherds and one unworked stone.\\n        Wupatki National Monument has determined that there is not sufficient evidence to support a cultural affiliation determination for the human remains described above.\\n        Determinations Made by Wupatki National Monument\\n        Officials of Wupatki National Monument have determined that:\\n        \\xe2\\x80\\xa2 Based on osteological analysis, the human remains are Native American.\\n        \\xe2\\x80\\xa2 Pursuant to 25 U.S.C. 3001(2), a relationship of shared group identity cannot be reasonably traced between the Native American human remains and any present-day Indian tribe.\\n        \\xe2\\x80\\xa2 According to final judgments of the Indian Claims Commission, the land from which the Native American human remains and associated funerary objects were removed is the aboriginal land of the Fort McDowell Yavapai Nation, Arizona; Havasupai Tribe of the Havasupai Reservation, Arizona; Hopi Tribe of Arizona; Hualapai Indian Tribe of the Hualapai Indian Reservation, Arizona; Kaibab Band of Paiute Indians of the Kaibab Indian Reservation, Arizona; Navajo Nation, Arizona, New Mexico & Utah; San Carlos Apache Tribe of the San Carlos Reservation, Arizona; San Juan Southern Paiute Tribe of Arizona; Tonto Apache Tribe of Arizona; White Mountain Apache Tribe of the Fort Apache Reservation, Arizona; Yavapai-Apache Nation of the Camp Verde Indian Reservation, Arizona; and Yavapai-Prescott Tribe of the Yavapai Reservation, Arizona.\\n        \\xe2\\x80\\xa2 Multiple lines of evidence, including treaties, Acts of Congress, and Executive Orders, indicate that the land from which the Native American human remains and associated funerary objects were removed is the aboriginal land of the Havasupai Tribe of the Havasupai Reservation, Arizona; Hopi Tribe of Arizona; Hualapai Indian Tribe of the Hualapai Indian Reservation, Arizona; Jicarilla Apache Nation, New Mexico; Kaibab Band of Paiute Indians of the Kaibab Indian Reservation, Arizona; Mescalero Apache Tribe of the Mescalero Reservation, New Mexico; Navajo Nation, Arizona, New Mexico & Utah; San Carlos Apache Tribe of the San Carlos Reservation, Arizona; San Juan Southern Paiute Tribe of Arizona; Tonto Apache Tribe of Arizona; and White Mountain Apache Tribe of the Fort Apache Reservation, Arizona.\\n\\n        \\xe2\\x80\\xa2 Other credible lines of evidence, including consultation with tribal representatives, indicate that the land from which the Native American human remains and associated funerary objects were removed is the aboriginal land of the Zuni Tribe of the Zuni Reservation, New Mexico.\\n        \\xe2\\x80\\xa2 Pursuant to 25 U.S.C. 3001(9), the human remains described in this notice represent the physical remains of six individuals of Native American ancestry.\\n        \\xe2\\x80\\xa2 Pursuant to 25 U.S.C. 3001(3)(A), the 26 objects described above are reasonably believed to have been placed with or near individual human remains at the time of death or later as part of the death rite or ceremony. The National Park Service intends to convey the associated funerary object to the tribes pursuant to 16 U.S.C. 18f-2.\\n        \\xe2\\x80\\xa2 Pursuant to 43 CFR 10.11(c)(1), the disposition of the human remains may be to the Fort McDowell Yavapai Nation, Arizona; Havasupai Tribe of the Havasupai Reservation, Arizona; Hopi Tribe of Arizona; Hualapai Indian Tribe of the Hualapai Indian Reservation, Arizona; Jicarilla Apache Nation, New Mexico; Kaibab Band of Paiute Indians of the Kaibab Indian Reservation, Arizona; Mescalero Apache Tribe of the Mescalero Reservation, New Mexico; Navajo Nation, Arizona, New Mexico & Utah; San Carlos Apache Tribe of the San Carlos Reservation, Arizona; San Juan Southern Paiute Tribe of Arizona; Tonto Apache Tribe of Arizona; White Mountain Apache Tribe of the Fort Apache Reservation, Arizona; Yavapai-Apache Nation of the Camp Verde Indian Reservation, Arizona; Yavapai-Prescott Tribe of the Yavapai Reservation, Arizona; and Zuni Tribe of the Zuni Reservation, New Mexico.\\n        Additional Requestors and Disposition\\n        Representatives of any Indian tribe that believes itself to be culturally affiliated with the human remains or any other Indian tribe that believes it satisfies the criteria in 43 CFR 10.11(c)(1) should contact Diane Chung, Superintendent, Wupatki National Monument, 6400 N. Hwy 89, Flagstaff, AZ 86004, telephone (928) 526-1157 ext. 227, before October 29, 2012. Disposition of the human remains to the Fort McDowell Yavapai Nation, Arizona; Havasupai Tribe of the Havasupai Reservation, Arizona; Hopi Tribe of Arizona; Hualapai Indian Tribe of the Hualapai Indian Reservation, Arizona; Jicarilla Apache Nation, New Mexico; Kaibab Band of Paiute Indians of the Kaibab Indian Reservation, Arizona; Mescalero Apache Tribe of the Mescalero Reservation, New Mexico; Navajo Nation, Arizona, New Mexico & Utah; San Carlos Apache Tribe of the San Carlos Reservation, Arizona; San Juan Southern Paiute Tribe of Arizona; Tonto Apache Tribe of Arizona; White Mountain Apache Tribe of the Fort Apache Reservation, Arizona; Yavapai-Apache Nation of the Camp Verde Indian Reservation, Arizona; Yavapai-Prescott Tribe of the Yavapai Reservation, Arizona; and Zuni Tribe of the Zuni Reservation, New Mexico, may proceed after that date if no additional requestors come forward.\\n        Wupatki National Monument is responsible for notifying The Tribes that this notice has been published.\\n        \\n          Dated: August 24, 2012.\\n          Melanie O\\'Brien,\\n          Acting Manager, National NAGPRA Program.\\n        \\n      \\n      [FR Doc. 2012-23906 Filed 9-27-12; 8:45 am]\\n      BILLING CODE 4312-50-P\\n    ", "agency1": "DEPARTMENT OF THE INTERIOR", "sub_agency1": "National Park Service", "dep_doc": "[NPS-WASO-NAGPRA-11157; 2200-1100-665]", "subject": "Notice of Inventory Completion: U.S. Department of the Interior, National Park Service, Wupatki National Monument, Flagstaff, AZ", "agency2": "National Park Service, Interior.", "action": "Notice.", "summary": "The U.S. Department of the Interior, National Park Service, Wupatki National Monument, has completed an inventory of human remains and associated funerary objects in consultation with the appropriate Indian tribes, and has determined that there is no cultural affiliation between the remains and any present-day tribe. Representatives of any Indian tribe that believes itself to be culturally affiliated with the human remains may contact Wupatki National Monument. Disposition of the human remains and associated funerary objects to the tribes stated below may occur if no additional requestors come forward.", "dates": "Representatives of any Indian tribe that believes it has a cultural affiliation with the human remains should contact Wupatki National Monument at the address below by October 29, 2012.", "addresses": "Diane Chung, Superintendent, Wupatki National Monument, 6400 N. Hwy 89, Flagstaff, AZ 86004, telephone (928) 526-1157 ext. 227.", "signature_dated": "Dated: August 24, 2012.", "signature_name": "Melanie O\\'Brien,", "signature_title": "Acting Manager, National NAGPRA Program.", "fr_doc": "[FR Doc. 2012-23906 Filed 9-27-12; 8:45 am]", "billing_code": "BILLING CODE 4312-50-P", "supp_info": "SUPPLEMENTARY INFORMATION: \n Notice is here given in accordance with the Native American Graves Protection and Repatriation Act (NAGPRA), 25 U.S.C. 3003, of the completion of an inventory of human remains and associated funerary objects in the possession of Wupatki National Monument, Flagstaff, AZ. The human remains and associated funerary objects were removed from within the boundaries of Wupatki National Monument in Coconino County, AZ. \n This notice is published as part of the National Park Service\\'s administrative responsibilities under NAGPRA, 25 U.S.C. 3003(d)(3) and 43 CFR 10.11(d). The determinations in this notice are the sole responsibility of the Superintendent, Wupatki National Monument. \n Consultation \n A detailed assessment of the human remains was made by Wupatki National Monument professional staff in consultation with representatives of the Fort McDowell Yavapai Nation, Arizona; Havasupai Tribe of the Havasupai Reservation, Arizona; Hopi Tribe of Arizona; Hualapai Indian Tribe of the Hualapai Indian Reservation, Arizona; Jicarilla Apache Nation, New Mexico; Kaibab Band of Paiute Indians of the Kaibab Indian Reservation, Arizona; Kewa Pueblo, New Mexico (formerly the Pueblo of Santo Domingo); Mescalero Apache Tribe of the Mescalero Reservation, New Mexico; Navajo Nation, Arizona, New Mexico & Utah; Ohkay Owingeh, New Mexico (formerly the Pueblo of San Juan); Pueblo of Acoma, New Mexico; Pueblo of Cochiti, New Mexico; Pueblo of Isleta, New Mexico; Pueblo of Jemez, New Mexico; Pueblo of Laguna, New Mexico; Pueblo of Nambe, New Mexico; Pueblo of Picuris, New Mexico; Pueblo of Pojoaque, New Mexico; Pueblo of San Ildefonso, New Mexico; Pueblo of Sandia, New Mexico; Pueblo of Santa Ana, New Mexico; Pueblo of Santa Clara, New Mexico; Pueblo of Taos, New Mexico; Pueblo of Tesuque, New Mexico; Pueblo of Zia, New Mexico; San Carlos Apache Tribe of the San Carlos Reservation, Arizona; San Juan Southern Paiute Tribe of Arizona; Tonto Apache Tribe of Arizona; White Mountain Apache Tribe of the Fort Apache Reservation, Arizona; Yavapai-Apache Nation of the Camp Verde Indian Reservation, Arizona; Yavapai-Prescott Tribe of the Yavapai Reservation, Arizona; Ysleta del Sur Pueblo of Texas; and Zuni Tribe of the Zuni Reservation, New Mexico. The Pueblo of San Felipe, New Mexico, was contacted, but did not have an internal process to address the issue of repatriation. Hereafter, all tribes listed above are referred to as \\xe2\\x80\\x9cThe Tribes.\\xe2\\x80\\x9d \n History and Description of the Remains \n In 1956, human remains representing a minimum of one individual were removed from NA404 in Coconino County, AZ, during a stabilization inventory conducted prior to the construction of the Sunset Crater-Wupatki loop road. No known individuals were identified. No associated funerary objects are present. \n In 1963, human remains representing a minimum of one individual were removed from NA2222 in Coconino County, AZ, by a National Park Service archeologist in an authorized emergency excavation. The site is a 30-room pueblo dated to A.D. 700-1200. No known individuals were identified. The 11 associated funerary objects are 2 Sunset Red bowls, 1 Dogozshi Black-on-White jar, 1 redware sherd, 2 Medicine Black-on-Red sherds, 4 turquoise beads, and 1 fragment of juniper bark matting. \n In 1982, human remains representing a minimum of one individual were removed from NA2222 in Coconino County, AZ, by a National Park Service archeologist in an authorized emergency excavation. No known individuals were identified. The 11 associated funerary objects are sherds. \n In 1989, human remains representing a minimum of two individuals were removed from NA1755 in Coconino County, AZ, during an authorized field school led by Northern Arizona University. No known individuals were identified. No associated funerary objects are present. \n At an unknown date, human remains representing a minimum of one individual were removed from an unknown location within the boundaries of Wupatki National Monument, Coconino County, AZ. No known individuals were identified. The four associated funerary objects are three black on white sherds and one unworked stone. \n Wupatki National Monument has determined that there is not sufficient evidence to support a cultural affiliation determination for the human remains described above. \n Determinations Made by Wupatki National Monument \n Officials of Wupatki National Monument have determined that: \n \\xe2\\x80\\xa2 Based on osteological analysis, the human remains are Native American. \n \\xe2\\x80\\xa2 Pursuant to 25 U.S.C. 3001(2), a relationship of shared group identity cannot be reasonably traced between the Native American human remains and any present-day Indian tribe. \n \\xe2\\x80\\xa2 According to final judgments of the Indian Claims Commission, the land from which the Native American human remains and associated funerary objects were removed is the aboriginal land of the Fort McDowell Yavapai Nation, Arizona; Havasupai Tribe of the Havasupai Reservation, Arizona; Hopi Tribe of Arizona; Hualapai Indian Tribe of the Hualapai Indian Reservation, Arizona; Kaibab Band of Paiute Indians of the Kaibab Indian Reservation, Arizona; Navajo Nation, Arizona, New Mexico & Utah; San Carlos Apache Tribe of the San Carlos Reservation, Arizona; San Juan Southern Paiute Tribe of Arizona; Tonto Apache Tribe of Arizona; White Mountain Apache Tribe of the Fort Apache Reservation, Arizona; Yavapai-Apache Nation of the Camp Verde Indian Reservation, Arizona; and Yavapai-Prescott Tribe of the Yavapai Reservation, Arizona. \n \\xe2\\x80\\xa2 Multiple lines of evidence, including treaties, Acts of Congress, and Executive Orders, indicate that the land from which the Native American human remains and associated funerary objects were removed is the aboriginal land of the Havasupai Tribe of the Havasupai Reservation, Arizona; Hopi Tribe of Arizona; Hualapai Indian Tribe of the Hualapai Indian Reservation, Arizona; Jicarilla Apache Nation, New Mexico; Kaibab Band of Paiute Indians of the Kaibab Indian Reservation, Arizona; Mescalero Apache Tribe of the Mescalero Reservation, New Mexico; Navajo Nation, Arizona, New Mexico & Utah; San Carlos Apache Tribe of the San Carlos Reservation, Arizona; San Juan Southern Paiute Tribe of Arizona; Tonto Apache Tribe of Arizona; and White Mountain Apache Tribe of the Fort Apache Reservation, Arizona. \n \\xe2\\x80\\xa2 Other credible lines of evidence, including consultation with tribal representatives, indicate that the land from which the Native American human remains and associated funerary objects were removed is the aboriginal land of the Zuni Tribe of the Zuni Reservation, New Mexico. \n \\xe2\\x80\\xa2 Pursuant to 25 U.S.C. 3001(9), the human remains described in this notice represent the physical remains of six individuals of Native American ancestry. \n \\xe2\\x80\\xa2 Pursuant to 25 U.S.C. 3001(3)(A), the 26 objects described above are reasonably believed to have been placed with or near individual human remains at the time of death or later as part of the death rite or ceremony. The National Park Service intends to convey the associated funerary object to the tribes pursuant to 16 U.S.C. 18f-2. \n \\xe2\\x80\\xa2 Pursuant to 43 CFR 10.11(c)(1), the disposition of the human remains may be to the Fort McDowell Yavapai Nation, Arizona; Havasupai Tribe of the Havasupai Reservation, Arizona; Hopi Tribe of Arizona; Hualapai Indian Tribe of the Hualapai Indian Reservation, Arizona; Jicarilla Apache Nation, New Mexico; Kaibab Band of Paiute Indians of the Kaibab Indian Reservation, Arizona; Mescalero Apache Tribe of the Mescalero Reservation, New Mexico; Navajo Nation, Arizona, New Mexico & Utah; San Carlos Apache Tribe of the San Carlos Reservation, Arizona; San Juan Southern Paiute Tribe of Arizona; Tonto Apache Tribe of Arizona; White Mountain Apache Tribe of the Fort Apache Reservation, Arizona; Yavapai-Apache Nation of the Camp Verde Indian Reservation, Arizona; Yavapai-Prescott Tribe of the Yavapai Reservation, Arizona; and Zuni Tribe of the Zuni Reservation, New Mexico. \n Additional Requestors and Disposition \n Representatives of any Indian tribe that believes itself to be culturally affiliated with the human remains or any other Indian tribe that believes it satisfies the criteria in 43 CFR 10.11(c)(1) should contact Diane Chung, Superintendent, Wupatki National Monument, 6400 N. Hwy 89, Flagstaff, AZ 86004, telephone (928) 526-1157 ext. 227, before October 29, 2012. Disposition of the human remains to the Fort McDowell Yavapai Nation, Arizona; Havasupai Tribe of the Havasupai Reservation, Arizona; Hopi Tribe of Arizona; Hualapai Indian Tribe of the Hualapai Indian Reservation, Arizona; Jicarilla Apache Nation, New Mexico; Kaibab Band of Paiute Indians of the Kaibab Indian Reservation, Arizona; Mescalero Apache Tribe of the Mescalero Reservation, New Mexico; Navajo Nation, Arizona, New Mexico & Utah; San Carlos Apache Tribe of the San Carlos Reservation, Arizona; San Juan Southern Paiute Tribe of Arizona; Tonto Apache Tribe of Arizona; White Mountain Apache Tribe of the Fort Apache Reservation, Arizona; Yavapai-Apache Nation of the Camp Verde Indian Reservation, Arizona; Yavapai-Prescott Tribe of the Yavapai Reservation, Arizona; and Zuni Tribe of the Zuni Reservation, New Mexico, may proceed after that date if no additional requestors come forward. \n Wupatki National Monument is responsible for notifying The Tribes that this notice has been published. \n ", "consultation": "A detailed assessment of the human remains was made by Wupatki National Monument professional staff in consultation with representatives of the Fort McDowell Yavapai Nation, Arizona; Havasupai Tribe of the Havasupai Reservation, Arizona; Hopi Tribe of Arizona; Hualapai Indian Tribe of the Hualapai Indian Reservation, Arizona; Jicarilla Apache Nation, New Mexico; Kaibab Band of Paiute Indians of the Kaibab Indian Reservation, Arizona; Kewa Pueblo, New Mexico (formerly the Pueblo of Santo Domingo); Mescalero Apache Tribe of the Mescalero Reservation, New Mexico; Navajo Nation, Arizona, New Mexico & Utah; Ohkay Owingeh, New Mexico (formerly the Pueblo of San Juan); Pueblo of Acoma, New Mexico; Pueblo of Cochiti, New Mexico; Pueblo of Isleta, New Mexico; Pueblo of Jemez, New Mexico; Pueblo of Laguna, New Mexico; Pueblo of Nambe, New Mexico; Pueblo of Picuris, New Mexico; Pueblo of Pojoaque, New Mexico; Pueblo of San Ildefonso, New Mexico; Pueblo of Sandia, New Mexico; Pueblo of Santa Ana, New Mexico; Pueblo of Santa Clara, New Mexico; Pueblo of Taos, New Mexico; Pueblo of Tesuque, New Mexico; Pueblo of Zia, New Mexico; San Carlos Apache Tribe of the San Carlos Reservation, Arizona; San Juan Southern Paiute Tribe of Arizona; Tonto Apache Tribe of Arizona; White Mountain Apache Tribe of the Fort Apache Reservation, Arizona; Yavapai-Apache Nation of the Camp Verde Indian Reservation, Arizona; Yavapai-Prescott Tribe of the Yavapai Reservation, Arizona; Ysleta del Sur Pueblo of Texas; and Zuni Tribe of the Zuni Reservation, New Mexico. The Pueblo of San Felipe, New Mexico, was contacted, but did not have an internal process to address the issue of repatriation. Hereafter, all tribes listed above are referred to as \\xe2\\x80\\x9cThe Tribes.\\xe2\\x80\\x9d \n ", "h_d_r": "In 1956, human remains representing a minimum of one individual were removed from NA404 in Coconino County, AZ, during a stabilization inventory conducted prior to the construction of the Sunset Crater-Wupatki loop road. No known individuals were identified. No associated funerary objects are present. \n In 1963, human remains representing a minimum of one individual were removed from NA2222 in Coconino County, AZ, by a National Park Service archeologist in an authorized emergency excavation. The site is a 30-room pueblo dated to A.D. 700-1200. No known individuals were identified. The 11 associated funerary objects are 2 Sunset Red bowls, 1 Dogozshi Black-on-White jar, 1 redware sherd, 2 Medicine Black-on-Red sherds, 4 turquoise beads, and 1 fragment of juniper bark matting. \n In 1982, human remains representing a minimum of one individual were removed from NA2222 in Coconino County, AZ, by a National Park Service archeologist in an authorized emergency excavation. No known individuals were identified. The 11 associated funerary objects are sherds. \n In 1989, human remains representing a minimum of two individuals were removed from NA1755 in Coconino County, AZ, during an authorized field school led by Northern Arizona University. No known individuals were identified. No associated funerary objects are present. \n At an unknown date, human remains representing a minimum of one individual were removed from an unknown location within the boundaries of Wupatki National Monument, Coconino County, AZ. No known individuals were identified. The four associated funerary objects are three black on white sherds and one unworked stone. \n Wupatki National Monument has determined that there is not sufficient evidence to support a cultural affiliation determination for the human remains described above. \n ", "h_d_ci": "Null", "determinations": "Determinations Made by Wupatki National Monument \n Officials of Wupatki National Monument have determined that: \n \\xe2\\x80\\xa2 Based on osteological analysis, the human remains are Native American. \n \\xe2\\x80\\xa2 Pursuant to 25 U.S.C. 3001(2), a relationship of shared group identity cannot be reasonably traced between the Native American human remains and any present-day Indian tribe. \n \\xe2\\x80\\xa2 According to final judgments of the Indian Claims Commission, the land from which the Native American human remains and associated funerary objects were removed is the aboriginal land of the Fort McDowell Yavapai Nation, Arizona; Havasupai Tribe of the Havasupai Reservation, Arizona; Hopi Tribe of Arizona; Hualapai Indian Tribe of the Hualapai Indian Reservation, Arizona; Kaibab Band of Paiute Indians of the Kaibab Indian Reservation, Arizona; Navajo Nation, Arizona, New Mexico & Utah; San Carlos Apache Tribe of the San Carlos Reservation, Arizona; San Juan Southern Paiute Tribe of Arizona; Tonto Apache Tribe of Arizona; White Mountain Apache Tribe of the Fort Apache Reservation, Arizona; Yavapai-Apache Nation of the Camp Verde Indian Reservation, Arizona; and Yavapai-Prescott Tribe of the Yavapai Reservation, Arizona. \n \\xe2\\x80\\xa2 Multiple lines of evidence, including treaties, Acts of Congress, and Executive Orders, indicate that the land from which the Native American human remains and associated funerary objects were removed is the aboriginal land of the Havasupai Tribe of the Havasupai Reservation, Arizona; Hopi Tribe of Arizona; Hualapai Indian Tribe of the Hualapai Indian Reservation, Arizona; Jicarilla Apache Nation, New Mexico; Kaibab Band of Paiute Indians of the Kaibab Indian Reservation, Arizona; Mescalero Apache Tribe of the Mescalero Reservation, New Mexico; Navajo Nation, Arizona, New Mexico & Utah; San Carlos Apache Tribe of the San Carlos Reservation, Arizona; San Juan Southern Paiute Tribe of Arizona; Tonto Apache Tribe of Arizona; and White Mountain Apache Tribe of the Fort Apache Reservation, Arizona. \n \\xe2\\x80\\xa2 Other credible lines of evidence, including consultation with tribal representatives, indicate that the land from which the Native American human remains and associated funerary objects were removed is the aboriginal land of the Zuni Tribe of the Zuni Reservation, New Mexico. \n \\xe2\\x80\\xa2 Pursuant to 25 U.S.C. 3001(9), the human remains described in this notice represent the physical remains of six individuals of Native American ancestry. \n \\xe2\\x80\\xa2 Pursuant to 25 U.S.C. 3001(3)(A), the 26 objects described above are reasonably believed to have been placed with or near individual human remains at the time of death or later as part of the death rite or ceremony. The National Park Service intends to convey the associated funerary object to the tribes pursuant to 16 U.S.C. 18f-2. \n \\xe2\\x80\\xa2 Pursuant to 43 CFR 10.11(c)(1), the disposition of the human remains may be to the Fort McDowell Yavapai Nation, Arizona; Havasupai Tribe of the Havasupai Reservation, Arizona; Hopi Tribe of Arizona; Hualapai Indian Tribe of the Hualapai Indian Reservation, Arizona; Jicarilla Apache Nation, New Mexico; Kaibab Band of Paiute Indians of the Kaibab Indian Reservation, Arizona; Mescalero Apache Tribe of the Mescalero Reservation, New Mexico; Navajo Nation, Arizona, New Mexico & Utah; San Carlos Apache Tribe of the San Carlos Reservation, Arizona; San Juan Southern Paiute Tribe of Arizona; Tonto Apache Tribe of Arizona; White Mountain Apache Tribe of the Fort Apache Reservation, Arizona; Yavapai-Apache Nation of the Camp Verde Indian Reservation, Arizona; Yavapai-Prescott Tribe of the Yavapai Reservation, Arizona; and Zuni Tribe of the Zuni Reservation, New Mexico. \n ", "a_r_d": "Representatives of any Indian tribe that believes itself to be culturally affiliated with the human remains or any other Indian tribe that believes it satisfies the criteria in 43 CFR 10.11(c)(1) should contact Diane Chung, Superintendent, Wupatki National Monument, 6400 N. Hwy 89, Flagstaff, AZ 86004, telephone (928) 526-1157 ext. 227, before October 29, 2012. Disposition of the human remains to the Fort McDowell Yavapai Nation, Arizona; Havasupai Tribe of the Havasupai Reservation, Arizona; Hopi Tribe of Arizona; Hualapai Indian Tribe of the Hualapai Indian Reservation, Arizona; Jicarilla Apache Nation, New Mexico; Kaibab Band of Paiute Indians of the Kaibab Indian Reservation, Arizona; Mescalero Apache Tribe of the Mescalero Reservation, New Mexico; Navajo Nation, Arizona, New Mexico & Utah; San Carlos Apache Tribe of the San Carlos Reservation, Arizona; San Juan Southern Paiute Tribe of Arizona; Tonto Apache Tribe of Arizona; White Mountain Apache Tribe of the Fort Apache Reservation, Arizona; Yavapai-Apache Nation of the Camp Verde Indian Reservation, Arizona; Yavapai-Prescott Tribe of the Yavapai Reservation, Arizona; and Zuni Tribe of the Zuni Reservation, New Mexico, may proceed after that date if no additional requestors come forward. \n Wupatki National Monument is responsible for notifying The Tribes that this notice has been published. \n "}