{"index": "I_994", "messy_full": "\\n      \\n        DEPARTMENT OF THE INTERIOR\\n        National Park Service\\n        [NPS-WASO-NAGPRA-11477; 2200-1100-665]\\n        Notice of Inventory Completion: Maxwell Museum of Anthropology, University of New Mexico, Albuquerque, NM\\n        \\n          AGENCY:\\n          National Park Service, Interior.\\n        \\n        \\n          ACTION:\\n          Notice.\\n        \\n        \\n          SUMMARY:\\n\\n          The Maxwell Museum\\'s Laboratory of Human Osteology has completed an inventory of human remains, in consultation with the appropriate Indian tribe, and has determined that there is a cultural affiliation between the human remains and a present-day Indian tribe. Representatives of any Indian tribe that believes itself to be culturally affiliated with the human remains may contact the Maxwell Museum of Anthropology. Repatriation of the human remains to the Indian tribe stated below may occur if no additional claimants come forward.\\n        \\n        \\n          DATES:\\n          Representatives of any Indian tribe that believes it has a cultural affiliation with the human remains should contact the Maxwell Museum at the address below by November 26, 2012.\\n        \\n        \\n          ADDRESSES:\\n          Dr. Heather Edgar, Maxwell Museum of Anthropology, MSC01 1050, University of New Mexico, Albuquerque, NM 87131-0001, telephone (505) 277-4415.\\n        \\n      \\n      \\n        SUPPLEMENTARY INFORMATION:\\n        Notice is here given in accordance with the Native American Graves Protection and Repatriation Act (NAGPRA), 25 U.S.C. 3003, of the completion of an inventory of human remains in the possession of the Maxwell Museum in Albuquerque, NM. The human remains were removed from Sandoval County, NM.\\n        This notice is published as part of the National Park Service\\'s administrative responsibilities under NAGPRA, 25 U.S.C. 3003(d)(3). The determinations in this notice are the sole responsibility of the museum, institution, or Federal agency that has control of the Native American human remains. The National Park Service is not responsible for the determinations in this notice.\\n        Consultation\\n        A detailed assessment of the human remains was made by the professional staff in the Maxwell Museum\\'s Laboratory of Human Osteology in consultation with representatives of the Pueblo of Jemez, New Mexico.\\n        History and Description of the Remains\\n        Between 1934 and 1935, human remains representing, at minimum, one individual were removed from the Jemez Cave site in Sandoval County, NM, by directors of the University of New Mexico Field School and eight laborers. The Museum of New Mexico, the School of American Research, and the University of New Mexico supported the project and the excavation. The human remains were accessioned by the Maxwell Museum in 1990. No known individuals were identified. No associated funerary objects are present.\\n        In the early 1900s, human remains representing, at minimum, seven individuals were removed from the Amoxiumqua site (LA 481), in Sandoval County, NM, during excavations by University of New Mexico field schools. The human remains were accessioned by the Maxwell Museum in 1973. No known individuals were identified. No associated funerary objects are present.\\n        Between 1939 and 1949, human remains representing, at minimum, 22 individuals were removed from the BJ 74 site (LA 38962), in Sandoval County, NM, during excavations by Paul Reiter and students from the University of New Mexico. The human remains were accessioned by the Maxwell Museum in 2006. No known individuals were identified. No associated funerary objects are present.\\n        The sites listed in this notice are Puebloan sites of the upper Jemez River drainage and are ancestral Jemez sites. Populations that inhabited these locations are linked by Native oral tradition, Euro-American records, and archaeological evidence to members of the present-day Pueblo of Jemez, New Mexico.\\n        Determinations Made by the Maxwell Museum\\n        Officials of the Maxwell Museum have determined that:\\n        \\xe2\\x80\\xa2 Pursuant to 25 U.S.C. 3001(9), the human remains described in this notice represent the physical remains of 30 individuals of Native American ancestry.\\n        \\xe2\\x80\\xa2 Pursuant to 25 U.S.C. 3001(2), there is a relationship of shared group identity that can be reasonably traced between the Native American human remains and the Pueblo of Jemez.\\n        Additional Requestors and Disposition\\n        Representatives of any Indian tribe that believes itself to be culturally affiliated with the human remains should contact Dr. Heather Edgar, Maxwell Museum of Anthropology, Albuquerque, NM 87131-0001, telephone (505) 277-4415 before November 26, 2012. Repatriation of the human remains to the Pueblo of Jemez, New Mexico, may proceed after that date if no additional claimants come forward.\\n        The Maxwell Museum is responsible for notifying the Pueblo of Jemez, New Mexico, that this notice has been published.\\n        \\n          Dated: October 10, 2012.\\n          Sherry Hutt,\\n          Manager, National NAGPRA Program. \\n        \\n      \\n      [FR Doc. 2012-26316 Filed 10-25-12; 8:45 am]\\n      BILLING CODE 4312-50-P\\n    ", "agency1": "DEPARTMENT OF THE INTERIOR", "sub_agency1": "National Park Service", "dep_doc": "[NPS-WASO-NAGPRA-11477; 2200-1100-665]", "subject": "Notice of Inventory Completion: Maxwell Museum of Anthropology, University of New Mexico, Albuquerque, NM", "agency2": "National Park Service, Interior.", "action": "Notice.", "summary": "The Maxwell Museum\\'s Laboratory of Human Osteology has completed an inventory of human remains, in consultation with the appropriate Indian tribe, and has determined that there is a cultural affiliation between the human remains and a present-day Indian tribe. Representatives of any Indian tribe that believes itself to be culturally affiliated with the human remains may contact the Maxwell Museum of Anthropology. Repatriation of the human remains to the Indian tribe stated below may occur if no additional claimants come forward.", "dates": "Representatives of any Indian tribe that believes it has a cultural affiliation with the human remains should contact the Maxwell Museum at the address below by November 26, 2012.", "addresses": "Dr. Heather Edgar, Maxwell Museum of Anthropology, MSC01 1050, University of New Mexico, Albuquerque, NM 87131-0001, telephone (505) 277-4415.", "signature_dated": "Dated: October 10, 2012.", "signature_name": "Sherry Hutt,", "signature_title": "Manager, National NAGPRA Program. ", "fr_doc": "[FR Doc. 2012-26316 Filed 10-25-12; 8:45 am]", "billing_code": "BILLING CODE 4312-50-P", "supp_info": "SUPPLEMENTARY INFORMATION: \n Notice is here given in accordance with the Native American Graves Protection and Repatriation Act (NAGPRA), 25 U.S.C. 3003, of the completion of an inventory of human remains in the possession of the Maxwell Museum in Albuquerque, NM. The human remains were removed from Sandoval County, NM. \n This notice is published as part of the National Park Service\\'s administrative responsibilities under NAGPRA, 25 U.S.C. 3003(d)(3). The determinations in this notice are the sole responsibility of the museum, institution, or Federal agency that has control of the Native American human remains. The National Park Service is not responsible for the determinations in this notice. \n Consultation \n A detailed assessment of the human remains was made by the professional staff in the Maxwell Museum\\'s Laboratory of Human Osteology in consultation with representatives of the Pueblo of Jemez, New Mexico. \n History and Description of the Remains \n Between 1934 and 1935, human remains representing, at minimum, one individual were removed from the Jemez Cave site in Sandoval County, NM, by directors of the University of New Mexico Field School and eight laborers. The Museum of New Mexico, the School of American Research, and the University of New Mexico supported the project and the excavation. The human remains were accessioned by the Maxwell Museum in 1990. No known individuals were identified. No associated funerary objects are present. \n In the early 1900s, human remains representing, at minimum, seven individuals were removed from the Amoxiumqua site (LA 481), in Sandoval County, NM, during excavations by University of New Mexico field schools. The human remains were accessioned by the Maxwell Museum in 1973. No known individuals were identified. No associated funerary objects are present. \n Between 1939 and 1949, human remains representing, at minimum, 22 individuals were removed from the BJ 74 site (LA 38962), in Sandoval County, NM, during excavations by Paul Reiter and students from the University of New Mexico. The human remains were accessioned by the Maxwell Museum in 2006. No known individuals were identified. No associated funerary objects are present. \n The sites listed in this notice are Puebloan sites of the upper Jemez River drainage and are ancestral Jemez sites. Populations that inhabited these locations are linked by Native oral tradition, Euro-American records, and archaeological evidence to members of the present-day Pueblo of Jemez, New Mexico. \n Determinations Made by the Maxwell Museum \n Officials of the Maxwell Museum have determined that: \n \\xe2\\x80\\xa2 Pursuant to 25 U.S.C. 3001(9), the human remains described in this notice represent the physical remains of 30 individuals of Native American ancestry. \n \\xe2\\x80\\xa2 Pursuant to 25 U.S.C. 3001(2), there is a relationship of shared group identity that can be reasonably traced between the Native American human remains and the Pueblo of Jemez. \n Additional Requestors and Disposition \n Representatives of any Indian tribe that believes itself to be culturally affiliated with the human remains should contact Dr. Heather Edgar, Maxwell Museum of Anthropology, Albuquerque, NM 87131-0001, telephone (505) 277-4415 before November 26, 2012. Repatriation of the human remains to the Pueblo of Jemez, New Mexico, may proceed after that date if no additional claimants come forward. \n The Maxwell Museum is responsible for notifying the Pueblo of Jemez, New Mexico, that this notice has been published. \n ", "consultation": "A detailed assessment of the human remains was made by the professional staff in the Maxwell Museum\\'s Laboratory of Human Osteology in consultation with representatives of the Pueblo of Jemez, New Mexico. \n ", "h_d_r": "Between 1934 and 1935, human remains representing, at minimum, one individual were removed from the Jemez Cave site in Sandoval County, NM, by directors of the University of New Mexico Field School and eight laborers. The Museum of New Mexico, the School of American Research, and the University of New Mexico supported the project and the excavation. The human remains were accessioned by the Maxwell Museum in 1990. No known individuals were identified. No associated funerary objects are present. \n In the early 1900s, human remains representing, at minimum, seven individuals were removed from the Amoxiumqua site (LA 481), in Sandoval County, NM, during excavations by University of New Mexico field schools. The human remains were accessioned by the Maxwell Museum in 1973. No known individuals were identified. No associated funerary objects are present. \n Between 1939 and 1949, human remains representing, at minimum, 22 individuals were removed from the BJ 74 site (LA 38962), in Sandoval County, NM, during excavations by Paul Reiter and students from the University of New Mexico. The human remains were accessioned by the Maxwell Museum in 2006. No known individuals were identified. No associated funerary objects are present. \n The sites listed in this notice are Puebloan sites of the upper Jemez River drainage and are ancestral Jemez sites. Populations that inhabited these locations are linked by Native oral tradition, Euro-American records, and archaeological evidence to members of the present-day Pueblo of Jemez, New Mexico. \n ", "h_d_ci": "Null", "determinations": "Determinations Made by the Maxwell Museum \n Officials of the Maxwell Museum have determined that: \n \\xe2\\x80\\xa2 Pursuant to 25 U.S.C. 3001(9), the human remains described in this notice represent the physical remains of 30 individuals of Native American ancestry. \n \\xe2\\x80\\xa2 Pursuant to 25 U.S.C. 3001(2), there is a relationship of shared group identity that can be reasonably traced between the Native American human remains and the Pueblo of Jemez. \n ", "a_r_d": "Representatives of any Indian tribe that believes itself to be culturally affiliated with the human remains should contact Dr. Heather Edgar, Maxwell Museum of Anthropology, Albuquerque, NM 87131-0001, telephone (505) 277-4415 before November 26, 2012. Repatriation of the human remains to the Pueblo of Jemez, New Mexico, may proceed after that date if no additional claimants come forward. \n The Maxwell Museum is responsible for notifying the Pueblo of Jemez, New Mexico, that this notice has been published. \n "}