{"index": "R_136", "messy_full": "\\n      \\n        DEPARTMENT OF THE INTERIOR\\n        National Park Service\\n        [NPS-WASO-NAGPRA-20039; PPWOCRADN0-PCU00RP14.R50000]\\n        Notice of Intent To Repatriate a Cultural Item: Binghamton University, State University of New York, Binghamton, NY\\n        \\n          AGENCY:\\n          National Park Service, Interior.\\n        \\n        \\n          ACTION:\\n          Notice.\\n        \\n        \\n          SUMMARY:\\n          Binghamton University, in consultation with the appropriate Indian tribes or Native Hawaiian organizations, has determined that the cultural item listed in this notice meets the definition of a sacred object. Lineal descendants or representatives of any Indian tribe or Native Hawaiian organization not identified in this notice that wish to claim these cultural items should submit a written request to Binghamton University. If no additional claimants come forward, transfer of control of the cultural items to the lineal descendants, Indian tribes, or Native Hawaiian organizations stated in this notice may proceed.\\n        \\n        \\n          DATES:\\n          Representatives of any Indian tribe that believes it has a cultural affiliation with the cultural item should contact Binghamton University at the address below by February 26, 2016.\\n        \\n        \\n          ADDRESSES:\\n          Nina M. Versaggi, Public Archaeology Facility, Binghamton University, Binghamton, NY 13902-6000, telephone (607) 777-4786.\\n        \\n      \\n      \\n        SUPPLEMENTARY INFORMATION:\\n        Notice is here given in accordance with the Native American Graves Protection and Repatriation Act (NAGPRA), 25 U.S.C. 3005, of the intent to repatriate a cultural item in the possession of Binghamton University that meets the definition of sacred object under 25 U.S.C. 3001.\\n        This notice is published as part of the National Park Service\\'s administrative responsibilities under NAGPRA, 25 U.S.C. 3003(d)(3). The determinations in this notice are the sole responsibility of the museum, institution, or Federal agency that has control of the Native American cultural item. The National Park Service is not responsible for the determinations in this notice.\\n        History and Description of the Cultural Item(s)\\n\\n        During the middle to late 1960s, the Anthropology Department at Binghamton University acquired a False Face mask made by an artist from the Six Nations, in Ontario, Canada. A typed index card accompanying the mask reads: \\xe2\\x80\\x9cBroken Nose, Seneca Nation, Snapping Turtle Clan, Six Nations Reservation\\xe2\\x80\\x94Ontario.\\xe2\\x80\\x9d The mask is carved wood with a black face with a red mouth, with a hole on one side (right side, facing out), and a pointed chin. The mask face has holes in the nose and metal eye inlays surrounding center eyeholes. The face is framed with yellow hair, and there are carved lines on the face.\\n        On March 11, 2003, Binghamton University hosted a consultation meeting for federally recognized tribes to review NAGPRA summaries as part of the process of determining cultural affiliation. A group of traditional representatives from the Cayuga Nation; Saint Regis Mohawk Tribe (previously listed as the St. Regis Band of Mohawk Indians of New York); Seneca Nation of Indians (previously listed as the Seneca Nation of New York); Tonawanda Band of Seneca (previously listed as the Tonawanda Band of Seneca Indians of New York); and the Tuscarora Nation, met privately after the open consultation. In January of 2013, letters were sent to Seneca representatives asking for comments or claims on the mask. On September 22, 2015, Scott Abrams, Acting Director of the Seneca Nation of Indians Tribal Historic Preservation Officer contacted Binghamton University and formally requested repatriation of the Seneca mask. Binghamton University asked other Seneca representatives if they agreed. No comments were received.\\n        Determinations Made by Binghamton University\\n        Officials of Binghamton University have determined that:\\n        \\xe2\\x80\\xa2 Pursuant to 25 U.S.C. 3001(3)(C), the one cultural item described above is a specific ceremonial object needed by traditional Native American religious leaders for the practice of traditional Native American religions by their present-day adherents.\\n        \\xe2\\x80\\xa2 Pursuant to 25 U.S.C. 3001(2), there is a relationship of shared group identity that can be reasonably traced between the sacred object and the Seneca Nation.\\n        Additional Requestors and Disposition\\n        Representatives of any other Indian tribe that believes itself to be culturally affiliated with the sacred object should contact Nina M. Versaggi, Public Archaeology Facility, Binghamton University, Binghamton, NY 13902-6000, telephone (607) 777-4786, before February 26, 2016. Repatriation of the sacred object to the Seneca Nation of Indians (previously listed as the Seneca Nation of New York) Tribal Historic Preservation Office may proceed after that date if no additional claimants come forward.\\n        Binghamton University is responsible for notifying the Cayuga Nation; Delaware Nation, Oklahoma; Delaware Tribe of Indians; Oneida Nation of New York; Oneida Tribe of Indians of Wisconsin; Onondaga Nation; Saint Regis Mohawk Tribe (previously listed as the St. Regis Band of Mohawk Indians of New York); Seneca Nation of Indians (previously listed as the Seneca Nation of New York); Seneca-Cayuga Tribe of Oklahoma; Stockbridge Munsee Community, Wisconsin; Tonawanda Band of Seneca (previously listed as the Tonawanda Band of Seneca Indians of New York); and Tuscarora Nation that this notice has been published.\\n        \\n          Dated: December 28, 2015.\\n          Melanie O\\'Brien,\\n          Manager, National NAGPRA Program. \\n        \\n      \\n      [FR Doc. 2016-01591 Filed 1-26-16; 8:45 am]\\n      BILLING CODE 4312-50-P\\n    ", "agency1": "DEPARTMENT OF THE INTERIOR", "sub_agency1": "National Park Service", "dep_doc": "[NPS-WASO-NAGPRA-20039; PPWOCRADN0-PCU00RP14.R50000]", "subject": "Notice of Intent To Repatriate a Cultural Item: Binghamton University, State University of New York, Binghamton, NY", "agency2": "National Park Service, Interior.", "action": "Notice.", "summary": "Binghamton University, in consultation with the appropriate Indian tribes or Native Hawaiian organizations, has determined that the cultural item listed in this notice meets the definition of a sacred object. Lineal descendants or representatives of any Indian tribe or Native Hawaiian organization not identified in this notice that wish to claim these cultural items should submit a written request to Binghamton University. If no additional claimants come forward, transfer of control of the cultural items to the lineal descendants, Indian tribes, or Native Hawaiian organizations stated in this notice may proceed.", "dates": "Representatives of any Indian tribe that believes it has a cultural affiliation with the cultural item should contact Binghamton University at the address below by February 26, 2016.", "addresses": "Nina M. Versaggi, Public Archaeology Facility, Binghamton University, Binghamton, NY 13902-6000, telephone (607) 777-4786.", "signature_dated": "Dated: December 28, 2015.", "signature_name": "Melanie O\\'Brien,", "signature_title": "Manager, National NAGPRA Program. ", "fr_doc": "[FR Doc. 2016-01591 Filed 1-26-16; 8:45 am]", "billing_code": "BILLING CODE 4312-50-P", "supp_info": "SUPPLEMENTARY INFORMATION: \n Notice is here given in accordance with the Native American Graves Protection and Repatriation Act (NAGPRA), 25 U.S.C. 3005, of the intent to repatriate a cultural item in the possession of Binghamton University that meets the definition of sacred object under 25 U.S.C. 3001. \n This notice is published as part of the National Park Service\\'s administrative responsibilities under NAGPRA, 25 U.S.C. 3003(d)(3). The determinations in this notice are the sole responsibility of the museum, institution, or Federal agency that has control of the Native American cultural item. The National Park Service is not responsible for the determinations in this notice. \n History and Description of the Cultural Item(s) \n During the middle to late 1960s, the Anthropology Department at Binghamton University acquired a False Face mask made by an artist from the Six Nations, in Ontario, Canada. A typed index card accompanying the mask reads: \\xe2\\x80\\x9cBroken Nose, Seneca Nation, Snapping Turtle Clan, Six Nations Reservation\\xe2\\x80\\x94Ontario.\\xe2\\x80\\x9d The mask is carved wood with a black face with a red mouth, with a hole on one side (right side, facing out), and a pointed chin. The mask face has holes in the nose and metal eye inlays surrounding center eyeholes. The face is framed with yellow hair, and there are carved lines on the face. \n On March 11, 2003, Binghamton University hosted a consultation meeting for federally recognized tribes to review NAGPRA summaries as part of the process of determining cultural affiliation. A group of traditional representatives from the Cayuga Nation; Saint Regis Mohawk Tribe (previously listed as the St. Regis Band of Mohawk Indians of New York); Seneca Nation of Indians (previously listed as the Seneca Nation of New York); Tonawanda Band of Seneca (previously listed as the Tonawanda Band of Seneca Indians of New York); and the Tuscarora Nation, met privately after the open consultation. In January of 2013, letters were sent to Seneca representatives asking for comments or claims on the mask. On September 22, 2015, Scott Abrams, Acting Director of the Seneca Nation of Indians Tribal Historic Preservation Officer contacted Binghamton University and formally requested repatriation of the Seneca mask. Binghamton University asked other Seneca representatives if they agreed. No comments were received. \n Determinations Made by Binghamton University \n Officials of Binghamton University have determined that: \n \\xe2\\x80\\xa2 Pursuant to 25 U.S.C. 3001(3)(C), the one cultural item described above is a specific ceremonial object needed by traditional Native American religious leaders for the practice of traditional Native American religions by their present-day adherents. \n \\xe2\\x80\\xa2 Pursuant to 25 U.S.C. 3001(2), there is a relationship of shared group identity that can be reasonably traced between the sacred object and the Seneca Nation. \n Additional Requestors and Disposition \n Representatives of any other Indian tribe that believes itself to be culturally affiliated with the sacred object should contact Nina M. Versaggi, Public Archaeology Facility, Binghamton University, Binghamton, NY 13902-6000, telephone (607) 777-4786, before February 26, 2016. Repatriation of the sacred object to the Seneca Nation of Indians (previously listed as the Seneca Nation of New York) Tribal Historic Preservation Office may proceed after that date if no additional claimants come forward. \n Binghamton University is responsible for notifying the Cayuga Nation; Delaware Nation, Oklahoma; Delaware Tribe of Indians; Oneida Nation of New York; Oneida Tribe of Indians of Wisconsin; Onondaga Nation; Saint Regis Mohawk Tribe (previously listed as the St. Regis Band of Mohawk Indians of New York); Seneca Nation of Indians (previously listed as the Seneca Nation of New York); Seneca-Cayuga Tribe of Oklahoma; Stockbridge Munsee Community, Wisconsin; Tonawanda Band of Seneca (previously listed as the Tonawanda Band of Seneca Indians of New York); and Tuscarora Nation that this notice has been published. \n ", "consultation": "Null", "h_d_r": "Null", "h_d_ci": "Null", "determinations": "Determinations Made by Binghamton University \n Officials of Binghamton University have determined that: \n \\xe2\\x80\\xa2 Pursuant to 25 U.S.C. 3001(3)(C), the one cultural item described above is a specific ceremonial object needed by traditional Native American religious leaders for the practice of traditional Native American religions by their present-day adherents. \n \\xe2\\x80\\xa2 Pursuant to 25 U.S.C. 3001(2), there is a relationship of shared group identity that can be reasonably traced between the sacred object and the Seneca Nation. \n ", "a_r_d": "Representatives of any other Indian tribe that believes itself to be culturally affiliated with the sacred object should contact Nina M. Versaggi, Public Archaeology Facility, Binghamton University, Binghamton, NY 13902-6000, telephone (607) 777-4786, before February 26, 2016. Repatriation of the sacred object to the Seneca Nation of Indians (previously listed as the Seneca Nation of New York) Tribal Historic Preservation Office may proceed after that date if no additional claimants come forward. \n Binghamton University is responsible for notifying the Cayuga Nation; Delaware Nation, Oklahoma; Delaware Tribe of Indians; Oneida Nation of New York; Oneida Tribe of Indians of Wisconsin; Onondaga Nation; Saint Regis Mohawk Tribe (previously listed as the St. Regis Band of Mohawk Indians of New York); Seneca Nation of Indians (previously listed as the Seneca Nation of New York); Seneca-Cayuga Tribe of Oklahoma; Stockbridge Munsee Community, Wisconsin; Tonawanda Band of Seneca (previously listed as the Tonawanda Band of Seneca Indians of New York); and Tuscarora Nation that this notice has been published. \n "}