{"index": "R_184", "messy_full": "\\n      \\n        \\n        DEPARTMENT OF THE INTERIOR\\n        National Park Service\\n        [NPS-WASO-NAGPRA-16410; PPWOCRADN0-PCU00RP14.R50000]\\n        Notice of Intent To Repatriate Cultural Items: Stephen F. Austin State University, Nacogdoches, TX\\n        \\n          AGENCY:\\n          National Park Service, Interior.\\n        \\n        \\n          ACTION:\\n          Notice.\\n        \\n        \\n          SUMMARY:\\n          The Stephen F. Austin State University, in consultation with the appropriate Indian tribes or Native Hawaiian organizations, has determined that the cultural items listed in this notice meet the definition of unassociated funerary objects. Lineal descendants or representatives of any Indian tribe or Native Hawaiian organization not identified in this notice that wish to claim these cultural items should submit a written request to the Stephen F. Austin State University. If no additional claimants come forward, transfer of control of the cultural items to the lineal descendants, Indian tribes, or Native Hawaiian organizations stated in this notice may proceed.\\n        \\n        \\n          DATES:\\n          Lineal descendants or representatives of any Indian tribe or Native Hawaiian organization not identified in this notice that wish to claim these cultural items should submit a written request with information in support of the claim to the Stephen F. Austin State University at the address in this notice by October 10, 2014.\\n        \\n        \\n          ADDRESSES:\\n          Dr. Jerry Williams, Stephen F. Austin State University, P.O. Box 13047, SFA Station, Nacogdoches, TX 75962, telephone (936) 468-2306.\\n        \\n      \\n      \\n        SUPPLEMENTARY INFORMATION:\\n        Notice is here given in accordance with the Native American Graves Protection and Repatriation Act (NAGPRA), 25 U.S.C. 3005, of the intent to repatriate cultural items under the control of the Stephen F. Austin University, Nacogdoches, TX, that meet the definition of unassociated funerary objects under 25 U.S.C. 3001.\\n        This notice is published as part of the National Park Service\\'s administrative responsibilities under NAGPRA, 25 U.S.C. 3003(d)(3). The determinations in this notice are the sole responsibility of the museum, institution, or Federal agency that has control of the Native American cultural items. The National Park Service is not responsible for the determinations in this notice.\\n        History and Description of the Cultural Item(s)\\n        The Robert L. Turner Jr. Collection contains unassociated funerary objects from twelve sites, all of which are from the Big Cypress Creek Basin except for the Cherokee County site, which is located in the Neches-Angelina River Basin. In 2012, Robert L. Turner Jr. donated unassociated funerary objects to the Stephen F. Austin University (SFA) Archaeological Laboratory. All of the items in this collection came from burial sites, in many cases numbered burials. The human remains from these burials are not present in the collection.\\n        In the late 1920s to early 1940s, 6 cultural items (Perttula et al. 2010a) were removed from the G.W. Rumsey site (41CP3) in Camp County, TX. The 6 unassociated funerary objects are three Ripley Engraved bowls, an incised jar, a plain carinated bowl, and an appliqu\\xc3\\xa9d-punctated jar.\\n        Between 1963 and 1967, 399 cultural items (Turner 1978:1) were removed from the Tuck Carpenter site (41CP5) in Camp County, TX. The 399 unassociated funerary objects are 81 vessels, 88 lithics, 2 pipes, 50 shell fragments, 15 animal bones, and 163 miscellaneous sherds.\\n        Between 1963 and 1967, 43 cultural items (Turner 1978:1) were removed from the Tuck Carpenter A site (41CP5), also known as the Wilkison site in Camp County, TX. The 43 unassociated funerary objects are 4 lithics, 6 animal bones, 31 miscellaneous sherds, and 2 other objects.\\n        In 1959, 532 cultural items (Perttula et al. 2010a) were removed from the Harold Williams site (41CP10) in Camp County, TX. The 532 unassociated funerary objects are 18 vessels, 1 lithic, 1 pipe, and 512 miscellaneous sherds.\\n        Between 1966 and 1984, 252 cultural items (Perttula 2010b) were removed from the Johns site (41CP12) in Camp County, TX. The 252 unassociated funerary objects are 62 vessels, 76 lithics, 2 animal bones, 111 miscellaneous sherds, and 1 other object.\\n        In 1958, 8 cultural items (Perttula et al. 2010a:10) were removed from the Graydon Adkins site #2 (41UR17) in Upshur County, TX. The 8 unassociated funerary objects are two bowls, one bottle, one plain carinated bowl, one engraved bowl, one engraved bottle, one punctuated jar, and one plain bowl.\\n        In 1958, 260 cultural items (Perttula et al. 2010a:8) were removed from the B.J. Horton site (41CP20) in Camp County, TX. The 260 unassociated funerary objects are 45 vessels, 53 lithics, and 162 miscellaneous sherds.\\n        Before 1978 (Perttula et al. 2010a:9) 114 cultural items were removed from the Cecil Guest site (41CP78) in Camp County, Texas. The 114 unassociated funerary objects are 19 vessels, 4 lithics, and 91 miscellaneous sherds.\\n        In 1986, 28 cultural items (Perttula et al. 2010a:9) were removed from the Lone Star Lake/Ellison Lake site (41MX65) in Morris County, TX. The 28 unassociated funerary objects are 28 vessels.\\n        In the 1950s, 72 cultural items (Perttula et al. 2010a:9) were removed from the Keith site (41TT11) in Titus County, TX. The 72 unassociated funerary objects are 10 vessels and 62 lithics.\\n        In 1959, 22 cultural items (Perttula et al. 2010a:10) were removed from the Alex Justiss site (41TT13) in Titus County, TX. The 22 unassociated funerary objects are 4 vessels, 17 lithics, and 1 pipe.\\n        In 1958, 3 cultural items (Perttula et al. 2010a:10) were removed from the Graydon Adkins site #1 (41UR21) in Upsur County, TX. The 3 unassociated funerary objects are 3 vessels.\\n        In 1930, 3 cultural items were removed from Cherokee County, TX. According to Robert L. Turner\\'s notes, the vessels from the unknown Cherokee County site originally came from the R.G. Upton Collection. They were found in about 1930 at the \\xe2\\x80\\x9cforks of Bowles and White Oak creeks\\xe2\\x80\\x9d in west central Cherokee County. The 3 unassociated funerary objects are 3 vessels.\\n        Determinations Made by the Stephen F. Austin University\\n\\n        Officials of the Stephen F. Austin University have determined that:\\n        \\n        \\xe2\\x80\\xa2 Pursuant to 25 U.S.C. 3001(3)(B), the 1,742 cultural items described above are reasonably believed to have been placed with or near individual human remains at the time of death or later as part of the death rite or ceremony and are believed, by a preponderance of the evidence, to have been removed from a specific burial site of a Native American individual.\\n        \\xe2\\x80\\xa2 Pursuant to 25 U.S.C. 3001(2), there is a relationship of shared group identity that can be reasonably traced between the unassociated funerary objects and Caddo Nation of Oklahoma.\\n        Additional Requestors and Disposition\\n\\n        Lineal descendants or representatives of any Indian tribe or Native Hawaiian organization not identified in this notice that wish to claim these cultural items should submit a written request with information in support of the claim to Dr. Jerry Williams, Stephen F. Austin State University, P.O. Box 13047, SFA Station, Nacogdoches, TX 75962, telephone (936) 468-2306, by October 10, 2014. After that date, if no additional claimants have come forward, transfer of control of the unassociated funerary objects to the Caddo Nation of Oklahoma may proceed.\\n        The Stephen F. Austin University is responsible for notifying the Caddo Nation of Oklahoma that this notice has been published.\\n        \\n          Dated: August 1, 2014.\\n          Melanie O\\'Brien,\\n          Acting Manager, National NAGPRA Program.\\n        \\n      \\n      [FR Doc. 2014-21483 Filed 9-9-14; 8:45 am]\\n      BILLING CODE 4312-50-P\\n    ", "agency1": "DEPARTMENT OF THE INTERIOR", "sub_agency1": "National Park Service", "dep_doc": "[NPS-WASO-NAGPRA-16410; PPWOCRADN0-PCU00RP14.R50000]", "subject": "Notice of Intent To Repatriate Cultural Items: Stephen F. Austin State University, Nacogdoches, TX", "agency2": "National Park Service, Interior.", "action": "Notice.", "summary": "The Stephen F. Austin State University, in consultation with the appropriate Indian tribes or Native Hawaiian organizations, has determined that the cultural items listed in this notice meet the definition of unassociated funerary objects. Lineal descendants or representatives of any Indian tribe or Native Hawaiian organization not identified in this notice that wish to claim these cultural items should submit a written request to the Stephen F. Austin State University. If no additional claimants come forward, transfer of control of the cultural items to the lineal descendants, Indian tribes, or Native Hawaiian organizations stated in this notice may proceed.", "dates": "Lineal descendants or representatives of any Indian tribe or Native Hawaiian organization not identified in this notice that wish to claim these cultural items should submit a written request with information in support of the claim to the Stephen F. Austin State University at the address in this notice by October 10, 2014.", "addresses": "Dr. Jerry Williams, Stephen F. Austin State University, P.O. Box 13047, SFA Station, Nacogdoches, TX 75962, telephone (936) 468-2306.", "signature_dated": "Dated: August 1, 2014.", "signature_name": "Melanie O\\'Brien,", "signature_title": "Acting Manager, National NAGPRA Program.", "fr_doc": "[FR Doc. 2014-21483 Filed 9-9-14; 8:45 am]", "billing_code": "BILLING CODE 4312-50-P", "supp_info": "SUPPLEMENTARY INFORMATION: \n Notice is here given in accordance with the Native American Graves Protection and Repatriation Act (NAGPRA), 25 U.S.C. 3005, of the intent to repatriate cultural items under the control of the Stephen F. Austin University, Nacogdoches, TX, that meet the definition of unassociated funerary objects under 25 U.S.C. 3001. \n This notice is published as part of the National Park Service\\'s administrative responsibilities under NAGPRA, 25 U.S.C. 3003(d)(3). The determinations in this notice are the sole responsibility of the museum, institution, or Federal agency that has control of the Native American cultural items. The National Park Service is not responsible for the determinations in this notice. \n History and Description of the Cultural Item(s) \n The Robert L. Turner Jr. Collection contains unassociated funerary objects from twelve sites, all of which are from the Big Cypress Creek Basin except for the Cherokee County site, which is located in the Neches-Angelina River Basin. In 2012, Robert L. Turner Jr. donated unassociated funerary objects to the Stephen F. Austin University (SFA) Archaeological Laboratory. All of the items in this collection came from burial sites, in many cases numbered burials. The human remains from these burials are not present in the collection. \n In the late 1920s to early 1940s, 6 cultural items (Perttula et al. 2010a) were removed from the G.W. Rumsey site (41CP3) in Camp County, TX. The 6 unassociated funerary objects are three Ripley Engraved bowls, an incised jar, a plain carinated bowl, and an appliqu\\xc3\\xa9d-punctated jar. \n Between 1963 and 1967, 399 cultural items (Turner 1978:1) were removed from the Tuck Carpenter site (41CP5) in Camp County, TX. The 399 unassociated funerary objects are 81 vessels, 88 lithics, 2 pipes, 50 shell fragments, 15 animal bones, and 163 miscellaneous sherds. \n Between 1963 and 1967, 43 cultural items (Turner 1978:1) were removed from the Tuck Carpenter A site (41CP5), also known as the Wilkison site in Camp County, TX. The 43 unassociated funerary objects are 4 lithics, 6 animal bones, 31 miscellaneous sherds, and 2 other objects. \n In 1959, 532 cultural items (Perttula et al. 2010a) were removed from the Harold Williams site (41CP10) in Camp County, TX. The 532 unassociated funerary objects are 18 vessels, 1 lithic, 1 pipe, and 512 miscellaneous sherds. \n Between 1966 and 1984, 252 cultural items (Perttula 2010b) were removed from the Johns site (41CP12) in Camp County, TX. The 252 unassociated funerary objects are 62 vessels, 76 lithics, 2 animal bones, 111 miscellaneous sherds, and 1 other object. \n In 1958, 8 cultural items (Perttula et al. 2010a:10) were removed from the Graydon Adkins site #2 (41UR17) in Upshur County, TX. The 8 unassociated funerary objects are two bowls, one bottle, one plain carinated bowl, one engraved bowl, one engraved bottle, one punctuated jar, and one plain bowl. \n In 1958, 260 cultural items (Perttula et al. 2010a:8) were removed from the B.J. Horton site (41CP20) in Camp County, TX. The 260 unassociated funerary objects are 45 vessels, 53 lithics, and 162 miscellaneous sherds. \n Before 1978 (Perttula et al. 2010a:9) 114 cultural items were removed from the Cecil Guest site (41CP78) in Camp County, Texas. The 114 unassociated funerary objects are 19 vessels, 4 lithics, and 91 miscellaneous sherds. \n In 1986, 28 cultural items (Perttula et al. 2010a:9) were removed from the Lone Star Lake/Ellison Lake site (41MX65) in Morris County, TX. The 28 unassociated funerary objects are 28 vessels. \n In the 1950s, 72 cultural items (Perttula et al. 2010a:9) were removed from the Keith site (41TT11) in Titus County, TX. The 72 unassociated funerary objects are 10 vessels and 62 lithics. \n In 1959, 22 cultural items (Perttula et al. 2010a:10) were removed from the Alex Justiss site (41TT13) in Titus County, TX. The 22 unassociated funerary objects are 4 vessels, 17 lithics, and 1 pipe. \n In 1958, 3 cultural items (Perttula et al. 2010a:10) were removed from the Graydon Adkins site #1 (41UR21) in Upsur County, TX. The 3 unassociated funerary objects are 3 vessels. \n In 1930, 3 cultural items were removed from Cherokee County, TX. According to Robert L. Turner\\'s notes, the vessels from the unknown Cherokee County site originally came from the R.G. Upton Collection. They were found in about 1930 at the \\xe2\\x80\\x9cforks of Bowles and White Oak creeks\\xe2\\x80\\x9d in west central Cherokee County. The 3 unassociated funerary objects are 3 vessels. \n Determinations Made by the Stephen F. Austin University \n Officials of the Stephen F. Austin University have determined that:\\n         \n \\xe2\\x80\\xa2 Pursuant to 25 U.S.C. 3001(3)(B), the 1,742 cultural items described above are reasonably believed to have been placed with or near individual human remains at the time of death or later as part of the death rite or ceremony and are believed, by a preponderance of the evidence, to have been removed from a specific burial site of a Native American individual. \n \\xe2\\x80\\xa2 Pursuant to 25 U.S.C. 3001(2), there is a relationship of shared group identity that can be reasonably traced between the unassociated funerary objects and Caddo Nation of Oklahoma. \n Additional Requestors and Disposition \n Lineal descendants or representatives of any Indian tribe or Native Hawaiian organization not identified in this notice that wish to claim these cultural items should submit a written request with information in support of the claim to Dr. Jerry Williams, Stephen F. Austin State University, P.O. Box 13047, SFA Station, Nacogdoches, TX 75962, telephone (936) 468-2306, by October 10, 2014. After that date, if no additional claimants have come forward, transfer of control of the unassociated funerary objects to the Caddo Nation of Oklahoma may proceed. \n The Stephen F. Austin University is responsible for notifying the Caddo Nation of Oklahoma that this notice has been published. \n ", "consultation": "Null", "h_d_r": "Null", "h_d_ci": "Null", "determinations": "Determinations Made by the Stephen F. Austin University \n Officials of the Stephen F. Austin University have determined that:\\n         \n \\xe2\\x80\\xa2 Pursuant to 25 U.S.C. 3001(3)(B), the 1,742 cultural items described above are reasonably believed to have been placed with or near individual human remains at the time of death or later as part of the death rite or ceremony and are believed, by a preponderance of the evidence, to have been removed from a specific burial site of a Native American individual. \n \\xe2\\x80\\xa2 Pursuant to 25 U.S.C. 3001(2), there is a relationship of shared group identity that can be reasonably traced between the unassociated funerary objects and Caddo Nation of Oklahoma. \n ", "a_r_d": "Lineal descendants or representatives of any Indian tribe or Native Hawaiian organization not identified in this notice that wish to claim these cultural items should submit a written request with information in support of the claim to Dr. Jerry Williams, Stephen F. Austin State University, P.O. Box 13047, SFA Station, Nacogdoches, TX 75962, telephone (936) 468-2306, by October 10, 2014. After that date, if no additional claimants have come forward, transfer of control of the unassociated funerary objects to the Caddo Nation of Oklahoma may proceed. \n The Stephen F. Austin University is responsible for notifying the Caddo Nation of Oklahoma that this notice has been published. \n "}