{"index": "R_187", "messy_full": "\\n      \\n        DEPARTMENT OF THE INTERIOR\\n        National Park Service\\n        [NPS-WASO-NAGPRA-16303; PPWOCRADN0-PCU00RP14.R50000]\\n        Notice of Intent To Repatriate Cultural Items: U.S. Department of Defense, Army, Fort Sill National Historic Landmark and Museum, Fort Sill, OK\\n        \\n          AGENCY:\\n          National Park Service, Interior.\\n        \\n        \\n          ACTION:\\n          Notice.\\n        \\n        \\n          SUMMARY:\\n          The Fort Sill National Historic Landmark and Museum, in consultation with the appropriate Indian tribes or Native Hawaiian organizations, has determined that the cultural items listed in this notice meet the definition of unassociated funerary objects. Lineal descendants or representatives of any Indian tribe or Native Hawaiian organization not identified in this notice that wish to claim these cultural items should submit a written request to the Fort Sill National Historic Landmark and Museum. If no additional claimants come forward, transfer of control of the cultural items to the lineal descendants, Indian tribes, or Native Hawaiian organizations stated in this notice may proceed.\\n        \\n        \\n          DATES:\\n          Lineal descendants or representatives of any Indian tribe or Native Hawaiian organization not identified in this notice that wish to claim these cultural items should submit a written request with information in support of the claim to the Fort Sill National Historic Landmark and Museum at the address in this notice by October 10, 2014.\\n        \\n        \\n          ADDRESSES:\\n\\n          Dr. Scott A. Neel, Director, Fort Sill National Historic Landmark and Museum, U.S. Army Fires Center of Excellence, Fort Sill, OK 73503, telephone (580) 442-6570, email scott.a.neel2.civ@mail.mil.\\n          \\n        \\n      \\n      \\n        SUPPLEMENTARY INFORMATION:\\n        Notice is here given in accordance with the Native American Graves Protection and Repatriation Act (NAGPRA), 25 U.S.C. 3005, of the intent to repatriate cultural items under the control of the Fort Sill National Historic Landmark and Museum that meet the definition of unassociated funerary objects under 25 U.S.C. 3001.\\n        This notice is published as part of the National Park Service\\'s administrative responsibilities under NAGPRA, 25 U.S.C. 3003(d)(3). The determinations in this notice are the sole responsibility of the museum, institution, or Federal agency that has control of the Native American cultural items. The National Park Service is not responsible for the determinations in this notice.\\n        History and Description of the Cultural Items\\n        In 1963, 85 cultural items were removed from the gravesite of Stumbling Bear who was interred at the Saddle Mountain KCA Intertribal Cemetery in Kiowa County, OK. The remains of Stumbling Bear were exhumed and moved to Chief\\'s Knoll at the Fort Sill Post Cemetery, but the cultural items were not reinterred with the human remains. It is unknown when the cultural items were given to the Fort Sill National Historic Landmark and Museum. Stumbling Bear was a Kiowa chief who was born in 1830 and died on March 14, 1903. The 85 unassociated funerary objects are 21 wire bracelets, 1 metal disk, 17 metal bells, 19 metal buttons, 4 metal rings, 1 metal chain, 3 plastic beads, 1 plastic button, 17 metal horse trappings, and 1 coffin hardware.\\n        Determinations Made by the Fort Sill National Historic Landmark and Museum\\n        Officials of the Fort Sill National Historic Landmark and Museum have determined that:\\n        \\xe2\\x80\\xa2 Pursuant to 25 U.S.C. 3001(3)(B), the 85 cultural items described in this notice are reasonably believed to have been placed with or near individual human remains at the time of death or later as part of the death rite or ceremony and are believed, by a preponderance of the evidence, to have been removed from a specific burial site of a Native American individual.\\n        \\xe2\\x80\\xa2 Pursuant to 25 U.S.C. 3001(2), there is a relationship of shared group identity that can be reasonably traced between the unassociated funerary objects and the Kiowa Indian Tribe of Oklahoma.\\n        Additional Requestors and Disposition\\n\\n        Lineal descendants or representatives of any Indian tribe or Native Hawaiian organization not identified in this notice that wish to claim these cultural items should submit a written request with information in support of the claim to Dr. Scott A. Neel, Director, Fort Sill National Historic Landmark and Museum, U.S. Army Fires Center of Excellence, Fort Sill, OK 73503, telephone (580) 442-6570, email scott.a.neel2.civ@mail.mil, by October 10, 2014. After that date, if no additional claimants have come forward, transfer of control of the unassociated funerary objects to the Kiowa Indian Tribe of Oklahoma may proceed.\\n        The Fort Sill National Historic Landmark and Museum is responsible for notifying the Kiowa Indian Tribe of Oklahoma that this notice has been published.\\n        \\n          Dated: July 17, 2014.\\n          Melanie O\\'Brien,\\n          Acting Manager, National NAGPRA Program. \\n        \\n      \\n      [FR Doc. 2014-21492 Filed 9-9-14; 8:45 am]\\n      BILLING CODE 4312-50-P\\n    ", "agency1": "DEPARTMENT OF THE INTERIOR", "sub_agency1": "National Park Service", "dep_doc": "[NPS-WASO-NAGPRA-16303; PPWOCRADN0-PCU00RP14.R50000]", "subject": "Notice of Intent To Repatriate Cultural Items: U.S. Department of Defense, Army, Fort Sill National Historic Landmark and Museum, Fort Sill, OK", "agency2": "National Park Service, Interior.", "action": "Notice.", "summary": "The Fort Sill National Historic Landmark and Museum, in consultation with the appropriate Indian tribes or Native Hawaiian organizations, has determined that the cultural items listed in this notice meet the definition of unassociated funerary objects. Lineal descendants or representatives of any Indian tribe or Native Hawaiian organization not identified in this notice that wish to claim these cultural items should submit a written request to the Fort Sill National Historic Landmark and Museum. If no additional claimants come forward, transfer of control of the cultural items to the lineal descendants, Indian tribes, or Native Hawaiian organizations stated in this notice may proceed.", "dates": "Lineal descendants or representatives of any Indian tribe or Native Hawaiian organization not identified in this notice that wish to claim these cultural items should submit a written request with information in support of the claim to the Fort Sill National Historic Landmark and Museum at the address in this notice by October 10, 2014.", "addresses": "Dr. Scott A. Neel, Director, Fort Sill National Historic Landmark and Museum, U.S. Army Fires Center of Excellence, Fort Sill, OK 73503, telephone (580) 442-6570, email scott.a.neel2.civ@mail.mil.\\n          ", "signature_dated": "Dated: July 17, 2014.", "signature_name": "Melanie O\\'Brien,", "signature_title": "Acting Manager, National NAGPRA Program. ", "fr_doc": "[FR Doc. 2014-21492 Filed 9-9-14; 8:45 am]", "billing_code": "BILLING CODE 4312-50-P", "supp_info": "SUPPLEMENTARY INFORMATION: \n Notice is here given in accordance with the Native American Graves Protection and Repatriation Act (NAGPRA), 25 U.S.C. 3005, of the intent to repatriate cultural items under the control of the Fort Sill National Historic Landmark and Museum that meet the definition of unassociated funerary objects under 25 U.S.C. 3001. \n This notice is published as part of the National Park Service\\'s administrative responsibilities under NAGPRA, 25 U.S.C. 3003(d)(3). The determinations in this notice are the sole responsibility of the museum, institution, or Federal agency that has control of the Native American cultural items. The National Park Service is not responsible for the determinations in this notice. \n History and Description of the Cultural Items \n In 1963, 85 cultural items were removed from the gravesite of Stumbling Bear who was interred at the Saddle Mountain KCA Intertribal Cemetery in Kiowa County, OK. The remains of Stumbling Bear were exhumed and moved to Chief\\'s Knoll at the Fort Sill Post Cemetery, but the cultural items were not reinterred with the human remains. It is unknown when the cultural items were given to the Fort Sill National Historic Landmark and Museum. Stumbling Bear was a Kiowa chief who was born in 1830 and died on March 14, 1903. The 85 unassociated funerary objects are 21 wire bracelets, 1 metal disk, 17 metal bells, 19 metal buttons, 4 metal rings, 1 metal chain, 3 plastic beads, 1 plastic button, 17 metal horse trappings, and 1 coffin hardware. \n Determinations Made by the Fort Sill National Historic Landmark and Museum \n Officials of the Fort Sill National Historic Landmark and Museum have determined that: \n \\xe2\\x80\\xa2 Pursuant to 25 U.S.C. 3001(3)(B), the 85 cultural items described in this notice are reasonably believed to have been placed with or near individual human remains at the time of death or later as part of the death rite or ceremony and are believed, by a preponderance of the evidence, to have been removed from a specific burial site of a Native American individual. \n \\xe2\\x80\\xa2 Pursuant to 25 U.S.C. 3001(2), there is a relationship of shared group identity that can be reasonably traced between the unassociated funerary objects and the Kiowa Indian Tribe of Oklahoma. \n Additional Requestors and Disposition \n Lineal descendants or representatives of any Indian tribe or Native Hawaiian organization not identified in this notice that wish to claim these cultural items should submit a written request with information in support of the claim to Dr. Scott A. Neel, Director, Fort Sill National Historic Landmark and Museum, U.S. Army Fires Center of Excellence, Fort Sill, OK 73503, telephone (580) 442-6570, email scott.a.neel2.civ@mail.mil, by October 10, 2014. After that date, if no additional claimants have come forward, transfer of control of the unassociated funerary objects to the Kiowa Indian Tribe of Oklahoma may proceed. \n The Fort Sill National Historic Landmark and Museum is responsible for notifying the Kiowa Indian Tribe of Oklahoma that this notice has been published. \n ", "consultation": "Null", "h_d_r": "Null", "h_d_ci": "In 1963, 85 cultural items were removed from the gravesite of Stumbling Bear who was interred at the Saddle Mountain KCA Intertribal Cemetery in Kiowa County, OK. The remains of Stumbling Bear were exhumed and moved to Chief\\'s Knoll at the Fort Sill Post Cemetery, but the cultural items were not reinterred with the human remains. It is unknown when the cultural items were given to the Fort Sill National Historic Landmark and Museum. Stumbling Bear was a Kiowa chief who was born in 1830 and died on March 14, 1903. The 85 unassociated funerary objects are 21 wire bracelets, 1 metal disk, 17 metal bells, 19 metal buttons, 4 metal rings, 1 metal chain, 3 plastic beads, 1 plastic button, 17 metal horse trappings, and 1 coffin hardware. \n ", "determinations": "Determinations Made by the Fort Sill National Historic Landmark and Museum \n Officials of the Fort Sill National Historic Landmark and Museum have determined that: \n \\xe2\\x80\\xa2 Pursuant to 25 U.S.C. 3001(3)(B), the 85 cultural items described in this notice are reasonably believed to have been placed with or near individual human remains at the time of death or later as part of the death rite or ceremony and are believed, by a preponderance of the evidence, to have been removed from a specific burial site of a Native American individual. \n \\xe2\\x80\\xa2 Pursuant to 25 U.S.C. 3001(2), there is a relationship of shared group identity that can be reasonably traced between the unassociated funerary objects and the Kiowa Indian Tribe of Oklahoma. \n ", "a_r_d": "Lineal descendants or representatives of any Indian tribe or Native Hawaiian organization not identified in this notice that wish to claim these cultural items should submit a written request with information in support of the claim to Dr. Scott A. Neel, Director, Fort Sill National Historic Landmark and Museum, U.S. Army Fires Center of Excellence, Fort Sill, OK 73503, telephone (580) 442-6570, email scott.a.neel2.civ@mail.mil, by October 10, 2014. After that date, if no additional claimants have come forward, transfer of control of the unassociated funerary objects to the Kiowa Indian Tribe of Oklahoma may proceed. \n The Fort Sill National Historic Landmark and Museum is responsible for notifying the Kiowa Indian Tribe of Oklahoma that this notice has been published. \n "}