{"index": "R_226", "messy_full": "\\n      \\n        DEPARTMENT OF THE INTERIOR\\n        National Park Service\\n        [NPS-WASO-NAGPRA-13278; PPWOCRADN0-PCU00RP14.R50000]\\n        Notice of Intent to Repatriate Cultural Item: Maxwell Museum of Anthropology, University of New Mexico, Albuquerque, NM\\n        \\n          AGENCY:\\n          National Park Service, Interior.\\n        \\n        \\n          ACTION:\\n          Notice.\\n        \\n        \\n          SUMMARY:\\n          The Maxwell Museum of Anthropology, in consultation with the appropriate Indian tribes or Native Hawaiian organizations, has determined that a cultural item listed in this notice meets the definition of sacred object. Lineal descendants or representatives of any Indian tribe or Native Hawaiian organization not identified in this notice that wish to claim this cultural item should submit a written request to the Maxwell Museum of Anthropology. If no additional claimants come forward, transfer of control of the cultural item to the lineal descendants, Indian tribes, or Native Hawaiian organizations stated in this notice may proceed.\\n        \\n        \\n          DATES:\\n          Lineal descendants or representatives of any Indian tribe or Native Hawaiian organization not identified in this notice that wish to claim this cultural item should submit a written request with information in support of the claim to the Maxwell Museum of Anthropology at the address in this notice by August 29, 2013.\\n        \\n        \\n          ADDRESSES:\\n          David Phillips, Curator of Archaeology, Maxwell Museum of Anthropology, MSC01 1050, University of New Mexico, Albuquerque, NM 87131, telephone (505) 277-9229.\\n        \\n      \\n      \\n        SUPPLEMENTARY INFORMATION:\\n        Notice is here given in accordance with the Native American Graves Protection and Repatriation Act (NAGPRA), 25 U.S.C. 3005, of the intent to repatriate a cultural item under the control of the Maxwell Museum of Anthropology, University of New Mexico, Albuquerque, NM, that meet the definition of sacred objects under 25 U.S.C. 3001.\\n        This notice is published as part of the National Park Service\\'s administrative responsibilities under NAGPRA, 25 U.S.C. 3003(d)(3). The determinations in this notice are the sole responsibility of the museum, institution, or Federal agency that has control of the Native American cultural item. The National Park Service is not responsible for the determinations in this notice.\\n        History and Description of the Cultural Item\\n        In 1970, a private collector donated a small collection of items to the Maxwell Museum of Anthropology, University of New Mexico. One item, catalogue number 70.77.8, is a ceremonial bandolier reported to be from the Kewa Pueblo, New Mexico (previously listed as the Pueblo of Santo Domingo), and possibly used as late as 1970. In 2013, a delegation from the Kewa Pueblo, New Mexico (previously listed as the Pueblo of Santo Domingo) inspected the bandolier, confirmed that it was a sacred object from their tribe, and requested its return.\\n        Determinations Made by the Maxwell Museum of Anthropology\\n        The Collections and Research Committee of the Maxwell Museum of Anthropology has determined that:\\n        \\xe2\\x80\\xa2 Pursuant to 25 U.S.C. 3001(3)(C), the cultural item described above is a specific ceremonial object needed by traditional Native American religious leaders for the practice of traditional Native American religions by their present-day adherents.\\n        \\xe2\\x80\\xa2 Pursuant to 25 U.S.C. 3001(2), there is a relationship of shared group identity that can be reasonably traced between the sacred object and the Kewa Pueblo, New Mexico (previously listed as the Pueblo of Santo Domingo).\\n        Additional Requestors and Disposition\\n\\n        Lineal descendants or representatives of any Indian tribe or Native Hawaiian organization not identified in this notice that wish to claim this cultural item should submit a written request with information in support of the claim to David Phillips, Curator of Archaeology, Maxwell Museum of Anthropology, MSC01 1050, University of New Mexico, Albuquerque NM 87131, telephone (505) 277-9229 by August 29, 2013. After that date, if no additional claimants have come forward, transfer of control of the sacred object to Kewa Pueblo, New Mexico (previously listed as the Pueblo of Santo Domingo) may proceed.\\n        The Maxwell Museum is responsible for notifying Kewa Pueblo, New Mexico (previously listed as the Pueblo of Santo Domingo) that this notice has been published.\\n        \\n          Dated: June 11, 2013.\\n          Sherry Hutt,\\n          Manager, National NAGPRA Program.\\n        \\n      \\n      [FR Doc. 2013-18279 Filed 7-29-13; 8:45 am]\\n      BILLING CODE 4312-50-P\\n    ", "agency1": "DEPARTMENT OF THE INTERIOR", "sub_agency1": "National Park Service", "dep_doc": "[NPS-WASO-NAGPRA-13278; PPWOCRADN0-PCU00RP14.R50000]", "subject": "Notice of Intent to Repatriate Cultural Item: Maxwell Museum of Anthropology, University of New Mexico, Albuquerque, NM", "agency2": "National Park Service, Interior.", "action": "Notice.", "summary": "The Maxwell Museum of Anthropology, in consultation with the appropriate Indian tribes or Native Hawaiian organizations, has determined that a cultural item listed in this notice meets the definition of sacred object. Lineal descendants or representatives of any Indian tribe or Native Hawaiian organization not identified in this notice that wish to claim this cultural item should submit a written request to the Maxwell Museum of Anthropology. If no additional claimants come forward, transfer of control of the cultural item to the lineal descendants, Indian tribes, or Native Hawaiian organizations stated in this notice may proceed.", "dates": "Lineal descendants or representatives of any Indian tribe or Native Hawaiian organization not identified in this notice that wish to claim this cultural item should submit a written request with information in support of the claim to the Maxwell Museum of Anthropology at the address in this notice by August 29, 2013.", "addresses": "David Phillips, Curator of Archaeology, Maxwell Museum of Anthropology, MSC01 1050, University of New Mexico, Albuquerque, NM 87131, telephone (505) 277-9229.", "signature_dated": "Dated: June 11, 2013.", "signature_name": "Sherry Hutt,", "signature_title": "Manager, National NAGPRA Program.", "fr_doc": "[FR Doc. 2013-18279 Filed 7-29-13; 8:45 am]", "billing_code": "BILLING CODE 4312-50-P", "supp_info": "SUPPLEMENTARY INFORMATION: \n Notice is here given in accordance with the Native American Graves Protection and Repatriation Act (NAGPRA), 25 U.S.C. 3005, of the intent to repatriate a cultural item under the control of the Maxwell Museum of Anthropology, University of New Mexico, Albuquerque, NM, that meet the definition of sacred objects under 25 U.S.C. 3001. \n This notice is published as part of the National Park Service\\'s administrative responsibilities under NAGPRA, 25 U.S.C. 3003(d)(3). The determinations in this notice are the sole responsibility of the museum, institution, or Federal agency that has control of the Native American cultural item. The National Park Service is not responsible for the determinations in this notice. \n History and Description of the Cultural Item \n In 1970, a private collector donated a small collection of items to the Maxwell Museum of Anthropology, University of New Mexico. One item, catalogue number 70.77.8, is a ceremonial bandolier reported to be from the Kewa Pueblo, New Mexico (previously listed as the Pueblo of Santo Domingo), and possibly used as late as 1970. In 2013, a delegation from the Kewa Pueblo, New Mexico (previously listed as the Pueblo of Santo Domingo) inspected the bandolier, confirmed that it was a sacred object from their tribe, and requested its return. \n Determinations Made by the Maxwell Museum of Anthropology \n The Collections and Research Committee of the Maxwell Museum of Anthropology has determined that: \n \\xe2\\x80\\xa2 Pursuant to 25 U.S.C. 3001(3)(C), the cultural item described above is a specific ceremonial object needed by traditional Native American religious leaders for the practice of traditional Native American religions by their present-day adherents. \n \\xe2\\x80\\xa2 Pursuant to 25 U.S.C. 3001(2), there is a relationship of shared group identity that can be reasonably traced between the sacred object and the Kewa Pueblo, New Mexico (previously listed as the Pueblo of Santo Domingo). \n Additional Requestors and Disposition \n Lineal descendants or representatives of any Indian tribe or Native Hawaiian organization not identified in this notice that wish to claim this cultural item should submit a written request with information in support of the claim to David Phillips, Curator of Archaeology, Maxwell Museum of Anthropology, MSC01 1050, University of New Mexico, Albuquerque NM 87131, telephone (505) 277-9229 by August 29, 2013. After that date, if no additional claimants have come forward, transfer of control of the sacred object to Kewa Pueblo, New Mexico (previously listed as the Pueblo of Santo Domingo) may proceed. \n The Maxwell Museum is responsible for notifying Kewa Pueblo, New Mexico (previously listed as the Pueblo of Santo Domingo) that this notice has been published. \n ", "consultation": "Null", "h_d_r": "Null", "h_d_ci": "Null", "determinations": "Determinations Made by the Maxwell Museum of Anthropology \n The Collections and Research Committee of the Maxwell Museum of Anthropology has determined that: \n \\xe2\\x80\\xa2 Pursuant to 25 U.S.C. 3001(3)(C), the cultural item described above is a specific ceremonial object needed by traditional Native American religious leaders for the practice of traditional Native American religions by their present-day adherents. \n \\xe2\\x80\\xa2 Pursuant to 25 U.S.C. 3001(2), there is a relationship of shared group identity that can be reasonably traced between the sacred object and the Kewa Pueblo, New Mexico (previously listed as the Pueblo of Santo Domingo). \n ", "a_r_d": "Lineal descendants or representatives of any Indian tribe or Native Hawaiian organization not identified in this notice that wish to claim this cultural item should submit a written request with information in support of the claim to David Phillips, Curator of Archaeology, Maxwell Museum of Anthropology, MSC01 1050, University of New Mexico, Albuquerque NM 87131, telephone (505) 277-9229 by August 29, 2013. After that date, if no additional claimants have come forward, transfer of control of the sacred object to Kewa Pueblo, New Mexico (previously listed as the Pueblo of Santo Domingo) may proceed. \n The Maxwell Museum is responsible for notifying Kewa Pueblo, New Mexico (previously listed as the Pueblo of Santo Domingo) that this notice has been published. \n "}