{"index": "R_224", "messy_full": "\\n      \\n        DEPARTMENT OF THE INTERIOR\\n        National Park Service\\n        [NPS-WASO-NAGPRA-13302; PPWOCRADN0-PCU00RP14.R50000]\\n        Notice of Intent To Repatriate Cultural Items: Field Museum of Natural History, Chicago, IL; Correction\\n        \\n          AGENCY:\\n          National Park Service, Interior.\\n        \\n        \\n          ACTION:\\n          Notice; correction.\\n        \\n        \\n          SUMMARY:\\n\\n          The Field Museum of Natural History has corrected a Notice of Intent to Repatriate published in the Federal Register on August 24, 2007. This notice corrects the NAGPRA category that the Field Museum, in consultation with the appropriate Indian tribes, has determined the cultural items meet. Transfer of control of the cultural items in this correction notice has occurred.\\n        \\n        \\n          ADDRESSES:\\n\\n          Helen Robbins, Repatriation Director, Field Museum of Natural History, 1400 South Lake Shore Drive, Chicago, IL 60605, telephone (312) 665-7317, email hrobbins@fieldmuseum.org.\\n          \\n        \\n      \\n      \\n        SUPPLEMENTARY INFORMATION:\\n        Notice is here given in accordance with the Native American Graves Protection and Repatriation Act (NAGPRA), 25 U.S.C. 3005, of a correction to the definition of cultural items previously under the control of the Field Museum of Natural History, Chicago, IL.\\n        This notice is published as part of the National Park Service\\'s administrative responsibilities under NAGPRA, 25 U.S.C. 3003(d)(3). The determinations in this notice are the sole responsibility of the museum, institution, or Federal agency that had control of the Native American cultural items. The National Park Service is not responsible for the determinations in this notice.\\n\\n        This notice corrects the NAGPRA category of the cultural items published in a Notice of Intent to Repatriate in the Federal Register on August 24, 2007 (72 FR 48672-48675). After the Notice of Intent to Repatriate was published, the Field Museum staff determined that the objects meet the NAGPRA definitions for sacred objects and objects of cultural patrimony. Transfer of control of the items in this correction notice has occurred.\\n        Correction\\n        In the Federal Register (72 FR 48672-48675), paragraph 1, sentence 1 is corrected by substituting the following sentence:\\n        \\n          \\n          Notice is here given in accordance with the Native American Graves Protection and Repatriation Act (NAGPRA), 25 U.S.C. 3005, of the intent to repatriate cultural items in the possession of the Field Museum of Natural History (Field Museum), Chicago, IL, that meet the definition of sacred objects and objects of cultural patrimony under 25 U.S.C. 3001.\\n        \\n        \\n        In the Federal Register (72 FR 48672-48675), paragraph 23, sentence 1 is corrected by substituting the following sentence:\\n        \\n        \\n          Officials of the Field Museum of Natural History have determined that the 56 cultural items described in this notice are specific ceremonial objects needed by traditional Native American religious leaders for the practice of traditional Native American religions by their present-day adherents, and that the 56 cultural items described above have ongoing historical, traditional, or cultural importance central to the Native American group or culture itself, rather than property owned by an individual. \\n        \\n        \\n        Additional Requestors and Disposition\\n        Transfer of control of the cultural items in this notice occurred after the 30-day waiting period expired for the original Notice of Intent to Repatriate. For questions related to this notice, contact Helen Robbins, Repatriation Director, Field Museum of Natural History, 1400 South Lake Shore Drive, Chicago, IL 60605, telephone (312) 665-7317.\\n        The Field Museum of Natural History is responsible for notifying the Apache Tribe of Oklahoma; Fort McDowell Yavapai Nation, Arizona; Fort Sill Apache Tribe of Oklahoma; Jicarilla Apache Nation, New Mexico; Mescalero Apache Tribe of the Mescalero Reservation, New Mexico; San Carlos Apache Tribe of the San Carlos Reservation, Arizona; Tonto Apache Tribe of Arizona; White Mountain Apache Tribe of the Fort Apache Reservation, Arizona; and the Yavapai-Apache Nation of the Camp Verde Indian Reservation, Arizona, that this notice has been published.\\n        \\n          Dated: June 12, 2013.\\n          Sherry Hutt,\\n          Manager, National NAGPRA Program.\\n        \\n      \\n      [FR Doc. 2013-19381 Filed 8-9-13; 8:45 am]\\n      BILLING CODE 4312-50-P\\n    ", "agency1": "DEPARTMENT OF THE INTERIOR", "sub_agency1": "National Park Service", "dep_doc": "[NPS-WASO-NAGPRA-13302; PPWOCRADN0-PCU00RP14.R50000]", "subject": "Notice of Intent To Repatriate Cultural Items: Field Museum of Natural History, Chicago, IL; Correction", "agency2": "National Park Service, Interior.", "action": "Notice; correction.", "summary": "The Field Museum of Natural History has corrected a Notice of Intent to Repatriate published in the Federal Register on August 24, 2007. This notice corrects the NAGPRA category that the Field Museum, in consultation with the appropriate Indian tribes, has determined the cultural items meet. Transfer of control of the cultural items in this correction notice has occurred.", "dates": "Null", "addresses": "Helen Robbins, Repatriation Director, Field Museum of Natural History, 1400 South Lake Shore Drive, Chicago, IL 60605, telephone (312) 665-7317, email hrobbins@fieldmuseum.org.\\n          ", "signature_dated": "Dated: June 12, 2013.", "signature_name": "Sherry Hutt,", "signature_title": "Manager, National NAGPRA Program.", "fr_doc": "[FR Doc. 2013-19381 Filed 8-9-13; 8:45 am]", "billing_code": "BILLING CODE 4312-50-P", "supp_info": "SUPPLEMENTARY INFORMATION: \n Notice is here given in accordance with the Native American Graves Protection and Repatriation Act (NAGPRA), 25 U.S.C. 3005, of a correction to the definition of cultural items previously under the control of the Field Museum of Natural History, Chicago, IL. \n This notice is published as part of the National Park Service\\'s administrative responsibilities under NAGPRA, 25 U.S.C. 3003(d)(3). The determinations in this notice are the sole responsibility of the museum, institution, or Federal agency that had control of the Native American cultural items. The National Park Service is not responsible for the determinations in this notice. \n This notice corrects the NAGPRA category of the cultural items published in a Notice of Intent to Repatriate in the Federal Register on August 24, 2007 (72 FR 48672-48675). After the Notice of Intent to Repatriate was published, the Field Museum staff determined that the objects meet the NAGPRA definitions for sacred objects and objects of cultural patrimony. Transfer of control of the items in this correction notice has occurred. \n Correction \n In the Federal Register (72 FR 48672-48675), paragraph 1, sentence 1 is corrected by substituting the following sentence: \n In the Federal Register (72 FR 48672-48675), paragraph 23, sentence 1 is corrected by substituting the following sentence: \n Additional Requestors and Disposition \n Transfer of control of the cultural items in this notice occurred after the 30-day waiting period expired for the original Notice of Intent to Repatriate. For questions related to this notice, contact Helen Robbins, Repatriation Director, Field Museum of Natural History, 1400 South Lake Shore Drive, Chicago, IL 60605, telephone (312) 665-7317. \n The Field Museum of Natural History is responsible for notifying the Apache Tribe of Oklahoma; Fort McDowell Yavapai Nation, Arizona; Fort Sill Apache Tribe of Oklahoma; Jicarilla Apache Nation, New Mexico; Mescalero Apache Tribe of the Mescalero Reservation, New Mexico; San Carlos Apache Tribe of the San Carlos Reservation, Arizona; Tonto Apache Tribe of Arizona; White Mountain Apache Tribe of the Fort Apache Reservation, Arizona; and the Yavapai-Apache Nation of the Camp Verde Indian Reservation, Arizona, that this notice has been published. \n ", "consultation": "Null", "h_d_r": "Null", "h_d_ci": "Null", "determinations": "Null", "a_r_d": "Transfer of control of the cultural items in this notice occurred after the 30-day waiting period expired for the original Notice of Intent to Repatriate. For questions related to this notice, contact Helen Robbins, Repatriation Director, Field Museum of Natural History, 1400 South Lake Shore Drive, Chicago, IL 60605, telephone (312) 665-7317. \n The Field Museum of Natural History is responsible for notifying the Apache Tribe of Oklahoma; Fort McDowell Yavapai Nation, Arizona; Fort Sill Apache Tribe of Oklahoma; Jicarilla Apache Nation, New Mexico; Mescalero Apache Tribe of the Mescalero Reservation, New Mexico; San Carlos Apache Tribe of the San Carlos Reservation, Arizona; Tonto Apache Tribe of Arizona; White Mountain Apache Tribe of the Fort Apache Reservation, Arizona; and the Yavapai-Apache Nation of the Camp Verde Indian Reservation, Arizona, that this notice has been published. \n "}