{"index": "R_236", "messy_full": "\\n      \\n        DEPARTMENT OF THE INTERIOR\\n        National Park Service\\n        [NPS-WASO-NAGPRA-12627; PPWOCRADN0-PCU00RP14.R50000]\\n        Notice of Intent To Repatriate a Cultural Item: U.S. Department of the Interior, Bureau of Indian Affairs, Washington, DC, and the Robert S. Peabody Museum of Archaeology, Phillips Academy, Andover, MA\\n        \\n          AGENCY:\\n          National Park Service, Interior.\\n        \\n        \\n          ACTION:\\n          Notice.\\n        \\n        \\n          SUMMARY:\\n          The U.S. Department of the Interior, Bureau of Indian Affairs, and the Robert S. Peabody Museum of Archaeology, in consultation with the appropriate Indian tribes, have determined that the cultural item listed in this notice meets the definition of unassociated funerary object. Lineal descendants or representatives of any Indian tribe or Native Hawaiian organization not identified in this notice that wish to claim this cultural item should submit a written request to the U.S. Department of the Interior, Bureau of Indian Affairs. If no additional claimants come forward, transfer of control of the cultural item to the lineal descendants, Indian tribes, or Native Hawaiian organizations stated in this notice may proceed.\\n        \\n        \\n          DATES:\\n          Lineal descendants or representatives of any Indian tribe or Native Hawaiian organization not identified in this notice that wish to claim this cultural item should submit a written request with information in support of the claim to the U.S. Department of the Interior, Bureau of Indian Affairs at the address in this notice by May 15, 2013.\\n        \\n        \\n          ADDRESSES:\\n\\n          Anna Pardo, Museum Program Manager/NAGPRA Coordinator, U.S. Department of the Interior, Indian Affairs, 12220 Sunrise Valley Drive, Room 6084, Reston, VA 20191, telephone (703) 390-6343, email Anna.Pardo@bia.gov.\\n        \\n      \\n      \\n        SUPPLEMENTARY INFORMATION:\\n        Notice is here given in accordance with the Native American Graves Protection and Repatriation Act (NAGPRA), 25 U.S.C. 3005, of the intent to repatriate a cultural item under the control of the U.S. Department of the Interior, Bureau of Indian Affairs, Washington, DC, and in the physical custody of the Robert S. Peabody Museum of Archaeology, Phillips Academy, Andover, MA, that meets the definition of unassociated funerary object under 25 U.S.C. 3001.\\n        This notice is published as part of the National Park Service\\'s administrative responsibilities under NAGPRA, 25 U.S.C. 3003(d)(3). The determinations in this notice are the sole responsibility of the museum, institution, or Federal agency that has control of the Native American cultural items. The National Park Service is not responsible for the determinations in this notice.\\n        History and Description of the Cultural Item(s)\\n        Between 1934 and 1935, a cultural item was removed from the Snaketown site (AZ U:13:1) on the Gila River Indian Reservation, in Pinal County, AZ, during legally authorized excavations conducted by the Gila Pueblo Foundation. In 1940, this item was donated to the Robert S. Peabody Museum of Archaeology as part of a larger collection donation. The one unassociated funerary object is a projectile point which was found in association with a human burial, but the human remains are not present in the collections. Archeological evidence places the Snaketown site within the archeologically-defined Hohokam tradition. The occupation of the Snaketown site spans the years from circa A.D. 500 or 700 to 1100 or 1150.\\n\\n        Continuities of mortuary practices, ethnographic materials, and technology indicate affiliation of Hohokam settlements with present-day O\\'odham (Piman) and Puebloan cultures. An August 2000 cultural affiliation study, submitted by the Gila River Indian Community of the Gila River Indian Reservation, addresses continuities between the Hohokam and the O\\'odham tribes.\\n        Determinations Made by the U.S. Department of the Interior, Bureau of Indian Affairs, Washington, DC, and the Robert S. Peabody Museum of Archaeology, Phillips Academy, Andover, MA\\n        Officials of the Bureau of Indian Affairs and the Robert S. Peabody Museum of Archaeology have determined that:\\n        \\xe2\\x80\\xa2 Pursuant to 25 U.S.C. 3001(3)(B), the one cultural item described above is reasonably believed to have been placed with or near individual human remains at the time of death or later as part of the death rite or ceremony and are believed, by a preponderance of the evidence, to have been removed from a specific burial site of a Native American individual.\\n        \\xe2\\x80\\xa2 Pursuant to 25 U.S.C. 3001(2), there is a relationship of shared group identity that can be reasonably traced between the unassociated funerary object and the Ak Chin Indian Community of the Maricopa (Ak Chin) Indian Reservation, Arizona; Gila River Indian Community of the Gila River Indian Reservation, Arizona; Hopi Tribe of Arizona; Salt River Pima-Maricopa Indian Community of the Salt River Reservation, Arizona; Tohono O\\'odham Nation of Arizona; and the Zuni Tribe of the Zuni Reservation, New Mexico (hereafter referred to as \\xe2\\x80\\x9cThe Tribes\\xe2\\x80\\x9d).\\n        Additional Requestors and Disposition\\n\\n        Lineal descendants or representatives of any Indian tribe or Native Hawaiian organization not identified in this notice that wish to claim this cultural item should submit a written request with information in support of the claim to Anna Pardo, Museum Program Manager/NAGPRA Coordinator, U.S. Department of the Interior, Indian Affairs, 12220 Sunrise Valley Drive, Room 6084, Reston, VA 20191, telephone (703) 390-6343, email Anna.Pardo@bia.gov, by May 15, 2013. After that date, if no additional claimants have come forward, transfer of control of the unassociated funerary object to The Tribes may proceed.\\n        The Bureau of Indian Affairs is responsible for notifying The Tribes that this notice has been published.\\n        \\n          Dated: March 21, 2013.\\n          Sherry Hutt,\\n          Manager, National NAGPRA Program.\\n        \\n      \\n      [FR Doc. 2013-08772 Filed 4-12-13; 8:45 am]\\n      BILLING CODE 4312-50-P\\n    ", "agency1": "DEPARTMENT OF THE INTERIOR", "sub_agency1": "National Park Service", "dep_doc": "[NPS-WASO-NAGPRA-12627; PPWOCRADN0-PCU00RP14.R50000]", "subject": "Notice of Intent To Repatriate a Cultural Item: U.S. Department of the Interior, Bureau of Indian Affairs, Washington, DC, and the Robert S. Peabody Museum of Archaeology, Phillips Academy, Andover, MA", "agency2": "National Park Service, Interior.", "action": "Notice.", "summary": "The U.S. Department of the Interior, Bureau of Indian Affairs, and the Robert S. Peabody Museum of Archaeology, in consultation with the appropriate Indian tribes, have determined that the cultural item listed in this notice meets the definition of unassociated funerary object. Lineal descendants or representatives of any Indian tribe or Native Hawaiian organization not identified in this notice that wish to claim this cultural item should submit a written request to the U.S. Department of the Interior, Bureau of Indian Affairs. If no additional claimants come forward, transfer of control of the cultural item to the lineal descendants, Indian tribes, or Native Hawaiian organizations stated in this notice may proceed.", "dates": "Lineal descendants or representatives of any Indian tribe or Native Hawaiian organization not identified in this notice that wish to claim this cultural item should submit a written request with information in support of the claim to the U.S. Department of the Interior, Bureau of Indian Affairs at the address in this notice by May 15, 2013.", "addresses": "Anna Pardo, Museum Program Manager/NAGPRA Coordinator, U.S. Department of the Interior, Indian Affairs, 12220 Sunrise Valley Drive, Room 6084, Reston, VA 20191, telephone (703) 390-6343, email Anna.Pardo@bia.gov.", "signature_dated": "Dated: March 21, 2013.", "signature_name": "Sherry Hutt,", "signature_title": "Manager, National NAGPRA Program.", "fr_doc": "[FR Doc. 2013-08772 Filed 4-12-13; 8:45 am]", "billing_code": "BILLING CODE 4312-50-P", "supp_info": "SUPPLEMENTARY INFORMATION: \n Notice is here given in accordance with the Native American Graves Protection and Repatriation Act (NAGPRA), 25 U.S.C. 3005, of the intent to repatriate a cultural item under the control of the U.S. Department of the Interior, Bureau of Indian Affairs, Washington, DC, and in the physical custody of the Robert S. Peabody Museum of Archaeology, Phillips Academy, Andover, MA, that meets the definition of unassociated funerary object under 25 U.S.C. 3001. \n This notice is published as part of the National Park Service\\'s administrative responsibilities under NAGPRA, 25 U.S.C. 3003(d)(3). The determinations in this notice are the sole responsibility of the museum, institution, or Federal agency that has control of the Native American cultural items. The National Park Service is not responsible for the determinations in this notice. \n History and Description of the Cultural Item(s) \n Between 1934 and 1935, a cultural item was removed from the Snaketown site (AZ U:13:1) on the Gila River Indian Reservation, in Pinal County, AZ, during legally authorized excavations conducted by the Gila Pueblo Foundation. In 1940, this item was donated to the Robert S. Peabody Museum of Archaeology as part of a larger collection donation. The one unassociated funerary object is a projectile point which was found in association with a human burial, but the human remains are not present in the collections. Archeological evidence places the Snaketown site within the archeologically-defined Hohokam tradition. The occupation of the Snaketown site spans the years from circa A.D. 500 or 700 to 1100 or 1150. \n Continuities of mortuary practices, ethnographic materials, and technology indicate affiliation of Hohokam settlements with present-day O\\'odham (Piman) and Puebloan cultures. An August 2000 cultural affiliation study, submitted by the Gila River Indian Community of the Gila River Indian Reservation, addresses continuities between the Hohokam and the O\\'odham tribes. \n Determinations Made by the U.S. Department of the Interior, Bureau of Indian Affairs, Washington, DC, and the Robert S. Peabody Museum of Archaeology, Phillips Academy, Andover, MA \n Officials of the Bureau of Indian Affairs and the Robert S. Peabody Museum of Archaeology have determined that: \n \\xe2\\x80\\xa2 Pursuant to 25 U.S.C. 3001(3)(B), the one cultural item described above is reasonably believed to have been placed with or near individual human remains at the time of death or later as part of the death rite or ceremony and are believed, by a preponderance of the evidence, to have been removed from a specific burial site of a Native American individual. \n \\xe2\\x80\\xa2 Pursuant to 25 U.S.C. 3001(2), there is a relationship of shared group identity that can be reasonably traced between the unassociated funerary object and the Ak Chin Indian Community of the Maricopa (Ak Chin) Indian Reservation, Arizona; Gila River Indian Community of the Gila River Indian Reservation, Arizona; Hopi Tribe of Arizona; Salt River Pima-Maricopa Indian Community of the Salt River Reservation, Arizona; Tohono O\\'odham Nation of Arizona; and the Zuni Tribe of the Zuni Reservation, New Mexico (hereafter referred to as \\xe2\\x80\\x9cThe Tribes\\xe2\\x80\\x9d). \n Additional Requestors and Disposition \n Lineal descendants or representatives of any Indian tribe or Native Hawaiian organization not identified in this notice that wish to claim this cultural item should submit a written request with information in support of the claim to Anna Pardo, Museum Program Manager/NAGPRA Coordinator, U.S. Department of the Interior, Indian Affairs, 12220 Sunrise Valley Drive, Room 6084, Reston, VA 20191, telephone (703) 390-6343, email Anna.Pardo@bia.gov, by May 15, 2013. After that date, if no additional claimants have come forward, transfer of control of the unassociated funerary object to The Tribes may proceed. \n The Bureau of Indian Affairs is responsible for notifying The Tribes that this notice has been published. \n ", "consultation": "Null", "h_d_r": "Null", "h_d_ci": "Null", "determinations": "Determinations Made by the U.S. Department of the Interior, Bureau of Indian Affairs, Washington, DC, and the Robert S. Peabody Museum of Archaeology, Phillips Academy, Andover, MA \n Officials of the Bureau of Indian Affairs and the Robert S. Peabody Museum of Archaeology have determined that: \n \\xe2\\x80\\xa2 Pursuant to 25 U.S.C. 3001(3)(B), the one cultural item described above is reasonably believed to have been placed with or near individual human remains at the time of death or later as part of the death rite or ceremony and are believed, by a preponderance of the evidence, to have been removed from a specific burial site of a Native American individual. \n \\xe2\\x80\\xa2 Pursuant to 25 U.S.C. 3001(2), there is a relationship of shared group identity that can be reasonably traced between the unassociated funerary object and the Ak Chin Indian Community of the Maricopa (Ak Chin) Indian Reservation, Arizona; Gila River Indian Community of the Gila River Indian Reservation, Arizona; Hopi Tribe of Arizona; Salt River Pima-Maricopa Indian Community of the Salt River Reservation, Arizona; Tohono O\\'odham Nation of Arizona; and the Zuni Tribe of the Zuni Reservation, New Mexico (hereafter referred to as \\xe2\\x80\\x9cThe Tribes\\xe2\\x80\\x9d). \n ", "a_r_d": "Lineal descendants or representatives of any Indian tribe or Native Hawaiian organization not identified in this notice that wish to claim this cultural item should submit a written request with information in support of the claim to Anna Pardo, Museum Program Manager/NAGPRA Coordinator, U.S. Department of the Interior, Indian Affairs, 12220 Sunrise Valley Drive, Room 6084, Reston, VA 20191, telephone (703) 390-6343, email Anna.Pardo@bia.gov, by May 15, 2013. After that date, if no additional claimants have come forward, transfer of control of the unassociated funerary object to The Tribes may proceed. \n The Bureau of Indian Affairs is responsible for notifying The Tribes that this notice has been published. \n "}