{"index": "R_256", "messy_full": "\\n      \\n        DEPARTMENT OF THE INTERIOR\\n        National Park Service\\n        [NPS-WASO-NAGPRA-11225; 2200-1100-665]\\n        Notice of Intent To Repatriate Cultural Items: Stanford University Archaeology Center, Stanford, CA\\n        \\n          AGENCY:\\n          National Park Service, Interior.\\n        \\n        \\n          ACTION:\\n          Notice.\\n        \\n        \\n          SUMMARY:\\n          The Stanford University Archaeology Center, in consultation with the appropriate Indian tribes, has determined that the cultural items meet the definition of sacred object and repatriation to the Indian tribes stated below may occur if no additional claimants come forward. Representatives of any Indian tribe that believes itself to be culturally affiliated with the cultural items may contact the Stanford University Archaeology Center.\\n        \\n        \\n          DATES:\\n          Representatives of any Indian tribe that believes it has a cultural affiliation with the cultural items should contact the Stanford University Archaeology Center at the address below by October 31, 2012.\\n        \\n        \\n          ADDRESSES:\\n          Laura Jones, Director, Heritage Services and University Archaeologist, Archaeology Center, 488 Escondido Mall, Stanford, CA 94305, telephone (650) 723-9664.\\n        \\n      \\n      \\n        SUPPLEMENTARY INFORMATION:\\n        Notice is here given in accordance with the Native American Graves Protection and Repatriation Act (NAGPRA), 25 U.S.C. 3005, of the intent to repatriate cultural items in the possession of the Stanford University Archaeology Center that meet the definition of sacred object under 25 U.S.C. 3001.\\n        This notice is published as part of the National Park Service\\'s administrative responsibilities under NAGPRA, 25 U.S.C. 3003(d)(3). The determinations in this notice are the sole responsibility of the museum, institution, or Federal agency that has control of the Native American cultural items. The National Park Service is not responsible for the determinations in this notice.\\n        History and Description of the Remains\\n        Sometime prior to 1905, 44 cultural items were removed from an unknown location in Tulare County, CA. Stanford University\\'s cofounder, Mrs. Jane Stanford, donated the cultural items to the Stanford Museum before her death in 1905. The sacred objects are 44 stone objects. Representatives from the Santa Rosa Indian Community of the Santa Rosa Rancheria, California, identified the 44 stone objects as sacred objects during a consultation visit to Stanford University in August 2011.\\n        The Santa Rosa Indian Community of the Santa Rosa Rancheria, California, has provided additional information regarding these cultural items to establish cultural affiliation to the Yokut tribes. Based on the site location and in accordance with the information received in the consultation process, the sacred objects are culturally affiliated with the Yokut communities represented by the present-day tribes of the Picayune Rancheria of Chukchansi Indians of California; Santa Rosa Indian Community of the Santa Rosa Rancheria, California; Table Mountain Rancheria of California; and the Tule River Indian Tribe of the Tule River Reservation, California.\\n        Determinations Made by the Stanford University Archaeology Center\\n        Officials of the Stanford University Archaeology Center have determined that:\\n        \\xe2\\x80\\xa2 Pursuant to 25 U.S.C. 3001(3) (C), the 44 cultural items described above are specific ceremonial objects needed by traditional Native American Religious leaders for the practice of traditional Native American religions by their present-day adherents.\\n        \\xe2\\x80\\xa2 Pursuant to 25 U.S.C. 3001(2), there is a relationship of shared group identity that can be reasonably traced between the Native American human remains and the Picayune Rancheria of Chukchansi Indians of California; Santa Rosa Indian Community of the Santa Rosa Rancheria, California; Table Mountain Rancheria of California; and the Tule River Indian Tribe of the Tule River Reservation, California.\\n        Additional Requestors and Disposition\\n\\n        Representatives of any Indian tribe that believes itself to be culturally affiliated with the sacred objects should contact Laura Jones, Director, Heritage Services and University Archaeologist, Archaeology Center, 488 Escondido Mall, Stanford, CA 94305, telephone (650) 723-9664 before October 31, 2012. Repatriation of the sacred objects to the Picayune Rancheria of Chukchansi Indians of California; Santa Rosa Indian Community of the Santa Rosa Rancheria, California; Table Mountain Rancheria of California; and the Tule River Indian Tribe of the Tule River Reservation, California, may proceed after that date if no additional claimants come forward.\\n        The Stanford University Archaeology Center is responsible for notifying the Picayune Rancheria of Chukchansi Indians of California; Santa Rosa Indian Community of the Santa Rosa Rancheria, California; Table Mountain Rancheria of California; and the Tule River Indian Tribe of the Tule River Reservation, California, that this notice has been published.\\n        \\n          Dated: September 5, 2012.\\n          Sherry Hutt,\\n          Manager, National NAGPRA Program.\\n        \\n      \\n      [FR Doc. 2012-24090 Filed 9-28-12; 8:45 am]\\n      BILLING CODE 4312-50-P\\n    ", "agency1": "DEPARTMENT OF THE INTERIOR", "sub_agency1": "National Park Service", "dep_doc": "[NPS-WASO-NAGPRA-11225; 2200-1100-665]", "subject": "Notice of Intent To Repatriate Cultural Items: Stanford University Archaeology Center, Stanford, CA", "agency2": "National Park Service, Interior.", "action": "Notice.", "summary": "The Stanford University Archaeology Center, in consultation with the appropriate Indian tribes, has determined that the cultural items meet the definition of sacred object and repatriation to the Indian tribes stated below may occur if no additional claimants come forward. Representatives of any Indian tribe that believes itself to be culturally affiliated with the cultural items may contact the Stanford University Archaeology Center.", "dates": "Representatives of any Indian tribe that believes it has a cultural affiliation with the cultural items should contact the Stanford University Archaeology Center at the address below by October 31, 2012.", "addresses": "Laura Jones, Director, Heritage Services and University Archaeologist, Archaeology Center, 488 Escondido Mall, Stanford, CA 94305, telephone (650) 723-9664.", "signature_dated": "Dated: September 5, 2012.", "signature_name": "Sherry Hutt,", "signature_title": "Manager, National NAGPRA Program.", "fr_doc": "[FR Doc. 2012-24090 Filed 9-28-12; 8:45 am]", "billing_code": "BILLING CODE 4312-50-P", "supp_info": "SUPPLEMENTARY INFORMATION: \n Notice is here given in accordance with the Native American Graves Protection and Repatriation Act (NAGPRA), 25 U.S.C. 3005, of the intent to repatriate cultural items in the possession of the Stanford University Archaeology Center that meet the definition of sacred object under 25 U.S.C. 3001. \n This notice is published as part of the National Park Service\\'s administrative responsibilities under NAGPRA, 25 U.S.C. 3003(d)(3). The determinations in this notice are the sole responsibility of the museum, institution, or Federal agency that has control of the Native American cultural items. The National Park Service is not responsible for the determinations in this notice. \n History and Description of the Remains \n Sometime prior to 1905, 44 cultural items were removed from an unknown location in Tulare County, CA. Stanford University\\'s cofounder, Mrs. Jane Stanford, donated the cultural items to the Stanford Museum before her death in 1905. The sacred objects are 44 stone objects. Representatives from the Santa Rosa Indian Community of the Santa Rosa Rancheria, California, identified the 44 stone objects as sacred objects during a consultation visit to Stanford University in August 2011. \n The Santa Rosa Indian Community of the Santa Rosa Rancheria, California, has provided additional information regarding these cultural items to establish cultural affiliation to the Yokut tribes. Based on the site location and in accordance with the information received in the consultation process, the sacred objects are culturally affiliated with the Yokut communities represented by the present-day tribes of the Picayune Rancheria of Chukchansi Indians of California; Santa Rosa Indian Community of the Santa Rosa Rancheria, California; Table Mountain Rancheria of California; and the Tule River Indian Tribe of the Tule River Reservation, California. \n Determinations Made by the Stanford University Archaeology Center \n Officials of the Stanford University Archaeology Center have determined that: \n \\xe2\\x80\\xa2 Pursuant to 25 U.S.C. 3001(3) (C), the 44 cultural items described above are specific ceremonial objects needed by traditional Native American Religious leaders for the practice of traditional Native American religions by their present-day adherents. \n \\xe2\\x80\\xa2 Pursuant to 25 U.S.C. 3001(2), there is a relationship of shared group identity that can be reasonably traced between the Native American human remains and the Picayune Rancheria of Chukchansi Indians of California; Santa Rosa Indian Community of the Santa Rosa Rancheria, California; Table Mountain Rancheria of California; and the Tule River Indian Tribe of the Tule River Reservation, California. \n Additional Requestors and Disposition \n Representatives of any Indian tribe that believes itself to be culturally affiliated with the sacred objects should contact Laura Jones, Director, Heritage Services and University Archaeologist, Archaeology Center, 488 Escondido Mall, Stanford, CA 94305, telephone (650) 723-9664 before October 31, 2012. Repatriation of the sacred objects to the Picayune Rancheria of Chukchansi Indians of California; Santa Rosa Indian Community of the Santa Rosa Rancheria, California; Table Mountain Rancheria of California; and the Tule River Indian Tribe of the Tule River Reservation, California, may proceed after that date if no additional claimants come forward. \n The Stanford University Archaeology Center is responsible for notifying the Picayune Rancheria of Chukchansi Indians of California; Santa Rosa Indian Community of the Santa Rosa Rancheria, California; Table Mountain Rancheria of California; and the Tule River Indian Tribe of the Tule River Reservation, California, that this notice has been published. \n ", "consultation": "Null", "h_d_r": "Sometime prior to 1905, 44 cultural items were removed from an unknown location in Tulare County, CA. Stanford University\\'s cofounder, Mrs. Jane Stanford, donated the cultural items to the Stanford Museum before her death in 1905. The sacred objects are 44 stone objects. Representatives from the Santa Rosa Indian Community of the Santa Rosa Rancheria, California, identified the 44 stone objects as sacred objects during a consultation visit to Stanford University in August 2011. \n The Santa Rosa Indian Community of the Santa Rosa Rancheria, California, has provided additional information regarding these cultural items to establish cultural affiliation to the Yokut tribes. Based on the site location and in accordance with the information received in the consultation process, the sacred objects are culturally affiliated with the Yokut communities represented by the present-day tribes of the Picayune Rancheria of Chukchansi Indians of California; Santa Rosa Indian Community of the Santa Rosa Rancheria, California; Table Mountain Rancheria of California; and the Tule River Indian Tribe of the Tule River Reservation, California. \n ", "h_d_ci": "Null", "determinations": "Determinations Made by the Stanford University Archaeology Center \n Officials of the Stanford University Archaeology Center have determined that: \n \\xe2\\x80\\xa2 Pursuant to 25 U.S.C. 3001(3) (C), the 44 cultural items described above are specific ceremonial objects needed by traditional Native American Religious leaders for the practice of traditional Native American religions by their present-day adherents. \n \\xe2\\x80\\xa2 Pursuant to 25 U.S.C. 3001(2), there is a relationship of shared group identity that can be reasonably traced between the Native American human remains and the Picayune Rancheria of Chukchansi Indians of California; Santa Rosa Indian Community of the Santa Rosa Rancheria, California; Table Mountain Rancheria of California; and the Tule River Indian Tribe of the Tule River Reservation, California. \n ", "a_r_d": "Representatives of any Indian tribe that believes itself to be culturally affiliated with the sacred objects should contact Laura Jones, Director, Heritage Services and University Archaeologist, Archaeology Center, 488 Escondido Mall, Stanford, CA 94305, telephone (650) 723-9664 before October 31, 2012. Repatriation of the sacred objects to the Picayune Rancheria of Chukchansi Indians of California; Santa Rosa Indian Community of the Santa Rosa Rancheria, California; Table Mountain Rancheria of California; and the Tule River Indian Tribe of the Tule River Reservation, California, may proceed after that date if no additional claimants come forward. \n The Stanford University Archaeology Center is responsible for notifying the Picayune Rancheria of Chukchansi Indians of California; Santa Rosa Indian Community of the Santa Rosa Rancheria, California; Table Mountain Rancheria of California; and the Tule River Indian Tribe of the Tule River Reservation, California, that this notice has been published. \n "}