{"index": "R_268", "messy_full": "\\n      \\n        DEPARTMENT OF THE INTERIOR\\n        National Park Service\\n        [NPS-WASO-NAGPRA-10376; 2200-1100-665]\\n        Notice of Intent To Repatriate Cultural Items: U.S. Department of the Interior, National Park Service, Little Bighorn Battlefield National Monument, Crow Agency, MT\\n        \\n          AGENCY:\\n          National Park Service, Interior.\\n        \\n        \\n          ACTION:\\n          Notice.\\n        \\n        \\n          SUMMARY:\\n          Little Bighorn Battlefield National Monument (LIBI), in consultation with the appropriate Indian tribes, has determined that the cultural items meet the definition of sacred objects and repatriation to the lineal descendant stated below may occur if no additional claimants come forward. Any other individuals who believe they are lineal descendants of the individual who owned these sacred objects and who wish to claim the items should contact LIBI.\\n        \\n        \\n          DATES:\\n          Any other individuals who believe they are lineal descendants of the individual who owned these sacred objects and who wish to claim the items should contact LIBI at the address below by July 12, 2012.\\n        \\n        \\n          ADDRESSES:\\n          Gus Sanchez, Acting Superintendent, Little Bighorn Battlefield National Monument, P.O. Box 39, Crow Agency, MT 59022-0039, telephone (406) 638-3201.\\n        \\n      \\n      \\n        \\n        SUPPLEMENTARY INFORMATION:\\n        Notice is here given in accordance with the Native American Graves Protection and Repatriation Act (NAGPRA), 25 U.S.C. 3005, of the intent to repatriate cultural items in the possession of the U.S. Department of the Interior, National Park Service, LIBI, Crow Agency, MT that meet the definition of sacred objects under 25 U.S.C. 3001.\\n        This notice is published as part of the National Park Service\\'s administrative responsibilities under NAGPRA, 25 U.S.C. 3003(d)(3). The determinations in this notice are the sole responsibility of the Superintendent, LIBI.\\n        History and Description of the Cultural Items\\n        The 18 cultural items are part of a medicine bundle and are one satchel made out of animal hide, 13 small medicine bags, and four stones. The items belonged to Spotted Hawk who resided on the Northern Cheyenne Reservation. On August 4, 1930, Cecilia Spotted Wolf, Spotted Hawk\\'s sister, traded or gifted the items to Dr. Thomas B. Marquis, a physician on the Tongue River Reservation (Northern Cheyenne). In 1942, the 18 objects were donated to Custer Battlefield National Cemetery, now known as LIBI, by Dr. Marquis\\' daughters, Mrs. Millie Ellen Marquis Hastings and Mrs. Anna Rose Octavia Marquis Heil.\\n        Jean Spotted Wolf Emmons, great-grand niece of Spotted Hawk, is requesting repatriation of the 18 cultural items. The medicine bundle is needed by Mrs. Emmons to continue traditional ceremonies. LIBI consulted with the Northern Cheyenne Cultural Commission and Tribal Historic Preservation Office to determine that Jean Emmons is an appropriate recipient under the Northern Cheyenne traditional kinship system and common law system of descendance.\\n        Determinations Made by Little Bighorn Battlefield National Monument\\n        Officials of LIBI have determined that:\\n        \\xe2\\x80\\xa2 Pursuant to 25 U.S.C. 3001(3)(C), the 18 cultural items described above are specific ceremonial objects needed by traditional Native American religious leaders for the practice of traditional Native American religions by their present-day adherents.\\n        \\xe2\\x80\\xa2 Pursuant to 25 U.S.C. 3005(a)(5)(A), Mrs. Emmons is the direct lineal descendant of the individual who owned these sacred objects.\\n        Additional Requestors and Disposition\\n        Any other individuals who believe they are lineal descendants of the individual who owned these sacred objects and who wish to claim the items should contact Gus Sanchez, Acting Superintendent, Little Bighorn Battlefield National Monument, P.O. Box 39, Crow Agency, MT 59022-0039, telephone (406) 638-3201, before July 12, 2012. Repatriation of the sacred objects to Mrs. Jean Spotted Wolf Emmons may proceed after that date if no additional claimants come forward.\\n        LIBI is responsible for notifying Mrs. Jean Spotted Wolf Emmons; the Arapaho Tribe of the Wind River Reservation, Wyoming; Assiniboine and Sioux Tribes of the Fort Peck Indian Reservation, Montana; Cheyenne and Arapaho Tribes, Oklahoma (formerly the Cheyenne-Arapaho Tribes of Oklahoma); Cheyenne River Sioux Tribe of the Cheyenne River Reservation, South Dakota; Crow Creek Sioux Tribe of the Crow Creek Reservation, South Dakota; Crow Tribe of Montana; Flandreau Santee Sioux Tribe of South Dakota; Lower Brule Sioux Tribe of the Lower Brule Reservation, South Dakota; Northern Cheyenne Tribe of the Northern Cheyenne Indian Reservation, Montana; Oglala Sioux Tribe of the Pine Ridge Reservation, South Dakota; Rosebud Sioux Tribe of the Rosebud Indian Reservation, South Dakota; Santee Sioux Nation, Nebraska; Sisseton-Wahpeton Oyate of the Lake Traverse Reservation, South Dakota; Spirit Lake Tribe, North Dakota; Standing Rock Sioux Tribe of North & South Dakota; Three Affiliated Tribes of the Fort Berthold Reservation, North Dakota; and the Yankton Sioux Tribe of South Dakota that this notice has been published.\\n        \\n          Dated: June 7, 2012.\\n          David Tarler,\\n          Acting Manager, National NAGPRA Program.\\n        \\n      \\n      [FR Doc. 2012-14311 Filed 6-11-12; 8:45 am]\\n      BILLING CODE 4312-50-P\\n    ", "agency1": "DEPARTMENT OF THE INTERIOR", "sub_agency1": "National Park Service", "dep_doc": "[NPS-WASO-NAGPRA-10376; 2200-1100-665]", "subject": "Notice of Intent To Repatriate Cultural Items: U.S. Department of the Interior, National Park Service, Little Bighorn Battlefield National Monument, Crow Agency, MT", "agency2": "National Park Service, Interior.", "action": "Notice.", "summary": "Little Bighorn Battlefield National Monument (LIBI), in consultation with the appropriate Indian tribes, has determined that the cultural items meet the definition of sacred objects and repatriation to the lineal descendant stated below may occur if no additional claimants come forward. Any other individuals who believe they are lineal descendants of the individual who owned these sacred objects and who wish to claim the items should contact LIBI.", "dates": "Any other individuals who believe they are lineal descendants of the individual who owned these sacred objects and who wish to claim the items should contact LIBI at the address below by July 12, 2012.", "addresses": "Gus Sanchez, Acting Superintendent, Little Bighorn Battlefield National Monument, P.O. Box 39, Crow Agency, MT 59022-0039, telephone (406) 638-3201.", "signature_dated": "Dated: June 7, 2012.", "signature_name": "David Tarler,", "signature_title": "Acting Manager, National NAGPRA Program.", "fr_doc": "[FR Doc. 2012-14311 Filed 6-11-12; 8:45 am]", "billing_code": "BILLING CODE 4312-50-P", "supp_info": "SUPPLEMENTARY INFORMATION: \n Notice is here given in accordance with the Native American Graves Protection and Repatriation Act (NAGPRA), 25 U.S.C. 3005, of the intent to repatriate cultural items in the possession of the U.S. Department of the Interior, National Park Service, LIBI, Crow Agency, MT that meet the definition of sacred objects under 25 U.S.C. 3001. \n This notice is published as part of the National Park Service\\'s administrative responsibilities under NAGPRA, 25 U.S.C. 3003(d)(3). The determinations in this notice are the sole responsibility of the Superintendent, LIBI. \n History and Description of the Cultural Items \n The 18 cultural items are part of a medicine bundle and are one satchel made out of animal hide, 13 small medicine bags, and four stones. The items belonged to Spotted Hawk who resided on the Northern Cheyenne Reservation. On August 4, 1930, Cecilia Spotted Wolf, Spotted Hawk\\'s sister, traded or gifted the items to Dr. Thomas B. Marquis, a physician on the Tongue River Reservation (Northern Cheyenne). In 1942, the 18 objects were donated to Custer Battlefield National Cemetery, now known as LIBI, by Dr. Marquis\\' daughters, Mrs. Millie Ellen Marquis Hastings and Mrs. Anna Rose Octavia Marquis Heil. \n Jean Spotted Wolf Emmons, great-grand niece of Spotted Hawk, is requesting repatriation of the 18 cultural items. The medicine bundle is needed by Mrs. Emmons to continue traditional ceremonies. LIBI consulted with the Northern Cheyenne Cultural Commission and Tribal Historic Preservation Office to determine that Jean Emmons is an appropriate recipient under the Northern Cheyenne traditional kinship system and common law system of descendance. \n Determinations Made by Little Bighorn Battlefield National Monument \n Officials of LIBI have determined that: \n \\xe2\\x80\\xa2 Pursuant to 25 U.S.C. 3001(3)(C), the 18 cultural items described above are specific ceremonial objects needed by traditional Native American religious leaders for the practice of traditional Native American religions by their present-day adherents. \n \\xe2\\x80\\xa2 Pursuant to 25 U.S.C. 3005(a)(5)(A), Mrs. Emmons is the direct lineal descendant of the individual who owned these sacred objects. \n Additional Requestors and Disposition \n Any other individuals who believe they are lineal descendants of the individual who owned these sacred objects and who wish to claim the items should contact Gus Sanchez, Acting Superintendent, Little Bighorn Battlefield National Monument, P.O. Box 39, Crow Agency, MT 59022-0039, telephone (406) 638-3201, before July 12, 2012. Repatriation of the sacred objects to Mrs. Jean Spotted Wolf Emmons may proceed after that date if no additional claimants come forward. \n LIBI is responsible for notifying Mrs. Jean Spotted Wolf Emmons; the Arapaho Tribe of the Wind River Reservation, Wyoming; Assiniboine and Sioux Tribes of the Fort Peck Indian Reservation, Montana; Cheyenne and Arapaho Tribes, Oklahoma (formerly the Cheyenne-Arapaho Tribes of Oklahoma); Cheyenne River Sioux Tribe of the Cheyenne River Reservation, South Dakota; Crow Creek Sioux Tribe of the Crow Creek Reservation, South Dakota; Crow Tribe of Montana; Flandreau Santee Sioux Tribe of South Dakota; Lower Brule Sioux Tribe of the Lower Brule Reservation, South Dakota; Northern Cheyenne Tribe of the Northern Cheyenne Indian Reservation, Montana; Oglala Sioux Tribe of the Pine Ridge Reservation, South Dakota; Rosebud Sioux Tribe of the Rosebud Indian Reservation, South Dakota; Santee Sioux Nation, Nebraska; Sisseton-Wahpeton Oyate of the Lake Traverse Reservation, South Dakota; Spirit Lake Tribe, North Dakota; Standing Rock Sioux Tribe of North & South Dakota; Three Affiliated Tribes of the Fort Berthold Reservation, North Dakota; and the Yankton Sioux Tribe of South Dakota that this notice has been published. \n ", "consultation": "Null", "h_d_r": "Null", "h_d_ci": "The 18 cultural items are part of a medicine bundle and are one satchel made out of animal hide, 13 small medicine bags, and four stones. The items belonged to Spotted Hawk who resided on the Northern Cheyenne Reservation. On August 4, 1930, Cecilia Spotted Wolf, Spotted Hawk\\'s sister, traded or gifted the items to Dr. Thomas B. Marquis, a physician on the Tongue River Reservation (Northern Cheyenne). In 1942, the 18 objects were donated to Custer Battlefield National Cemetery, now known as LIBI, by Dr. Marquis\\' daughters, Mrs. Millie Ellen Marquis Hastings and Mrs. Anna Rose Octavia Marquis Heil. \n Jean Spotted Wolf Emmons, great-grand niece of Spotted Hawk, is requesting repatriation of the 18 cultural items. The medicine bundle is needed by Mrs. Emmons to continue traditional ceremonies. LIBI consulted with the Northern Cheyenne Cultural Commission and Tribal Historic Preservation Office to determine that Jean Emmons is an appropriate recipient under the Northern Cheyenne traditional kinship system and common law system of descendance. \n ", "determinations": "Determinations Made by Little Bighorn Battlefield National Monument \n Officials of LIBI have determined that: \n \\xe2\\x80\\xa2 Pursuant to 25 U.S.C. 3001(3)(C), the 18 cultural items described above are specific ceremonial objects needed by traditional Native American religious leaders for the practice of traditional Native American religions by their present-day adherents. \n \\xe2\\x80\\xa2 Pursuant to 25 U.S.C. 3005(a)(5)(A), Mrs. Emmons is the direct lineal descendant of the individual who owned these sacred objects. \n ", "a_r_d": "Any other individuals who believe they are lineal descendants of the individual who owned these sacred objects and who wish to claim the items should contact Gus Sanchez, Acting Superintendent, Little Bighorn Battlefield National Monument, P.O. Box 39, Crow Agency, MT 59022-0039, telephone (406) 638-3201, before July 12, 2012. Repatriation of the sacred objects to Mrs. Jean Spotted Wolf Emmons may proceed after that date if no additional claimants come forward. \n LIBI is responsible for notifying Mrs. Jean Spotted Wolf Emmons; the Arapaho Tribe of the Wind River Reservation, Wyoming; Assiniboine and Sioux Tribes of the Fort Peck Indian Reservation, Montana; Cheyenne and Arapaho Tribes, Oklahoma (formerly the Cheyenne-Arapaho Tribes of Oklahoma); Cheyenne River Sioux Tribe of the Cheyenne River Reservation, South Dakota; Crow Creek Sioux Tribe of the Crow Creek Reservation, South Dakota; Crow Tribe of Montana; Flandreau Santee Sioux Tribe of South Dakota; Lower Brule Sioux Tribe of the Lower Brule Reservation, South Dakota; Northern Cheyenne Tribe of the Northern Cheyenne Indian Reservation, Montana; Oglala Sioux Tribe of the Pine Ridge Reservation, South Dakota; Rosebud Sioux Tribe of the Rosebud Indian Reservation, South Dakota; Santee Sioux Nation, Nebraska; Sisseton-Wahpeton Oyate of the Lake Traverse Reservation, South Dakota; Spirit Lake Tribe, North Dakota; Standing Rock Sioux Tribe of North & South Dakota; Three Affiliated Tribes of the Fort Berthold Reservation, North Dakota; and the Yankton Sioux Tribe of South Dakota that this notice has been published. \n "}