{"index": "R_270", "messy_full": "\\n      \\n        DEPARTMENT OF THE INTERIOR\\n        National Park Service\\n        [NPS-WASO-NAGPRA-10271; 2200-1100-665]\\n        Notice of Intent To Repatriate Cultural Items: Tennessee Valley Authority and the University of Tennessee McClung Museum, Knoxville, TN\\n        \\n          AGENCY:\\n          National Park Service, Interior.\\n        \\n        \\n          ACTION:\\n          Notice.\\n        \\n        \\n          SUMMARY:\\n          The Tennessee Valley Authority (TVA) and the University of Tennessee McClung Museum (McClung Museum), in consultation with the appropriate Indian tribes, have determined that the cultural items meet the definition of unassociated funerary objects and repatriation to the Indian tribe identified below may occur if no additional claimants come forward. Representatives of any Indian tribe that believes itself to be culturally affiliated with the cultural items may contact the TVA and McClung Museum.\\n        \\n        \\n          DATES:\\n          Representatives of any Indian tribe that believes it has a cultural affiliation with the cultural items should contact the TVA and McClung Museum at the address below by July 5, 2012.\\n        \\n        \\n          ADDRESSES:\\n          Dr. Thomas O. Maher, TVA, 400 West Summit Hill Drive, WT 11D, Knoxville, TN 37902-1401, telephone (865) 632-7458.\\n        \\n      \\n      \\n        SUPPLEMENTARY INFORMATION:\\n        Notice is here given in accordance with the Native American Graves Protection and Repatriation Act (NAGPRA), 25 U.S.C. 3005, of the intent to repatriate cultural items under the control of the TVA and in the custody of the McClung Museum that meet the definition of unassociated funerary objects under 25 U.S.C. 3001.\\n        This notice is published as part of the National Park Service\\'s administrative responsibilities under NAGPRA, 25 U.S.C. 3003(d)(3). The determinations in this notice are the sole responsibility of the museum, institution, or Federal agency that has control of the Native American cultural items. The National Park Service is not responsible for the determinations in this notice.\\n        History and Description of the Cultural Item(s)\\n        On June 21, 1937 unassociated funerary objects were removed by archeologist from the University of Tennessee\\'s Division of Anthropology on Hiwassee Island, site 40MG031, from burial unit 063MG001. No human remains were recovered from this burial unit. The unassociated funerary objects are 1 lot of approximately 150 glass trade beads, which were found in this badly disturbed burial unit. The TVA and the McClung Museum do not have control or possession of any human remains from this burial unit. Since excavation, the unassociated funerary objects have been curated at the McClung Museum at the University of Tennessee.\\n\\n        Hiwassee Island is located seven miles south of the town of Dayton, TN, and is approximately 29 miles upstream of the TVA\\'s Chickamauga Dam. The archeologists were working under a \\xe2\\x80\\x9cPermit for Archeological Exploration\\xe2\\x80\\x9d between the landowner and the TVA, and the excavations were undertaken in connection with the TVA\\'s construction of Chickamauga Dam and Reservoir. Details regarding the excavations and analysis can be found in Hiwassee Island: An Archaeological Account of Four Tennessee Indian Peoples, by Thomas M.N. Lewis and Madeline Kneberg, University of Tennessee Press, Knoxville, TN.\\n        Determinations Made by the TVA and McClung Museum\\n        Officials of the TVA and McClung Museum have determined that:\\n        \\xe2\\x80\\xa2 Pursuant to 25 U.S.C. 3001(3)(B), the 1 lot of cultural items described above are reasonably believed to have been placed with or near individual human remains at the time of death or later as part of the death rite or ceremony and are believed, by a preponderance of the evidence, to have been removed from a specific burial site of a Native American individual.\\n        \\xe2\\x80\\xa2 Pursuant to 25 U.S.C. 3001(2), there is a relationship of shared group identity that can be reasonably traced between the unassociated funerary objects above and the Muscogee (Creek) Nation of Oklahoma.\\n        Additional Requestors and Disposition\\n        Representatives of any other Indian tribe that believes itself to be culturally affiliated with the unassociated funerary objects should contact Dr. Thomas O. Maher, TVA, 400 West Summit Hill Drive, WT 11D, Knoxville, TN 37902-1401, telephone (865-632-7458), before July 5, 2012. Repatriation of the unassociated funerary objects to the Muscogee (Creek) Nation of Oklahoma may proceed after that date if no additional claimants come forward.\\n        The TVA is responsible for notifying the Muscogee (Creek) Nation of Oklahoma that this notice has been published.\\n        \\n          \\n          Dated: May 30, 2012.\\n          Sherry Hutt,\\n          Manager, National NAGPRA Program. \\n        \\n      \\n      [FR Doc. 2012-13453 Filed 6-1-12; 8:45 am]\\n      BILLING CODE 4312-50-P\\n    ", "agency1": "DEPARTMENT OF THE INTERIOR", "sub_agency1": "National Park Service", "dep_doc": "[NPS-WASO-NAGPRA-10271; 2200-1100-665]", "subject": "Notice of Intent To Repatriate Cultural Items: Tennessee Valley Authority and the University of Tennessee McClung Museum, Knoxville, TN", "agency2": "National Park Service, Interior.", "action": "Notice.", "summary": "The Tennessee Valley Authority (TVA) and the University of Tennessee McClung Museum (McClung Museum), in consultation with the appropriate Indian tribes, have determined that the cultural items meet the definition of unassociated funerary objects and repatriation to the Indian tribe identified below may occur if no additional claimants come forward. Representatives of any Indian tribe that believes itself to be culturally affiliated with the cultural items may contact the TVA and McClung Museum.", "dates": "Representatives of any Indian tribe that believes it has a cultural affiliation with the cultural items should contact the TVA and McClung Museum at the address below by July 5, 2012.", "addresses": "Dr. Thomas O. Maher, TVA, 400 West Summit Hill Drive, WT 11D, Knoxville, TN 37902-1401, telephone (865) 632-7458.", "signature_dated": "Dated: May 30, 2012.", "signature_name": "Sherry Hutt,", "signature_title": "Manager, National NAGPRA Program. ", "fr_doc": "[FR Doc. 2012-13453 Filed 6-1-12; 8:45 am]", "billing_code": "BILLING CODE 4312-50-P", "supp_info": "SUPPLEMENTARY INFORMATION: \n Notice is here given in accordance with the Native American Graves Protection and Repatriation Act (NAGPRA), 25 U.S.C. 3005, of the intent to repatriate cultural items under the control of the TVA and in the custody of the McClung Museum that meet the definition of unassociated funerary objects under 25 U.S.C. 3001. \n This notice is published as part of the National Park Service\\'s administrative responsibilities under NAGPRA, 25 U.S.C. 3003(d)(3). The determinations in this notice are the sole responsibility of the museum, institution, or Federal agency that has control of the Native American cultural items. The National Park Service is not responsible for the determinations in this notice. \n History and Description of the Cultural Item(s) \n On June 21, 1937 unassociated funerary objects were removed by archeologist from the University of Tennessee\\'s Division of Anthropology on Hiwassee Island, site 40MG031, from burial unit 063MG001. No human remains were recovered from this burial unit. The unassociated funerary objects are 1 lot of approximately 150 glass trade beads, which were found in this badly disturbed burial unit. The TVA and the McClung Museum do not have control or possession of any human remains from this burial unit. Since excavation, the unassociated funerary objects have been curated at the McClung Museum at the University of Tennessee. \n Hiwassee Island is located seven miles south of the town of Dayton, TN, and is approximately 29 miles upstream of the TVA\\'s Chickamauga Dam. The archeologists were working under a \\xe2\\x80\\x9cPermit for Archeological Exploration\\xe2\\x80\\x9d between the landowner and the TVA, and the excavations were undertaken in connection with the TVA\\'s construction of Chickamauga Dam and Reservoir. Details regarding the excavations and analysis can be found in Hiwassee Island: An Archaeological Account of Four Tennessee Indian Peoples, by Thomas M.N. Lewis and Madeline Kneberg, University of Tennessee Press, Knoxville, TN. \n Determinations Made by the TVA and McClung Museum \n Officials of the TVA and McClung Museum have determined that: \n \\xe2\\x80\\xa2 Pursuant to 25 U.S.C. 3001(3)(B), the 1 lot of cultural items described above are reasonably believed to have been placed with or near individual human remains at the time of death or later as part of the death rite or ceremony and are believed, by a preponderance of the evidence, to have been removed from a specific burial site of a Native American individual. \n \\xe2\\x80\\xa2 Pursuant to 25 U.S.C. 3001(2), there is a relationship of shared group identity that can be reasonably traced between the unassociated funerary objects above and the Muscogee (Creek) Nation of Oklahoma. \n Additional Requestors and Disposition \n Representatives of any other Indian tribe that believes itself to be culturally affiliated with the unassociated funerary objects should contact Dr. Thomas O. Maher, TVA, 400 West Summit Hill Drive, WT 11D, Knoxville, TN 37902-1401, telephone (865-632-7458), before July 5, 2012. Repatriation of the unassociated funerary objects to the Muscogee (Creek) Nation of Oklahoma may proceed after that date if no additional claimants come forward. \n The TVA is responsible for notifying the Muscogee (Creek) Nation of Oklahoma that this notice has been published. \n ", "consultation": "Null", "h_d_r": "Null", "h_d_ci": "Null", "determinations": "Determinations Made by the TVA and McClung Museum \n Officials of the TVA and McClung Museum have determined that: \n \\xe2\\x80\\xa2 Pursuant to 25 U.S.C. 3001(3)(B), the 1 lot of cultural items described above are reasonably believed to have been placed with or near individual human remains at the time of death or later as part of the death rite or ceremony and are believed, by a preponderance of the evidence, to have been removed from a specific burial site of a Native American individual. \n \\xe2\\x80\\xa2 Pursuant to 25 U.S.C. 3001(2), there is a relationship of shared group identity that can be reasonably traced between the unassociated funerary objects above and the Muscogee (Creek) Nation of Oklahoma. \n ", "a_r_d": "Representatives of any other Indian tribe that believes itself to be culturally affiliated with the unassociated funerary objects should contact Dr. Thomas O. Maher, TVA, 400 West Summit Hill Drive, WT 11D, Knoxville, TN 37902-1401, telephone (865-632-7458), before July 5, 2012. Repatriation of the unassociated funerary objects to the Muscogee (Creek) Nation of Oklahoma may proceed after that date if no additional claimants come forward. \n The TVA is responsible for notifying the Muscogee (Creek) Nation of Oklahoma that this notice has been published. \n "}