{"index": "R_30", "messy_full": "\\n      \\n        DEPARTMENT OF THE INTERIOR\\n        National Park Service\\n        [NPS-WASO-NAGPRA-NPS0027158; PPWOCRADN0-PCU00RP14.R50000]\\n        Notice of Intent To Repatriate Cultural Items: New York State Museum, Albany, NY\\n        \\n          AGENCY:\\n          National Park Service, Interior.\\n        \\n        \\n          ACTION:\\n          Notice.\\n        \\n        \\n          SUMMARY:\\n          The New York State Museum, in consultation with the appropriate Indian Tribes or Native Hawaiian organizations, has determined that the cultural item listed in this notice meets the definition of objects of cultural patrimony. Lineal descendants or representatives of any Indian Tribe or Native Hawaiian organization not identified in this notice that wish to claim this cultural item should submit a written request to the New York State Museum. If no additional claimants come forward, transfer of control of the cultural item to the lineal descendants, Indian Tribes, or Native Hawaiian organizations stated in this notice may proceed.\\n        \\n        \\n          DATES:\\n          Lineal descendants or representatives of any Indian Tribe or Native Hawaiian organization not identified in this notice that wish to claim this cultural item should submit a written request with information in support of the claim to the New York State Museum at the address in this notice by March 11, 2019.\\n        \\n        \\n          ADDRESSES:\\n\\n          Lisa Anderson, NAGPRA Coordinator, New York State Museum, 3049 Cultural Education Center, Albany, NY 12230, telephone (518) 486-2020, email lisa.anderson@nysed.gov.\\n          \\n        \\n      \\n      \\n        SUPPLEMENTARY INFORMATION:\\n        Notice is here given in accordance with the Native American Graves Protection and Repatriation Act (NAGPRA), 25 U.S.C. 3005, of the intent to repatriate cultural items under the control of the New York State Museum, Albany, NY that meet the definition of objects of cultural patrimony under 25 U.S.C. 3001.\\n        This notice is published as part of the National Park Service\\'s administrative responsibilities under NAGPRA, 25 U.S.C. 3003(d)(3). The determinations in this notice are the sole responsibility of the museum, institution, or Federal agency that has control of the Native American cultural items. The National Park Service is not responsible for the determinations in this notice.\\n        History and Description of the Cultural Item\\n        In the late nineteenth century, one cultural item was acquired by the New York State Museum through Harriet Maxwell Converse (E-37417). The one cultural item is a wampum belt known as the Ransom wampum belt. It is composed of six rows of purple beads interspersed with white beads forming five diagonal bands and two white open hexagons. The wampum belt is strung on leather warps with thread wefts and mounted on linen backing. The wampum belt measures 243/4 inches long and 13/4 inches wide.\\n        Museum records indicate Converse identified the Ransom wampum belt as \\xe2\\x80\\x9cOnondaga.\\xe2\\x80\\x9d She reported that this wampum belt was used by women as ransom to spare the life of a prisoner. As such, the Ransom wampum belt symbolizes the role of women in the adoption of captives.\\n        The records of the New York State Museum establish the cultural affiliation of this wampum belt with the Haudenosaunee Confederacy, and specifically with the Onondaga Nation. Based on consultation with the Onondaga Nation, the Ransom wampum belt is an object of cultural patrimony, as it relates to the civil functions of a Council.\\n        Determinations Made by the New York State Museum\\n        Officials of the New York State Museum have determined that:\\n        \\xe2\\x80\\xa2 Pursuant to 25 U.S.C. 3001(3)(D), the one cultural item described above has ongoing historical, traditional, or cultural importance central to the Native American group or culture itself, rather than property owned by an individual.\\n        \\xe2\\x80\\xa2 Pursuant to 25 U.S.C. 3001(2), there is a relationship of shared group identity that can be reasonably traced between the object of cultural patrimony and the Onondaga Nation.\\n        Additional Requestors and Disposition\\n\\n        Lineal descendants or representatives of any Indian Tribe or Native Hawaiian organization not identified in this notice that wish to claim this cultural item should submit a written request with information in support of the claim to Lisa Anderson, NAGPRA Coordinator, New York State Museum, 3049 Cultural Education Center, Albany, NY 12230, telephone (518) 486-2020, email lisa.anderson@nysed.gov, by March 11, 2019. After that date, if no additional claimants have come forward, transfer of control of the object of cultural patrimony to the Onondaga Nation may proceed.\\n        The New York State Museum is responsible for notifying the Onondaga Nation that this notice has been published.\\n        \\n          Dated: December 11, 2018.\\n          Melanie O\\'Brien,\\n          Manager, National NAGPRA Program.\\n        \\n      \\n      [FR Doc. 2019-01616 Filed 2-7-19; 8:45 am]\\n       BILLING CODE 4312-52-P\\n    ", "agency1": "DEPARTMENT OF THE INTERIOR", "sub_agency1": "National Park Service", "dep_doc": "[NPS-WASO-NAGPRA-NPS0027158; PPWOCRADN0-PCU00RP14.R50000]", "subject": "Notice of Intent To Repatriate Cultural Items: New York State Museum, Albany, NY", "agency2": "National Park Service, Interior.", "action": "Notice.", "summary": "The New York State Museum, in consultation with the appropriate Indian Tribes or Native Hawaiian organizations, has determined that the cultural item listed in this notice meets the definition of objects of cultural patrimony. Lineal descendants or representatives of any Indian Tribe or Native Hawaiian organization not identified in this notice that wish to claim this cultural item should submit a written request to the New York State Museum. If no additional claimants come forward, transfer of control of the cultural item to the lineal descendants, Indian Tribes, or Native Hawaiian organizations stated in this notice may proceed.", "dates": "Lineal descendants or representatives of any Indian Tribe or Native Hawaiian organization not identified in this notice that wish to claim this cultural item should submit a written request with information in support of the claim to the New York State Museum at the address in this notice by March 11, 2019.", "addresses": "Lisa Anderson, NAGPRA Coordinator, New York State Museum, 3049 Cultural Education Center, Albany, NY 12230, telephone (518) 486-2020, email lisa.anderson@nysed.gov.\\n          ", "signature_dated": "Dated: December 11, 2018.", "signature_name": "Melanie O\\'Brien,", "signature_title": "Manager, National NAGPRA Program.", "fr_doc": "[FR Doc. 2019-01616 Filed 2-7-19; 8:45 am]", "billing_code": " BILLING CODE 4312-52-P", "supp_info": "SUPPLEMENTARY INFORMATION: \n Notice is here given in accordance with the Native American Graves Protection and Repatriation Act (NAGPRA), 25 U.S.C. 3005, of the intent to repatriate cultural items under the control of the New York State Museum, Albany, NY that meet the definition of objects of cultural patrimony under 25 U.S.C. 3001. \n This notice is published as part of the National Park Service\\'s administrative responsibilities under NAGPRA, 25 U.S.C. 3003(d)(3). The determinations in this notice are the sole responsibility of the museum, institution, or Federal agency that has control of the Native American cultural items. The National Park Service is not responsible for the determinations in this notice. \n History and Description of the Cultural Item \n In the late nineteenth century, one cultural item was acquired by the New York State Museum through Harriet Maxwell Converse (E-37417). The one cultural item is a wampum belt known as the Ransom wampum belt. It is composed of six rows of purple beads interspersed with white beads forming five diagonal bands and two white open hexagons. The wampum belt is strung on leather warps with thread wefts and mounted on linen backing. The wampum belt measures 243/4 inches long and 13/4 inches wide. \n Museum records indicate Converse identified the Ransom wampum belt as \\xe2\\x80\\x9cOnondaga.\\xe2\\x80\\x9d She reported that this wampum belt was used by women as ransom to spare the life of a prisoner. As such, the Ransom wampum belt symbolizes the role of women in the adoption of captives. \n The records of the New York State Museum establish the cultural affiliation of this wampum belt with the Haudenosaunee Confederacy, and specifically with the Onondaga Nation. Based on consultation with the Onondaga Nation, the Ransom wampum belt is an object of cultural patrimony, as it relates to the civil functions of a Council. \n Determinations Made by the New York State Museum \n Officials of the New York State Museum have determined that: \n \\xe2\\x80\\xa2 Pursuant to 25 U.S.C. 3001(3)(D), the one cultural item described above has ongoing historical, traditional, or cultural importance central to the Native American group or culture itself, rather than property owned by an individual. \n \\xe2\\x80\\xa2 Pursuant to 25 U.S.C. 3001(2), there is a relationship of shared group identity that can be reasonably traced between the object of cultural patrimony and the Onondaga Nation. \n Additional Requestors and Disposition \n Lineal descendants or representatives of any Indian Tribe or Native Hawaiian organization not identified in this notice that wish to claim this cultural item should submit a written request with information in support of the claim to Lisa Anderson, NAGPRA Coordinator, New York State Museum, 3049 Cultural Education Center, Albany, NY 12230, telephone (518) 486-2020, email lisa.anderson@nysed.gov, by March 11, 2019. After that date, if no additional claimants have come forward, transfer of control of the object of cultural patrimony to the Onondaga Nation may proceed. \n The New York State Museum is responsible for notifying the Onondaga Nation that this notice has been published. \n ", "consultation": "Null", "h_d_r": "Null", "h_d_ci": "Null", "determinations": "Determinations Made by the New York State Museum \n Officials of the New York State Museum have determined that: \n \\xe2\\x80\\xa2 Pursuant to 25 U.S.C. 3001(3)(D), the one cultural item described above has ongoing historical, traditional, or cultural importance central to the Native American group or culture itself, rather than property owned by an individual. \n \\xe2\\x80\\xa2 Pursuant to 25 U.S.C. 3001(2), there is a relationship of shared group identity that can be reasonably traced between the object of cultural patrimony and the Onondaga Nation. \n ", "a_r_d": "Lineal descendants or representatives of any Indian Tribe or Native Hawaiian organization not identified in this notice that wish to claim this cultural item should submit a written request with information in support of the claim to Lisa Anderson, NAGPRA Coordinator, New York State Museum, 3049 Cultural Education Center, Albany, NY 12230, telephone (518) 486-2020, email lisa.anderson@nysed.gov, by March 11, 2019. After that date, if no additional claimants have come forward, transfer of control of the object of cultural patrimony to the Onondaga Nation may proceed. \n The New York State Museum is responsible for notifying the Onondaga Nation that this notice has been published. \n "}