{"index": "R_413", "messy_full": "\\n      \\n        DEPARTMENT OF THE INTERIOR\\n        National Park Service\\n        Notice of Intent to Repatriate Cultural Items: U.S. Department of Agriculture, Forest Service, Coronado National Forest, Tucson, AZ and Arizona State Museum, University of Arizona, Tucson, AZ; Correction\\n        \\n          AGENCY:\\n          National Park Service, Interior.\\n        \\n        \\n          ACTION:\\n          Notice; correction.\\n        \\n        Notice is here given in accordance with the Native American Graves Protection and Repatriation Act (NAGPRA), 25 U.S.C. 3005, of the intent to repatriate cultural items in the possession of the U.S. Department of Agriculture, Forest Service, Coronado National Forest, Tucson, AZ, and in the possession of the Arizona State Museum, University of Arizona, Tucson, AZ, that meet the definition of \\xe2\\x80\\x9cobjects of cultural patrimony\\xe2\\x80\\x9d under 25 U.S.C. 3001.\\n        This notice is published as part of the National Park Service\\'s administrative responsibilities under NAGPRA, 25 U.S.C. 3003 (d)(3). The determinations in this notice are the sole responsibility of the museum, institution, or Federal agency that has control of the Native American human remains and associated funerary objects. The National Park Service is not responsible for the determinations in this notice.\\n\\n        This notice corrects the number of cultural items with the addition of one object of cultural patrimony, which was found in Arizona State Museum\\'s collection after the publication of a Notice of Intent to Repatriate in the Federal Register on November 20, 2007 (FR Doc E7-22671, Page 65354).\\n        In the Federal Register of November 20, 2007, the notice is corrected by substituting the following for paragraph 3:\\n        The 59 cultural items are part of an archeological collection known as the Pinaleno Cotton Cache. The 59 cultural items are 2 caches of raw, native cotton, 3 ceramic jars, 3 ceramic bowls, 2 coiled basketry bowls, 1 coiled basketry pot stand, and 48 botanical and faunal items.\\n        Representatives of any other Indian tribe that believes itself to be culturally affiliated with the objects of cultural patrimony should contact Dr. Frank E. Wozniak, NAGPRA Coordinator, Southwestern Region, USDA Forest Service, 333 Broadway Blvd., SE, Albuquerque, NM 87102, telephone (505) 842-3238, before December 26, 2008. Repatriation of the objects of cultural patrimony to the Tohono O\\'odham Nation of Arizona may proceed after that date if no additional claimants come forward.\\n        The Coronado National Forest is responsible for notifying the Ak Chin Indian Community of the Maricopa (Ak Chin) Indian Reservation, Arizona; Gila River Indian Community of the Gila River Indian Reservation, Arizona; Hopi Tribe of Arizona; Salt River Pima-Maricopa Indian Community of the Salt River Reservation; and the Tohono O\\'odham Nation of Arizona that this notice has been published.\\n        \\n          Dated: October 31, 2008\\n          Sherry Hutt,\\n          Manager, National NAGPRA Program.\\n        \\n      \\n      [FR Doc. E8-28040 Filed 11-24-08; 8:45 am]\\n      BILLING CODE 4312-50-S\\n    ", "agency1": "DEPARTMENT OF THE INTERIOR", "sub_agency1": "National Park Service", "dep_doc": "Null", "subject": "Notice of Intent to Repatriate Cultural Items: U.S. Department of Agriculture, Forest Service, Coronado National Forest, Tucson, AZ and Arizona State Museum, University of Arizona, Tucson, AZ; Correction", "agency2": "National Park Service, Interior.", "action": "Notice; correction.", "summary": "Null", "dates": "Null", "addresses": "Null", "signature_dated": "Dated: October 31, 2008", "signature_name": "Sherry Hutt,", "signature_title": "Manager, National NAGPRA Program.", "fr_doc": "[FR Doc. E8-28040 Filed 11-24-08; 8:45 am]", "billing_code": "BILLING CODE 4312-50-S", "supp_info": "Null", "consultation": "Null", "h_d_r": "Null", "h_d_ci": "Null", "determinations": "Null", "a_r_d": "Null"}