{"index": "R_452", "messy_full": "\\n      \\n        DEPARTMENT OF THE INTERIOR\\n        National Park Service\\n        Notice of Intent to Repatriate Cultural Items: Seton Hall University Museum, Seton Hall University, South Orange, NJ; Correction\\n        \\n          AGENCY:\\n          National Park Service, Interior.\\n        \\n        \\n          ACTION:\\n          Notice; correction.\\n        \\n        Notice is here given in accordance with the Native American Graves Protection and Repatriation Act (NAGPRA), 25 U.S.C. 3005, of the intent to repatriate cultural items in the possession of the Seton Hall University Museum, Seton Hall University, South Orange, NJ, that meet the definition of \\xe2\\x80\\x9csacred objects\\xe2\\x80\\x9d and \\xe2\\x80\\x9cobjects of cultural patrimony\\xe2\\x80\\x9d under 25 U.S.C. 3001.\\n        This notice is published as part of the National Park Service\\'s administrative responsibilities under NAGPRA, 25 U.S.C. 3003 (d)(3). The determinations in this notice are the sole responsibility of the museum, institution, or Federal agency that has control of the Native American human remains and associated funerary objects. The National Park Service is not responsible for the determinations in this notice.\\n\\n        This notice corrects an error in the telephone number of the Seton Hall University Museum and adds an e-mail address. In the Federal Register of May 23, 2008 (FR Doc E-8-11572, Pages 30159-30160], paragraph 8 is corrected by substituting the following paragraph:\\n        Representatives of any other Indian tribe or Nation that believes itself to be culturally affiliated with the sacred objects/objects of cultural patrimony should contact Dr. Thomas W. Kavanagh, Seton Hall University Museum, Seton Hall University, 400 South Orange Ave., South Orange, NJ 07079, telephone (973) 275-5873 or e-mail kavanath@shu.edu, before August 13, 2008. Repatriation of the sacred objects/objects of cultural patrimony to the Onondaga Nation of New York may proceed after that date if no additional claimants come forward.\\n        The Seton Hall University Museum is responsible for notifying the Cayuga Nation of New York; Oneida Nation of New York; Oneida Tribe of Indians of Wisconsin; Onondaga Nation of New York; Seneca Nation of New York; Seneca-Cayuga Tribe of Oklahoma; Saint Regis Mohawk Tribe, New York; Tonawanda Band of Seneca Indians of New York; Tuscarora Nation of New York; and Haudenosaunee Standing Committee on Burial Rules and Regulations, a non-federally recognized Indian organization, that this notice has been published.\\n        \\n          Dated: June 16, 2008\\n          Sherry Hutt,\\n          Manager, National NAGPRA Program.\\n        \\n      \\n      [FR Doc. E8-15910 Filed 7-11-08; 8:45 am]\\n      BILLING CODE 4312-50-S\\n    ", "agency1": "DEPARTMENT OF THE INTERIOR", "sub_agency1": "National Park Service", "dep_doc": "Null", "subject": "Notice of Intent to Repatriate Cultural Items: Seton Hall University Museum, Seton Hall University, South Orange, NJ; Correction", "agency2": "National Park Service, Interior.", "action": "Notice; correction.", "summary": "Null", "dates": "Null", "addresses": "Null", "signature_dated": "Dated: June 16, 2008", "signature_name": "Sherry Hutt,", "signature_title": "Manager, National NAGPRA Program.", "fr_doc": "[FR Doc. E8-15910 Filed 7-11-08; 8:45 am]", "billing_code": "BILLING CODE 4312-50-S", "supp_info": "Null", "consultation": "Null", "h_d_r": "Null", "h_d_ci": "Null", "determinations": "Null", "a_r_d": "Null"}