{"index": "R_50", "messy_full": "\\n      \\n        DEPARTMENT OF THE INTERIOR\\n        National Park Service\\n        [NPS-WASO-NAGPRA; PPWOCRADN0-PCU00RP14.R50000]\\n        Notice of Intent To Repatriate Cultural Items: U.S. Fish and Wildlife Service, Office of Law Enforcement, Albuquerque, NM\\n        \\n          AGENCY:\\n          National Park Service, Interior.\\n        \\n        \\n          ACTION:\\n          Notice.\\n        \\n        \\n          SUMMARY:\\n          The U.S. Fish and Wildlife Service, Office of Law Enforcement, in consultation with the appropriate Indian Tribes or Native Hawaiian organizations, has determined that the cultural item listed in this notice meets the definition of object of cultural patrimony. Lineal descendants or representatives of any Indian Tribe or Native Hawaiian organization not identified in this notice that wish to claim this cultural item should submit a written request to the U.S. Fish and Wildlife Service, Office of Law Enforcement. If no additional claimants come forward, transfer of control of the cultural item to the lineal descendants, Indian Tribes, or Native Hawaiian organizations stated in this notice may proceed.\\n        \\n        \\n          DATES:\\n          Lineal descendants or representatives of any Indian Tribe or Native Hawaiian organization not identified in this notice that wish to claim this cultural item should submit a written request with information in support of the claim to the U.S. Fish and Wildlife Service, Office of Law Enforcement, at the address in this notice by May 4, 2018.\\n        \\n        \\n          ADDRESSES:\\n\\n          Ariel R. Vazquez, Resident Agent in Charge, Arizona/New Mexico District, U.S. Fish and Wildlife Service, Office of Law Enforcement, 4901 Paseo del Norte NE, Suite D, Albuquerque, NM 87113, telephone (505) 346-7828, email ariel_vazquez@fws.gov.\\n          \\n        \\n      \\n      \\n        SUPPLEMENTARY INFORMATION:\\n        Notice is here given in accordance with the Native American Graves Protection and Repatriation Act (NAGPRA), 25 U.S.C. 3005, of the intent to repatriate a cultural item under the control of the U.S. Fish and Wildlife Service, Office of Law Enforcement, Albuquerque, NM, that meets the definition of object of cultural patrimony under 25 U.S.C. 3001.\\n        This notice is published as part of the National Park Service\\'s administrative responsibilities under NAGPRA, 25 U.S.C. 3003(d)(3). The determinations in this notice are the sole responsibility of the museum, institution or Federal agency that has control of the Native American cultural items. The National Park Service is not responsible for the determinations in this notice.\\n        History and Description of the Cultural Item(s)\\n        In February 2016, a cultural item was removed from a residence in McKinley County, NM. The cultural item was included in a collection of items with eagle feathers surrendered to law enforcement agents. The one object of cultural patrimony is a bison headdress with glass beading and eagle plume feathers. Cultural affiliation was determined based on the type of beading, which compares with historic photos of beaded headdresses provided by the Comanche Nation, Oklahoma.\\n        Determinations Made by the U.S. Fish and Wildlife Service, Office of Law Enforcement\\n        Officials of the U.S. Fish and Wildlife Service, Office of Law Enforcement, have determined that:\\n        \\xe2\\x80\\xa2 Pursuant to 25 U.S.C. 3001(3)(D), the one cultural item described above has ongoing historical, traditional, or cultural importance central to the Native American group or culture itself, rather than property owned by an individual.\\n        \\xe2\\x80\\xa2 Pursuant to 25 U.S.C. 3001(2), there is a relationship of shared group identity that can be reasonably traced between the object of cultural patrimony and the Comanche Nation, Oklahoma.\\n        Additional Requestors and Disposition\\n\\n        Lineal descendants or representatives of any Indian Tribe or Native Hawaiian organization not identified in this notice that wish to claim these cultural items should submit a written request with information in support of the claim to: Ariel R. Vazquez, Resident Agent in Charge, Arizona/New Mexico District, U.S. Fish and Wildlife Service, Office of Law Enforcement, 4901 Paseo del Norte NE, Suite D, Albuquerque, NM 87113, telephone (505) 346-7828, email ariel_vazquez@fws.gov, by May 4, 2018. After that date, if no additional claimants have come forward, transfer of control of the object of cultural patrimony to the Comanche Nation, Oklahoma may proceed.\\n        The U.S. Fish and Wildlife Service is responsible for notifying the Comanche Nation, Oklahoma that this notice has been published.\\n        \\n          Dated: February 28, 2018.\\n          Melanie O\\'Brien,\\n          Manager, National NAGPRA Program.\\n        \\n      \\n      [FR Doc. 2018-06836 Filed 4-3-18; 8:45 am]\\n       BILLING CODE 4312-52-P\\n    ", "agency1": "DEPARTMENT OF THE INTERIOR", "sub_agency1": "National Park Service", "dep_doc": "[NPS-WASO-NAGPRA; PPWOCRADN0-PCU00RP14.R50000]", "subject": "Notice of Intent To Repatriate Cultural Items: U.S. Fish and Wildlife Service, Office of Law Enforcement, Albuquerque, NM", "agency2": "National Park Service, Interior.", "action": "Notice.", "summary": "The U.S. Fish and Wildlife Service, Office of Law Enforcement, in consultation with the appropriate Indian Tribes or Native Hawaiian organizations, has determined that the cultural item listed in this notice meets the definition of object of cultural patrimony. Lineal descendants or representatives of any Indian Tribe or Native Hawaiian organization not identified in this notice that wish to claim this cultural item should submit a written request to the U.S. Fish and Wildlife Service, Office of Law Enforcement. If no additional claimants come forward, transfer of control of the cultural item to the lineal descendants, Indian Tribes, or Native Hawaiian organizations stated in this notice may proceed.", "dates": "Lineal descendants or representatives of any Indian Tribe or Native Hawaiian organization not identified in this notice that wish to claim this cultural item should submit a written request with information in support of the claim to the U.S. Fish and Wildlife Service, Office of Law Enforcement, at the address in this notice by May 4, 2018.", "addresses": "Ariel R. Vazquez, Resident Agent in Charge, Arizona/New Mexico District, U.S. Fish and Wildlife Service, Office of Law Enforcement, 4901 Paseo del Norte NE, Suite D, Albuquerque, NM 87113, telephone (505) 346-7828, email ariel_vazquez@fws.gov.\\n          ", "signature_dated": "Dated: February 28, 2018.", "signature_name": "Melanie O\\'Brien,", "signature_title": "Manager, National NAGPRA Program.", "fr_doc": "[FR Doc. 2018-06836 Filed 4-3-18; 8:45 am]", "billing_code": " BILLING CODE 4312-52-P", "supp_info": "SUPPLEMENTARY INFORMATION: \n Notice is here given in accordance with the Native American Graves Protection and Repatriation Act (NAGPRA), 25 U.S.C. 3005, of the intent to repatriate a cultural item under the control of the U.S. Fish and Wildlife Service, Office of Law Enforcement, Albuquerque, NM, that meets the definition of object of cultural patrimony under 25 U.S.C. 3001. \n This notice is published as part of the National Park Service\\'s administrative responsibilities under NAGPRA, 25 U.S.C. 3003(d)(3). The determinations in this notice are the sole responsibility of the museum, institution or Federal agency that has control of the Native American cultural items. The National Park Service is not responsible for the determinations in this notice. \n History and Description of the Cultural Item(s) \n In February 2016, a cultural item was removed from a residence in McKinley County, NM. The cultural item was included in a collection of items with eagle feathers surrendered to law enforcement agents. The one object of cultural patrimony is a bison headdress with glass beading and eagle plume feathers. Cultural affiliation was determined based on the type of beading, which compares with historic photos of beaded headdresses provided by the Comanche Nation, Oklahoma. \n Determinations Made by the U.S. Fish and Wildlife Service, Office of Law Enforcement \n Officials of the U.S. Fish and Wildlife Service, Office of Law Enforcement, have determined that: \n \\xe2\\x80\\xa2 Pursuant to 25 U.S.C. 3001(3)(D), the one cultural item described above has ongoing historical, traditional, or cultural importance central to the Native American group or culture itself, rather than property owned by an individual. \n \\xe2\\x80\\xa2 Pursuant to 25 U.S.C. 3001(2), there is a relationship of shared group identity that can be reasonably traced between the object of cultural patrimony and the Comanche Nation, Oklahoma. \n Additional Requestors and Disposition \n Lineal descendants or representatives of any Indian Tribe or Native Hawaiian organization not identified in this notice that wish to claim these cultural items should submit a written request with information in support of the claim to: Ariel R. Vazquez, Resident Agent in Charge, Arizona/New Mexico District, U.S. Fish and Wildlife Service, Office of Law Enforcement, 4901 Paseo del Norte NE, Suite D, Albuquerque, NM 87113, telephone (505) 346-7828, email ariel_vazquez@fws.gov, by May 4, 2018. After that date, if no additional claimants have come forward, transfer of control of the object of cultural patrimony to the Comanche Nation, Oklahoma may proceed. \n The U.S. Fish and Wildlife Service is responsible for notifying the Comanche Nation, Oklahoma that this notice has been published. \n ", "consultation": "Null", "h_d_r": "Null", "h_d_ci": "Null", "determinations": "Determinations Made by the U.S. Fish and Wildlife Service, Office of Law Enforcement \n Officials of the U.S. Fish and Wildlife Service, Office of Law Enforcement, have determined that: \n \\xe2\\x80\\xa2 Pursuant to 25 U.S.C. 3001(3)(D), the one cultural item described above has ongoing historical, traditional, or cultural importance central to the Native American group or culture itself, rather than property owned by an individual. \n \\xe2\\x80\\xa2 Pursuant to 25 U.S.C. 3001(2), there is a relationship of shared group identity that can be reasonably traced between the object of cultural patrimony and the Comanche Nation, Oklahoma. \n ", "a_r_d": "Lineal descendants or representatives of any Indian Tribe or Native Hawaiian organization not identified in this notice that wish to claim these cultural items should submit a written request with information in support of the claim to: Ariel R. Vazquez, Resident Agent in Charge, Arizona/New Mexico District, U.S. Fish and Wildlife Service, Office of Law Enforcement, 4901 Paseo del Norte NE, Suite D, Albuquerque, NM 87113, telephone (505) 346-7828, email ariel_vazquez@fws.gov, by May 4, 2018. After that date, if no additional claimants have come forward, transfer of control of the object of cultural patrimony to the Comanche Nation, Oklahoma may proceed. \n The U.S. Fish and Wildlife Service is responsible for notifying the Comanche Nation, Oklahoma that this notice has been published. \n "}