{"index": "R_55", "messy_full": "\\n      \\n        DEPARTMENT OF THE INTERIOR\\n        National Park Service\\n        [NPS-WASO-NAGPRA-NPS0024991; PPWOCRADN0-PCU00RP14.R50000]\\n        Notice of Intent To Repatriate Cultural Items: New York State Museum, Albany, NY\\n        \\n          AGENCY:\\n          National Park Service, Interior.\\n        \\n        \\n          ACTION:\\n          Notice.\\n        \\n        \\n          SUMMARY:\\n          The New York State Museum, in consultation with the appropriate Indian Tribes or Native Hawaiian organizations, has determined that the cultural item listed in this notice meets the definition of a sacred object. Lineal descendants or representatives of any Indian Tribe or Native Hawaiian organization not identified in this notice that wish to claim these cultural items should submit a written request to the New York State Museum. If no additional claimants come forward, transfer of control of the cultural items to the lineal descendants, Indian Tribes, or Native Hawaiian organizations stated in this notice may proceed.\\n        \\n        \\n          DATES:\\n\\n          Lineal descendants or representatives of any Indian Tribe or Native Hawaiian organization not identified in this notice that wish to claim these cultural items should submit a written request with information in support of the claim to the New York State Museum at the address in this notice by March 26, 2018.\\n        \\n        \\n          ADDRESSES:\\n\\n          Lisa Anderson, New York State Museum, 3049 Cultural Education Center, Albany, NY 12230, telephone (518) 486-2020, email lisa.anderson@nysed.gov.\\n          \\n        \\n      \\n      \\n        SUPPLEMENTARY INFORMATION:\\n        Notice is here given in accordance with the Native American Graves Protection and Repatriation Act (NAGPRA), 25 U.S.C. 3005, of the intent to repatriate a cultural item under the control of the New York State Museum, Albany, NY, that meets the definition of a sacred object under 25 U.S.C. 3001.\\n        This notice is published as part of the National Park Service\\'s administrative responsibilities under NAGPRA, 25 U.S.C. 3003(d)(3). The determinations in this notice are the sole responsibility of the museum, institution, or Federal agency that has control of the Native American cultural items. The National Park Service is not responsible for the determinations in this notice.\\n        History and Description of the Cultural Item(s)\\n        In 1956, the museum acquired one cultural item as part of a larger collection purchased from the Albert G. Heath Collection at the Logan Museum of Anthropology at Beloit College in Beloit, WI. The cultural item was originally purchased by Mr. Heath from Joe Kishigobenesse, an Ottawa, who resided in Emmet County, MI.\\n        The sacred object is a water drum identified by representatives of the Little Traverse Bay Bands of Odawa Indians, Michigan, as a Grandfather Drum used by the Midewiwin medicine society. Traditional religious leaders of the Little Traverse Bay Bands of Odawa Indians, Michigan, have identified the drum as necessary for the practice of traditional Native American religions by present-day adherents. Museum documentation, supported by oral and written evidence presented during consultation, indicates the drum is culturally affiliated with the Little Traverse Bay Bands of Odawa Indians, Michigan.\\n        Determinations Made by the New York State Museum\\n        Officials of the New York State Museum have determined that:\\n        \\xe2\\x80\\xa2 \\xe2\\x80\\x89Pursuant to 25 U.S.C. 3001(3)(C), the one cultural item described above is a specific ceremonial object needed by traditional Native American religious leaders for the practice of traditional Native American religions by their present-day adherents.\\n        \\xe2\\x80\\xa2 \\xe2\\x80\\x89Pursuant to 25 U.S.C. 3001(2), there is a relationship of shared group identity that can be reasonably traced between the sacred object and the Little Traverse Bay Bands of Odawa Indians, Michigan.\\n        Additional Requestors and Disposition\\n\\n        Lineal descendants or representatives of any Indian Tribe or Native Hawaiian organization not identified in this notice that wish to claim this cultural item should submit a written request with information in support of the claim to Lisa Anderson, New York State Museum, 3049 Cultural Education Center, Albany, NY 12230, telephone (518) 486-2020, email lisa.anderson@nysed.gov, by March 26, 2018. After that date, if no additional claimants have come forward, transfer of control of the sacred object to Little Traverse Bay Bands of Odawa Indians, Michigan, may proceed.\\n        The New York State Museum is responsible for notifying the Little Traverse Bay Bands of Odawa Indians, Michigan, that this notice has been published.\\n        \\n          Dated: February 2, 2018.\\n          Melanie O\\'Brien,\\n          Manager, National NAGPRA Program.\\n        \\n      \\n      [FR Doc. 2018-03638 Filed 2-21-18; 8:45 am]\\n       BILLING CODE 4312-52-P\\n    ", "agency1": "DEPARTMENT OF THE INTERIOR", "sub_agency1": "National Park Service", "dep_doc": "[NPS-WASO-NAGPRA-NPS0024991; PPWOCRADN0-PCU00RP14.R50000]", "subject": "Notice of Intent To Repatriate Cultural Items: New York State Museum, Albany, NY", "agency2": "National Park Service, Interior.", "action": "Notice.", "summary": "The New York State Museum, in consultation with the appropriate Indian Tribes or Native Hawaiian organizations, has determined that the cultural item listed in this notice meets the definition of a sacred object. Lineal descendants or representatives of any Indian Tribe or Native Hawaiian organization not identified in this notice that wish to claim these cultural items should submit a written request to the New York State Museum. If no additional claimants come forward, transfer of control of the cultural items to the lineal descendants, Indian Tribes, or Native Hawaiian organizations stated in this notice may proceed.", "dates": "Lineal descendants or representatives of any Indian Tribe or Native Hawaiian organization not identified in this notice that wish to claim these cultural items should submit a written request with information in support of the claim to the New York State Museum at the address in this notice by March 26, 2018.", "addresses": "Lisa Anderson, New York State Museum, 3049 Cultural Education Center, Albany, NY 12230, telephone (518) 486-2020, email lisa.anderson@nysed.gov.\\n          ", "signature_dated": "Dated: February 2, 2018.", "signature_name": "Melanie O\\'Brien,", "signature_title": "Manager, National NAGPRA Program.", "fr_doc": "[FR Doc. 2018-03638 Filed 2-21-18; 8:45 am]", "billing_code": " BILLING CODE 4312-52-P", "supp_info": "SUPPLEMENTARY INFORMATION: \n Notice is here given in accordance with the Native American Graves Protection and Repatriation Act (NAGPRA), 25 U.S.C. 3005, of the intent to repatriate a cultural item under the control of the New York State Museum, Albany, NY, that meets the definition of a sacred object under 25 U.S.C. 3001. \n This notice is published as part of the National Park Service\\'s administrative responsibilities under NAGPRA, 25 U.S.C. 3003(d)(3). The determinations in this notice are the sole responsibility of the museum, institution, or Federal agency that has control of the Native American cultural items. The National Park Service is not responsible for the determinations in this notice. \n History and Description of the Cultural Item(s) \n In 1956, the museum acquired one cultural item as part of a larger collection purchased from the Albert G. Heath Collection at the Logan Museum of Anthropology at Beloit College in Beloit, WI. The cultural item was originally purchased by Mr. Heath from Joe Kishigobenesse, an Ottawa, who resided in Emmet County, MI. \n The sacred object is a water drum identified by representatives of the Little Traverse Bay Bands of Odawa Indians, Michigan, as a Grandfather Drum used by the Midewiwin medicine society. Traditional religious leaders of the Little Traverse Bay Bands of Odawa Indians, Michigan, have identified the drum as necessary for the practice of traditional Native American religions by present-day adherents. Museum documentation, supported by oral and written evidence presented during consultation, indicates the drum is culturally affiliated with the Little Traverse Bay Bands of Odawa Indians, Michigan. \n Determinations Made by the New York State Museum \n Officials of the New York State Museum have determined that: \n \\xe2\\x80\\xa2 \\xe2\\x80\\x89Pursuant to 25 U.S.C. 3001(3)(C), the one cultural item described above is a specific ceremonial object needed by traditional Native American religious leaders for the practice of traditional Native American religions by their present-day adherents. \n \\xe2\\x80\\xa2 \\xe2\\x80\\x89Pursuant to 25 U.S.C. 3001(2), there is a relationship of shared group identity that can be reasonably traced between the sacred object and the Little Traverse Bay Bands of Odawa Indians, Michigan. \n Additional Requestors and Disposition \n Lineal descendants or representatives of any Indian Tribe or Native Hawaiian organization not identified in this notice that wish to claim this cultural item should submit a written request with information in support of the claim to Lisa Anderson, New York State Museum, 3049 Cultural Education Center, Albany, NY 12230, telephone (518) 486-2020, email lisa.anderson@nysed.gov, by March 26, 2018. After that date, if no additional claimants have come forward, transfer of control of the sacred object to Little Traverse Bay Bands of Odawa Indians, Michigan, may proceed. \n The New York State Museum is responsible for notifying the Little Traverse Bay Bands of Odawa Indians, Michigan, that this notice has been published. \n ", "consultation": "Null", "h_d_r": "Null", "h_d_ci": "Null", "determinations": "Determinations Made by the New York State Museum \n Officials of the New York State Museum have determined that: \n \\xe2\\x80\\xa2 \\xe2\\x80\\x89Pursuant to 25 U.S.C. 3001(3)(C), the one cultural item described above is a specific ceremonial object needed by traditional Native American religious leaders for the practice of traditional Native American religions by their present-day adherents. \n \\xe2\\x80\\xa2 \\xe2\\x80\\x89Pursuant to 25 U.S.C. 3001(2), there is a relationship of shared group identity that can be reasonably traced between the sacred object and the Little Traverse Bay Bands of Odawa Indians, Michigan. \n ", "a_r_d": "Lineal descendants or representatives of any Indian Tribe or Native Hawaiian organization not identified in this notice that wish to claim this cultural item should submit a written request with information in support of the claim to Lisa Anderson, New York State Museum, 3049 Cultural Education Center, Albany, NY 12230, telephone (518) 486-2020, email lisa.anderson@nysed.gov, by March 26, 2018. After that date, if no additional claimants have come forward, transfer of control of the sacred object to Little Traverse Bay Bands of Odawa Indians, Michigan, may proceed. \n The New York State Museum is responsible for notifying the Little Traverse Bay Bands of Odawa Indians, Michigan, that this notice has been published. \n "}