{"index": "R_72", "messy_full": "\\n      \\n        DEPARTMENT OF THE INTERIOR\\n        National Park Service\\n        [NPS-WASO-NAGPRA-NPS0023998; PPWOCRADN0-PCU00RP14.R50000]\\n        Notice of Intent To Repatriate Cultural Items: U.S. Department of Agriculture, Forest Service, Tonto National Forest, Phoenix, AZ\\n        \\n          AGENCY:\\n          National Park Service, Interior.\\n        \\n        \\n          ACTION:\\n          Notice.\\n        \\n        \\n          SUMMARY:\\n          The U.S. Department of Agriculture (USDA), Forest Service, Tonto National Forest, has completed an inventory of unassociated funerary objects, in consultation with the appropriate Indian Tribes or Native Hawaiian organizations, and has determined that there is a cultural affiliation between the unassociated funerary objects and present-day Indian Tribes or Native Hawaiian organizations. Lineal descendants or representatives of any Indian Tribe or Native Hawaiian organization not identified in this notice that wish to request transfer of control of these cultural items should submit a written request to the Tonto National Forest. If no additional requestors come forward, transfer of control of the unassociated funerary objects to the lineal descendants, Indian Tribes, or Native Hawaiian organizations stated in this notice may proceed.\\n        \\n        \\n          DATES:\\n          Lineal descendants or representatives of any Indian Tribe or Native Hawaiian organization not identified in this notice that wish to request transfer of control of these cultural items should submit a written request with information in support of the request to the Tonto National Forest at the address in this notice by September 29, 2017.\\n        \\n        \\n          ADDRESSES:\\n\\n          Neil Bosworth, Tonto National Forest, 2324 East McDowell Road, Phoenix, AZ 85206, telephone (602) 225-5201, email nbosworth@fs.fed.us.\\n          \\n        \\n      \\n      \\n        SUPPLEMENTARY INFORMATION:\\n\\n        Notice is here given in accordance with the Native American Graves Protection and Repatriation Act (NAGPRA), 25 U.S.C. 3005, of the intent to repatriate cultural items under the control of the Tonto National Forest, Phoenix, AZ, that meet the definition of unassociated funerary objects under 25 U.S.C. 3001.\\n        This notice is published as part of the National Park Service\\'s administrative responsibilities under NAGPRA, 25 U.S.C. 3003(d)(3). The determinations in this notice are the sole responsibility of the museum, institution, or Federal agency that has control of the unassociated funerary objects. The National Park Service is not responsible for the determinations in this notice.\\n        History and Description of the Cultural Items\\n        Prior to 1990, 11 unassociated funerary objects were removed from Six Shooter Canyon in Gila County, AZ. The unassociated funerary objects were donated to the Grand Canyon Museum and then transferred to the Tonto National Forest on December 29, 2016. The 11 unassociated funerary objects are three shell bracelets, three shell rings, and five turquoise tessera pieces. A detailed assessment of the unassociated funerary objects was made by the Tonto National Forest professional staff in consultation with representatives of the Salt River Pima-Maricopa Indian Community, who submitted a repatriation claim for the cultural items.\\n        In accordance with the Plan for the Treatment and Disposition of Human Remains and Other Cultural Items from the Tonto National Forest Pursuant to the Native American Graves Protection and Repatriation Act (as revised in 2001), it has been determined that the primary cultural affiliation of these unassociated funerary objects is with the Ak-Chin Indian Community (previously listed as the Ak Chin Indian Community of the Maricopa (Ak Chin) Indian Reservation, Arizona); Gila River Indian Community of the Gila River Indian Reservation, Arizona; Salt River Pima-Maricopa Indian Community of the Salt River Reservation, Arizona; and the Tohono O\\'odham Nation of Arizona.\\n        Determinations Made by the USDA, Forest Service, Tonto National Forest\\n        Officials of the Tonto National Forest have determined that:\\n        \\xe2\\x80\\xa2 Pursuant to 25 U.S.C. 3001(3)(B), the 11 objects described in this notice are reasonably believed to have been placed with or near individual human remains at the time of death or later as part of the death rite or ceremony.\\n        \\xe2\\x80\\xa2 Pursuant to 25 U.S.C. 3001(2), there is a relationship of shared group identity that can be reasonably traced between the unassociated funerary objects and the Ak-Chin Indian Community (previously listed as the Ak Chin Indian Community of the Maricopa (Ak Chin) Indian Reservation, Arizona); Gila River Indian Community of the Gila River Indian Reservation, Arizona; Salt River Pima-Maricopa Indian Community of the Salt River Reservation, Arizona; and the Tohono O\\'odham Nation of Arizona.\\n        Additional Requestors and Disposition\\n\\n        Lineal descendants or representatives of any Indian Tribe or Native Hawaiian organization not identified in this notice that wish to request transfer of control of these unassociated funerary objects should submit a written request with information in support of the request to Neil Bosworth, Tonto National Forest, 2324 E McDowell Road, Phoenix, AZ 85206, telephone (602) 225-5201, email nbosworth@fs.fed.us, by September 29, 2017. After that date, if no additional requestors have come forward, transfer of control of the unassociated funerary objects to the Salt River Pima-Maricopa Indian Community of the Salt River Reservation, Arizona, may proceed.\\n        The Tonto National Forest is responsible for notifying the Ak-Chin Indian Community (previously listed as the Ak Chin Indian Community of the Maricopa (Ak Chin) Indian Reservation, Arizona); Gila River Indian Community of the Gila River Indian Reservation, Arizona; Salt River Pima-Maricopa Indian Community of the Salt River Reservation, Arizona; and the Tohono O\\'odham Nation of Arizona that this notice has been published.\\n        \\n          Dated: August 14, 2017.\\n          Sarah Glass,\\n          Acting Manager, National NAGPRA Program. \\n        \\n      \\n      [FR Doc. 2017-18346 Filed 8-29-17; 8:45 am]\\n       BILLING CODE 4312-52-P\\n    ", "agency1": "DEPARTMENT OF THE INTERIOR", "sub_agency1": "National Park Service", "dep_doc": "[NPS-WASO-NAGPRA-NPS0023998; PPWOCRADN0-PCU00RP14.R50000]", "subject": "Notice of Intent To Repatriate Cultural Items: U.S. Department of Agriculture, Forest Service, Tonto National Forest, Phoenix, AZ", "agency2": "National Park Service, Interior.", "action": "Notice.", "summary": "The U.S. Department of Agriculture (USDA), Forest Service, Tonto National Forest, has completed an inventory of unassociated funerary objects, in consultation with the appropriate Indian Tribes or Native Hawaiian organizations, and has determined that there is a cultural affiliation between the unassociated funerary objects and present-day Indian Tribes or Native Hawaiian organizations. Lineal descendants or representatives of any Indian Tribe or Native Hawaiian organization not identified in this notice that wish to request transfer of control of these cultural items should submit a written request to the Tonto National Forest. If no additional requestors come forward, transfer of control of the unassociated funerary objects to the lineal descendants, Indian Tribes, or Native Hawaiian organizations stated in this notice may proceed.", "dates": "Lineal descendants or representatives of any Indian Tribe or Native Hawaiian organization not identified in this notice that wish to request transfer of control of these cultural items should submit a written request with information in support of the request to the Tonto National Forest at the address in this notice by September 29, 2017.", "addresses": "Neil Bosworth, Tonto National Forest, 2324 East McDowell Road, Phoenix, AZ 85206, telephone (602) 225-5201, email nbosworth@fs.fed.us.\\n          ", "signature_dated": "Dated: August 14, 2017.", "signature_name": "Sarah Glass,", "signature_title": "Acting Manager, National NAGPRA Program. ", "fr_doc": "[FR Doc. 2017-18346 Filed 8-29-17; 8:45 am]", "billing_code": " BILLING CODE 4312-52-P", "supp_info": "SUPPLEMENTARY INFORMATION: \n Notice is here given in accordance with the Native American Graves Protection and Repatriation Act (NAGPRA), 25 U.S.C. 3005, of the intent to repatriate cultural items under the control of the Tonto National Forest, Phoenix, AZ, that meet the definition of unassociated funerary objects under 25 U.S.C. 3001. \n This notice is published as part of the National Park Service\\'s administrative responsibilities under NAGPRA, 25 U.S.C. 3003(d)(3). The determinations in this notice are the sole responsibility of the museum, institution, or Federal agency that has control of the unassociated funerary objects. The National Park Service is not responsible for the determinations in this notice. \n History and Description of the Cultural Items \n Prior to 1990, 11 unassociated funerary objects were removed from Six Shooter Canyon in Gila County, AZ. The unassociated funerary objects were donated to the Grand Canyon Museum and then transferred to the Tonto National Forest on December 29, 2016. The 11 unassociated funerary objects are three shell bracelets, three shell rings, and five turquoise tessera pieces. A detailed assessment of the unassociated funerary objects was made by the Tonto National Forest professional staff in consultation with representatives of the Salt River Pima-Maricopa Indian Community, who submitted a repatriation claim for the cultural items. \n In accordance with the Plan for the Treatment and Disposition of Human Remains and Other Cultural Items from the Tonto National Forest Pursuant to the Native American Graves Protection and Repatriation Act (as revised in 2001), it has been determined that the primary cultural affiliation of these unassociated funerary objects is with the Ak-Chin Indian Community (previously listed as the Ak Chin Indian Community of the Maricopa (Ak Chin) Indian Reservation, Arizona); Gila River Indian Community of the Gila River Indian Reservation, Arizona; Salt River Pima-Maricopa Indian Community of the Salt River Reservation, Arizona; and the Tohono O\\'odham Nation of Arizona. \n Determinations Made by the USDA, Forest Service, Tonto National Forest \n Officials of the Tonto National Forest have determined that: \n \\xe2\\x80\\xa2 Pursuant to 25 U.S.C. 3001(3)(B), the 11 objects described in this notice are reasonably believed to have been placed with or near individual human remains at the time of death or later as part of the death rite or ceremony. \n \\xe2\\x80\\xa2 Pursuant to 25 U.S.C. 3001(2), there is a relationship of shared group identity that can be reasonably traced between the unassociated funerary objects and the Ak-Chin Indian Community (previously listed as the Ak Chin Indian Community of the Maricopa (Ak Chin) Indian Reservation, Arizona); Gila River Indian Community of the Gila River Indian Reservation, Arizona; Salt River Pima-Maricopa Indian Community of the Salt River Reservation, Arizona; and the Tohono O\\'odham Nation of Arizona. \n Additional Requestors and Disposition \n Lineal descendants or representatives of any Indian Tribe or Native Hawaiian organization not identified in this notice that wish to request transfer of control of these unassociated funerary objects should submit a written request with information in support of the request to Neil Bosworth, Tonto National Forest, 2324 E McDowell Road, Phoenix, AZ 85206, telephone (602) 225-5201, email nbosworth@fs.fed.us, by September 29, 2017. After that date, if no additional requestors have come forward, transfer of control of the unassociated funerary objects to the Salt River Pima-Maricopa Indian Community of the Salt River Reservation, Arizona, may proceed. \n The Tonto National Forest is responsible for notifying the Ak-Chin Indian Community (previously listed as the Ak Chin Indian Community of the Maricopa (Ak Chin) Indian Reservation, Arizona); Gila River Indian Community of the Gila River Indian Reservation, Arizona; Salt River Pima-Maricopa Indian Community of the Salt River Reservation, Arizona; and the Tohono O\\'odham Nation of Arizona that this notice has been published. \n ", "consultation": "Null", "h_d_r": "Null", "h_d_ci": "Prior to 1990, 11 unassociated funerary objects were removed from Six Shooter Canyon in Gila County, AZ. The unassociated funerary objects were donated to the Grand Canyon Museum and then transferred to the Tonto National Forest on December 29, 2016. The 11 unassociated funerary objects are three shell bracelets, three shell rings, and five turquoise tessera pieces. A detailed assessment of the unassociated funerary objects was made by the Tonto National Forest professional staff in consultation with representatives of the Salt River Pima-Maricopa Indian Community, who submitted a repatriation claim for the cultural items. \n In accordance with the Plan for the Treatment and Disposition of Human Remains and Other Cultural Items from the Tonto National Forest Pursuant to the Native American Graves Protection and Repatriation Act (as revised in 2001), it has been determined that the primary cultural affiliation of these unassociated funerary objects is with the Ak-Chin Indian Community (previously listed as the Ak Chin Indian Community of the Maricopa (Ak Chin) Indian Reservation, Arizona); Gila River Indian Community of the Gila River Indian Reservation, Arizona; Salt River Pima-Maricopa Indian Community of the Salt River Reservation, Arizona; and the Tohono O\\'odham Nation of Arizona. \n ", "determinations": "Determinations Made by the USDA, Forest Service, Tonto National Forest \n Officials of the Tonto National Forest have determined that: \n \\xe2\\x80\\xa2 Pursuant to 25 U.S.C. 3001(3)(B), the 11 objects described in this notice are reasonably believed to have been placed with or near individual human remains at the time of death or later as part of the death rite or ceremony. \n \\xe2\\x80\\xa2 Pursuant to 25 U.S.C. 3001(2), there is a relationship of shared group identity that can be reasonably traced between the unassociated funerary objects and the Ak-Chin Indian Community (previously listed as the Ak Chin Indian Community of the Maricopa (Ak Chin) Indian Reservation, Arizona); Gila River Indian Community of the Gila River Indian Reservation, Arizona; Salt River Pima-Maricopa Indian Community of the Salt River Reservation, Arizona; and the Tohono O\\'odham Nation of Arizona. \n ", "a_r_d": "Lineal descendants or representatives of any Indian Tribe or Native Hawaiian organization not identified in this notice that wish to request transfer of control of these unassociated funerary objects should submit a written request with information in support of the request to Neil Bosworth, Tonto National Forest, 2324 E McDowell Road, Phoenix, AZ 85206, telephone (602) 225-5201, email nbosworth@fs.fed.us, by September 29, 2017. After that date, if no additional requestors have come forward, transfer of control of the unassociated funerary objects to the Salt River Pima-Maricopa Indian Community of the Salt River Reservation, Arizona, may proceed. \n The Tonto National Forest is responsible for notifying the Ak-Chin Indian Community (previously listed as the Ak Chin Indian Community of the Maricopa (Ak Chin) Indian Reservation, Arizona); Gila River Indian Community of the Gila River Indian Reservation, Arizona; Salt River Pima-Maricopa Indian Community of the Salt River Reservation, Arizona; and the Tohono O\\'odham Nation of Arizona that this notice has been published. \n "}