{"index": "R_90", "messy_full": "\\n      \\n        DEPARTMENT OF THE INTERIOR\\n        National Park Service\\n        [NPS-WASO-NAGPRA-23041;PPWOCRADN0-PCU00RP14.R50000]\\n        Notice of Intent To Repatriate Cultural Items: Worcester Society of Natural History d.b.a. EcoTarium, Worcester, MA\\n        \\n          AGENCY:\\n          National Park Service, Interior.\\n        \\n        \\n          ACTION:\\n          Notice.\\n        \\n        \\n          SUMMARY:\\n          The Worcester Society of Natural History d.b.a. EcoTarium, in consultation with the appropriate Indian tribes or Native Hawaiian organizations, has determined that the cultural items listed in this notice meet the definition of sacred objects. Lineal descendants or representatives of any Indian tribe or Native Hawaiian organization not identified in this notice that wish to claim these cultural items should submit a written request to the Worcester Society of Natural History d.b.a. EcoTarium. If no additional claimants come forward, transfer of control of the cultural items to the lineal descendants, Indian tribes, or Native Hawaiian organizations stated in this notice may proceed.\\n        \\n        \\n          DATES:\\n          Lineal descendants or representatives of any Indian tribe or Native Hawaiian organization not identified in this notice that wish to claim these cultural items should submit a written request with information in support of the claim to the Worcester Society of Natural History d.b.a. EcoTarium at the address in this notice by June 2, 2017.\\n        \\n        \\n          ADDRESSES:\\n\\n          Shana Hawrylchak, Manager of Exhibits and Collections, EcoTarium, 222 Harrington Way, Worcester, MA 01604, telephone (508) 929-2733, email shawrylchak@ecotarium.org.\\n          \\n        \\n      \\n      \\n        SUPPLEMENTARY INFORMATION:\\n        Notice is here given in accordance with the Native American Graves Protection and Repatriation Act (NAGPRA), 25 U.S.C. 3005, of the intent to repatriate cultural items under the control of the Worcester Society of Natural History d.b.a. EcoTarium, Worcester, MA, that meet the definition of sacred objects under 25 U.S.C. 3001.\\n        This notice is published as part of the National Park Service\\'s administrative responsibilities under NAGPRA, 25 U.S.C. 3003(d)(3). The determinations in this notice are the sole responsibility of the museum, institution, or Federal agency that has control of the Native American cultural items. The National Park Service is not responsible for the determinations in this notice.\\n        History and Description of the Cultural Item(s)\\n        At an unknown date, one cultural item was removed from an unknown location. The one sacred object is a fan made of eagle feathers, hide, and small beadwork. In 2016, the fan was found in the collections storage facilities of the EcoTarium together with an associated exhibit label which read \\xe2\\x80\\x9cFan used in the peyote ceremony\\xe2\\x80\\x9d. No information on the fan was found in the Museum\\'s accession files or internal archives indicating either the provenience or the provenance of the fan. Based on the age of other materials in the Museum\\'s anthropology collection, it is likely that the fan entered the collection in the 1950s. In the opinion of Douglas Diehl, Director of American Indian & Ethnographic Art at Skinner Auction House, the piece was Kiowa or Comanche, based on the design.\\n\\n        In consultation with Margaret Murrow, Tribal Historic Preservation Officer for the Comanche Nation, further details of the design were identified as being in the Comanche style. In particular, the feathers were cut, or \\xe2\\x80\\x9cnarrowed\\xe2\\x80\\x9d, in a manner that is similar to traditional Comanche treatment of feathers and distinct from the fuller feather treatments seen in most Kiowa fans. The beadwork also follows traditional Comanche color schemes and patterns.\\n        \\n        Determinations Made by the Worcester Society of Natural History d.b.a. EcoTarium\\n\\n        Officials of the Worcester Society of Natural History d.b.a. EcoTarium have determined that:\\n        \\n        \\xe2\\x80\\xa2 Pursuant to 25 U.S.C. 3001(3)(C), the one cultural item described above is a specific ceremonial object needed by traditional Native American religious leaders for the practice of traditional Native American religions by their present-day adherents.\\n        Additional Requestors and Disposition\\n\\n        Lineal descendants or representatives of any Indian tribe or Native Hawaiian organization not identified in this notice that wish to claim these cultural items should submit a written request with information in support of the claim to Shana Hawrylchak, Manager of Exhibits and Collections, EcoTarium, 222 Harrington Way, Worcester, MA 01604, telephone (508) 929-2733, email shawrylchak@ecotarium.org, by June 2, 2017. After that date, if no additional claimants have come forward, transfer of control of the sacred object to the Comanche Nation, Oklahoma, may proceed.\\n        The Worcester Society of Natural History d.b.a. EcoTarium is responsible for notifying the Comanche Nation, Oklahoma, that this notice has been published.\\n        \\n          Dated: March 7, 2017.\\n          Melanie O\\'Brien,\\n          Manager, National NAGPRA Program.\\n        \\n      \\n      [FR Doc. 2017-08866 Filed 5-2-17; 8:45 am]\\n       BILLING CODE 4312-52-P\\n    ", "agency1": "DEPARTMENT OF THE INTERIOR", "sub_agency1": "National Park Service", "dep_doc": "[NPS-WASO-NAGPRA-23041;PPWOCRADN0-PCU00RP14.R50000]", "subject": "Notice of Intent To Repatriate Cultural Items: Worcester Society of Natural History d.b.a. EcoTarium, Worcester, MA", "agency2": "National Park Service, Interior.", "action": "Notice.", "summary": "The Worcester Society of Natural History d.b.a. EcoTarium, in consultation with the appropriate Indian tribes or Native Hawaiian organizations, has determined that the cultural items listed in this notice meet the definition of sacred objects. Lineal descendants or representatives of any Indian tribe or Native Hawaiian organization not identified in this notice that wish to claim these cultural items should submit a written request to the Worcester Society of Natural History d.b.a. EcoTarium. If no additional claimants come forward, transfer of control of the cultural items to the lineal descendants, Indian tribes, or Native Hawaiian organizations stated in this notice may proceed.", "dates": "Lineal descendants or representatives of any Indian tribe or Native Hawaiian organization not identified in this notice that wish to claim these cultural items should submit a written request with information in support of the claim to the Worcester Society of Natural History d.b.a. EcoTarium at the address in this notice by June 2, 2017.", "addresses": "Shana Hawrylchak, Manager of Exhibits and Collections, EcoTarium, 222 Harrington Way, Worcester, MA 01604, telephone (508) 929-2733, email shawrylchak@ecotarium.org.\\n          ", "signature_dated": "Dated: March 7, 2017.", "signature_name": "Melanie O\\'Brien,", "signature_title": "Manager, National NAGPRA Program.", "fr_doc": "[FR Doc. 2017-08866 Filed 5-2-17; 8:45 am]", "billing_code": " BILLING CODE 4312-52-P", "supp_info": "SUPPLEMENTARY INFORMATION: \n Notice is here given in accordance with the Native American Graves Protection and Repatriation Act (NAGPRA), 25 U.S.C. 3005, of the intent to repatriate cultural items under the control of the Worcester Society of Natural History d.b.a. EcoTarium, Worcester, MA, that meet the definition of sacred objects under 25 U.S.C. 3001. \n This notice is published as part of the National Park Service\\'s administrative responsibilities under NAGPRA, 25 U.S.C. 3003(d)(3). The determinations in this notice are the sole responsibility of the museum, institution, or Federal agency that has control of the Native American cultural items. The National Park Service is not responsible for the determinations in this notice. \n History and Description of the Cultural Item(s) \n At an unknown date, one cultural item was removed from an unknown location. The one sacred object is a fan made of eagle feathers, hide, and small beadwork. In 2016, the fan was found in the collections storage facilities of the EcoTarium together with an associated exhibit label which read \\xe2\\x80\\x9cFan used in the peyote ceremony\\xe2\\x80\\x9d. No information on the fan was found in the Museum\\'s accession files or internal archives indicating either the provenience or the provenance of the fan. Based on the age of other materials in the Museum\\'s anthropology collection, it is likely that the fan entered the collection in the 1950s. In the opinion of Douglas Diehl, Director of American Indian & Ethnographic Art at Skinner Auction House, the piece was Kiowa or Comanche, based on the design. \n In consultation with Margaret Murrow, Tribal Historic Preservation Officer for the Comanche Nation, further details of the design were identified as being in the Comanche style. In particular, the feathers were cut, or \\xe2\\x80\\x9cnarrowed\\xe2\\x80\\x9d, in a manner that is similar to traditional Comanche treatment of feathers and distinct from the fuller feather treatments seen in most Kiowa fans. The beadwork also follows traditional Comanche color schemes and patterns.\\n         \n Determinations Made by the Worcester Society of Natural History d.b.a. EcoTarium \n Officials of the Worcester Society of Natural History d.b.a. EcoTarium have determined that:\\n         \n \\xe2\\x80\\xa2 Pursuant to 25 U.S.C. 3001(3)(C), the one cultural item described above is a specific ceremonial object needed by traditional Native American religious leaders for the practice of traditional Native American religions by their present-day adherents. \n Additional Requestors and Disposition \n Lineal descendants or representatives of any Indian tribe or Native Hawaiian organization not identified in this notice that wish to claim these cultural items should submit a written request with information in support of the claim to Shana Hawrylchak, Manager of Exhibits and Collections, EcoTarium, 222 Harrington Way, Worcester, MA 01604, telephone (508) 929-2733, email shawrylchak@ecotarium.org, by June 2, 2017. After that date, if no additional claimants have come forward, transfer of control of the sacred object to the Comanche Nation, Oklahoma, may proceed. \n The Worcester Society of Natural History d.b.a. EcoTarium is responsible for notifying the Comanche Nation, Oklahoma, that this notice has been published. \n ", "consultation": "Null", "h_d_r": "Null", "h_d_ci": "Null", "determinations": "Determinations Made by the Worcester Society of Natural History d.b.a. EcoTarium \n Officials of the Worcester Society of Natural History d.b.a. EcoTarium have determined that:\\n         \n \\xe2\\x80\\xa2 Pursuant to 25 U.S.C. 3001(3)(C), the one cultural item described above is a specific ceremonial object needed by traditional Native American religious leaders for the practice of traditional Native American religions by their present-day adherents. \n ", "a_r_d": "Lineal descendants or representatives of any Indian tribe or Native Hawaiian organization not identified in this notice that wish to claim these cultural items should submit a written request with information in support of the claim to Shana Hawrylchak, Manager of Exhibits and Collections, EcoTarium, 222 Harrington Way, Worcester, MA 01604, telephone (508) 929-2733, email shawrylchak@ecotarium.org, by June 2, 2017. After that date, if no additional claimants have come forward, transfer of control of the sacred object to the Comanche Nation, Oklahoma, may proceed. \n The Worcester Society of Natural History d.b.a. EcoTarium is responsible for notifying the Comanche Nation, Oklahoma, that this notice has been published. \n "}