{"index": "R_96", "messy_full": "\\n      \\n        DEPARTMENT OF THE INTERIOR\\n        National Park Service\\n        [NPS-WASO-NAGPRA-22929; PPWOCRADN0-PCU00RP14.R50000]\\n        Notice of Intent To Repatriate Cultural Items: Museum of Natural History and Planetarium, Roger Williams Park, Providence, RI\\n        \\n          AGENCY:\\n          National Park Service, Interior.\\n        \\n        \\n          ACTION:\\n          Notice.\\n        \\n        \\n          SUMMARY:\\n          The Museum of Natural History and Planetarium, Roger Williams Park, in consultation with the appropriate Indian tribes or Native Hawaiian organizations, has determined that the cultural items listed in this notice meet the definition of unassociated funerary objects. Lineal descendants or representatives of any Indian tribe or Native Hawaiian organization not identified in this notice that wish to claim these cultural items should submit a written request to the Museum of Natural History and Planetarium, Roger Williams Park. If no additional claimants come forward, transfer of control of the cultural items to the lineal descendants, Indian tribes, or Native Hawaiian organizations stated in this notice may proceed.\\n        \\n        \\n          DATES:\\n          Lineal descendants or representatives of any Indian tribe or Native Hawaiian organization not identified in this notice that wish to claim these cultural items should submit a written request with information in support of the claim to the Museum of Natural History and Planetarium, Roger Williams Park, at the address in this notice by April 14, 2017.\\n        \\n        \\n          ADDRESSES:\\n\\n          Michael W. Kieron, Museum of Natural History and Planetarium, Roger Williams Park, 100 Elmwood Avenue, Providence, RI 02907, telephone (401) 680-7248, email m.kieron@musnathist.com.\\n          \\n        \\n      \\n      \\n        SUPPLEMENTARY INFORMATION:\\n        Notice is here given in accordance with the Native American Graves Protection and Repatriation Act (NAGPRA), 25 U.S.C. 3005, of the intent to repatriate cultural items under the control of the Museum of Natural History and Planetarium, Roger Williams Park, that meet the definition of unassociated funerary objects under 25 U.S.C. 3001.\\n        This notice is published as part of the National Park Service\\'s administrative responsibilities under NAGPRA, 25 U.S.C. 3003(d)(3). The determinations in this notice are the sole responsibility of the museum, institution, or Federal agency that has control of the Native American cultural items. The National Park Service is not responsible for the determinations in this notice.\\n        History and Description of the Cultural Items\\n        In the late 1920s and early 1930s, six cultural items were removed from the Mix Cave site (PU 93) in Pulaski County, MO, by Mr. and Mrs. Edward H. Nadeau. The six unassociated funerary objects are 5 potsherds and 1 worked white-tailed deer ulna. The objects were donated to the Museum of Natural History and Planetarium, Roger Williams Park, by Mr. and Mrs. Nadeau on January 23, 1933. The objects are all labeled \\xe2\\x80\\x9cMix Cave, Pulaski Co., Mo.\\xe2\\x80\\x9d They were given the catalog number E2706 and the accession number 8918. The objects were part of a collection of 50 lots of American Indian objects and geological specimens collected in the 1920s by the Nadeaus. No other records related to this donation have been located.\\n        Following an examination by representatives of The Osage Nation (previously listed as the Osage Tribe) in January 2016, the Osage Nation and the museum concurred that the objects are unassociated funerary objects. The Osage Nation considers the Mix Cave site (PU 93) a sacred site and a burial located on Osage ancestral lands.\\n        Determinations Made by the Museum of Natural History and Planetarium, Roger Williams Park\\n\\n        Officials of the Museum of Natural History and Planetarium, Roger Williams Park, have determined that:\\n        \\n        \\xe2\\x80\\xa2 Pursuant to 25 U.S.C. 3001(3)(B), the 6 cultural items described above are reasonably believed to have been placed with or near individual human remains at the time of death or later as part of the death rite or ceremony and are believed, by a preponderance of the evidence, to have been removed from a specific burial site of a Native American individual.\\n        \\xe2\\x80\\xa2 Pursuant to 25 U.S.C. 3001(2), there is a relationship of shared group identity that can be reasonably traced between the unassociated funerary objects and The Osage Nation (previously listed as the Osage Tribe).\\n        Additional Requestors and Disposition\\n\\n        Lineal descendants or representatives of any Indian tribe or Native Hawaiian organization not identified in this notice that wish to claim these cultural items should submit a written request with information in support of the claim to Michael W. Kieron, Museum of Natural History and Planetarium, Roger Williams Park, 100 Elmwood Avenue, Providence, RI 02907, telephone (401) 680-7248, email m.kieron@musnathist.com by April 14, 2017. After that date, if no additional claimants have come forward, transfer of control of the unassociated funerary objects to The Osage Nation (previously listed as the Osage Tribe) may proceed.\\n        The Museum of Natural History and Planetarium, Roger Williams Park, is responsible for notifying The Osage Nation (previously listed as the Osage Tribe) that this notice has been published.\\n        \\n          Dated: February 14, 2017.\\n          Melanie O\\'Brien,\\n          Manager, National NAGPRA Program.\\n        \\n      \\n      [FR Doc. 2017-05094 Filed 3-14-17; 8:45 am]\\n       BILLING CODE 4312-52-P\\n    ", "agency1": "DEPARTMENT OF THE INTERIOR", "sub_agency1": "National Park Service", "dep_doc": "[NPS-WASO-NAGPRA-22929; PPWOCRADN0-PCU00RP14.R50000]", "subject": "Notice of Intent To Repatriate Cultural Items: Museum of Natural History and Planetarium, Roger Williams Park, Providence, RI", "agency2": "National Park Service, Interior.", "action": "Notice.", "summary": "The Museum of Natural History and Planetarium, Roger Williams Park, in consultation with the appropriate Indian tribes or Native Hawaiian organizations, has determined that the cultural items listed in this notice meet the definition of unassociated funerary objects. Lineal descendants or representatives of any Indian tribe or Native Hawaiian organization not identified in this notice that wish to claim these cultural items should submit a written request to the Museum of Natural History and Planetarium, Roger Williams Park. If no additional claimants come forward, transfer of control of the cultural items to the lineal descendants, Indian tribes, or Native Hawaiian organizations stated in this notice may proceed.", "dates": "Lineal descendants or representatives of any Indian tribe or Native Hawaiian organization not identified in this notice that wish to claim these cultural items should submit a written request with information in support of the claim to the Museum of Natural History and Planetarium, Roger Williams Park, at the address in this notice by April 14, 2017.", "addresses": "Michael W. Kieron, Museum of Natural History and Planetarium, Roger Williams Park, 100 Elmwood Avenue, Providence, RI 02907, telephone (401) 680-7248, email m.kieron@musnathist.com.\\n          ", "signature_dated": "Dated: February 14, 2017.", "signature_name": "Melanie O\\'Brien,", "signature_title": "Manager, National NAGPRA Program.", "fr_doc": "[FR Doc. 2017-05094 Filed 3-14-17; 8:45 am]", "billing_code": " BILLING CODE 4312-52-P", "supp_info": "SUPPLEMENTARY INFORMATION: \n Notice is here given in accordance with the Native American Graves Protection and Repatriation Act (NAGPRA), 25 U.S.C. 3005, of the intent to repatriate cultural items under the control of the Museum of Natural History and Planetarium, Roger Williams Park, that meet the definition of unassociated funerary objects under 25 U.S.C. 3001. \n This notice is published as part of the National Park Service\\'s administrative responsibilities under NAGPRA, 25 U.S.C. 3003(d)(3). The determinations in this notice are the sole responsibility of the museum, institution, or Federal agency that has control of the Native American cultural items. The National Park Service is not responsible for the determinations in this notice. \n History and Description of the Cultural Items \n In the late 1920s and early 1930s, six cultural items were removed from the Mix Cave site (PU 93) in Pulaski County, MO, by Mr. and Mrs. Edward H. Nadeau. The six unassociated funerary objects are 5 potsherds and 1 worked white-tailed deer ulna. The objects were donated to the Museum of Natural History and Planetarium, Roger Williams Park, by Mr. and Mrs. Nadeau on January 23, 1933. The objects are all labeled \\xe2\\x80\\x9cMix Cave, Pulaski Co., Mo.\\xe2\\x80\\x9d They were given the catalog number E2706 and the accession number 8918. The objects were part of a collection of 50 lots of American Indian objects and geological specimens collected in the 1920s by the Nadeaus. No other records related to this donation have been located. \n Following an examination by representatives of The Osage Nation (previously listed as the Osage Tribe) in January 2016, the Osage Nation and the museum concurred that the objects are unassociated funerary objects. The Osage Nation considers the Mix Cave site (PU 93) a sacred site and a burial located on Osage ancestral lands. \n Determinations Made by the Museum of Natural History and Planetarium, Roger Williams Park \n Officials of the Museum of Natural History and Planetarium, Roger Williams Park, have determined that:\\n         \n \\xe2\\x80\\xa2 Pursuant to 25 U.S.C. 3001(3)(B), the 6 cultural items described above are reasonably believed to have been placed with or near individual human remains at the time of death or later as part of the death rite or ceremony and are believed, by a preponderance of the evidence, to have been removed from a specific burial site of a Native American individual. \n \\xe2\\x80\\xa2 Pursuant to 25 U.S.C. 3001(2), there is a relationship of shared group identity that can be reasonably traced between the unassociated funerary objects and The Osage Nation (previously listed as the Osage Tribe). \n Additional Requestors and Disposition \n Lineal descendants or representatives of any Indian tribe or Native Hawaiian organization not identified in this notice that wish to claim these cultural items should submit a written request with information in support of the claim to Michael W. Kieron, Museum of Natural History and Planetarium, Roger Williams Park, 100 Elmwood Avenue, Providence, RI 02907, telephone (401) 680-7248, email m.kieron@musnathist.com by April 14, 2017. After that date, if no additional claimants have come forward, transfer of control of the unassociated funerary objects to The Osage Nation (previously listed as the Osage Tribe) may proceed. \n The Museum of Natural History and Planetarium, Roger Williams Park, is responsible for notifying The Osage Nation (previously listed as the Osage Tribe) that this notice has been published. \n ", "consultation": "Null", "h_d_r": "Null", "h_d_ci": "In the late 1920s and early 1930s, six cultural items were removed from the Mix Cave site (PU 93) in Pulaski County, MO, by Mr. and Mrs. Edward H. Nadeau. The six unassociated funerary objects are 5 potsherds and 1 worked white-tailed deer ulna. The objects were donated to the Museum of Natural History and Planetarium, Roger Williams Park, by Mr. and Mrs. Nadeau on January 23, 1933. The objects are all labeled \\xe2\\x80\\x9cMix Cave, Pulaski Co., Mo.\\xe2\\x80\\x9d They were given the catalog number E2706 and the accession number 8918. The objects were part of a collection of 50 lots of American Indian objects and geological specimens collected in the 1920s by the Nadeaus. No other records related to this donation have been located. \n Following an examination by representatives of The Osage Nation (previously listed as the Osage Tribe) in January 2016, the Osage Nation and the museum concurred that the objects are unassociated funerary objects. The Osage Nation considers the Mix Cave site (PU 93) a sacred site and a burial located on Osage ancestral lands. \n ", "determinations": "Determinations Made by the Museum of Natural History and Planetarium, Roger Williams Park \n Officials of the Museum of Natural History and Planetarium, Roger Williams Park, have determined that:\\n         \n \\xe2\\x80\\xa2 Pursuant to 25 U.S.C. 3001(3)(B), the 6 cultural items described above are reasonably believed to have been placed with or near individual human remains at the time of death or later as part of the death rite or ceremony and are believed, by a preponderance of the evidence, to have been removed from a specific burial site of a Native American individual. \n \\xe2\\x80\\xa2 Pursuant to 25 U.S.C. 3001(2), there is a relationship of shared group identity that can be reasonably traced between the unassociated funerary objects and The Osage Nation (previously listed as the Osage Tribe). \n ", "a_r_d": "Lineal descendants or representatives of any Indian tribe or Native Hawaiian organization not identified in this notice that wish to claim these cultural items should submit a written request with information in support of the claim to Michael W. Kieron, Museum of Natural History and Planetarium, Roger Williams Park, 100 Elmwood Avenue, Providence, RI 02907, telephone (401) 680-7248, email m.kieron@musnathist.com by April 14, 2017. After that date, if no additional claimants have come forward, transfer of control of the unassociated funerary objects to The Osage Nation (previously listed as the Osage Tribe) may proceed. \n The Museum of Natural History and Planetarium, Roger Williams Park, is responsible for notifying The Osage Nation (previously listed as the Osage Tribe) that this notice has been published. \n "}